Workbook
Name lst_region: OFFSET(Lists!$A$2,0,0,MAX(1,COUNTA(Lists!$A$2:$A$100)),1)
Name lst_currency: OFFSET(Lists!$B$2,0,0,MAX(1,COUNTA(Lists!$B$2:$B$100)),1)
Name lst_contract_type: OFFSET(Lists!$C$2,0,0,MAX(1,COUNTA(Lists!$C$2:$C$100)),1)
Name lst_employment_type: OFFSET(Lists!$D$2,0,0,MAX(1,COUNTA(Lists!$D$2:$D$100)),1)
Name lst_allocation_type: OFFSET(Lists!$E$2,0,0,MAX(1,COUNTA(Lists!$E$2:$E$100)),1)
Name lst_source_type: OFFSET(Lists!$F$2,0,0,MAX(1,COUNTA(Lists!$F$2:$F$100)),1)
Name lst_cost_category: OFFSET(Lists!$G$2,0,0,MAX(1,COUNTA(Lists!$G$2:$G$100)),1)
Name lst_rate_type: OFFSET(Lists!$H$2,0,0,MAX(1,COUNTA(Lists!$H$2:$H$100)),1)
Name lst_yes_no: OFFSET(Lists!$I$2,0,0,MAX(1,COUNTA(Lists!$I$2:$I$100)),1)
Name lst_cost_center: OFFSET(Cost_Centers!$A$2,0,0,MAX(1,COUNTA(Cost_Centers!$A$2:$A$2000)),1)
Name lst_account: OFFSET(Accounts!$A$2,0,0,MAX(1,COUNTA(Accounts!$A$2:$A$5000)),1)
Name rng_BvA: Budget_vs_Actual!$A$8:$V$1209
Name prm_close_month: Budget_vs_Actual!$C$4

Sheet Field_Definitions
A1: GDS Budget Ledger – Field Definitions / 項目定義
A3: How to use / 使い方
A4: • | B4: Opex_Budget is the only place where budgets are entered. It will be locked once the budget is final. | E4: 予算を入れる場所はOpex_Budgetだけです。予算確定後はロックされます。
A5: • | B5: Actuals: the budget manager pastes the accounting data as values at the end of the table every month, with import_batch set to the closing month. | E5: Actuals：予算管理者が毎月、会計データを表の末尾に値で貼り付けます。import_batchには締め月を入れます。
A6: • | B6: Budget_vs_Actual: set fiscal_year, close_month and display_currency at the top. Owners enter only the Forecast (input) and Rationale rows (light blue cells). | E6: Budget_vs_Actual：上部で会計年度・締め月・表示通貨を指定します。責任者が入力するのは見込み入力行と理由行（薄い青のセル）だけです。
A7: • | B7: Monthly order (budget manager, Excel desktop): 1) on Prior_Forecast, right-click the table > Refresh; 2) paste the new actuals into Actuals; 3) advance close_month. Always refresh Prior_Forecast before pasting actuals. See the monthly runbook for details. | E7: 毎月の手順（予算管理者、デスクトップ版Excel）：①Prior_Forecastの表を右クリック＞更新 ②新しい実績をActualsに貼り付ける ③締め月を進める。Prior_Forecastの更新は必ず実績の貼り付けより前に行う。詳細は月次運用手順書を参照。
A8: • | B8: If a check at the top of Budget_vs_Actual is not 0, some budget or actual rows have no block. Ask IT Finance to add the cost center and account. | E8: Budget_vs_Actual上部のチェックが0でない場合、ブロックのない予算・実績があります。ITファイナンスにコストセンター・勘定科目の追加を依頼してください。
A9: • | B9: Use Sheet View (View > Sheet View) to filter or sort, so other users are not affected. | E9: 絞り込み・並べ替えは「シートビュー」（表示＞シートビュー）で行い、他の人の表示を変えないでください。
A10: • | B10: Enter one record per row. Do not insert blank rows, merge cells or change column headers. | E10: 1行に1件を入力します。空行の挿入、セルの結合、列見出しの変更はしないでください。
A11: • | B11: Yes = required. Yes* = required depending on the type (see description). Use the dropdowns for List fields. | E11: Yes＝必須。Yes*＝種別によって必須（説明を参照）。List型はプルダウンから選びます。
A12: • | B12: Dates: YYYY-MM-DD. Amounts: excluding tax, in the currency of the row. Do not convert currencies. | E12: 日付はYYYY-MM-DD。金額は税抜で、その行の通貨のまま入力します。換算はしないでください。
A13: • | B13: The Example column shows the expected format only. Do not copy example values. | E13: Example列は入力形式の例です。例の値を転記しないでください。
A14: • | B14: Grey sheets (Cost_Centers, Accounts, FX_Rates, Lists) are copies of the master data file and must not be edited. To get the latest values, open in Excel desktop and click Data > Refresh All (not needed every time). To add or change values, ask IT Finance. | E14: グレーのシート（Cost_Centers・Accounts・FX_Rates・Lists）はマスタファイルの写しで、編集しません。最新にするときはデスクトップ版Excelで「データ＞すべて更新」を押します（毎回は不要）。値の追加・変更はITファイナンスに依頼してください。
A16: Sheets / シート一覧
A17: Sheet | B17: Maintained by | C17: Purpose (EN) | E17: 目的（日本語）
A18: Opex_Budget | B18: Input | C18: All budgets of GDS. Fixed (locked) once the budget is final. One row per fiscal year. | E18: GDSの予算をすべて集約するシート。予算確定後は固定（ロック）する。1行＝1会計年度
A19: Actuals | B19: ITF only | C19: Actuals downloaded from each region's accounting system, pasted monthly by the budget manager. | E19: 各リージョンの会計システムからダウンロードした実績。予算管理者が毎月貼り付ける
A20: Dashboard | B20: Auto (do not edit) | C20: Overview: KPIs, region x sub-function, monthly trend and the largest variances. Follows the settings at the top of Budget_vs_Actual. | E20: 全体像：KPI、リージョン×サブファンクション、月次推移、差異の大きい項目。Budget_vs_Actual上部の設定（年度・締め月・通貨）に連動する
A21: Budget_vs_Actual | B21: Auto (do not edit) / Forecast & Rationale: Input | C21: Budget, actual and actual + forecast by cost center and account, with variances and rationale. Budget and actual are filled automatically. | E21: コストセンター×勘定科目ごとの予算・実績・実績＋見込みと、差異・理由。予算と実績は自動で表示される
A22: Prior_Forecast | B22: ITF only | C22: Snapshot of the Actual + Forecast rows, refreshed by Power Query before new actuals are pasted. Feeds the Prior Month Forecast row. | E22: 実績＋見込み行の控え。新しい実績を貼り付ける前にPower Queryで更新する。前月見込みの行に表示される
A24: Opex_Budget — Input
A25: Sheet | B25: Field (EN) | C25: 項目名（日本語） | D25: Type | E25: Required | F25: Example | G25: Description (EN) | H25: 説明（日本語）
A26: Opex_Budget | B26: fiscal_year | C26: 会計年度 | D26: Integer | E26: Yes | F26: 2027 | G26: Fiscal year (January to December). | H26: 会計年度（1月〜12月）
A27: Opex_Budget | B27: region | C27: リージョン | D27: List | E27: Yes | F27: JP | G27: Region of the cost center. JP / NA / EMEA. | H27: コストセンターのリージョン。JP／NA／EMEA
A28: Opex_Budget | B28: owner | C28: 入力責任者 | D28: Text | E28: Yes | F28: T. Yamada | G28: Person responsible for keeping this row up to date. | H28: この行を最新に保つ責任者
A29: Opex_Budget | B29: budget_id | C29: 予算ID | D29: Text | E29: No | F29: BT-0012 | G29: Optional ID to identify the budget line (e.g. budget transfer case ID, internal budget number). | H29: 予算行を識別する任意のID（予算移管の案件ID、社内の予算番号など）
A30: Opex_Budget | B30: cost_center_code | C30: コストセンター | D30: List | E30: Yes | F30: JP-GDS-APP | G30: Cost center that bears the cost. | H30: 費用を計上するコストセンター
A31: Opex_Budget | B31: account_key | C31: 勘定科目 | D31: List | E31: Yes | F31: JP|5101 | G31: Local account of the region (format: region|local code). | H31: 当該リージョンの現地勘定科目（形式：リージョン|現地科目コード）
A32: Opex_Budget | B32: cost_category | C32: 費用区分 | D32: List | E32: Yes | F32: SaaS / License | G32: Nature of the cost, independent of the accounting account: SaaS / License, Maintenance, Outsourcing, Cloud, Telecom, Hardware, Personnel, Depreciation, Travel & Training, Other. | H32: 会計上の勘定科目とは別に、費用の性質で分類する区分（SaaS・ライセンス、保守、業務委託、クラウド、通信、ハードウェア、人件費、減価償却、出張・研修、その他）
A33: Opex_Budget | B33: system_name | C33: システム名 | D33: Text | E33: Yes | F33: Salesforce | G33: System the cost relates to. Use 'Common' for costs not tied to one system. | H33: 費用が関係するシステム。特定のシステムに紐づかない費用は「Common」と書く
A34: Opex_Budget | B34: vendor_name | C34: ベンダー名 | D34: Text | E34: Yes | F34: Salesforce Japan | G34: Vendor or supplier. Use 'Internal' for internal staff cost. | H34: ベンダー・取引先。社内人件費は「Internal」と書く
A35: Opex_Budget | B35: expense_item | C35: 費目 | D35: Text | E35: Yes | F35: Domestic travel | G35: What the budget is for. Several items may share the same cost center and account. | H35: 予算の内容。同じコストセンター・勘定科目の中で複数に分けてよい
A36: Opex_Budget | B36: project_id | C36: プロジェクトID | D36: Text | E36: Yes* | F36: CAPEX-2027-014 | G36: Capital investment budget number. *Required when the cost belongs to a project. | H36: 設備投資予算の管理番号。※プロジェクト案件の費用の場合は必須
... A51: Opex_Budget | B51: m12 | C51: 12月 | D51: Number | E51: No | F51: 500000 | G51: Budget for month 12, excluding tax. | H51: 12月の予算額（税抜）
A52: Opex_Budget | B52: note | C52: 備考 | D52: Text | E52: No | G52: Free comment. | H52: 備考
A54: Actuals — ITF only
A55: Sheet | B55: Field (EN) | C55: 項目名（日本語） | D55: Type | E55: Required | F55: Example | G55: Description (EN) | H55: 説明（日本語）
A56: Actuals | B56: region | C56: リージョン | D56: List | E56: Yes | F56: JP | G56: Region of the cost center. JP / NA / EMEA. | H56: コストセンターのリージョン。JP／NA／EMEA
A57: Actuals | B57: fiscal_year | C57: 会計年度 | D57: Integer | E57: Yes | F57: 2027 | G57: Fiscal year of the posting. | H57: 計上の会計年度
A58: Actuals | B58: month | C58: 月 | D58: Integer | E58: Yes | F58: 4 | G58: Posting month (1-12). | H58: 計上月（1〜12）
A59: Actuals | B59: cost_center_code | C59: コストセンター | D59: Text | E59: Yes | F59: JP-GDS-APP | G59: Cost center on the journal entry. | H59: 仕訳に指定されたコストセンター
A60: Actuals | B60: local_account_code | C60: 現地勘定科目コード | D60: Text | E60: Yes | F60: 5101 | G60: Account code in the region's accounting system (without region prefix). | H60: リージョンの会計システム上の科目コード（リージョン接頭辞なし）
A61: Actuals | B61: currency | C61: 通貨 | D61: List | E61: Yes | F61: JPY | G61: Currency of the posted amount. | H61: 計上額の通貨
A62: Actuals | B62: amount | C62: 金額 | D62: Number | E62: Yes | F62: 98000 | G62: Posted P&L amount, excluding tax. Credits as negative. | H62: PL計上額（税抜）。貸方はマイナス
A63: Actuals | B63: description | C63: 摘要・取引先 | D63: Text | E63: No | F63: Microsoft | G63: Optional, for investigating variances. | H63: 任意。差異の調査用
A64: Actuals | B64: import_batch | C64: 取込バッチ | D64: Text | E64: Yes | F64: 202704 | G64: YYYYMM of the closing month when the data was imported. | H64: 取り込んだときの締め月（YYYYMM）
A66: Budget_vs_Actual — Auto (do not edit) / Forecast & Rationale: Input
A67: Sheet | B67: Field (EN) | C67: 項目名（日本語） | D67: Type | E67: Required | F67: Example | G67: Description (EN) | H67: 説明（日本語）
A68: Budget_vs_Actual | B68: fiscal_year (C3) | C68: 会計年度 | D68: Integer | E68: Yes | F68: 2027 | G68: Fiscal year to display. | H68: 表示する会計年度
A69: Budget_vs_Actual | B69: close_month (C4) | C69: 締め月 | D69: Integer 1-12 | E69: Yes | F69: 6 | G69: Last month with actuals. Months up to this month use actuals; later months use the forecast. | H69: 実績がそろっている最後の月。この月までは実績、以降は見込みを使う
A70: Budget_vs_Actual | B70: display_currency (C5) | C70: 表示通貨 | D70: List | E70: Yes | F70: JPY | G70: All amounts are converted to this currency at the budget rate (FX_Rates). | H70: すべての金額をこの通貨に予算レート（FX_Rates）で換算して表示する
A71: Budget_vs_Actual | B71: cost_center_code / account_key | C71: コストセンター／勘定科目 | D71: Key | E71: Yes | F71: JP-GDS-APP / JP|5101 | G71: Set by IT Finance on the first row of each block after the budget is fixed. Other rows follow automatically. | H71: 予算確定後、ITファイナンスが各ブロックの1行目に設定する。他の行は自動で連動する
A72: Budget_vs_Actual | B72: owner | C72: 責任者 | D72: Text | E72: Yes | F72: T. Yamada | G72: Person who explains variances and maintains the forecast for this block. | H72: このブロックの差異説明と見込み更新の責任者
A73: Budget_vs_Actual | B73: Budget | C73: 予算 | D73: Row (auto) | E73: - | G73: Sum of Opex_Budget for the cost center and account. | H73: Opex_Budgetの該当コストセンター・勘定科目の合計
A74: Budget_vs_Actual | B74: Actual | C74: 実績 | D74: Row (auto) | E74: - | G74: Sum of Actuals. Shown up to close_month. | H74: Actualsの合計。締め月まで表示
A75: Budget_vs_Actual | B75: Variance vs Budget | C75: 差異（対予算） | D75: Row (auto) | E75: - | G75: Months / YTD: Actual - Budget. MTG: forecast for the remaining months - Budget. FY = YTD + MTG. Positive = overspend. | H75: 各月・YTD：実績−予算。MTG：残り期間の見込み−予算。FY＝YTD＋MTG。プラスは超過
A76: Budget_vs_Actual | B76: Forecast (input) | C76: 見込み（入力） | D76: Row (input) | E76: No | F76: 120000 | G76: Expected amount for months after close_month. Leave blank to keep the budget amount. | H76: 締め月より後の月の見込み額。空欄なら予算額のまま
A77: Budget_vs_Actual | B77: Actual + Forecast | C77: 実績＋見込み | D77: Row (auto) | E77: - | G77: Actual up to close_month (taken from the Actual row); after that, the Forecast (input) row above, or the budget if it is blank. | H77: 締め月まではActual行の実績を転記、以降は直上の見込み入力行の値（空欄なら予算）
A78: Budget_vs_Actual | B78: Prior Month Forecast | C78: 前月見込み | D78: Row (auto) | E78: - | G78: Actual + Forecast as of the previous month, read from the Prior_Forecast sheet by cost center and account. | H78: 前月時点の実績＋見込み。Prior_Forecastシートからコストセンター・勘定科目で引いて表示する
A79: Budget_vs_Actual | B79: Variance vs Prior Month | C79: 差異（対前月見込み） | D79: Row (auto) | E79: - | G79: (Actual + Forecast) - Prior Month Forecast. Shows how much the outlook moved this month. Positive = increase. | H79: （実績＋見込み）−前月見込み。今月どれだけ見込みが動いたか。プラスは増加
A80: Budget_vs_Actual | B80: Rationale | C80: 理由 | D80: Row (input) | E80: When variance | F80: Invoice delayed | G80: Month columns: reason for each month's variance. YTD column: comment on the year-to-date total. MTG column: comment on the remaining-period forecast (vs budget and vs prior month). | H80: 月の列：各月の差異の理由。YTD列：累計に対するコメント。MTG列：残り期間の見込みに対するコメント（対予算・対前月）

Sheet Dashboard
A1: GDS Budget Dashboard / 予算ダッシュボード
A2: ="FY "&Budget_vs_Actual!$C$3&" | Close month: "&Budget_vs_Actual!$C$4&" | Currency: "&Budget_vs_Actual!$C$5&" | Prior forecast as of month: "&Budget_vs_Actual!$G$7
A4: Key figures / 主要指標
A5: FY Budget | B5: YTD Budget | C5: YTD Actual | D5: YTD Variance | E5: FY Actual + Forecast | F5: FY Variance vs Budget | G5: FY Variance vs Budget (prior month) | H5: Change vs Prior Month
A6: 通期予算 | B6: 累計予算 | C6: 累計実績 | D6: 累計差異 | E6: 通期着地見込み | F6: 通期差異（対予算） | G6: 前月時点の通期差異（対予算） | H6: 前月からの変化
A7: =SUMIFS(Budget_vs_Actual!$V:$V,Budget_vs_Actual!$G:$G,"Budget") | B7: =SUMIFS(Budget_vs_Actual!$T:$T,Budget_vs_Actual!$G:$G,"Budget") | C7: =SUMIFS(Budget_vs_Actual!$T:$T,Budget_vs_Actual!$G:$G,"Actual") | D7: =C7-B7 | E7: =SUMIFS(Budget_vs_Actual!$V:$V,Budget_vs_Actual!$G:$G,"Actual + Forecast") | F7: =E7-A7 | G7: =F7-H7 | H7: =SUMIFS(Budget_vs_Actual!$V:$V,Budget_vs_Actual!$G:$G,"Variance vs Prior Month")
D8: =IFERROR(D7/B7,0) | F8: =IFERROR(F7/A7,0) | G8: =IFERROR(G7/A7,0) | H8: =IFERROR(H7/A7,0)
A11: By region and sub-function / リージョン×サブファンクション別
A12: Region | B12: Sub-function | C12: FY Budget | D12: YTD Budget | E12: YTD Actual | F12: YTD Variance | G12: FY Actual + Forecast | H12: FY Variance | I12: Change vs Prior
A13: JP | B13: Applications | C13: =SUMIFS(Budget_vs_Actual!$V:$V,Budget_vs_Actual!$G:$G,"Budget",Budget_vs_Actual!$A:$A,"JP",Budget_vs_Actual!$X:$X,"Applications",Budget_vs_Actual!$Y:$Y,"GDS") | D13: =SUMIFS(Budget_vs_Actual!$T:$T,Budget_vs_Actual!$G:$G,"Budget",Budget_vs_Actual!$A:$A,"JP",Budget_vs_Actual!$X:$X,"Applications",Budget_vs_Actual!$Y:$Y,"GDS") | E13: =SUMIFS(Budget_vs_Actual!$T:$T,Budget_vs_Actual!$G:$G,"Actual",Budget_vs_Actual!$A:$A,"JP",Budget_vs_Actual!$X:$X,"Applications",Budget_vs_Actual!$Y:$Y,"GDS") | F13: =E13-D13 | G13: =SUMIFS(Budget_vs_Actual!$V:$V,Budget_vs_Actual!$G:$G,"Actual + Forecast",Budget_vs_Actual!$A:$A,"JP",Budget_vs_Actual!$X:$X,"Applications",Budget_vs_Actual!$Y:$Y,"GDS") | H13: =G13-C13 | I13: =SUMIFS(Budget_vs_Actual!$V:$V,Budget_vs_Actual!$G:$G,"Variance vs Prior Month",Budget_vs_Actual!$A:$A,"JP",Budget_vs_Actual!$X:$X,"Applications",Budget_vs_Actual!$Y:$Y,"GDS")
A14: JP | B14: Infrastructure | C14: =SUMIFS(Budget_vs_Actual!$V:$V,Budget_vs_Actual!$G:$G,"Budget",Budget_vs_Actual!$A:$A,"JP",Budget_vs_Actual!$X:$X,"Infrastructure",Budget_vs_Actual!$Y:$Y,"GDS") | D14: =SUMIFS(Budget_vs_Actual!$T:$T,Budget_vs_Actual!$G:$G,"Budget",Budget_vs_Actual!$A:$A,"JP",Budget_vs_Actual!$X:$X,"Infrastructure",Budget_vs_Actual!$Y:$Y,"GDS") | E14: =SUMIFS(Budget_vs_Actual!$T:$T,Budget_vs_Actual!$G:$G,"Actual",Budget_vs_Actual!$A:$A,"JP",Budget_vs_Actual!$X:$X,"Infrastructure",Budget_vs_Actual!$Y:$Y,"GDS") | F14: =E14-D14 | G14: =SUMIFS(Budget_vs_Actual!$V:$V,Budget_vs_Actual!$G:$G,"Actual + Forecast",Budget_vs_Actual!$A:$A,"JP",Budget_vs_Actual!$X:$X,"Infrastructure",Budget_vs_Actual!$Y:$Y,"GDS") | H14: =G14-C14 | I14: =SUMIFS(Budget_vs_Actual!$V:$V,Budget_vs_Actual!$G:$G,"Variance vs Prior Month",Budget_vs_Actual!$A:$A,"JP",Budget_vs_Actual!$X:$X,"Infrastructure",Budget_vs_Actual!$Y:$Y,"GDS")
A15: JP | B15: Data | C15: =SUMIFS(Budget_vs_Actual!$V:$V,Budget_vs_Actual!$G:$G,"Budget",Budget_vs_Actual!$A:$A,"JP",Budget_vs_Actual!$X:$X,"Data",Budget_vs_Actual!$Y:$Y,"GDS") | D15: =SUMIFS(Budget_vs_Actual!$T:$T,Budget_vs_Actual!$G:$G,"Budget",Budget_vs_Actual!$A:$A,"JP",Budget_vs_Actual!$X:$X,"Data",Budget_vs_Actual!$Y:$Y,"GDS") | E15: =SUMIFS(Budget_vs_Actual!$T:$T,Budget_vs_Actual!$G:$G,"Actual",Budget_vs_Actual!$A:$A,"JP",Budget_vs_Actual!$X:$X,"Data",Budget_vs_Actual!$Y:$Y,"GDS") | F15: =E15-D15 | G15: =SUMIFS(Budget_vs_Actual!$V:$V,Budget_vs_Actual!$G:$G,"Actual + Forecast",Budget_vs_Actual!$A:$A,"JP",Budget_vs_Actual!$X:$X,"Data",Budget_vs_Actual!$Y:$Y,"GDS") | H15: =G15-C15 | I15: =SUMIFS(Budget_vs_Actual!$V:$V,Budget_vs_Actual!$G:$G,"Variance vs Prior Month",Budget_vs_Actual!$A:$A,"JP",Budget_vs_Actual!$X:$X,"Data",Budget_vs_Actual!$Y:$Y,"GDS")
A16: JP | B16: Security | C16: =SUMIFS(Budget_vs_Actual!$V:$V,Budget_vs_Actual!$G:$G,"Budget",Budget_vs_Actual!$A:$A,"JP",Budget_vs_Actual!$X:$X,"Security",Budget_vs_Actual!$Y:$Y,"GDS") | D16: =SUMIFS(Budget_vs_Actual!$T:$T,Budget_vs_Actual!$G:$G,"Budget",Budget_vs_Actual!$A:$A,"JP",Budget_vs_Actual!$X:$X,"Security",Budget_vs_Actual!$Y:$Y,"GDS") | E16: =SUMIFS(Budget_vs_Actual!$T:$T,Budget_vs_Actual!$G:$G,"Actual",Budget_vs_Actual!$A:$A,"JP",Budget_vs_Actual!$X:$X,"Security",Budget_vs_Actual!$Y:$Y,"GDS") | F16: =E16-D16 | G16: =SUMIFS(Budget_vs_Actual!$V:$V,Budget_vs_Actual!$G:$G,"Actual + Forecast",Budget_vs_Actual!$A:$A,"JP",Budget_vs_Actual!$X:$X,"Security",Budget_vs_Actual!$Y:$Y,"GDS") | H16: =G16-C16 | I16: =SUMIFS(Budget_vs_Actual!$V:$V,Budget_vs_Actual!$G:$G,"Variance vs Prior Month",Budget_vs_Actual!$A:$A,"JP",Budget_vs_Actual!$X:$X,"Security",Budget_vs_Actual!$Y:$Y,"GDS")
A17: JP | B17: Governance | C17: =SUMIFS(Budget_vs_Actual!$V:$V,Budget_vs_Actual!$G:$G,"Budget",Budget_vs_Actual!$A:$A,"JP",Budget_vs_Actual!$X:$X,"Governance",Budget_vs_Actual!$Y:$Y,"GDS") | D17: =SUMIFS(Budget_vs_Actual!$T:$T,Budget_vs_Actual!$G:$G,"Budget",Budget_vs_Actual!$A:$A,"JP",Budget_vs_Actual!$X:$X,"Governance",Budget_vs_Actual!$Y:$Y,"GDS") | E17: =SUMIFS(Budget_vs_Actual!$T:$T,Budget_vs_Actual!$G:$G,"Actual",Budget_vs_Actual!$A:$A,"JP",Budget_vs_Actual!$X:$X,"Governance",Budget_vs_Actual!$Y:$Y,"GDS") | F17: =E17-D17 | G17: =SUMIFS(Budget_vs_Actual!$V:$V,Budget_vs_Actual!$G:$G,"Actual + Forecast",Budget_vs_Actual!$A:$A,"JP",Budget_vs_Actual!$X:$X,"Governance",Budget_vs_Actual!$Y:$Y,"GDS") | H17: =G17-C17 | I17: =SUMIFS(Budget_vs_Actual!$V:$V,Budget_vs_Actual!$G:$G,"Variance vs Prior Month",Budget_vs_Actual!$A:$A,"JP",Budget_vs_Actual!$X:$X,"Governance",Budget_vs_Actual!$Y:$Y,"GDS")
A18: JP | B18: Transferred (other functions) | C18: =SUMIFS(Budget_vs_Actual!$V:$V,Budget_vs_Actual!$G:$G,"Budget",Budget_vs_Actual!$A:$A,"JP",Budget_vs_Actual!$Y:$Y,"<>GDS") | D18: =SUMIFS(Budget_vs_Actual!$T:$T,Budget_vs_Actual!$G:$G,"Budget",Budget_vs_Actual!$A:$A,"JP",Budget_vs_Actual!$Y:$Y,"<>GDS") | E18: =SUMIFS(Budget_vs_Actual!$T:$T,Budget_vs_Actual!$G:$G,"Actual",Budget_vs_Actual!$A:$A,"JP",Budget_vs_Actual!$Y:$Y,"<>GDS") | F18: =E18-D18 | G18: =SUMIFS(Budget_vs_Actual!$V:$V,Budget_vs_Actual!$G:$G,"Actual + Forecast",Budget_vs_Actual!$A:$A,"JP",Budget_vs_Actual!$Y:$Y,"<>GDS") | H18: =G18-C18 | I18: =SUMIFS(Budget_vs_Actual!$V:$V,Budget_vs_Actual!$G:$G,"Variance vs Prior Month",Budget_vs_Actual!$A:$A,"JP",Budget_vs_Actual!$Y:$Y,"<>GDS")
A19: JP | B19: Subtotal | C19: =SUM(C13:C18) | D19: =SUM(D13:D18) | E19: =SUM(E13:E18) | F19: =SUM(F13:F18) | G19: =SUM(G13:G18) | H19: =SUM(H13:H18) | I19: =SUM(I13:I18)
A20: NA | B20: Applications | C20: =SUMIFS(Budget_vs_Actual!$V:$V,Budget_vs_Actual!$G:$G,"Budget",Budget_vs_Actual!$A:$A,"NA",Budget_vs_Actual!$X:$X,"Applications",Budget_vs_Actual!$Y:$Y,"GDS") | D20: =SUMIFS(Budget_vs_Actual!$T:$T,Budget_vs_Actual!$G:$G,"Budget",Budget_vs_Actual!$A:$A,"NA",Budget_vs_Actual!$X:$X,"Applications",Budget_vs_Actual!$Y:$Y,"GDS") | E20: =SUMIFS(Budget_vs_Actual!$T:$T,Budget_vs_Actual!$G:$G,"Actual",Budget_vs_Actual!$A:$A,"NA",Budget_vs_Actual!$X:$X,"Applications",Budget_vs_Actual!$Y:$Y,"GDS") | F20: =E20-D20 | G20: =SUMIFS(Budget_vs_Actual!$V:$V,Budget_vs_Actual!$G:$G,"Actual + Forecast",Budget_vs_Actual!$A:$A,"NA",Budget_vs_Actual!$X:$X,"Applications",Budget_vs_Actual!$Y:$Y,"GDS") | H20: =G20-C20 | I20: =SUMIFS(Budget_vs_Actual!$V:$V,Budget_vs_Actual!$G:$G,"Variance vs Prior Month",Budget_vs_Actual!$A:$A,"NA",Budget_vs_Actual!$X:$X,"Applications",Budget_vs_Actual!$Y:$Y,"GDS")
A21: NA | B21: Infrastructure | C21: =SUMIFS(Budget_vs_Actual!$V:$V,Budget_vs_Actual!$G:$G,"Budget",Budget_vs_Actual!$A:$A,"NA",Budget_vs_Actual!$X:$X,"Infrastructure",Budget_vs_Actual!$Y:$Y,"GDS") | D21: =SUMIFS(Budget_vs_Actual!$T:$T,Budget_vs_Actual!$G:$G,"Budget",Budget_vs_Actual!$A:$A,"NA",Budget_vs_Actual!$X:$X,"Infrastructure",Budget_vs_Actual!$Y:$Y,"GDS") | E21: =SUMIFS(Budget_vs_Actual!$T:$T,Budget_vs_Actual!$G:$G,"Actual",Budget_vs_Actual!$A:$A,"NA",Budget_vs_Actual!$X:$X,"Infrastructure",Budget_vs_Actual!$Y:$Y,"GDS") | F21: =E21-D21 | G21: =SUMIFS(Budget_vs_Actual!$V:$V,Budget_vs_Actual!$G:$G,"Actual + Forecast",Budget_vs_Actual!$A:$A,"NA",Budget_vs_Actual!$X:$X,"Infrastructure",Budget_vs_Actual!$Y:$Y,"GDS") | H21: =G21-C21 | I21: =SUMIFS(Budget_vs_Actual!$V:$V,Budget_vs_Actual!$G:$G,"Variance vs Prior Month",Budget_vs_Actual!$A:$A,"NA",Budget_vs_Actual!$X:$X,"Infrastructure",Budget_vs_Actual!$Y:$Y,"GDS")
A22: NA | B22: Data | C22: =SUMIFS(Budget_vs_Actual!$V:$V,Budget_vs_Actual!$G:$G,"Budget",Budget_vs_Actual!$A:$A,"NA",Budget_vs_Actual!$X:$X,"Data",Budget_vs_Actual!$Y:$Y,"GDS") | D22: =SUMIFS(Budget_vs_Actual!$T:$T,Budget_vs_Actual!$G:$G,"Budget",Budget_vs_Actual!$A:$A,"NA",Budget_vs_Actual!$X:$X,"Data",Budget_vs_Actual!$Y:$Y,"GDS") | E22: =SUMIFS(Budget_vs_Actual!$T:$T,Budget_vs_Actual!$G:$G,"Actual",Budget_vs_Actual!$A:$A,"NA",Budget_vs_Actual!$X:$X,"Data",Budget_vs_Actual!$Y:$Y,"GDS") | F22: =E22-D22 | G22: =SUMIFS(Budget_vs_Actual!$V:$V,Budget_vs_Actual!$G:$G,"Actual + Forecast",Budget_vs_Actual!$A:$A,"NA",Budget_vs_Actual!$X:$X,"Data",Budget_vs_Actual!$Y:$Y,"GDS") | H22: =G22-C22 | I22: =SUMIFS(Budget_vs_Actual!$V:$V,Budget_vs_Actual!$G:$G,"Variance vs Prior Month",Budget_vs_Actual!$A:$A,"NA",Budget_vs_Actual!$X:$X,"Data",Budget_vs_Actual!$Y:$Y,"GDS")
A23: NA | B23: Security | C23: =SUMIFS(Budget_vs_Actual!$V:$V,Budget_vs_Actual!$G:$G,"Budget",Budget_vs_Actual!$A:$A,"NA",Budget_vs_Actual!$X:$X,"Security",Budget_vs_Actual!$Y:$Y,"GDS") | D23: =SUMIFS(Budget_vs_Actual!$T:$T,Budget_vs_Actual!$G:$G,"Budget",Budget_vs_Actual!$A:$A,"NA",Budget_vs_Actual!$X:$X,"Security",Budget_vs_Actual!$Y:$Y,"GDS") | E23: =SUMIFS(Budget_vs_Actual!$T:$T,Budget_vs_Actual!$G:$G,"Actual",Budget_vs_Actual!$A:$A,"NA",Budget_vs_Actual!$X:$X,"Security",Budget_vs_Actual!$Y:$Y,"GDS") | F23: =E23-D23 | G23: =SUMIFS(Budget_vs_Actual!$V:$V,Budget_vs_Actual!$G:$G,"Actual + Forecast",Budget_vs_Actual!$A:$A,"NA",Budget_vs_Actual!$X:$X,"Security",Budget_vs_Actual!$Y:$Y,"GDS") | H23: =G23-C23 | I23: =SUMIFS(Budget_vs_Actual!$V:$V,Budget_vs_Actual!$G:$G,"Variance vs Prior Month",Budget_vs_Actual!$A:$A,"NA",Budget_vs_Actual!$X:$X,"Security",Budget_vs_Actual!$Y:$Y,"GDS")
A24: NA | B24: Governance | C24: =SUMIFS(Budget_vs_Actual!$V:$V,Budget_vs_Actual!$G:$G,"Budget",Budget_vs_Actual!$A:$A,"NA",Budget_vs_Actual!$X:$X,"Governance",Budget_vs_Actual!$Y:$Y,"GDS") | D24: =SUMIFS(Budget_vs_Actual!$T:$T,Budget_vs_Actual!$G:$G,"Budget",Budget_vs_Actual!$A:$A,"NA",Budget_vs_Actual!$X:$X,"Governance",Budget_vs_Actual!$Y:$Y,"GDS") | E24: =SUMIFS(Budget_vs_Actual!$T:$T,Budget_vs_Actual!$G:$G,"Actual",Budget_vs_Actual!$A:$A,"NA",Budget_vs_Actual!$X:$X,"Governance",Budget_vs_Actual!$Y:$Y,"GDS") | F24: =E24-D24 | G24: =SUMIFS(Budget_vs_Actual!$V:$V,Budget_vs_Actual!$G:$G,"Actual + Forecast",Budget_vs_Actual!$A:$A,"NA",Budget_vs_Actual!$X:$X,"Governance",Budget_vs_Actual!$Y:$Y,"GDS") | H24: =G24-C24 | I24: =SUMIFS(Budget_vs_Actual!$V:$V,Budget_vs_Actual!$G:$G,"Variance vs Prior Month",Budget_vs_Actual!$A:$A,"NA",Budget_vs_Actual!$X:$X,"Governance",Budget_vs_Actual!$Y:$Y,"GDS")
A25: NA | B25: Transferred (other functions) | C25: =SUMIFS(Budget_vs_Actual!$V:$V,Budget_vs_Actual!$G:$G,"Budget",Budget_vs_Actual!$A:$A,"NA",Budget_vs_Actual!$Y:$Y,"<>GDS") | D25: =SUMIFS(Budget_vs_Actual!$T:$T,Budget_vs_Actual!$G:$G,"Budget",Budget_vs_Actual!$A:$A,"NA",Budget_vs_Actual!$Y:$Y,"<>GDS") | E25: =SUMIFS(Budget_vs_Actual!$T:$T,Budget_vs_Actual!$G:$G,"Actual",Budget_vs_Actual!$A:$A,"NA",Budget_vs_Actual!$Y:$Y,"<>GDS") | F25: =E25-D25 | G25: =SUMIFS(Budget_vs_Actual!$V:$V,Budget_vs_Actual!$G:$G,"Actual + Forecast",Budget_vs_Actual!$A:$A,"NA",Budget_vs_Actual!$Y:$Y,"<>GDS") | H25: =G25-C25 | I25: =SUMIFS(Budget_vs_Actual!$V:$V,Budget_vs_Actual!$G:$G,"Variance vs Prior Month",Budget_vs_Actual!$A:$A,"NA",Budget_vs_Actual!$Y:$Y,"<>GDS")
A26: NA | B26: Subtotal | C26: =SUM(C20:C25) | D26: =SUM(D20:D25) | E26: =SUM(E20:E25) | F26: =SUM(F20:F25) | G26: =SUM(G20:G25) | H26: =SUM(H20:H25) | I26: =SUM(I20:I25)
A27: EMEA | B27: Applications | C27: =SUMIFS(Budget_vs_Actual!$V:$V,Budget_vs_Actual!$G:$G,"Budget",Budget_vs_Actual!$A:$A,"EMEA",Budget_vs_Actual!$X:$X,"Applications",Budget_vs_Actual!$Y:$Y,"GDS") | D27: =SUMIFS(Budget_vs_Actual!$T:$T,Budget_vs_Actual!$G:$G,"Budget",Budget_vs_Actual!$A:$A,"EMEA",Budget_vs_Actual!$X:$X,"Applications",Budget_vs_Actual!$Y:$Y,"GDS") | E27: =SUMIFS(Budget_vs_Actual!$T:$T,Budget_vs_Actual!$G:$G,"Actual",Budget_vs_Actual!$A:$A,"EMEA",Budget_vs_Actual!$X:$X,"Applications",Budget_vs_Actual!$Y:$Y,"GDS") | F27: =E27-D27 | G27: =SUMIFS(Budget_vs_Actual!$V:$V,Budget_vs_Actual!$G:$G,"Actual + Forecast",Budget_vs_Actual!$A:$A,"EMEA",Budget_vs_Actual!$X:$X,"Applications",Budget_vs_Actual!$Y:$Y,"GDS") | H27: =G27-C27 | I27: =SUMIFS(Budget_vs_Actual!$V:$V,Budget_vs_Actual!$G:$G,"Variance vs Prior Month",Budget_vs_Actual!$A:$A,"EMEA",Budget_vs_Actual!$X:$X,"Applications",Budget_vs_Actual!$Y:$Y,"GDS")
A28: EMEA | B28: Infrastructure | C28: =SUMIFS(Budget_vs_Actual!$V:$V,Budget_vs_Actual!$G:$G,"Budget",Budget_vs_Actual!$A:$A,"EMEA",Budget_vs_Actual!$X:$X,"Infrastructure",Budget_vs_Actual!$Y:$Y,"GDS") | D28: =SUMIFS(Budget_vs_Actual!$T:$T,Budget_vs_Actual!$G:$G,"Budget",Budget_vs_Actual!$A:$A,"EMEA",Budget_vs_Actual!$X:$X,"Infrastructure",Budget_vs_Actual!$Y:$Y,"GDS") | E28: =SUMIFS(Budget_vs_Actual!$T:$T,Budget_vs_Actual!$G:$G,"Actual",Budget_vs_Actual!$A:$A,"EMEA",Budget_vs_Actual!$X:$X,"Infrastructure",Budget_vs_Actual!$Y:$Y,"GDS") | F28: =E28-D28 | G28: =SUMIFS(Budget_vs_Actual!$V:$V,Budget_vs_Actual!$G:$G,"Actual + Forecast",Budget_vs_Actual!$A:$A,"EMEA",Budget_vs_Actual!$X:$X,"Infrastructure",Budget_vs_Actual!$Y:$Y,"GDS") | H28: =G28-C28 | I28: =SUMIFS(Budget_vs_Actual!$V:$V,Budget_vs_Actual!$G:$G,"Variance vs Prior Month",Budget_vs_Actual!$A:$A,"EMEA",Budget_vs_Actual!$X:$X,"Infrastructure",Budget_vs_Actual!$Y:$Y,"GDS")
A29: EMEA | B29: Data | C29: =SUMIFS(Budget_vs_Actual!$V:$V,Budget_vs_Actual!$G:$G,"Budget",Budget_vs_Actual!$A:$A,"EMEA",Budget_vs_Actual!$X:$X,"Data",Budget_vs_Actual!$Y:$Y,"GDS") | D29: =SUMIFS(Budget_vs_Actual!$T:$T,Budget_vs_Actual!$G:$G,"Budget",Budget_vs_Actual!$A:$A,"EMEA",Budget_vs_Actual!$X:$X,"Data",Budget_vs_Actual!$Y:$Y,"GDS") | E29: =SUMIFS(Budget_vs_Actual!$T:$T,Budget_vs_Actual!$G:$G,"Actual",Budget_vs_Actual!$A:$A,"EMEA",Budget_vs_Actual!$X:$X,"Data",Budget_vs_Actual!$Y:$Y,"GDS") | F29: =E29-D29 | G29: =SUMIFS(Budget_vs_Actual!$V:$V,Budget_vs_Actual!$G:$G,"Actual + Forecast",Budget_vs_Actual!$A:$A,"EMEA",Budget_vs_Actual!$X:$X,"Data",Budget_vs_Actual!$Y:$Y,"GDS") | H29: =G29-C29 | I29: =SUMIFS(Budget_vs_Actual!$V:$V,Budget_vs_Actual!$G:$G,"Variance vs Prior Month",Budget_vs_Actual!$A:$A,"EMEA",Budget_vs_Actual!$X:$X,"Data",Budget_vs_Actual!$Y:$Y,"GDS")
A30: EMEA | B30: Security | C30: =SUMIFS(Budget_vs_Actual!$V:$V,Budget_vs_Actual!$G:$G,"Budget",Budget_vs_Actual!$A:$A,"EMEA",Budget_vs_Actual!$X:$X,"Security",Budget_vs_Actual!$Y:$Y,"GDS") | D30: =SUMIFS(Budget_vs_Actual!$T:$T,Budget_vs_Actual!$G:$G,"Budget",Budget_vs_Actual!$A:$A,"EMEA",Budget_vs_Actual!$X:$X,"Security",Budget_vs_Actual!$Y:$Y,"GDS") | E30: =SUMIFS(Budget_vs_Actual!$T:$T,Budget_vs_Actual!$G:$G,"Actual",Budget_vs_Actual!$A:$A,"EMEA",Budget_vs_Actual!$X:$X,"Security",Budget_vs_Actual!$Y:$Y,"GDS") | F30: =E30-D30 | G30: =SUMIFS(Budget_vs_Actual!$V:$V,Budget_vs_Actual!$G:$G,"Actual + Forecast",Budget_vs_Actual!$A:$A,"EMEA",Budget_vs_Actual!$X:$X,"Security",Budget_vs_Actual!$Y:$Y,"GDS") | H30: =G30-C30 | I30: =SUMIFS(Budget_vs_Actual!$V:$V,Budget_vs_Actual!$G:$G,"Variance vs Prior Month",Budget_vs_Actual!$A:$A,"EMEA",Budget_vs_Actual!$X:$X,"Security",Budget_vs_Actual!$Y:$Y,"GDS")
A31: EMEA | B31: Governance | C31: =SUMIFS(Budget_vs_Actual!$V:$V,Budget_vs_Actual!$G:$G,"Budget",Budget_vs_Actual!$A:$A,"EMEA",Budget_vs_Actual!$X:$X,"Governance",Budget_vs_Actual!$Y:$Y,"GDS") | D31: =SUMIFS(Budget_vs_Actual!$T:$T,Budget_vs_Actual!$G:$G,"Budget",Budget_vs_Actual!$A:$A,"EMEA",Budget_vs_Actual!$X:$X,"Governance",Budget_vs_Actual!$Y:$Y,"GDS") | E31: =SUMIFS(Budget_vs_Actual!$T:$T,Budget_vs_Actual!$G:$G,"Actual",Budget_vs_Actual!$A:$A,"EMEA",Budget_vs_Actual!$X:$X,"Governance",Budget_vs_Actual!$Y:$Y,"GDS") | F31: =E31-D31 | G31: =SUMIFS(Budget_vs_Actual!$V:$V,Budget_vs_Actual!$G:$G,"Actual + Forecast",Budget_vs_Actual!$A:$A,"EMEA",Budget_vs_Actual!$X:$X,"Governance",Budget_vs_Actual!$Y:$Y,"GDS") | H31: =G31-C31 | I31: =SUMIFS(Budget_vs_Actual!$V:$V,Budget_vs_Actual!$G:$G,"Variance vs Prior Month",Budget_vs_Actual!$A:$A,"EMEA",Budget_vs_Actual!$X:$X,"Governance",Budget_vs_Actual!$Y:$Y,"GDS")
A32: EMEA | B32: Transferred (other functions) | C32: =SUMIFS(Budget_vs_Actual!$V:$V,Budget_vs_Actual!$G:$G,"Budget",Budget_vs_Actual!$A:$A,"EMEA",Budget_vs_Actual!$Y:$Y,"<>GDS") | D32: =SUMIFS(Budget_vs_Actual!$T:$T,Budget_vs_Actual!$G:$G,"Budget",Budget_vs_Actual!$A:$A,"EMEA",Budget_vs_Actual!$Y:$Y,"<>GDS") | E32: =SUMIFS(Budget_vs_Actual!$T:$T,Budget_vs_Actual!$G:$G,"Actual",Budget_vs_Actual!$A:$A,"EMEA",Budget_vs_Actual!$Y:$Y,"<>GDS") | F32: =E32-D32 | G32: =SUMIFS(Budget_vs_Actual!$V:$V,Budget_vs_Actual!$G:$G,"Actual + Forecast",Budget_vs_Actual!$A:$A,"EMEA",Budget_vs_Actual!$Y:$Y,"<>GDS") | H32: =G32-C32 | I32: =SUMIFS(Budget_vs_Actual!$V:$V,Budget_vs_Actual!$G:$G,"Variance vs Prior Month",Budget_vs_Actual!$A:$A,"EMEA",Budget_vs_Actual!$Y:$Y,"<>GDS")
A33: EMEA | B33: Subtotal | C33: =SUM(C27:C32) | D33: =SUM(D27:D32) | E33: =SUM(E27:E32) | F33: =SUM(F27:F32) | G33: =SUM(G27:G32) | H33: =SUM(H27:H32) | I33: =SUM(I27:I32)
A34: Total | C34: =SUMIFS(C13:C33,$B13:$B33,"Subtotal") | D34: =SUMIFS(D13:D33,$B13:$B33,"Subtotal") | E34: =SUMIFS(E13:E33,$B13:$B33,"Subtotal") | F34: =SUMIFS(F13:F33,$B13:$B33,"Subtotal") | G34: =SUMIFS(G13:G33,$B13:$B33,"Subtotal") | H34: =SUMIFS(H13:H33,$B13:$B33,"Subtotal") | I34: =SUMIFS(I13:I33,$B13:$B33,"Subtotal")
A37: Monthly budget vs actual / 月次の予算と実績
A38: Month | B38: Budget | C38: Actual | D38: Forecast | E38: Variance %
A39: Jan | B39: =SUMIFS(Budget_vs_Actual!$H:$H,Budget_vs_Actual!$G:$G,"Budget") | C39: =IF(1<=Budget_vs_Actual!$C$4,SUMIFS(Budget_vs_Actual!$H:$H,Budget_vs_Actual!$G:$G,"Actual"),0) | D39: =IF(1>Budget_vs_Actual!$C$4,SUMIFS(Budget_vs_Actual!$H:$H,Budget_vs_Actual!$G:$G,"Actual + Forecast"),0) | E39: =IFERROR((C39+D39-B39)/B39,0)
A40: Feb | B40: =SUMIFS(Budget_vs_Actual!$I:$I,Budget_vs_Actual!$G:$G,"Budget") | C40: =IF(2<=Budget_vs_Actual!$C$4,SUMIFS(Budget_vs_Actual!$I:$I,Budget_vs_Actual!$G:$G,"Actual"),0) | D40: =IF(2>Budget_vs_Actual!$C$4,SUMIFS(Budget_vs_Actual!$I:$I,Budget_vs_Actual!$G:$G,"Actual + Forecast"),0) | E40: =IFERROR((C40+D40-B40)/B40,0)
A41: Mar | B41: =SUMIFS(Budget_vs_Actual!$J:$J,Budget_vs_Actual!$G:$G,"Budget") | C41: =IF(3<=Budget_vs_Actual!$C$4,SUMIFS(Budget_vs_Actual!$J:$J,Budget_vs_Actual!$G:$G,"Actual"),0) | D41: =IF(3>Budget_vs_Actual!$C$4,SUMIFS(Budget_vs_Actual!$J:$J,Budget_vs_Actual!$G:$G,"Actual + Forecast"),0) | E41: =IFERROR((C41+D41-B41)/B41,0)
A42: Apr | B42: =SUMIFS(Budget_vs_Actual!$K:$K,Budget_vs_Actual!$G:$G,"Budget") | C42: =IF(4<=Budget_vs_Actual!$C$4,SUMIFS(Budget_vs_Actual!$K:$K,Budget_vs_Actual!$G:$G,"Actual"),0) | D42: =IF(4>Budget_vs_Actual!$C$4,SUMIFS(Budget_vs_Actual!$K:$K,Budget_vs_Actual!$G:$G,"Actual + Forecast"),0) | E42: =IFERROR((C42+D42-B42)/B42,0)
A43: May | B43: =SUMIFS(Budget_vs_Actual!$L:$L,Budget_vs_Actual!$G:$G,"Budget") | C43: =IF(5<=Budget_vs_Actual!$C$4,SUMIFS(Budget_vs_Actual!$L:$L,Budget_vs_Actual!$G:$G,"Actual"),0) | D43: =IF(5>Budget_vs_Actual!$C$4,SUMIFS(Budget_vs_Actual!$L:$L,Budget_vs_Actual!$G:$G,"Actual + Forecast"),0) | E43: =IFERROR((C43+D43-B43)/B43,0)
A44: Jun | B44: =SUMIFS(Budget_vs_Actual!$M:$M,Budget_vs_Actual!$G:$G,"Budget") | C44: =IF(6<=Budget_vs_Actual!$C$4,SUMIFS(Budget_vs_Actual!$M:$M,Budget_vs_Actual!$G:$G,"Actual"),0) | D44: =IF(6>Budget_vs_Actual!$C$4,SUMIFS(Budget_vs_Actual!$M:$M,Budget_vs_Actual!$G:$G,"Actual + Forecast"),0) | E44: =IFERROR((C44+D44-B44)/B44,0)
A45: Jul | B45: =SUMIFS(Budget_vs_Actual!$N:$N,Budget_vs_Actual!$G:$G,"Budget") | C45: =IF(7<=Budget_vs_Actual!$C$4,SUMIFS(Budget_vs_Actual!$N:$N,Budget_vs_Actual!$G:$G,"Actual"),0) | D45: =IF(7>Budget_vs_Actual!$C$4,SUMIFS(Budget_vs_Actual!$N:$N,Budget_vs_Actual!$G:$G,"Actual + Forecast"),0) | E45: =IFERROR((C45+D45-B45)/B45,0)
A46: Aug | B46: =SUMIFS(Budget_vs_Actual!$O:$O,Budget_vs_Actual!$G:$G,"Budget") | C46: =IF(8<=Budget_vs_Actual!$C$4,SUMIFS(Budget_vs_Actual!$O:$O,Budget_vs_Actual!$G:$G,"Actual"),0) | D46: =IF(8>Budget_vs_Actual!$C$4,SUMIFS(Budget_vs_Actual!$O:$O,Budget_vs_Actual!$G:$G,"Actual + Forecast"),0) | E46: =IFERROR((C46+D46-B46)/B46,0)
A47: Sep | B47: =SUMIFS(Budget_vs_Actual!$P:$P,Budget_vs_Actual!$G:$G,"Budget") | C47: =IF(9<=Budget_vs_Actual!$C$4,SUMIFS(Budget_vs_Actual!$P:$P,Budget_vs_Actual!$G:$G,"Actual"),0) | D47: =IF(9>Budget_vs_Actual!$C$4,SUMIFS(Budget_vs_Actual!$P:$P,Budget_vs_Actual!$G:$G,"Actual + Forecast"),0) | E47: =IFERROR((C47+D47-B47)/B47,0)
A48: Oct | B48: =SUMIFS(Budget_vs_Actual!$Q:$Q,Budget_vs_Actual!$G:$G,"Budget") | C48: =IF(10<=Budget_vs_Actual!$C$4,SUMIFS(Budget_vs_Actual!$Q:$Q,Budget_vs_Actual!$G:$G,"Actual"),0) | D48: =IF(10>Budget_vs_Actual!$C$4,SUMIFS(Budget_vs_Actual!$Q:$Q,Budget_vs_Actual!$G:$G,"Actual + Forecast"),0) | E48: =IFERROR((C48+D48-B48)/B48,0)
A49: Nov | B49: =SUMIFS(Budget_vs_Actual!$R:$R,Budget_vs_Actual!$G:$G,"Budget") | C49: =IF(11<=Budget_vs_Actual!$C$4,SUMIFS(Budget_vs_Actual!$R:$R,Budget_vs_Actual!$G:$G,"Actual"),0) | D49: =IF(11>Budget_vs_Actual!$C$4,SUMIFS(Budget_vs_Actual!$R:$R,Budget_vs_Actual!$G:$G,"Actual + Forecast"),0) | E49: =IFERROR((C49+D49-B49)/B49,0)
A50: Dec | B50: =SUMIFS(Budget_vs_Actual!$S:$S,Budget_vs_Actual!$G:$G,"Budget") | C50: =IF(12<=Budget_vs_Actual!$C$4,SUMIFS(Budget_vs_Actual!$S:$S,Budget_vs_Actual!$G:$G,"Actual"),0) | D50: =IF(12>Budget_vs_Actual!$C$4,SUMIFS(Budget_vs_Actual!$S:$S,Budget_vs_Actual!$G:$G,"Actual + Forecast"),0) | E50: =IFERROR((C50+D50-B50)/B50,0)
A51: Bars: actual (dark) up to the close month, forecast (light) after. Dashed line: budget. Red line: (actual + forecast - budget) / budget on the right axis (±15%, 0 in the middle).
A61: Largest variances vs budget (FY) / 対予算の差異が大きい項目（通期）
A62: # | B62: Cost center | C62: Account | D62: Owner | E62: YTD Variance | F62: MTG Variance | G62: FY Variance | H62: Rationale (YTD) | I62: Rationale (MTG)
A63: 1 | B63: =IF($L63="","",INDEX(Budget_vs_Actual!$C:$C,$L63+0)&"") | C63: =IF($L63="","",INDEX(Budget_vs_Actual!$E:$E,$L63+0)&"") | D63: =IF($L63="","",INDEX(Budget_vs_Actual!$F:$F,$L63+0)&"") | E63: =IF($L63="","",INDEX(Budget_vs_Actual!$T:$T,$L63+0)) | F63: =IF($L63="","",INDEX(Budget_vs_Actual!$U:$U,$L63+0)) | G63: =IF($L63="","",INDEX(Budget_vs_Actual!$V:$V,$L63+0)) | H63: =IF($L63="","",INDEX(Budget_vs_Actual!$T:$T,$L63+5)&"") | I63: =IF($L63="","",INDEX(Budget_vs_Actual!$U:$U,$L63+5)&"") | K63: =IFERROR(LARGE(Budget_vs_Actual!$Z:$Z,1),0) | L63: =IF($K63<1,"",MATCH($K63,Budget_vs_Actual!$Z:$Z,0))
A64: 2 | B64: =IF($L64="","",INDEX(Budget_vs_Actual!$C:$C,$L64+0)&"") | C64: =IF($L64="","",INDEX(Budget_vs_Actual!$E:$E,$L64+0)&"") | D64: =IF($L64="","",INDEX(Budget_vs_Actual!$F:$F,$L64+0)&"") | E64: =IF($L64="","",INDEX(Budget_vs_Actual!$T:$T,$L64+0)) | F64: =IF($L64="","",INDEX(Budget_vs_Actual!$U:$U,$L64+0)) | G64: =IF($L64="","",INDEX(Budget_vs_Actual!$V:$V,$L64+0)) | H64: =IF($L64="","",INDEX(Budget_vs_Actual!$T:$T,$L64+5)&"") | I64: =IF($L64="","",INDEX(Budget_vs_Actual!$U:$U,$L64+5)&"") | K64: =IFERROR(LARGE(Budget_vs_Actual!$Z:$Z,2),0) | L64: =IF($K64<1,"",MATCH($K64,Budget_vs_Actual!$Z:$Z,0))
A65: 3 | B65: =IF($L65="","",INDEX(Budget_vs_Actual!$C:$C,$L65+0)&"") | C65: =IF($L65="","",INDEX(Budget_vs_Actual!$E:$E,$L65+0)&"") | D65: =IF($L65="","",INDEX(Budget_vs_Actual!$F:$F,$L65+0)&"") | E65: =IF($L65="","",INDEX(Budget_vs_Actual!$T:$T,$L65+0)) | F65: =IF($L65="","",INDEX(Budget_vs_Actual!$U:$U,$L65+0)) | G65: =IF($L65="","",INDEX(Budget_vs_Actual!$V:$V,$L65+0)) | H65: =IF($L65="","",INDEX(Budget_vs_Actual!$T:$T,$L65+5)&"") | I65: =IF($L65="","",INDEX(Budget_vs_Actual!$U:$U,$L65+5)&"") | K65: =IFERROR(LARGE(Budget_vs_Actual!$Z:$Z,3),0) | L65: =IF($K65<1,"",MATCH($K65,Budget_vs_Actual!$Z:$Z,0))
A66: 4 | B66: =IF($L66="","",INDEX(Budget_vs_Actual!$C:$C,$L66+0)&"") | C66: =IF($L66="","",INDEX(Budget_vs_Actual!$E:$E,$L66+0)&"") | D66: =IF($L66="","",INDEX(Budget_vs_Actual!$F:$F,$L66+0)&"") | E66: =IF($L66="","",INDEX(Budget_vs_Actual!$T:$T,$L66+0)) | F66: =IF($L66="","",INDEX(Budget_vs_Actual!$U:$U,$L66+0)) | G66: =IF($L66="","",INDEX(Budget_vs_Actual!$V:$V,$L66+0)) | H66: =IF($L66="","",INDEX(Budget_vs_Actual!$T:$T,$L66+5)&"") | I66: =IF($L66="","",INDEX(Budget_vs_Actual!$U:$U,$L66+5)&"") | K66: =IFERROR(LARGE(Budget_vs_Actual!$Z:$Z,4),0) | L66: =IF($K66<1,"",MATCH($K66,Budget_vs_Actual!$Z:$Z,0))
A67: 5 | B67: =IF($L67="","",INDEX(Budget_vs_Actual!$C:$C,$L67+0)&"") | C67: =IF($L67="","",INDEX(Budget_vs_Actual!$E:$E,$L67+0)&"") | D67: =IF($L67="","",INDEX(Budget_vs_Actual!$F:$F,$L67+0)&"") | E67: =IF($L67="","",INDEX(Budget_vs_Actual!$T:$T,$L67+0)) | F67: =IF($L67="","",INDEX(Budget_vs_Actual!$U:$U,$L67+0)) | G67: =IF($L67="","",INDEX(Budget_vs_Actual!$V:$V,$L67+0)) | H67: =IF($L67="","",INDEX(Budget_vs_Actual!$T:$T,$L67+5)&"") | I67: =IF($L67="","",INDEX(Budget_vs_Actual!$U:$U,$L67+5)&"") | K67: =IFERROR(LARGE(Budget_vs_Actual!$Z:$Z,5),0) | L67: =IF($K67<1,"",MATCH($K67,Budget_vs_Actual!$Z:$Z,0))
A68: 6 | B68: =IF($L68="","",INDEX(Budget_vs_Actual!$C:$C,$L68+0)&"") | C68: =IF($L68="","",INDEX(Budget_vs_Actual!$E:$E,$L68+0)&"") | D68: =IF($L68="","",INDEX(Budget_vs_Actual!$F:$F,$L68+0)&"") | E68: =IF($L68="","",INDEX(Budget_vs_Actual!$T:$T,$L68+0)) | F68: =IF($L68="","",INDEX(Budget_vs_Actual!$U:$U,$L68+0)) | G68: =IF($L68="","",INDEX(Budget_vs_Actual!$V:$V,$L68+0)) | H68: =IF($L68="","",INDEX(Budget_vs_Actual!$T:$T,$L68+5)&"") | I68: =IF($L68="","",INDEX(Budget_vs_Actual!$U:$U,$L68+5)&"") | K68: =IFERROR(LARGE(Budget_vs_Actual!$Z:$Z,6),0) | L68: =IF($K68<1,"",MATCH($K68,Budget_vs_Actual!$Z:$Z,0))
A69: 7 | B69: =IF($L69="","",INDEX(Budget_vs_Actual!$C:$C,$L69+0)&"") | C69: =IF($L69="","",INDEX(Budget_vs_Actual!$E:$E,$L69+0)&"") | D69: =IF($L69="","",INDEX(Budget_vs_Actual!$F:$F,$L69+0)&"") | E69: =IF($L69="","",INDEX(Budget_vs_Actual!$T:$T,$L69+0)) | F69: =IF($L69="","",INDEX(Budget_vs_Actual!$U:$U,$L69+0)) | G69: =IF($L69="","",INDEX(Budget_vs_Actual!$V:$V,$L69+0)) | H69: =IF($L69="","",INDEX(Budget_vs_Actual!$T:$T,$L69+5)&"") | I69: =IF($L69="","",INDEX(Budget_vs_Actual!$U:$U,$L69+5)&"") | K69: =IFERROR(LARGE(Budget_vs_Actual!$Z:$Z,7),0) | L69: =IF($K69<1,"",MATCH($K69,Budget_vs_Actual!$Z:$Z,0))
A70: 8 | B70: =IF($L70="","",INDEX(Budget_vs_Actual!$C:$C,$L70+0)&"") | C70: =IF($L70="","",INDEX(Budget_vs_Actual!$E:$E,$L70+0)&"") | D70: =IF($L70="","",INDEX(Budget_vs_Actual!$F:$F,$L70+0)&"") | E70: =IF($L70="","",INDEX(Budget_vs_Actual!$T:$T,$L70+0)) | F70: =IF($L70="","",INDEX(Budget_vs_Actual!$U:$U,$L70+0)) | G70: =IF($L70="","",INDEX(Budget_vs_Actual!$V:$V,$L70+0)) | H70: =IF($L70="","",INDEX(Budget_vs_Actual!$T:$T,$L70+5)&"") | I70: =IF($L70="","",INDEX(Budget_vs_Actual!$U:$U,$L70+5)&"") | K70: =IFERROR(LARGE(Budget_vs_Actual!$Z:$Z,8),0) | L70: =IF($K70<1,"",MATCH($K70,Budget_vs_Actual!$Z:$Z,0))
A71: 9 | B71: =IF($L71="","",INDEX(Budget_vs_Actual!$C:$C,$L71+0)&"") | C71: =IF($L71="","",INDEX(Budget_vs_Actual!$E:$E,$L71+0)&"") | D71: =IF($L71="","",INDEX(Budget_vs_Actual!$F:$F,$L71+0)&"") | E71: =IF($L71="","",INDEX(Budget_vs_Actual!$T:$T,$L71+0)) | F71: =IF($L71="","",INDEX(Budget_vs_Actual!$U:$U,$L71+0)) | G71: =IF($L71="","",INDEX(Budget_vs_Actual!$V:$V,$L71+0)) | H71: =IF($L71="","",INDEX(Budget_vs_Actual!$T:$T,$L71+5)&"") | I71: =IF($L71="","",INDEX(Budget_vs_Actual!$U:$U,$L71+5)&"") | K71: =IFERROR(LARGE(Budget_vs_Actual!$Z:$Z,9),0) | L71: =IF($K71<1,"",MATCH($K71,Budget_vs_Actual!$Z:$Z,0))
A72: 10 | B72: =IF($L72="","",INDEX(Budget_vs_Actual!$C:$C,$L72+0)&"") | C72: =IF($L72="","",INDEX(Budget_vs_Actual!$E:$E,$L72+0)&"") | D72: =IF($L72="","",INDEX(Budget_vs_Actual!$F:$F,$L72+0)&"") | E72: =IF($L72="","",INDEX(Budget_vs_Actual!$T:$T,$L72+0)) | F72: =IF($L72="","",INDEX(Budget_vs_Actual!$U:$U,$L72+0)) | G72: =IF($L72="","",INDEX(Budget_vs_Actual!$V:$V,$L72+0)) | H72: =IF($L72="","",INDEX(Budget_vs_Actual!$T:$T,$L72+5)&"") | I72: =IF($L72="","",INDEX(Budget_vs_Actual!$U:$U,$L72+5)&"") | K72: =IFERROR(LARGE(Budget_vs_Actual!$Z:$Z,10),0) | L72: =IF($K72<1,"",MATCH($K72,Budget_vs_Actual!$Z:$Z,0))

Sheet Budget_vs_Actual
A1: Budget vs Actual / 予実対比
A3: fiscal_year | C3: 2027 | E3: FX factor to display currency (budget rate) | J3: Checks (should be 0) / チェック（0であること）
A4: close_month | C4: 1 | E4: JPY | F4: USD | G4: EUR | H4: GBP | J4: Budget not in any block / ブロック外の予算 | P4: =ROUND((SUMPRODUCT((Opex_Budget!$A$2:$A$2001=$C$3)*(Opex_Budget!$N$2:$N$2001="JPY")*Opex_Budget!$O$2:$Z$2001)*$E$5+SUMPRODUCT((Opex_Budget!$A$2:$A$2001=$C$3)*(Opex_Budget!$N$2:$N$2001="USD")*Opex_Budget!$O$2:$Z$2001)*$F$5+SUMPRODUCT((Opex_Budget!$A$2:$A$2001=$C$3)*(Opex_Budget!$N$2:$N$2001="EUR")*Opex_Budget!$O$2:$Z$2001)*$G$5+SUMPRODUCT((Opex_Budget!$A$2:$A$2001=$C$3)*(Opex_Budget!$N$2:$N$2001="GBP")*Opex_Budget!$O$2:$Z$2001)*$H$5)-SUMIFS($V$10:$V$1210,$G$10:$G$1210,"Budget"),0)
A5: display_currency | C5: JPY | E5: =IF(E$4=$C$5,1,IFERROR(SUMIFS(FX_Rates!$D:$D,FX_Rates!$A:$A,$C$3,FX_Rates!$B:$B,"BUDGET",FX_Rates!$C:$C,E$4)/SUMIFS(FX_Rates!$D:$D,FX_Rates!$A:$A,$C$3,FX_Rates!$B:$B,"BUDGET",FX_Rates!$C:$C,$C$5),0)) | F5: =IF(F$4=$C$5,1,IFERROR(SUMIFS(FX_Rates!$D:$D,FX_Rates!$A:$A,$C$3,FX_Rates!$B:$B,"BUDGET",FX_Rates!$C:$C,F$4)/SUMIFS(FX_Rates!$D:$D,FX_Rates!$A:$A,$C$3,FX_Rates!$B:$B,"BUDGET",FX_Rates!$C:$C,$C$5),0)) | G5: =IF(G$4=$C$5,1,IFERROR(SUMIFS(FX_Rates!$D:$D,FX_Rates!$A:$A,$C$3,FX_Rates!$B:$B,"BUDGET",FX_Rates!$C:$C,G$4)/SUMIFS(FX_Rates!$D:$D,FX_Rates!$A:$A,$C$3,FX_Rates!$B:$B,"BUDGET",FX_Rates!$C:$C,$C$5),0)) | H5: =IF(H$4=$C$5,1,IFERROR(SUMIFS(FX_Rates!$D:$D,FX_Rates!$A:$A,$C$3,FX_Rates!$B:$B,"BUDGET",FX_Rates!$C:$C,H$4)/SUMIFS(FX_Rates!$D:$D,FX_Rates!$A:$A,$C$3,FX_Rates!$B:$B,"BUDGET",FX_Rates!$C:$C,$C$5),0)) | J5: Actual not in any block / ブロック外の実績 | P5: =ROUND((SUMIFS(Actuals!$G:$G,Actuals!$B:$B,$C$3,Actuals!$C:$C,"<="&$C$4,Actuals!$F:$F,"JPY")*$E$5+SUMIFS(Actuals!$G:$G,Actuals!$B:$B,$C$3,Actuals!$C:$C,"<="&$C$4,Actuals!$F:$F,"USD")*$F$5+SUMIFS(Actuals!$G:$G,Actuals!$B:$B,$C$3,Actuals!$C:$C,"<="&$C$4,Actuals!$F:$F,"EUR")*$G$5+SUMIFS(Actuals!$G:$G,Actuals!$B:$B,$C$3,Actuals!$C:$C,"<="&$C$4,Actuals!$F:$F,"GBP")*$H$5)-SUMIFS($T$10:$T$1210,$G$10:$G$1210,"Actual"),0)
E7: Prior forecast as of close month / 前月見込みの基準月: | G7: =IFERROR(MAX(Prior_Forecast!$R:$R),"") | H7: 1 | I7: 2 | J7: 3 | K7: 4 | L7: 5 | M7: 6 | N7: 7 | O7: 8 | P7: 9 | Q7: 10 | R7: 11 | S7: 12
A8: region | B8: cost_center_code | C8: cost_center_name | D8: account_key | E8: account_name | F8: owner | G8: line | H8: Jan | I8: Feb | J8: Mar | K8: Apr | L8: May | M8: Jun | N8: Jul | O8: Aug | P8: Sep | Q8: Oct | R8: Nov | S8: Dec | T8: YTD | U8: MTG | V8: FY | X8: sub_function | Y8: function | Z8: abs_fy_var
A10: =IF($D$10="","",LEFT($D$10,FIND("|",$D$10&"|")-1)) | C10: =IF($B$10="","",IFERROR(INDEX(Cost_Centers!$B:$B,MATCH($B$10,Cost_Centers!$A:$A,0)),"(not in master)")) | E10: =IF($D$10="","",IFERROR(INDEX(Accounts!$D:$D,MATCH($D$10,Accounts!$A:$A,0)),"(not in master)")) | G10: Budget | H10: =IF($B$10="","",SUMIFS(Opex_Budget!$O:$O,Opex_Budget!$A:$A,$C$3,Opex_Budget!$E:$E,$B$10,Opex_Budget!$F:$F,$D$10,Opex_Budget!$N:$N,"JPY")*$E$5+SUMIFS(Opex_Budget!$O:$O,Opex_Budget!$A:$A,$C$3,Opex_Budget!$E:$E,$B$10,Opex_Budget!$F:$F,$D$10,Opex_Budget!$N:$N,"USD")*$F$5+SUMIFS(Opex_Budget!$O:$O,Opex_Budget!$A:$A,$C$3,Opex_Budget!$E:$E,$B$10,Opex_Budget!$F:$F,$D$10,Opex_Budget!$N:$N,"EUR")*$G$5+SUMIFS(Opex_Budget!$O:$O,Opex_Budget!$A:$A,$C$3,Opex_Budget!$E:$E,$B$10,Opex_Budget!$F:$F,$D$10,Opex_Budget!$N:$N,"GBP")*$H$5) | I10: =IF($B$10="","",SUMIFS(Opex_Budget!$P:$P,Opex_Budget!$A:$A,$C$3,Opex_Budget!$E:$E,$B$10,Opex_Budget!$F:$F,$D$10,Opex_Budget!$N:$N,"JPY")*$E$5+SUMIFS(Opex_Budget!$P:$P,Opex_Budget!$A:$A,$C$3,Opex_Budget!$E:$E,$B$10,Opex_Budget!$F:$F,$D$10,Opex_Budget!$N:$N,"USD")*$F$5+SUMIFS(Opex_Budget!$P:$P,Opex_Budget!$A:$A,$C$3,Opex_Budget!$E:$E,$B$10,Opex_Budget!$F:$F,$D$10,Opex_Budget!$N:$N,"EUR")*$G$5+SUMIFS(Opex_Budget!$P:$P,Opex_Budget!$A:$A,$C$3,Opex_Budget!$E:$E,$B$10,Opex_Budget!$F:$F,$D$10,Opex_Budget!$N:$N,"GBP")*$H$5) | J10: =IF($B$10="","",SUMIFS(Opex_Budget!$Q:$Q,Opex_Budget!$A:$A,$C$3,Opex_Budget!$E:$E,$B$10,Opex_Budget!$F:$F,$D$10,Opex_Budget!$N:$N,"JPY")*$E$5+SUMIFS(Opex_Budget!$Q:$Q,Opex_Budget!$A:$A,$C$3,Opex_Budget!$E:$E,$B$10,Opex_Budget!$F:$F,$D$10,Opex_Budget!$N:$N,"USD")*$F$5+SUMIFS(Opex_Budget!$Q:$Q,Opex_Budget!$A:$A,$C$3,Opex_Budget!$E:$E,$B$10,Opex_Budget!$F:$F,$D$10,Opex_Budget!$N:$N,"EUR")*$G$5+SUMIFS(Opex_Budget!$Q:$Q,Opex_Budget!$A:$A,$C$3,Opex_Budget!$E:$E,$B$10,Opex_Budget!$F:$F,$D$10,Opex_Budget!$N:$N,"GBP")*$H$5) | K10: =IF($B$10="","",SUMIFS(Opex_Budget!$R:$R,Opex_Budget!$A:$A,$C$3,Opex_Budget!$E:$E,$B$10,Opex_Budget!$F:$F,$D$10,Opex_Budget!$N:$N,"JPY")*$E$5+SUMIFS(Opex_Budget!$R:$R,Opex_Budget!$A:$A,$C$3,Opex_Budget!$E:$E,$B$10,Opex_Budget!$F:$F,$D$10,Opex_Budget!$N:$N,"USD")*$F$5+SUMIFS(Opex_Budget!$R:$R,Opex_Budget!$A:$A,$C$3,Opex_Budget!$E:$E,$B$10,Opex_Budget!$F:$F,$D$10,Opex_Budget!$N:$N,"EUR")*$G$5+SUMIFS(Opex_Budget!$R:$R,Opex_Budget!$A:$A,$C$3,Opex_Budget!$E:$E,$B$10,Opex_Budget!$F:$F,$D$10,Opex_Budget!$N:$N,"GBP")*$H$5) | L10: =IF($B$10="","",SUMIFS(Opex_Budget!$S:$S,Opex_Budget!$A:$A,$C$3,Opex_Budget!$E:$E,$B$10,Opex_Budget!$F:$F,$D$10,Opex_Budget!$N:$N,"JPY")*$E$5+SUMIFS(Opex_Budget!$S:$S,Opex_Budget!$A:$A,$C$3,Opex_Budget!$E:$E,$B$10,Opex_Budget!$F:$F,$D$10,Opex_Budget!$N:$N,"USD")*$F$5+SUMIFS(Opex_Budget!$S:$S,Opex_Budget!$A:$A,$C$3,Opex_Budget!$E:$E,$B$10,Opex_Budget!$F:$F,$D$10,Opex_Budget!$N:$N,"EUR")*$G$5+SUMIFS(Opex_Budget!$S:$S,Opex_Budget!$A:$A,$C$3,Opex_Budget!$E:$E,$B$10,Opex_Budget!$F:$F,$D$10,Opex_Budget!$N:$N,"GBP")*$H$5) | M10: =IF($B$10="","",SUMIFS(Opex_Budget!$T:$T,Opex_Budget!$A:$A,$C$3,Opex_Budget!$E:$E,$B$10,Opex_Budget!$F:$F,$D$10,Opex_Budget!$N:$N,"JPY")*$E$5+SUMIFS(Opex_Budget!$T:$T,Opex_Budget!$A:$A,$C$3,Opex_Budget!$E:$E,$B$10,Opex_Budget!$F:$F,$D$10,Opex_Budget!$N:$N,"USD")*$F$5+SUMIFS(Opex_Budget!$T:$T,Opex_Budget!$A:$A,$C$3,Opex_Budget!$E:$E,$B$10,Opex_Budget!$F:$F,$D$10,Opex_Budget!$N:$N,"EUR")*$G$5+SUMIFS(Opex_Budget!$T:$T,Opex_Budget!$A:$A,$C$3,Opex_Budget!$E:$E,$B$10,Opex_Budget!$F:$F,$D$10,Opex_Budget!$N:$N,"GBP")*$H$5) | N10: =IF($B$10="","",SUMIFS(Opex_Budget!$U:$U,Opex_Budget!$A:$A,$C$3,Opex_Budget!$E:$E,$B$10,Opex_Budget!$F:$F,$D$10,Opex_Budget!$N:$N,"JPY")*$E$5+SUMIFS(Opex_Budget!$U:$U,Opex_Budget!$A:$A,$C$3,Opex_Budget!$E:$E,$B$10,Opex_Budget!$F:$F,$D$10,Opex_Budget!$N:$N,"USD")*$F$5+SUMIFS(Opex_Budget!$U:$U,Opex_Budget!$A:$A,$C$3,Opex_Budget!$E:$E,$B$10,Opex_Budget!$F:$F,$D$10,Opex_Budget!$N:$N,"EUR")*$G$5+SUMIFS(Opex_Budget!$U:$U,Opex_Budget!$A:$A,$C$3,Opex_Budget!$E:$E,$B$10,Opex_Budget!$F:$F,$D$10,Opex_Budget!$N:$N,"GBP")*$H$5) | O10: =IF($B$10="","",SUMIFS(Opex_Budget!$V:$V,Opex_Budget!$A:$A,$C$3,Opex_Budget!$E:$E,$B$10,Opex_Budget!$F:$F,$D$10,Opex_Budget!$N:$N,"JPY")*$E$5+SUMIFS(Opex_Budget!$V:$V,Opex_Budget!$A:$A,$C$3,Opex_Budget!$E:$E,$B$10,Opex_Budget!$F:$F,$D$10,Opex_Budget!$N:$N,"USD")*$F$5+SUMIFS(Opex_Budget!$V:$V,Opex_Budget!$A:$A,$C$3,Opex_Budget!$E:$E,$B$10,Opex_Budget!$F:$F,$D$10,Opex_Budget!$N:$N,"EUR")*$G$5+SUMIFS(Opex_Budget!$V:$V,Opex_Budget!$A:$A,$C$3,Opex_Budget!$E:$E,$B$10,Opex_Budget!$F:$F,$D$10,Opex_Budget!$N:$N,"GBP")*$H$5) | P10: =IF($B$10="","",SUMIFS(Opex_Budget!$W:$W,Opex_Budget!$A:$A,$C$3,Opex_Budget!$E:$E,$B$10,Opex_Budget!$F:$F,$D$10,Opex_Budget!$N:$N,"JPY")*$E$5+SUMIFS(Opex_Budget!$W:$W,Opex_Budget!$A:$A,$C$3,Opex_Budget!$E:$E,$B$10,Opex_Budget!$F:$F,$D$10,Opex_Budget!$N:$N,"USD")*$F$5+SUMIFS(Opex_Budget!$W:$W,Opex_Budget!$A:$A,$C$3,Opex_Budget!$E:$E,$B$10,Opex_Budget!$F:$F,$D$10,Opex_Budget!$N:$N,"EUR")*$G$5+SUMIFS(Opex_Budget!$W:$W,Opex_Budget!$A:$A,$C$3,Opex_Budget!$E:$E,$B$10,Opex_Budget!$F:$F,$D$10,Opex_Budget!$N:$N,"GBP")*$H$5) | Q10: =IF($B$10="","",SUMIFS(Opex_Budget!$X:$X,Opex_Budget!$A:$A,$C$3,Opex_Budget!$E:$E,$B$10,Opex_Budget!$F:$F,$D$10,Opex_Budget!$N:$N,"JPY")*$E$5+SUMIFS(Opex_Budget!$X:$X,Opex_Budget!$A:$A,$C$3,Opex_Budget!$E:$E,$B$10,Opex_Budget!$F:$F,$D$10,Opex_Budget!$N:$N,"USD")*$F$5+SUMIFS(Opex_Budget!$X:$X,Opex_Budget!$A:$A,$C$3,Opex_Budget!$E:$E,$B$10,Opex_Budget!$F:$F,$D$10,Opex_Budget!$N:$N,"EUR")*$G$5+SUMIFS(Opex_Budget!$X:$X,Opex_Budget!$A:$A,$C$3,Opex_Budget!$E:$E,$B$10,Opex_Budget!$F:$F,$D$10,Opex_Budget!$N:$N,"GBP")*$H$5) | R10: =IF($B$10="","",SUMIFS(Opex_Budget!$Y:$Y,Opex_Budget!$A:$A,$C$3,Opex_Budget!$E:$E,$B$10,Opex_Budget!$F:$F,$D$10,Opex_Budget!$N:$N,"JPY")*$E$5+SUMIFS(Opex_Budget!$Y:$Y,Opex_Budget!$A:$A,$C$3,Opex_Budget!$E:$E,$B$10,Opex_Budget!$F:$F,$D$10,Opex_Budget!$N:$N,"USD")*$F$5+SUMIFS(Opex_Budget!$Y:$Y,Opex_Budget!$A:$A,$C$3,Opex_Budget!$E:$E,$B$10,Opex_Budget!$F:$F,$D$10,Opex_Budget!$N:$N,"EUR")*$G$5+SUMIFS(Opex_Budget!$Y:$Y,Opex_Budget!$A:$A,$C$3,Opex_Budget!$E:$E,$B$10,Opex_Budget!$F:$F,$D$10,Opex_Budget!$N:$N,"GBP")*$H$5) | S10: =IF($B$10="","",SUMIFS(Opex_Budget!$Z:$Z,Opex_Budget!$A:$A,$C$3,Opex_Budget!$E:$E,$B$10,Opex_Budget!$F:$F,$D$10,Opex_Budget!$N:$N,"JPY")*$E$5+SUMIFS(Opex_Budget!$Z:$Z,Opex_Budget!$A:$A,$C$3,Opex_Budget!$E:$E,$B$10,Opex_Budget!$F:$F,$D$10,Opex_Budget!$N:$N,"USD")*$F$5+SUMIFS(Opex_Budget!$Z:$Z,Opex_Budget!$A:$A,$C$3,Opex_Budget!$E:$E,$B$10,Opex_Budget!$F:$F,$D$10,Opex_Budget!$N:$N,"EUR")*$G$5+SUMIFS(Opex_Budget!$Z:$Z,Opex_Budget!$A:$A,$C$3,Opex_Budget!$E:$E,$B$10,Opex_Budget!$F:$F,$D$10,Opex_Budget!$N:$N,"GBP")*$H$5) | T10: =IF($B$10="","",SUMIF($H$7:$S$7,"<="&$C$4,$H10:$S10)) | U10: =IF($B$10="","",SUMIF($H$7:$S$7,">"&$C$4,$H10:$S10)) | V10: =IF($B$10="","",SUM($H10:$S10)) | X10: =IF($B10="","",IFERROR(INDEX(Cost_Centers!$E:$E,MATCH($B10,Cost_Centers!$A:$A,0)),"(unknown)")) | Y10: =IF($B10="","",IFERROR(INDEX(Cost_Centers!$D:$D,MATCH($B10,Cost_Centers!$A:$A,0)),"(unknown)")) | Z10: =IF(OR($B10="",$G10<>"Variance vs Budget"),"",ABS(N($V10))+ROW()/1000000000)
A11: =IF(A$10="","",A$10) | B11: =IF(B$10="","",B$10) | C11: =IF(C$10="","",C$10) | D11: =IF(D$10="","",D$10) | E11: =IF(E$10="","",E$10) | F11: =IF(F$10="","",F$10) | G11: Actual | H11: =IF(OR($B$10="",1>$C$4),"",SUMIFS(Actuals!$G:$G,Actuals!$B:$B,$C$3,Actuals!$C:$C,1,Actuals!$D:$D,$B$10,Actuals!$A:$A,LEFT($D$10,FIND("|",$D$10&"|")-1),Actuals!$E:$E,MID($D$10,FIND("|",$D$10&"|")+1,50),Actuals!$F:$F,"JPY")*$E$5+SUMIFS(Actuals!$G:$G,Actuals!$B:$B,$C$3,Actuals!$C:$C,1,Actuals!$D:$D,$B$10,Actuals!$A:$A,LEFT($D$10,FIND("|",$D$10&"|")-1),Actuals!$E:$E,MID($D$10,FIND("|",$D$10&"|")+1,50),Actuals!$F:$F,"USD")*$F$5+SUMIFS(Actuals!$G:$G,Actuals!$B:$B,$C$3,Actuals!$C:$C,1,Actuals!$D:$D,$B$10,Actuals!$A:$A,LEFT($D$10,FIND("|",$D$10&"|")-1),Actuals!$E:$E,MID($D$10,FIND("|",$D$10&"|")+1,50),Actuals!$F:$F,"EUR")*$G$5+SUMIFS(Actuals!$G:$G,Actuals!$B:$B,$C$3,Actuals!$C:$C,1,Actuals!$D:$D,$B$10,Actuals!$A:$A,LEFT($D$10,FIND("|",$D$10&"|")-1),Actuals!$E:$E,MID($D$10,FIND("|",$D$10&"|")+1,50),Actuals!$F:$F,"GBP")*$H$5) | I11: =IF(OR($B$10="",2>$C$4),"",SUMIFS(Actuals!$G:$G,Actuals!$B:$B,$C$3,Actuals!$C:$C,2,Actuals!$D:$D,$B$10,Actuals!$A:$A,LEFT($D$10,FIND("|",$D$10&"|")-1),Actuals!$E:$E,MID($D$10,FIND("|",$D$10&"|")+1,50),Actuals!$F:$F,"JPY")*$E$5+SUMIFS(Actuals!$G:$G,Actuals!$B:$B,$C$3,Actuals!$C:$C,2,Actuals!$D:$D,$B$10,Actuals!$A:$A,LEFT($D$10,FIND("|",$D$10&"|")-1),Actuals!$E:$E,MID($D$10,FIND("|",$D$10&"|")+1,50),Actuals!$F:$F,"USD")*$F$5+SUMIFS(Actuals!$G:$G,Actuals!$B:$B,$C$3,Actuals!$C:$C,2,Actuals!$D:$D,$B$10,Actuals!$A:$A,LEFT($D$10,FIND("|",$D$10&"|")-1),Actuals!$E:$E,MID($D$10,FIND("|",$D$10&"|")+1,50),Actuals!$F:$F,"EUR")*$G$5+SUMIFS(Actuals!$G:$G,Actuals!$B:$B,$C$3,Actuals!$C:$C,2,Actuals!$D:$D,$B$10,Actuals!$A:$A,LEFT($D$10,FIND("|",$D$10&"|")-1),Actuals!$E:$E,MID($D$10,FIND("|",$D$10&"|")+1,50),Actuals!$F:$F,"GBP")*$H$5) | J11: =IF(OR($B$10="",3>$C$4),"",SUMIFS(Actuals!$G:$G,Actuals!$B:$B,$C$3,Actuals!$C:$C,3,Actuals!$D:$D,$B$10,Actuals!$A:$A,LEFT($D$10,FIND("|",$D$10&"|")-1),Actuals!$E:$E,MID($D$10,FIND("|",$D$10&"|")+1,50),Actuals!$F:$F,"JPY")*$E$5+SUMIFS(Actuals!$G:$G,Actuals!$B:$B,$C$3,Actuals!$C:$C,3,Actuals!$D:$D,$B$10,Actuals!$A:$A,LEFT($D$10,FIND("|",$D$10&"|")-1),Actuals!$E:$E,MID($D$10,FIND("|",$D$10&"|")+1,50),Actuals!$F:$F,"USD")*$F$5+SUMIFS(Actuals!$G:$G,Actuals!$B:$B,$C$3,Actuals!$C:$C,3,Actuals!$D:$D,$B$10,Actuals!$A:$A,LEFT($D$10,FIND("|",$D$10&"|")-1),Actuals!$E:$E,MID($D$10,FIND("|",$D$10&"|")+1,50),Actuals!$F:$F,"EUR")*$G$5+SUMIFS(Actuals!$G:$G,Actuals!$B:$B,$C$3,Actuals!$C:$C,3,Actuals!$D:$D,$B$10,Actuals!$A:$A,LEFT($D$10,FIND("|",$D$10&"|")-1),Actuals!$E:$E,MID($D$10,FIND("|",$D$10&"|")+1,50),Actuals!$F:$F,"GBP")*$H$5) | K11: =IF(OR($B$10="",4>$C$4),"",SUMIFS(Actuals!$G:$G,Actuals!$B:$B,$C$3,Actuals!$C:$C,4,Actuals!$D:$D,$B$10,Actuals!$A:$A,LEFT($D$10,FIND("|",$D$10&"|")-1),Actuals!$E:$E,MID($D$10,FIND("|",$D$10&"|")+1,50),Actuals!$F:$F,"JPY")*$E$5+SUMIFS(Actuals!$G:$G,Actuals!$B:$B,$C$3,Actuals!$C:$C,4,Actuals!$D:$D,$B$10,Actuals!$A:$A,LEFT($D$10,FIND("|",$D$10&"|")-1),Actuals!$E:$E,MID($D$10,FIND("|",$D$10&"|")+1,50),Actuals!$F:$F,"USD")*$F$5+SUMIFS(Actuals!$G:$G,Actuals!$B:$B,$C$3,Actuals!$C:$C,4,Actuals!$D:$D,$B$10,Actuals!$A:$A,LEFT($D$10,FIND("|",$D$10&"|")-1),Actuals!$E:$E,MID($D$10,FIND("|",$D$10&"|")+1,50),Actuals!$F:$F,"EUR")*$G$5+SUMIFS(Actuals!$G:$G,Actuals!$B:$B,$C$3,Actuals!$C:$C,4,Actuals!$D:$D,$B$10,Actuals!$A:$A,LEFT($D$10,FIND("|",$D$10&"|")-1),Actuals!$E:$E,MID($D$10,FIND("|",$D$10&"|")+1,50),Actuals!$F:$F,"GBP")*$H$5) | L11: =IF(OR($B$10="",5>$C$4),"",SUMIFS(Actuals!$G:$G,Actuals!$B:$B,$C$3,Actuals!$C:$C,5,Actuals!$D:$D,$B$10,Actuals!$A:$A,LEFT($D$10,FIND("|",$D$10&"|")-1),Actuals!$E:$E,MID($D$10,FIND("|",$D$10&"|")+1,50),Actuals!$F:$F,"JPY")*$E$5+SUMIFS(Actuals!$G:$G,Actuals!$B:$B,$C$3,Actuals!$C:$C,5,Actuals!$D:$D,$B$10,Actuals!$A:$A,LEFT($D$10,FIND("|",$D$10&"|")-1),Actuals!$E:$E,MID($D$10,FIND("|",$D$10&"|")+1,50),Actuals!$F:$F,"USD")*$F$5+SUMIFS(Actuals!$G:$G,Actuals!$B:$B,$C$3,Actuals!$C:$C,5,Actuals!$D:$D,$B$10,Actuals!$A:$A,LEFT($D$10,FIND("|",$D$10&"|")-1),Actuals!$E:$E,MID($D$10,FIND("|",$D$10&"|")+1,50),Actuals!$F:$F,"EUR")*$G$5+SUMIFS(Actuals!$G:$G,Actuals!$B:$B,$C$3,Actuals!$C:$C,5,Actuals!$D:$D,$B$10,Actuals!$A:$A,LEFT($D$10,FIND("|",$D$10&"|")-1),Actuals!$E:$E,MID($D$10,FIND("|",$D$10&"|")+1,50),Actuals!$F:$F,"GBP")*$H$5) | M11: =IF(OR($B$10="",6>$C$4),"",SUMIFS(Actuals!$G:$G,Actuals!$B:$B,$C$3,Actuals!$C:$C,6,Actuals!$D:$D,$B$10,Actuals!$A:$A,LEFT($D$10,FIND("|",$D$10&"|")-1),Actuals!$E:$E,MID($D$10,FIND("|",$D$10&"|")+1,50),Actuals!$F:$F,"JPY")*$E$5+SUMIFS(Actuals!$G:$G,Actuals!$B:$B,$C$3,Actuals!$C:$C,6,Actuals!$D:$D,$B$10,Actuals!$A:$A,LEFT($D$10,FIND("|",$D$10&"|")-1),Actuals!$E:$E,MID($D$10,FIND("|",$D$10&"|")+1,50),Actuals!$F:$F,"USD")*$F$5+SUMIFS(Actuals!$G:$G,Actuals!$B:$B,$C$3,Actuals!$C:$C,6,Actuals!$D:$D,$B$10,Actuals!$A:$A,LEFT($D$10,FIND("|",$D$10&"|")-1),Actuals!$E:$E,MID($D$10,FIND("|",$D$10&"|")+1,50),Actuals!$F:$F,"EUR")*$G$5+SUMIFS(Actuals!$G:$G,Actuals!$B:$B,$C$3,Actuals!$C:$C,6,Actuals!$D:$D,$B$10,Actuals!$A:$A,LEFT($D$10,FIND("|",$D$10&"|")-1),Actuals!$E:$E,MID($D$10,FIND("|",$D$10&"|")+1,50),Actuals!$F:$F,"GBP")*$H$5) | N11: =IF(OR($B$10="",7>$C$4),"",SUMIFS(Actuals!$G:$G,Actuals!$B:$B,$C$3,Actuals!$C:$C,7,Actuals!$D:$D,$B$10,Actuals!$A:$A,LEFT($D$10,FIND("|",$D$10&"|")-1),Actuals!$E:$E,MID($D$10,FIND("|",$D$10&"|")+1,50),Actuals!$F:$F,"JPY")*$E$5+SUMIFS(Actuals!$G:$G,Actuals!$B:$B,$C$3,Actuals!$C:$C,7,Actuals!$D:$D,$B$10,Actuals!$A:$A,LEFT($D$10,FIND("|",$D$10&"|")-1),Actuals!$E:$E,MID($D$10,FIND("|",$D$10&"|")+1,50),Actuals!$F:$F,"USD")*$F$5+SUMIFS(Actuals!$G:$G,Actuals!$B:$B,$C$3,Actuals!$C:$C,7,Actuals!$D:$D,$B$10,Actuals!$A:$A,LEFT($D$10,FIND("|",$D$10&"|")-1),Actuals!$E:$E,MID($D$10,FIND("|",$D$10&"|")+1,50),Actuals!$F:$F,"EUR")*$G$5+SUMIFS(Actuals!$G:$G,Actuals!$B:$B,$C$3,Actuals!$C:$C,7,Actuals!$D:$D,$B$10,Actuals!$A:$A,LEFT($D$10,FIND("|",$D$10&"|")-1),Actuals!$E:$E,MID($D$10,FIND("|",$D$10&"|")+1,50),Actuals!$F:$F,"GBP")*$H$5) | O11: =IF(OR($B$10="",8>$C$4),"",SUMIFS(Actuals!$G:$G,Actuals!$B:$B,$C$3,Actuals!$C:$C,8,Actuals!$D:$D,$B$10,Actuals!$A:$A,LEFT($D$10,FIND("|",$D$10&"|")-1),Actuals!$E:$E,MID($D$10,FIND("|",$D$10&"|")+1,50),Actuals!$F:$F,"JPY")*$E$5+SUMIFS(Actuals!$G:$G,Actuals!$B:$B,$C$3,Actuals!$C:$C,8,Actuals!$D:$D,$B$10,Actuals!$A:$A,LEFT($D$10,FIND("|",$D$10&"|")-1),Actuals!$E:$E,MID($D$10,FIND("|",$D$10&"|")+1,50),Actuals!$F:$F,"USD")*$F$5+SUMIFS(Actuals!$G:$G,Actuals!$B:$B,$C$3,Actuals!$C:$C,8,Actuals!$D:$D,$B$10,Actuals!$A:$A,LEFT($D$10,FIND("|",$D$10&"|")-1),Actuals!$E:$E,MID($D$10,FIND("|",$D$10&"|")+1,50),Actuals!$F:$F,"EUR")*$G$5+SUMIFS(Actuals!$G:$G,Actuals!$B:$B,$C$3,Actuals!$C:$C,8,Actuals!$D:$D,$B$10,Actuals!$A:$A,LEFT($D$10,FIND("|",$D$10&"|")-1),Actuals!$E:$E,MID($D$10,FIND("|",$D$10&"|")+1,50),Actuals!$F:$F,"GBP")*$H$5) | P11: =IF(OR($B$10="",9>$C$4),"",SUMIFS(Actuals!$G:$G,Actuals!$B:$B,$C$3,Actuals!$C:$C,9,Actuals!$D:$D,$B$10,Actuals!$A:$A,LEFT($D$10,FIND("|",$D$10&"|")-1),Actuals!$E:$E,MID($D$10,FIND("|",$D$10&"|")+1,50),Actuals!$F:$F,"JPY")*$E$5+SUMIFS(Actuals!$G:$G,Actuals!$B:$B,$C$3,Actuals!$C:$C,9,Actuals!$D:$D,$B$10,Actuals!$A:$A,LEFT($D$10,FIND("|",$D$10&"|")-1),Actuals!$E:$E,MID($D$10,FIND("|",$D$10&"|")+1,50),Actuals!$F:$F,"USD")*$F$5+SUMIFS(Actuals!$G:$G,Actuals!$B:$B,$C$3,Actuals!$C:$C,9,Actuals!$D:$D,$B$10,Actuals!$A:$A,LEFT($D$10,FIND("|",$D$10&"|")-1),Actuals!$E:$E,MID($D$10,FIND("|",$D$10&"|")+1,50),Actuals!$F:$F,"EUR")*$G$5+SUMIFS(Actuals!$G:$G,Actuals!$B:$B,$C$3,Actuals!$C:$C,9,Actuals!$D:$D,$B$10,Actuals!$A:$A,LEFT($D$10,FIND("|",$D$10&"|")-1),Actuals!$E:$E,MID($D$10,FIND("|",$D$10&"|")+1,50),Actuals!$F:$F,"GBP")*$H$5) | Q11: =IF(OR($B$10="",10>$C$4),"",SUMIFS(Actuals!$G:$G,Actuals!$B:$B,$C$3,Actuals!$C:$C,10,Actuals!$D:$D,$B$10,Actuals!$A:$A,LEFT($D$10,FIND("|",$D$10&"|")-1),Actuals!$E:$E,MID($D$10,FIND("|",$D$10&"|")+1,50),Actuals!$F:$F,"JPY")*$E$5+SUMIFS(Actuals!$G:$G,Actuals!$B:$B,$C$3,Actuals!$C:$C,10,Actuals!$D:$D,$B$10,Actuals!$A:$A,LEFT($D$10,FIND("|",$D$10&"|")-1),Actuals!$E:$E,MID($D$10,FIND("|",$D$10&"|")+1,50),Actuals!$F:$F,"USD")*$F$5+SUMIFS(Actuals!$G:$G,Actuals!$B:$B,$C$3,Actuals!$C:$C,10,Actuals!$D:$D,$B$10,Actuals!$A:$A,LEFT($D$10,FIND("|",$D$10&"|")-1),Actuals!$E:$E,MID($D$10,FIND("|",$D$10&"|")+1,50),Actuals!$F:$F,"EUR")*$G$5+SUMIFS(Actuals!$G:$G,Actuals!$B:$B,$C$3,Actuals!$C:$C,10,Actuals!$D:$D,$B$10,Actuals!$A:$A,LEFT($D$10,FIND("|",$D$10&"|")-1),Actuals!$E:$E,MID($D$10,FIND("|",$D$10&"|")+1,50),Actuals!$F:$F,"GBP")*$H$5) | R11: =IF(OR($B$10="",11>$C$4),"",SUMIFS(Actuals!$G:$G,Actuals!$B:$B,$C$3,Actuals!$C:$C,11,Actuals!$D:$D,$B$10,Actuals!$A:$A,LEFT($D$10,FIND("|",$D$10&"|")-1),Actuals!$E:$E,MID($D$10,FIND("|",$D$10&"|")+1,50),Actuals!$F:$F,"JPY")*$E$5+SUMIFS(Actuals!$G:$G,Actuals!$B:$B,$C$3,Actuals!$C:$C,11,Actuals!$D:$D,$B$10,Actuals!$A:$A,LEFT($D$10,FIND("|",$D$10&"|")-1),Actuals!$E:$E,MID($D$10,FIND("|",$D$10&"|")+1,50),Actuals!$F:$F,"USD")*$F$5+SUMIFS(Actuals!$G:$G,Actuals!$B:$B,$C$3,Actuals!$C:$C,11,Actuals!$D:$D,$B$10,Actuals!$A:$A,LEFT($D$10,FIND("|",$D$10&"|")-1),Actuals!$E:$E,MID($D$10,FIND("|",$D$10&"|")+1,50),Actuals!$F:$F,"EUR")*$G$5+SUMIFS(Actuals!$G:$G,Actuals!$B:$B,$C$3,Actuals!$C:$C,11,Actuals!$D:$D,$B$10,Actuals!$A:$A,LEFT($D$10,FIND("|",$D$10&"|")-1),Actuals!$E:$E,MID($D$10,FIND("|",$D$10&"|")+1,50),Actuals!$F:$F,"GBP")*$H$5) | S11: =IF(OR($B$10="",12>$C$4),"",SUMIFS(Actuals!$G:$G,Actuals!$B:$B,$C$3,Actuals!$C:$C,12,Actuals!$D:$D,$B$10,Actuals!$A:$A,LEFT($D$10,FIND("|",$D$10&"|")-1),Actuals!$E:$E,MID($D$10,FIND("|",$D$10&"|")+1,50),Actuals!$F:$F,"JPY")*$E$5+SUMIFS(Actuals!$G:$G,Actuals!$B:$B,$C$3,Actuals!$C:$C,12,Actuals!$D:$D,$B$10,Actuals!$A:$A,LEFT($D$10,FIND("|",$D$10&"|")-1),Actuals!$E:$E,MID($D$10,FIND("|",$D$10&"|")+1,50),Actuals!$F:$F,"USD")*$F$5+SUMIFS(Actuals!$G:$G,Actuals!$B:$B,$C$3,Actuals!$C:$C,12,Actuals!$D:$D,$B$10,Actuals!$A:$A,LEFT($D$10,FIND("|",$D$10&"|")-1),Actuals!$E:$E,MID($D$10,FIND("|",$D$10&"|")+1,50),Actuals!$F:$F,"EUR")*$G$5+SUMIFS(Actuals!$G:$G,Actuals!$B:$B,$C$3,Actuals!$C:$C,12,Actuals!$D:$D,$B$10,Actuals!$A:$A,LEFT($D$10,FIND("|",$D$10&"|")-1),Actuals!$E:$E,MID($D$10,FIND("|",$D$10&"|")+1,50),Actuals!$F:$F,"GBP")*$H$5) | T11: =IF($B$10="","",SUMIF($H$7:$S$7,"<="&$C$4,$H11:$S11)) | X11: =IF($B11="","",IFERROR(INDEX(Cost_Centers!$E:$E,MATCH($B11,Cost_Centers!$A:$A,0)),"(unknown)")) | Y11: =IF($B11="","",IFERROR(INDEX(Cost_Centers!$D:$D,MATCH($B11,Cost_Centers!$A:$A,0)),"(unknown)")) | Z11: =IF(OR($B11="",$G11<>"Variance vs Budget"),"",ABS(N($V11))+ROW()/1000000000)
A12: =IF(A$10="","",A$10) | B12: =IF(B$10="","",B$10) | C12: =IF(C$10="","",C$10) | D12: =IF(D$10="","",D$10) | E12: =IF(E$10="","",E$10) | F12: =IF(F$10="","",F$10) | G12: Variance vs Budget | H12: =IF(OR($B$10="",1>$C$4),"",N(H11)-H10) | I12: =IF(OR($B$10="",2>$C$4),"",N(I11)-I10) | J12: =IF(OR($B$10="",3>$C$4),"",N(J11)-J10) | K12: =IF(OR($B$10="",4>$C$4),"",N(K11)-K10) | L12: =IF(OR($B$10="",5>$C$4),"",N(L11)-L10) | M12: =IF(OR($B$10="",6>$C$4),"",N(M11)-M10) | N12: =IF(OR($B$10="",7>$C$4),"",N(N11)-N10) | O12: =IF(OR($B$10="",8>$C$4),"",N(O11)-O10) | P12: =IF(OR($B$10="",9>$C$4),"",N(P11)-P10) | Q12: =IF(OR($B$10="",10>$C$4),"",N(Q11)-Q10) | R12: =IF(OR($B$10="",11>$C$4),"",N(R11)-R10) | S12: =IF(OR($B$10="",12>$C$4),"",N(S11)-S10) | T12: =IF($B$10="","",T11-T10) | U12: =IF($B$10="","",U14-U10) | V12: =IF($B$10="","",V14-V10) | X12: =IF($B12="","",IFERROR(INDEX(Cost_Centers!$E:$E,MATCH($B12,Cost_Centers!$A:$A,0)),"(unknown)")) | Y12: =IF($B12="","",IFERROR(INDEX(Cost_Centers!$D:$D,MATCH($B12,Cost_Centers!$A:$A,0)),"(unknown)")) | Z12: =IF(OR($B12="",$G12<>"Variance vs Budget"),"",ABS(N($V12))+ROW()/1000000000)
A13: =IF(A$10="","",A$10) | B13: =IF(B$10="","",B$10) | C13: =IF(C$10="","",C$10) | D13: =IF(D$10="","",D$10) | E13: =IF(E$10="","",E$10) | F13: =IF(F$10="","",F$10) | G13: Forecast (input) | X13: =IF($B13="","",IFERROR(INDEX(Cost_Centers!$E:$E,MATCH($B13,Cost_Centers!$A:$A,0)),"(unknown)")) | Y13: =IF($B13="","",IFERROR(INDEX(Cost_Centers!$D:$D,MATCH($B13,Cost_Centers!$A:$A,0)),"(unknown)")) | Z13: =IF(OR($B13="",$G13<>"Variance vs Budget"),"",ABS(N($V13))+ROW()/1000000000)
A14: =IF(A$10="","",A$10) | B14: =IF(B$10="","",B$10) | C14: =IF(C$10="","",C$10) | D14: =IF(D$10="","",D$10) | E14: =IF(E$10="","",E$10) | F14: =IF(F$10="","",F$10) | G14: Actual + Forecast | H14: =IF($B$10="","",IF(1<=$C$4,N(H11),IF(H13="",H10,H13))) | I14: =IF($B$10="","",IF(2<=$C$4,N(I11),IF(I13="",I10,I13))) | J14: =IF($B$10="","",IF(3<=$C$4,N(J11),IF(J13="",J10,J13))) | K14: =IF($B$10="","",IF(4<=$C$4,N(K11),IF(K13="",K10,K13))) | L14: =IF($B$10="","",IF(5<=$C$4,N(L11),IF(L13="",L10,L13))) | M14: =IF($B$10="","",IF(6<=$C$4,N(M11),IF(M13="",M10,M13))) | N14: =IF($B$10="","",IF(7<=$C$4,N(N11),IF(N13="",N10,N13))) | O14: =IF($B$10="","",IF(8<=$C$4,N(O11),IF(O13="",O10,O13))) | P14: =IF($B$10="","",IF(9<=$C$4,N(P11),IF(P13="",P10,P13))) | Q14: =IF($B$10="","",IF(10<=$C$4,N(Q11),IF(Q13="",Q10,Q13))) | R14: =IF($B$10="","",IF(11<=$C$4,N(R11),IF(R13="",R10,R13))) | S14: =IF($B$10="","",IF(12<=$C$4,N(S11),IF(S13="",S10,S13))) | T14: =IF($B$10="","",SUMIF($H$7:$S$7,"<="&$C$4,$H14:$S14)) | U14: =IF($B$10="","",SUMIF($H$7:$S$7,">"&$C$4,$H14:$S14)) | V14: =IF($B$10="","",SUM($H14:$S14)) | X14: =IF($B14="","",IFERROR(INDEX(Cost_Centers!$E:$E,MATCH($B14,Cost_Centers!$A:$A,0)),"(unknown)")) | Y14: =IF($B14="","",IFERROR(INDEX(Cost_Centers!$D:$D,MATCH($B14,Cost_Centers!$A:$A,0)),"(unknown)")) | Z14: =IF(OR($B14="",$G14<>"Variance vs Budget"),"",ABS(N($V14))+ROW()/1000000000)
A15: =IF(A$10="","",A$10) | B15: =IF(B$10="","",B$10) | C15: =IF(C$10="","",C$10) | D15: =IF(D$10="","",D$10) | E15: =IF(E$10="","",E$10) | F15: =IF(F$10="","",F$10) | G15: Prior Month Forecast | H15: =IF($B$10="","",IF(COUNTIFS(Prior_Forecast!$A:$A,$B$10,Prior_Forecast!$B:$B,$D$10)>0,SUMIFS(Prior_Forecast!$C:$C,Prior_Forecast!$A:$A,$B$10,Prior_Forecast!$B:$B,$D$10),"")) | I15: =IF($B$10="","",IF(COUNTIFS(Prior_Forecast!$A:$A,$B$10,Prior_Forecast!$B:$B,$D$10)>0,SUMIFS(Prior_Forecast!$D:$D,Prior_Forecast!$A:$A,$B$10,Prior_Forecast!$B:$B,$D$10),"")) | J15: =IF($B$10="","",IF(COUNTIFS(Prior_Forecast!$A:$A,$B$10,Prior_Forecast!$B:$B,$D$10)>0,SUMIFS(Prior_Forecast!$E:$E,Prior_Forecast!$A:$A,$B$10,Prior_Forecast!$B:$B,$D$10),"")) | K15: =IF($B$10="","",IF(COUNTIFS(Prior_Forecast!$A:$A,$B$10,Prior_Forecast!$B:$B,$D$10)>0,SUMIFS(Prior_Forecast!$F:$F,Prior_Forecast!$A:$A,$B$10,Prior_Forecast!$B:$B,$D$10),"")) | L15: =IF($B$10="","",IF(COUNTIFS(Prior_Forecast!$A:$A,$B$10,Prior_Forecast!$B:$B,$D$10)>0,SUMIFS(Prior_Forecast!$G:$G,Prior_Forecast!$A:$A,$B$10,Prior_Forecast!$B:$B,$D$10),"")) | M15: =IF($B$10="","",IF(COUNTIFS(Prior_Forecast!$A:$A,$B$10,Prior_Forecast!$B:$B,$D$10)>0,SUMIFS(Prior_Forecast!$H:$H,Prior_Forecast!$A:$A,$B$10,Prior_Forecast!$B:$B,$D$10),"")) | N15: =IF($B$10="","",IF(COUNTIFS(Prior_Forecast!$A:$A,$B$10,Prior_Forecast!$B:$B,$D$10)>0,SUMIFS(Prior_Forecast!$I:$I,Prior_Forecast!$A:$A,$B$10,Prior_Forecast!$B:$B,$D$10),"")) | O15: =IF($B$10="","",IF(COUNTIFS(Prior_Forecast!$A:$A,$B$10,Prior_Forecast!$B:$B,$D$10)>0,SUMIFS(Prior_Forecast!$J:$J,Prior_Forecast!$A:$A,$B$10,Prior_Forecast!$B:$B,$D$10),"")) | P15: =IF($B$10="","",IF(COUNTIFS(Prior_Forecast!$A:$A,$B$10,Prior_Forecast!$B:$B,$D$10)>0,SUMIFS(Prior_Forecast!$K:$K,Prior_Forecast!$A:$A,$B$10,Prior_Forecast!$B:$B,$D$10),"")) | Q15: =IF($B$10="","",IF(COUNTIFS(Prior_Forecast!$A:$A,$B$10,Prior_Forecast!$B:$B,$D$10)>0,SUMIFS(Prior_Forecast!$L:$L,Prior_Forecast!$A:$A,$B$10,Prior_Forecast!$B:$B,$D$10),"")) | R15: =IF($B$10="","",IF(COUNTIFS(Prior_Forecast!$A:$A,$B$10,Prior_Forecast!$B:$B,$D$10)>0,SUMIFS(Prior_Forecast!$M:$M,Prior_Forecast!$A:$A,$B$10,Prior_Forecast!$B:$B,$D$10),"")) | S15: =IF($B$10="","",IF(COUNTIFS(Prior_Forecast!$A:$A,$B$10,Prior_Forecast!$B:$B,$D$10)>0,SUMIFS(Prior_Forecast!$N:$N,Prior_Forecast!$A:$A,$B$10,Prior_Forecast!$B:$B,$D$10),"")) | T15: =IF($B$10="","",IF(COUNTIFS(Prior_Forecast!$A:$A,$B$10,Prior_Forecast!$B:$B,$D$10)>0,SUMIFS(Prior_Forecast!$O:$O,Prior_Forecast!$A:$A,$B$10,Prior_Forecast!$B:$B,$D$10),"")) | U15: =IF($B$10="","",IF(COUNTIFS(Prior_Forecast!$A:$A,$B$10,Prior_Forecast!$B:$B,$D$10)>0,SUMIFS(Prior_Forecast!$P:$P,Prior_Forecast!$A:$A,$B$10,Prior_Forecast!$B:$B,$D$10),"")) | V15: =IF($B$10="","",IF(COUNTIFS(Prior_Forecast!$A:$A,$B$10,Prior_Forecast!$B:$B,$D$10)>0,SUMIFS(Prior_Forecast!$Q:$Q,Prior_Forecast!$A:$A,$B$10,Prior_Forecast!$B:$B,$D$10),"")) | X15: =IF($B15="","",IFERROR(INDEX(Cost_Centers!$E:$E,MATCH($B15,Cost_Centers!$A:$A,0)),"(unknown)")) | Y15: =IF($B15="","",IFERROR(INDEX(Cost_Centers!$D:$D,MATCH($B15,Cost_Centers!$A:$A,0)),"(unknown)")) | Z15: =IF(OR($B15="",$G15<>"Variance vs Budget"),"",ABS(N($V15))+ROW()/1000000000)
A16: =IF(A$10="","",A$10) | B16: =IF(B$10="","",B$10) | C16: =IF(C$10="","",C$10) | D16: =IF(D$10="","",D$10) | E16: =IF(E$10="","",E$10) | F16: =IF(F$10="","",F$10) | G16: Variance vs Prior Month | H16: =IF(OR($B$10="",H15=""),"",H14-H15) | I16: =IF(OR($B$10="",I15=""),"",I14-I15) | J16: =IF(OR($B$10="",J15=""),"",J14-J15) | K16: =IF(OR($B$10="",K15=""),"",K14-K15) | L16: =IF(OR($B$10="",L15=""),"",L14-L15) | M16: =IF(OR($B$10="",M15=""),"",M14-M15) | N16: =IF(OR($B$10="",N15=""),"",N14-N15) | O16: =IF(OR($B$10="",O15=""),"",O14-O15) | ... V16: =IF(OR($B$10="",V15=""),"",V14-V15) | X16: =IF($B16="","",IFERROR(INDEX(Cost_Centers!$E:$E,MATCH($B16,Cost_Centers!$A:$A,0)),"(unknown)")) | Y16: =IF($B16="","",IFERROR(INDEX(Cost_Centers!$D:$D,MATCH($B16,Cost_Centers!$A:$A,0)),"(unknown)")) | Z16: =IF(OR($B16="",$G16<>"Variance vs Budget"),"",ABS(N($V16))+ROW()/1000000000)
A17: =IF(A$10="","",A$10) | B17: =IF(B$10="","",B$10) | C17: =IF(C$10="","",C$10) | D17: =IF(D$10="","",D$10) | E17: =IF(E$10="","",E$10) | F17: =IF(F$10="","",F$10) | G17: Rationale | X17: =IF($B17="","",IFERROR(INDEX(Cost_Centers!$E:$E,MATCH($B17,Cost_Centers!$A:$A,0)),"(unknown)")) | Y17: =IF($B17="","",IFERROR(INDEX(Cost_Centers!$D:$D,MATCH($B17,Cost_Centers!$A:$A,0)),"(unknown)")) | Z17: =IF(OR($B17="",$G17<>"Variance vs Budget"),"",ABS(N($V17))+ROW()/1000000000)
A18: =IF($D$18="","",LEFT($D$18,FIND("|",$D$18&"|")-1)) | C18: =IF($B$18="","",IFERROR(INDEX(Cost_Centers!$B:$B,MATCH($B$18,Cost_Centers!$A:$A,0)),"(not in master)")) | E18: =IF($D$18="","",IFERROR(INDEX(Accounts!$D:$D,MATCH($D$18,Accounts!$A:$A,0)),"(not in master)")) | G18: Budget | H18: =IF($B$18="","",SUMIFS(Opex_Budget!$O:$O,Opex_Budget!$A:$A,$C$3,Opex_Budget!$E:$E,$B$18,Opex_Budget!$F:$F,$D$18,Opex_Budget!$N:$N,"JPY")*$E$5+SUMIFS(Opex_Budget!$O:$O,Opex_Budget!$A:$A,$C$3,Opex_Budget!$E:$E,$B$18,Opex_Budget!$F:$F,$D$18,Opex_Budget!$N:$N,"USD")*$F$5+SUMIFS(Opex_Budget!$O:$O,Opex_Budget!$A:$A,$C$3,Opex_Budget!$E:$E,$B$18,Opex_Budget!$F:$F,$D$18,Opex_Budget!$N:$N,"EUR")*$G$5+SUMIFS(Opex_Budget!$O:$O,Opex_Budget!$A:$A,$C$3,Opex_Budget!$E:$E,$B$18,Opex_Budget!$F:$F,$D$18,Opex_Budget!$N:$N,"GBP")*$H$5) | I18: =IF($B$18="","",SUMIFS(Opex_Budget!$P:$P,Opex_Budget!$A:$A,$C$3,Opex_Budget!$E:$E,$B$18,Opex_Budget!$F:$F,$D$18,Opex_Budget!$N:$N,"JPY")*$E$5+SUMIFS(Opex_Budget!$P:$P,Opex_Budget!$A:$A,$C$3,Opex_Budget!$E:$E,$B$18,Opex_Budget!$F:$F,$D$18,Opex_Budget!$N:$N,"USD")*$F$5+SUMIFS(Opex_Budget!$P:$P,Opex_Budget!$A:$A,$C$3,Opex_Budget!$E:$E,$B$18,Opex_Budget!$F:$F,$D$18,Opex_Budget!$N:$N,"EUR")*$G$5+SUMIFS(Opex_Budget!$P:$P,Opex_Budget!$A:$A,$C$3,Opex_Budget!$E:$E,$B$18,Opex_Budget!$F:$F,$D$18,Opex_Budget!$N:$N,"GBP")*$H$5) | J18: =IF($B$18="","",SUMIFS(Opex_Budget!$Q:$Q,Opex_Budget!$A:$A,$C$3,Opex_Budget!$E:$E,$B$18,Opex_Budget!$F:$F,$D$18,Opex_Budget!$N:$N,"JPY")*$E$5+SUMIFS(Opex_Budget!$Q:$Q,Opex_Budget!$A:$A,$C$3,Opex_Budget!$E:$E,$B$18,Opex_Budget!$F:$F,$D$18,Opex_Budget!$N:$N,"USD")*$F$5+SUMIFS(Opex_Budget!$Q:$Q,Opex_Budget!$A:$A,$C$3,Opex_Budget!$E:$E,$B$18,Opex_Budget!$F:$F,$D$18,Opex_Budget!$N:$N,"EUR")*$G$5+SUMIFS(Opex_Budget!$Q:$Q,Opex_Budget!$A:$A,$C$3,Opex_Budget!$E:$E,$B$18,Opex_Budget!$F:$F,$D$18,Opex_Budget!$N:$N,"GBP")*$H$5) | K18: =IF($B$18="","",SUMIFS(Opex_Budget!$R:$R,Opex_Budget!$A:$A,$C$3,Opex_Budget!$E:$E,$B$18,Opex_Budget!$F:$F,$D$18,Opex_Budget!$N:$N,"JPY")*$E$5+SUMIFS(Opex_Budget!$R:$R,Opex_Budget!$A:$A,$C$3,Opex_Budget!$E:$E,$B$18,Opex_Budget!$F:$F,$D$18,Opex_Budget!$N:$N,"USD")*$F$5+SUMIFS(Opex_Budget!$R:$R,Opex_Budget!$A:$A,$C$3,Opex_Budget!$E:$E,$B$18,Opex_Budget!$F:$F,$D$18,Opex_Budget!$N:$N,"EUR")*$G$5+SUMIFS(Opex_Budget!$R:$R,Opex_Budget!$A:$A,$C$3,Opex_Budget!$E:$E,$B$18,Opex_Budget!$F:$F,$D$18,Opex_Budget!$N:$N,"GBP")*$H$5) | L18: =IF($B$18="","",SUMIFS(Opex_Budget!$S:$S,Opex_Budget!$A:$A,$C$3,Opex_Budget!$E:$E,$B$18,Opex_Budget!$F:$F,$D$18,Opex_Budget!$N:$N,"JPY")*$E$5+SUMIFS(Opex_Budget!$S:$S,Opex_Budget!$A:$A,$C$3,Opex_Budget!$E:$E,$B$18,Opex_Budget!$F:$F,$D$18,Opex_Budget!$N:$N,"USD")*$F$5+SUMIFS(Opex_Budget!$S:$S,Opex_Budget!$A:$A,$C$3,Opex_Budget!$E:$E,$B$18,Opex_Budget!$F:$F,$D$18,Opex_Budget!$N:$N,"EUR")*$G$5+SUMIFS(Opex_Budget!$S:$S,Opex_Budget!$A:$A,$C$3,Opex_Budget!$E:$E,$B$18,Opex_Budget!$F:$F,$D$18,Opex_Budget!$N:$N,"GBP")*$H$5) | M18: =IF($B$18="","",SUMIFS(Opex_Budget!$T:$T,Opex_Budget!$A:$A,$C$3,Opex_Budget!$E:$E,$B$18,Opex_Budget!$F:$F,$D$18,Opex_Budget!$N:$N,"JPY")*$E$5+SUMIFS(Opex_Budget!$T:$T,Opex_Budget!$A:$A,$C$3,Opex_Budget!$E:$E,$B$18,Opex_Budget!$F:$F,$D$18,Opex_Budget!$N:$N,"USD")*$F$5+SUMIFS(Opex_Budget!$T:$T,Opex_Budget!$A:$A,$C$3,Opex_Budget!$E:$E,$B$18,Opex_Budget!$F:$F,$D$18,Opex_Budget!$N:$N,"EUR")*$G$5+SUMIFS(Opex_Budget!$T:$T,Opex_Budget!$A:$A,$C$3,Opex_Budget!$E:$E,$B$18,Opex_Budget!$F:$F,$D$18,Opex_Budget!$N:$N,"GBP")*$H$5) | N18: =IF($B$18="","",SUMIFS(Opex_Budget!$U:$U,Opex_Budget!$A:$A,$C$3,Opex_Budget!$E:$E,$B$18,Opex_Budget!$F:$F,$D$18,Opex_Budget!$N:$N,"JPY")*$E$5+SUMIFS(Opex_Budget!$U:$U,Opex_Budget!$A:$A,$C$3,Opex_Budget!$E:$E,$B$18,Opex_Budget!$F:$F,$D$18,Opex_Budget!$N:$N,"USD")*$F$5+SUMIFS(Opex_Budget!$U:$U,Opex_Budget!$A:$A,$C$3,Opex_Budget!$E:$E,$B$18,Opex_Budget!$F:$F,$D$18,Opex_Budget!$N:$N,"EUR")*$G$5+SUMIFS(Opex_Budget!$U:$U,Opex_Budget!$A:$A,$C$3,Opex_Budget!$E:$E,$B$18,Opex_Budget!$F:$F,$D$18,Opex_Budget!$N:$N,"GBP")*$H$5) | O18: =IF($B$18="","",SUMIFS(Opex_Budget!$V:$V,Opex_Budget!$A:$A,$C$3,Opex_Budget!$E:$E,$B$18,Opex_Budget!$F:$F,$D$18,Opex_Budget!$N:$N,"JPY")*$E$5+SUMIFS(Opex_Budget!$V:$V,Opex_Budget!$A:$A,$C$3,Opex_Budget!$E:$E,$B$18,Opex_Budget!$F:$F,$D$18,Opex_Budget!$N:$N,"USD")*$F$5+SUMIFS(Opex_Budget!$V:$V,Opex_Budget!$A:$A,$C$3,Opex_Budget!$E:$E,$B$18,Opex_Budget!$F:$F,$D$18,Opex_Budget!$N:$N,"EUR")*$G$5+SUMIFS(Opex_Budget!$V:$V,Opex_Budget!$A:$A,$C$3,Opex_Budget!$E:$E,$B$18,Opex_Budget!$F:$F,$D$18,Opex_Budget!$N:$N,"GBP")*$H$5) | P18: =IF($B$18="","",SUMIFS(Opex_Budget!$W:$W,Opex_Budget!$A:$A,$C$3,Opex_Budget!$E:$E,$B$18,Opex_Budget!$F:$F,$D$18,Opex_Budget!$N:$N,"JPY")*$E$5+SUMIFS(Opex_Budget!$W:$W,Opex_Budget!$A:$A,$C$3,Opex_Budget!$E:$E,$B$18,Opex_Budget!$F:$F,$D$18,Opex_Budget!$N:$N,"USD")*$F$5+SUMIFS(Opex_Budget!$W:$W,Opex_Budget!$A:$A,$C$3,Opex_Budget!$E:$E,$B$18,Opex_Budget!$F:$F,$D$18,Opex_Budget!$N:$N,"EUR")*$G$5+SUMIFS(Opex_Budget!$W:$W,Opex_Budget!$A:$A,$C$3,Opex_Budget!$E:$E,$B$18,Opex_Budget!$F:$F,$D$18,Opex_Budget!$N:$N,"GBP")*$H$5) | Q18: =IF($B$18="","",SUMIFS(Opex_Budget!$X:$X,Opex_Budget!$A:$A,$C$3,Opex_Budget!$E:$E,$B$18,Opex_Budget!$F:$F,$D$18,Opex_Budget!$N:$N,"JPY")*$E$5+SUMIFS(Opex_Budget!$X:$X,Opex_Budget!$A:$A,$C$3,Opex_Budget!$E:$E,$B$18,Opex_Budget!$F:$F,$D$18,Opex_Budget!$N:$N,"USD")*$F$5+SUMIFS(Opex_Budget!$X:$X,Opex_Budget!$A:$A,$C$3,Opex_Budget!$E:$E,$B$18,Opex_Budget!$F:$F,$D$18,Opex_Budget!$N:$N,"EUR")*$G$5+SUMIFS(Opex_Budget!$X:$X,Opex_Budget!$A:$A,$C$3,Opex_Budget!$E:$E,$B$18,Opex_Budget!$F:$F,$D$18,Opex_Budget!$N:$N,"GBP")*$H$5) | R18: =IF($B$18="","",SUMIFS(Opex_Budget!$Y:$Y,Opex_Budget!$A:$A,$C$3,Opex_Budget!$E:$E,$B$18,Opex_Budget!$F:$F,$D$18,Opex_Budget!$N:$N,"JPY")*$E$5+SUMIFS(Opex_Budget!$Y:$Y,Opex_Budget!$A:$A,$C$3,Opex_Budget!$E:$E,$B$18,Opex_Budget!$F:$F,$D$18,Opex_Budget!$N:$N,"USD")*$F$5+SUMIFS(Opex_Budget!$Y:$Y,Opex_Budget!$A:$A,$C$3,Opex_Budget!$E:$E,$B$18,Opex_Budget!$F:$F,$D$18,Opex_Budget!$N:$N,"EUR")*$G$5+SUMIFS(Opex_Budget!$Y:$Y,Opex_Budget!$A:$A,$C$3,Opex_Budget!$E:$E,$B$18,Opex_Budget!$F:$F,$D$18,Opex_Budget!$N:$N,"GBP")*$H$5) | S18: =IF($B$18="","",SUMIFS(Opex_Budget!$Z:$Z,Opex_Budget!$A:$A,$C$3,Opex_Budget!$E:$E,$B$18,Opex_Budget!$F:$F,$D$18,Opex_Budget!$N:$N,"JPY")*$E$5+SUMIFS(Opex_Budget!$Z:$Z,Opex_Budget!$A:$A,$C$3,Opex_Budget!$E:$E,$B$18,Opex_Budget!$F:$F,$D$18,Opex_Budget!$N:$N,"USD")*$F$5+SUMIFS(Opex_Budget!$Z:$Z,Opex_Budget!$A:$A,$C$3,Opex_Budget!$E:$E,$B$18,Opex_Budget!$F:$F,$D$18,Opex_Budget!$N:$N,"EUR")*$G$5+SUMIFS(Opex_Budget!$Z:$Z,Opex_Budget!$A:$A,$C$3,Opex_Budget!$E:$E,$B$18,Opex_Budget!$F:$F,$D$18,Opex_Budget!$N:$N,"GBP")*$H$5) | T18: =IF($B$18="","",SUMIF($H$7:$S$7,"<="&$C$4,$H18:$S18)) | U18: =IF($B$18="","",SUMIF($H$7:$S$7,">"&$C$4,$H18:$S18)) | V18: =IF($B$18="","",SUM($H18:$S18)) | X18: =IF($B18="","",IFERROR(INDEX(Cost_Centers!$E:$E,MATCH($B18,Cost_Centers!$A:$A,0)),"(unknown)")) | Y18: =IF($B18="","",IFERROR(INDEX(Cost_Centers!$D:$D,MATCH($B18,Cost_Centers!$A:$A,0)),"(unknown)")) | Z18: =IF(OR($B18="",$G18<>"Variance vs Budget"),"",ABS(N($V18))+ROW()/1000000000)
A19: =IF(A$18="","",A$18) | B19: =IF(B$18="","",B$18) | C19: =IF(C$18="","",C$18) | D19: =IF(D$18="","",D$18) | E19: =IF(E$18="","",E$18) | F19: =IF(F$18="","",F$18) | G19: Actual | H19: =IF(OR($B$18="",1>$C$4),"",SUMIFS(Actuals!$G:$G,Actuals!$B:$B,$C$3,Actuals!$C:$C,1,Actuals!$D:$D,$B$18,Actuals!$A:$A,LEFT($D$18,FIND("|",$D$18&"|")-1),Actuals!$E:$E,MID($D$18,FIND("|",$D$18&"|")+1,50),Actuals!$F:$F,"JPY")*$E$5+SUMIFS(Actuals!$G:$G,Actuals!$B:$B,$C$3,Actuals!$C:$C,1,Actuals!$D:$D,$B$18,Actuals!$A:$A,LEFT($D$18,FIND("|",$D$18&"|")-1),Actuals!$E:$E,MID($D$18,FIND("|",$D$18&"|")+1,50),Actuals!$F:$F,"USD")*$F$5+SUMIFS(Actuals!$G:$G,Actuals!$B:$B,$C$3,Actuals!$C:$C,1,Actuals!$D:$D,$B$18,Actuals!$A:$A,LEFT($D$18,FIND("|",$D$18&"|")-1),Actuals!$E:$E,MID($D$18,FIND("|",$D$18&"|")+1,50),Actuals!$F:$F,"EUR")*$G$5+SUMIFS(Actuals!$G:$G,Actuals!$B:$B,$C$3,Actuals!$C:$C,1,Actuals!$D:$D,$B$18,Actuals!$A:$A,LEFT($D$18,FIND("|",$D$18&"|")-1),Actuals!$E:$E,MID($D$18,FIND("|",$D$18&"|")+1,50),Actuals!$F:$F,"GBP")*$H$5) | I19: =IF(OR($B$18="",2>$C$4),"",SUMIFS(Actuals!$G:$G,Actuals!$B:$B,$C$3,Actuals!$C:$C,2,Actuals!$D:$D,$B$18,Actuals!$A:$A,LEFT($D$18,FIND("|",$D$18&"|")-1),Actuals!$E:$E,MID($D$18,FIND("|",$D$18&"|")+1,50),Actuals!$F:$F,"JPY")*$E$5+SUMIFS(Actuals!$G:$G,Actuals!$B:$B,$C$3,Actuals!$C:$C,2,Actuals!$D:$D,$B$18,Actuals!$A:$A,LEFT($D$18,FIND("|",$D$18&"|")-1),Actuals!$E:$E,MID($D$18,FIND("|",$D$18&"|")+1,50),Actuals!$F:$F,"USD")*$F$5+SUMIFS(Actuals!$G:$G,Actuals!$B:$B,$C$3,Actuals!$C:$C,2,Actuals!$D:$D,$B$18,Actuals!$A:$A,LEFT($D$18,FIND("|",$D$18&"|")-1),Actuals!$E:$E,MID($D$18,FIND("|",$D$18&"|")+1,50),Actuals!$F:$F,"EUR")*$G$5+SUMIFS(Actuals!$G:$G,Actuals!$B:$B,$C$3,Actuals!$C:$C,2,Actuals!$D:$D,$B$18,Actuals!$A:$A,LEFT($D$18,FIND("|",$D$18&"|")-1),Actuals!$E:$E,MID($D$18,FIND("|",$D$18&"|")+1,50),Actuals!$F:$F,"GBP")*$H$5) | J19: =IF(OR($B$18="",3>$C$4),"",SUMIFS(Actuals!$G:$G,Actuals!$B:$B,$C$3,Actuals!$C:$C,3,Actuals!$D:$D,$B$18,Actuals!$A:$A,LEFT($D$18,FIND("|",$D$18&"|")-1),Actuals!$E:$E,MID($D$18,FIND("|",$D$18&"|")+1,50),Actuals!$F:$F,"JPY")*$E$5+SUMIFS(Actuals!$G:$G,Actuals!$B:$B,$C$3,Actuals!$C:$C,3,Actuals!$D:$D,$B$18,Actuals!$A:$A,LEFT($D$18,FIND("|",$D$18&"|")-1),Actuals!$E:$E,MID($D$18,FIND("|",$D$18&"|")+1,50),Actuals!$F:$F,"USD")*$F$5+SUMIFS(Actuals!$G:$G,Actuals!$B:$B,$C$3,Actuals!$C:$C,3,Actuals!$D:$D,$B$18,Actuals!$A:$A,LEFT($D$18,FIND("|",$D$18&"|")-1),Actuals!$E:$E,MID($D$18,FIND("|",$D$18&"|")+1,50),Actuals!$F:$F,"EUR")*$G$5+SUMIFS(Actuals!$G:$G,Actuals!$B:$B,$C$3,Actuals!$C:$C,3,Actuals!$D:$D,$B$18,Actuals!$A:$A,LEFT($D$18,FIND("|",$D$18&"|")-1),Actuals!$E:$E,MID($D$18,FIND("|",$D$18&"|")+1,50),Actuals!$F:$F,"GBP")*$H$5) | K19: =IF(OR($B$18="",4>$C$4),"",SUMIFS(Actuals!$G:$G,Actuals!$B:$B,$C$3,Actuals!$C:$C,4,Actuals!$D:$D,$B$18,Actuals!$A:$A,LEFT($D$18,FIND("|",$D$18&"|")-1),Actuals!$E:$E,MID($D$18,FIND("|",$D$18&"|")+1,50),Actuals!$F:$F,"JPY")*$E$5+SUMIFS(Actuals!$G:$G,Actuals!$B:$B,$C$3,Actuals!$C:$C,4,Actuals!$D:$D,$B$18,Actuals!$A:$A,LEFT($D$18,FIND("|",$D$18&"|")-1),Actuals!$E:$E,MID($D$18,FIND("|",$D$18&"|")+1,50),Actuals!$F:$F,"USD")*$F$5+SUMIFS(Actuals!$G:$G,Actuals!$B:$B,$C$3,Actuals!$C:$C,4,Actuals!$D:$D,$B$18,Actuals!$A:$A,LEFT($D$18,FIND("|",$D$18&"|")-1),Actuals!$E:$E,MID($D$18,FIND("|",$D$18&"|")+1,50),Actuals!$F:$F,"EUR")*$G$5+SUMIFS(Actuals!$G:$G,Actuals!$B:$B,$C$3,Actuals!$C:$C,4,Actuals!$D:$D,$B$18,Actuals!$A:$A,LEFT($D$18,FIND("|",$D$18&"|")-1),Actuals!$E:$E,MID($D$18,FIND("|",$D$18&"|")+1,50),Actuals!$F:$F,"GBP")*$H$5) | L19: =IF(OR($B$18="",5>$C$4),"",SUMIFS(Actuals!$G:$G,Actuals!$B:$B,$C$3,Actuals!$C:$C,5,Actuals!$D:$D,$B$18,Actuals!$A:$A,LEFT($D$18,FIND("|",$D$18&"|")-1),Actuals!$E:$E,MID($D$18,FIND("|",$D$18&"|")+1,50),Actuals!$F:$F,"JPY")*$E$5+SUMIFS(Actuals!$G:$G,Actuals!$B:$B,$C$3,Actuals!$C:$C,5,Actuals!$D:$D,$B$18,Actuals!$A:$A,LEFT($D$18,FIND("|",$D$18&"|")-1),Actuals!$E:$E,MID($D$18,FIND("|",$D$18&"|")+1,50),Actuals!$F:$F,"USD")*$F$5+SUMIFS(Actuals!$G:$G,Actuals!$B:$B,$C$3,Actuals!$C:$C,5,Actuals!$D:$D,$B$18,Actuals!$A:$A,LEFT($D$18,FIND("|",$D$18&"|")-1),Actuals!$E:$E,MID($D$18,FIND("|",$D$18&"|")+1,50),Actuals!$F:$F,"EUR")*$G$5+SUMIFS(Actuals!$G:$G,Actuals!$B:$B,$C$3,Actuals!$C:$C,5,Actuals!$D:$D,$B$18,Actuals!$A:$A,LEFT($D$18,FIND("|",$D$18&"|")-1),Actuals!$E:$E,MID($D$18,FIND("|",$D$18&"|")+1,50),Actuals!$F:$F,"GBP")*$H$5) | M19: =IF(OR($B$18="",6>$C$4),"",SUMIFS(Actuals!$G:$G,Actuals!$B:$B,$C$3,Actuals!$C:$C,6,Actuals!$D:$D,$B$18,Actuals!$A:$A,LEFT($D$18,FIND("|",$D$18&"|")-1),Actuals!$E:$E,MID($D$18,FIND("|",$D$18&"|")+1,50),Actuals!$F:$F,"JPY")*$E$5+SUMIFS(Actuals!$G:$G,Actuals!$B:$B,$C$3,Actuals!$C:$C,6,Actuals!$D:$D,$B$18,Actuals!$A:$A,LEFT($D$18,FIND("|",$D$18&"|")-1),Actuals!$E:$E,MID($D$18,FIND("|",$D$18&"|")+1,50),Actuals!$F:$F,"USD")*$F$5+SUMIFS(Actuals!$G:$G,Actuals!$B:$B,$C$3,Actuals!$C:$C,6,Actuals!$D:$D,$B$18,Actuals!$A:$A,LEFT($D$18,FIND("|",$D$18&"|")-1),Actuals!$E:$E,MID($D$18,FIND("|",$D$18&"|")+1,50),Actuals!$F:$F,"EUR")*$G$5+SUMIFS(Actuals!$G:$G,Actuals!$B:$B,$C$3,Actuals!$C:$C,6,Actuals!$D:$D,$B$18,Actuals!$A:$A,LEFT($D$18,FIND("|",$D$18&"|")-1),Actuals!$E:$E,MID($D$18,FIND("|",$D$18&"|")+1,50),Actuals!$F:$F,"GBP")*$H$5) | N19: =IF(OR($B$18="",7>$C$4),"",SUMIFS(Actuals!$G:$G,Actuals!$B:$B,$C$3,Actuals!$C:$C,7,Actuals!$D:$D,$B$18,Actuals!$A:$A,LEFT($D$18,FIND("|",$D$18&"|")-1),Actuals!$E:$E,MID($D$18,FIND("|",$D$18&"|")+1,50),Actuals!$F:$F,"JPY")*$E$5+SUMIFS(Actuals!$G:$G,Actuals!$B:$B,$C$3,Actuals!$C:$C,7,Actuals!$D:$D,$B$18,Actuals!$A:$A,LEFT($D$18,FIND("|",$D$18&"|")-1),Actuals!$E:$E,MID($D$18,FIND("|",$D$18&"|")+1,50),Actuals!$F:$F,"USD")*$F$5+SUMIFS(Actuals!$G:$G,Actuals!$B:$B,$C$3,Actuals!$C:$C,7,Actuals!$D:$D,$B$18,Actuals!$A:$A,LEFT($D$18,FIND("|",$D$18&"|")-1),Actuals!$E:$E,MID($D$18,FIND("|",$D$18&"|")+1,50),Actuals!$F:$F,"EUR")*$G$5+SUMIFS(Actuals!$G:$G,Actuals!$B:$B,$C$3,Actuals!$C:$C,7,Actuals!$D:$D,$B$18,Actuals!$A:$A,LEFT($D$18,FIND("|",$D$18&"|")-1),Actuals!$E:$E,MID($D$18,FIND("|",$D$18&"|")+1,50),Actuals!$F:$F,"GBP")*$H$5) | O19: =IF(OR($B$18="",8>$C$4),"",SUMIFS(Actuals!$G:$G,Actuals!$B:$B,$C$3,Actuals!$C:$C,8,Actuals!$D:$D,$B$18,Actuals!$A:$A,LEFT($D$18,FIND("|",$D$18&"|")-1),Actuals!$E:$E,MID($D$18,FIND("|",$D$18&"|")+1,50),Actuals!$F:$F,"JPY")*$E$5+SUMIFS(Actuals!$G:$G,Actuals!$B:$B,$C$3,Actuals!$C:$C,8,Actuals!$D:$D,$B$18,Actuals!$A:$A,LEFT($D$18,FIND("|",$D$18&"|")-1),Actuals!$E:$E,MID($D$18,FIND("|",$D$18&"|")+1,50),Actuals!$F:$F,"USD")*$F$5+SUMIFS(Actuals!$G:$G,Actuals!$B:$B,$C$3,Actuals!$C:$C,8,Actuals!$D:$D,$B$18,Actuals!$A:$A,LEFT($D$18,FIND("|",$D$18&"|")-1),Actuals!$E:$E,MID($D$18,FIND("|",$D$18&"|")+1,50),Actuals!$F:$F,"EUR")*$G$5+SUMIFS(Actuals!$G:$G,Actuals!$B:$B,$C$3,Actuals!$C:$C,8,Actuals!$D:$D,$B$18,Actuals!$A:$A,LEFT($D$18,FIND("|",$D$18&"|")-1),Actuals!$E:$E,MID($D$18,FIND("|",$D$18&"|")+1,50),Actuals!$F:$F,"GBP")*$H$5) | P19: =IF(OR($B$18="",9>$C$4),"",SUMIFS(Actuals!$G:$G,Actuals!$B:$B,$C$3,Actuals!$C:$C,9,Actuals!$D:$D,$B$18,Actuals!$A:$A,LEFT($D$18,FIND("|",$D$18&"|")-1),Actuals!$E:$E,MID($D$18,FIND("|",$D$18&"|")+1,50),Actuals!$F:$F,"JPY")*$E$5+SUMIFS(Actuals!$G:$G,Actuals!$B:$B,$C$3,Actuals!$C:$C,9,Actuals!$D:$D,$B$18,Actuals!$A:$A,LEFT($D$18,FIND("|",$D$18&"|")-1),Actuals!$E:$E,MID($D$18,FIND("|",$D$18&"|")+1,50),Actuals!$F:$F,"USD")*$F$5+SUMIFS(Actuals!$G:$G,Actuals!$B:$B,$C$3,Actuals!$C:$C,9,Actuals!$D:$D,$B$18,Actuals!$A:$A,LEFT($D$18,FIND("|",$D$18&"|")-1),Actuals!$E:$E,MID($D$18,FIND("|",$D$18&"|")+1,50),Actuals!$F:$F,"EUR")*$G$5+SUMIFS(Actuals!$G:$G,Actuals!$B:$B,$C$3,Actuals!$C:$C,9,Actuals!$D:$D,$B$18,Actuals!$A:$A,LEFT($D$18,FIND("|",$D$18&"|")-1),Actuals!$E:$E,MID($D$18,FIND("|",$D$18&"|")+1,50),Actuals!$F:$F,"GBP")*$H$5) | Q19: =IF(OR($B$18="",10>$C$4),"",SUMIFS(Actuals!$G:$G,Actuals!$B:$B,$C$3,Actuals!$C:$C,10,Actuals!$D:$D,$B$18,Actuals!$A:$A,LEFT($D$18,FIND("|",$D$18&"|")-1),Actuals!$E:$E,MID($D$18,FIND("|",$D$18&"|")+1,50),Actuals!$F:$F,"JPY")*$E$5+SUMIFS(Actuals!$G:$G,Actuals!$B:$B,$C$3,Actuals!$C:$C,10,Actuals!$D:$D,$B$18,Actuals!$A:$A,LEFT($D$18,FIND("|",$D$18&"|")-1),Actuals!$E:$E,MID($D$18,FIND("|",$D$18&"|")+1,50),Actuals!$F:$F,"USD")*$F$5+SUMIFS(Actuals!$G:$G,Actuals!$B:$B,$C$3,Actuals!$C:$C,10,Actuals!$D:$D,$B$18,Actuals!$A:$A,LEFT($D$18,FIND("|",$D$18&"|")-1),Actuals!$E:$E,MID($D$18,FIND("|",$D$18&"|")+1,50),Actuals!$F:$F,"EUR")*$G$5+SUMIFS(Actuals!$G:$G,Actuals!$B:$B,$C$3,Actuals!$C:$C,10,Actuals!$D:$D,$B$18,Actuals!$A:$A,LEFT($D$18,FIND("|",$D$18&"|")-1),Actuals!$E:$E,MID($D$18,FIND("|",$D$18&"|")+1,50),Actuals!$F:$F,"GBP")*$H$5) | R19: =IF(OR($B$18="",11>$C$4),"",SUMIFS(Actuals!$G:$G,Actuals!$B:$B,$C$3,Actuals!$C:$C,11,Actuals!$D:$D,$B$18,Actuals!$A:$A,LEFT($D$18,FIND("|",$D$18&"|")-1),Actuals!$E:$E,MID($D$18,FIND("|",$D$18&"|")+1,50),Actuals!$F:$F,"JPY")*$E$5+SUMIFS(Actuals!$G:$G,Actuals!$B:$B,$C$3,Actuals!$C:$C,11,Actuals!$D:$D,$B$18,Actuals!$A:$A,LEFT($D$18,FIND("|",$D$18&"|")-1),Actuals!$E:$E,MID($D$18,FIND("|",$D$18&"|")+1,50),Actuals!$F:$F,"USD")*$F$5+SUMIFS(Actuals!$G:$G,Actuals!$B:$B,$C$3,Actuals!$C:$C,11,Actuals!$D:$D,$B$18,Actuals!$A:$A,LEFT($D$18,FIND("|",$D$18&"|")-1),Actuals!$E:$E,MID($D$18,FIND("|",$D$18&"|")+1,50),Actuals!$F:$F,"EUR")*$G$5+SUMIFS(Actuals!$G:$G,Actuals!$B:$B,$C$3,Actuals!$C:$C,11,Actuals!$D:$D,$B$18,Actuals!$A:$A,LEFT($D$18,FIND("|",$D$18&"|")-1),Actuals!$E:$E,MID($D$18,FIND("|",$D$18&"|")+1,50),Actuals!$F:$F,"GBP")*$H$5) | S19: =IF(OR($B$18="",12>$C$4),"",SUMIFS(Actuals!$G:$G,Actuals!$B:$B,$C$3,Actuals!$C:$C,12,Actuals!$D:$D,$B$18,Actuals!$A:$A,LEFT($D$18,FIND("|",$D$18&"|")-1),Actuals!$E:$E,MID($D$18,FIND("|",$D$18&"|")+1,50),Actuals!$F:$F,"JPY")*$E$5+SUMIFS(Actuals!$G:$G,Actuals!$B:$B,$C$3,Actuals!$C:$C,12,Actuals!$D:$D,$B$18,Actuals!$A:$A,LEFT($D$18,FIND("|",$D$18&"|")-1),Actuals!$E:$E,MID($D$18,FIND("|",$D$18&"|")+1,50),Actuals!$F:$F,"USD")*$F$5+SUMIFS(Actuals!$G:$G,Actuals!$B:$B,$C$3,Actuals!$C:$C,12,Actuals!$D:$D,$B$18,Actuals!$A:$A,LEFT($D$18,FIND("|",$D$18&"|")-1),Actuals!$E:$E,MID($D$18,FIND("|",$D$18&"|")+1,50),Actuals!$F:$F,"EUR")*$G$5+SUMIFS(Actuals!$G:$G,Actuals!$B:$B,$C$3,Actuals!$C:$C,12,Actuals!$D:$D,$B$18,Actuals!$A:$A,LEFT($D$18,FIND("|",$D$18&"|")-1),Actuals!$E:$E,MID($D$18,FIND("|",$D$18&"|")+1,50),Actuals!$F:$F,"GBP")*$H$5) | T19: =IF($B$18="","",SUMIF($H$7:$S$7,"<="&$C$4,$H19:$S19)) | X19: =IF($B19="","",IFERROR(INDEX(Cost_Centers!$E:$E,MATCH($B19,Cost_Centers!$A:$A,0)),"(unknown)")) | Y19: =IF($B19="","",IFERROR(INDEX(Cost_Centers!$D:$D,MATCH($B19,Cost_Centers!$A:$A,0)),"(unknown)")) | Z19: =IF(OR($B19="",$G19<>"Variance vs Budget"),"",ABS(N($V19))+ROW()/1000000000)
A20: =IF(A$18="","",A$18) | B20: =IF(B$18="","",B$18) | C20: =IF(C$18="","",C$18) | D20: =IF(D$18="","",D$18) | E20: =IF(E$18="","",E$18) | F20: =IF(F$18="","",F$18) | G20: Variance vs Budget | H20: =IF(OR($B$18="",1>$C$4),"",N(H19)-H18) | I20: =IF(OR($B$18="",2>$C$4),"",N(I19)-I18) | J20: =IF(OR($B$18="",3>$C$4),"",N(J19)-J18) | K20: =IF(OR($B$18="",4>$C$4),"",N(K19)-K18) | L20: =IF(OR($B$18="",5>$C$4),"",N(L19)-L18) | M20: =IF(OR($B$18="",6>$C$4),"",N(M19)-M18) | N20: =IF(OR($B$18="",7>$C$4),"",N(N19)-N18) | O20: =IF(OR($B$18="",8>$C$4),"",N(O19)-O18) | P20: =IF(OR($B$18="",9>$C$4),"",N(P19)-P18) | Q20: =IF(OR($B$18="",10>$C$4),"",N(Q19)-Q18) | R20: =IF(OR($B$18="",11>$C$4),"",N(R19)-R18) | S20: =IF(OR($B$18="",12>$C$4),"",N(S19)-S18) | T20: =IF($B$18="","",T19-T18) | U20: =IF($B$18="","",U22-U18) | V20: =IF($B$18="","",V22-V18) | X20: =IF($B20="","",IFERROR(INDEX(Cost_Centers!$E:$E,MATCH($B20,Cost_Centers!$A:$A,0)),"(unknown)")) | Y20: =IF($B20="","",IFERROR(INDEX(Cost_Centers!$D:$D,MATCH($B20,Cost_Centers!$A:$A,0)),"(unknown)")) | Z20: =IF(OR($B20="",$G20<>"Variance vs Budget"),"",ABS(N($V20))+ROW()/1000000000)
A21: =IF(A$18="","",A$18) | B21: =IF(B$18="","",B$18) | C21: =IF(C$18="","",C$18) | D21: =IF(D$18="","",D$18) | E21: =IF(E$18="","",E$18) | F21: =IF(F$18="","",F$18) | G21: Forecast (input) | X21: =IF($B21="","",IFERROR(INDEX(Cost_Centers!$E:$E,MATCH($B21,Cost_Centers!$A:$A,0)),"(unknown)")) | Y21: =IF($B21="","",IFERROR(INDEX(Cost_Centers!$D:$D,MATCH($B21,Cost_Centers!$A:$A,0)),"(unknown)")) | Z21: =IF(OR($B21="",$G21<>"Variance vs Budget"),"",ABS(N($V21))+ROW()/1000000000)
A22: =IF(A$18="","",A$18) | B22: =IF(B$18="","",B$18) | C22: =IF(C$18="","",C$18) | D22: =IF(D$18="","",D$18) | E22: =IF(E$18="","",E$18) | F22: =IF(F$18="","",F$18) | G22: Actual + Forecast | H22: =IF($B$18="","",IF(1<=$C$4,N(H19),IF(H21="",H18,H21))) | I22: =IF($B$18="","",IF(2<=$C$4,N(I19),IF(I21="",I18,I21))) | J22: =IF($B$18="","",IF(3<=$C$4,N(J19),IF(J21="",J18,J21))) | K22: =IF($B$18="","",IF(4<=$C$4,N(K19),IF(K21="",K18,K21))) | L22: =IF($B$18="","",IF(5<=$C$4,N(L19),IF(L21="",L18,L21))) | M22: =IF($B$18="","",IF(6<=$C$4,N(M19),IF(M21="",M18,M21))) | N22: =IF($B$18="","",IF(7<=$C$4,N(N19),IF(N21="",N18,N21))) | O22: =IF($B$18="","",IF(8<=$C$4,N(O19),IF(O21="",O18,O21))) | P22: =IF($B$18="","",IF(9<=$C$4,N(P19),IF(P21="",P18,P21))) | Q22: =IF($B$18="","",IF(10<=$C$4,N(Q19),IF(Q21="",Q18,Q21))) | R22: =IF($B$18="","",IF(11<=$C$4,N(R19),IF(R21="",R18,R21))) | S22: =IF($B$18="","",IF(12<=$C$4,N(S19),IF(S21="",S18,S21))) | T22: =IF($B$18="","",SUMIF($H$7:$S$7,"<="&$C$4,$H22:$S22)) | U22: =IF($B$18="","",SUMIF($H$7:$S$7,">"&$C$4,$H22:$S22)) | V22: =IF($B$18="","",SUM($H22:$S22)) | X22: =IF($B22="","",IFERROR(INDEX(Cost_Centers!$E:$E,MATCH($B22,Cost_Centers!$A:$A,0)),"(unknown)")) | Y22: =IF($B22="","",IFERROR(INDEX(Cost_Centers!$D:$D,MATCH($B22,Cost_Centers!$A:$A,0)),"(unknown)")) | Z22: =IF(OR($B22="",$G22<>"Variance vs Budget"),"",ABS(N($V22))+ROW()/1000000000)
A23: =IF(A$18="","",A$18) | B23: =IF(B$18="","",B$18) | C23: =IF(C$18="","",C$18) | D23: =IF(D$18="","",D$18) | E23: =IF(E$18="","",E$18) | F23: =IF(F$18="","",F$18) | G23: Prior Month Forecast | H23: =IF($B$18="","",IF(COUNTIFS(Prior_Forecast!$A:$A,$B$18,Prior_Forecast!$B:$B,$D$18)>0,SUMIFS(Prior_Forecast!$C:$C,Prior_Forecast!$A:$A,$B$18,Prior_Forecast!$B:$B,$D$18),"")) | I23: =IF($B$18="","",IF(COUNTIFS(Prior_Forecast!$A:$A,$B$18,Prior_Forecast!$B:$B,$D$18)>0,SUMIFS(Prior_Forecast!$D:$D,Prior_Forecast!$A:$A,$B$18,Prior_Forecast!$B:$B,$D$18),"")) | J23: =IF($B$18="","",IF(COUNTIFS(Prior_Forecast!$A:$A,$B$18,Prior_Forecast!$B:$B,$D$18)>0,SUMIFS(Prior_Forecast!$E:$E,Prior_Forecast!$A:$A,$B$18,Prior_Forecast!$B:$B,$D$18),"")) | K23: =IF($B$18="","",IF(COUNTIFS(Prior_Forecast!$A:$A,$B$18,Prior_Forecast!$B:$B,$D$18)>0,SUMIFS(Prior_Forecast!$F:$F,Prior_Forecast!$A:$A,$B$18,Prior_Forecast!$B:$B,$D$18),"")) | L23: =IF($B$18="","",IF(COUNTIFS(Prior_Forecast!$A:$A,$B$18,Prior_Forecast!$B:$B,$D$18)>0,SUMIFS(Prior_Forecast!$G:$G,Prior_Forecast!$A:$A,$B$18,Prior_Forecast!$B:$B,$D$18),"")) | M23: =IF($B$18="","",IF(COUNTIFS(Prior_Forecast!$A:$A,$B$18,Prior_Forecast!$B:$B,$D$18)>0,SUMIFS(Prior_Forecast!$H:$H,Prior_Forecast!$A:$A,$B$18,Prior_Forecast!$B:$B,$D$18),"")) | N23: =IF($B$18="","",IF(COUNTIFS(Prior_Forecast!$A:$A,$B$18,Prior_Forecast!$B:$B,$D$18)>0,SUMIFS(Prior_Forecast!$I:$I,Prior_Forecast!$A:$A,$B$18,Prior_Forecast!$B:$B,$D$18),"")) | O23: =IF($B$18="","",IF(COUNTIFS(Prior_Forecast!$A:$A,$B$18,Prior_Forecast!$B:$B,$D$18)>0,SUMIFS(Prior_Forecast!$J:$J,Prior_Forecast!$A:$A,$B$18,Prior_Forecast!$B:$B,$D$18),"")) | P23: =IF($B$18="","",IF(COUNTIFS(Prior_Forecast!$A:$A,$B$18,Prior_Forecast!$B:$B,$D$18)>0,SUMIFS(Prior_Forecast!$K:$K,Prior_Forecast!$A:$A,$B$18,Prior_Forecast!$B:$B,$D$18),"")) | Q23: =IF($B$18="","",IF(COUNTIFS(Prior_Forecast!$A:$A,$B$18,Prior_Forecast!$B:$B,$D$18)>0,SUMIFS(Prior_Forecast!$L:$L,Prior_Forecast!$A:$A,$B$18,Prior_Forecast!$B:$B,$D$18),"")) | R23: =IF($B$18="","",IF(COUNTIFS(Prior_Forecast!$A:$A,$B$18,Prior_Forecast!$B:$B,$D$18)>0,SUMIFS(Prior_Forecast!$M:$M,Prior_Forecast!$A:$A,$B$18,Prior_Forecast!$B:$B,$D$18),"")) | S23: =IF($B$18="","",IF(COUNTIFS(Prior_Forecast!$A:$A,$B$18,Prior_Forecast!$B:$B,$D$18)>0,SUMIFS(Prior_Forecast!$N:$N,Prior_Forecast!$A:$A,$B$18,Prior_Forecast!$B:$B,$D$18),"")) | T23: =IF($B$18="","",IF(COUNTIFS(Prior_Forecast!$A:$A,$B$18,Prior_Forecast!$B:$B,$D$18)>0,SUMIFS(Prior_Forecast!$O:$O,Prior_Forecast!$A:$A,$B$18,Prior_Forecast!$B:$B,$D$18),"")) | U23: =IF($B$18="","",IF(COUNTIFS(Prior_Forecast!$A:$A,$B$18,Prior_Forecast!$B:$B,$D$18)>0,SUMIFS(Prior_Forecast!$P:$P,Prior_Forecast!$A:$A,$B$18,Prior_Forecast!$B:$B,$D$18),"")) | V23: =IF($B$18="","",IF(COUNTIFS(Prior_Forecast!$A:$A,$B$18,Prior_Forecast!$B:$B,$D$18)>0,SUMIFS(Prior_Forecast!$Q:$Q,Prior_Forecast!$A:$A,$B$18,Prior_Forecast!$B:$B,$D$18),"")) | X23: =IF($B23="","",IFERROR(INDEX(Cost_Centers!$E:$E,MATCH($B23,Cost_Centers!$A:$A,0)),"(unknown)")) | Y23: =IF($B23="","",IFERROR(INDEX(Cost_Centers!$D:$D,MATCH($B23,Cost_Centers!$A:$A,0)),"(unknown)")) | Z23: =IF(OR($B23="",$G23<>"Variance vs Budget"),"",ABS(N($V23))+ROW()/1000000000)
A24: =IF(A$18="","",A$18) | B24: =IF(B$18="","",B$18) | C24: =IF(C$18="","",C$18) | D24: =IF(D$18="","",D$18) | E24: =IF(E$18="","",E$18) | F24: =IF(F$18="","",F$18) | G24: Variance vs Prior Month | H24: =IF(OR($B$18="",H23=""),"",H22-H23) | I24: =IF(OR($B$18="",I23=""),"",I22-I23) | J24: =IF(OR($B$18="",J23=""),"",J22-J23) | K24: =IF(OR($B$18="",K23=""),"",K22-K23) | L24: =IF(OR($B$18="",L23=""),"",L22-L23) | M24: =IF(OR($B$18="",M23=""),"",M22-M23) | N24: =IF(OR($B$18="",N23=""),"",N22-N23) | O24: =IF(OR($B$18="",O23=""),"",O22-O23) | ... V24: =IF(OR($B$18="",V23=""),"",V22-V23) | X24: =IF($B24="","",IFERROR(INDEX(Cost_Centers!$E:$E,MATCH($B24,Cost_Centers!$A:$A,0)),"(unknown)")) | Y24: =IF($B24="","",IFERROR(INDEX(Cost_Centers!$D:$D,MATCH($B24,Cost_Centers!$A:$A,0)),"(unknown)")) | Z24: =IF(OR($B24="",$G24<>"Variance vs Budget"),"",ABS(N($V24))+ROW()/1000000000)
A25: =IF(A$18="","",A$18) | B25: =IF(B$18="","",B$18) | C25: =IF(C$18="","",C$18) | D25: =IF(D$18="","",D$18) | E25: =IF(E$18="","",E$18) | F25: =IF(F$18="","",F$18) | G25: Rationale | X25: =IF($B25="","",IFERROR(INDEX(Cost_Centers!$E:$E,MATCH($B25,Cost_Centers!$A:$A,0)),"(unknown)")) | Y25: =IF($B25="","",IFERROR(INDEX(Cost_Centers!$D:$D,MATCH($B25,Cost_Centers!$A:$A,0)),"(unknown)")) | Z25: =IF(OR($B25="",$G25<>"Variance vs Budget"),"",ABS(N($V25))+ROW()/1000000000)
A26: =IF($D$26="","",LEFT($D$26,FIND("|",$D$26&"|")-1)) | C26: =IF($B$26="","",IFERROR(INDEX(Cost_Centers!$B:$B,MATCH($B$26,Cost_Centers!$A:$A,0)),"(not in master)")) | E26: =IF($D$26="","",IFERROR(INDEX(Accounts!$D:$D,MATCH($D$26,Accounts!$A:$A,0)),"(not in master)")) | G26: Budget | H26: =IF($B$26="","",SUMIFS(Opex_Budget!$O:$O,Opex_Budget!$A:$A,$C$3,Opex_Budget!$E:$E,$B$26,Opex_Budget!$F:$F,$D$26,Opex_Budget!$N:$N,"JPY")*$E$5+SUMIFS(Opex_Budget!$O:$O,Opex_Budget!$A:$A,$C$3,Opex_Budget!$E:$E,$B$26,Opex_Budget!$F:$F,$D$26,Opex_Budget!$N:$N,"USD")*$F$5+SUMIFS(Opex_Budget!$O:$O,Opex_Budget!$A:$A,$C$3,Opex_Budget!$E:$E,$B$26,Opex_Budget!$F:$F,$D$26,Opex_Budget!$N:$N,"EUR")*$G$5+SUMIFS(Opex_Budget!$O:$O,Opex_Budget!$A:$A,$C$3,Opex_Budget!$E:$E,$B$26,Opex_Budget!$F:$F,$D$26,Opex_Budget!$N:$N,"GBP")*$H$5) | I26: =IF($B$26="","",SUMIFS(Opex_Budget!$P:$P,Opex_Budget!$A:$A,$C$3,Opex_Budget!$E:$E,$B$26,Opex_Budget!$F:$F,$D$26,Opex_Budget!$N:$N,"JPY")*$E$5+SUMIFS(Opex_Budget!$P:$P,Opex_Budget!$A:$A,$C$3,Opex_Budget!$E:$E,$B$26,Opex_Budget!$F:$F,$D$26,Opex_Budget!$N:$N,"USD")*$F$5+SUMIFS(Opex_Budget!$P:$P,Opex_Budget!$A:$A,$C$3,Opex_Budget!$E:$E,$B$26,Opex_Budget!$F:$F,$D$26,Opex_Budget!$N:$N,"EUR")*$G$5+SUMIFS(Opex_Budget!$P:$P,Opex_Budget!$A:$A,$C$3,Opex_Budget!$E:$E,$B$26,Opex_Budget!$F:$F,$D$26,Opex_Budget!$N:$N,"GBP")*$H$5) | J26: =IF($B$26="","",SUMIFS(Opex_Budget!$Q:$Q,Opex_Budget!$A:$A,$C$3,Opex_Budget!$E:$E,$B$26,Opex_Budget!$F:$F,$D$26,Opex_Budget!$N:$N,"JPY")*$E$5+SUMIFS(Opex_Budget!$Q:$Q,Opex_Budget!$A:$A,$C$3,Opex_Budget!$E:$E,$B$26,Opex_Budget!$F:$F,$D$26,Opex_Budget!$N:$N,"USD")*$F$5+SUMIFS(Opex_Budget!$Q:$Q,Opex_Budget!$A:$A,$C$3,Opex_Budget!$E:$E,$B$26,Opex_Budget!$F:$F,$D$26,Opex_Budget!$N:$N,"EUR")*$G$5+SUMIFS(Opex_Budget!$Q:$Q,Opex_Budget!$A:$A,$C$3,Opex_Budget!$E:$E,$B$26,Opex_Budget!$F:$F,$D$26,Opex_Budget!$N:$N,"GBP")*$H$5) | K26: =IF($B$26="","",SUMIFS(Opex_Budget!$R:$R,Opex_Budget!$A:$A,$C$3,Opex_Budget!$E:$E,$B$26,Opex_Budget!$F:$F,$D$26,Opex_Budget!$N:$N,"JPY")*$E$5+SUMIFS(Opex_Budget!$R:$R,Opex_Budget!$A:$A,$C$3,Opex_Budget!$E:$E,$B$26,Opex_Budget!$F:$F,$D$26,Opex_Budget!$N:$N,"USD")*$F$5+SUMIFS(Opex_Budget!$R:$R,Opex_Budget!$A:$A,$C$3,Opex_Budget!$E:$E,$B$26,Opex_Budget!$F:$F,$D$26,Opex_Budget!$N:$N,"EUR")*$G$5+SUMIFS(Opex_Budget!$R:$R,Opex_Budget!$A:$A,$C$3,Opex_Budget!$E:$E,$B$26,Opex_Budget!$F:$F,$D$26,Opex_Budget!$N:$N,"GBP")*$H$5) | L26: =IF($B$26="","",SUMIFS(Opex_Budget!$S:$S,Opex_Budget!$A:$A,$C$3,Opex_Budget!$E:$E,$B$26,Opex_Budget!$F:$F,$D$26,Opex_Budget!$N:$N,"JPY")*$E$5+SUMIFS(Opex_Budget!$S:$S,Opex_Budget!$A:$A,$C$3,Opex_Budget!$E:$E,$B$26,Opex_Budget!$F:$F,$D$26,Opex_Budget!$N:$N,"USD")*$F$5+SUMIFS(Opex_Budget!$S:$S,Opex_Budget!$A:$A,$C$3,Opex_Budget!$E:$E,$B$26,Opex_Budget!$F:$F,$D$26,Opex_Budget!$N:$N,"EUR")*$G$5+SUMIFS(Opex_Budget!$S:$S,Opex_Budget!$A:$A,$C$3,Opex_Budget!$E:$E,$B$26,Opex_Budget!$F:$F,$D$26,Opex_Budget!$N:$N,"GBP")*$H$5) | M26: =IF($B$26="","",SUMIFS(Opex_Budget!$T:$T,Opex_Budget!$A:$A,$C$3,Opex_Budget!$E:$E,$B$26,Opex_Budget!$F:$F,$D$26,Opex_Budget!$N:$N,"JPY")*$E$5+SUMIFS(Opex_Budget!$T:$T,Opex_Budget!$A:$A,$C$3,Opex_Budget!$E:$E,$B$26,Opex_Budget!$F:$F,$D$26,Opex_Budget!$N:$N,"USD")*$F$5+SUMIFS(Opex_Budget!$T:$T,Opex_Budget!$A:$A,$C$3,Opex_Budget!$E:$E,$B$26,Opex_Budget!$F:$F,$D$26,Opex_Budget!$N:$N,"EUR")*$G$5+SUMIFS(Opex_Budget!$T:$T,Opex_Budget!$A:$A,$C$3,Opex_Budget!$E:$E,$B$26,Opex_Budget!$F:$F,$D$26,Opex_Budget!$N:$N,"GBP")*$H$5) | N26: =IF($B$26="","",SUMIFS(Opex_Budget!$U:$U,Opex_Budget!$A:$A,$C$3,Opex_Budget!$E:$E,$B$26,Opex_Budget!$F:$F,$D$26,Opex_Budget!$N:$N,"JPY")*$E$5+SUMIFS(Opex_Budget!$U:$U,Opex_Budget!$A:$A,$C$3,Opex_Budget!$E:$E,$B$26,Opex_Budget!$F:$F,$D$26,Opex_Budget!$N:$N,"USD")*$F$5+SUMIFS(Opex_Budget!$U:$U,Opex_Budget!$A:$A,$C$3,Opex_Budget!$E:$E,$B$26,Opex_Budget!$F:$F,$D$26,Opex_Budget!$N:$N,"EUR")*$G$5+SUMIFS(Opex_Budget!$U:$U,Opex_Budget!$A:$A,$C$3,Opex_Budget!$E:$E,$B$26,Opex_Budget!$F:$F,$D$26,Opex_Budget!$N:$N,"GBP")*$H$5) | O26: =IF($B$26="","",SUMIFS(Opex_Budget!$V:$V,Opex_Budget!$A:$A,$C$3,Opex_Budget!$E:$E,$B$26,Opex_Budget!$F:$F,$D$26,Opex_Budget!$N:$N,"JPY")*$E$5+SUMIFS(Opex_Budget!$V:$V,Opex_Budget!$A:$A,$C$3,Opex_Budget!$E:$E,$B$26,Opex_Budget!$F:$F,$D$26,Opex_Budget!$N:$N,"USD")*$F$5+SUMIFS(Opex_Budget!$V:$V,Opex_Budget!$A:$A,$C$3,Opex_Budget!$E:$E,$B$26,Opex_Budget!$F:$F,$D$26,Opex_Budget!$N:$N,"EUR")*$G$5+SUMIFS(Opex_Budget!$V:$V,Opex_Budget!$A:$A,$C$3,Opex_Budget!$E:$E,$B$26,Opex_Budget!$F:$F,$D$26,Opex_Budget!$N:$N,"GBP")*$H$5) | P26: =IF($B$26="","",SUMIFS(Opex_Budget!$W:$W,Opex_Budget!$A:$A,$C$3,Opex_Budget!$E:$E,$B$26,Opex_Budget!$F:$F,$D$26,Opex_Budget!$N:$N,"JPY")*$E$5+SUMIFS(Opex_Budget!$W:$W,Opex_Budget!$A:$A,$C$3,Opex_Budget!$E:$E,$B$26,Opex_Budget!$F:$F,$D$26,Opex_Budget!$N:$N,"USD")*$F$5+SUMIFS(Opex_Budget!$W:$W,Opex_Budget!$A:$A,$C$3,Opex_Budget!$E:$E,$B$26,Opex_Budget!$F:$F,$D$26,Opex_Budget!$N:$N,"EUR")*$G$5+SUMIFS(Opex_Budget!$W:$W,Opex_Budget!$A:$A,$C$3,Opex_Budget!$E:$E,$B$26,Opex_Budget!$F:$F,$D$26,Opex_Budget!$N:$N,"GBP")*$H$5) | Q26: =IF($B$26="","",SUMIFS(Opex_Budget!$X:$X,Opex_Budget!$A:$A,$C$3,Opex_Budget!$E:$E,$B$26,Opex_Budget!$F:$F,$D$26,Opex_Budget!$N:$N,"JPY")*$E$5+SUMIFS(Opex_Budget!$X:$X,Opex_Budget!$A:$A,$C$3,Opex_Budget!$E:$E,$B$26,Opex_Budget!$F:$F,$D$26,Opex_Budget!$N:$N,"USD")*$F$5+SUMIFS(Opex_Budget!$X:$X,Opex_Budget!$A:$A,$C$3,Opex_Budget!$E:$E,$B$26,Opex_Budget!$F:$F,$D$26,Opex_Budget!$N:$N,"EUR")*$G$5+SUMIFS(Opex_Budget!$X:$X,Opex_Budget!$A:$A,$C$3,Opex_Budget!$E:$E,$B$26,Opex_Budget!$F:$F,$D$26,Opex_Budget!$N:$N,"GBP")*$H$5) | R26: =IF($B$26="","",SUMIFS(Opex_Budget!$Y:$Y,Opex_Budget!$A:$A,$C$3,Opex_Budget!$E:$E,$B$26,Opex_Budget!$F:$F,$D$26,Opex_Budget!$N:$N,"JPY")*$E$5+SUMIFS(Opex_Budget!$Y:$Y,Opex_Budget!$A:$A,$C$3,Opex_Budget!$E:$E,$B$26,Opex_Budget!$F:$F,$D$26,Opex_Budget!$N:$N,"USD")*$F$5+SUMIFS(Opex_Budget!$Y:$Y,Opex_Budget!$A:$A,$C$3,Opex_Budget!$E:$E,$B$26,Opex_Budget!$F:$F,$D$26,Opex_Budget!$N:$N,"EUR")*$G$5+SUMIFS(Opex_Budget!$Y:$Y,Opex_Budget!$A:$A,$C$3,Opex_Budget!$E:$E,$B$26,Opex_Budget!$F:$F,$D$26,Opex_Budget!$N:$N,"GBP")*$H$5) | S26: =IF($B$26="","",SUMIFS(Opex_Budget!$Z:$Z,Opex_Budget!$A:$A,$C$3,Opex_Budget!$E:$E,$B$26,Opex_Budget!$F:$F,$D$26,Opex_Budget!$N:$N,"JPY")*$E$5+SUMIFS(Opex_Budget!$Z:$Z,Opex_Budget!$A:$A,$C$3,Opex_Budget!$E:$E,$B$26,Opex_Budget!$F:$F,$D$26,Opex_Budget!$N:$N,"USD")*$F$5+SUMIFS(Opex_Budget!$Z:$Z,Opex_Budget!$A:$A,$C$3,Opex_Budget!$E:$E,$B$26,Opex_Budget!$F:$F,$D$26,Opex_Budget!$N:$N,"EUR")*$G$5+SUMIFS(Opex_Budget!$Z:$Z,Opex_Budget!$A:$A,$C$3,Opex_Budget!$E:$E,$B$26,Opex_Budget!$F:$F,$D$26,Opex_Budget!$N:$N,"GBP")*$H$5) | T26: =IF($B$26="","",SUMIF($H$7:$S$7,"<="&$C$4,$H26:$S26)) | U26: =IF($B$26="","",SUMIF($H$7:$S$7,">"&$C$4,$H26:$S26)) | V26: =IF($B$26="","",SUM($H26:$S26)) | X26: =IF($B26="","",IFERROR(INDEX(Cost_Centers!$E:$E,MATCH($B26,Cost_Centers!$A:$A,0)),"(unknown)")) | Y26: =IF($B26="","",IFERROR(INDEX(Cost_Centers!$D:$D,MATCH($B26,Cost_Centers!$A:$A,0)),"(unknown)")) | Z26: =IF(OR($B26="",$G26<>"Variance vs Budget"),"",ABS(N($V26))+ROW()/1000000000)
A27: =IF(A$26="","",A$26) | B27: =IF(B$26="","",B$26) | C27: =IF(C$26="","",C$26) | D27: =IF(D$26="","",D$26) | E27: =IF(E$26="","",E$26) | F27: =IF(F$26="","",F$26) | G27: Actual | H27: =IF(OR($B$26="",1>$C$4),"",SUMIFS(Actuals!$G:$G,Actuals!$B:$B,$C$3,Actuals!$C:$C,1,Actuals!$D:$D,$B$26,Actuals!$A:$A,LEFT($D$26,FIND("|",$D$26&"|")-1),Actuals!$E:$E,MID($D$26,FIND("|",$D$26&"|")+1,50),Actuals!$F:$F,"JPY")*$E$5+SUMIFS(Actuals!$G:$G,Actuals!$B:$B,$C$3,Actuals!$C:$C,1,Actuals!$D:$D,$B$26,Actuals!$A:$A,LEFT($D$26,FIND("|",$D$26&"|")-1),Actuals!$E:$E,MID($D$26,FIND("|",$D$26&"|")+1,50),Actuals!$F:$F,"USD")*$F$5+SUMIFS(Actuals!$G:$G,Actuals!$B:$B,$C$3,Actuals!$C:$C,1,Actuals!$D:$D,$B$26,Actuals!$A:$A,LEFT($D$26,FIND("|",$D$26&"|")-1),Actuals!$E:$E,MID($D$26,FIND("|",$D$26&"|")+1,50),Actuals!$F:$F,"EUR")*$G$5+SUMIFS(Actuals!$G:$G,Actuals!$B:$B,$C$3,Actuals!$C:$C,1,Actuals!$D:$D,$B$26,Actuals!$A:$A,LEFT($D$26,FIND("|",$D$26&"|")-1),Actuals!$E:$E,MID($D$26,FIND("|",$D$26&"|")+1,50),Actuals!$F:$F,"GBP")*$H$5) | I27: =IF(OR($B$26="",2>$C$4),"",SUMIFS(Actuals!$G:$G,Actuals!$B:$B,$C$3,Actuals!$C:$C,2,Actuals!$D:$D,$B$26,Actuals!$A:$A,LEFT($D$26,FIND("|",$D$26&"|")-1),Actuals!$E:$E,MID($D$26,FIND("|",$D$26&"|")+1,50),Actuals!$F:$F,"JPY")*$E$5+SUMIFS(Actuals!$G:$G,Actuals!$B:$B,$C$3,Actuals!$C:$C,2,Actuals!$D:$D,$B$26,Actuals!$A:$A,LEFT($D$26,FIND("|",$D$26&"|")-1),Actuals!$E:$E,MID($D$26,FIND("|",$D$26&"|")+1,50),Actuals!$F:$F,"USD")*$F$5+SUMIFS(Actuals!$G:$G,Actuals!$B:$B,$C$3,Actuals!$C:$C,2,Actuals!$D:$D,$B$26,Actuals!$A:$A,LEFT($D$26,FIND("|",$D$26&"|")-1),Actuals!$E:$E,MID($D$26,FIND("|",$D$26&"|")+1,50),Actuals!$F:$F,"EUR")*$G$5+SUMIFS(Actuals!$G:$G,Actuals!$B:$B,$C$3,Actuals!$C:$C,2,Actuals!$D:$D,$B$26,Actuals!$A:$A,LEFT($D$26,FIND("|",$D$26&"|")-1),Actuals!$E:$E,MID($D$26,FIND("|",$D$26&"|")+1,50),Actuals!$F:$F,"GBP")*$H$5) | J27: =IF(OR($B$26="",3>$C$4),"",SUMIFS(Actuals!$G:$G,Actuals!$B:$B,$C$3,Actuals!$C:$C,3,Actuals!$D:$D,$B$26,Actuals!$A:$A,LEFT($D$26,FIND("|",$D$26&"|")-1),Actuals!$E:$E,MID($D$26,FIND("|",$D$26&"|")+1,50),Actuals!$F:$F,"JPY")*$E$5+SUMIFS(Actuals!$G:$G,Actuals!$B:$B,$C$3,Actuals!$C:$C,3,Actuals!$D:$D,$B$26,Actuals!$A:$A,LEFT($D$26,FIND("|",$D$26&"|")-1),Actuals!$E:$E,MID($D$26,FIND("|",$D$26&"|")+1,50),Actuals!$F:$F,"USD")*$F$5+SUMIFS(Actuals!$G:$G,Actuals!$B:$B,$C$3,Actuals!$C:$C,3,Actuals!$D:$D,$B$26,Actuals!$A:$A,LEFT($D$26,FIND("|",$D$26&"|")-1),Actuals!$E:$E,MID($D$26,FIND("|",$D$26&"|")+1,50),Actuals!$F:$F,"EUR")*$G$5+SUMIFS(Actuals!$G:$G,Actuals!$B:$B,$C$3,Actuals!$C:$C,3,Actuals!$D:$D,$B$26,Actuals!$A:$A,LEFT($D$26,FIND("|",$D$26&"|")-1),Actuals!$E:$E,MID($D$26,FIND("|",$D$26&"|")+1,50),Actuals!$F:$F,"GBP")*$H$5) | K27: =IF(OR($B$26="",4>$C$4),"",SUMIFS(Actuals!$G:$G,Actuals!$B:$B,$C$3,Actuals!$C:$C,4,Actuals!$D:$D,$B$26,Actuals!$A:$A,LEFT($D$26,FIND("|",$D$26&"|")-1),Actuals!$E:$E,MID($D$26,FIND("|",$D$26&"|")+1,50),Actuals!$F:$F,"JPY")*$E$5+SUMIFS(Actuals!$G:$G,Actuals!$B:$B,$C$3,Actuals!$C:$C,4,Actuals!$D:$D,$B$26,Actuals!$A:$A,LEFT($D$26,FIND("|",$D$26&"|")-1),Actuals!$E:$E,MID($D$26,FIND("|",$D$26&"|")+1,50),Actuals!$F:$F,"USD")*$F$5+SUMIFS(Actuals!$G:$G,Actuals!$B:$B,$C$3,Actuals!$C:$C,4,Actuals!$D:$D,$B$26,Actuals!$A:$A,LEFT($D$26,FIND("|",$D$26&"|")-1),Actuals!$E:$E,MID($D$26,FIND("|",$D$26&"|")+1,50),Actuals!$F:$F,"EUR")*$G$5+SUMIFS(Actuals!$G:$G,Actuals!$B:$B,$C$3,Actuals!$C:$C,4,Actuals!$D:$D,$B$26,Actuals!$A:$A,LEFT($D$26,FIND("|",$D$26&"|")-1),Actuals!$E:$E,MID($D$26,FIND("|",$D$26&"|")+1,50),Actuals!$F:$F,"GBP")*$H$5) | L27: =IF(OR($B$26="",5>$C$4),"",SUMIFS(Actuals!$G:$G,Actuals!$B:$B,$C$3,Actuals!$C:$C,5,Actuals!$D:$D,$B$26,Actuals!$A:$A,LEFT($D$26,FIND("|",$D$26&"|")-1),Actuals!$E:$E,MID($D$26,FIND("|",$D$26&"|")+1,50),Actuals!$F:$F,"JPY")*$E$5+SUMIFS(Actuals!$G:$G,Actuals!$B:$B,$C$3,Actuals!$C:$C,5,Actuals!$D:$D,$B$26,Actuals!$A:$A,LEFT($D$26,FIND("|",$D$26&"|")-1),Actuals!$E:$E,MID($D$26,FIND("|",$D$26&"|")+1,50),Actuals!$F:$F,"USD")*$F$5+SUMIFS(Actuals!$G:$G,Actuals!$B:$B,$C$3,Actuals!$C:$C,5,Actuals!$D:$D,$B$26,Actuals!$A:$A,LEFT($D$26,FIND("|",$D$26&"|")-1),Actuals!$E:$E,MID($D$26,FIND("|",$D$26&"|")+1,50),Actuals!$F:$F,"EUR")*$G$5+SUMIFS(Actuals!$G:$G,Actuals!$B:$B,$C$3,Actuals!$C:$C,5,Actuals!$D:$D,$B$26,Actuals!$A:$A,LEFT($D$26,FIND("|",$D$26&"|")-1),Actuals!$E:$E,MID($D$26,FIND("|",$D$26&"|")+1,50),Actuals!$F:$F,"GBP")*$H$5) | M27: =IF(OR($B$26="",6>$C$4),"",SUMIFS(Actuals!$G:$G,Actuals!$B:$B,$C$3,Actuals!$C:$C,6,Actuals!$D:$D,$B$26,Actuals!$A:$A,LEFT($D$26,FIND("|",$D$26&"|")-1),Actuals!$E:$E,MID($D$26,FIND("|",$D$26&"|")+1,50),Actuals!$F:$F,"JPY")*$E$5+SUMIFS(Actuals!$G:$G,Actuals!$B:$B,$C$3,Actuals!$C:$C,6,Actuals!$D:$D,$B$26,Actuals!$A:$A,LEFT($D$26,FIND("|",$D$26&"|")-1),Actuals!$E:$E,MID($D$26,FIND("|",$D$26&"|")+1,50),Actuals!$F:$F,"USD")*$F$5+SUMIFS(Actuals!$G:$G,Actuals!$B:$B,$C$3,Actuals!$C:$C,6,Actuals!$D:$D,$B$26,Actuals!$A:$A,LEFT($D$26,FIND("|",$D$26&"|")-1),Actuals!$E:$E,MID($D$26,FIND("|",$D$26&"|")+1,50),Actuals!$F:$F,"EUR")*$G$5+SUMIFS(Actuals!$G:$G,Actuals!$B:$B,$C$3,Actuals!$C:$C,6,Actuals!$D:$D,$B$26,Actuals!$A:$A,LEFT($D$26,FIND("|",$D$26&"|")-1),Actuals!$E:$E,MID($D$26,FIND("|",$D$26&"|")+1,50),Actuals!$F:$F,"GBP")*$H$5) | N27: =IF(OR($B$26="",7>$C$4),"",SUMIFS(Actuals!$G:$G,Actuals!$B:$B,$C$3,Actuals!$C:$C,7,Actuals!$D:$D,$B$26,Actuals!$A:$A,LEFT($D$26,FIND("|",$D$26&"|")-1),Actuals!$E:$E,MID($D$26,FIND("|",$D$26&"|")+1,50),Actuals!$F:$F,"JPY")*$E$5+SUMIFS(Actuals!$G:$G,Actuals!$B:$B,$C$3,Actuals!$C:$C,7,Actuals!$D:$D,$B$26,Actuals!$A:$A,LEFT($D$26,FIND("|",$D$26&"|")-1),Actuals!$E:$E,MID($D$26,FIND("|",$D$26&"|")+1,50),Actuals!$F:$F,"USD")*$F$5+SUMIFS(Actuals!$G:$G,Actuals!$B:$B,$C$3,Actuals!$C:$C,7,Actuals!$D:$D,$B$26,Actuals!$A:$A,LEFT($D$26,FIND("|",$D$26&"|")-1),Actuals!$E:$E,MID($D$26,FIND("|",$D$26&"|")+1,50),Actuals!$F:$F,"EUR")*$G$5+SUMIFS(Actuals!$G:$G,Actuals!$B:$B,$C$3,Actuals!$C:$C,7,Actuals!$D:$D,$B$26,Actuals!$A:$A,LEFT($D$26,FIND("|",$D$26&"|")-1),Actuals!$E:$E,MID($D$26,FIND("|",$D$26&"|")+1,50),Actuals!$F:$F,"GBP")*$H$5) | O27: =IF(OR($B$26="",8>$C$4),"",SUMIFS(Actuals!$G:$G,Actuals!$B:$B,$C$3,Actuals!$C:$C,8,Actuals!$D:$D,$B$26,Actuals!$A:$A,LEFT($D$26,FIND("|",$D$26&"|")-1),Actuals!$E:$E,MID($D$26,FIND("|",$D$26&"|")+1,50),Actuals!$F:$F,"JPY")*$E$5+SUMIFS(Actuals!$G:$G,Actuals!$B:$B,$C$3,Actuals!$C:$C,8,Actuals!$D:$D,$B$26,Actuals!$A:$A,LEFT($D$26,FIND("|",$D$26&"|")-1),Actuals!$E:$E,MID($D$26,FIND("|",$D$26&"|")+1,50),Actuals!$F:$F,"USD")*$F$5+SUMIFS(Actuals!$G:$G,Actuals!$B:$B,$C$3,Actuals!$C:$C,8,Actuals!$D:$D,$B$26,Actuals!$A:$A,LEFT($D$26,FIND("|",$D$26&"|")-1),Actuals!$E:$E,MID($D$26,FIND("|",$D$26&"|")+1,50),Actuals!$F:$F,"EUR")*$G$5+SUMIFS(Actuals!$G:$G,Actuals!$B:$B,$C$3,Actuals!$C:$C,8,Actuals!$D:$D,$B$26,Actuals!$A:$A,LEFT($D$26,FIND("|",$D$26&"|")-1),Actuals!$E:$E,MID($D$26,FIND("|",$D$26&"|")+1,50),Actuals!$F:$F,"GBP")*$H$5) | P27: =IF(OR($B$26="",9>$C$4),"",SUMIFS(Actuals!$G:$G,Actuals!$B:$B,$C$3,Actuals!$C:$C,9,Actuals!$D:$D,$B$26,Actuals!$A:$A,LEFT($D$26,FIND("|",$D$26&"|")-1),Actuals!$E:$E,MID($D$26,FIND("|",$D$26&"|")+1,50),Actuals!$F:$F,"JPY")*$E$5+SUMIFS(Actuals!$G:$G,Actuals!$B:$B,$C$3,Actuals!$C:$C,9,Actuals!$D:$D,$B$26,Actuals!$A:$A,LEFT($D$26,FIND("|",$D$26&"|")-1),Actuals!$E:$E,MID($D$26,FIND("|",$D$26&"|")+1,50),Actuals!$F:$F,"USD")*$F$5+SUMIFS(Actuals!$G:$G,Actuals!$B:$B,$C$3,Actuals!$C:$C,9,Actuals!$D:$D,$B$26,Actuals!$A:$A,LEFT($D$26,FIND("|",$D$26&"|")-1),Actuals!$E:$E,MID($D$26,FIND("|",$D$26&"|")+1,50),Actuals!$F:$F,"EUR")*$G$5+SUMIFS(Actuals!$G:$G,Actuals!$B:$B,$C$3,Actuals!$C:$C,9,Actuals!$D:$D,$B$26,Actuals!$A:$A,LEFT($D$26,FIND("|",$D$26&"|")-1),Actuals!$E:$E,MID($D$26,FIND("|",$D$26&"|")+1,50),Actuals!$F:$F,"GBP")*$H$5) | Q27: =IF(OR($B$26="",10>$C$4),"",SUMIFS(Actuals!$G:$G,Actuals!$B:$B,$C$3,Actuals!$C:$C,10,Actuals!$D:$D,$B$26,Actuals!$A:$A,LEFT($D$26,FIND("|",$D$26&"|")-1),Actuals!$E:$E,MID($D$26,FIND("|",$D$26&"|")+1,50),Actuals!$F:$F,"JPY")*$E$5+SUMIFS(Actuals!$G:$G,Actuals!$B:$B,$C$3,Actuals!$C:$C,10,Actuals!$D:$D,$B$26,Actuals!$A:$A,LEFT($D$26,FIND("|",$D$26&"|")-1),Actuals!$E:$E,MID($D$26,FIND("|",$D$26&"|")+1,50),Actuals!$F:$F,"USD")*$F$5+SUMIFS(Actuals!$G:$G,Actuals!$B:$B,$C$3,Actuals!$C:$C,10,Actuals!$D:$D,$B$26,Actuals!$A:$A,LEFT($D$26,FIND("|",$D$26&"|")-1),Actuals!$E:$E,MID($D$26,FIND("|",$D$26&"|")+1,50),Actuals!$F:$F,"EUR")*$G$5+SUMIFS(Actuals!$G:$G,Actuals!$B:$B,$C$3,Actuals!$C:$C,10,Actuals!$D:$D,$B$26,Actuals!$A:$A,LEFT($D$26,FIND("|",$D$26&"|")-1),Actuals!$E:$E,MID($D$26,FIND("|",$D$26&"|")+1,50),Actuals!$F:$F,"GBP")*$H$5) | R27: =IF(OR($B$26="",11>$C$4),"",SUMIFS(Actuals!$G:$G,Actuals!$B:$B,$C$3,Actuals!$C:$C,11,Actuals!$D:$D,$B$26,Actuals!$A:$A,LEFT($D$26,FIND("|",$D$26&"|")-1),Actuals!$E:$E,MID($D$26,FIND("|",$D$26&"|")+1,50),Actuals!$F:$F,"JPY")*$E$5+SUMIFS(Actuals!$G:$G,Actuals!$B:$B,$C$3,Actuals!$C:$C,11,Actuals!$D:$D,$B$26,Actuals!$A:$A,LEFT($D$26,FIND("|",$D$26&"|")-1),Actuals!$E:$E,MID($D$26,FIND("|",$D$26&"|")+1,50),Actuals!$F:$F,"USD")*$F$5+SUMIFS(Actuals!$G:$G,Actuals!$B:$B,$C$3,Actuals!$C:$C,11,Actuals!$D:$D,$B$26,Actuals!$A:$A,LEFT($D$26,FIND("|",$D$26&"|")-1),Actuals!$E:$E,MID($D$26,FIND("|",$D$26&"|")+1,50),Actuals!$F:$F,"EUR")*$G$5+SUMIFS(Actuals!$G:$G,Actuals!$B:$B,$C$3,Actuals!$C:$C,11,Actuals!$D:$D,$B$26,Actuals!$A:$A,LEFT($D$26,FIND("|",$D$26&"|")-1),Actuals!$E:$E,MID($D$26,FIND("|",$D$26&"|")+1,50),Actuals!$F:$F,"GBP")*$H$5) | S27: =IF(OR($B$26="",12>$C$4),"",SUMIFS(Actuals!$G:$G,Actuals!$B:$B,$C$3,Actuals!$C:$C,12,Actuals!$D:$D,$B$26,Actuals!$A:$A,LEFT($D$26,FIND("|",$D$26&"|")-1),Actuals!$E:$E,MID($D$26,FIND("|",$D$26&"|")+1,50),Actuals!$F:$F,"JPY")*$E$5+SUMIFS(Actuals!$G:$G,Actuals!$B:$B,$C$3,Actuals!$C:$C,12,Actuals!$D:$D,$B$26,Actuals!$A:$A,LEFT($D$26,FIND("|",$D$26&"|")-1),Actuals!$E:$E,MID($D$26,FIND("|",$D$26&"|")+1,50),Actuals!$F:$F,"USD")*$F$5+SUMIFS(Actuals!$G:$G,Actuals!$B:$B,$C$3,Actuals!$C:$C,12,Actuals!$D:$D,$B$26,Actuals!$A:$A,LEFT($D$26,FIND("|",$D$26&"|")-1),Actuals!$E:$E,MID($D$26,FIND("|",$D$26&"|")+1,50),Actuals!$F:$F,"EUR")*$G$5+SUMIFS(Actuals!$G:$G,Actuals!$B:$B,$C$3,Actuals!$C:$C,12,Actuals!$D:$D,$B$26,Actuals!$A:$A,LEFT($D$26,FIND("|",$D$26&"|")-1),Actuals!$E:$E,MID($D$26,FIND("|",$D$26&"|")+1,50),Actuals!$F:$F,"GBP")*$H$5) | T27: =IF($B$26="","",SUMIF($H$7:$S$7,"<="&$C$4,$H27:$S27)) | X27: =IF($B27="","",IFERROR(INDEX(Cost_Centers!$E:$E,MATCH($B27,Cost_Centers!$A:$A,0)),"(unknown)")) | Y27: =IF($B27="","",IFERROR(INDEX(Cost_Centers!$D:$D,MATCH($B27,Cost_Centers!$A:$A,0)),"(unknown)")) | Z27: =IF(OR($B27="",$G27<>"Variance vs Budget"),"",ABS(N($V27))+ROW()/1000000000)
A28: =IF(A$26="","",A$26) | B28: =IF(B$26="","",B$26) | C28: =IF(C$26="","",C$26) | D28: =IF(D$26="","",D$26) | E28: =IF(E$26="","",E$26) | F28: =IF(F$26="","",F$26) | G28: Variance vs Budget | H28: =IF(OR($B$26="",1>$C$4),"",N(H27)-H26) | I28: =IF(OR($B$26="",2>$C$4),"",N(I27)-I26) | J28: =IF(OR($B$26="",3>$C$4),"",N(J27)-J26) | K28: =IF(OR($B$26="",4>$C$4),"",N(K27)-K26) | L28: =IF(OR($B$26="",5>$C$4),"",N(L27)-L26) | M28: =IF(OR($B$26="",6>$C$4),"",N(M27)-M26) | N28: =IF(OR($B$26="",7>$C$4),"",N(N27)-N26) | O28: =IF(OR($B$26="",8>$C$4),"",N(O27)-O26) | P28: =IF(OR($B$26="",9>$C$4),"",N(P27)-P26) | Q28: =IF(OR($B$26="",10>$C$4),"",N(Q27)-Q26) | R28: =IF(OR($B$26="",11>$C$4),"",N(R27)-R26) | S28: =IF(OR($B$26="",12>$C$4),"",N(S27)-S26) | T28: =IF($B$26="","",T27-T26) | U28: =IF($B$26="","",U30-U26) | V28: =IF($B$26="","",V30-V26) | X28: =IF($B28="","",IFERROR(INDEX(Cost_Centers!$E:$E,MATCH($B28,Cost_Centers!$A:$A,0)),"(unknown)")) | Y28: =IF($B28="","",IFERROR(INDEX(Cost_Centers!$D:$D,MATCH($B28,Cost_Centers!$A:$A,0)),"(unknown)")) | Z28: =IF(OR($B28="",$G28<>"Variance vs Budget"),"",ABS(N($V28))+ROW()/1000000000)
A29: =IF(A$26="","",A$26) | B29: =IF(B$26="","",B$26) | C29: =IF(C$26="","",C$26) | D29: =IF(D$26="","",D$26) | E29: =IF(E$26="","",E$26) | F29: =IF(F$26="","",F$26) | G29: Forecast (input) | X29: =IF($B29="","",IFERROR(INDEX(Cost_Centers!$E:$E,MATCH($B29,Cost_Centers!$A:$A,0)),"(unknown)")) | Y29: =IF($B29="","",IFERROR(INDEX(Cost_Centers!$D:$D,MATCH($B29,Cost_Centers!$A:$A,0)),"(unknown)")) | Z29: =IF(OR($B29="",$G29<>"Variance vs Budget"),"",ABS(N($V29))+ROW()/1000000000)
A30: =IF(A$26="","",A$26) | B30: =IF(B$26="","",B$26) | C30: =IF(C$26="","",C$26) | D30: =IF(D$26="","",D$26) | E30: =IF(E$26="","",E$26) | F30: =IF(F$26="","",F$26) | G30: Actual + Forecast | H30: =IF($B$26="","",IF(1<=$C$4,N(H27),IF(H29="",H26,H29))) | I30: =IF($B$26="","",IF(2<=$C$4,N(I27),IF(I29="",I26,I29))) | J30: =IF($B$26="","",IF(3<=$C$4,N(J27),IF(J29="",J26,J29))) | K30: =IF($B$26="","",IF(4<=$C$4,N(K27),IF(K29="",K26,K29))) | L30: =IF($B$26="","",IF(5<=$C$4,N(L27),IF(L29="",L26,L29))) | M30: =IF($B$26="","",IF(6<=$C$4,N(M27),IF(M29="",M26,M29))) | N30: =IF($B$26="","",IF(7<=$C$4,N(N27),IF(N29="",N26,N29))) | O30: =IF($B$26="","",IF(8<=$C$4,N(O27),IF(O29="",O26,O29))) | P30: =IF($B$26="","",IF(9<=$C$4,N(P27),IF(P29="",P26,P29))) | Q30: =IF($B$26="","",IF(10<=$C$4,N(Q27),IF(Q29="",Q26,Q29))) | R30: =IF($B$26="","",IF(11<=$C$4,N(R27),IF(R29="",R26,R29))) | S30: =IF($B$26="","",IF(12<=$C$4,N(S27),IF(S29="",S26,S29))) | T30: =IF($B$26="","",SUMIF($H$7:$S$7,"<="&$C$4,$H30:$S30)) | U30: =IF($B$26="","",SUMIF($H$7:$S$7,">"&$C$4,$H30:$S30)) | V30: =IF($B$26="","",SUM($H30:$S30)) | X30: =IF($B30="","",IFERROR(INDEX(Cost_Centers!$E:$E,MATCH($B30,Cost_Centers!$A:$A,0)),"(unknown)")) | Y30: =IF($B30="","",IFERROR(INDEX(Cost_Centers!$D:$D,MATCH($B30,Cost_Centers!$A:$A,0)),"(unknown)")) | Z30: =IF(OR($B30="",$G30<>"Variance vs Budget"),"",ABS(N($V30))+ROW()/1000000000)
A31: =IF(A$26="","",A$26) | B31: =IF(B$26="","",B$26) | C31: =IF(C$26="","",C$26) | D31: =IF(D$26="","",D$26) | E31: =IF(E$26="","",E$26) | F31: =IF(F$26="","",F$26) | G31: Prior Month Forecast | H31: =IF($B$26="","",IF(COUNTIFS(Prior_Forecast!$A:$A,$B$26,Prior_Forecast!$B:$B,$D$26)>0,SUMIFS(Prior_Forecast!$C:$C,Prior_Forecast!$A:$A,$B$26,Prior_Forecast!$B:$B,$D$26),"")) | I31: =IF($B$26="","",IF(COUNTIFS(Prior_Forecast!$A:$A,$B$26,Prior_Forecast!$B:$B,$D$26)>0,SUMIFS(Prior_Forecast!$D:$D,Prior_Forecast!$A:$A,$B$26,Prior_Forecast!$B:$B,$D$26),"")) | J31: =IF($B$26="","",IF(COUNTIFS(Prior_Forecast!$A:$A,$B$26,Prior_Forecast!$B:$B,$D$26)>0,SUMIFS(Prior_Forecast!$E:$E,Prior_Forecast!$A:$A,$B$26,Prior_Forecast!$B:$B,$D$26),"")) | K31: =IF($B$26="","",IF(COUNTIFS(Prior_Forecast!$A:$A,$B$26,Prior_Forecast!$B:$B,$D$26)>0,SUMIFS(Prior_Forecast!$F:$F,Prior_Forecast!$A:$A,$B$26,Prior_Forecast!$B:$B,$D$26),"")) | L31: =IF($B$26="","",IF(COUNTIFS(Prior_Forecast!$A:$A,$B$26,Prior_Forecast!$B:$B,$D$26)>0,SUMIFS(Prior_Forecast!$G:$G,Prior_Forecast!$A:$A,$B$26,Prior_Forecast!$B:$B,$D$26),"")) | M31: =IF($B$26="","",IF(COUNTIFS(Prior_Forecast!$A:$A,$B$26,Prior_Forecast!$B:$B,$D$26)>0,SUMIFS(Prior_Forecast!$H:$H,Prior_Forecast!$A:$A,$B$26,Prior_Forecast!$B:$B,$D$26),"")) | N31: =IF($B$26="","",IF(COUNTIFS(Prior_Forecast!$A:$A,$B$26,Prior_Forecast!$B:$B,$D$26)>0,SUMIFS(Prior_Forecast!$I:$I,Prior_Forecast!$A:$A,$B$26,Prior_Forecast!$B:$B,$D$26),"")) | O31: =IF($B$26="","",IF(COUNTIFS(Prior_Forecast!$A:$A,$B$26,Prior_Forecast!$B:$B,$D$26)>0,SUMIFS(Prior_Forecast!$J:$J,Prior_Forecast!$A:$A,$B$26,Prior_Forecast!$B:$B,$D$26),"")) | P31: =IF($B$26="","",IF(COUNTIFS(Prior_Forecast!$A:$A,$B$26,Prior_Forecast!$B:$B,$D$26)>0,SUMIFS(Prior_Forecast!$K:$K,Prior_Forecast!$A:$A,$B$26,Prior_Forecast!$B:$B,$D$26),"")) | Q31: =IF($B$26="","",IF(COUNTIFS(Prior_Forecast!$A:$A,$B$26,Prior_Forecast!$B:$B,$D$26)>0,SUMIFS(Prior_Forecast!$L:$L,Prior_Forecast!$A:$A,$B$26,Prior_Forecast!$B:$B,$D$26),"")) | R31: =IF($B$26="","",IF(COUNTIFS(Prior_Forecast!$A:$A,$B$26,Prior_Forecast!$B:$B,$D$26)>0,SUMIFS(Prior_Forecast!$M:$M,Prior_Forecast!$A:$A,$B$26,Prior_Forecast!$B:$B,$D$26),"")) | S31: =IF($B$26="","",IF(COUNTIFS(Prior_Forecast!$A:$A,$B$26,Prior_Forecast!$B:$B,$D$26)>0,SUMIFS(Prior_Forecast!$N:$N,Prior_Forecast!$A:$A,$B$26,Prior_Forecast!$B:$B,$D$26),"")) | T31: =IF($B$26="","",IF(COUNTIFS(Prior_Forecast!$A:$A,$B$26,Prior_Forecast!$B:$B,$D$26)>0,SUMIFS(Prior_Forecast!$O:$O,Prior_Forecast!$A:$A,$B$26,Prior_Forecast!$B:$B,$D$26),"")) | U31: =IF($B$26="","",IF(COUNTIFS(Prior_Forecast!$A:$A,$B$26,Prior_Forecast!$B:$B,$D$26)>0,SUMIFS(Prior_Forecast!$P:$P,Prior_Forecast!$A:$A,$B$26,Prior_Forecast!$B:$B,$D$26),"")) | V31: =IF($B$26="","",IF(COUNTIFS(Prior_Forecast!$A:$A,$B$26,Prior_Forecast!$B:$B,$D$26)>0,SUMIFS(Prior_Forecast!$Q:$Q,Prior_Forecast!$A:$A,$B$26,Prior_Forecast!$B:$B,$D$26),"")) | X31: =IF($B31="","",IFERROR(INDEX(Cost_Centers!$E:$E,MATCH($B31,Cost_Centers!$A:$A,0)),"(unknown)")) | Y31: =IF($B31="","",IFERROR(INDEX(Cost_Centers!$D:$D,MATCH($B31,Cost_Centers!$A:$A,0)),"(unknown)")) | Z31: =IF(OR($B31="",$G31<>"Variance vs Budget"),"",ABS(N($V31))+ROW()/1000000000)
A32: =IF(A$26="","",A$26) | B32: =IF(B$26="","",B$26) | C32: =IF(C$26="","",C$26) | D32: =IF(D$26="","",D$26) | E32: =IF(E$26="","",E$26) | F32: =IF(F$26="","",F$26) | G32: Variance vs Prior Month | H32: =IF(OR($B$26="",H31=""),"",H30-H31) | I32: =IF(OR($B$26="",I31=""),"",I30-I31) | J32: =IF(OR($B$26="",J31=""),"",J30-J31) | K32: =IF(OR($B$26="",K31=""),"",K30-K31) | L32: =IF(OR($B$26="",L31=""),"",L30-L31) | M32: =IF(OR($B$26="",M31=""),"",M30-M31) | N32: =IF(OR($B$26="",N31=""),"",N30-N31) | O32: =IF(OR($B$26="",O31=""),"",O30-O31) | ... V32: =IF(OR($B$26="",V31=""),"",V30-V31) | X32: =IF($B32="","",IFERROR(INDEX(Cost_Centers!$E:$E,MATCH($B32,Cost_Centers!$A:$A,0)),"(unknown)")) | Y32: =IF($B32="","",IFERROR(INDEX(Cost_Centers!$D:$D,MATCH($B32,Cost_Centers!$A:$A,0)),"(unknown)")) | Z32: =IF(OR($B32="",$G32<>"Variance vs Budget"),"",ABS(N($V32))+ROW()/1000000000)
A33: =IF(A$26="","",A$26) | B33: =IF(B$26="","",B$26) | C33: =IF(C$26="","",C$26) | D33: =IF(D$26="","",D$26) | E33: =IF(E$26="","",E$26) | F33: =IF(F$26="","",F$26) | G33: Rationale | X33: =IF($B33="","",IFERROR(INDEX(Cost_Centers!$E:$E,MATCH($B33,Cost_Centers!$A:$A,0)),"(unknown)")) | Y33: =IF($B33="","",IFERROR(INDEX(Cost_Centers!$D:$D,MATCH($B33,Cost_Centers!$A:$A,0)),"(unknown)")) | Z33: =IF(OR($B33="",$G33<>"Variance vs Budget"),"",ABS(N($V33))+ROW()/1000000000)
A34: =IF($D$34="","",LEFT($D$34,FIND("|",$D$34&"|")-1)) | C34: =IF($B$34="","",IFERROR(INDEX(Cost_Centers!$B:$B,MATCH($B$34,Cost_Centers!$A:$A,0)),"(not in master)")) | E34: =IF($D$34="","",IFERROR(INDEX(Accounts!$D:$D,MATCH($D$34,Accounts!$A:$A,0)),"(not in master)")) | G34: Budget | H34: =IF($B$34="","",SUMIFS(Opex_Budget!$O:$O,Opex_Budget!$A:$A,$C$3,Opex_Budget!$E:$E,$B$34,Opex_Budget!$F:$F,$D$34,Opex_Budget!$N:$N,"JPY")*$E$5+SUMIFS(Opex_Budget!$O:$O,Opex_Budget!$A:$A,$C$3,Opex_Budget!$E:$E,$B$34,Opex_Budget!$F:$F,$D$34,Opex_Budget!$N:$N,"USD")*$F$5+SUMIFS(Opex_Budget!$O:$O,Opex_Budget!$A:$A,$C$3,Opex_Budget!$E:$E,$B$34,Opex_Budget!$F:$F,$D$34,Opex_Budget!$N:$N,"EUR")*$G$5+SUMIFS(Opex_Budget!$O:$O,Opex_Budget!$A:$A,$C$3,Opex_Budget!$E:$E,$B$34,Opex_Budget!$F:$F,$D$34,Opex_Budget!$N:$N,"GBP")*$H$5) | I34: =IF($B$34="","",SUMIFS(Opex_Budget!$P:$P,Opex_Budget!$A:$A,$C$3,Opex_Budget!$E:$E,$B$34,Opex_Budget!$F:$F,$D$34,Opex_Budget!$N:$N,"JPY")*$E$5+SUMIFS(Opex_Budget!$P:$P,Opex_Budget!$A:$A,$C$3,Opex_Budget!$E:$E,$B$34,Opex_Budget!$F:$F,$D$34,Opex_Budget!$N:$N,"USD")*$F$5+SUMIFS(Opex_Budget!$P:$P,Opex_Budget!$A:$A,$C$3,Opex_Budget!$E:$E,$B$34,Opex_Budget!$F:$F,$D$34,Opex_Budget!$N:$N,"EUR")*$G$5+SUMIFS(Opex_Budget!$P:$P,Opex_Budget!$A:$A,$C$3,Opex_Budget!$E:$E,$B$34,Opex_Budget!$F:$F,$D$34,Opex_Budget!$N:$N,"GBP")*$H$5) | J34: =IF($B$34="","",SUMIFS(Opex_Budget!$Q:$Q,Opex_Budget!$A:$A,$C$3,Opex_Budget!$E:$E,$B$34,Opex_Budget!$F:$F,$D$34,Opex_Budget!$N:$N,"JPY")*$E$5+SUMIFS(Opex_Budget!$Q:$Q,Opex_Budget!$A:$A,$C$3,Opex_Budget!$E:$E,$B$34,Opex_Budget!$F:$F,$D$34,Opex_Budget!$N:$N,"USD")*$F$5+SUMIFS(Opex_Budget!$Q:$Q,Opex_Budget!$A:$A,$C$3,Opex_Budget!$E:$E,$B$34,Opex_Budget!$F:$F,$D$34,Opex_Budget!$N:$N,"EUR")*$G$5+SUMIFS(Opex_Budget!$Q:$Q,Opex_Budget!$A:$A,$C$3,Opex_Budget!$E:$E,$B$34,Opex_Budget!$F:$F,$D$34,Opex_Budget!$N:$N,"GBP")*$H$5) | K34: =IF($B$34="","",SUMIFS(Opex_Budget!$R:$R,Opex_Budget!$A:$A,$C$3,Opex_Budget!$E:$E,$B$34,Opex_Budget!$F:$F,$D$34,Opex_Budget!$N:$N,"JPY")*$E$5+SUMIFS(Opex_Budget!$R:$R,Opex_Budget!$A:$A,$C$3,Opex_Budget!$E:$E,$B$34,Opex_Budget!$F:$F,$D$34,Opex_Budget!$N:$N,"USD")*$F$5+SUMIFS(Opex_Budget!$R:$R,Opex_Budget!$A:$A,$C$3,Opex_Budget!$E:$E,$B$34,Opex_Budget!$F:$F,$D$34,Opex_Budget!$N:$N,"EUR")*$G$5+SUMIFS(Opex_Budget!$R:$R,Opex_Budget!$A:$A,$C$3,Opex_Budget!$E:$E,$B$34,Opex_Budget!$F:$F,$D$34,Opex_Budget!$N:$N,"GBP")*$H$5) | L34: =IF($B$34="","",SUMIFS(Opex_Budget!$S:$S,Opex_Budget!$A:$A,$C$3,Opex_Budget!$E:$E,$B$34,Opex_Budget!$F:$F,$D$34,Opex_Budget!$N:$N,"JPY")*$E$5+SUMIFS(Opex_Budget!$S:$S,Opex_Budget!$A:$A,$C$3,Opex_Budget!$E:$E,$B$34,Opex_Budget!$F:$F,$D$34,Opex_Budget!$N:$N,"USD")*$F$5+SUMIFS(Opex_Budget!$S:$S,Opex_Budget!$A:$A,$C$3,Opex_Budget!$E:$E,$B$34,Opex_Budget!$F:$F,$D$34,Opex_Budget!$N:$N,"EUR")*$G$5+SUMIFS(Opex_Budget!$S:$S,Opex_Budget!$A:$A,$C$3,Opex_Budget!$E:$E,$B$34,Opex_Budget!$F:$F,$D$34,Opex_Budget!$N:$N,"GBP")*$H$5) | M34: =IF($B$34="","",SUMIFS(Opex_Budget!$T:$T,Opex_Budget!$A:$A,$C$3,Opex_Budget!$E:$E,$B$34,Opex_Budget!$F:$F,$D$34,Opex_Budget!$N:$N,"JPY")*$E$5+SUMIFS(Opex_Budget!$T:$T,Opex_Budget!$A:$A,$C$3,Opex_Budget!$E:$E,$B$34,Opex_Budget!$F:$F,$D$34,Opex_Budget!$N:$N,"USD")*$F$5+SUMIFS(Opex_Budget!$T:$T,Opex_Budget!$A:$A,$C$3,Opex_Budget!$E:$E,$B$34,Opex_Budget!$F:$F,$D$34,Opex_Budget!$N:$N,"EUR")*$G$5+SUMIFS(Opex_Budget!$T:$T,Opex_Budget!$A:$A,$C$3,Opex_Budget!$E:$E,$B$34,Opex_Budget!$F:$F,$D$34,Opex_Budget!$N:$N,"GBP")*$H$5) | N34: =IF($B$34="","",SUMIFS(Opex_Budget!$U:$U,Opex_Budget!$A:$A,$C$3,Opex_Budget!$E:$E,$B$34,Opex_Budget!$F:$F,$D$34,Opex_Budget!$N:$N,"JPY")*$E$5+SUMIFS(Opex_Budget!$U:$U,Opex_Budget!$A:$A,$C$3,Opex_Budget!$E:$E,$B$34,Opex_Budget!$F:$F,$D$34,Opex_Budget!$N:$N,"USD")*$F$5+SUMIFS(Opex_Budget!$U:$U,Opex_Budget!$A:$A,$C$3,Opex_Budget!$E:$E,$B$34,Opex_Budget!$F:$F,$D$34,Opex_Budget!$N:$N,"EUR")*$G$5+SUMIFS(Opex_Budget!$U:$U,Opex_Budget!$A:$A,$C$3,Opex_Budget!$E:$E,$B$34,Opex_Budget!$F:$F,$D$34,Opex_Budget!$N:$N,"GBP")*$H$5) | O34: =IF($B$34="","",SUMIFS(Opex_Budget!$V:$V,Opex_Budget!$A:$A,$C$3,Opex_Budget!$E:$E,$B$34,Opex_Budget!$F:$F,$D$34,Opex_Budget!$N:$N,"JPY")*$E$5+SUMIFS(Opex_Budget!$V:$V,Opex_Budget!$A:$A,$C$3,Opex_Budget!$E:$E,$B$34,Opex_Budget!$F:$F,$D$34,Opex_Budget!$N:$N,"USD")*$F$5+SUMIFS(Opex_Budget!$V:$V,Opex_Budget!$A:$A,$C$3,Opex_Budget!$E:$E,$B$34,Opex_Budget!$F:$F,$D$34,Opex_Budget!$N:$N,"EUR")*$G$5+SUMIFS(Opex_Budget!$V:$V,Opex_Budget!$A:$A,$C$3,Opex_Budget!$E:$E,$B$34,Opex_Budget!$F:$F,$D$34,Opex_Budget!$N:$N,"GBP")*$H$5) | P34: =IF($B$34="","",SUMIFS(Opex_Budget!$W:$W,Opex_Budget!$A:$A,$C$3,Opex_Budget!$E:$E,$B$34,Opex_Budget!$F:$F,$D$34,Opex_Budget!$N:$N,"JPY")*$E$5+SUMIFS(Opex_Budget!$W:$W,Opex_Budget!$A:$A,$C$3,Opex_Budget!$E:$E,$B$34,Opex_Budget!$F:$F,$D$34,Opex_Budget!$N:$N,"USD")*$F$5+SUMIFS(Opex_Budget!$W:$W,Opex_Budget!$A:$A,$C$3,Opex_Budget!$E:$E,$B$34,Opex_Budget!$F:$F,$D$34,Opex_Budget!$N:$N,"EUR")*$G$5+SUMIFS(Opex_Budget!$W:$W,Opex_Budget!$A:$A,$C$3,Opex_Budget!$E:$E,$B$34,Opex_Budget!$F:$F,$D$34,Opex_Budget!$N:$N,"GBP")*$H$5) | Q34: =IF($B$34="","",SUMIFS(Opex_Budget!$X:$X,Opex_Budget!$A:$A,$C$3,Opex_Budget!$E:$E,$B$34,Opex_Budget!$F:$F,$D$34,Opex_Budget!$N:$N,"JPY")*$E$5+SUMIFS(Opex_Budget!$X:$X,Opex_Budget!$A:$A,$C$3,Opex_Budget!$E:$E,$B$34,Opex_Budget!$F:$F,$D$34,Opex_Budget!$N:$N,"USD")*$F$5+SUMIFS(Opex_Budget!$X:$X,Opex_Budget!$A:$A,$C$3,Opex_Budget!$E:$E,$B$34,Opex_Budget!$F:$F,$D$34,Opex_Budget!$N:$N,"EUR")*$G$5+SUMIFS(Opex_Budget!$X:$X,Opex_Budget!$A:$A,$C$3,Opex_Budget!$E:$E,$B$34,Opex_Budget!$F:$F,$D$34,Opex_Budget!$N:$N,"GBP")*$H$5) | R34: =IF($B$34="","",SUMIFS(Opex_Budget!$Y:$Y,Opex_Budget!$A:$A,$C$3,Opex_Budget!$E:$E,$B$34,Opex_Budget!$F:$F,$D$34,Opex_Budget!$N:$N,"JPY")*$E$5+SUMIFS(Opex_Budget!$Y:$Y,Opex_Budget!$A:$A,$C$3,Opex_Budget!$E:$E,$B$34,Opex_Budget!$F:$F,$D$34,Opex_Budget!$N:$N,"USD")*$F$5+SUMIFS(Opex_Budget!$Y:$Y,Opex_Budget!$A:$A,$C$3,Opex_Budget!$E:$E,$B$34,Opex_Budget!$F:$F,$D$34,Opex_Budget!$N:$N,"EUR")*$G$5+SUMIFS(Opex_Budget!$Y:$Y,Opex_Budget!$A:$A,$C$3,Opex_Budget!$E:$E,$B$34,Opex_Budget!$F:$F,$D$34,Opex_Budget!$N:$N,"GBP")*$H$5) | S34: =IF($B$34="","",SUMIFS(Opex_Budget!$Z:$Z,Opex_Budget!$A:$A,$C$3,Opex_Budget!$E:$E,$B$34,Opex_Budget!$F:$F,$D$34,Opex_Budget!$N:$N,"JPY")*$E$5+SUMIFS(Opex_Budget!$Z:$Z,Opex_Budget!$A:$A,$C$3,Opex_Budget!$E:$E,$B$34,Opex_Budget!$F:$F,$D$34,Opex_Budget!$N:$N,"USD")*$F$5+SUMIFS(Opex_Budget!$Z:$Z,Opex_Budget!$A:$A,$C$3,Opex_Budget!$E:$E,$B$34,Opex_Budget!$F:$F,$D$34,Opex_Budget!$N:$N,"EUR")*$G$5+SUMIFS(Opex_Budget!$Z:$Z,Opex_Budget!$A:$A,$C$3,Opex_Budget!$E:$E,$B$34,Opex_Budget!$F:$F,$D$34,Opex_Budget!$N:$N,"GBP")*$H$5) | T34: =IF($B$34="","",SUMIF($H$7:$S$7,"<="&$C$4,$H34:$S34)) | U34: =IF($B$34="","",SUMIF($H$7:$S$7,">"&$C$4,$H34:$S34)) | V34: =IF($B$34="","",SUM($H34:$S34)) | X34: =IF($B34="","",IFERROR(INDEX(Cost_Centers!$E:$E,MATCH($B34,Cost_Centers!$A:$A,0)),"(unknown)")) | Y34: =IF($B34="","",IFERROR(INDEX(Cost_Centers!$D:$D,MATCH($B34,Cost_Centers!$A:$A,0)),"(unknown)")) | Z34: =IF(OR($B34="",$G34<>"Variance vs Budget"),"",ABS(N($V34))+ROW()/1000000000)
A35: =IF(A$34="","",A$34) | B35: =IF(B$34="","",B$34) | C35: =IF(C$34="","",C$34) | D35: =IF(D$34="","",D$34) | E35: =IF(E$34="","",E$34) | F35: =IF(F$34="","",F$34) | G35: Actual | H35: =IF(OR($B$34="",1>$C$4),"",SUMIFS(Actuals!$G:$G,Actuals!$B:$B,$C$3,Actuals!$C:$C,1,Actuals!$D:$D,$B$34,Actuals!$A:$A,LEFT($D$34,FIND("|",$D$34&"|")-1),Actuals!$E:$E,MID($D$34,FIND("|",$D$34&"|")+1,50),Actuals!$F:$F,"JPY")*$E$5+SUMIFS(Actuals!$G:$G,Actuals!$B:$B,$C$3,Actuals!$C:$C,1,Actuals!$D:$D,$B$34,Actuals!$A:$A,LEFT($D$34,FIND("|",$D$34&"|")-1),Actuals!$E:$E,MID($D$34,FIND("|",$D$34&"|")+1,50),Actuals!$F:$F,"USD")*$F$5+SUMIFS(Actuals!$G:$G,Actuals!$B:$B,$C$3,Actuals!$C:$C,1,Actuals!$D:$D,$B$34,Actuals!$A:$A,LEFT($D$34,FIND("|",$D$34&"|")-1),Actuals!$E:$E,MID($D$34,FIND("|",$D$34&"|")+1,50),Actuals!$F:$F,"EUR")*$G$5+SUMIFS(Actuals!$G:$G,Actuals!$B:$B,$C$3,Actuals!$C:$C,1,Actuals!$D:$D,$B$34,Actuals!$A:$A,LEFT($D$34,FIND("|",$D$34&"|")-1),Actuals!$E:$E,MID($D$34,FIND("|",$D$34&"|")+1,50),Actuals!$F:$F,"GBP")*$H$5) | I35: =IF(OR($B$34="",2>$C$4),"",SUMIFS(Actuals!$G:$G,Actuals!$B:$B,$C$3,Actuals!$C:$C,2,Actuals!$D:$D,$B$34,Actuals!$A:$A,LEFT($D$34,FIND("|",$D$34&"|")-1),Actuals!$E:$E,MID($D$34,FIND("|",$D$34&"|")+1,50),Actuals!$F:$F,"JPY")*$E$5+SUMIFS(Actuals!$G:$G,Actuals!$B:$B,$C$3,Actuals!$C:$C,2,Actuals!$D:$D,$B$34,Actuals!$A:$A,LEFT($D$34,FIND("|",$D$34&"|")-1),Actuals!$E:$E,MID($D$34,FIND("|",$D$34&"|")+1,50),Actuals!$F:$F,"USD")*$F$5+SUMIFS(Actuals!$G:$G,Actuals!$B:$B,$C$3,Actuals!$C:$C,2,Actuals!$D:$D,$B$34,Actuals!$A:$A,LEFT($D$34,FIND("|",$D$34&"|")-1),Actuals!$E:$E,MID($D$34,FIND("|",$D$34&"|")+1,50),Actuals!$F:$F,"EUR")*$G$5+SUMIFS(Actuals!$G:$G,Actuals!$B:$B,$C$3,Actuals!$C:$C,2,Actuals!$D:$D,$B$34,Actuals!$A:$A,LEFT($D$34,FIND("|",$D$34&"|")-1),Actuals!$E:$E,MID($D$34,FIND("|",$D$34&"|")+1,50),Actuals!$F:$F,"GBP")*$H$5) | J35: =IF(OR($B$34="",3>$C$4),"",SUMIFS(Actuals!$G:$G,Actuals!$B:$B,$C$3,Actuals!$C:$C,3,Actuals!$D:$D,$B$34,Actuals!$A:$A,LEFT($D$34,FIND("|",$D$34&"|")-1),Actuals!$E:$E,MID($D$34,FIND("|",$D$34&"|")+1,50),Actuals!$F:$F,"JPY")*$E$5+SUMIFS(Actuals!$G:$G,Actuals!$B:$B,$C$3,Actuals!$C:$C,3,Actuals!$D:$D,$B$34,Actuals!$A:$A,LEFT($D$34,FIND("|",$D$34&"|")-1),Actuals!$E:$E,MID($D$34,FIND("|",$D$34&"|")+1,50),Actuals!$F:$F,"USD")*$F$5+SUMIFS(Actuals!$G:$G,Actuals!$B:$B,$C$3,Actuals!$C:$C,3,Actuals!$D:$D,$B$34,Actuals!$A:$A,LEFT($D$34,FIND("|",$D$34&"|")-1),Actuals!$E:$E,MID($D$34,FIND("|",$D$34&"|")+1,50),Actuals!$F:$F,"EUR")*$G$5+SUMIFS(Actuals!$G:$G,Actuals!$B:$B,$C$3,Actuals!$C:$C,3,Actuals!$D:$D,$B$34,Actuals!$A:$A,LEFT($D$34,FIND("|",$D$34&"|")-1),Actuals!$E:$E,MID($D$34,FIND("|",$D$34&"|")+1,50),Actuals!$F:$F,"GBP")*$H$5) | K35: =IF(OR($B$34="",4>$C$4),"",SUMIFS(Actuals!$G:$G,Actuals!$B:$B,$C$3,Actuals!$C:$C,4,Actuals!$D:$D,$B$34,Actuals!$A:$A,LEFT($D$34,FIND("|",$D$34&"|")-1),Actuals!$E:$E,MID($D$34,FIND("|",$D$34&"|")+1,50),Actuals!$F:$F,"JPY")*$E$5+SUMIFS(Actuals!$G:$G,Actuals!$B:$B,$C$3,Actuals!$C:$C,4,Actuals!$D:$D,$B$34,Actuals!$A:$A,LEFT($D$34,FIND("|",$D$34&"|")-1),Actuals!$E:$E,MID($D$34,FIND("|",$D$34&"|")+1,50),Actuals!$F:$F,"USD")*$F$5+SUMIFS(Actuals!$G:$G,Actuals!$B:$B,$C$3,Actuals!$C:$C,4,Actuals!$D:$D,$B$34,Actuals!$A:$A,LEFT($D$34,FIND("|",$D$34&"|")-1),Actuals!$E:$E,MID($D$34,FIND("|",$D$34&"|")+1,50),Actuals!$F:$F,"EUR")*$G$5+SUMIFS(Actuals!$G:$G,Actuals!$B:$B,$C$3,Actuals!$C:$C,4,Actuals!$D:$D,$B$34,Actuals!$A:$A,LEFT($D$34,FIND("|",$D$34&"|")-1),Actuals!$E:$E,MID($D$34,FIND("|",$D$34&"|")+1,50),Actuals!$F:$F,"GBP")*$H$5) | L35: =IF(OR($B$34="",5>$C$4),"",SUMIFS(Actuals!$G:$G,Actuals!$B:$B,$C$3,Actuals!$C:$C,5,Actuals!$D:$D,$B$34,Actuals!$A:$A,LEFT($D$34,FIND("|",$D$34&"|")-1),Actuals!$E:$E,MID($D$34,FIND("|",$D$34&"|")+1,50),Actuals!$F:$F,"JPY")*$E$5+SUMIFS(Actuals!$G:$G,Actuals!$B:$B,$C$3,Actuals!$C:$C,5,Actuals!$D:$D,$B$34,Actuals!$A:$A,LEFT($D$34,FIND("|",$D$34&"|")-1),Actuals!$E:$E,MID($D$34,FIND("|",$D$34&"|")+1,50),Actuals!$F:$F,"USD")*$F$5+SUMIFS(Actuals!$G:$G,Actuals!$B:$B,$C$3,Actuals!$C:$C,5,Actuals!$D:$D,$B$34,Actuals!$A:$A,LEFT($D$34,FIND("|",$D$34&"|")-1),Actuals!$E:$E,MID($D$34,FIND("|",$D$34&"|")+1,50),Actuals!$F:$F,"EUR")*$G$5+SUMIFS(Actuals!$G:$G,Actuals!$B:$B,$C$3,Actuals!$C:$C,5,Actuals!$D:$D,$B$34,Actuals!$A:$A,LEFT($D$34,FIND("|",$D$34&"|")-1),Actuals!$E:$E,MID($D$34,FIND("|",$D$34&"|")+1,50),Actuals!$F:$F,"GBP")*$H$5) | M35: =IF(OR($B$34="",6>$C$4),"",SUMIFS(Actuals!$G:$G,Actuals!$B:$B,$C$3,Actuals!$C:$C,6,Actuals!$D:$D,$B$34,Actuals!$A:$A,LEFT($D$34,FIND("|",$D$34&"|")-1),Actuals!$E:$E,MID($D$34,FIND("|",$D$34&"|")+1,50),Actuals!$F:$F,"JPY")*$E$5+SUMIFS(Actuals!$G:$G,Actuals!$B:$B,$C$3,Actuals!$C:$C,6,Actuals!$D:$D,$B$34,Actuals!$A:$A,LEFT($D$34,FIND("|",$D$34&"|")-1),Actuals!$E:$E,MID($D$34,FIND("|",$D$34&"|")+1,50),Actuals!$F:$F,"USD")*$F$5+SUMIFS(Actuals!$G:$G,Actuals!$B:$B,$C$3,Actuals!$C:$C,6,Actuals!$D:$D,$B$34,Actuals!$A:$A,LEFT($D$34,FIND("|",$D$34&"|")-1),Actuals!$E:$E,MID($D$34,FIND("|",$D$34&"|")+1,50),Actuals!$F:$F,"EUR")*$G$5+SUMIFS(Actuals!$G:$G,Actuals!$B:$B,$C$3,Actuals!$C:$C,6,Actuals!$D:$D,$B$34,Actuals!$A:$A,LEFT($D$34,FIND("|",$D$34&"|")-1),Actuals!$E:$E,MID($D$34,FIND("|",$D$34&"|")+1,50),Actuals!$F:$F,"GBP")*$H$5) | N35: =IF(OR($B$34="",7>$C$4),"",SUMIFS(Actuals!$G:$G,Actuals!$B:$B,$C$3,Actuals!$C:$C,7,Actuals!$D:$D,$B$34,Actuals!$A:$A,LEFT($D$34,FIND("|",$D$34&"|")-1),Actuals!$E:$E,MID($D$34,FIND("|",$D$34&"|")+1,50),Actuals!$F:$F,"JPY")*$E$5+SUMIFS(Actuals!$G:$G,Actuals!$B:$B,$C$3,Actuals!$C:$C,7,Actuals!$D:$D,$B$34,Actuals!$A:$A,LEFT($D$34,FIND("|",$D$34&"|")-1),Actuals!$E:$E,MID($D$34,FIND("|",$D$34&"|")+1,50),Actuals!$F:$F,"USD")*$F$5+SUMIFS(Actuals!$G:$G,Actuals!$B:$B,$C$3,Actuals!$C:$C,7,Actuals!$D:$D,$B$34,Actuals!$A:$A,LEFT($D$34,FIND("|",$D$34&"|")-1),Actuals!$E:$E,MID($D$34,FIND("|",$D$34&"|")+1,50),Actuals!$F:$F,"EUR")*$G$5+SUMIFS(Actuals!$G:$G,Actuals!$B:$B,$C$3,Actuals!$C:$C,7,Actuals!$D:$D,$B$34,Actuals!$A:$A,LEFT($D$34,FIND("|",$D$34&"|")-1),Actuals!$E:$E,MID($D$34,FIND("|",$D$34&"|")+1,50),Actuals!$F:$F,"GBP")*$H$5) | O35: =IF(OR($B$34="",8>$C$4),"",SUMIFS(Actuals!$G:$G,Actuals!$B:$B,$C$3,Actuals!$C:$C,8,Actuals!$D:$D,$B$34,Actuals!$A:$A,LEFT($D$34,FIND("|",$D$34&"|")-1),Actuals!$E:$E,MID($D$34,FIND("|",$D$34&"|")+1,50),Actuals!$F:$F,"JPY")*$E$5+SUMIFS(Actuals!$G:$G,Actuals!$B:$B,$C$3,Actuals!$C:$C,8,Actuals!$D:$D,$B$34,Actuals!$A:$A,LEFT($D$34,FIND("|",$D$34&"|")-1),Actuals!$E:$E,MID($D$34,FIND("|",$D$34&"|")+1,50),Actuals!$F:$F,"USD")*$F$5+SUMIFS(Actuals!$G:$G,Actuals!$B:$B,$C$3,Actuals!$C:$C,8,Actuals!$D:$D,$B$34,Actuals!$A:$A,LEFT($D$34,FIND("|",$D$34&"|")-1),Actuals!$E:$E,MID($D$34,FIND("|",$D$34&"|")+1,50),Actuals!$F:$F,"EUR")*$G$5+SUMIFS(Actuals!$G:$G,Actuals!$B:$B,$C$3,Actuals!$C:$C,8,Actuals!$D:$D,$B$34,Actuals!$A:$A,LEFT($D$34,FIND("|",$D$34&"|")-1),Actuals!$E:$E,MID($D$34,FIND("|",$D$34&"|")+1,50),Actuals!$F:$F,"GBP")*$H$5) | P35: =IF(OR($B$34="",9>$C$4),"",SUMIFS(Actuals!$G:$G,Actuals!$B:$B,$C$3,Actuals!$C:$C,9,Actuals!$D:$D,$B$34,Actuals!$A:$A,LEFT($D$34,FIND("|",$D$34&"|")-1),Actuals!$E:$E,MID($D$34,FIND("|",$D$34&"|")+1,50),Actuals!$F:$F,"JPY")*$E$5+SUMIFS(Actuals!$G:$G,Actuals!$B:$B,$C$3,Actuals!$C:$C,9,Actuals!$D:$D,$B$34,Actuals!$A:$A,LEFT($D$34,FIND("|",$D$34&"|")-1),Actuals!$E:$E,MID($D$34,FIND("|",$D$34&"|")+1,50),Actuals!$F:$F,"USD")*$F$5+SUMIFS(Actuals!$G:$G,Actuals!$B:$B,$C$3,Actuals!$C:$C,9,Actuals!$D:$D,$B$34,Actuals!$A:$A,LEFT($D$34,FIND("|",$D$34&"|")-1),Actuals!$E:$E,MID($D$34,FIND("|",$D$34&"|")+1,50),Actuals!$F:$F,"EUR")*$G$5+SUMIFS(Actuals!$G:$G,Actuals!$B:$B,$C$3,Actuals!$C:$C,9,Actuals!$D:$D,$B$34,Actuals!$A:$A,LEFT($D$34,FIND("|",$D$34&"|")-1),Actuals!$E:$E,MID($D$34,FIND("|",$D$34&"|")+1,50),Actuals!$F:$F,"GBP")*$H$5) | Q35: =IF(OR($B$34="",10>$C$4),"",SUMIFS(Actuals!$G:$G,Actuals!$B:$B,$C$3,Actuals!$C:$C,10,Actuals!$D:$D,$B$34,Actuals!$A:$A,LEFT($D$34,FIND("|",$D$34&"|")-1),Actuals!$E:$E,MID($D$34,FIND("|",$D$34&"|")+1,50),Actuals!$F:$F,"JPY")*$E$5+SUMIFS(Actuals!$G:$G,Actuals!$B:$B,$C$3,Actuals!$C:$C,10,Actuals!$D:$D,$B$34,Actuals!$A:$A,LEFT($D$34,FIND("|",$D$34&"|")-1),Actuals!$E:$E,MID($D$34,FIND("|",$D$34&"|")+1,50),Actuals!$F:$F,"USD")*$F$5+SUMIFS(Actuals!$G:$G,Actuals!$B:$B,$C$3,Actuals!$C:$C,10,Actuals!$D:$D,$B$34,Actuals!$A:$A,LEFT($D$34,FIND("|",$D$34&"|")-1),Actuals!$E:$E,MID($D$34,FIND("|",$D$34&"|")+1,50),Actuals!$F:$F,"EUR")*$G$5+SUMIFS(Actuals!$G:$G,Actuals!$B:$B,$C$3,Actuals!$C:$C,10,Actuals!$D:$D,$B$34,Actuals!$A:$A,LEFT($D$34,FIND("|",$D$34&"|")-1),Actuals!$E:$E,MID($D$34,FIND("|",$D$34&"|")+1,50),Actuals!$F:$F,"GBP")*$H$5) | R35: =IF(OR($B$34="",11>$C$4),"",SUMIFS(Actuals!$G:$G,Actuals!$B:$B,$C$3,Actuals!$C:$C,11,Actuals!$D:$D,$B$34,Actuals!$A:$A,LEFT($D$34,FIND("|",$D$34&"|")-1),Actuals!$E:$E,MID($D$34,FIND("|",$D$34&"|")+1,50),Actuals!$F:$F,"JPY")*$E$5+SUMIFS(Actuals!$G:$G,Actuals!$B:$B,$C$3,Actuals!$C:$C,11,Actuals!$D:$D,$B$34,Actuals!$A:$A,LEFT($D$34,FIND("|",$D$34&"|")-1),Actuals!$E:$E,MID($D$34,FIND("|",$D$34&"|")+1,50),Actuals!$F:$F,"USD")*$F$5+SUMIFS(Actuals!$G:$G,Actuals!$B:$B,$C$3,Actuals!$C:$C,11,Actuals!$D:$D,$B$34,Actuals!$A:$A,LEFT($D$34,FIND("|",$D$34&"|")-1),Actuals!$E:$E,MID($D$34,FIND("|",$D$34&"|")+1,50),Actuals!$F:$F,"EUR")*$G$5+SUMIFS(Actuals!$G:$G,Actuals!$B:$B,$C$3,Actuals!$C:$C,11,Actuals!$D:$D,$B$34,Actuals!$A:$A,LEFT($D$34,FIND("|",$D$34&"|")-1),Actuals!$E:$E,MID($D$34,FIND("|",$D$34&"|")+1,50),Actuals!$F:$F,"GBP")*$H$5) | S35: =IF(OR($B$34="",12>$C$4),"",SUMIFS(Actuals!$G:$G,Actuals!$B:$B,$C$3,Actuals!$C:$C,12,Actuals!$D:$D,$B$34,Actuals!$A:$A,LEFT($D$34,FIND("|",$D$34&"|")-1),Actuals!$E:$E,MID($D$34,FIND("|",$D$34&"|")+1,50),Actuals!$F:$F,"JPY")*$E$5+SUMIFS(Actuals!$G:$G,Actuals!$B:$B,$C$3,Actuals!$C:$C,12,Actuals!$D:$D,$B$34,Actuals!$A:$A,LEFT($D$34,FIND("|",$D$34&"|")-1),Actuals!$E:$E,MID($D$34,FIND("|",$D$34&"|")+1,50),Actuals!$F:$F,"USD")*$F$5+SUMIFS(Actuals!$G:$G,Actuals!$B:$B,$C$3,Actuals!$C:$C,12,Actuals!$D:$D,$B$34,Actuals!$A:$A,LEFT($D$34,FIND("|",$D$34&"|")-1),Actuals!$E:$E,MID($D$34,FIND("|",$D$34&"|")+1,50),Actuals!$F:$F,"EUR")*$G$5+SUMIFS(Actuals!$G:$G,Actuals!$B:$B,$C$3,Actuals!$C:$C,12,Actuals!$D:$D,$B$34,Actuals!$A:$A,LEFT($D$34,FIND("|",$D$34&"|")-1),Actuals!$E:$E,MID($D$34,FIND("|",$D$34&"|")+1,50),Actuals!$F:$F,"GBP")*$H$5) | T35: =IF($B$34="","",SUMIF($H$7:$S$7,"<="&$C$4,$H35:$S35)) | X35: =IF($B35="","",IFERROR(INDEX(Cost_Centers!$E:$E,MATCH($B35,Cost_Centers!$A:$A,0)),"(unknown)")) | Y35: =IF($B35="","",IFERROR(INDEX(Cost_Centers!$D:$D,MATCH($B35,Cost_Centers!$A:$A,0)),"(unknown)")) | Z35: =IF(OR($B35="",$G35<>"Variance vs Budget"),"",ABS(N($V35))+ROW()/1000000000)
A36: =IF(A$34="","",A$34) | B36: =IF(B$34="","",B$34) | C36: =IF(C$34="","",C$34) | D36: =IF(D$34="","",D$34) | E36: =IF(E$34="","",E$34) | F36: =IF(F$34="","",F$34) | G36: Variance vs Budget | H36: =IF(OR($B$34="",1>$C$4),"",N(H35)-H34) | I36: =IF(OR($B$34="",2>$C$4),"",N(I35)-I34) | J36: =IF(OR($B$34="",3>$C$4),"",N(J35)-J34) | K36: =IF(OR($B$34="",4>$C$4),"",N(K35)-K34) | L36: =IF(OR($B$34="",5>$C$4),"",N(L35)-L34) | M36: =IF(OR($B$34="",6>$C$4),"",N(M35)-M34) | N36: =IF(OR($B$34="",7>$C$4),"",N(N35)-N34) | O36: =IF(OR($B$34="",8>$C$4),"",N(O35)-O34) | P36: =IF(OR($B$34="",9>$C$4),"",N(P35)-P34) | Q36: =IF(OR($B$34="",10>$C$4),"",N(Q35)-Q34) | R36: =IF(OR($B$34="",11>$C$4),"",N(R35)-R34) | S36: =IF(OR($B$34="",12>$C$4),"",N(S35)-S34) | T36: =IF($B$34="","",T35-T34) | U36: =IF($B$34="","",U38-U34) | V36: =IF($B$34="","",V38-V34) | X36: =IF($B36="","",IFERROR(INDEX(Cost_Centers!$E:$E,MATCH($B36,Cost_Centers!$A:$A,0)),"(unknown)")) | Y36: =IF($B36="","",IFERROR(INDEX(Cost_Centers!$D:$D,MATCH($B36,Cost_Centers!$A:$A,0)),"(unknown)")) | Z36: =IF(OR($B36="",$G36<>"Variance vs Budget"),"",ABS(N($V36))+ROW()/1000000000)
A37: =IF(A$34="","",A$34) | B37: =IF(B$34="","",B$34) | C37: =IF(C$34="","",C$34) | D37: =IF(D$34="","",D$34) | E37: =IF(E$34="","",E$34) | F37: =IF(F$34="","",F$34) | G37: Forecast (input) | X37: =IF($B37="","",IFERROR(INDEX(Cost_Centers!$E:$E,MATCH($B37,Cost_Centers!$A:$A,0)),"(unknown)")) | Y37: =IF($B37="","",IFERROR(INDEX(Cost_Centers!$D:$D,MATCH($B37,Cost_Centers!$A:$A,0)),"(unknown)")) | Z37: =IF(OR($B37="",$G37<>"Variance vs Budget"),"",ABS(N($V37))+ROW()/1000000000)
A38: =IF(A$34="","",A$34) | B38: =IF(B$34="","",B$34) | C38: =IF(C$34="","",C$34) | D38: =IF(D$34="","",D$34) | E38: =IF(E$34="","",E$34) | F38: =IF(F$34="","",F$34) | G38: Actual + Forecast | H38: =IF($B$34="","",IF(1<=$C$4,N(H35),IF(H37="",H34,H37))) | I38: =IF($B$34="","",IF(2<=$C$4,N(I35),IF(I37="",I34,I37))) | J38: =IF($B$34="","",IF(3<=$C$4,N(J35),IF(J37="",J34,J37))) | K38: =IF($B$34="","",IF(4<=$C$4,N(K35),IF(K37="",K34,K37))) | L38: =IF($B$34="","",IF(5<=$C$4,N(L35),IF(L37="",L34,L37))) | M38: =IF($B$34="","",IF(6<=$C$4,N(M35),IF(M37="",M34,M37))) | N38: =IF($B$34="","",IF(7<=$C$4,N(N35),IF(N37="",N34,N37))) | O38: =IF($B$34="","",IF(8<=$C$4,N(O35),IF(O37="",O34,O37))) | P38: =IF($B$34="","",IF(9<=$C$4,N(P35),IF(P37="",P34,P37))) | Q38: =IF($B$34="","",IF(10<=$C$4,N(Q35),IF(Q37="",Q34,Q37))) | R38: =IF($B$34="","",IF(11<=$C$4,N(R35),IF(R37="",R34,R37))) | S38: =IF($B$34="","",IF(12<=$C$4,N(S35),IF(S37="",S34,S37))) | T38: =IF($B$34="","",SUMIF($H$7:$S$7,"<="&$C$4,$H38:$S38)) | U38: =IF($B$34="","",SUMIF($H$7:$S$7,">"&$C$4,$H38:$S38)) | V38: =IF($B$34="","",SUM($H38:$S38)) | X38: =IF($B38="","",IFERROR(INDEX(Cost_Centers!$E:$E,MATCH($B38,Cost_Centers!$A:$A,0)),"(unknown)")) | Y38: =IF($B38="","",IFERROR(INDEX(Cost_Centers!$D:$D,MATCH($B38,Cost_Centers!$A:$A,0)),"(unknown)")) | Z38: =IF(OR($B38="",$G38<>"Variance vs Budget"),"",ABS(N($V38))+ROW()/1000000000)
A39: =IF(A$34="","",A$34) | B39: =IF(B$34="","",B$34) | C39: =IF(C$34="","",C$34) | D39: =IF(D$34="","",D$34) | E39: =IF(E$34="","",E$34) | F39: =IF(F$34="","",F$34) | G39: Prior Month Forecast | H39: =IF($B$34="","",IF(COUNTIFS(Prior_Forecast!$A:$A,$B$34,Prior_Forecast!$B:$B,$D$34)>0,SUMIFS(Prior_Forecast!$C:$C,Prior_Forecast!$A:$A,$B$34,Prior_Forecast!$B:$B,$D$34),"")) | I39: =IF($B$34="","",IF(COUNTIFS(Prior_Forecast!$A:$A,$B$34,Prior_Forecast!$B:$B,$D$34)>0,SUMIFS(Prior_Forecast!$D:$D,Prior_Forecast!$A:$A,$B$34,Prior_Forecast!$B:$B,$D$34),"")) | J39: =IF($B$34="","",IF(COUNTIFS(Prior_Forecast!$A:$A,$B$34,Prior_Forecast!$B:$B,$D$34)>0,SUMIFS(Prior_Forecast!$E:$E,Prior_Forecast!$A:$A,$B$34,Prior_Forecast!$B:$B,$D$34),"")) | K39: =IF($B$34="","",IF(COUNTIFS(Prior_Forecast!$A:$A,$B$34,Prior_Forecast!$B:$B,$D$34)>0,SUMIFS(Prior_Forecast!$F:$F,Prior_Forecast!$A:$A,$B$34,Prior_Forecast!$B:$B,$D$34),"")) | L39: =IF($B$34="","",IF(COUNTIFS(Prior_Forecast!$A:$A,$B$34,Prior_Forecast!$B:$B,$D$34)>0,SUMIFS(Prior_Forecast!$G:$G,Prior_Forecast!$A:$A,$B$34,Prior_Forecast!$B:$B,$D$34),"")) | M39: =IF($B$34="","",IF(COUNTIFS(Prior_Forecast!$A:$A,$B$34,Prior_Forecast!$B:$B,$D$34)>0,SUMIFS(Prior_Forecast!$H:$H,Prior_Forecast!$A:$A,$B$34,Prior_Forecast!$B:$B,$D$34),"")) | N39: =IF($B$34="","",IF(COUNTIFS(Prior_Forecast!$A:$A,$B$34,Prior_Forecast!$B:$B,$D$34)>0,SUMIFS(Prior_Forecast!$I:$I,Prior_Forecast!$A:$A,$B$34,Prior_Forecast!$B:$B,$D$34),"")) | O39: =IF($B$34="","",IF(COUNTIFS(Prior_Forecast!$A:$A,$B$34,Prior_Forecast!$B:$B,$D$34)>0,SUMIFS(Prior_Forecast!$J:$J,Prior_Forecast!$A:$A,$B$34,Prior_Forecast!$B:$B,$D$34),"")) | P39: =IF($B$34="","",IF(COUNTIFS(Prior_Forecast!$A:$A,$B$34,Prior_Forecast!$B:$B,$D$34)>0,SUMIFS(Prior_Forecast!$K:$K,Prior_Forecast!$A:$A,$B$34,Prior_Forecast!$B:$B,$D$34),"")) | Q39: =IF($B$34="","",IF(COUNTIFS(Prior_Forecast!$A:$A,$B$34,Prior_Forecast!$B:$B,$D$34)>0,SUMIFS(Prior_Forecast!$L:$L,Prior_Forecast!$A:$A,$B$34,Prior_Forecast!$B:$B,$D$34),"")) | R39: =IF($B$34="","",IF(COUNTIFS(Prior_Forecast!$A:$A,$B$34,Prior_Forecast!$B:$B,$D$34)>0,SUMIFS(Prior_Forecast!$M:$M,Prior_Forecast!$A:$A,$B$34,Prior_Forecast!$B:$B,$D$34),"")) | S39: =IF($B$34="","",IF(COUNTIFS(Prior_Forecast!$A:$A,$B$34,Prior_Forecast!$B:$B,$D$34)>0,SUMIFS(Prior_Forecast!$N:$N,Prior_Forecast!$A:$A,$B$34,Prior_Forecast!$B:$B,$D$34),"")) | T39: =IF($B$34="","",IF(COUNTIFS(Prior_Forecast!$A:$A,$B$34,Prior_Forecast!$B:$B,$D$34)>0,SUMIFS(Prior_Forecast!$O:$O,Prior_Forecast!$A:$A,$B$34,Prior_Forecast!$B:$B,$D$34),"")) | U39: =IF($B$34="","",IF(COUNTIFS(Prior_Forecast!$A:$A,$B$34,Prior_Forecast!$B:$B,$D$34)>0,SUMIFS(Prior_Forecast!$P:$P,Prior_Forecast!$A:$A,$B$34,Prior_Forecast!$B:$B,$D$34),"")) | V39: =IF($B$34="","",IF(COUNTIFS(Prior_Forecast!$A:$A,$B$34,Prior_Forecast!$B:$B,$D$34)>0,SUMIFS(Prior_Forecast!$Q:$Q,Prior_Forecast!$A:$A,$B$34,Prior_Forecast!$B:$B,$D$34),"")) | X39: =IF($B39="","",IFERROR(INDEX(Cost_Centers!$E:$E,MATCH($B39,Cost_Centers!$A:$A,0)),"(unknown)")) | Y39: =IF($B39="","",IFERROR(INDEX(Cost_Centers!$D:$D,MATCH($B39,Cost_Centers!$A:$A,0)),"(unknown)")) | Z39: =IF(OR($B39="",$G39<>"Variance vs Budget"),"",ABS(N($V39))+ROW()/1000000000)
A40: =IF(A$34="","",A$34) | B40: =IF(B$34="","",B$34) | C40: =IF(C$34="","",C$34) | D40: =IF(D$34="","",D$34) | E40: =IF(E$34="","",E$34) | F40: =IF(F$34="","",F$34) | G40: Variance vs Prior Month | H40: =IF(OR($B$34="",H39=""),"",H38-H39) | I40: =IF(OR($B$34="",I39=""),"",I38-I39) | J40: =IF(OR($B$34="",J39=""),"",J38-J39) | K40: =IF(OR($B$34="",K39=""),"",K38-K39) | L40: =IF(OR($B$34="",L39=""),"",L38-L39) | M40: =IF(OR($B$34="",M39=""),"",M38-M39) | N40: =IF(OR($B$34="",N39=""),"",N38-N39) | O40: =IF(OR($B$34="",O39=""),"",O38-O39) | ... V40: =IF(OR($B$34="",V39=""),"",V38-V39) | X40: =IF($B40="","",IFERROR(INDEX(Cost_Centers!$E:$E,MATCH($B40,Cost_Centers!$A:$A,0)),"(unknown)")) | Y40: =IF($B40="","",IFERROR(INDEX(Cost_Centers!$D:$D,MATCH($B40,Cost_Centers!$A:$A,0)),"(unknown)")) | Z40: =IF(OR($B40="",$G40<>"Variance vs Budget"),"",ABS(N($V40))+ROW()/1000000000)
A41: =IF(A$34="","",A$34) | B41: =IF(B$34="","",B$34) | C41: =IF(C$34="","",C$34) | D41: =IF(D$34="","",D$34) | E41: =IF(E$34="","",E$34) | F41: =IF(F$34="","",F$34) | G41: Rationale | X41: =IF($B41="","",IFERROR(INDEX(Cost_Centers!$E:$E,MATCH($B41,Cost_Centers!$A:$A,0)),"(unknown)")) | Y41: =IF($B41="","",IFERROR(INDEX(Cost_Centers!$D:$D,MATCH($B41,Cost_Centers!$A:$A,0)),"(unknown)")) | Z41: =IF(OR($B41="",$G41<>"Variance vs Budget"),"",ABS(N($V41))+ROW()/1000000000)
A42: =IF($D$42="","",LEFT($D$42,FIND("|",$D$42&"|")-1)) | C42: =IF($B$42="","",IFERROR(INDEX(Cost_Centers!$B:$B,MATCH($B$42,Cost_Centers!$A:$A,0)),"(not in master)")) | E42: =IF($D$42="","",IFERROR(INDEX(Accounts!$D:$D,MATCH($D$42,Accounts!$A:$A,0)),"(not in master)")) | G42: Budget | H42: =IF($B$42="","",SUMIFS(Opex_Budget!$O:$O,Opex_Budget!$A:$A,$C$3,Opex_Budget!$E:$E,$B$42,Opex_Budget!$F:$F,$D$42,Opex_Budget!$N:$N,"JPY")*$E$5+SUMIFS(Opex_Budget!$O:$O,Opex_Budget!$A:$A,$C$3,Opex_Budget!$E:$E,$B$42,Opex_Budget!$F:$F,$D$42,Opex_Budget!$N:$N,"USD")*$F$5+SUMIFS(Opex_Budget!$O:$O,Opex_Budget!$A:$A,$C$3,Opex_Budget!$E:$E,$B$42,Opex_Budget!$F:$F,$D$42,Opex_Budget!$N:$N,"EUR")*$G$5+SUMIFS(Opex_Budget!$O:$O,Opex_Budget!$A:$A,$C$3,Opex_Budget!$E:$E,$B$42,Opex_Budget!$F:$F,$D$42,Opex_Budget!$N:$N,"GBP")*$H$5) | I42: =IF($B$42="","",SUMIFS(Opex_Budget!$P:$P,Opex_Budget!$A:$A,$C$3,Opex_Budget!$E:$E,$B$42,Opex_Budget!$F:$F,$D$42,Opex_Budget!$N:$N,"JPY")*$E$5+SUMIFS(Opex_Budget!$P:$P,Opex_Budget!$A:$A,$C$3,Opex_Budget!$E:$E,$B$42,Opex_Budget!$F:$F,$D$42,Opex_Budget!$N:$N,"USD")*$F$5+SUMIFS(Opex_Budget!$P:$P,Opex_Budget!$A:$A,$C$3,Opex_Budget!$E:$E,$B$42,Opex_Budget!$F:$F,$D$42,Opex_Budget!$N:$N,"EUR")*$G$5+SUMIFS(Opex_Budget!$P:$P,Opex_Budget!$A:$A,$C$3,Opex_Budget!$E:$E,$B$42,Opex_Budget!$F:$F,$D$42,Opex_Budget!$N:$N,"GBP")*$H$5) | J42: =IF($B$42="","",SUMIFS(Opex_Budget!$Q:$Q,Opex_Budget!$A:$A,$C$3,Opex_Budget!$E:$E,$B$42,Opex_Budget!$F:$F,$D$42,Opex_Budget!$N:$N,"JPY")*$E$5+SUMIFS(Opex_Budget!$Q:$Q,Opex_Budget!$A:$A,$C$3,Opex_Budget!$E:$E,$B$42,Opex_Budget!$F:$F,$D$42,Opex_Budget!$N:$N,"USD")*$F$5+SUMIFS(Opex_Budget!$Q:$Q,Opex_Budget!$A:$A,$C$3,Opex_Budget!$E:$E,$B$42,Opex_Budget!$F:$F,$D$42,Opex_Budget!$N:$N,"EUR")*$G$5+SUMIFS(Opex_Budget!$Q:$Q,Opex_Budget!$A:$A,$C$3,Opex_Budget!$E:$E,$B$42,Opex_Budget!$F:$F,$D$42,Opex_Budget!$N:$N,"GBP")*$H$5) | K42: =IF($B$42="","",SUMIFS(Opex_Budget!$R:$R,Opex_Budget!$A:$A,$C$3,Opex_Budget!$E:$E,$B$42,Opex_Budget!$F:$F,$D$42,Opex_Budget!$N:$N,"JPY")*$E$5+SUMIFS(Opex_Budget!$R:$R,Opex_Budget!$A:$A,$C$3,Opex_Budget!$E:$E,$B$42,Opex_Budget!$F:$F,$D$42,Opex_Budget!$N:$N,"USD")*$F$5+SUMIFS(Opex_Budget!$R:$R,Opex_Budget!$A:$A,$C$3,Opex_Budget!$E:$E,$B$42,Opex_Budget!$F:$F,$D$42,Opex_Budget!$N:$N,"EUR")*$G$5+SUMIFS(Opex_Budget!$R:$R,Opex_Budget!$A:$A,$C$3,Opex_Budget!$E:$E,$B$42,Opex_Budget!$F:$F,$D$42,Opex_Budget!$N:$N,"GBP")*$H$5) | L42: =IF($B$42="","",SUMIFS(Opex_Budget!$S:$S,Opex_Budget!$A:$A,$C$3,Opex_Budget!$E:$E,$B$42,Opex_Budget!$F:$F,$D$42,Opex_Budget!$N:$N,"JPY")*$E$5+SUMIFS(Opex_Budget!$S:$S,Opex_Budget!$A:$A,$C$3,Opex_Budget!$E:$E,$B$42,Opex_Budget!$F:$F,$D$42,Opex_Budget!$N:$N,"USD")*$F$5+SUMIFS(Opex_Budget!$S:$S,Opex_Budget!$A:$A,$C$3,Opex_Budget!$E:$E,$B$42,Opex_Budget!$F:$F,$D$42,Opex_Budget!$N:$N,"EUR")*$G$5+SUMIFS(Opex_Budget!$S:$S,Opex_Budget!$A:$A,$C$3,Opex_Budget!$E:$E,$B$42,Opex_Budget!$F:$F,$D$42,Opex_Budget!$N:$N,"GBP")*$H$5) | M42: =IF($B$42="","",SUMIFS(Opex_Budget!$T:$T,Opex_Budget!$A:$A,$C$3,Opex_Budget!$E:$E,$B$42,Opex_Budget!$F:$F,$D$42,Opex_Budget!$N:$N,"JPY")*$E$5+SUMIFS(Opex_Budget!$T:$T,Opex_Budget!$A:$A,$C$3,Opex_Budget!$E:$E,$B$42,Opex_Budget!$F:$F,$D$42,Opex_Budget!$N:$N,"USD")*$F$5+SUMIFS(Opex_Budget!$T:$T,Opex_Budget!$A:$A,$C$3,Opex_Budget!$E:$E,$B$42,Opex_Budget!$F:$F,$D$42,Opex_Budget!$N:$N,"EUR")*$G$5+SUMIFS(Opex_Budget!$T:$T,Opex_Budget!$A:$A,$C$3,Opex_Budget!$E:$E,$B$42,Opex_Budget!$F:$F,$D$42,Opex_Budget!$N:$N,"GBP")*$H$5) | N42: =IF($B$42="","",SUMIFS(Opex_Budget!$U:$U,Opex_Budget!$A:$A,$C$3,Opex_Budget!$E:$E,$B$42,Opex_Budget!$F:$F,$D$42,Opex_Budget!$N:$N,"JPY")*$E$5+SUMIFS(Opex_Budget!$U:$U,Opex_Budget!$A:$A,$C$3,Opex_Budget!$E:$E,$B$42,Opex_Budget!$F:$F,$D$42,Opex_Budget!$N:$N,"USD")*$F$5+SUMIFS(Opex_Budget!$U:$U,Opex_Budget!$A:$A,$C$3,Opex_Budget!$E:$E,$B$42,Opex_Budget!$F:$F,$D$42,Opex_Budget!$N:$N,"EUR")*$G$5+SUMIFS(Opex_Budget!$U:$U,Opex_Budget!$A:$A,$C$3,Opex_Budget!$E:$E,$B$42,Opex_Budget!$F:$F,$D$42,Opex_Budget!$N:$N,"GBP")*$H$5) | O42: =IF($B$42="","",SUMIFS(Opex_Budget!$V:$V,Opex_Budget!$A:$A,$C$3,Opex_Budget!$E:$E,$B$42,Opex_Budget!$F:$F,$D$42,Opex_Budget!$N:$N,"JPY")*$E$5+SUMIFS(Opex_Budget!$V:$V,Opex_Budget!$A:$A,$C$3,Opex_Budget!$E:$E,$B$42,Opex_Budget!$F:$F,$D$42,Opex_Budget!$N:$N,"USD")*$F$5+SUMIFS(Opex_Budget!$V:$V,Opex_Budget!$A:$A,$C$3,Opex_Budget!$E:$E,$B$42,Opex_Budget!$F:$F,$D$42,Opex_Budget!$N:$N,"EUR")*$G$5+SUMIFS(Opex_Budget!$V:$V,Opex_Budget!$A:$A,$C$3,Opex_Budget!$E:$E,$B$42,Opex_Budget!$F:$F,$D$42,Opex_Budget!$N:$N,"GBP")*$H$5) | P42: =IF($B$42="","",SUMIFS(Opex_Budget!$W:$W,Opex_Budget!$A:$A,$C$3,Opex_Budget!$E:$E,$B$42,Opex_Budget!$F:$F,$D$42,Opex_Budget!$N:$N,"JPY")*$E$5+SUMIFS(Opex_Budget!$W:$W,Opex_Budget!$A:$A,$C$3,Opex_Budget!$E:$E,$B$42,Opex_Budget!$F:$F,$D$42,Opex_Budget!$N:$N,"USD")*$F$5+SUMIFS(Opex_Budget!$W:$W,Opex_Budget!$A:$A,$C$3,Opex_Budget!$E:$E,$B$42,Opex_Budget!$F:$F,$D$42,Opex_Budget!$N:$N,"EUR")*$G$5+SUMIFS(Opex_Budget!$W:$W,Opex_Budget!$A:$A,$C$3,Opex_Budget!$E:$E,$B$42,Opex_Budget!$F:$F,$D$42,Opex_Budget!$N:$N,"GBP")*$H$5) | Q42: =IF($B$42="","",SUMIFS(Opex_Budget!$X:$X,Opex_Budget!$A:$A,$C$3,Opex_Budget!$E:$E,$B$42,Opex_Budget!$F:$F,$D$42,Opex_Budget!$N:$N,"JPY")*$E$5+SUMIFS(Opex_Budget!$X:$X,Opex_Budget!$A:$A,$C$3,Opex_Budget!$E:$E,$B$42,Opex_Budget!$F:$F,$D$42,Opex_Budget!$N:$N,"USD")*$F$5+SUMIFS(Opex_Budget!$X:$X,Opex_Budget!$A:$A,$C$3,Opex_Budget!$E:$E,$B$42,Opex_Budget!$F:$F,$D$42,Opex_Budget!$N:$N,"EUR")*$G$5+SUMIFS(Opex_Budget!$X:$X,Opex_Budget!$A:$A,$C$3,Opex_Budget!$E:$E,$B$42,Opex_Budget!$F:$F,$D$42,Opex_Budget!$N:$N,"GBP")*$H$5) | R42: =IF($B$42="","",SUMIFS(Opex_Budget!$Y:$Y,Opex_Budget!$A:$A,$C$3,Opex_Budget!$E:$E,$B$42,Opex_Budget!$F:$F,$D$42,Opex_Budget!$N:$N,"JPY")*$E$5+SUMIFS(Opex_Budget!$Y:$Y,Opex_Budget!$A:$A,$C$3,Opex_Budget!$E:$E,$B$42,Opex_Budget!$F:$F,$D$42,Opex_Budget!$N:$N,"USD")*$F$5+SUMIFS(Opex_Budget!$Y:$Y,Opex_Budget!$A:$A,$C$3,Opex_Budget!$E:$E,$B$42,Opex_Budget!$F:$F,$D$42,Opex_Budget!$N:$N,"EUR")*$G$5+SUMIFS(Opex_Budget!$Y:$Y,Opex_Budget!$A:$A,$C$3,Opex_Budget!$E:$E,$B$42,Opex_Budget!$F:$F,$D$42,Opex_Budget!$N:$N,"GBP")*$H$5) | S42: =IF($B$42="","",SUMIFS(Opex_Budget!$Z:$Z,Opex_Budget!$A:$A,$C$3,Opex_Budget!$E:$E,$B$42,Opex_Budget!$F:$F,$D$42,Opex_Budget!$N:$N,"JPY")*$E$5+SUMIFS(Opex_Budget!$Z:$Z,Opex_Budget!$A:$A,$C$3,Opex_Budget!$E:$E,$B$42,Opex_Budget!$F:$F,$D$42,Opex_Budget!$N:$N,"USD")*$F$5+SUMIFS(Opex_Budget!$Z:$Z,Opex_Budget!$A:$A,$C$3,Opex_Budget!$E:$E,$B$42,Opex_Budget!$F:$F,$D$42,Opex_Budget!$N:$N,"EUR")*$G$5+SUMIFS(Opex_Budget!$Z:$Z,Opex_Budget!$A:$A,$C$3,Opex_Budget!$E:$E,$B$42,Opex_Budget!$F:$F,$D$42,Opex_Budget!$N:$N,"GBP")*$H$5) | T42: =IF($B$42="","",SUMIF($H$7:$S$7,"<="&$C$4,$H42:$S42)) | U42: =IF($B$42="","",SUMIF($H$7:$S$7,">"&$C$4,$H42:$S42)) | V42: =IF($B$42="","",SUM($H42:$S42)) | X42: =IF($B42="","",IFERROR(INDEX(Cost_Centers!$E:$E,MATCH($B42,Cost_Centers!$A:$A,0)),"(unknown)")) | Y42: =IF($B42="","",IFERROR(INDEX(Cost_Centers!$D:$D,MATCH($B42,Cost_Centers!$A:$A,0)),"(unknown)")) | Z42: =IF(OR($B42="",$G42<>"Variance vs Budget"),"",ABS(N($V42))+ROW()/1000000000)
A43: =IF(A$42="","",A$42) | B43: =IF(B$42="","",B$42) | C43: =IF(C$42="","",C$42) | D43: =IF(D$42="","",D$42) | E43: =IF(E$42="","",E$42) | F43: =IF(F$42="","",F$42) | G43: Actual | H43: =IF(OR($B$42="",1>$C$4),"",SUMIFS(Actuals!$G:$G,Actuals!$B:$B,$C$3,Actuals!$C:$C,1,Actuals!$D:$D,$B$42,Actuals!$A:$A,LEFT($D$42,FIND("|",$D$42&"|")-1),Actuals!$E:$E,MID($D$42,FIND("|",$D$42&"|")+1,50),Actuals!$F:$F,"JPY")*$E$5+SUMIFS(Actuals!$G:$G,Actuals!$B:$B,$C$3,Actuals!$C:$C,1,Actuals!$D:$D,$B$42,Actuals!$A:$A,LEFT($D$42,FIND("|",$D$42&"|")-1),Actuals!$E:$E,MID($D$42,FIND("|",$D$42&"|")+1,50),Actuals!$F:$F,"USD")*$F$5+SUMIFS(Actuals!$G:$G,Actuals!$B:$B,$C$3,Actuals!$C:$C,1,Actuals!$D:$D,$B$42,Actuals!$A:$A,LEFT($D$42,FIND("|",$D$42&"|")-1),Actuals!$E:$E,MID($D$42,FIND("|",$D$42&"|")+1,50),Actuals!$F:$F,"EUR")*$G$5+SUMIFS(Actuals!$G:$G,Actuals!$B:$B,$C$3,Actuals!$C:$C,1,Actuals!$D:$D,$B$42,Actuals!$A:$A,LEFT($D$42,FIND("|",$D$42&"|")-1),Actuals!$E:$E,MID($D$42,FIND("|",$D$42&"|")+1,50),Actuals!$F:$F,"GBP")*$H$5) | I43: =IF(OR($B$42="",2>$C$4),"",SUMIFS(Actuals!$G:$G,Actuals!$B:$B,$C$3,Actuals!$C:$C,2,Actuals!$D:$D,$B$42,Actuals!$A:$A,LEFT($D$42,FIND("|",$D$42&"|")-1),Actuals!$E:$E,MID($D$42,FIND("|",$D$42&"|")+1,50),Actuals!$F:$F,"JPY")*$E$5+SUMIFS(Actuals!$G:$G,Actuals!$B:$B,$C$3,Actuals!$C:$C,2,Actuals!$D:$D,$B$42,Actuals!$A:$A,LEFT($D$42,FIND("|",$D$42&"|")-1),Actuals!$E:$E,MID($D$42,FIND("|",$D$42&"|")+1,50),Actuals!$F:$F,"USD")*$F$5+SUMIFS(Actuals!$G:$G,Actuals!$B:$B,$C$3,Actuals!$C:$C,2,Actuals!$D:$D,$B$42,Actuals!$A:$A,LEFT($D$42,FIND("|",$D$42&"|")-1),Actuals!$E:$E,MID($D$42,FIND("|",$D$42&"|")+1,50),Actuals!$F:$F,"EUR")*$G$5+SUMIFS(Actuals!$G:$G,Actuals!$B:$B,$C$3,Actuals!$C:$C,2,Actuals!$D:$D,$B$42,Actuals!$A:$A,LEFT($D$42,FIND("|",$D$42&"|")-1),Actuals!$E:$E,MID($D$42,FIND("|",$D$42&"|")+1,50),Actuals!$F:$F,"GBP")*$H$5) | J43: =IF(OR($B$42="",3>$C$4),"",SUMIFS(Actuals!$G:$G,Actuals!$B:$B,$C$3,Actuals!$C:$C,3,Actuals!$D:$D,$B$42,Actuals!$A:$A,LEFT($D$42,FIND("|",$D$42&"|")-1),Actuals!$E:$E,MID($D$42,FIND("|",$D$42&"|")+1,50),Actuals!$F:$F,"JPY")*$E$5+SUMIFS(Actuals!$G:$G,Actuals!$B:$B,$C$3,Actuals!$C:$C,3,Actuals!$D:$D,$B$42,Actuals!$A:$A,LEFT($D$42,FIND("|",$D$42&"|")-1),Actuals!$E:$E,MID($D$42,FIND("|",$D$42&"|")+1,50),Actuals!$F:$F,"USD")*$F$5+SUMIFS(Actuals!$G:$G,Actuals!$B:$B,$C$3,Actuals!$C:$C,3,Actuals!$D:$D,$B$42,Actuals!$A:$A,LEFT($D$42,FIND("|",$D$42&"|")-1),Actuals!$E:$E,MID($D$42,FIND("|",$D$42&"|")+1,50),Actuals!$F:$F,"EUR")*$G$5+SUMIFS(Actuals!$G:$G,Actuals!$B:$B,$C$3,Actuals!$C:$C,3,Actuals!$D:$D,$B$42,Actuals!$A:$A,LEFT($D$42,FIND("|",$D$42&"|")-1),Actuals!$E:$E,MID($D$42,FIND("|",$D$42&"|")+1,50),Actuals!$F:$F,"GBP")*$H$5) | K43: =IF(OR($B$42="",4>$C$4),"",SUMIFS(Actuals!$G:$G,Actuals!$B:$B,$C$3,Actuals!$C:$C,4,Actuals!$D:$D,$B$42,Actuals!$A:$A,LEFT($D$42,FIND("|",$D$42&"|")-1),Actuals!$E:$E,MID($D$42,FIND("|",$D$42&"|")+1,50),Actuals!$F:$F,"JPY")*$E$5+SUMIFS(Actuals!$G:$G,Actuals!$B:$B,$C$3,Actuals!$C:$C,4,Actuals!$D:$D,$B$42,Actuals!$A:$A,LEFT($D$42,FIND("|",$D$42&"|")-1),Actuals!$E:$E,MID($D$42,FIND("|",$D$42&"|")+1,50),Actuals!$F:$F,"USD")*$F$5+SUMIFS(Actuals!$G:$G,Actuals!$B:$B,$C$3,Actuals!$C:$C,4,Actuals!$D:$D,$B$42,Actuals!$A:$A,LEFT($D$42,FIND("|",$D$42&"|")-1),Actuals!$E:$E,MID($D$42,FIND("|",$D$42&"|")+1,50),Actuals!$F:$F,"EUR")*$G$5+SUMIFS(Actuals!$G:$G,Actuals!$B:$B,$C$3,Actuals!$C:$C,4,Actuals!$D:$D,$B$42,Actuals!$A:$A,LEFT($D$42,FIND("|",$D$42&"|")-1),Actuals!$E:$E,MID($D$42,FIND("|",$D$42&"|")+1,50),Actuals!$F:$F,"GBP")*$H$5) | L43: =IF(OR($B$42="",5>$C$4),"",SUMIFS(Actuals!$G:$G,Actuals!$B:$B,$C$3,Actuals!$C:$C,5,Actuals!$D:$D,$B$42,Actuals!$A:$A,LEFT($D$42,FIND("|",$D$42&"|")-1),Actuals!$E:$E,MID($D$42,FIND("|",$D$42&"|")+1,50),Actuals!$F:$F,"JPY")*$E$5+SUMIFS(Actuals!$G:$G,Actuals!$B:$B,$C$3,Actuals!$C:$C,5,Actuals!$D:$D,$B$42,Actuals!$A:$A,LEFT($D$42,FIND("|",$D$42&"|")-1),Actuals!$E:$E,MID($D$42,FIND("|",$D$42&"|")+1,50),Actuals!$F:$F,"USD")*$F$5+SUMIFS(Actuals!$G:$G,Actuals!$B:$B,$C$3,Actuals!$C:$C,5,Actuals!$D:$D,$B$42,Actuals!$A:$A,LEFT($D$42,FIND("|",$D$42&"|")-1),Actuals!$E:$E,MID($D$42,FIND("|",$D$42&"|")+1,50),Actuals!$F:$F,"EUR")*$G$5+SUMIFS(Actuals!$G:$G,Actuals!$B:$B,$C$3,Actuals!$C:$C,5,Actuals!$D:$D,$B$42,Actuals!$A:$A,LEFT($D$42,FIND("|",$D$42&"|")-1),Actuals!$E:$E,MID($D$42,FIND("|",$D$42&"|")+1,50),Actuals!$F:$F,"GBP")*$H$5) | M43: =IF(OR($B$42="",6>$C$4),"",SUMIFS(Actuals!$G:$G,Actuals!$B:$B,$C$3,Actuals!$C:$C,6,Actuals!$D:$D,$B$42,Actuals!$A:$A,LEFT($D$42,FIND("|",$D$42&"|")-1),Actuals!$E:$E,MID($D$42,FIND("|",$D$42&"|")+1,50),Actuals!$F:$F,"JPY")*$E$5+SUMIFS(Actuals!$G:$G,Actuals!$B:$B,$C$3,Actuals!$C:$C,6,Actuals!$D:$D,$B$42,Actuals!$A:$A,LEFT($D$42,FIND("|",$D$42&"|")-1),Actuals!$E:$E,MID($D$42,FIND("|",$D$42&"|")+1,50),Actuals!$F:$F,"USD")*$F$5+SUMIFS(Actuals!$G:$G,Actuals!$B:$B,$C$3,Actuals!$C:$C,6,Actuals!$D:$D,$B$42,Actuals!$A:$A,LEFT($D$42,FIND("|",$D$42&"|")-1),Actuals!$E:$E,MID($D$42,FIND("|",$D$42&"|")+1,50),Actuals!$F:$F,"EUR")*$G$5+SUMIFS(Actuals!$G:$G,Actuals!$B:$B,$C$3,Actuals!$C:$C,6,Actuals!$D:$D,$B$42,Actuals!$A:$A,LEFT($D$42,FIND("|",$D$42&"|")-1),Actuals!$E:$E,MID($D$42,FIND("|",$D$42&"|")+1,50),Actuals!$F:$F,"GBP")*$H$5) | N43: =IF(OR($B$42="",7>$C$4),"",SUMIFS(Actuals!$G:$G,Actuals!$B:$B,$C$3,Actuals!$C:$C,7,Actuals!$D:$D,$B$42,Actuals!$A:$A,LEFT($D$42,FIND("|",$D$42&"|")-1),Actuals!$E:$E,MID($D$42,FIND("|",$D$42&"|")+1,50),Actuals!$F:$F,"JPY")*$E$5+SUMIFS(Actuals!$G:$G,Actuals!$B:$B,$C$3,Actuals!$C:$C,7,Actuals!$D:$D,$B$42,Actuals!$A:$A,LEFT($D$42,FIND("|",$D$42&"|")-1),Actuals!$E:$E,MID($D$42,FIND("|",$D$42&"|")+1,50),Actuals!$F:$F,"USD")*$F$5+SUMIFS(Actuals!$G:$G,Actuals!$B:$B,$C$3,Actuals!$C:$C,7,Actuals!$D:$D,$B$42,Actuals!$A:$A,LEFT($D$42,FIND("|",$D$42&"|")-1),Actuals!$E:$E,MID($D$42,FIND("|",$D$42&"|")+1,50),Actuals!$F:$F,"EUR")*$G$5+SUMIFS(Actuals!$G:$G,Actuals!$B:$B,$C$3,Actuals!$C:$C,7,Actuals!$D:$D,$B$42,Actuals!$A:$A,LEFT($D$42,FIND("|",$D$42&"|")-1),Actuals!$E:$E,MID($D$42,FIND("|",$D$42&"|")+1,50),Actuals!$F:$F,"GBP")*$H$5) | O43: =IF(OR($B$42="",8>$C$4),"",SUMIFS(Actuals!$G:$G,Actuals!$B:$B,$C$3,Actuals!$C:$C,8,Actuals!$D:$D,$B$42,Actuals!$A:$A,LEFT($D$42,FIND("|",$D$42&"|")-1),Actuals!$E:$E,MID($D$42,FIND("|",$D$42&"|")+1,50),Actuals!$F:$F,"JPY")*$E$5+SUMIFS(Actuals!$G:$G,Actuals!$B:$B,$C$3,Actuals!$C:$C,8,Actuals!$D:$D,$B$42,Actuals!$A:$A,LEFT($D$42,FIND("|",$D$42&"|")-1),Actuals!$E:$E,MID($D$42,FIND("|",$D$42&"|")+1,50),Actuals!$F:$F,"USD")*$F$5+SUMIFS(Actuals!$G:$G,Actuals!$B:$B,$C$3,Actuals!$C:$C,8,Actuals!$D:$D,$B$42,Actuals!$A:$A,LEFT($D$42,FIND("|",$D$42&"|")-1),Actuals!$E:$E,MID($D$42,FIND("|",$D$42&"|")+1,50),Actuals!$F:$F,"EUR")*$G$5+SUMIFS(Actuals!$G:$G,Actuals!$B:$B,$C$3,Actuals!$C:$C,8,Actuals!$D:$D,$B$42,Actuals!$A:$A,LEFT($D$42,FIND("|",$D$42&"|")-1),Actuals!$E:$E,MID($D$42,FIND("|",$D$42&"|")+1,50),Actuals!$F:$F,"GBP")*$H$5) | P43: =IF(OR($B$42="",9>$C$4),"",SUMIFS(Actuals!$G:$G,Actuals!$B:$B,$C$3,Actuals!$C:$C,9,Actuals!$D:$D,$B$42,Actuals!$A:$A,LEFT($D$42,FIND("|",$D$42&"|")-1),Actuals!$E:$E,MID($D$42,FIND("|",$D$42&"|")+1,50),Actuals!$F:$F,"JPY")*$E$5+SUMIFS(Actuals!$G:$G,Actuals!$B:$B,$C$3,Actuals!$C:$C,9,Actuals!$D:$D,$B$42,Actuals!$A:$A,LEFT($D$42,FIND("|",$D$42&"|")-1),Actuals!$E:$E,MID($D$42,FIND("|",$D$42&"|")+1,50),Actuals!$F:$F,"USD")*$F$5+SUMIFS(Actuals!$G:$G,Actuals!$B:$B,$C$3,Actuals!$C:$C,9,Actuals!$D:$D,$B$42,Actuals!$A:$A,LEFT($D$42,FIND("|",$D$42&"|")-1),Actuals!$E:$E,MID($D$42,FIND("|",$D$42&"|")+1,50),Actuals!$F:$F,"EUR")*$G$5+SUMIFS(Actuals!$G:$G,Actuals!$B:$B,$C$3,Actuals!$C:$C,9,Actuals!$D:$D,$B$42,Actuals!$A:$A,LEFT($D$42,FIND("|",$D$42&"|")-1),Actuals!$E:$E,MID($D$42,FIND("|",$D$42&"|")+1,50),Actuals!$F:$F,"GBP")*$H$5) | Q43: =IF(OR($B$42="",10>$C$4),"",SUMIFS(Actuals!$G:$G,Actuals!$B:$B,$C$3,Actuals!$C:$C,10,Actuals!$D:$D,$B$42,Actuals!$A:$A,LEFT($D$42,FIND("|",$D$42&"|")-1),Actuals!$E:$E,MID($D$42,FIND("|",$D$42&"|")+1,50),Actuals!$F:$F,"JPY")*$E$5+SUMIFS(Actuals!$G:$G,Actuals!$B:$B,$C$3,Actuals!$C:$C,10,Actuals!$D:$D,$B$42,Actuals!$A:$A,LEFT($D$42,FIND("|",$D$42&"|")-1),Actuals!$E:$E,MID($D$42,FIND("|",$D$42&"|")+1,50),Actuals!$F:$F,"USD")*$F$5+SUMIFS(Actuals!$G:$G,Actuals!$B:$B,$C$3,Actuals!$C:$C,10,Actuals!$D:$D,$B$42,Actuals!$A:$A,LEFT($D$42,FIND("|",$D$42&"|")-1),Actuals!$E:$E,MID($D$42,FIND("|",$D$42&"|")+1,50),Actuals!$F:$F,"EUR")*$G$5+SUMIFS(Actuals!$G:$G,Actuals!$B:$B,$C$3,Actuals!$C:$C,10,Actuals!$D:$D,$B$42,Actuals!$A:$A,LEFT($D$42,FIND("|",$D$42&"|")-1),Actuals!$E:$E,MID($D$42,FIND("|",$D$42&"|")+1,50),Actuals!$F:$F,"GBP")*$H$5) | R43: =IF(OR($B$42="",11>$C$4),"",SUMIFS(Actuals!$G:$G,Actuals!$B:$B,$C$3,Actuals!$C:$C,11,Actuals!$D:$D,$B$42,Actuals!$A:$A,LEFT($D$42,FIND("|",$D$42&"|")-1),Actuals!$E:$E,MID($D$42,FIND("|",$D$42&"|")+1,50),Actuals!$F:$F,"JPY")*$E$5+SUMIFS(Actuals!$G:$G,Actuals!$B:$B,$C$3,Actuals!$C:$C,11,Actuals!$D:$D,$B$42,Actuals!$A:$A,LEFT($D$42,FIND("|",$D$42&"|")-1),Actuals!$E:$E,MID($D$42,FIND("|",$D$42&"|")+1,50),Actuals!$F:$F,"USD")*$F$5+SUMIFS(Actuals!$G:$G,Actuals!$B:$B,$C$3,Actuals!$C:$C,11,Actuals!$D:$D,$B$42,Actuals!$A:$A,LEFT($D$42,FIND("|",$D$42&"|")-1),Actuals!$E:$E,MID($D$42,FIND("|",$D$42&"|")+1,50),Actuals!$F:$F,"EUR")*$G$5+SUMIFS(Actuals!$G:$G,Actuals!$B:$B,$C$3,Actuals!$C:$C,11,Actuals!$D:$D,$B$42,Actuals!$A:$A,LEFT($D$42,FIND("|",$D$42&"|")-1),Actuals!$E:$E,MID($D$42,FIND("|",$D$42&"|")+1,50),Actuals!$F:$F,"GBP")*$H$5) | S43: =IF(OR($B$42="",12>$C$4),"",SUMIFS(Actuals!$G:$G,Actuals!$B:$B,$C$3,Actuals!$C:$C,12,Actuals!$D:$D,$B$42,Actuals!$A:$A,LEFT($D$42,FIND("|",$D$42&"|")-1),Actuals!$E:$E,MID($D$42,FIND("|",$D$42&"|")+1,50),Actuals!$F:$F,"JPY")*$E$5+SUMIFS(Actuals!$G:$G,Actuals!$B:$B,$C$3,Actuals!$C:$C,12,Actuals!$D:$D,$B$42,Actuals!$A:$A,LEFT($D$42,FIND("|",$D$42&"|")-1),Actuals!$E:$E,MID($D$42,FIND("|",$D$42&"|")+1,50),Actuals!$F:$F,"USD")*$F$5+SUMIFS(Actuals!$G:$G,Actuals!$B:$B,$C$3,Actuals!$C:$C,12,Actuals!$D:$D,$B$42,Actuals!$A:$A,LEFT($D$42,FIND("|",$D$42&"|")-1),Actuals!$E:$E,MID($D$42,FIND("|",$D$42&"|")+1,50),Actuals!$F:$F,"EUR")*$G$5+SUMIFS(Actuals!$G:$G,Actuals!$B:$B,$C$3,Actuals!$C:$C,12,Actuals!$D:$D,$B$42,Actuals!$A:$A,LEFT($D$42,FIND("|",$D$42&"|")-1),Actuals!$E:$E,MID($D$42,FIND("|",$D$42&"|")+1,50),Actuals!$F:$F,"GBP")*$H$5) | T43: =IF($B$42="","",SUMIF($H$7:$S$7,"<="&$C$4,$H43:$S43)) | X43: =IF($B43="","",IFERROR(INDEX(Cost_Centers!$E:$E,MATCH($B43,Cost_Centers!$A:$A,0)),"(unknown)")) | Y43: =IF($B43="","",IFERROR(INDEX(Cost_Centers!$D:$D,MATCH($B43,Cost_Centers!$A:$A,0)),"(unknown)")) | Z43: =IF(OR($B43="",$G43<>"Variance vs Budget"),"",ABS(N($V43))+ROW()/1000000000)
A44: =IF(A$42="","",A$42) | B44: =IF(B$42="","",B$42) | C44: =IF(C$42="","",C$42) | D44: =IF(D$42="","",D$42) | E44: =IF(E$42="","",E$42) | F44: =IF(F$42="","",F$42) | G44: Variance vs Budget | H44: =IF(OR($B$42="",1>$C$4),"",N(H43)-H42) | I44: =IF(OR($B$42="",2>$C$4),"",N(I43)-I42) | J44: =IF(OR($B$42="",3>$C$4),"",N(J43)-J42) | K44: =IF(OR($B$42="",4>$C$4),"",N(K43)-K42) | L44: =IF(OR($B$42="",5>$C$4),"",N(L43)-L42) | M44: =IF(OR($B$42="",6>$C$4),"",N(M43)-M42) | N44: =IF(OR($B$42="",7>$C$4),"",N(N43)-N42) | O44: =IF(OR($B$42="",8>$C$4),"",N(O43)-O42) | P44: =IF(OR($B$42="",9>$C$4),"",N(P43)-P42) | Q44: =IF(OR($B$42="",10>$C$4),"",N(Q43)-Q42) | R44: =IF(OR($B$42="",11>$C$4),"",N(R43)-R42) | S44: =IF(OR($B$42="",12>$C$4),"",N(S43)-S42) | T44: =IF($B$42="","",T43-T42) | U44: =IF($B$42="","",U46-U42) | V44: =IF($B$42="","",V46-V42) | X44: =IF($B44="","",IFERROR(INDEX(Cost_Centers!$E:$E,MATCH($B44,Cost_Centers!$A:$A,0)),"(unknown)")) | Y44: =IF($B44="","",IFERROR(INDEX(Cost_Centers!$D:$D,MATCH($B44,Cost_Centers!$A:$A,0)),"(unknown)")) | Z44: =IF(OR($B44="",$G44<>"Variance vs Budget"),"",ABS(N($V44))+ROW()/1000000000)
A45: =IF(A$42="","",A$42) | B45: =IF(B$42="","",B$42) | C45: =IF(C$42="","",C$42) | D45: =IF(D$42="","",D$42) | E45: =IF(E$42="","",E$42) | F45: =IF(F$42="","",F$42) | G45: Forecast (input) | X45: =IF($B45="","",IFERROR(INDEX(Cost_Centers!$E:$E,MATCH($B45,Cost_Centers!$A:$A,0)),"(unknown)")) | Y45: =IF($B45="","",IFERROR(INDEX(Cost_Centers!$D:$D,MATCH($B45,Cost_Centers!$A:$A,0)),"(unknown)")) | Z45: =IF(OR($B45="",$G45<>"Variance vs Budget"),"",ABS(N($V45))+ROW()/1000000000)
A46: =IF(A$42="","",A$42) | B46: =IF(B$42="","",B$42) | C46: =IF(C$42="","",C$42) | D46: =IF(D$42="","",D$42) | E46: =IF(E$42="","",E$42) | F46: =IF(F$42="","",F$42) | G46: Actual + Forecast | H46: =IF($B$42="","",IF(1<=$C$4,N(H43),IF(H45="",H42,H45))) | I46: =IF($B$42="","",IF(2<=$C$4,N(I43),IF(I45="",I42,I45))) | J46: =IF($B$42="","",IF(3<=$C$4,N(J43),IF(J45="",J42,J45))) | K46: =IF($B$42="","",IF(4<=$C$4,N(K43),IF(K45="",K42,K45))) | L46: =IF($B$42="","",IF(5<=$C$4,N(L43),IF(L45="",L42,L45))) | M46: =IF($B$42="","",IF(6<=$C$4,N(M43),IF(M45="",M42,M45))) | N46: =IF($B$42="","",IF(7<=$C$4,N(N43),IF(N45="",N42,N45))) | O46: =IF($B$42="","",IF(8<=$C$4,N(O43),IF(O45="",O42,O45))) | P46: =IF($B$42="","",IF(9<=$C$4,N(P43),IF(P45="",P42,P45))) | Q46: =IF($B$42="","",IF(10<=$C$4,N(Q43),IF(Q45="",Q42,Q45))) | R46: =IF($B$42="","",IF(11<=$C$4,N(R43),IF(R45="",R42,R45))) | S46: =IF($B$42="","",IF(12<=$C$4,N(S43),IF(S45="",S42,S45))) | T46: =IF($B$42="","",SUMIF($H$7:$S$7,"<="&$C$4,$H46:$S46)) | U46: =IF($B$42="","",SUMIF($H$7:$S$7,">"&$C$4,$H46:$S46)) | V46: =IF($B$42="","",SUM($H46:$S46)) | X46: =IF($B46="","",IFERROR(INDEX(Cost_Centers!$E:$E,MATCH($B46,Cost_Centers!$A:$A,0)),"(unknown)")) | Y46: =IF($B46="","",IFERROR(INDEX(Cost_Centers!$D:$D,MATCH($B46,Cost_Centers!$A:$A,0)),"(unknown)")) | Z46: =IF(OR($B46="",$G46<>"Variance vs Budget"),"",ABS(N($V46))+ROW()/1000000000)
A47: =IF(A$42="","",A$42) | B47: =IF(B$42="","",B$42) | C47: =IF(C$42="","",C$42) | D47: =IF(D$42="","",D$42) | E47: =IF(E$42="","",E$42) | F47: =IF(F$42="","",F$42) | G47: Prior Month Forecast | H47: =IF($B$42="","",IF(COUNTIFS(Prior_Forecast!$A:$A,$B$42,Prior_Forecast!$B:$B,$D$42)>0,SUMIFS(Prior_Forecast!$C:$C,Prior_Forecast!$A:$A,$B$42,Prior_Forecast!$B:$B,$D$42),"")) | I47: =IF($B$42="","",IF(COUNTIFS(Prior_Forecast!$A:$A,$B$42,Prior_Forecast!$B:$B,$D$42)>0,SUMIFS(Prior_Forecast!$D:$D,Prior_Forecast!$A:$A,$B$42,Prior_Forecast!$B:$B,$D$42),"")) | J47: =IF($B$42="","",IF(COUNTIFS(Prior_Forecast!$A:$A,$B$42,Prior_Forecast!$B:$B,$D$42)>0,SUMIFS(Prior_Forecast!$E:$E,Prior_Forecast!$A:$A,$B$42,Prior_Forecast!$B:$B,$D$42),"")) | K47: =IF($B$42="","",IF(COUNTIFS(Prior_Forecast!$A:$A,$B$42,Prior_Forecast!$B:$B,$D$42)>0,SUMIFS(Prior_Forecast!$F:$F,Prior_Forecast!$A:$A,$B$42,Prior_Forecast!$B:$B,$D$42),"")) | L47: =IF($B$42="","",IF(COUNTIFS(Prior_Forecast!$A:$A,$B$42,Prior_Forecast!$B:$B,$D$42)>0,SUMIFS(Prior_Forecast!$G:$G,Prior_Forecast!$A:$A,$B$42,Prior_Forecast!$B:$B,$D$42),"")) | M47: =IF($B$42="","",IF(COUNTIFS(Prior_Forecast!$A:$A,$B$42,Prior_Forecast!$B:$B,$D$42)>0,SUMIFS(Prior_Forecast!$H:$H,Prior_Forecast!$A:$A,$B$42,Prior_Forecast!$B:$B,$D$42),"")) | N47: =IF($B$42="","",IF(COUNTIFS(Prior_Forecast!$A:$A,$B$42,Prior_Forecast!$B:$B,$D$42)>0,SUMIFS(Prior_Forecast!$I:$I,Prior_Forecast!$A:$A,$B$42,Prior_Forecast!$B:$B,$D$42),"")) | O47: =IF($B$42="","",IF(COUNTIFS(Prior_Forecast!$A:$A,$B$42,Prior_Forecast!$B:$B,$D$42)>0,SUMIFS(Prior_Forecast!$J:$J,Prior_Forecast!$A:$A,$B$42,Prior_Forecast!$B:$B,$D$42),"")) | P47: =IF($B$42="","",IF(COUNTIFS(Prior_Forecast!$A:$A,$B$42,Prior_Forecast!$B:$B,$D$42)>0,SUMIFS(Prior_Forecast!$K:$K,Prior_Forecast!$A:$A,$B$42,Prior_Forecast!$B:$B,$D$42),"")) | Q47: =IF($B$42="","",IF(COUNTIFS(Prior_Forecast!$A:$A,$B$42,Prior_Forecast!$B:$B,$D$42)>0,SUMIFS(Prior_Forecast!$L:$L,Prior_Forecast!$A:$A,$B$42,Prior_Forecast!$B:$B,$D$42),"")) | R47: =IF($B$42="","",IF(COUNTIFS(Prior_Forecast!$A:$A,$B$42,Prior_Forecast!$B:$B,$D$42)>0,SUMIFS(Prior_Forecast!$M:$M,Prior_Forecast!$A:$A,$B$42,Prior_Forecast!$B:$B,$D$42),"")) | S47: =IF($B$42="","",IF(COUNTIFS(Prior_Forecast!$A:$A,$B$42,Prior_Forecast!$B:$B,$D$42)>0,SUMIFS(Prior_Forecast!$N:$N,Prior_Forecast!$A:$A,$B$42,Prior_Forecast!$B:$B,$D$42),"")) | T47: =IF($B$42="","",IF(COUNTIFS(Prior_Forecast!$A:$A,$B$42,Prior_Forecast!$B:$B,$D$42)>0,SUMIFS(Prior_Forecast!$O:$O,Prior_Forecast!$A:$A,$B$42,Prior_Forecast!$B:$B,$D$42),"")) | U47: =IF($B$42="","",IF(COUNTIFS(Prior_Forecast!$A:$A,$B$42,Prior_Forecast!$B:$B,$D$42)>0,SUMIFS(Prior_Forecast!$P:$P,Prior_Forecast!$A:$A,$B$42,Prior_Forecast!$B:$B,$D$42),"")) | V47: =IF($B$42="","",IF(COUNTIFS(Prior_Forecast!$A:$A,$B$42,Prior_Forecast!$B:$B,$D$42)>0,SUMIFS(Prior_Forecast!$Q:$Q,Prior_Forecast!$A:$A,$B$42,Prior_Forecast!$B:$B,$D$42),"")) | X47: =IF($B47="","",IFERROR(INDEX(Cost_Centers!$E:$E,MATCH($B47,Cost_Centers!$A:$A,0)),"(unknown)")) | Y47: =IF($B47="","",IFERROR(INDEX(Cost_Centers!$D:$D,MATCH($B47,Cost_Centers!$A:$A,0)),"(unknown)")) | Z47: =IF(OR($B47="",$G47<>"Variance vs Budget"),"",ABS(N($V47))+ROW()/1000000000)
A48: =IF(A$42="","",A$42) | B48: =IF(B$42="","",B$42) | C48: =IF(C$42="","",C$42) | D48: =IF(D$42="","",D$42) | E48: =IF(E$42="","",E$42) | F48: =IF(F$42="","",F$42) | G48: Variance vs Prior Month | H48: =IF(OR($B$42="",H47=""),"",H46-H47) | I48: =IF(OR($B$42="",I47=""),"",I46-I47) | J48: =IF(OR($B$42="",J47=""),"",J46-J47) | K48: =IF(OR($B$42="",K47=""),"",K46-K47) | L48: =IF(OR($B$42="",L47=""),"",L46-L47) | M48: =IF(OR($B$42="",M47=""),"",M46-M47) | N48: =IF(OR($B$42="",N47=""),"",N46-N47) | O48: =IF(OR($B$42="",O47=""),"",O46-O47) | ... V48: =IF(OR($B$42="",V47=""),"",V46-V47) | X48: =IF($B48="","",IFERROR(INDEX(Cost_Centers!$E:$E,MATCH($B48,Cost_Centers!$A:$A,0)),"(unknown)")) | Y48: =IF($B48="","",IFERROR(INDEX(Cost_Centers!$D:$D,MATCH($B48,Cost_Centers!$A:$A,0)),"(unknown)")) | Z48: =IF(OR($B48="",$G48<>"Variance vs Budget"),"",ABS(N($V48))+ROW()/1000000000)
A49: =IF(A$42="","",A$42) | B49: =IF(B$42="","",B$42) | C49: =IF(C$42="","",C$42) | D49: =IF(D$42="","",D$42) | E49: =IF(E$42="","",E$42) | F49: =IF(F$42="","",F$42) | G49: Rationale | X49: =IF($B49="","",IFERROR(INDEX(Cost_Centers!$E:$E,MATCH($B49,Cost_Centers!$A:$A,0)),"(unknown)")) | Y49: =IF($B49="","",IFERROR(INDEX(Cost_Centers!$D:$D,MATCH($B49,Cost_Centers!$A:$A,0)),"(unknown)")) | Z49: =IF(OR($B49="",$G49<>"Variance vs Budget"),"",ABS(N($V49))+ROW()/1000000000)
A50: =IF($D$50="","",LEFT($D$50,FIND("|",$D$50&"|")-1)) | C50: =IF($B$50="","",IFERROR(INDEX(Cost_Centers!$B:$B,MATCH($B$50,Cost_Centers!$A:$A,0)),"(not in master)")) | E50: =IF($D$50="","",IFERROR(INDEX(Accounts!$D:$D,MATCH($D$50,Accounts!$A:$A,0)),"(not in master)")) | G50: Budget | H50: =IF($B$50="","",SUMIFS(Opex_Budget!$O:$O,Opex_Budget!$A:$A,$C$3,Opex_Budget!$E:$E,$B$50,Opex_Budget!$F:$F,$D$50,Opex_Budget!$N:$N,"JPY")*$E$5+SUMIFS(Opex_Budget!$O:$O,Opex_Budget!$A:$A,$C$3,Opex_Budget!$E:$E,$B$50,Opex_Budget!$F:$F,$D$50,Opex_Budget!$N:$N,"USD")*$F$5+SUMIFS(Opex_Budget!$O:$O,Opex_Budget!$A:$A,$C$3,Opex_Budget!$E:$E,$B$50,Opex_Budget!$F:$F,$D$50,Opex_Budget!$N:$N,"EUR")*$G$5+SUMIFS(Opex_Budget!$O:$O,Opex_Budget!$A:$A,$C$3,Opex_Budget!$E:$E,$B$50,Opex_Budget!$F:$F,$D$50,Opex_Budget!$N:$N,"GBP")*$H$5) | I50: =IF($B$50="","",SUMIFS(Opex_Budget!$P:$P,Opex_Budget!$A:$A,$C$3,Opex_Budget!$E:$E,$B$50,Opex_Budget!$F:$F,$D$50,Opex_Budget!$N:$N,"JPY")*$E$5+SUMIFS(Opex_Budget!$P:$P,Opex_Budget!$A:$A,$C$3,Opex_Budget!$E:$E,$B$50,Opex_Budget!$F:$F,$D$50,Opex_Budget!$N:$N,"USD")*$F$5+SUMIFS(Opex_Budget!$P:$P,Opex_Budget!$A:$A,$C$3,Opex_Budget!$E:$E,$B$50,Opex_Budget!$F:$F,$D$50,Opex_Budget!$N:$N,"EUR")*$G$5+SUMIFS(Opex_Budget!$P:$P,Opex_Budget!$A:$A,$C$3,Opex_Budget!$E:$E,$B$50,Opex_Budget!$F:$F,$D$50,Opex_Budget!$N:$N,"GBP")*$H$5) | J50: =IF($B$50="","",SUMIFS(Opex_Budget!$Q:$Q,Opex_Budget!$A:$A,$C$3,Opex_Budget!$E:$E,$B$50,Opex_Budget!$F:$F,$D$50,Opex_Budget!$N:$N,"JPY")*$E$5+SUMIFS(Opex_Budget!$Q:$Q,Opex_Budget!$A:$A,$C$3,Opex_Budget!$E:$E,$B$50,Opex_Budget!$F:$F,$D$50,Opex_Budget!$N:$N,"USD")*$F$5+SUMIFS(Opex_Budget!$Q:$Q,Opex_Budget!$A:$A,$C$3,Opex_Budget!$E:$E,$B$50,Opex_Budget!$F:$F,$D$50,Opex_Budget!$N:$N,"EUR")*$G$5+SUMIFS(Opex_Budget!$Q:$Q,Opex_Budget!$A:$A,$C$3,Opex_Budget!$E:$E,$B$50,Opex_Budget!$F:$F,$D$50,Opex_Budget!$N:$N,"GBP")*$H$5) | K50: =IF($B$50="","",SUMIFS(Opex_Budget!$R:$R,Opex_Budget!$A:$A,$C$3,Opex_Budget!$E:$E,$B$50,Opex_Budget!$F:$F,$D$50,Opex_Budget!$N:$N,"JPY")*$E$5+SUMIFS(Opex_Budget!$R:$R,Opex_Budget!$A:$A,$C$3,Opex_Budget!$E:$E,$B$50,Opex_Budget!$F:$F,$D$50,Opex_Budget!$N:$N,"USD")*$F$5+SUMIFS(Opex_Budget!$R:$R,Opex_Budget!$A:$A,$C$3,Opex_Budget!$E:$E,$B$50,Opex_Budget!$F:$F,$D$50,Opex_Budget!$N:$N,"EUR")*$G$5+SUMIFS(Opex_Budget!$R:$R,Opex_Budget!$A:$A,$C$3,Opex_Budget!$E:$E,$B$50,Opex_Budget!$F:$F,$D$50,Opex_Budget!$N:$N,"GBP")*$H$5) | L50: =IF($B$50="","",SUMIFS(Opex_Budget!$S:$S,Opex_Budget!$A:$A,$C$3,Opex_Budget!$E:$E,$B$50,Opex_Budget!$F:$F,$D$50,Opex_Budget!$N:$N,"JPY")*$E$5+SUMIFS(Opex_Budget!$S:$S,Opex_Budget!$A:$A,$C$3,Opex_Budget!$E:$E,$B$50,Opex_Budget!$F:$F,$D$50,Opex_Budget!$N:$N,"USD")*$F$5+SUMIFS(Opex_Budget!$S:$S,Opex_Budget!$A:$A,$C$3,Opex_Budget!$E:$E,$B$50,Opex_Budget!$F:$F,$D$50,Opex_Budget!$N:$N,"EUR")*$G$5+SUMIFS(Opex_Budget!$S:$S,Opex_Budget!$A:$A,$C$3,Opex_Budget!$E:$E,$B$50,Opex_Budget!$F:$F,$D$50,Opex_Budget!$N:$N,"GBP")*$H$5) | M50: =IF($B$50="","",SUMIFS(Opex_Budget!$T:$T,Opex_Budget!$A:$A,$C$3,Opex_Budget!$E:$E,$B$50,Opex_Budget!$F:$F,$D$50,Opex_Budget!$N:$N,"JPY")*$E$5+SUMIFS(Opex_Budget!$T:$T,Opex_Budget!$A:$A,$C$3,Opex_Budget!$E:$E,$B$50,Opex_Budget!$F:$F,$D$50,Opex_Budget!$N:$N,"USD")*$F$5+SUMIFS(Opex_Budget!$T:$T,Opex_Budget!$A:$A,$C$3,Opex_Budget!$E:$E,$B$50,Opex_Budget!$F:$F,$D$50,Opex_Budget!$N:$N,"EUR")*$G$5+SUMIFS(Opex_Budget!$T:$T,Opex_Budget!$A:$A,$C$3,Opex_Budget!$E:$E,$B$50,Opex_Budget!$F:$F,$D$50,Opex_Budget!$N:$N,"GBP")*$H$5) | N50: =IF($B$50="","",SUMIFS(Opex_Budget!$U:$U,Opex_Budget!$A:$A,$C$3,Opex_Budget!$E:$E,$B$50,Opex_Budget!$F:$F,$D$50,Opex_Budget!$N:$N,"JPY")*$E$5+SUMIFS(Opex_Budget!$U:$U,Opex_Budget!$A:$A,$C$3,Opex_Budget!$E:$E,$B$50,Opex_Budget!$F:$F,$D$50,Opex_Budget!$N:$N,"USD")*$F$5+SUMIFS(Opex_Budget!$U:$U,Opex_Budget!$A:$A,$C$3,Opex_Budget!$E:$E,$B$50,Opex_Budget!$F:$F,$D$50,Opex_Budget!$N:$N,"EUR")*$G$5+SUMIFS(Opex_Budget!$U:$U,Opex_Budget!$A:$A,$C$3,Opex_Budget!$E:$E,$B$50,Opex_Budget!$F:$F,$D$50,Opex_Budget!$N:$N,"GBP")*$H$5) | O50: =IF($B$50="","",SUMIFS(Opex_Budget!$V:$V,Opex_Budget!$A:$A,$C$3,Opex_Budget!$E:$E,$B$50,Opex_Budget!$F:$F,$D$50,Opex_Budget!$N:$N,"JPY")*$E$5+SUMIFS(Opex_Budget!$V:$V,Opex_Budget!$A:$A,$C$3,Opex_Budget!$E:$E,$B$50,Opex_Budget!$F:$F,$D$50,Opex_Budget!$N:$N,"USD")*$F$5+SUMIFS(Opex_Budget!$V:$V,Opex_Budget!$A:$A,$C$3,Opex_Budget!$E:$E,$B$50,Opex_Budget!$F:$F,$D$50,Opex_Budget!$N:$N,"EUR")*$G$5+SUMIFS(Opex_Budget!$V:$V,Opex_Budget!$A:$A,$C$3,Opex_Budget!$E:$E,$B$50,Opex_Budget!$F:$F,$D$50,Opex_Budget!$N:$N,"GBP")*$H$5) | P50: =IF($B$50="","",SUMIFS(Opex_Budget!$W:$W,Opex_Budget!$A:$A,$C$3,Opex_Budget!$E:$E,$B$50,Opex_Budget!$F:$F,$D$50,Opex_Budget!$N:$N,"JPY")*$E$5+SUMIFS(Opex_Budget!$W:$W,Opex_Budget!$A:$A,$C$3,Opex_Budget!$E:$E,$B$50,Opex_Budget!$F:$F,$D$50,Opex_Budget!$N:$N,"USD")*$F$5+SUMIFS(Opex_Budget!$W:$W,Opex_Budget!$A:$A,$C$3,Opex_Budget!$E:$E,$B$50,Opex_Budget!$F:$F,$D$50,Opex_Budget!$N:$N,"EUR")*$G$5+SUMIFS(Opex_Budget!$W:$W,Opex_Budget!$A:$A,$C$3,Opex_Budget!$E:$E,$B$50,Opex_Budget!$F:$F,$D$50,Opex_Budget!$N:$N,"GBP")*$H$5) | Q50: =IF($B$50="","",SUMIFS(Opex_Budget!$X:$X,Opex_Budget!$A:$A,$C$3,Opex_Budget!$E:$E,$B$50,Opex_Budget!$F:$F,$D$50,Opex_Budget!$N:$N,"JPY")*$E$5+SUMIFS(Opex_Budget!$X:$X,Opex_Budget!$A:$A,$C$3,Opex_Budget!$E:$E,$B$50,Opex_Budget!$F:$F,$D$50,Opex_Budget!$N:$N,"USD")*$F$5+SUMIFS(Opex_Budget!$X:$X,Opex_Budget!$A:$A,$C$3,Opex_Budget!$E:$E,$B$50,Opex_Budget!$F:$F,$D$50,Opex_Budget!$N:$N,"EUR")*$G$5+SUMIFS(Opex_Budget!$X:$X,Opex_Budget!$A:$A,$C$3,Opex_Budget!$E:$E,$B$50,Opex_Budget!$F:$F,$D$50,Opex_Budget!$N:$N,"GBP")*$H$5) | R50: =IF($B$50="","",SUMIFS(Opex_Budget!$Y:$Y,Opex_Budget!$A:$A,$C$3,Opex_Budget!$E:$E,$B$50,Opex_Budget!$F:$F,$D$50,Opex_Budget!$N:$N,"JPY")*$E$5+SUMIFS(Opex_Budget!$Y:$Y,Opex_Budget!$A:$A,$C$3,Opex_Budget!$E:$E,$B$50,Opex_Budget!$F:$F,$D$50,Opex_Budget!$N:$N,"USD")*$F$5+SUMIFS(Opex_Budget!$Y:$Y,Opex_Budget!$A:$A,$C$3,Opex_Budget!$E:$E,$B$50,Opex_Budget!$F:$F,$D$50,Opex_Budget!$N:$N,"EUR")*$G$5+SUMIFS(Opex_Budget!$Y:$Y,Opex_Budget!$A:$A,$C$3,Opex_Budget!$E:$E,$B$50,Opex_Budget!$F:$F,$D$50,Opex_Budget!$N:$N,"GBP")*$H$5) | S50: =IF($B$50="","",SUMIFS(Opex_Budget!$Z:$Z,Opex_Budget!$A:$A,$C$3,Opex_Budget!$E:$E,$B$50,Opex_Budget!$F:$F,$D$50,Opex_Budget!$N:$N,"JPY")*$E$5+SUMIFS(Opex_Budget!$Z:$Z,Opex_Budget!$A:$A,$C$3,Opex_Budget!$E:$E,$B$50,Opex_Budget!$F:$F,$D$50,Opex_Budget!$N:$N,"USD")*$F$5+SUMIFS(Opex_Budget!$Z:$Z,Opex_Budget!$A:$A,$C$3,Opex_Budget!$E:$E,$B$50,Opex_Budget!$F:$F,$D$50,Opex_Budget!$N:$N,"EUR")*$G$5+SUMIFS(Opex_Budget!$Z:$Z,Opex_Budget!$A:$A,$C$3,Opex_Budget!$E:$E,$B$50,Opex_Budget!$F:$F,$D$50,Opex_Budget!$N:$N,"GBP")*$H$5) | T50: =IF($B$50="","",SUMIF($H$7:$S$7,"<="&$C$4,$H50:$S50)) | U50: =IF($B$50="","",SUMIF($H$7:$S$7,">"&$C$4,$H50:$S50)) | V50: =IF($B$50="","",SUM($H50:$S50)) | X50: =IF($B50="","",IFERROR(INDEX(Cost_Centers!$E:$E,MATCH($B50,Cost_Centers!$A:$A,0)),"(unknown)")) | Y50: =IF($B50="","",IFERROR(INDEX(Cost_Centers!$D:$D,MATCH($B50,Cost_Centers!$A:$A,0)),"(unknown)")) | Z50: =IF(OR($B50="",$G50<>"Variance vs Budget"),"",ABS(N($V50))+ROW()/1000000000)
A51: =IF(A$50="","",A$50) | B51: =IF(B$50="","",B$50) | C51: =IF(C$50="","",C$50) | D51: =IF(D$50="","",D$50) | E51: =IF(E$50="","",E$50) | F51: =IF(F$50="","",F$50) | G51: Actual | H51: =IF(OR($B$50="",1>$C$4),"",SUMIFS(Actuals!$G:$G,Actuals!$B:$B,$C$3,Actuals!$C:$C,1,Actuals!$D:$D,$B$50,Actuals!$A:$A,LEFT($D$50,FIND("|",$D$50&"|")-1),Actuals!$E:$E,MID($D$50,FIND("|",$D$50&"|")+1,50),Actuals!$F:$F,"JPY")*$E$5+SUMIFS(Actuals!$G:$G,Actuals!$B:$B,$C$3,Actuals!$C:$C,1,Actuals!$D:$D,$B$50,Actuals!$A:$A,LEFT($D$50,FIND("|",$D$50&"|")-1),Actuals!$E:$E,MID($D$50,FIND("|",$D$50&"|")+1,50),Actuals!$F:$F,"USD")*$F$5+SUMIFS(Actuals!$G:$G,Actuals!$B:$B,$C$3,Actuals!$C:$C,1,Actuals!$D:$D,$B$50,Actuals!$A:$A,LEFT($D$50,FIND("|",$D$50&"|")-1),Actuals!$E:$E,MID($D$50,FIND("|",$D$50&"|")+1,50),Actuals!$F:$F,"EUR")*$G$5+SUMIFS(Actuals!$G:$G,Actuals!$B:$B,$C$3,Actuals!$C:$C,1,Actuals!$D:$D,$B$50,Actuals!$A:$A,LEFT($D$50,FIND("|",$D$50&"|")-1),Actuals!$E:$E,MID($D$50,FIND("|",$D$50&"|")+1,50),Actuals!$F:$F,"GBP")*$H$5) | I51: =IF(OR($B$50="",2>$C$4),"",SUMIFS(Actuals!$G:$G,Actuals!$B:$B,$C$3,Actuals!$C:$C,2,Actuals!$D:$D,$B$50,Actuals!$A:$A,LEFT($D$50,FIND("|",$D$50&"|")-1),Actuals!$E:$E,MID($D$50,FIND("|",$D$50&"|")+1,50),Actuals!$F:$F,"JPY")*$E$5+SUMIFS(Actuals!$G:$G,Actuals!$B:$B,$C$3,Actuals!$C:$C,2,Actuals!$D:$D,$B$50,Actuals!$A:$A,LEFT($D$50,FIND("|",$D$50&"|")-1),Actuals!$E:$E,MID($D$50,FIND("|",$D$50&"|")+1,50),Actuals!$F:$F,"USD")*$F$5+SUMIFS(Actuals!$G:$G,Actuals!$B:$B,$C$3,Actuals!$C:$C,2,Actuals!$D:$D,$B$50,Actuals!$A:$A,LEFT($D$50,FIND("|",$D$50&"|")-1),Actuals!$E:$E,MID($D$50,FIND("|",$D$50&"|")+1,50),Actuals!$F:$F,"EUR")*$G$5+SUMIFS(Actuals!$G:$G,Actuals!$B:$B,$C$3,Actuals!$C:$C,2,Actuals!$D:$D,$B$50,Actuals!$A:$A,LEFT($D$50,FIND("|",$D$50&"|")-1),Actuals!$E:$E,MID($D$50,FIND("|",$D$50&"|")+1,50),Actuals!$F:$F,"GBP")*$H$5) | J51: =IF(OR($B$50="",3>$C$4),"",SUMIFS(Actuals!$G:$G,Actuals!$B:$B,$C$3,Actuals!$C:$C,3,Actuals!$D:$D,$B$50,Actuals!$A:$A,LEFT($D$50,FIND("|",$D$50&"|")-1),Actuals!$E:$E,MID($D$50,FIND("|",$D$50&"|")+1,50),Actuals!$F:$F,"JPY")*$E$5+SUMIFS(Actuals!$G:$G,Actuals!$B:$B,$C$3,Actuals!$C:$C,3,Actuals!$D:$D,$B$50,Actuals!$A:$A,LEFT($D$50,FIND("|",$D$50&"|")-1),Actuals!$E:$E,MID($D$50,FIND("|",$D$50&"|")+1,50),Actuals!$F:$F,"USD")*$F$5+SUMIFS(Actuals!$G:$G,Actuals!$B:$B,$C$3,Actuals!$C:$C,3,Actuals!$D:$D,$B$50,Actuals!$A:$A,LEFT($D$50,FIND("|",$D$50&"|")-1),Actuals!$E:$E,MID($D$50,FIND("|",$D$50&"|")+1,50),Actuals!$F:$F,"EUR")*$G$5+SUMIFS(Actuals!$G:$G,Actuals!$B:$B,$C$3,Actuals!$C:$C,3,Actuals!$D:$D,$B$50,Actuals!$A:$A,LEFT($D$50,FIND("|",$D$50&"|")-1),Actuals!$E:$E,MID($D$50,FIND("|",$D$50&"|")+1,50),Actuals!$F:$F,"GBP")*$H$5) | K51: =IF(OR($B$50="",4>$C$4),"",SUMIFS(Actuals!$G:$G,Actuals!$B:$B,$C$3,Actuals!$C:$C,4,Actuals!$D:$D,$B$50,Actuals!$A:$A,LEFT($D$50,FIND("|",$D$50&"|")-1),Actuals!$E:$E,MID($D$50,FIND("|",$D$50&"|")+1,50),Actuals!$F:$F,"JPY")*$E$5+SUMIFS(Actuals!$G:$G,Actuals!$B:$B,$C$3,Actuals!$C:$C,4,Actuals!$D:$D,$B$50,Actuals!$A:$A,LEFT($D$50,FIND("|",$D$50&"|")-1),Actuals!$E:$E,MID($D$50,FIND("|",$D$50&"|")+1,50),Actuals!$F:$F,"USD")*$F$5+SUMIFS(Actuals!$G:$G,Actuals!$B:$B,$C$3,Actuals!$C:$C,4,Actuals!$D:$D,$B$50,Actuals!$A:$A,LEFT($D$50,FIND("|",$D$50&"|")-1),Actuals!$E:$E,MID($D$50,FIND("|",$D$50&"|")+1,50),Actuals!$F:$F,"EUR")*$G$5+SUMIFS(Actuals!$G:$G,Actuals!$B:$B,$C$3,Actuals!$C:$C,4,Actuals!$D:$D,$B$50,Actuals!$A:$A,LEFT($D$50,FIND("|",$D$50&"|")-1),Actuals!$E:$E,MID($D$50,FIND("|",$D$50&"|")+1,50),Actuals!$F:$F,"GBP")*$H$5) | L51: =IF(OR($B$50="",5>$C$4),"",SUMIFS(Actuals!$G:$G,Actuals!$B:$B,$C$3,Actuals!$C:$C,5,Actuals!$D:$D,$B$50,Actuals!$A:$A,LEFT($D$50,FIND("|",$D$50&"|")-1),Actuals!$E:$E,MID($D$50,FIND("|",$D$50&"|")+1,50),Actuals!$F:$F,"JPY")*$E$5+SUMIFS(Actuals!$G:$G,Actuals!$B:$B,$C$3,Actuals!$C:$C,5,Actuals!$D:$D,$B$50,Actuals!$A:$A,LEFT($D$50,FIND("|",$D$50&"|")-1),Actuals!$E:$E,MID($D$50,FIND("|",$D$50&"|")+1,50),Actuals!$F:$F,"USD")*$F$5+SUMIFS(Actuals!$G:$G,Actuals!$B:$B,$C$3,Actuals!$C:$C,5,Actuals!$D:$D,$B$50,Actuals!$A:$A,LEFT($D$50,FIND("|",$D$50&"|")-1),Actuals!$E:$E,MID($D$50,FIND("|",$D$50&"|")+1,50),Actuals!$F:$F,"EUR")*$G$5+SUMIFS(Actuals!$G:$G,Actuals!$B:$B,$C$3,Actuals!$C:$C,5,Actuals!$D:$D,$B$50,Actuals!$A:$A,LEFT($D$50,FIND("|",$D$50&"|")-1),Actuals!$E:$E,MID($D$50,FIND("|",$D$50&"|")+1,50),Actuals!$F:$F,"GBP")*$H$5) | M51: =IF(OR($B$50="",6>$C$4),"",SUMIFS(Actuals!$G:$G,Actuals!$B:$B,$C$3,Actuals!$C:$C,6,Actuals!$D:$D,$B$50,Actuals!$A:$A,LEFT($D$50,FIND("|",$D$50&"|")-1),Actuals!$E:$E,MID($D$50,FIND("|",$D$50&"|")+1,50),Actuals!$F:$F,"JPY")*$E$5+SUMIFS(Actuals!$G:$G,Actuals!$B:$B,$C$3,Actuals!$C:$C,6,Actuals!$D:$D,$B$50,Actuals!$A:$A,LEFT($D$50,FIND("|",$D$50&"|")-1),Actuals!$E:$E,MID($D$50,FIND("|",$D$50&"|")+1,50),Actuals!$F:$F,"USD")*$F$5+SUMIFS(Actuals!$G:$G,Actuals!$B:$B,$C$3,Actuals!$C:$C,6,Actuals!$D:$D,$B$50,Actuals!$A:$A,LEFT($D$50,FIND("|",$D$50&"|")-1),Actuals!$E:$E,MID($D$50,FIND("|",$D$50&"|")+1,50),Actuals!$F:$F,"EUR")*$G$5+SUMIFS(Actuals!$G:$G,Actuals!$B:$B,$C$3,Actuals!$C:$C,6,Actuals!$D:$D,$B$50,Actuals!$A:$A,LEFT($D$50,FIND("|",$D$50&"|")-1),Actuals!$E:$E,MID($D$50,FIND("|",$D$50&"|")+1,50),Actuals!$F:$F,"GBP")*$H$5) | N51: =IF(OR($B$50="",7>$C$4),"",SUMIFS(Actuals!$G:$G,Actuals!$B:$B,$C$3,Actuals!$C:$C,7,Actuals!$D:$D,$B$50,Actuals!$A:$A,LEFT($D$50,FIND("|",$D$50&"|")-1),Actuals!$E:$E,MID($D$50,FIND("|",$D$50&"|")+1,50),Actuals!$F:$F,"JPY")*$E$5+SUMIFS(Actuals!$G:$G,Actuals!$B:$B,$C$3,Actuals!$C:$C,7,Actuals!$D:$D,$B$50,Actuals!$A:$A,LEFT($D$50,FIND("|",$D$50&"|")-1),Actuals!$E:$E,MID($D$50,FIND("|",$D$50&"|")+1,50),Actuals!$F:$F,"USD")*$F$5+SUMIFS(Actuals!$G:$G,Actuals!$B:$B,$C$3,Actuals!$C:$C,7,Actuals!$D:$D,$B$50,Actuals!$A:$A,LEFT($D$50,FIND("|",$D$50&"|")-1),Actuals!$E:$E,MID($D$50,FIND("|",$D$50&"|")+1,50),Actuals!$F:$F,"EUR")*$G$5+SUMIFS(Actuals!$G:$G,Actuals!$B:$B,$C$3,Actuals!$C:$C,7,Actuals!$D:$D,$B$50,Actuals!$A:$A,LEFT($D$50,FIND("|",$D$50&"|")-1),Actuals!$E:$E,MID($D$50,FIND("|",$D$50&"|")+1,50),Actuals!$F:$F,"GBP")*$H$5) | O51: =IF(OR($B$50="",8>$C$4),"",SUMIFS(Actuals!$G:$G,Actuals!$B:$B,$C$3,Actuals!$C:$C,8,Actuals!$D:$D,$B$50,Actuals!$A:$A,LEFT($D$50,FIND("|",$D$50&"|")-1),Actuals!$E:$E,MID($D$50,FIND("|",$D$50&"|")+1,50),Actuals!$F:$F,"JPY")*$E$5+SUMIFS(Actuals!$G:$G,Actuals!$B:$B,$C$3,Actuals!$C:$C,8,Actuals!$D:$D,$B$50,Actuals!$A:$A,LEFT($D$50,FIND("|",$D$50&"|")-1),Actuals!$E:$E,MID($D$50,FIND("|",$D$50&"|")+1,50),Actuals!$F:$F,"USD")*$F$5+SUMIFS(Actuals!$G:$G,Actuals!$B:$B,$C$3,Actuals!$C:$C,8,Actuals!$D:$D,$B$50,Actuals!$A:$A,LEFT($D$50,FIND("|",$D$50&"|")-1),Actuals!$E:$E,MID($D$50,FIND("|",$D$50&"|")+1,50),Actuals!$F:$F,"EUR")*$G$5+SUMIFS(Actuals!$G:$G,Actuals!$B:$B,$C$3,Actuals!$C:$C,8,Actuals!$D:$D,$B$50,Actuals!$A:$A,LEFT($D$50,FIND("|",$D$50&"|")-1),Actuals!$E:$E,MID($D$50,FIND("|",$D$50&"|")+1,50),Actuals!$F:$F,"GBP")*$H$5) | P51: =IF(OR($B$50="",9>$C$4),"",SUMIFS(Actuals!$G:$G,Actuals!$B:$B,$C$3,Actuals!$C:$C,9,Actuals!$D:$D,$B$50,Actuals!$A:$A,LEFT($D$50,FIND("|",$D$50&"|")-1),Actuals!$E:$E,MID($D$50,FIND("|",$D$50&"|")+1,50),Actuals!$F:$F,"JPY")*$E$5+SUMIFS(Actuals!$G:$G,Actuals!$B:$B,$C$3,Actuals!$C:$C,9,Actuals!$D:$D,$B$50,Actuals!$A:$A,LEFT($D$50,FIND("|",$D$50&"|")-1),Actuals!$E:$E,MID($D$50,FIND("|",$D$50&"|")+1,50),Actuals!$F:$F,"USD")*$F$5+SUMIFS(Actuals!$G:$G,Actuals!$B:$B,$C$3,Actuals!$C:$C,9,Actuals!$D:$D,$B$50,Actuals!$A:$A,LEFT($D$50,FIND("|",$D$50&"|")-1),Actuals!$E:$E,MID($D$50,FIND("|",$D$50&"|")+1,50),Actuals!$F:$F,"EUR")*$G$5+SUMIFS(Actuals!$G:$G,Actuals!$B:$B,$C$3,Actuals!$C:$C,9,Actuals!$D:$D,$B$50,Actuals!$A:$A,LEFT($D$50,FIND("|",$D$50&"|")-1),Actuals!$E:$E,MID($D$50,FIND("|",$D$50&"|")+1,50),Actuals!$F:$F,"GBP")*$H$5) | Q51: =IF(OR($B$50="",10>$C$4),"",SUMIFS(Actuals!$G:$G,Actuals!$B:$B,$C$3,Actuals!$C:$C,10,Actuals!$D:$D,$B$50,Actuals!$A:$A,LEFT($D$50,FIND("|",$D$50&"|")-1),Actuals!$E:$E,MID($D$50,FIND("|",$D$50&"|")+1,50),Actuals!$F:$F,"JPY")*$E$5+SUMIFS(Actuals!$G:$G,Actuals!$B:$B,$C$3,Actuals!$C:$C,10,Actuals!$D:$D,$B$50,Actuals!$A:$A,LEFT($D$50,FIND("|",$D$50&"|")-1),Actuals!$E:$E,MID($D$50,FIND("|",$D$50&"|")+1,50),Actuals!$F:$F,"USD")*$F$5+SUMIFS(Actuals!$G:$G,Actuals!$B:$B,$C$3,Actuals!$C:$C,10,Actuals!$D:$D,$B$50,Actuals!$A:$A,LEFT($D$50,FIND("|",$D$50&"|")-1),Actuals!$E:$E,MID($D$50,FIND("|",$D$50&"|")+1,50),Actuals!$F:$F,"EUR")*$G$5+SUMIFS(Actuals!$G:$G,Actuals!$B:$B,$C$3,Actuals!$C:$C,10,Actuals!$D:$D,$B$50,Actuals!$A:$A,LEFT($D$50,FIND("|",$D$50&"|")-1),Actuals!$E:$E,MID($D$50,FIND("|",$D$50&"|")+1,50),Actuals!$F:$F,"GBP")*$H$5) | R51: =IF(OR($B$50="",11>$C$4),"",SUMIFS(Actuals!$G:$G,Actuals!$B:$B,$C$3,Actuals!$C:$C,11,Actuals!$D:$D,$B$50,Actuals!$A:$A,LEFT($D$50,FIND("|",$D$50&"|")-1),Actuals!$E:$E,MID($D$50,FIND("|",$D$50&"|")+1,50),Actuals!$F:$F,"JPY")*$E$5+SUMIFS(Actuals!$G:$G,Actuals!$B:$B,$C$3,Actuals!$C:$C,11,Actuals!$D:$D,$B$50,Actuals!$A:$A,LEFT($D$50,FIND("|",$D$50&"|")-1),Actuals!$E:$E,MID($D$50,FIND("|",$D$50&"|")+1,50),Actuals!$F:$F,"USD")*$F$5+SUMIFS(Actuals!$G:$G,Actuals!$B:$B,$C$3,Actuals!$C:$C,11,Actuals!$D:$D,$B$50,Actuals!$A:$A,LEFT($D$50,FIND("|",$D$50&"|")-1),Actuals!$E:$E,MID($D$50,FIND("|",$D$50&"|")+1,50),Actuals!$F:$F,"EUR")*$G$5+SUMIFS(Actuals!$G:$G,Actuals!$B:$B,$C$3,Actuals!$C:$C,11,Actuals!$D:$D,$B$50,Actuals!$A:$A,LEFT($D$50,FIND("|",$D$50&"|")-1),Actuals!$E:$E,MID($D$50,FIND("|",$D$50&"|")+1,50),Actuals!$F:$F,"GBP")*$H$5) | S51: =IF(OR($B$50="",12>$C$4),"",SUMIFS(Actuals!$G:$G,Actuals!$B:$B,$C$3,Actuals!$C:$C,12,Actuals!$D:$D,$B$50,Actuals!$A:$A,LEFT($D$50,FIND("|",$D$50&"|")-1),Actuals!$E:$E,MID($D$50,FIND("|",$D$50&"|")+1,50),Actuals!$F:$F,"JPY")*$E$5+SUMIFS(Actuals!$G:$G,Actuals!$B:$B,$C$3,Actuals!$C:$C,12,Actuals!$D:$D,$B$50,Actuals!$A:$A,LEFT($D$50,FIND("|",$D$50&"|")-1),Actuals!$E:$E,MID($D$50,FIND("|",$D$50&"|")+1,50),Actuals!$F:$F,"USD")*$F$5+SUMIFS(Actuals!$G:$G,Actuals!$B:$B,$C$3,Actuals!$C:$C,12,Actuals!$D:$D,$B$50,Actuals!$A:$A,LEFT($D$50,FIND("|",$D$50&"|")-1),Actuals!$E:$E,MID($D$50,FIND("|",$D$50&"|")+1,50),Actuals!$F:$F,"EUR")*$G$5+SUMIFS(Actuals!$G:$G,Actuals!$B:$B,$C$3,Actuals!$C:$C,12,Actuals!$D:$D,$B$50,Actuals!$A:$A,LEFT($D$50,FIND("|",$D$50&"|")-1),Actuals!$E:$E,MID($D$50,FIND("|",$D$50&"|")+1,50),Actuals!$F:$F,"GBP")*$H$5) | T51: =IF($B$50="","",SUMIF($H$7:$S$7,"<="&$C$4,$H51:$S51)) | X51: =IF($B51="","",IFERROR(INDEX(Cost_Centers!$E:$E,MATCH($B51,Cost_Centers!$A:$A,0)),"(unknown)")) | Y51: =IF($B51="","",IFERROR(INDEX(Cost_Centers!$D:$D,MATCH($B51,Cost_Centers!$A:$A,0)),"(unknown)")) | Z51: =IF(OR($B51="",$G51<>"Variance vs Budget"),"",ABS(N($V51))+ROW()/1000000000)
A52: =IF(A$50="","",A$50) | B52: =IF(B$50="","",B$50) | C52: =IF(C$50="","",C$50) | D52: =IF(D$50="","",D$50) | E52: =IF(E$50="","",E$50) | F52: =IF(F$50="","",F$50) | G52: Variance vs Budget | H52: =IF(OR($B$50="",1>$C$4),"",N(H51)-H50) | I52: =IF(OR($B$50="",2>$C$4),"",N(I51)-I50) | J52: =IF(OR($B$50="",3>$C$4),"",N(J51)-J50) | K52: =IF(OR($B$50="",4>$C$4),"",N(K51)-K50) | L52: =IF(OR($B$50="",5>$C$4),"",N(L51)-L50) | M52: =IF(OR($B$50="",6>$C$4),"",N(M51)-M50) | N52: =IF(OR($B$50="",7>$C$4),"",N(N51)-N50) | O52: =IF(OR($B$50="",8>$C$4),"",N(O51)-O50) | P52: =IF(OR($B$50="",9>$C$4),"",N(P51)-P50) | Q52: =IF(OR($B$50="",10>$C$4),"",N(Q51)-Q50) | R52: =IF(OR($B$50="",11>$C$4),"",N(R51)-R50) | S52: =IF(OR($B$50="",12>$C$4),"",N(S51)-S50) | T52: =IF($B$50="","",T51-T50) | U52: =IF($B$50="","",U54-U50) | V52: =IF($B$50="","",V54-V50) | X52: =IF($B52="","",IFERROR(INDEX(Cost_Centers!$E:$E,MATCH($B52,Cost_Centers!$A:$A,0)),"(unknown)")) | Y52: =IF($B52="","",IFERROR(INDEX(Cost_Centers!$D:$D,MATCH($B52,Cost_Centers!$A:$A,0)),"(unknown)")) | Z52: =IF(OR($B52="",$G52<>"Variance vs Budget"),"",ABS(N($V52))+ROW()/1000000000)
A53: =IF(A$50="","",A$50) | B53: =IF(B$50="","",B$50) | C53: =IF(C$50="","",C$50) | D53: =IF(D$50="","",D$50) | E53: =IF(E$50="","",E$50) | F53: =IF(F$50="","",F$50) | G53: Forecast (input) | X53: =IF($B53="","",IFERROR(INDEX(Cost_Centers!$E:$E,MATCH($B53,Cost_Centers!$A:$A,0)),"(unknown)")) | Y53: =IF($B53="","",IFERROR(INDEX(Cost_Centers!$D:$D,MATCH($B53,Cost_Centers!$A:$A,0)),"(unknown)")) | Z53: =IF(OR($B53="",$G53<>"Variance vs Budget"),"",ABS(N($V53))+ROW()/1000000000)
A54: =IF(A$50="","",A$50) | B54: =IF(B$50="","",B$50) | C54: =IF(C$50="","",C$50) | D54: =IF(D$50="","",D$50) | E54: =IF(E$50="","",E$50) | F54: =IF(F$50="","",F$50) | G54: Actual + Forecast | H54: =IF($B$50="","",IF(1<=$C$4,N(H51),IF(H53="",H50,H53))) | I54: =IF($B$50="","",IF(2<=$C$4,N(I51),IF(I53="",I50,I53))) | J54: =IF($B$50="","",IF(3<=$C$4,N(J51),IF(J53="",J50,J53))) | K54: =IF($B$50="","",IF(4<=$C$4,N(K51),IF(K53="",K50,K53))) | L54: =IF($B$50="","",IF(5<=$C$4,N(L51),IF(L53="",L50,L53))) | M54: =IF($B$50="","",IF(6<=$C$4,N(M51),IF(M53="",M50,M53))) | N54: =IF($B$50="","",IF(7<=$C$4,N(N51),IF(N53="",N50,N53))) | O54: =IF($B$50="","",IF(8<=$C$4,N(O51),IF(O53="",O50,O53))) | P54: =IF($B$50="","",IF(9<=$C$4,N(P51),IF(P53="",P50,P53))) | Q54: =IF($B$50="","",IF(10<=$C$4,N(Q51),IF(Q53="",Q50,Q53))) | R54: =IF($B$50="","",IF(11<=$C$4,N(R51),IF(R53="",R50,R53))) | S54: =IF($B$50="","",IF(12<=$C$4,N(S51),IF(S53="",S50,S53))) | T54: =IF($B$50="","",SUMIF($H$7:$S$7,"<="&$C$4,$H54:$S54)) | U54: =IF($B$50="","",SUMIF($H$7:$S$7,">"&$C$4,$H54:$S54)) | V54: =IF($B$50="","",SUM($H54:$S54)) | X54: =IF($B54="","",IFERROR(INDEX(Cost_Centers!$E:$E,MATCH($B54,Cost_Centers!$A:$A,0)),"(unknown)")) | Y54: =IF($B54="","",IFERROR(INDEX(Cost_Centers!$D:$D,MATCH($B54,Cost_Centers!$A:$A,0)),"(unknown)")) | Z54: =IF(OR($B54="",$G54<>"Variance vs Budget"),"",ABS(N($V54))+ROW()/1000000000)
A55: =IF(A$50="","",A$50) | B55: =IF(B$50="","",B$50) | C55: =IF(C$50="","",C$50) | D55: =IF(D$50="","",D$50) | E55: =IF(E$50="","",E$50) | F55: =IF(F$50="","",F$50) | G55: Prior Month Forecast | H55: =IF($B$50="","",IF(COUNTIFS(Prior_Forecast!$A:$A,$B$50,Prior_Forecast!$B:$B,$D$50)>0,SUMIFS(Prior_Forecast!$C:$C,Prior_Forecast!$A:$A,$B$50,Prior_Forecast!$B:$B,$D$50),"")) | I55: =IF($B$50="","",IF(COUNTIFS(Prior_Forecast!$A:$A,$B$50,Prior_Forecast!$B:$B,$D$50)>0,SUMIFS(Prior_Forecast!$D:$D,Prior_Forecast!$A:$A,$B$50,Prior_Forecast!$B:$B,$D$50),"")) | J55: =IF($B$50="","",IF(COUNTIFS(Prior_Forecast!$A:$A,$B$50,Prior_Forecast!$B:$B,$D$50)>0,SUMIFS(Prior_Forecast!$E:$E,Prior_Forecast!$A:$A,$B$50,Prior_Forecast!$B:$B,$D$50),"")) | K55: =IF($B$50="","",IF(COUNTIFS(Prior_Forecast!$A:$A,$B$50,Prior_Forecast!$B:$B,$D$50)>0,SUMIFS(Prior_Forecast!$F:$F,Prior_Forecast!$A:$A,$B$50,Prior_Forecast!$B:$B,$D$50),"")) | L55: =IF($B$50="","",IF(COUNTIFS(Prior_Forecast!$A:$A,$B$50,Prior_Forecast!$B:$B,$D$50)>0,SUMIFS(Prior_Forecast!$G:$G,Prior_Forecast!$A:$A,$B$50,Prior_Forecast!$B:$B,$D$50),"")) | M55: =IF($B$50="","",IF(COUNTIFS(Prior_Forecast!$A:$A,$B$50,Prior_Forecast!$B:$B,$D$50)>0,SUMIFS(Prior_Forecast!$H:$H,Prior_Forecast!$A:$A,$B$50,Prior_Forecast!$B:$B,$D$50),"")) | N55: =IF($B$50="","",IF(COUNTIFS(Prior_Forecast!$A:$A,$B$50,Prior_Forecast!$B:$B,$D$50)>0,SUMIFS(Prior_Forecast!$I:$I,Prior_Forecast!$A:$A,$B$50,Prior_Forecast!$B:$B,$D$50),"")) | O55: =IF($B$50="","",IF(COUNTIFS(Prior_Forecast!$A:$A,$B$50,Prior_Forecast!$B:$B,$D$50)>0,SUMIFS(Prior_Forecast!$J:$J,Prior_Forecast!$A:$A,$B$50,Prior_Forecast!$B:$B,$D$50),"")) | P55: =IF($B$50="","",IF(COUNTIFS(Prior_Forecast!$A:$A,$B$50,Prior_Forecast!$B:$B,$D$50)>0,SUMIFS(Prior_Forecast!$K:$K,Prior_Forecast!$A:$A,$B$50,Prior_Forecast!$B:$B,$D$50),"")) | Q55: =IF($B$50="","",IF(COUNTIFS(Prior_Forecast!$A:$A,$B$50,Prior_Forecast!$B:$B,$D$50)>0,SUMIFS(Prior_Forecast!$L:$L,Prior_Forecast!$A:$A,$B$50,Prior_Forecast!$B:$B,$D$50),"")) | R55: =IF($B$50="","",IF(COUNTIFS(Prior_Forecast!$A:$A,$B$50,Prior_Forecast!$B:$B,$D$50)>0,SUMIFS(Prior_Forecast!$M:$M,Prior_Forecast!$A:$A,$B$50,Prior_Forecast!$B:$B,$D$50),"")) | S55: =IF($B$50="","",IF(COUNTIFS(Prior_Forecast!$A:$A,$B$50,Prior_Forecast!$B:$B,$D$50)>0,SUMIFS(Prior_Forecast!$N:$N,Prior_Forecast!$A:$A,$B$50,Prior_Forecast!$B:$B,$D$50),"")) | T55: =IF($B$50="","",IF(COUNTIFS(Prior_Forecast!$A:$A,$B$50,Prior_Forecast!$B:$B,$D$50)>0,SUMIFS(Prior_Forecast!$O:$O,Prior_Forecast!$A:$A,$B$50,Prior_Forecast!$B:$B,$D$50),"")) | U55: =IF($B$50="","",IF(COUNTIFS(Prior_Forecast!$A:$A,$B$50,Prior_Forecast!$B:$B,$D$50)>0,SUMIFS(Prior_Forecast!$P:$P,Prior_Forecast!$A:$A,$B$50,Prior_Forecast!$B:$B,$D$50),"")) | V55: =IF($B$50="","",IF(COUNTIFS(Prior_Forecast!$A:$A,$B$50,Prior_Forecast!$B:$B,$D$50)>0,SUMIFS(Prior_Forecast!$Q:$Q,Prior_Forecast!$A:$A,$B$50,Prior_Forecast!$B:$B,$D$50),"")) | X55: =IF($B55="","",IFERROR(INDEX(Cost_Centers!$E:$E,MATCH($B55,Cost_Centers!$A:$A,0)),"(unknown)")) | Y55: =IF($B55="","",IFERROR(INDEX(Cost_Centers!$D:$D,MATCH($B55,Cost_Centers!$A:$A,0)),"(unknown)")) | Z55: =IF(OR($B55="",$G55<>"Variance vs Budget"),"",ABS(N($V55))+ROW()/1000000000)
A56: =IF(A$50="","",A$50) | B56: =IF(B$50="","",B$50) | C56: =IF(C$50="","",C$50) | D56: =IF(D$50="","",D$50) | E56: =IF(E$50="","",E$50) | F56: =IF(F$50="","",F$50) | G56: Variance vs Prior Month | H56: =IF(OR($B$50="",H55=""),"",H54-H55) | I56: =IF(OR($B$50="",I55=""),"",I54-I55) | J56: =IF(OR($B$50="",J55=""),"",J54-J55) | K56: =IF(OR($B$50="",K55=""),"",K54-K55) | L56: =IF(OR($B$50="",L55=""),"",L54-L55) | M56: =IF(OR($B$50="",M55=""),"",M54-M55) | N56: =IF(OR($B$50="",N55=""),"",N54-N55) | O56: =IF(OR($B$50="",O55=""),"",O54-O55) | ... V56: =IF(OR($B$50="",V55=""),"",V54-V55) | X56: =IF($B56="","",IFERROR(INDEX(Cost_Centers!$E:$E,MATCH($B56,Cost_Centers!$A:$A,0)),"(unknown)")) | Y56: =IF($B56="","",IFERROR(INDEX(Cost_Centers!$D:$D,MATCH($B56,Cost_Centers!$A:$A,0)),"(unknown)")) | Z56: =IF(OR($B56="",$G56<>"Variance vs Budget"),"",ABS(N($V56))+ROW()/1000000000)
A57: =IF(A$50="","",A$50) | B57: =IF(B$50="","",B$50) | C57: =IF(C$50="","",C$50) | D57: =IF(D$50="","",D$50) | E57: =IF(E$50="","",E$50) | F57: =IF(F$50="","",F$50) | G57: Rationale | X57: =IF($B57="","",IFERROR(INDEX(Cost_Centers!$E:$E,MATCH($B57,Cost_Centers!$A:$A,0)),"(unknown)")) | Y57: =IF($B57="","",IFERROR(INDEX(Cost_Centers!$D:$D,MATCH($B57,Cost_Centers!$A:$A,0)),"(unknown)")) | Z57: =IF(OR($B57="",$G57<>"Variance vs Budget"),"",ABS(N($V57))+ROW()/1000000000)
