Workbook
Name lst_region: OFFSET(Lists!$A$2,0,0,MAX(1,COUNTA(Lists!$A$2:$A$100)),1)
Name lst_currency: OFFSET(Lists!$B$2,0,0,MAX(1,COUNTA(Lists!$B$2:$B$100)),1)
Name lst_contract_type: OFFSET(Lists!$C$2,0,0,MAX(1,COUNTA(Lists!$C$2:$C$100)),1)
Name lst_employment_type: OFFSET(Lists!$D$2,0,0,MAX(1,COUNTA(Lists!$D$2:$D$100)),1)
Name lst_allocation_type: OFFSET(Lists!$E$2,0,0,MAX(1,COUNTA(Lists!$E$2:$E$100)),1)
Name lst_source_type: OFFSET(Lists!$F$2,0,0,MAX(1,COUNTA(Lists!$F$2:$F$100)),1)
Name lst_rate_type: OFFSET(Lists!$G$2,0,0,MAX(1,COUNTA(Lists!$G$2:$G$100)),1)
Name lst_yes_no: OFFSET(Lists!$H$2,0,0,MAX(1,COUNTA(Lists!$H$2:$H$100)),1)
Name lst_cost_center: OFFSET(Cost_Centers!$A$2,0,0,MAX(1,COUNTA(Cost_Centers!$A$2:$A$2000)),1)
Name lst_account: OFFSET(Accounts!$A$2,0,0,MAX(1,COUNTA(Accounts!$A$2:$A$5000)),1)

Sheet Field_Definitions
A1: GDS Budget Utility – Field Definitions / 項目定義
A3: How to use / 使い方
A4: • | B4: Keep your own copy of this file. Enter contracts, assets and staff; the Export sheet converts them into Opex_Budget rows. | E4: このファイルは各自で1つ持ちます。契約・資産・要員を入力すると、Exportシートが予算の行（Opex_Budget形式）に変換します。
A5: • | B5: To transfer: on Export, filter row_total (column X) to exclude 0, copy columns A to V of the visible rows, and paste as values at the end of Opex_Budget in the ledger. | E5: 転記の手順：Exportでrow_total（X列）が0の行を除外し、表示されている行のA〜V列をコピーして、共有台帳のOpex_Budgetの末尾に値で貼り付けます。
A6: • | B6: Before pasting an update, delete the rows you pasted last time from Opex_Budget. | E6: 更新して貼り直すときは、前回貼り付けた自分の行をOpex_Budgetから先に削除してください。
A7: • | B7: Enter one record per row. Do not insert blank rows, merge cells or change column headers. | E7: 1行に1件を入力します。空行の挿入、セルの結合、列見出しの変更はしないでください。
A8: • | B8: Yes = required. Yes* = required depending on the type (see description). Use the dropdowns for List fields. | E8: Yes＝必須。Yes*＝種別によって必須（説明を参照）。List型はプルダウンから選びます。
A9: • | B9: Dates: YYYY-MM-DD. Amounts: excluding tax, in the currency of the row. Do not convert currencies. | E9: 日付はYYYY-MM-DD。金額は税抜で、その行の通貨のまま入力します。換算はしないでください。
A10: • | B10: The Example column shows the expected format only. Do not copy example values. | E10: Example列は入力形式の例です。例の値を転記しないでください。
A11: • | B11: Grey sheets (Cost_Centers, Accounts, Projects, Lists) are copies of the master data file and must not be edited. To get the latest values, open in Excel desktop and click Data > Refresh All (not needed every time). To add or change values, ask IT Finance. | E11: グレーのシート（Cost_Centers・Accounts・Projects・Lists）はマスタファイルの写しで、編集しません。最新にするときはデスクトップ版Excelで「データ＞すべて更新」を押します（毎回は不要）。値の追加・変更はITファイナンスに依頼してください。
A13: Sheets / シート一覧
A14: Sheet | B14: Maintained by | C14: Purpose (EN) | E14: 目的（日本語）
A15: Settings | B15: ITF only | C15: First fiscal year of the budget period and row counts used by Export. | E15: 予算期間の初年度と、Exportが使う行数
A16: Contracts | B16: Input | C16: Contract-driven costs: SaaS, maintenance, telecom, fixed-fee outsourcing. | E16: 契約に基づく費用（SaaS・保守・通信・月額固定の業務委託）
A17: Fixed_Assets | B17: Input | C17: Depreciation of capitalized assets. | E17: 資産計上した物品の減価償却費
A18: Workforce | B18: Input | C18: Employees and external staff paid by rate. | E18: 正社員と、単価で支払う外部人材
A19: FTE_Allocation | B19: Input | C19: How each person's cost is split across cost centers and projects, by year. | E19: 要員ごとの費用を、年ごとにコストセンター・プロジェクトへ配分する比率
A20: Export | B20: Auto (do not edit) | C20: Rows in Opex_Budget format, calculated from the four input sheets. Copy columns A to V and paste as values into the ledger. | E20: 4つの入力シートから計算した、Opex_Budget形式の行。A〜V列をコピーして共有台帳に値で貼り付ける
A22: Contracts — Input
A23: Sheet | B23: Field (EN) | C23: 項目名（日本語） | D23: Type | E23: Required | F23: Example | G23: Description (EN) | H23: 説明（日本語）
A24: Contracts | B24: contract_id | C24: 契約ID | D24: Text | E24: Yes | F24: CT-0001 | G24: Unique key. Also referenced from Workforce for external staff. | H24: 一意キー。外部人材の参照キーとしても使う
A25: Contracts | B25: budget_id | C25: 予算ID | D25: Text | E25: No | F25: BT-0012 | G25: Optional. Copied to budget_id in Opex_Budget. | H25: 任意。Opex_Budgetのbudget_idにそのまま転記される
A26: Contracts | B26: contract_group_id | C26: 契約グループID | D26: Text | E26: No | F26: G-M365 | G26: Groups yearly rows of the same multi-year contract. | H26: 複数年契約を年度ごとに分けた行を束ねるキー
A27: Contracts | B27: region | C27: リージョン | D27: List | E27: Yes | F27: JP | G27: Region that pays the cost. Must match the region of cost_center_code. | H27: 費用を支払うリージョン。コストセンターのリージョンと一致させる
A28: Contracts | B28: owner | C28: 入力責任者 | D28: Text | E28: Yes | F28: T. Yamada | G28: Person responsible for keeping this row up to date. | H28: この行を最新に保つ責任者
A29: Contracts | B29: vendor_name | C29: ベンダー名 | D29: Text | E29: Yes | F29: Microsoft | G29: Vendor name. | H29: ベンダー名
A30: Contracts | B30: contract_name | C30: 契約名 | D30: Text | E30: Yes | F30: M365 E5 (FY27) | G30: Contract or service name. | H30: 契約名・サービス名
A31: Contracts | B31: category | C31: カテゴリ | D31: Text | E31: No | F31: SaaS | G31: Free tag (SaaS, Telecom, Maintenance, etc.). | H31: タグ（SaaS、通信、保守など）
A32: Contracts | B32: contract_type | C32: 契約種別 | D32: List | E32: Yes | F32: PREPAID | G32: PREPAID = prepaid lump sum, amortized / MONTHLY = fixed monthly fee / RATE_REF = rate card for external staff (reference only, no budget generated). | H32: PREPAID＝前払一括型（償却）／MONTHLY＝月額固定型／RATE_REF＝業務委託単価型（単価参照専用。予算は作られない）
A33: Contracts | B33: start_date | C33: 開始日 | D33: Date | E33: Yes | F33: 2027-04-01 | G33: PREPAID: payment month (amortization starts). MONTHLY: first month of charge. | H33: 前払一括型は支払月（償却開始月）、月額固定型は計上開始月
A34: Contracts | B34: end_date_effective | C34: 終了日（実効） | D34: Date | E34: No | F34: 2028-03-31 | G34: MONTHLY only. Date the contract will actually end. Blank = continues. | H34: 月額固定型のみ。実際に契約が終了する時期。空欄は継続
... A43: Contracts | B43: unit_price_min | C43: 下限単価 | D43: Number | E43: No | F43: 1300000 | G43: RATE_REF only. Only if stated in the contract. | H43: 業務委託単価型のみ。契約書に明記がある場合だけ
A44: Contracts | B44: note | C44: 備考 | D44: Text | E44: No | G44: Free comment. | H44: 備考
A46: Fixed_Assets — Input
A47: Sheet | B47: Field (EN) | C47: 項目名（日本語） | D47: Type | E47: Required | F47: Example | G47: Description (EN) | H47: 説明（日本語）
A48: Fixed_Assets | B48: asset_id | C48: 資産ID | D48: Text | E48: Yes | F48: FA-0001 | G48: Unique key. | H48: 一意キー
A49: Fixed_Assets | B49: budget_id | C49: 予算ID | D49: Text | E49: No | F49: BT-0012 | G49: Optional. Copied to budget_id in Opex_Budget. | H49: 任意。Opex_Budgetのbudget_idにそのまま転記される
A50: Fixed_Assets | B50: region | C50: リージョン | D50: List | E50: Yes | F50: JP | G50: Region that acquired the asset. | H50: 資産を取得したリージョン
A51: Fixed_Assets | B51: owner | C51: 入力責任者 | D51: Text | E51: Yes | F51: T. Yamada | G51: Person responsible for keeping this row up to date. | H51: この行を最新に保つ責任者
A52: Fixed_Assets | B52: asset_name | C52: 資産名 | D52: Text | E52: Yes | F52: Laptops x120 (2027-01) | G52: Asset name or purpose. | H52: 資産名・用途
A53: Fixed_Assets | B53: asset_class | C53: 資産区分 | D53: Text | E53: No | F53: Tangible | G53: Free tag. | H53: 区分（任意）
A54: Fixed_Assets | B54: acquisition_date | C54: 取得日 | D54: Date | E54: Yes | F54: 2027-01-15 | G54: Depreciation starts in this month. | H54: 取得日。この月から償却を開始する
A55: Fixed_Assets | B55: acquisition_cost | C55: 取得価額 | D55: Number | E55: Yes | F55: 21600000 | G55: Excluding tax. | H55: 取得価額（税抜）
A56: Fixed_Assets | B56: currency | C56: 通貨 | D56: List | E56: Yes | F56: JPY | G56: Currency of acquisition. | H56: 取得時の通貨
A57: Fixed_Assets | B57: useful_life_months | C57: 耐用月数 | D57: Integer | E57: Yes | F57: 36 | G57: Internal useful life in months (straight-line). | H57: 社内耐用年数を月数で（定額法）
A58: Fixed_Assets | B58: cost_center_code | C58: コストセンター | D58: List | E58: Yes | F58: JP-GDS-INF | G58: Cost center that bears the depreciation. | H58: 減価償却費を計上するコストセンター
A59: Fixed_Assets | B59: account_key | C59: 勘定科目 | D59: List | E59: Yes | F59: JP|5201 | G59: Local account (usually depreciation). | H59: 現地勘定科目（通常は減価償却費）
A60: Fixed_Assets | B60: note | C60: 備考 | D60: Text | E60: No | G60: Free comment. | H60: 備考
A62: Workforce — Input
A63: Sheet | B63: Field (EN) | C63: 項目名（日本語） | D63: Type | E63: Required | F63: Example | G63: Description (EN) | H63: 説明（日本語）
A64: Workforce | B64: person_id | C64: 要員ID | D64: Text | E64: Yes | F64: EMP-001 | G64: Unique key. Referenced from FTE_Allocation. | H64: 一意キー。FTE_Allocationから参照される
A65: Workforce | B65: region | C65: リージョン | D65: List | E65: Yes | F65: JP | G65: Region of employment. All allocations must stay in this region. | H65: 所属リージョン。配分先はすべてこのリージョン内にする
A66: Workforce | B66: owner | C66: 入力責任者 | D66: Text | E66: Yes | F66: T. Yamada | G66: Person responsible for keeping this row up to date. | H66: この行を最新に保つ責任者
A67: Workforce | B67: person_name | C67: 氏名・識別子 | D67: Text | E67: Yes | F67: GDS Head | G67: Name or role. Not exported. | H67: 氏名または役割名。Exportには出ない
A68: Workforce | B68: employment_type | C68: 雇用区分 | D68: List | E68: Yes | F68: EMPLOYEE | G68: EMPLOYEE = employee / EXTERNAL = external staff. | H68: EMPLOYEE＝正社員／EXTERNAL＝外部人材
A69: Workforce | B69: monthly_rate | C69: 月額単価 | D69: Number | E69: Yes | F69: 1750000 | G69: Monthly cost. For EXTERNAL, enter the amount to budget (not calculated). | H69: 月額単価。外部人材は予算計上額を手入力する
A70: Workforce | B70: rate_currency | C70: 単価通貨 | D70: List | E70: Yes | F70: JPY | G70: Currency of monthly_rate. | H70: 月額単価の通貨
A71: Workforce | B71: contract_id_ref | C71: 参照契約ID | D71: Text | E71: Yes* | F71: CT-0201 | G71: EXTERNAL only. contract_id of the RATE_REF contract. | H71: 外部人材のみ。業務委託単価型の契約ID
A72: Workforce | B72: valid_from | C72: 開始日 | D72: Date | E72: No | F72: 2027-04-01 | G72: Start of employment or contract. Blank = no limit. | H72: 在籍・契約の開始。空欄は制限なし
A73: Workforce | B73: valid_to | C73: 終了日 | D73: Date | E73: No | F73: 2028-12-31 | G73: End of employment or contract. Blank = no limit. | H73: 在籍・契約の終了。空欄は制限なし
A74: Workforce | B74: account_key | C74: 勘定科目 | D74: List | E74: Yes | F74: JP|5301 | G74: Local account (salaries for EMPLOYEE, outsourcing for EXTERNAL). | H74: 現地勘定科目（正社員は給与手当、外部人材は業務委託費）
A75: Workforce | B75: note | C75: 備考 | D75: Text | E75: No | G75: Free comment. | H75: 備考
A77: FTE_Allocation — Input
A78: Sheet | B78: Field (EN) | C78: 項目名（日本語） | D78: Type | E78: Required | F78: Example | G78: Description (EN) | H78: 説明（日本語）
A79: FTE_Allocation | B79: person_id | C79: 要員ID | D79: Text | E79: Yes | F79: EMP-013 | G79: person_id in Workforce. | H79: Workforceの要員ID
A80: FTE_Allocation | B80: budget_id | C80: 予算ID | D80: Text | E80: No | F80: BT-0012 | G80: Optional. Copied to budget_id in Opex_Budget. | H80: 任意。Opex_Budgetのbudget_idにそのまま転記される
A81: FTE_Allocation | B81: owner | C81: 入力責任者 | D81: Text | E81: Yes | F81: T. Yamada | G81: Person responsible for keeping this row up to date. | H81: この行を最新に保つ責任者
A82: FTE_Allocation | B82: allocation_type | C82: 配分種別 | D82: List | E82: Yes | F82: COST_CENTER | G82: COST_CENTER = allocate to a cost center / PROJECT = allocate to a project. | H82: COST_CENTER＝コストセンターへ配分／PROJECT＝プロジェクトへ配分
A83: FTE_Allocation | B83: allocation_code | C83: 配分先 | D83: Text | E83: Yes | F83: JP-GDS-INF | G83: cost_center_code or project_code, depending on allocation_type. Same region as the person. | H83: 配分種別に応じてコストセンターコードまたはプロジェクトコード。要員と同じリージョン内
A84: FTE_Allocation | B84: fte_2027 | C84: FTE 2027 | D84: Number 0-1 | E84: No | F84: 1.0 | G84: FTE ratio for 2027. Blank = no allocation. Total per person and period must be 1.0. | H84: 2027年のFTE比率。空欄はその年の配分なし。1人・同一期間の合計は1.0
A85: FTE_Allocation | B85: fte_2028 | C85: FTE 2028 | D85: Number 0-1 | E85: No | F85: 0.7 | G85: FTE ratio for 2028. | H85: 2028年のFTE比率
A86: FTE_Allocation | B86: fte_2029 | C86: FTE 2029 | D86: Number 0-1 | E86: No | F86: 1.0 | G86: FTE ratio for 2029. | H86: 2029年のFTE比率
A87: FTE_Allocation | B87: valid_from | C87: 開始日 | D87: Date | E87: No | F87: 2028-04-01 | G87: Only if the allocation changes mid-year. Blank = whole year. | H87: 年の途中で配分が変わる場合だけ。空欄は通期
A88: FTE_Allocation | B88: valid_to | C88: 終了日 | D88: Date | E88: No | F88: 2028-09-30 | G88: Only if the allocation changes mid-year. Blank = whole year. | H88: 年の途中で配分が変わる場合だけ。空欄は通期
A89: FTE_Allocation | B89: note | C89: 備考 | D89: Text | E89: No | G89: Free comment. | H89: 備考

Sheet Contracts
A1: contract_id | B1: budget_id | C1: contract_group_id | D1: region | E1: owner | F1: vendor_name | G1: contract_name | H1: category | I1: contract_type | J1: start_date | K1: end_date_effective | L1: currency | M1: amount | N1: amortization_months | O1: chargeback_ratio | P1: cost_center_code | Q1: account_key | R1: unit_price | S1: unit_price_max | T1: unit_price_min | U1: note

Sheet Fixed_Assets
A1: asset_id | B1: budget_id | C1: region | D1: owner | E1: asset_name | F1: asset_class | G1: acquisition_date | H1: acquisition_cost | I1: currency | J1: useful_life_months | K1: cost_center_code | L1: account_key | M1: note

Sheet Workforce
A1: person_id | B1: region | C1: owner | D1: person_name | E1: employment_type | F1: monthly_rate | G1: rate_currency | H1: contract_id_ref | I1: valid_from | J1: valid_to | K1: account_key | L1: note

Sheet FTE_Allocation
A1: person_id | B1: budget_id | C1: owner | D1: allocation_type | E1: allocation_code | F1: fte_2027 | G1: fte_2028 | H1: fte_2029 | I1: valid_from | J1: valid_to | K1: note

Sheet Export
A1: fiscal_year | B1: region | C1: owner | D1: budget_id | E1: cost_center_code | F1: account_key | G1: expense_item | H1: source_type | I1: currency | J1: m01 | K1: m02 | L1: m03 | M1: m04 | N1: m05 | O1: m06 | P1: m07 | Q1: m08 | R1: m09 | S1: m10 | T1: m11 | U1: m12 | V1: note | X1: row_total | Y1: seq | Z1: src | AA1: local | AB1: idx | AC1: yidx | AD1: year | AE1: p_start | AF1: p_end | AG1: p_monthly
A2: =IF($Z2="","",$AD2) | B2: =IF($Z2="C",INDEX(Contracts!$D$2:$D$151,$AB2)&"",IF($Z2="A",INDEX(Fixed_Assets!$C$2:$C$201,$AB2)&"",IF($Z2="F",INDEX(Workforce!$B$2:$B$151,MATCH(INDEX(FTE_Allocation!$A$2:$A$201,$AB2),Workforce!$A$2:$A$151,0))&"",""))) | C2: =IF($Z2="C",INDEX(Contracts!$E$2:$E$151,$AB2)&"",IF($Z2="A",INDEX(Fixed_Assets!$D$2:$D$201,$AB2)&"",IF($Z2="F",INDEX(FTE_Allocation!$C$2:$C$201,$AB2)&"",""))) | D2: =IF($Z2="C",INDEX(Contracts!$B$2:$B$151,$AB2)&"",IF($Z2="A",INDEX(Fixed_Assets!$B$2:$B$201,$AB2)&"",IF($Z2="F",INDEX(FTE_Allocation!$B$2:$B$201,$AB2)&"",""))) | E2: =IF($Z2="C",INDEX(Contracts!$P$2:$P$151,$AB2)&"",IF($Z2="A",INDEX(Fixed_Assets!$K$2:$K$201,$AB2)&"",IF($Z2="F",IF(INDEX(FTE_Allocation!$D$2:$D$201,$AB2)="PROJECT",IFERROR(INDEX(Projects!$D:$D,MATCH(INDEX(FTE_Allocation!$E$2:$E$201,$AB2),Projects!$A:$A,0))&"","#PROJECT?"),INDEX(FTE_Allocation!$E$2:$E$201,$AB2)&""),""))) | F2: =IF($Z2="C",INDEX(Contracts!$Q$2:$Q$151,$AB2)&"",IF($Z2="A",INDEX(Fixed_Assets!$L$2:$L$201,$AB2)&"",IF($Z2="F",INDEX(Workforce!$K$2:$K$151,MATCH(INDEX(FTE_Allocation!$A$2:$A$201,$AB2),Workforce!$A$2:$A$151,0))&"",""))) | G2: =IF($Z2="C",INDEX(Contracts!$F$2:$F$151,$AB2)&" / "&INDEX(Contracts!$G$2:$G$151,$AB2),IF($Z2="A",INDEX(Fixed_Assets!$E$2:$E$201,$AB2)&"",IF($Z2="F","Personnel "&INDEX(FTE_Allocation!$A$2:$A$201,$AB2)&IF(INDEX(FTE_Allocation!$D$2:$D$201,$AB2)="PROJECT"," ("&INDEX(FTE_Allocation!$E$2:$E$201,$AB2)&")",""),""))) | H2: =IF($Z2="C","CONTRACT",IF($Z2="A","ASSET",IF($Z2="F","WORKFORCE",""))) | I2: =IF($Z2="C",INDEX(Contracts!$L$2:$L$151,$AB2)&"",IF($Z2="A",INDEX(Fixed_Assets!$I$2:$I$201,$AB2)&"",IF($Z2="F",INDEX(Workforce!$G$2:$G$151,MATCH(INDEX(FTE_Allocation!$A$2:$A$201,$AB2),Workforce!$A$2:$A$151,0))&"",""))) | J2: =IF($Z2="","",IF(AND(DATE($AD2,1,1)>=$AE2,DATE($AD2,1,1)<=$AF2),ROUND($AG2,2),0)) | K2: =IF($Z2="","",IF(AND(DATE($AD2,2,1)>=$AE2,DATE($AD2,2,1)<=$AF2),ROUND($AG2,2),0)) | L2: =IF($Z2="","",IF(AND(DATE($AD2,3,1)>=$AE2,DATE($AD2,3,1)<=$AF2),ROUND($AG2,2),0)) | M2: =IF($Z2="","",IF(AND(DATE($AD2,4,1)>=$AE2,DATE($AD2,4,1)<=$AF2),ROUND($AG2,2),0)) | N2: =IF($Z2="","",IF(AND(DATE($AD2,5,1)>=$AE2,DATE($AD2,5,1)<=$AF2),ROUND($AG2,2),0)) | O2: =IF($Z2="","",IF(AND(DATE($AD2,6,1)>=$AE2,DATE($AD2,6,1)<=$AF2),ROUND($AG2,2),0)) | P2: =IF($Z2="","",IF(AND(DATE($AD2,7,1)>=$AE2,DATE($AD2,7,1)<=$AF2),ROUND($AG2,2),0)) | Q2: =IF($Z2="","",IF(AND(DATE($AD2,8,1)>=$AE2,DATE($AD2,8,1)<=$AF2),ROUND($AG2,2),0)) | R2: =IF($Z2="","",IF(AND(DATE($AD2,9,1)>=$AE2,DATE($AD2,9,1)<=$AF2),ROUND($AG2,2),0)) | S2: =IF($Z2="","",IF(AND(DATE($AD2,10,1)>=$AE2,DATE($AD2,10,1)<=$AF2),ROUND($AG2,2),0)) | T2: =IF($Z2="","",IF(AND(DATE($AD2,11,1)>=$AE2,DATE($AD2,11,1)<=$AF2),ROUND($AG2,2),0)) | U2: =IF($Z2="","",IF(AND(DATE($AD2,12,1)>=$AE2,DATE($AD2,12,1)<=$AF2),ROUND($AG2,2),0)) | V2: =IF($Z2="C","Generated from "&INDEX(Contracts!$A$2:$A$151,$AB2),IF($Z2="A","Generated from "&INDEX(Fixed_Assets!$A$2:$A$201,$AB2),IF($Z2="F","Generated from "&INDEX(FTE_Allocation!$A$2:$A$201,$AB2),""))) | X2: =IF($Z2="","",SUM(J2:U2)) | Y2: =ROW()-1 | Z2: =IF($Y2<=Settings!$B$4*3,"C",IF($Y2<=(Settings!$B$4+Settings!$B$5)*3,"A",IF($Y2<=(Settings!$B$4+Settings!$B$5+Settings!$B$6)*3,"F",""))) | AA2: =IF($Z2="C",$Y2,IF($Z2="A",$Y2-Settings!$B$4*3,IF($Z2="F",$Y2-(Settings!$B$4+Settings!$B$5)*3,""))) | AB2: =IF($Z2="","",INT(($AA2-1)/3)+1) | AC2: =IF($Z2="","",MOD($AA2-1,3)+1) | AD2: =IF($Z2="","",Settings!$B$2+$AC2-1) | AE2: =IF($Z2="C",DATE(YEAR(INDEX(Contracts!$J$2:$J$151,$AB2)),MONTH(INDEX(Contracts!$J$2:$J$151,$AB2)),1),IF($Z2="A",DATE(YEAR(INDEX(Fixed_Assets!$G$2:$G$201,$AB2)),MONTH(INDEX(Fixed_Assets!$G$2:$G$201,$AB2)),1),IF($Z2="F",DATE(YEAR(MAX(N(INDEX(Workforce!$I$2:$I$151,MATCH(INDEX(FTE_Allocation!$A$2:$A$201,$AB2),Workforce!$A$2:$A$151,0))),N(INDEX(FTE_Allocation!$I$2:$I$201,$AB2)))),MONTH(MAX(N(INDEX(Workforce!$I$2:$I$151,MATCH(INDEX(FTE_Allocation!$A$2:$A$201,$AB2),Workforce!$A$2:$A$151,0))),N(INDEX(FTE_Allocation!$I$2:$I$201,$AB2)))),1),""))) | AF2: =IF($Z2="C",IF(INDEX(Contracts!$I$2:$I$151,$AB2)="PREPAID",EDATE(DATE(YEAR(INDEX(Contracts!$J$2:$J$151,$AB2)),MONTH(INDEX(Contracts!$J$2:$J$151,$AB2)),1),IF(INDEX(Contracts!$N$2:$N$151,$AB2)="",12,INDEX(Contracts!$N$2:$N$151,$AB2))-1),IF(INDEX(Contracts!$I$2:$I$151,$AB2)="MONTHLY",IF(INDEX(Contracts!$K$2:$K$151,$AB2)="",2958101,INDEX(Contracts!$K$2:$K$151,$AB2)),0)),IF($Z2="A",EDATE(DATE(YEAR(INDEX(Fixed_Assets!$G$2:$G$201,$AB2)),MONTH(INDEX(Fixed_Assets!$G$2:$G$201,$AB2)),1),INDEX(Fixed_Assets!$J$2:$J$201,$AB2)-1),IF($Z2="F",MIN(IF(INDEX(Workforce!$J$2:$J$151,MATCH(INDEX(FTE_Allocation!$A$2:$A$201,$AB2),Workforce!$A$2:$A$151,0))="",2958101,INDEX(Workforce!$J$2:$J$151,MATCH(INDEX(FTE_Allocation!$A$2:$A$201,$AB2),Workforce!$A$2:$A$151,0))),IF(INDEX(FTE_Allocation!$J$2:$J$201,$AB2)="",2958101,INDEX(FTE_Allocation!$J$2:$J$201,$AB2))),""))) | AG2: =IF($Z2="C",IF(INDEX(Contracts!$I$2:$I$151,$AB2)="PREPAID",INDEX(Contracts!$M$2:$M$151,$AB2)/IF(INDEX(Contracts!$N$2:$N$151,$AB2)="",12,INDEX(Contracts!$N$2:$N$151,$AB2)),IF(INDEX(Contracts!$I$2:$I$151,$AB2)="MONTHLY",INDEX(Contracts!$M$2:$M$151,$AB2),0))*(1-N(INDEX(Contracts!$O$2:$O$151,$AB2))),IF($Z2="A",INDEX(Fixed_Assets!$H$2:$H$201,$AB2)/INDEX(Fixed_Assets!$J$2:$J$201,$AB2),IF($Z2="F",INDEX(Workforce!$F$2:$F$151,MATCH(INDEX(FTE_Allocation!$A$2:$A$201,$AB2),Workforce!$A$2:$A$151,0))*N(INDEX(FTE_Allocation!$F$2:$H$201,$AB2,$AC2)),"")))
A3: =IF($Z3="","",$AD3) | B3: =IF($Z3="C",INDEX(Contracts!$D$2:$D$151,$AB3)&"",IF($Z3="A",INDEX(Fixed_Assets!$C$2:$C$201,$AB3)&"",IF($Z3="F",INDEX(Workforce!$B$2:$B$151,MATCH(INDEX(FTE_Allocation!$A$2:$A$201,$AB3),Workforce!$A$2:$A$151,0))&"",""))) | C3: =IF($Z3="C",INDEX(Contracts!$E$2:$E$151,$AB3)&"",IF($Z3="A",INDEX(Fixed_Assets!$D$2:$D$201,$AB3)&"",IF($Z3="F",INDEX(FTE_Allocation!$C$2:$C$201,$AB3)&"",""))) | D3: =IF($Z3="C",INDEX(Contracts!$B$2:$B$151,$AB3)&"",IF($Z3="A",INDEX(Fixed_Assets!$B$2:$B$201,$AB3)&"",IF($Z3="F",INDEX(FTE_Allocation!$B$2:$B$201,$AB3)&"",""))) | E3: =IF($Z3="C",INDEX(Contracts!$P$2:$P$151,$AB3)&"",IF($Z3="A",INDEX(Fixed_Assets!$K$2:$K$201,$AB3)&"",IF($Z3="F",IF(INDEX(FTE_Allocation!$D$2:$D$201,$AB3)="PROJECT",IFERROR(INDEX(Projects!$D:$D,MATCH(INDEX(FTE_Allocation!$E$2:$E$201,$AB3),Projects!$A:$A,0))&"","#PROJECT?"),INDEX(FTE_Allocation!$E$2:$E$201,$AB3)&""),""))) | F3: =IF($Z3="C",INDEX(Contracts!$Q$2:$Q$151,$AB3)&"",IF($Z3="A",INDEX(Fixed_Assets!$L$2:$L$201,$AB3)&"",IF($Z3="F",INDEX(Workforce!$K$2:$K$151,MATCH(INDEX(FTE_Allocation!$A$2:$A$201,$AB3),Workforce!$A$2:$A$151,0))&"",""))) | G3: =IF($Z3="C",INDEX(Contracts!$F$2:$F$151,$AB3)&" / "&INDEX(Contracts!$G$2:$G$151,$AB3),IF($Z3="A",INDEX(Fixed_Assets!$E$2:$E$201,$AB3)&"",IF($Z3="F","Personnel "&INDEX(FTE_Allocation!$A$2:$A$201,$AB3)&IF(INDEX(FTE_Allocation!$D$2:$D$201,$AB3)="PROJECT"," ("&INDEX(FTE_Allocation!$E$2:$E$201,$AB3)&")",""),""))) | H3: =IF($Z3="C","CONTRACT",IF($Z3="A","ASSET",IF($Z3="F","WORKFORCE",""))) | I3: =IF($Z3="C",INDEX(Contracts!$L$2:$L$151,$AB3)&"",IF($Z3="A",INDEX(Fixed_Assets!$I$2:$I$201,$AB3)&"",IF($Z3="F",INDEX(Workforce!$G$2:$G$151,MATCH(INDEX(FTE_Allocation!$A$2:$A$201,$AB3),Workforce!$A$2:$A$151,0))&"",""))) | J3: =IF($Z3="","",IF(AND(DATE($AD3,1,1)>=$AE3,DATE($AD3,1,1)<=$AF3),ROUND($AG3,2),0)) | K3: =IF($Z3="","",IF(AND(DATE($AD3,2,1)>=$AE3,DATE($AD3,2,1)<=$AF3),ROUND($AG3,2),0)) | L3: =IF($Z3="","",IF(AND(DATE($AD3,3,1)>=$AE3,DATE($AD3,3,1)<=$AF3),ROUND($AG3,2),0)) | M3: =IF($Z3="","",IF(AND(DATE($AD3,4,1)>=$AE3,DATE($AD3,4,1)<=$AF3),ROUND($AG3,2),0)) | N3: =IF($Z3="","",IF(AND(DATE($AD3,5,1)>=$AE3,DATE($AD3,5,1)<=$AF3),ROUND($AG3,2),0)) | O3: =IF($Z3="","",IF(AND(DATE($AD3,6,1)>=$AE3,DATE($AD3,6,1)<=$AF3),ROUND($AG3,2),0)) | P3: =IF($Z3="","",IF(AND(DATE($AD3,7,1)>=$AE3,DATE($AD3,7,1)<=$AF3),ROUND($AG3,2),0)) | Q3: =IF($Z3="","",IF(AND(DATE($AD3,8,1)>=$AE3,DATE($AD3,8,1)<=$AF3),ROUND($AG3,2),0)) | R3: =IF($Z3="","",IF(AND(DATE($AD3,9,1)>=$AE3,DATE($AD3,9,1)<=$AF3),ROUND($AG3,2),0)) | S3: =IF($Z3="","",IF(AND(DATE($AD3,10,1)>=$AE3,DATE($AD3,10,1)<=$AF3),ROUND($AG3,2),0)) | T3: =IF($Z3="","",IF(AND(DATE($AD3,11,1)>=$AE3,DATE($AD3,11,1)<=$AF3),ROUND($AG3,2),0)) | U3: =IF($Z3="","",IF(AND(DATE($AD3,12,1)>=$AE3,DATE($AD3,12,1)<=$AF3),ROUND($AG3,2),0)) | V3: =IF($Z3="C","Generated from "&INDEX(Contracts!$A$2:$A$151,$AB3),IF($Z3="A","Generated from "&INDEX(Fixed_Assets!$A$2:$A$201,$AB3),IF($Z3="F","Generated from "&INDEX(FTE_Allocation!$A$2:$A$201,$AB3),""))) | X3: =IF($Z3="","",SUM(J3:U3)) | Y3: =ROW()-1 | Z3: =IF($Y3<=Settings!$B$4*3,"C",IF($Y3<=(Settings!$B$4+Settings!$B$5)*3,"A",IF($Y3<=(Settings!$B$4+Settings!$B$5+Settings!$B$6)*3,"F",""))) | AA3: =IF($Z3="C",$Y3,IF($Z3="A",$Y3-Settings!$B$4*3,IF($Z3="F",$Y3-(Settings!$B$4+Settings!$B$5)*3,""))) | AB3: =IF($Z3="","",INT(($AA3-1)/3)+1) | AC3: =IF($Z3="","",MOD($AA3-1,3)+1) | AD3: =IF($Z3="","",Settings!$B$2+$AC3-1) | AE3: =IF($Z3="C",DATE(YEAR(INDEX(Contracts!$J$2:$J$151,$AB3)),MONTH(INDEX(Contracts!$J$2:$J$151,$AB3)),1),IF($Z3="A",DATE(YEAR(INDEX(Fixed_Assets!$G$2:$G$201,$AB3)),MONTH(INDEX(Fixed_Assets!$G$2:$G$201,$AB3)),1),IF($Z3="F",DATE(YEAR(MAX(N(INDEX(Workforce!$I$2:$I$151,MATCH(INDEX(FTE_Allocation!$A$2:$A$201,$AB3),Workforce!$A$2:$A$151,0))),N(INDEX(FTE_Allocation!$I$2:$I$201,$AB3)))),MONTH(MAX(N(INDEX(Workforce!$I$2:$I$151,MATCH(INDEX(FTE_Allocation!$A$2:$A$201,$AB3),Workforce!$A$2:$A$151,0))),N(INDEX(FTE_Allocation!$I$2:$I$201,$AB3)))),1),""))) | AF3: =IF($Z3="C",IF(INDEX(Contracts!$I$2:$I$151,$AB3)="PREPAID",EDATE(DATE(YEAR(INDEX(Contracts!$J$2:$J$151,$AB3)),MONTH(INDEX(Contracts!$J$2:$J$151,$AB3)),1),IF(INDEX(Contracts!$N$2:$N$151,$AB3)="",12,INDEX(Contracts!$N$2:$N$151,$AB3))-1),IF(INDEX(Contracts!$I$2:$I$151,$AB3)="MONTHLY",IF(INDEX(Contracts!$K$2:$K$151,$AB3)="",2958101,INDEX(Contracts!$K$2:$K$151,$AB3)),0)),IF($Z3="A",EDATE(DATE(YEAR(INDEX(Fixed_Assets!$G$2:$G$201,$AB3)),MONTH(INDEX(Fixed_Assets!$G$2:$G$201,$AB3)),1),INDEX(Fixed_Assets!$J$2:$J$201,$AB3)-1),IF($Z3="F",MIN(IF(INDEX(Workforce!$J$2:$J$151,MATCH(INDEX(FTE_Allocation!$A$2:$A$201,$AB3),Workforce!$A$2:$A$151,0))="",2958101,INDEX(Workforce!$J$2:$J$151,MATCH(INDEX(FTE_Allocation!$A$2:$A$201,$AB3),Workforce!$A$2:$A$151,0))),IF(INDEX(FTE_Allocation!$J$2:$J$201,$AB3)="",2958101,INDEX(FTE_Allocation!$J$2:$J$201,$AB3))),""))) | AG3: =IF($Z3="C",IF(INDEX(Contracts!$I$2:$I$151,$AB3)="PREPAID",INDEX(Contracts!$M$2:$M$151,$AB3)/IF(INDEX(Contracts!$N$2:$N$151,$AB3)="",12,INDEX(Contracts!$N$2:$N$151,$AB3)),IF(INDEX(Contracts!$I$2:$I$151,$AB3)="MONTHLY",INDEX(Contracts!$M$2:$M$151,$AB3),0))*(1-N(INDEX(Contracts!$O$2:$O$151,$AB3))),IF($Z3="A",INDEX(Fixed_Assets!$H$2:$H$201,$AB3)/INDEX(Fixed_Assets!$J$2:$J$201,$AB3),IF($Z3="F",INDEX(Workforce!$F$2:$F$151,MATCH(INDEX(FTE_Allocation!$A$2:$A$201,$AB3),Workforce!$A$2:$A$151,0))*N(INDEX(FTE_Allocation!$F$2:$H$201,$AB3,$AC3)),"")))
A4: =IF($Z4="","",$AD4) | B4: =IF($Z4="C",INDEX(Contracts!$D$2:$D$151,$AB4)&"",IF($Z4="A",INDEX(Fixed_Assets!$C$2:$C$201,$AB4)&"",IF($Z4="F",INDEX(Workforce!$B$2:$B$151,MATCH(INDEX(FTE_Allocation!$A$2:$A$201,$AB4),Workforce!$A$2:$A$151,0))&"",""))) | C4: =IF($Z4="C",INDEX(Contracts!$E$2:$E$151,$AB4)&"",IF($Z4="A",INDEX(Fixed_Assets!$D$2:$D$201,$AB4)&"",IF($Z4="F",INDEX(FTE_Allocation!$C$2:$C$201,$AB4)&"",""))) | D4: =IF($Z4="C",INDEX(Contracts!$B$2:$B$151,$AB4)&"",IF($Z4="A",INDEX(Fixed_Assets!$B$2:$B$201,$AB4)&"",IF($Z4="F",INDEX(FTE_Allocation!$B$2:$B$201,$AB4)&"",""))) | E4: =IF($Z4="C",INDEX(Contracts!$P$2:$P$151,$AB4)&"",IF($Z4="A",INDEX(Fixed_Assets!$K$2:$K$201,$AB4)&"",IF($Z4="F",IF(INDEX(FTE_Allocation!$D$2:$D$201,$AB4)="PROJECT",IFERROR(INDEX(Projects!$D:$D,MATCH(INDEX(FTE_Allocation!$E$2:$E$201,$AB4),Projects!$A:$A,0))&"","#PROJECT?"),INDEX(FTE_Allocation!$E$2:$E$201,$AB4)&""),""))) | F4: =IF($Z4="C",INDEX(Contracts!$Q$2:$Q$151,$AB4)&"",IF($Z4="A",INDEX(Fixed_Assets!$L$2:$L$201,$AB4)&"",IF($Z4="F",INDEX(Workforce!$K$2:$K$151,MATCH(INDEX(FTE_Allocation!$A$2:$A$201,$AB4),Workforce!$A$2:$A$151,0))&"",""))) | G4: =IF($Z4="C",INDEX(Contracts!$F$2:$F$151,$AB4)&" / "&INDEX(Contracts!$G$2:$G$151,$AB4),IF($Z4="A",INDEX(Fixed_Assets!$E$2:$E$201,$AB4)&"",IF($Z4="F","Personnel "&INDEX(FTE_Allocation!$A$2:$A$201,$AB4)&IF(INDEX(FTE_Allocation!$D$2:$D$201,$AB4)="PROJECT"," ("&INDEX(FTE_Allocation!$E$2:$E$201,$AB4)&")",""),""))) | H4: =IF($Z4="C","CONTRACT",IF($Z4="A","ASSET",IF($Z4="F","WORKFORCE",""))) | I4: =IF($Z4="C",INDEX(Contracts!$L$2:$L$151,$AB4)&"",IF($Z4="A",INDEX(Fixed_Assets!$I$2:$I$201,$AB4)&"",IF($Z4="F",INDEX(Workforce!$G$2:$G$151,MATCH(INDEX(FTE_Allocation!$A$2:$A$201,$AB4),Workforce!$A$2:$A$151,0))&"",""))) | J4: =IF($Z4="","",IF(AND(DATE($AD4,1,1)>=$AE4,DATE($AD4,1,1)<=$AF4),ROUND($AG4,2),0)) | K4: =IF($Z4="","",IF(AND(DATE($AD4,2,1)>=$AE4,DATE($AD4,2,1)<=$AF4),ROUND($AG4,2),0)) | L4: =IF($Z4="","",IF(AND(DATE($AD4,3,1)>=$AE4,DATE($AD4,3,1)<=$AF4),ROUND($AG4,2),0)) | M4: =IF($Z4="","",IF(AND(DATE($AD4,4,1)>=$AE4,DATE($AD4,4,1)<=$AF4),ROUND($AG4,2),0)) | N4: =IF($Z4="","",IF(AND(DATE($AD4,5,1)>=$AE4,DATE($AD4,5,1)<=$AF4),ROUND($AG4,2),0)) | O4: =IF($Z4="","",IF(AND(DATE($AD4,6,1)>=$AE4,DATE($AD4,6,1)<=$AF4),ROUND($AG4,2),0)) | P4: =IF($Z4="","",IF(AND(DATE($AD4,7,1)>=$AE4,DATE($AD4,7,1)<=$AF4),ROUND($AG4,2),0)) | Q4: =IF($Z4="","",IF(AND(DATE($AD4,8,1)>=$AE4,DATE($AD4,8,1)<=$AF4),ROUND($AG4,2),0)) | R4: =IF($Z4="","",IF(AND(DATE($AD4,9,1)>=$AE4,DATE($AD4,9,1)<=$AF4),ROUND($AG4,2),0)) | S4: =IF($Z4="","",IF(AND(DATE($AD4,10,1)>=$AE4,DATE($AD4,10,1)<=$AF4),ROUND($AG4,2),0)) | T4: =IF($Z4="","",IF(AND(DATE($AD4,11,1)>=$AE4,DATE($AD4,11,1)<=$AF4),ROUND($AG4,2),0)) | U4: =IF($Z4="","",IF(AND(DATE($AD4,12,1)>=$AE4,DATE($AD4,12,1)<=$AF4),ROUND($AG4,2),0)) | V4: =IF($Z4="C","Generated from "&INDEX(Contracts!$A$2:$A$151,$AB4),IF($Z4="A","Generated from "&INDEX(Fixed_Assets!$A$2:$A$201,$AB4),IF($Z4="F","Generated from "&INDEX(FTE_Allocation!$A$2:$A$201,$AB4),""))) | X4: =IF($Z4="","",SUM(J4:U4)) | Y4: =ROW()-1 | Z4: =IF($Y4<=Settings!$B$4*3,"C",IF($Y4<=(Settings!$B$4+Settings!$B$5)*3,"A",IF($Y4<=(Settings!$B$4+Settings!$B$5+Settings!$B$6)*3,"F",""))) | AA4: =IF($Z4="C",$Y4,IF($Z4="A",$Y4-Settings!$B$4*3,IF($Z4="F",$Y4-(Settings!$B$4+Settings!$B$5)*3,""))) | AB4: =IF($Z4="","",INT(($AA4-1)/3)+1) | AC4: =IF($Z4="","",MOD($AA4-1,3)+1) | AD4: =IF($Z4="","",Settings!$B$2+$AC4-1) | AE4: =IF($Z4="C",DATE(YEAR(INDEX(Contracts!$J$2:$J$151,$AB4)),MONTH(INDEX(Contracts!$J$2:$J$151,$AB4)),1),IF($Z4="A",DATE(YEAR(INDEX(Fixed_Assets!$G$2:$G$201,$AB4)),MONTH(INDEX(Fixed_Assets!$G$2:$G$201,$AB4)),1),IF($Z4="F",DATE(YEAR(MAX(N(INDEX(Workforce!$I$2:$I$151,MATCH(INDEX(FTE_Allocation!$A$2:$A$201,$AB4),Workforce!$A$2:$A$151,0))),N(INDEX(FTE_Allocation!$I$2:$I$201,$AB4)))),MONTH(MAX(N(INDEX(Workforce!$I$2:$I$151,MATCH(INDEX(FTE_Allocation!$A$2:$A$201,$AB4),Workforce!$A$2:$A$151,0))),N(INDEX(FTE_Allocation!$I$2:$I$201,$AB4)))),1),""))) | AF4: =IF($Z4="C",IF(INDEX(Contracts!$I$2:$I$151,$AB4)="PREPAID",EDATE(DATE(YEAR(INDEX(Contracts!$J$2:$J$151,$AB4)),MONTH(INDEX(Contracts!$J$2:$J$151,$AB4)),1),IF(INDEX(Contracts!$N$2:$N$151,$AB4)="",12,INDEX(Contracts!$N$2:$N$151,$AB4))-1),IF(INDEX(Contracts!$I$2:$I$151,$AB4)="MONTHLY",IF(INDEX(Contracts!$K$2:$K$151,$AB4)="",2958101,INDEX(Contracts!$K$2:$K$151,$AB4)),0)),IF($Z4="A",EDATE(DATE(YEAR(INDEX(Fixed_Assets!$G$2:$G$201,$AB4)),MONTH(INDEX(Fixed_Assets!$G$2:$G$201,$AB4)),1),INDEX(Fixed_Assets!$J$2:$J$201,$AB4)-1),IF($Z4="F",MIN(IF(INDEX(Workforce!$J$2:$J$151,MATCH(INDEX(FTE_Allocation!$A$2:$A$201,$AB4),Workforce!$A$2:$A$151,0))="",2958101,INDEX(Workforce!$J$2:$J$151,MATCH(INDEX(FTE_Allocation!$A$2:$A$201,$AB4),Workforce!$A$2:$A$151,0))),IF(INDEX(FTE_Allocation!$J$2:$J$201,$AB4)="",2958101,INDEX(FTE_Allocation!$J$2:$J$201,$AB4))),""))) | AG4: =IF($Z4="C",IF(INDEX(Contracts!$I$2:$I$151,$AB4)="PREPAID",INDEX(Contracts!$M$2:$M$151,$AB4)/IF(INDEX(Contracts!$N$2:$N$151,$AB4)="",12,INDEX(Contracts!$N$2:$N$151,$AB4)),IF(INDEX(Contracts!$I$2:$I$151,$AB4)="MONTHLY",INDEX(Contracts!$M$2:$M$151,$AB4),0))*(1-N(INDEX(Contracts!$O$2:$O$151,$AB4))),IF($Z4="A",INDEX(Fixed_Assets!$H$2:$H$201,$AB4)/INDEX(Fixed_Assets!$J$2:$J$201,$AB4),IF($Z4="F",INDEX(Workforce!$F$2:$F$151,MATCH(INDEX(FTE_Allocation!$A$2:$A$201,$AB4),Workforce!$A$2:$A$151,0))*N(INDEX(FTE_Allocation!$F$2:$H$201,$AB4,$AC4)),"")))
A5: =IF($Z5="","",$AD5) | B5: =IF($Z5="C",INDEX(Contracts!$D$2:$D$151,$AB5)&"",IF($Z5="A",INDEX(Fixed_Assets!$C$2:$C$201,$AB5)&"",IF($Z5="F",INDEX(Workforce!$B$2:$B$151,MATCH(INDEX(FTE_Allocation!$A$2:$A$201,$AB5),Workforce!$A$2:$A$151,0))&"",""))) | C5: =IF($Z5="C",INDEX(Contracts!$E$2:$E$151,$AB5)&"",IF($Z5="A",INDEX(Fixed_Assets!$D$2:$D$201,$AB5)&"",IF($Z5="F",INDEX(FTE_Allocation!$C$2:$C$201,$AB5)&"",""))) | D5: =IF($Z5="C",INDEX(Contracts!$B$2:$B$151,$AB5)&"",IF($Z5="A",INDEX(Fixed_Assets!$B$2:$B$201,$AB5)&"",IF($Z5="F",INDEX(FTE_Allocation!$B$2:$B$201,$AB5)&"",""))) | E5: =IF($Z5="C",INDEX(Contracts!$P$2:$P$151,$AB5)&"",IF($Z5="A",INDEX(Fixed_Assets!$K$2:$K$201,$AB5)&"",IF($Z5="F",IF(INDEX(FTE_Allocation!$D$2:$D$201,$AB5)="PROJECT",IFERROR(INDEX(Projects!$D:$D,MATCH(INDEX(FTE_Allocation!$E$2:$E$201,$AB5),Projects!$A:$A,0))&"","#PROJECT?"),INDEX(FTE_Allocation!$E$2:$E$201,$AB5)&""),""))) | F5: =IF($Z5="C",INDEX(Contracts!$Q$2:$Q$151,$AB5)&"",IF($Z5="A",INDEX(Fixed_Assets!$L$2:$L$201,$AB5)&"",IF($Z5="F",INDEX(Workforce!$K$2:$K$151,MATCH(INDEX(FTE_Allocation!$A$2:$A$201,$AB5),Workforce!$A$2:$A$151,0))&"",""))) | G5: =IF($Z5="C",INDEX(Contracts!$F$2:$F$151,$AB5)&" / "&INDEX(Contracts!$G$2:$G$151,$AB5),IF($Z5="A",INDEX(Fixed_Assets!$E$2:$E$201,$AB5)&"",IF($Z5="F","Personnel "&INDEX(FTE_Allocation!$A$2:$A$201,$AB5)&IF(INDEX(FTE_Allocation!$D$2:$D$201,$AB5)="PROJECT"," ("&INDEX(FTE_Allocation!$E$2:$E$201,$AB5)&")",""),""))) | H5: =IF($Z5="C","CONTRACT",IF($Z5="A","ASSET",IF($Z5="F","WORKFORCE",""))) | I5: =IF($Z5="C",INDEX(Contracts!$L$2:$L$151,$AB5)&"",IF($Z5="A",INDEX(Fixed_Assets!$I$2:$I$201,$AB5)&"",IF($Z5="F",INDEX(Workforce!$G$2:$G$151,MATCH(INDEX(FTE_Allocation!$A$2:$A$201,$AB5),Workforce!$A$2:$A$151,0))&"",""))) | J5: =IF($Z5="","",IF(AND(DATE($AD5,1,1)>=$AE5,DATE($AD5,1,1)<=$AF5),ROUND($AG5,2),0)) | K5: =IF($Z5="","",IF(AND(DATE($AD5,2,1)>=$AE5,DATE($AD5,2,1)<=$AF5),ROUND($AG5,2),0)) | L5: =IF($Z5="","",IF(AND(DATE($AD5,3,1)>=$AE5,DATE($AD5,3,1)<=$AF5),ROUND($AG5,2),0)) | M5: =IF($Z5="","",IF(AND(DATE($AD5,4,1)>=$AE5,DATE($AD5,4,1)<=$AF5),ROUND($AG5,2),0)) | N5: =IF($Z5="","",IF(AND(DATE($AD5,5,1)>=$AE5,DATE($AD5,5,1)<=$AF5),ROUND($AG5,2),0)) | O5: =IF($Z5="","",IF(AND(DATE($AD5,6,1)>=$AE5,DATE($AD5,6,1)<=$AF5),ROUND($AG5,2),0)) | P5: =IF($Z5="","",IF(AND(DATE($AD5,7,1)>=$AE5,DATE($AD5,7,1)<=$AF5),ROUND($AG5,2),0)) | Q5: =IF($Z5="","",IF(AND(DATE($AD5,8,1)>=$AE5,DATE($AD5,8,1)<=$AF5),ROUND($AG5,2),0)) | R5: =IF($Z5="","",IF(AND(DATE($AD5,9,1)>=$AE5,DATE($AD5,9,1)<=$AF5),ROUND($AG5,2),0)) | S5: =IF($Z5="","",IF(AND(DATE($AD5,10,1)>=$AE5,DATE($AD5,10,1)<=$AF5),ROUND($AG5,2),0)) | T5: =IF($Z5="","",IF(AND(DATE($AD5,11,1)>=$AE5,DATE($AD5,11,1)<=$AF5),ROUND($AG5,2),0)) | U5: =IF($Z5="","",IF(AND(DATE($AD5,12,1)>=$AE5,DATE($AD5,12,1)<=$AF5),ROUND($AG5,2),0)) | V5: =IF($Z5="C","Generated from "&INDEX(Contracts!$A$2:$A$151,$AB5),IF($Z5="A","Generated from "&INDEX(Fixed_Assets!$A$2:$A$201,$AB5),IF($Z5="F","Generated from "&INDEX(FTE_Allocation!$A$2:$A$201,$AB5),""))) | X5: =IF($Z5="","",SUM(J5:U5)) | Y5: =ROW()-1 | Z5: =IF($Y5<=Settings!$B$4*3,"C",IF($Y5<=(Settings!$B$4+Settings!$B$5)*3,"A",IF($Y5<=(Settings!$B$4+Settings!$B$5+Settings!$B$6)*3,"F",""))) | AA5: =IF($Z5="C",$Y5,IF($Z5="A",$Y5-Settings!$B$4*3,IF($Z5="F",$Y5-(Settings!$B$4+Settings!$B$5)*3,""))) | AB5: =IF($Z5="","",INT(($AA5-1)/3)+1) | AC5: =IF($Z5="","",MOD($AA5-1,3)+1) | AD5: =IF($Z5="","",Settings!$B$2+$AC5-1) | AE5: =IF($Z5="C",DATE(YEAR(INDEX(Contracts!$J$2:$J$151,$AB5)),MONTH(INDEX(Contracts!$J$2:$J$151,$AB5)),1),IF($Z5="A",DATE(YEAR(INDEX(Fixed_Assets!$G$2:$G$201,$AB5)),MONTH(INDEX(Fixed_Assets!$G$2:$G$201,$AB5)),1),IF($Z5="F",DATE(YEAR(MAX(N(INDEX(Workforce!$I$2:$I$151,MATCH(INDEX(FTE_Allocation!$A$2:$A$201,$AB5),Workforce!$A$2:$A$151,0))),N(INDEX(FTE_Allocation!$I$2:$I$201,$AB5)))),MONTH(MAX(N(INDEX(Workforce!$I$2:$I$151,MATCH(INDEX(FTE_Allocation!$A$2:$A$201,$AB5),Workforce!$A$2:$A$151,0))),N(INDEX(FTE_Allocation!$I$2:$I$201,$AB5)))),1),""))) | AF5: =IF($Z5="C",IF(INDEX(Contracts!$I$2:$I$151,$AB5)="PREPAID",EDATE(DATE(YEAR(INDEX(Contracts!$J$2:$J$151,$AB5)),MONTH(INDEX(Contracts!$J$2:$J$151,$AB5)),1),IF(INDEX(Contracts!$N$2:$N$151,$AB5)="",12,INDEX(Contracts!$N$2:$N$151,$AB5))-1),IF(INDEX(Contracts!$I$2:$I$151,$AB5)="MONTHLY",IF(INDEX(Contracts!$K$2:$K$151,$AB5)="",2958101,INDEX(Contracts!$K$2:$K$151,$AB5)),0)),IF($Z5="A",EDATE(DATE(YEAR(INDEX(Fixed_Assets!$G$2:$G$201,$AB5)),MONTH(INDEX(Fixed_Assets!$G$2:$G$201,$AB5)),1),INDEX(Fixed_Assets!$J$2:$J$201,$AB5)-1),IF($Z5="F",MIN(IF(INDEX(Workforce!$J$2:$J$151,MATCH(INDEX(FTE_Allocation!$A$2:$A$201,$AB5),Workforce!$A$2:$A$151,0))="",2958101,INDEX(Workforce!$J$2:$J$151,MATCH(INDEX(FTE_Allocation!$A$2:$A$201,$AB5),Workforce!$A$2:$A$151,0))),IF(INDEX(FTE_Allocation!$J$2:$J$201,$AB5)="",2958101,INDEX(FTE_Allocation!$J$2:$J$201,$AB5))),""))) | AG5: =IF($Z5="C",IF(INDEX(Contracts!$I$2:$I$151,$AB5)="PREPAID",INDEX(Contracts!$M$2:$M$151,$AB5)/IF(INDEX(Contracts!$N$2:$N$151,$AB5)="",12,INDEX(Contracts!$N$2:$N$151,$AB5)),IF(INDEX(Contracts!$I$2:$I$151,$AB5)="MONTHLY",INDEX(Contracts!$M$2:$M$151,$AB5),0))*(1-N(INDEX(Contracts!$O$2:$O$151,$AB5))),IF($Z5="A",INDEX(Fixed_Assets!$H$2:$H$201,$AB5)/INDEX(Fixed_Assets!$J$2:$J$201,$AB5),IF($Z5="F",INDEX(Workforce!$F$2:$F$151,MATCH(INDEX(FTE_Allocation!$A$2:$A$201,$AB5),Workforce!$A$2:$A$151,0))*N(INDEX(FTE_Allocation!$F$2:$H$201,$AB5,$AC5)),"")))
A6: =IF($Z6="","",$AD6) | B6: =IF($Z6="C",INDEX(Contracts!$D$2:$D$151,$AB6)&"",IF($Z6="A",INDEX(Fixed_Assets!$C$2:$C$201,$AB6)&"",IF($Z6="F",INDEX(Workforce!$B$2:$B$151,MATCH(INDEX(FTE_Allocation!$A$2:$A$201,$AB6),Workforce!$A$2:$A$151,0))&"",""))) | C6: =IF($Z6="C",INDEX(Contracts!$E$2:$E$151,$AB6)&"",IF($Z6="A",INDEX(Fixed_Assets!$D$2:$D$201,$AB6)&"",IF($Z6="F",INDEX(FTE_Allocation!$C$2:$C$201,$AB6)&"",""))) | D6: =IF($Z6="C",INDEX(Contracts!$B$2:$B$151,$AB6)&"",IF($Z6="A",INDEX(Fixed_Assets!$B$2:$B$201,$AB6)&"",IF($Z6="F",INDEX(FTE_Allocation!$B$2:$B$201,$AB6)&"",""))) | E6: =IF($Z6="C",INDEX(Contracts!$P$2:$P$151,$AB6)&"",IF($Z6="A",INDEX(Fixed_Assets!$K$2:$K$201,$AB6)&"",IF($Z6="F",IF(INDEX(FTE_Allocation!$D$2:$D$201,$AB6)="PROJECT",IFERROR(INDEX(Projects!$D:$D,MATCH(INDEX(FTE_Allocation!$E$2:$E$201,$AB6),Projects!$A:$A,0))&"","#PROJECT?"),INDEX(FTE_Allocation!$E$2:$E$201,$AB6)&""),""))) | F6: =IF($Z6="C",INDEX(Contracts!$Q$2:$Q$151,$AB6)&"",IF($Z6="A",INDEX(Fixed_Assets!$L$2:$L$201,$AB6)&"",IF($Z6="F",INDEX(Workforce!$K$2:$K$151,MATCH(INDEX(FTE_Allocation!$A$2:$A$201,$AB6),Workforce!$A$2:$A$151,0))&"",""))) | G6: =IF($Z6="C",INDEX(Contracts!$F$2:$F$151,$AB6)&" / "&INDEX(Contracts!$G$2:$G$151,$AB6),IF($Z6="A",INDEX(Fixed_Assets!$E$2:$E$201,$AB6)&"",IF($Z6="F","Personnel "&INDEX(FTE_Allocation!$A$2:$A$201,$AB6)&IF(INDEX(FTE_Allocation!$D$2:$D$201,$AB6)="PROJECT"," ("&INDEX(FTE_Allocation!$E$2:$E$201,$AB6)&")",""),""))) | H6: =IF($Z6="C","CONTRACT",IF($Z6="A","ASSET",IF($Z6="F","WORKFORCE",""))) | I6: =IF($Z6="C",INDEX(Contracts!$L$2:$L$151,$AB6)&"",IF($Z6="A",INDEX(Fixed_Assets!$I$2:$I$201,$AB6)&"",IF($Z6="F",INDEX(Workforce!$G$2:$G$151,MATCH(INDEX(FTE_Allocation!$A$2:$A$201,$AB6),Workforce!$A$2:$A$151,0))&"",""))) | J6: =IF($Z6="","",IF(AND(DATE($AD6,1,1)>=$AE6,DATE($AD6,1,1)<=$AF6),ROUND($AG6,2),0)) | K6: =IF($Z6="","",IF(AND(DATE($AD6,2,1)>=$AE6,DATE($AD6,2,1)<=$AF6),ROUND($AG6,2),0)) | L6: =IF($Z6="","",IF(AND(DATE($AD6,3,1)>=$AE6,DATE($AD6,3,1)<=$AF6),ROUND($AG6,2),0)) | M6: =IF($Z6="","",IF(AND(DATE($AD6,4,1)>=$AE6,DATE($AD6,4,1)<=$AF6),ROUND($AG6,2),0)) | N6: =IF($Z6="","",IF(AND(DATE($AD6,5,1)>=$AE6,DATE($AD6,5,1)<=$AF6),ROUND($AG6,2),0)) | O6: =IF($Z6="","",IF(AND(DATE($AD6,6,1)>=$AE6,DATE($AD6,6,1)<=$AF6),ROUND($AG6,2),0)) | P6: =IF($Z6="","",IF(AND(DATE($AD6,7,1)>=$AE6,DATE($AD6,7,1)<=$AF6),ROUND($AG6,2),0)) | Q6: =IF($Z6="","",IF(AND(DATE($AD6,8,1)>=$AE6,DATE($AD6,8,1)<=$AF6),ROUND($AG6,2),0)) | R6: =IF($Z6="","",IF(AND(DATE($AD6,9,1)>=$AE6,DATE($AD6,9,1)<=$AF6),ROUND($AG6,2),0)) | S6: =IF($Z6="","",IF(AND(DATE($AD6,10,1)>=$AE6,DATE($AD6,10,1)<=$AF6),ROUND($AG6,2),0)) | T6: =IF($Z6="","",IF(AND(DATE($AD6,11,1)>=$AE6,DATE($AD6,11,1)<=$AF6),ROUND($AG6,2),0)) | U6: =IF($Z6="","",IF(AND(DATE($AD6,12,1)>=$AE6,DATE($AD6,12,1)<=$AF6),ROUND($AG6,2),0)) | V6: =IF($Z6="C","Generated from "&INDEX(Contracts!$A$2:$A$151,$AB6),IF($Z6="A","Generated from "&INDEX(Fixed_Assets!$A$2:$A$201,$AB6),IF($Z6="F","Generated from "&INDEX(FTE_Allocation!$A$2:$A$201,$AB6),""))) | X6: =IF($Z6="","",SUM(J6:U6)) | Y6: =ROW()-1 | Z6: =IF($Y6<=Settings!$B$4*3,"C",IF($Y6<=(Settings!$B$4+Settings!$B$5)*3,"A",IF($Y6<=(Settings!$B$4+Settings!$B$5+Settings!$B$6)*3,"F",""))) | AA6: =IF($Z6="C",$Y6,IF($Z6="A",$Y6-Settings!$B$4*3,IF($Z6="F",$Y6-(Settings!$B$4+Settings!$B$5)*3,""))) | AB6: =IF($Z6="","",INT(($AA6-1)/3)+1) | AC6: =IF($Z6="","",MOD($AA6-1,3)+1) | AD6: =IF($Z6="","",Settings!$B$2+$AC6-1) | AE6: =IF($Z6="C",DATE(YEAR(INDEX(Contracts!$J$2:$J$151,$AB6)),MONTH(INDEX(Contracts!$J$2:$J$151,$AB6)),1),IF($Z6="A",DATE(YEAR(INDEX(Fixed_Assets!$G$2:$G$201,$AB6)),MONTH(INDEX(Fixed_Assets!$G$2:$G$201,$AB6)),1),IF($Z6="F",DATE(YEAR(MAX(N(INDEX(Workforce!$I$2:$I$151,MATCH(INDEX(FTE_Allocation!$A$2:$A$201,$AB6),Workforce!$A$2:$A$151,0))),N(INDEX(FTE_Allocation!$I$2:$I$201,$AB6)))),MONTH(MAX(N(INDEX(Workforce!$I$2:$I$151,MATCH(INDEX(FTE_Allocation!$A$2:$A$201,$AB6),Workforce!$A$2:$A$151,0))),N(INDEX(FTE_Allocation!$I$2:$I$201,$AB6)))),1),""))) | AF6: =IF($Z6="C",IF(INDEX(Contracts!$I$2:$I$151,$AB6)="PREPAID",EDATE(DATE(YEAR(INDEX(Contracts!$J$2:$J$151,$AB6)),MONTH(INDEX(Contracts!$J$2:$J$151,$AB6)),1),IF(INDEX(Contracts!$N$2:$N$151,$AB6)="",12,INDEX(Contracts!$N$2:$N$151,$AB6))-1),IF(INDEX(Contracts!$I$2:$I$151,$AB6)="MONTHLY",IF(INDEX(Contracts!$K$2:$K$151,$AB6)="",2958101,INDEX(Contracts!$K$2:$K$151,$AB6)),0)),IF($Z6="A",EDATE(DATE(YEAR(INDEX(Fixed_Assets!$G$2:$G$201,$AB6)),MONTH(INDEX(Fixed_Assets!$G$2:$G$201,$AB6)),1),INDEX(Fixed_Assets!$J$2:$J$201,$AB6)-1),IF($Z6="F",MIN(IF(INDEX(Workforce!$J$2:$J$151,MATCH(INDEX(FTE_Allocation!$A$2:$A$201,$AB6),Workforce!$A$2:$A$151,0))="",2958101,INDEX(Workforce!$J$2:$J$151,MATCH(INDEX(FTE_Allocation!$A$2:$A$201,$AB6),Workforce!$A$2:$A$151,0))),IF(INDEX(FTE_Allocation!$J$2:$J$201,$AB6)="",2958101,INDEX(FTE_Allocation!$J$2:$J$201,$AB6))),""))) | AG6: =IF($Z6="C",IF(INDEX(Contracts!$I$2:$I$151,$AB6)="PREPAID",INDEX(Contracts!$M$2:$M$151,$AB6)/IF(INDEX(Contracts!$N$2:$N$151,$AB6)="",12,INDEX(Contracts!$N$2:$N$151,$AB6)),IF(INDEX(Contracts!$I$2:$I$151,$AB6)="MONTHLY",INDEX(Contracts!$M$2:$M$151,$AB6),0))*(1-N(INDEX(Contracts!$O$2:$O$151,$AB6))),IF($Z6="A",INDEX(Fixed_Assets!$H$2:$H$201,$AB6)/INDEX(Fixed_Assets!$J$2:$J$201,$AB6),IF($Z6="F",INDEX(Workforce!$F$2:$F$151,MATCH(INDEX(FTE_Allocation!$A$2:$A$201,$AB6),Workforce!$A$2:$A$151,0))*N(INDEX(FTE_Allocation!$F$2:$H$201,$AB6,$AC6)),"")))
A7: =IF($Z7="","",$AD7) | B7: =IF($Z7="C",INDEX(Contracts!$D$2:$D$151,$AB7)&"",IF($Z7="A",INDEX(Fixed_Assets!$C$2:$C$201,$AB7)&"",IF($Z7="F",INDEX(Workforce!$B$2:$B$151,MATCH(INDEX(FTE_Allocation!$A$2:$A$201,$AB7),Workforce!$A$2:$A$151,0))&"",""))) | C7: =IF($Z7="C",INDEX(Contracts!$E$2:$E$151,$AB7)&"",IF($Z7="A",INDEX(Fixed_Assets!$D$2:$D$201,$AB7)&"",IF($Z7="F",INDEX(FTE_Allocation!$C$2:$C$201,$AB7)&"",""))) | D7: =IF($Z7="C",INDEX(Contracts!$B$2:$B$151,$AB7)&"",IF($Z7="A",INDEX(Fixed_Assets!$B$2:$B$201,$AB7)&"",IF($Z7="F",INDEX(FTE_Allocation!$B$2:$B$201,$AB7)&"",""))) | E7: =IF($Z7="C",INDEX(Contracts!$P$2:$P$151,$AB7)&"",IF($Z7="A",INDEX(Fixed_Assets!$K$2:$K$201,$AB7)&"",IF($Z7="F",IF(INDEX(FTE_Allocation!$D$2:$D$201,$AB7)="PROJECT",IFERROR(INDEX(Projects!$D:$D,MATCH(INDEX(FTE_Allocation!$E$2:$E$201,$AB7),Projects!$A:$A,0))&"","#PROJECT?"),INDEX(FTE_Allocation!$E$2:$E$201,$AB7)&""),""))) | F7: =IF($Z7="C",INDEX(Contracts!$Q$2:$Q$151,$AB7)&"",IF($Z7="A",INDEX(Fixed_Assets!$L$2:$L$201,$AB7)&"",IF($Z7="F",INDEX(Workforce!$K$2:$K$151,MATCH(INDEX(FTE_Allocation!$A$2:$A$201,$AB7),Workforce!$A$2:$A$151,0))&"",""))) | G7: =IF($Z7="C",INDEX(Contracts!$F$2:$F$151,$AB7)&" / "&INDEX(Contracts!$G$2:$G$151,$AB7),IF($Z7="A",INDEX(Fixed_Assets!$E$2:$E$201,$AB7)&"",IF($Z7="F","Personnel "&INDEX(FTE_Allocation!$A$2:$A$201,$AB7)&IF(INDEX(FTE_Allocation!$D$2:$D$201,$AB7)="PROJECT"," ("&INDEX(FTE_Allocation!$E$2:$E$201,$AB7)&")",""),""))) | H7: =IF($Z7="C","CONTRACT",IF($Z7="A","ASSET",IF($Z7="F","WORKFORCE",""))) | I7: =IF($Z7="C",INDEX(Contracts!$L$2:$L$151,$AB7)&"",IF($Z7="A",INDEX(Fixed_Assets!$I$2:$I$201,$AB7)&"",IF($Z7="F",INDEX(Workforce!$G$2:$G$151,MATCH(INDEX(FTE_Allocation!$A$2:$A$201,$AB7),Workforce!$A$2:$A$151,0))&"",""))) | J7: =IF($Z7="","",IF(AND(DATE($AD7,1,1)>=$AE7,DATE($AD7,1,1)<=$AF7),ROUND($AG7,2),0)) | K7: =IF($Z7="","",IF(AND(DATE($AD7,2,1)>=$AE7,DATE($AD7,2,1)<=$AF7),ROUND($AG7,2),0)) | L7: =IF($Z7="","",IF(AND(DATE($AD7,3,1)>=$AE7,DATE($AD7,3,1)<=$AF7),ROUND($AG7,2),0)) | M7: =IF($Z7="","",IF(AND(DATE($AD7,4,1)>=$AE7,DATE($AD7,4,1)<=$AF7),ROUND($AG7,2),0)) | N7: =IF($Z7="","",IF(AND(DATE($AD7,5,1)>=$AE7,DATE($AD7,5,1)<=$AF7),ROUND($AG7,2),0)) | O7: =IF($Z7="","",IF(AND(DATE($AD7,6,1)>=$AE7,DATE($AD7,6,1)<=$AF7),ROUND($AG7,2),0)) | P7: =IF($Z7="","",IF(AND(DATE($AD7,7,1)>=$AE7,DATE($AD7,7,1)<=$AF7),ROUND($AG7,2),0)) | Q7: =IF($Z7="","",IF(AND(DATE($AD7,8,1)>=$AE7,DATE($AD7,8,1)<=$AF7),ROUND($AG7,2),0)) | R7: =IF($Z7="","",IF(AND(DATE($AD7,9,1)>=$AE7,DATE($AD7,9,1)<=$AF7),ROUND($AG7,2),0)) | S7: =IF($Z7="","",IF(AND(DATE($AD7,10,1)>=$AE7,DATE($AD7,10,1)<=$AF7),ROUND($AG7,2),0)) | T7: =IF($Z7="","",IF(AND(DATE($AD7,11,1)>=$AE7,DATE($AD7,11,1)<=$AF7),ROUND($AG7,2),0)) | U7: =IF($Z7="","",IF(AND(DATE($AD7,12,1)>=$AE7,DATE($AD7,12,1)<=$AF7),ROUND($AG7,2),0)) | V7: =IF($Z7="C","Generated from "&INDEX(Contracts!$A$2:$A$151,$AB7),IF($Z7="A","Generated from "&INDEX(Fixed_Assets!$A$2:$A$201,$AB7),IF($Z7="F","Generated from "&INDEX(FTE_Allocation!$A$2:$A$201,$AB7),""))) | X7: =IF($Z7="","",SUM(J7:U7)) | Y7: =ROW()-1 | Z7: =IF($Y7<=Settings!$B$4*3,"C",IF($Y7<=(Settings!$B$4+Settings!$B$5)*3,"A",IF($Y7<=(Settings!$B$4+Settings!$B$5+Settings!$B$6)*3,"F",""))) | AA7: =IF($Z7="C",$Y7,IF($Z7="A",$Y7-Settings!$B$4*3,IF($Z7="F",$Y7-(Settings!$B$4+Settings!$B$5)*3,""))) | AB7: =IF($Z7="","",INT(($AA7-1)/3)+1) | AC7: =IF($Z7="","",MOD($AA7-1,3)+1) | AD7: =IF($Z7="","",Settings!$B$2+$AC7-1) | AE7: =IF($Z7="C",DATE(YEAR(INDEX(Contracts!$J$2:$J$151,$AB7)),MONTH(INDEX(Contracts!$J$2:$J$151,$AB7)),1),IF($Z7="A",DATE(YEAR(INDEX(Fixed_Assets!$G$2:$G$201,$AB7)),MONTH(INDEX(Fixed_Assets!$G$2:$G$201,$AB7)),1),IF($Z7="F",DATE(YEAR(MAX(N(INDEX(Workforce!$I$2:$I$151,MATCH(INDEX(FTE_Allocation!$A$2:$A$201,$AB7),Workforce!$A$2:$A$151,0))),N(INDEX(FTE_Allocation!$I$2:$I$201,$AB7)))),MONTH(MAX(N(INDEX(Workforce!$I$2:$I$151,MATCH(INDEX(FTE_Allocation!$A$2:$A$201,$AB7),Workforce!$A$2:$A$151,0))),N(INDEX(FTE_Allocation!$I$2:$I$201,$AB7)))),1),""))) | AF7: =IF($Z7="C",IF(INDEX(Contracts!$I$2:$I$151,$AB7)="PREPAID",EDATE(DATE(YEAR(INDEX(Contracts!$J$2:$J$151,$AB7)),MONTH(INDEX(Contracts!$J$2:$J$151,$AB7)),1),IF(INDEX(Contracts!$N$2:$N$151,$AB7)="",12,INDEX(Contracts!$N$2:$N$151,$AB7))-1),IF(INDEX(Contracts!$I$2:$I$151,$AB7)="MONTHLY",IF(INDEX(Contracts!$K$2:$K$151,$AB7)="",2958101,INDEX(Contracts!$K$2:$K$151,$AB7)),0)),IF($Z7="A",EDATE(DATE(YEAR(INDEX(Fixed_Assets!$G$2:$G$201,$AB7)),MONTH(INDEX(Fixed_Assets!$G$2:$G$201,$AB7)),1),INDEX(Fixed_Assets!$J$2:$J$201,$AB7)-1),IF($Z7="F",MIN(IF(INDEX(Workforce!$J$2:$J$151,MATCH(INDEX(FTE_Allocation!$A$2:$A$201,$AB7),Workforce!$A$2:$A$151,0))="",2958101,INDEX(Workforce!$J$2:$J$151,MATCH(INDEX(FTE_Allocation!$A$2:$A$201,$AB7),Workforce!$A$2:$A$151,0))),IF(INDEX(FTE_Allocation!$J$2:$J$201,$AB7)="",2958101,INDEX(FTE_Allocation!$J$2:$J$201,$AB7))),""))) | AG7: =IF($Z7="C",IF(INDEX(Contracts!$I$2:$I$151,$AB7)="PREPAID",INDEX(Contracts!$M$2:$M$151,$AB7)/IF(INDEX(Contracts!$N$2:$N$151,$AB7)="",12,INDEX(Contracts!$N$2:$N$151,$AB7)),IF(INDEX(Contracts!$I$2:$I$151,$AB7)="MONTHLY",INDEX(Contracts!$M$2:$M$151,$AB7),0))*(1-N(INDEX(Contracts!$O$2:$O$151,$AB7))),IF($Z7="A",INDEX(Fixed_Assets!$H$2:$H$201,$AB7)/INDEX(Fixed_Assets!$J$2:$J$201,$AB7),IF($Z7="F",INDEX(Workforce!$F$2:$F$151,MATCH(INDEX(FTE_Allocation!$A$2:$A$201,$AB7),Workforce!$A$2:$A$151,0))*N(INDEX(FTE_Allocation!$F$2:$H$201,$AB7,$AC7)),"")))
A8: =IF($Z8="","",$AD8) | B8: =IF($Z8="C",INDEX(Contracts!$D$2:$D$151,$AB8)&"",IF($Z8="A",INDEX(Fixed_Assets!$C$2:$C$201,$AB8)&"",IF($Z8="F",INDEX(Workforce!$B$2:$B$151,MATCH(INDEX(FTE_Allocation!$A$2:$A$201,$AB8),Workforce!$A$2:$A$151,0))&"",""))) | C8: =IF($Z8="C",INDEX(Contracts!$E$2:$E$151,$AB8)&"",IF($Z8="A",INDEX(Fixed_Assets!$D$2:$D$201,$AB8)&"",IF($Z8="F",INDEX(FTE_Allocation!$C$2:$C$201,$AB8)&"",""))) | D8: =IF($Z8="C",INDEX(Contracts!$B$2:$B$151,$AB8)&"",IF($Z8="A",INDEX(Fixed_Assets!$B$2:$B$201,$AB8)&"",IF($Z8="F",INDEX(FTE_Allocation!$B$2:$B$201,$AB8)&"",""))) | E8: =IF($Z8="C",INDEX(Contracts!$P$2:$P$151,$AB8)&"",IF($Z8="A",INDEX(Fixed_Assets!$K$2:$K$201,$AB8)&"",IF($Z8="F",IF(INDEX(FTE_Allocation!$D$2:$D$201,$AB8)="PROJECT",IFERROR(INDEX(Projects!$D:$D,MATCH(INDEX(FTE_Allocation!$E$2:$E$201,$AB8),Projects!$A:$A,0))&"","#PROJECT?"),INDEX(FTE_Allocation!$E$2:$E$201,$AB8)&""),""))) | F8: =IF($Z8="C",INDEX(Contracts!$Q$2:$Q$151,$AB8)&"",IF($Z8="A",INDEX(Fixed_Assets!$L$2:$L$201,$AB8)&"",IF($Z8="F",INDEX(Workforce!$K$2:$K$151,MATCH(INDEX(FTE_Allocation!$A$2:$A$201,$AB8),Workforce!$A$2:$A$151,0))&"",""))) | G8: =IF($Z8="C",INDEX(Contracts!$F$2:$F$151,$AB8)&" / "&INDEX(Contracts!$G$2:$G$151,$AB8),IF($Z8="A",INDEX(Fixed_Assets!$E$2:$E$201,$AB8)&"",IF($Z8="F","Personnel "&INDEX(FTE_Allocation!$A$2:$A$201,$AB8)&IF(INDEX(FTE_Allocation!$D$2:$D$201,$AB8)="PROJECT"," ("&INDEX(FTE_Allocation!$E$2:$E$201,$AB8)&")",""),""))) | H8: =IF($Z8="C","CONTRACT",IF($Z8="A","ASSET",IF($Z8="F","WORKFORCE",""))) | I8: =IF($Z8="C",INDEX(Contracts!$L$2:$L$151,$AB8)&"",IF($Z8="A",INDEX(Fixed_Assets!$I$2:$I$201,$AB8)&"",IF($Z8="F",INDEX(Workforce!$G$2:$G$151,MATCH(INDEX(FTE_Allocation!$A$2:$A$201,$AB8),Workforce!$A$2:$A$151,0))&"",""))) | J8: =IF($Z8="","",IF(AND(DATE($AD8,1,1)>=$AE8,DATE($AD8,1,1)<=$AF8),ROUND($AG8,2),0)) | K8: =IF($Z8="","",IF(AND(DATE($AD8,2,1)>=$AE8,DATE($AD8,2,1)<=$AF8),ROUND($AG8,2),0)) | L8: =IF($Z8="","",IF(AND(DATE($AD8,3,1)>=$AE8,DATE($AD8,3,1)<=$AF8),ROUND($AG8,2),0)) | M8: =IF($Z8="","",IF(AND(DATE($AD8,4,1)>=$AE8,DATE($AD8,4,1)<=$AF8),ROUND($AG8,2),0)) | N8: =IF($Z8="","",IF(AND(DATE($AD8,5,1)>=$AE8,DATE($AD8,5,1)<=$AF8),ROUND($AG8,2),0)) | O8: =IF($Z8="","",IF(AND(DATE($AD8,6,1)>=$AE8,DATE($AD8,6,1)<=$AF8),ROUND($AG8,2),0)) | P8: =IF($Z8="","",IF(AND(DATE($AD8,7,1)>=$AE8,DATE($AD8,7,1)<=$AF8),ROUND($AG8,2),0)) | Q8: =IF($Z8="","",IF(AND(DATE($AD8,8,1)>=$AE8,DATE($AD8,8,1)<=$AF8),ROUND($AG8,2),0)) | R8: =IF($Z8="","",IF(AND(DATE($AD8,9,1)>=$AE8,DATE($AD8,9,1)<=$AF8),ROUND($AG8,2),0)) | S8: =IF($Z8="","",IF(AND(DATE($AD8,10,1)>=$AE8,DATE($AD8,10,1)<=$AF8),ROUND($AG8,2),0)) | T8: =IF($Z8="","",IF(AND(DATE($AD8,11,1)>=$AE8,DATE($AD8,11,1)<=$AF8),ROUND($AG8,2),0)) | U8: =IF($Z8="","",IF(AND(DATE($AD8,12,1)>=$AE8,DATE($AD8,12,1)<=$AF8),ROUND($AG8,2),0)) | V8: =IF($Z8="C","Generated from "&INDEX(Contracts!$A$2:$A$151,$AB8),IF($Z8="A","Generated from "&INDEX(Fixed_Assets!$A$2:$A$201,$AB8),IF($Z8="F","Generated from "&INDEX(FTE_Allocation!$A$2:$A$201,$AB8),""))) | X8: =IF($Z8="","",SUM(J8:U8)) | Y8: =ROW()-1 | Z8: =IF($Y8<=Settings!$B$4*3,"C",IF($Y8<=(Settings!$B$4+Settings!$B$5)*3,"A",IF($Y8<=(Settings!$B$4+Settings!$B$5+Settings!$B$6)*3,"F",""))) | AA8: =IF($Z8="C",$Y8,IF($Z8="A",$Y8-Settings!$B$4*3,IF($Z8="F",$Y8-(Settings!$B$4+Settings!$B$5)*3,""))) | AB8: =IF($Z8="","",INT(($AA8-1)/3)+1) | AC8: =IF($Z8="","",MOD($AA8-1,3)+1) | AD8: =IF($Z8="","",Settings!$B$2+$AC8-1) | AE8: =IF($Z8="C",DATE(YEAR(INDEX(Contracts!$J$2:$J$151,$AB8)),MONTH(INDEX(Contracts!$J$2:$J$151,$AB8)),1),IF($Z8="A",DATE(YEAR(INDEX(Fixed_Assets!$G$2:$G$201,$AB8)),MONTH(INDEX(Fixed_Assets!$G$2:$G$201,$AB8)),1),IF($Z8="F",DATE(YEAR(MAX(N(INDEX(Workforce!$I$2:$I$151,MATCH(INDEX(FTE_Allocation!$A$2:$A$201,$AB8),Workforce!$A$2:$A$151,0))),N(INDEX(FTE_Allocation!$I$2:$I$201,$AB8)))),MONTH(MAX(N(INDEX(Workforce!$I$2:$I$151,MATCH(INDEX(FTE_Allocation!$A$2:$A$201,$AB8),Workforce!$A$2:$A$151,0))),N(INDEX(FTE_Allocation!$I$2:$I$201,$AB8)))),1),""))) | AF8: =IF($Z8="C",IF(INDEX(Contracts!$I$2:$I$151,$AB8)="PREPAID",EDATE(DATE(YEAR(INDEX(Contracts!$J$2:$J$151,$AB8)),MONTH(INDEX(Contracts!$J$2:$J$151,$AB8)),1),IF(INDEX(Contracts!$N$2:$N$151,$AB8)="",12,INDEX(Contracts!$N$2:$N$151,$AB8))-1),IF(INDEX(Contracts!$I$2:$I$151,$AB8)="MONTHLY",IF(INDEX(Contracts!$K$2:$K$151,$AB8)="",2958101,INDEX(Contracts!$K$2:$K$151,$AB8)),0)),IF($Z8="A",EDATE(DATE(YEAR(INDEX(Fixed_Assets!$G$2:$G$201,$AB8)),MONTH(INDEX(Fixed_Assets!$G$2:$G$201,$AB8)),1),INDEX(Fixed_Assets!$J$2:$J$201,$AB8)-1),IF($Z8="F",MIN(IF(INDEX(Workforce!$J$2:$J$151,MATCH(INDEX(FTE_Allocation!$A$2:$A$201,$AB8),Workforce!$A$2:$A$151,0))="",2958101,INDEX(Workforce!$J$2:$J$151,MATCH(INDEX(FTE_Allocation!$A$2:$A$201,$AB8),Workforce!$A$2:$A$151,0))),IF(INDEX(FTE_Allocation!$J$2:$J$201,$AB8)="",2958101,INDEX(FTE_Allocation!$J$2:$J$201,$AB8))),""))) | AG8: =IF($Z8="C",IF(INDEX(Contracts!$I$2:$I$151,$AB8)="PREPAID",INDEX(Contracts!$M$2:$M$151,$AB8)/IF(INDEX(Contracts!$N$2:$N$151,$AB8)="",12,INDEX(Contracts!$N$2:$N$151,$AB8)),IF(INDEX(Contracts!$I$2:$I$151,$AB8)="MONTHLY",INDEX(Contracts!$M$2:$M$151,$AB8),0))*(1-N(INDEX(Contracts!$O$2:$O$151,$AB8))),IF($Z8="A",INDEX(Fixed_Assets!$H$2:$H$201,$AB8)/INDEX(Fixed_Assets!$J$2:$J$201,$AB8),IF($Z8="F",INDEX(Workforce!$F$2:$F$151,MATCH(INDEX(FTE_Allocation!$A$2:$A$201,$AB8),Workforce!$A$2:$A$151,0))*N(INDEX(FTE_Allocation!$F$2:$H$201,$AB8,$AC8)),"")))
A9: =IF($Z9="","",$AD9) | B9: =IF($Z9="C",INDEX(Contracts!$D$2:$D$151,$AB9)&"",IF($Z9="A",INDEX(Fixed_Assets!$C$2:$C$201,$AB9)&"",IF($Z9="F",INDEX(Workforce!$B$2:$B$151,MATCH(INDEX(FTE_Allocation!$A$2:$A$201,$AB9),Workforce!$A$2:$A$151,0))&"",""))) | C9: =IF($Z9="C",INDEX(Contracts!$E$2:$E$151,$AB9)&"",IF($Z9="A",INDEX(Fixed_Assets!$D$2:$D$201,$AB9)&"",IF($Z9="F",INDEX(FTE_Allocation!$C$2:$C$201,$AB9)&"",""))) | D9: =IF($Z9="C",INDEX(Contracts!$B$2:$B$151,$AB9)&"",IF($Z9="A",INDEX(Fixed_Assets!$B$2:$B$201,$AB9)&"",IF($Z9="F",INDEX(FTE_Allocation!$B$2:$B$201,$AB9)&"",""))) | E9: =IF($Z9="C",INDEX(Contracts!$P$2:$P$151,$AB9)&"",IF($Z9="A",INDEX(Fixed_Assets!$K$2:$K$201,$AB9)&"",IF($Z9="F",IF(INDEX(FTE_Allocation!$D$2:$D$201,$AB9)="PROJECT",IFERROR(INDEX(Projects!$D:$D,MATCH(INDEX(FTE_Allocation!$E$2:$E$201,$AB9),Projects!$A:$A,0))&"","#PROJECT?"),INDEX(FTE_Allocation!$E$2:$E$201,$AB9)&""),""))) | F9: =IF($Z9="C",INDEX(Contracts!$Q$2:$Q$151,$AB9)&"",IF($Z9="A",INDEX(Fixed_Assets!$L$2:$L$201,$AB9)&"",IF($Z9="F",INDEX(Workforce!$K$2:$K$151,MATCH(INDEX(FTE_Allocation!$A$2:$A$201,$AB9),Workforce!$A$2:$A$151,0))&"",""))) | G9: =IF($Z9="C",INDEX(Contracts!$F$2:$F$151,$AB9)&" / "&INDEX(Contracts!$G$2:$G$151,$AB9),IF($Z9="A",INDEX(Fixed_Assets!$E$2:$E$201,$AB9)&"",IF($Z9="F","Personnel "&INDEX(FTE_Allocation!$A$2:$A$201,$AB9)&IF(INDEX(FTE_Allocation!$D$2:$D$201,$AB9)="PROJECT"," ("&INDEX(FTE_Allocation!$E$2:$E$201,$AB9)&")",""),""))) | H9: =IF($Z9="C","CONTRACT",IF($Z9="A","ASSET",IF($Z9="F","WORKFORCE",""))) | I9: =IF($Z9="C",INDEX(Contracts!$L$2:$L$151,$AB9)&"",IF($Z9="A",INDEX(Fixed_Assets!$I$2:$I$201,$AB9)&"",IF($Z9="F",INDEX(Workforce!$G$2:$G$151,MATCH(INDEX(FTE_Allocation!$A$2:$A$201,$AB9),Workforce!$A$2:$A$151,0))&"",""))) | J9: =IF($Z9="","",IF(AND(DATE($AD9,1,1)>=$AE9,DATE($AD9,1,1)<=$AF9),ROUND($AG9,2),0)) | K9: =IF($Z9="","",IF(AND(DATE($AD9,2,1)>=$AE9,DATE($AD9,2,1)<=$AF9),ROUND($AG9,2),0)) | L9: =IF($Z9="","",IF(AND(DATE($AD9,3,1)>=$AE9,DATE($AD9,3,1)<=$AF9),ROUND($AG9,2),0)) | M9: =IF($Z9="","",IF(AND(DATE($AD9,4,1)>=$AE9,DATE($AD9,4,1)<=$AF9),ROUND($AG9,2),0)) | N9: =IF($Z9="","",IF(AND(DATE($AD9,5,1)>=$AE9,DATE($AD9,5,1)<=$AF9),ROUND($AG9,2),0)) | O9: =IF($Z9="","",IF(AND(DATE($AD9,6,1)>=$AE9,DATE($AD9,6,1)<=$AF9),ROUND($AG9,2),0)) | P9: =IF($Z9="","",IF(AND(DATE($AD9,7,1)>=$AE9,DATE($AD9,7,1)<=$AF9),ROUND($AG9,2),0)) | Q9: =IF($Z9="","",IF(AND(DATE($AD9,8,1)>=$AE9,DATE($AD9,8,1)<=$AF9),ROUND($AG9,2),0)) | R9: =IF($Z9="","",IF(AND(DATE($AD9,9,1)>=$AE9,DATE($AD9,9,1)<=$AF9),ROUND($AG9,2),0)) | S9: =IF($Z9="","",IF(AND(DATE($AD9,10,1)>=$AE9,DATE($AD9,10,1)<=$AF9),ROUND($AG9,2),0)) | T9: =IF($Z9="","",IF(AND(DATE($AD9,11,1)>=$AE9,DATE($AD9,11,1)<=$AF9),ROUND($AG9,2),0)) | U9: =IF($Z9="","",IF(AND(DATE($AD9,12,1)>=$AE9,DATE($AD9,12,1)<=$AF9),ROUND($AG9,2),0)) | V9: =IF($Z9="C","Generated from "&INDEX(Contracts!$A$2:$A$151,$AB9),IF($Z9="A","Generated from "&INDEX(Fixed_Assets!$A$2:$A$201,$AB9),IF($Z9="F","Generated from "&INDEX(FTE_Allocation!$A$2:$A$201,$AB9),""))) | X9: =IF($Z9="","",SUM(J9:U9)) | Y9: =ROW()-1 | Z9: =IF($Y9<=Settings!$B$4*3,"C",IF($Y9<=(Settings!$B$4+Settings!$B$5)*3,"A",IF($Y9<=(Settings!$B$4+Settings!$B$5+Settings!$B$6)*3,"F",""))) | AA9: =IF($Z9="C",$Y9,IF($Z9="A",$Y9-Settings!$B$4*3,IF($Z9="F",$Y9-(Settings!$B$4+Settings!$B$5)*3,""))) | AB9: =IF($Z9="","",INT(($AA9-1)/3)+1) | AC9: =IF($Z9="","",MOD($AA9-1,3)+1) | AD9: =IF($Z9="","",Settings!$B$2+$AC9-1) | AE9: =IF($Z9="C",DATE(YEAR(INDEX(Contracts!$J$2:$J$151,$AB9)),MONTH(INDEX(Contracts!$J$2:$J$151,$AB9)),1),IF($Z9="A",DATE(YEAR(INDEX(Fixed_Assets!$G$2:$G$201,$AB9)),MONTH(INDEX(Fixed_Assets!$G$2:$G$201,$AB9)),1),IF($Z9="F",DATE(YEAR(MAX(N(INDEX(Workforce!$I$2:$I$151,MATCH(INDEX(FTE_Allocation!$A$2:$A$201,$AB9),Workforce!$A$2:$A$151,0))),N(INDEX(FTE_Allocation!$I$2:$I$201,$AB9)))),MONTH(MAX(N(INDEX(Workforce!$I$2:$I$151,MATCH(INDEX(FTE_Allocation!$A$2:$A$201,$AB9),Workforce!$A$2:$A$151,0))),N(INDEX(FTE_Allocation!$I$2:$I$201,$AB9)))),1),""))) | AF9: =IF($Z9="C",IF(INDEX(Contracts!$I$2:$I$151,$AB9)="PREPAID",EDATE(DATE(YEAR(INDEX(Contracts!$J$2:$J$151,$AB9)),MONTH(INDEX(Contracts!$J$2:$J$151,$AB9)),1),IF(INDEX(Contracts!$N$2:$N$151,$AB9)="",12,INDEX(Contracts!$N$2:$N$151,$AB9))-1),IF(INDEX(Contracts!$I$2:$I$151,$AB9)="MONTHLY",IF(INDEX(Contracts!$K$2:$K$151,$AB9)="",2958101,INDEX(Contracts!$K$2:$K$151,$AB9)),0)),IF($Z9="A",EDATE(DATE(YEAR(INDEX(Fixed_Assets!$G$2:$G$201,$AB9)),MONTH(INDEX(Fixed_Assets!$G$2:$G$201,$AB9)),1),INDEX(Fixed_Assets!$J$2:$J$201,$AB9)-1),IF($Z9="F",MIN(IF(INDEX(Workforce!$J$2:$J$151,MATCH(INDEX(FTE_Allocation!$A$2:$A$201,$AB9),Workforce!$A$2:$A$151,0))="",2958101,INDEX(Workforce!$J$2:$J$151,MATCH(INDEX(FTE_Allocation!$A$2:$A$201,$AB9),Workforce!$A$2:$A$151,0))),IF(INDEX(FTE_Allocation!$J$2:$J$201,$AB9)="",2958101,INDEX(FTE_Allocation!$J$2:$J$201,$AB9))),""))) | AG9: =IF($Z9="C",IF(INDEX(Contracts!$I$2:$I$151,$AB9)="PREPAID",INDEX(Contracts!$M$2:$M$151,$AB9)/IF(INDEX(Contracts!$N$2:$N$151,$AB9)="",12,INDEX(Contracts!$N$2:$N$151,$AB9)),IF(INDEX(Contracts!$I$2:$I$151,$AB9)="MONTHLY",INDEX(Contracts!$M$2:$M$151,$AB9),0))*(1-N(INDEX(Contracts!$O$2:$O$151,$AB9))),IF($Z9="A",INDEX(Fixed_Assets!$H$2:$H$201,$AB9)/INDEX(Fixed_Assets!$J$2:$J$201,$AB9),IF($Z9="F",INDEX(Workforce!$F$2:$F$151,MATCH(INDEX(FTE_Allocation!$A$2:$A$201,$AB9),Workforce!$A$2:$A$151,0))*N(INDEX(FTE_Allocation!$F$2:$H$201,$AB9,$AC9)),"")))
A10: =IF($Z10="","",$AD10) | B10: =IF($Z10="C",INDEX(Contracts!$D$2:$D$151,$AB10)&"",IF($Z10="A",INDEX(Fixed_Assets!$C$2:$C$201,$AB10)&"",IF($Z10="F",INDEX(Workforce!$B$2:$B$151,MATCH(INDEX(FTE_Allocation!$A$2:$A$201,$AB10),Workforce!$A$2:$A$151,0))&"",""))) | C10: =IF($Z10="C",INDEX(Contracts!$E$2:$E$151,$AB10)&"",IF($Z10="A",INDEX(Fixed_Assets!$D$2:$D$201,$AB10)&"",IF($Z10="F",INDEX(FTE_Allocation!$C$2:$C$201,$AB10)&"",""))) | D10: =IF($Z10="C",INDEX(Contracts!$B$2:$B$151,$AB10)&"",IF($Z10="A",INDEX(Fixed_Assets!$B$2:$B$201,$AB10)&"",IF($Z10="F",INDEX(FTE_Allocation!$B$2:$B$201,$AB10)&"",""))) | E10: =IF($Z10="C",INDEX(Contracts!$P$2:$P$151,$AB10)&"",IF($Z10="A",INDEX(Fixed_Assets!$K$2:$K$201,$AB10)&"",IF($Z10="F",IF(INDEX(FTE_Allocation!$D$2:$D$201,$AB10)="PROJECT",IFERROR(INDEX(Projects!$D:$D,MATCH(INDEX(FTE_Allocation!$E$2:$E$201,$AB10),Projects!$A:$A,0))&"","#PROJECT?"),INDEX(FTE_Allocation!$E$2:$E$201,$AB10)&""),""))) | F10: =IF($Z10="C",INDEX(Contracts!$Q$2:$Q$151,$AB10)&"",IF($Z10="A",INDEX(Fixed_Assets!$L$2:$L$201,$AB10)&"",IF($Z10="F",INDEX(Workforce!$K$2:$K$151,MATCH(INDEX(FTE_Allocation!$A$2:$A$201,$AB10),Workforce!$A$2:$A$151,0))&"",""))) | G10: =IF($Z10="C",INDEX(Contracts!$F$2:$F$151,$AB10)&" / "&INDEX(Contracts!$G$2:$G$151,$AB10),IF($Z10="A",INDEX(Fixed_Assets!$E$2:$E$201,$AB10)&"",IF($Z10="F","Personnel "&INDEX(FTE_Allocation!$A$2:$A$201,$AB10)&IF(INDEX(FTE_Allocation!$D$2:$D$201,$AB10)="PROJECT"," ("&INDEX(FTE_Allocation!$E$2:$E$201,$AB10)&")",""),""))) | H10: =IF($Z10="C","CONTRACT",IF($Z10="A","ASSET",IF($Z10="F","WORKFORCE",""))) | I10: =IF($Z10="C",INDEX(Contracts!$L$2:$L$151,$AB10)&"",IF($Z10="A",INDEX(Fixed_Assets!$I$2:$I$201,$AB10)&"",IF($Z10="F",INDEX(Workforce!$G$2:$G$151,MATCH(INDEX(FTE_Allocation!$A$2:$A$201,$AB10),Workforce!$A$2:$A$151,0))&"",""))) | J10: =IF($Z10="","",IF(AND(DATE($AD10,1,1)>=$AE10,DATE($AD10,1,1)<=$AF10),ROUND($AG10,2),0)) | K10: =IF($Z10="","",IF(AND(DATE($AD10,2,1)>=$AE10,DATE($AD10,2,1)<=$AF10),ROUND($AG10,2),0)) | L10: =IF($Z10="","",IF(AND(DATE($AD10,3,1)>=$AE10,DATE($AD10,3,1)<=$AF10),ROUND($AG10,2),0)) | M10: =IF($Z10="","",IF(AND(DATE($AD10,4,1)>=$AE10,DATE($AD10,4,1)<=$AF10),ROUND($AG10,2),0)) | N10: =IF($Z10="","",IF(AND(DATE($AD10,5,1)>=$AE10,DATE($AD10,5,1)<=$AF10),ROUND($AG10,2),0)) | O10: =IF($Z10="","",IF(AND(DATE($AD10,6,1)>=$AE10,DATE($AD10,6,1)<=$AF10),ROUND($AG10,2),0)) | P10: =IF($Z10="","",IF(AND(DATE($AD10,7,1)>=$AE10,DATE($AD10,7,1)<=$AF10),ROUND($AG10,2),0)) | Q10: =IF($Z10="","",IF(AND(DATE($AD10,8,1)>=$AE10,DATE($AD10,8,1)<=$AF10),ROUND($AG10,2),0)) | R10: =IF($Z10="","",IF(AND(DATE($AD10,9,1)>=$AE10,DATE($AD10,9,1)<=$AF10),ROUND($AG10,2),0)) | S10: =IF($Z10="","",IF(AND(DATE($AD10,10,1)>=$AE10,DATE($AD10,10,1)<=$AF10),ROUND($AG10,2),0)) | T10: =IF($Z10="","",IF(AND(DATE($AD10,11,1)>=$AE10,DATE($AD10,11,1)<=$AF10),ROUND($AG10,2),0)) | U10: =IF($Z10="","",IF(AND(DATE($AD10,12,1)>=$AE10,DATE($AD10,12,1)<=$AF10),ROUND($AG10,2),0)) | V10: =IF($Z10="C","Generated from "&INDEX(Contracts!$A$2:$A$151,$AB10),IF($Z10="A","Generated from "&INDEX(Fixed_Assets!$A$2:$A$201,$AB10),IF($Z10="F","Generated from "&INDEX(FTE_Allocation!$A$2:$A$201,$AB10),""))) | X10: =IF($Z10="","",SUM(J10:U10)) | Y10: =ROW()-1 | Z10: =IF($Y10<=Settings!$B$4*3,"C",IF($Y10<=(Settings!$B$4+Settings!$B$5)*3,"A",IF($Y10<=(Settings!$B$4+Settings!$B$5+Settings!$B$6)*3,"F",""))) | AA10: =IF($Z10="C",$Y10,IF($Z10="A",$Y10-Settings!$B$4*3,IF($Z10="F",$Y10-(Settings!$B$4+Settings!$B$5)*3,""))) | AB10: =IF($Z10="","",INT(($AA10-1)/3)+1) | AC10: =IF($Z10="","",MOD($AA10-1,3)+1) | AD10: =IF($Z10="","",Settings!$B$2+$AC10-1) | AE10: =IF($Z10="C",DATE(YEAR(INDEX(Contracts!$J$2:$J$151,$AB10)),MONTH(INDEX(Contracts!$J$2:$J$151,$AB10)),1),IF($Z10="A",DATE(YEAR(INDEX(Fixed_Assets!$G$2:$G$201,$AB10)),MONTH(INDEX(Fixed_Assets!$G$2:$G$201,$AB10)),1),IF($Z10="F",DATE(YEAR(MAX(N(INDEX(Workforce!$I$2:$I$151,MATCH(INDEX(FTE_Allocation!$A$2:$A$201,$AB10),Workforce!$A$2:$A$151,0))),N(INDEX(FTE_Allocation!$I$2:$I$201,$AB10)))),MONTH(MAX(N(INDEX(Workforce!$I$2:$I$151,MATCH(INDEX(FTE_Allocation!$A$2:$A$201,$AB10),Workforce!$A$2:$A$151,0))),N(INDEX(FTE_Allocation!$I$2:$I$201,$AB10)))),1),""))) | AF10: =IF($Z10="C",IF(INDEX(Contracts!$I$2:$I$151,$AB10)="PREPAID",EDATE(DATE(YEAR(INDEX(Contracts!$J$2:$J$151,$AB10)),MONTH(INDEX(Contracts!$J$2:$J$151,$AB10)),1),IF(INDEX(Contracts!$N$2:$N$151,$AB10)="",12,INDEX(Contracts!$N$2:$N$151,$AB10))-1),IF(INDEX(Contracts!$I$2:$I$151,$AB10)="MONTHLY",IF(INDEX(Contracts!$K$2:$K$151,$AB10)="",2958101,INDEX(Contracts!$K$2:$K$151,$AB10)),0)),IF($Z10="A",EDATE(DATE(YEAR(INDEX(Fixed_Assets!$G$2:$G$201,$AB10)),MONTH(INDEX(Fixed_Assets!$G$2:$G$201,$AB10)),1),INDEX(Fixed_Assets!$J$2:$J$201,$AB10)-1),IF($Z10="F",MIN(IF(INDEX(Workforce!$J$2:$J$151,MATCH(INDEX(FTE_Allocation!$A$2:$A$201,$AB10),Workforce!$A$2:$A$151,0))="",2958101,INDEX(Workforce!$J$2:$J$151,MATCH(INDEX(FTE_Allocation!$A$2:$A$201,$AB10),Workforce!$A$2:$A$151,0))),IF(INDEX(FTE_Allocation!$J$2:$J$201,$AB10)="",2958101,INDEX(FTE_Allocation!$J$2:$J$201,$AB10))),""))) | AG10: =IF($Z10="C",IF(INDEX(Contracts!$I$2:$I$151,$AB10)="PREPAID",INDEX(Contracts!$M$2:$M$151,$AB10)/IF(INDEX(Contracts!$N$2:$N$151,$AB10)="",12,INDEX(Contracts!$N$2:$N$151,$AB10)),IF(INDEX(Contracts!$I$2:$I$151,$AB10)="MONTHLY",INDEX(Contracts!$M$2:$M$151,$AB10),0))*(1-N(INDEX(Contracts!$O$2:$O$151,$AB10))),IF($Z10="A",INDEX(Fixed_Assets!$H$2:$H$201,$AB10)/INDEX(Fixed_Assets!$J$2:$J$201,$AB10),IF($Z10="F",INDEX(Workforce!$F$2:$F$151,MATCH(INDEX(FTE_Allocation!$A$2:$A$201,$AB10),Workforce!$A$2:$A$151,0))*N(INDEX(FTE_Allocation!$F$2:$H$201,$AB10,$AC10)),"")))
A11: =IF($Z11="","",$AD11) | B11: =IF($Z11="C",INDEX(Contracts!$D$2:$D$151,$AB11)&"",IF($Z11="A",INDEX(Fixed_Assets!$C$2:$C$201,$AB11)&"",IF($Z11="F",INDEX(Workforce!$B$2:$B$151,MATCH(INDEX(FTE_Allocation!$A$2:$A$201,$AB11),Workforce!$A$2:$A$151,0))&"",""))) | C11: =IF($Z11="C",INDEX(Contracts!$E$2:$E$151,$AB11)&"",IF($Z11="A",INDEX(Fixed_Assets!$D$2:$D$201,$AB11)&"",IF($Z11="F",INDEX(FTE_Allocation!$C$2:$C$201,$AB11)&"",""))) | D11: =IF($Z11="C",INDEX(Contracts!$B$2:$B$151,$AB11)&"",IF($Z11="A",INDEX(Fixed_Assets!$B$2:$B$201,$AB11)&"",IF($Z11="F",INDEX(FTE_Allocation!$B$2:$B$201,$AB11)&"",""))) | E11: =IF($Z11="C",INDEX(Contracts!$P$2:$P$151,$AB11)&"",IF($Z11="A",INDEX(Fixed_Assets!$K$2:$K$201,$AB11)&"",IF($Z11="F",IF(INDEX(FTE_Allocation!$D$2:$D$201,$AB11)="PROJECT",IFERROR(INDEX(Projects!$D:$D,MATCH(INDEX(FTE_Allocation!$E$2:$E$201,$AB11),Projects!$A:$A,0))&"","#PROJECT?"),INDEX(FTE_Allocation!$E$2:$E$201,$AB11)&""),""))) | F11: =IF($Z11="C",INDEX(Contracts!$Q$2:$Q$151,$AB11)&"",IF($Z11="A",INDEX(Fixed_Assets!$L$2:$L$201,$AB11)&"",IF($Z11="F",INDEX(Workforce!$K$2:$K$151,MATCH(INDEX(FTE_Allocation!$A$2:$A$201,$AB11),Workforce!$A$2:$A$151,0))&"",""))) | G11: =IF($Z11="C",INDEX(Contracts!$F$2:$F$151,$AB11)&" / "&INDEX(Contracts!$G$2:$G$151,$AB11),IF($Z11="A",INDEX(Fixed_Assets!$E$2:$E$201,$AB11)&"",IF($Z11="F","Personnel "&INDEX(FTE_Allocation!$A$2:$A$201,$AB11)&IF(INDEX(FTE_Allocation!$D$2:$D$201,$AB11)="PROJECT"," ("&INDEX(FTE_Allocation!$E$2:$E$201,$AB11)&")",""),""))) | H11: =IF($Z11="C","CONTRACT",IF($Z11="A","ASSET",IF($Z11="F","WORKFORCE",""))) | I11: =IF($Z11="C",INDEX(Contracts!$L$2:$L$151,$AB11)&"",IF($Z11="A",INDEX(Fixed_Assets!$I$2:$I$201,$AB11)&"",IF($Z11="F",INDEX(Workforce!$G$2:$G$151,MATCH(INDEX(FTE_Allocation!$A$2:$A$201,$AB11),Workforce!$A$2:$A$151,0))&"",""))) | J11: =IF($Z11="","",IF(AND(DATE($AD11,1,1)>=$AE11,DATE($AD11,1,1)<=$AF11),ROUND($AG11,2),0)) | K11: =IF($Z11="","",IF(AND(DATE($AD11,2,1)>=$AE11,DATE($AD11,2,1)<=$AF11),ROUND($AG11,2),0)) | L11: =IF($Z11="","",IF(AND(DATE($AD11,3,1)>=$AE11,DATE($AD11,3,1)<=$AF11),ROUND($AG11,2),0)) | M11: =IF($Z11="","",IF(AND(DATE($AD11,4,1)>=$AE11,DATE($AD11,4,1)<=$AF11),ROUND($AG11,2),0)) | N11: =IF($Z11="","",IF(AND(DATE($AD11,5,1)>=$AE11,DATE($AD11,5,1)<=$AF11),ROUND($AG11,2),0)) | O11: =IF($Z11="","",IF(AND(DATE($AD11,6,1)>=$AE11,DATE($AD11,6,1)<=$AF11),ROUND($AG11,2),0)) | P11: =IF($Z11="","",IF(AND(DATE($AD11,7,1)>=$AE11,DATE($AD11,7,1)<=$AF11),ROUND($AG11,2),0)) | Q11: =IF($Z11="","",IF(AND(DATE($AD11,8,1)>=$AE11,DATE($AD11,8,1)<=$AF11),ROUND($AG11,2),0)) | R11: =IF($Z11="","",IF(AND(DATE($AD11,9,1)>=$AE11,DATE($AD11,9,1)<=$AF11),ROUND($AG11,2),0)) | S11: =IF($Z11="","",IF(AND(DATE($AD11,10,1)>=$AE11,DATE($AD11,10,1)<=$AF11),ROUND($AG11,2),0)) | T11: =IF($Z11="","",IF(AND(DATE($AD11,11,1)>=$AE11,DATE($AD11,11,1)<=$AF11),ROUND($AG11,2),0)) | U11: =IF($Z11="","",IF(AND(DATE($AD11,12,1)>=$AE11,DATE($AD11,12,1)<=$AF11),ROUND($AG11,2),0)) | V11: =IF($Z11="C","Generated from "&INDEX(Contracts!$A$2:$A$151,$AB11),IF($Z11="A","Generated from "&INDEX(Fixed_Assets!$A$2:$A$201,$AB11),IF($Z11="F","Generated from "&INDEX(FTE_Allocation!$A$2:$A$201,$AB11),""))) | X11: =IF($Z11="","",SUM(J11:U11)) | Y11: =ROW()-1 | Z11: =IF($Y11<=Settings!$B$4*3,"C",IF($Y11<=(Settings!$B$4+Settings!$B$5)*3,"A",IF($Y11<=(Settings!$B$4+Settings!$B$5+Settings!$B$6)*3,"F",""))) | AA11: =IF($Z11="C",$Y11,IF($Z11="A",$Y11-Settings!$B$4*3,IF($Z11="F",$Y11-(Settings!$B$4+Settings!$B$5)*3,""))) | AB11: =IF($Z11="","",INT(($AA11-1)/3)+1) | AC11: =IF($Z11="","",MOD($AA11-1,3)+1) | AD11: =IF($Z11="","",Settings!$B$2+$AC11-1) | AE11: =IF($Z11="C",DATE(YEAR(INDEX(Contracts!$J$2:$J$151,$AB11)),MONTH(INDEX(Contracts!$J$2:$J$151,$AB11)),1),IF($Z11="A",DATE(YEAR(INDEX(Fixed_Assets!$G$2:$G$201,$AB11)),MONTH(INDEX(Fixed_Assets!$G$2:$G$201,$AB11)),1),IF($Z11="F",DATE(YEAR(MAX(N(INDEX(Workforce!$I$2:$I$151,MATCH(INDEX(FTE_Allocation!$A$2:$A$201,$AB11),Workforce!$A$2:$A$151,0))),N(INDEX(FTE_Allocation!$I$2:$I$201,$AB11)))),MONTH(MAX(N(INDEX(Workforce!$I$2:$I$151,MATCH(INDEX(FTE_Allocation!$A$2:$A$201,$AB11),Workforce!$A$2:$A$151,0))),N(INDEX(FTE_Allocation!$I$2:$I$201,$AB11)))),1),""))) | AF11: =IF($Z11="C",IF(INDEX(Contracts!$I$2:$I$151,$AB11)="PREPAID",EDATE(DATE(YEAR(INDEX(Contracts!$J$2:$J$151,$AB11)),MONTH(INDEX(Contracts!$J$2:$J$151,$AB11)),1),IF(INDEX(Contracts!$N$2:$N$151,$AB11)="",12,INDEX(Contracts!$N$2:$N$151,$AB11))-1),IF(INDEX(Contracts!$I$2:$I$151,$AB11)="MONTHLY",IF(INDEX(Contracts!$K$2:$K$151,$AB11)="",2958101,INDEX(Contracts!$K$2:$K$151,$AB11)),0)),IF($Z11="A",EDATE(DATE(YEAR(INDEX(Fixed_Assets!$G$2:$G$201,$AB11)),MONTH(INDEX(Fixed_Assets!$G$2:$G$201,$AB11)),1),INDEX(Fixed_Assets!$J$2:$J$201,$AB11)-1),IF($Z11="F",MIN(IF(INDEX(Workforce!$J$2:$J$151,MATCH(INDEX(FTE_Allocation!$A$2:$A$201,$AB11),Workforce!$A$2:$A$151,0))="",2958101,INDEX(Workforce!$J$2:$J$151,MATCH(INDEX(FTE_Allocation!$A$2:$A$201,$AB11),Workforce!$A$2:$A$151,0))),IF(INDEX(FTE_Allocation!$J$2:$J$201,$AB11)="",2958101,INDEX(FTE_Allocation!$J$2:$J$201,$AB11))),""))) | AG11: =IF($Z11="C",IF(INDEX(Contracts!$I$2:$I$151,$AB11)="PREPAID",INDEX(Contracts!$M$2:$M$151,$AB11)/IF(INDEX(Contracts!$N$2:$N$151,$AB11)="",12,INDEX(Contracts!$N$2:$N$151,$AB11)),IF(INDEX(Contracts!$I$2:$I$151,$AB11)="MONTHLY",INDEX(Contracts!$M$2:$M$151,$AB11),0))*(1-N(INDEX(Contracts!$O$2:$O$151,$AB11))),IF($Z11="A",INDEX(Fixed_Assets!$H$2:$H$201,$AB11)/INDEX(Fixed_Assets!$J$2:$J$201,$AB11),IF($Z11="F",INDEX(Workforce!$F$2:$F$151,MATCH(INDEX(FTE_Allocation!$A$2:$A$201,$AB11),Workforce!$A$2:$A$151,0))*N(INDEX(FTE_Allocation!$F$2:$H$201,$AB11,$AC11)),"")))
A12: =IF($Z12="","",$AD12) | B12: =IF($Z12="C",INDEX(Contracts!$D$2:$D$151,$AB12)&"",IF($Z12="A",INDEX(Fixed_Assets!$C$2:$C$201,$AB12)&"",IF($Z12="F",INDEX(Workforce!$B$2:$B$151,MATCH(INDEX(FTE_Allocation!$A$2:$A$201,$AB12),Workforce!$A$2:$A$151,0))&"",""))) | C12: =IF($Z12="C",INDEX(Contracts!$E$2:$E$151,$AB12)&"",IF($Z12="A",INDEX(Fixed_Assets!$D$2:$D$201,$AB12)&"",IF($Z12="F",INDEX(FTE_Allocation!$C$2:$C$201,$AB12)&"",""))) | D12: =IF($Z12="C",INDEX(Contracts!$B$2:$B$151,$AB12)&"",IF($Z12="A",INDEX(Fixed_Assets!$B$2:$B$201,$AB12)&"",IF($Z12="F",INDEX(FTE_Allocation!$B$2:$B$201,$AB12)&"",""))) | E12: =IF($Z12="C",INDEX(Contracts!$P$2:$P$151,$AB12)&"",IF($Z12="A",INDEX(Fixed_Assets!$K$2:$K$201,$AB12)&"",IF($Z12="F",IF(INDEX(FTE_Allocation!$D$2:$D$201,$AB12)="PROJECT",IFERROR(INDEX(Projects!$D:$D,MATCH(INDEX(FTE_Allocation!$E$2:$E$201,$AB12),Projects!$A:$A,0))&"","#PROJECT?"),INDEX(FTE_Allocation!$E$2:$E$201,$AB12)&""),""))) | F12: =IF($Z12="C",INDEX(Contracts!$Q$2:$Q$151,$AB12)&"",IF($Z12="A",INDEX(Fixed_Assets!$L$2:$L$201,$AB12)&"",IF($Z12="F",INDEX(Workforce!$K$2:$K$151,MATCH(INDEX(FTE_Allocation!$A$2:$A$201,$AB12),Workforce!$A$2:$A$151,0))&"",""))) | G12: =IF($Z12="C",INDEX(Contracts!$F$2:$F$151,$AB12)&" / "&INDEX(Contracts!$G$2:$G$151,$AB12),IF($Z12="A",INDEX(Fixed_Assets!$E$2:$E$201,$AB12)&"",IF($Z12="F","Personnel "&INDEX(FTE_Allocation!$A$2:$A$201,$AB12)&IF(INDEX(FTE_Allocation!$D$2:$D$201,$AB12)="PROJECT"," ("&INDEX(FTE_Allocation!$E$2:$E$201,$AB12)&")",""),""))) | H12: =IF($Z12="C","CONTRACT",IF($Z12="A","ASSET",IF($Z12="F","WORKFORCE",""))) | I12: =IF($Z12="C",INDEX(Contracts!$L$2:$L$151,$AB12)&"",IF($Z12="A",INDEX(Fixed_Assets!$I$2:$I$201,$AB12)&"",IF($Z12="F",INDEX(Workforce!$G$2:$G$151,MATCH(INDEX(FTE_Allocation!$A$2:$A$201,$AB12),Workforce!$A$2:$A$151,0))&"",""))) | J12: =IF($Z12="","",IF(AND(DATE($AD12,1,1)>=$AE12,DATE($AD12,1,1)<=$AF12),ROUND($AG12,2),0)) | K12: =IF($Z12="","",IF(AND(DATE($AD12,2,1)>=$AE12,DATE($AD12,2,1)<=$AF12),ROUND($AG12,2),0)) | L12: =IF($Z12="","",IF(AND(DATE($AD12,3,1)>=$AE12,DATE($AD12,3,1)<=$AF12),ROUND($AG12,2),0)) | M12: =IF($Z12="","",IF(AND(DATE($AD12,4,1)>=$AE12,DATE($AD12,4,1)<=$AF12),ROUND($AG12,2),0)) | N12: =IF($Z12="","",IF(AND(DATE($AD12,5,1)>=$AE12,DATE($AD12,5,1)<=$AF12),ROUND($AG12,2),0)) | O12: =IF($Z12="","",IF(AND(DATE($AD12,6,1)>=$AE12,DATE($AD12,6,1)<=$AF12),ROUND($AG12,2),0)) | P12: =IF($Z12="","",IF(AND(DATE($AD12,7,1)>=$AE12,DATE($AD12,7,1)<=$AF12),ROUND($AG12,2),0)) | Q12: =IF($Z12="","",IF(AND(DATE($AD12,8,1)>=$AE12,DATE($AD12,8,1)<=$AF12),ROUND($AG12,2),0)) | R12: =IF($Z12="","",IF(AND(DATE($AD12,9,1)>=$AE12,DATE($AD12,9,1)<=$AF12),ROUND($AG12,2),0)) | S12: =IF($Z12="","",IF(AND(DATE($AD12,10,1)>=$AE12,DATE($AD12,10,1)<=$AF12),ROUND($AG12,2),0)) | T12: =IF($Z12="","",IF(AND(DATE($AD12,11,1)>=$AE12,DATE($AD12,11,1)<=$AF12),ROUND($AG12,2),0)) | U12: =IF($Z12="","",IF(AND(DATE($AD12,12,1)>=$AE12,DATE($AD12,12,1)<=$AF12),ROUND($AG12,2),0)) | V12: =IF($Z12="C","Generated from "&INDEX(Contracts!$A$2:$A$151,$AB12),IF($Z12="A","Generated from "&INDEX(Fixed_Assets!$A$2:$A$201,$AB12),IF($Z12="F","Generated from "&INDEX(FTE_Allocation!$A$2:$A$201,$AB12),""))) | X12: =IF($Z12="","",SUM(J12:U12)) | Y12: =ROW()-1 | Z12: =IF($Y12<=Settings!$B$4*3,"C",IF($Y12<=(Settings!$B$4+Settings!$B$5)*3,"A",IF($Y12<=(Settings!$B$4+Settings!$B$5+Settings!$B$6)*3,"F",""))) | AA12: =IF($Z12="C",$Y12,IF($Z12="A",$Y12-Settings!$B$4*3,IF($Z12="F",$Y12-(Settings!$B$4+Settings!$B$5)*3,""))) | AB12: =IF($Z12="","",INT(($AA12-1)/3)+1) | AC12: =IF($Z12="","",MOD($AA12-1,3)+1) | AD12: =IF($Z12="","",Settings!$B$2+$AC12-1) | AE12: =IF($Z12="C",DATE(YEAR(INDEX(Contracts!$J$2:$J$151,$AB12)),MONTH(INDEX(Contracts!$J$2:$J$151,$AB12)),1),IF($Z12="A",DATE(YEAR(INDEX(Fixed_Assets!$G$2:$G$201,$AB12)),MONTH(INDEX(Fixed_Assets!$G$2:$G$201,$AB12)),1),IF($Z12="F",DATE(YEAR(MAX(N(INDEX(Workforce!$I$2:$I$151,MATCH(INDEX(FTE_Allocation!$A$2:$A$201,$AB12),Workforce!$A$2:$A$151,0))),N(INDEX(FTE_Allocation!$I$2:$I$201,$AB12)))),MONTH(MAX(N(INDEX(Workforce!$I$2:$I$151,MATCH(INDEX(FTE_Allocation!$A$2:$A$201,$AB12),Workforce!$A$2:$A$151,0))),N(INDEX(FTE_Allocation!$I$2:$I$201,$AB12)))),1),""))) | AF12: =IF($Z12="C",IF(INDEX(Contracts!$I$2:$I$151,$AB12)="PREPAID",EDATE(DATE(YEAR(INDEX(Contracts!$J$2:$J$151,$AB12)),MONTH(INDEX(Contracts!$J$2:$J$151,$AB12)),1),IF(INDEX(Contracts!$N$2:$N$151,$AB12)="",12,INDEX(Contracts!$N$2:$N$151,$AB12))-1),IF(INDEX(Contracts!$I$2:$I$151,$AB12)="MONTHLY",IF(INDEX(Contracts!$K$2:$K$151,$AB12)="",2958101,INDEX(Contracts!$K$2:$K$151,$AB12)),0)),IF($Z12="A",EDATE(DATE(YEAR(INDEX(Fixed_Assets!$G$2:$G$201,$AB12)),MONTH(INDEX(Fixed_Assets!$G$2:$G$201,$AB12)),1),INDEX(Fixed_Assets!$J$2:$J$201,$AB12)-1),IF($Z12="F",MIN(IF(INDEX(Workforce!$J$2:$J$151,MATCH(INDEX(FTE_Allocation!$A$2:$A$201,$AB12),Workforce!$A$2:$A$151,0))="",2958101,INDEX(Workforce!$J$2:$J$151,MATCH(INDEX(FTE_Allocation!$A$2:$A$201,$AB12),Workforce!$A$2:$A$151,0))),IF(INDEX(FTE_Allocation!$J$2:$J$201,$AB12)="",2958101,INDEX(FTE_Allocation!$J$2:$J$201,$AB12))),""))) | AG12: =IF($Z12="C",IF(INDEX(Contracts!$I$2:$I$151,$AB12)="PREPAID",INDEX(Contracts!$M$2:$M$151,$AB12)/IF(INDEX(Contracts!$N$2:$N$151,$AB12)="",12,INDEX(Contracts!$N$2:$N$151,$AB12)),IF(INDEX(Contracts!$I$2:$I$151,$AB12)="MONTHLY",INDEX(Contracts!$M$2:$M$151,$AB12),0))*(1-N(INDEX(Contracts!$O$2:$O$151,$AB12))),IF($Z12="A",INDEX(Fixed_Assets!$H$2:$H$201,$AB12)/INDEX(Fixed_Assets!$J$2:$J$201,$AB12),IF($Z12="F",INDEX(Workforce!$F$2:$F$151,MATCH(INDEX(FTE_Allocation!$A$2:$A$201,$AB12),Workforce!$A$2:$A$151,0))*N(INDEX(FTE_Allocation!$F$2:$H$201,$AB12,$AC12)),"")))
A13: =IF($Z13="","",$AD13) | B13: =IF($Z13="C",INDEX(Contracts!$D$2:$D$151,$AB13)&"",IF($Z13="A",INDEX(Fixed_Assets!$C$2:$C$201,$AB13)&"",IF($Z13="F",INDEX(Workforce!$B$2:$B$151,MATCH(INDEX(FTE_Allocation!$A$2:$A$201,$AB13),Workforce!$A$2:$A$151,0))&"",""))) | C13: =IF($Z13="C",INDEX(Contracts!$E$2:$E$151,$AB13)&"",IF($Z13="A",INDEX(Fixed_Assets!$D$2:$D$201,$AB13)&"",IF($Z13="F",INDEX(FTE_Allocation!$C$2:$C$201,$AB13)&"",""))) | D13: =IF($Z13="C",INDEX(Contracts!$B$2:$B$151,$AB13)&"",IF($Z13="A",INDEX(Fixed_Assets!$B$2:$B$201,$AB13)&"",IF($Z13="F",INDEX(FTE_Allocation!$B$2:$B$201,$AB13)&"",""))) | E13: =IF($Z13="C",INDEX(Contracts!$P$2:$P$151,$AB13)&"",IF($Z13="A",INDEX(Fixed_Assets!$K$2:$K$201,$AB13)&"",IF($Z13="F",IF(INDEX(FTE_Allocation!$D$2:$D$201,$AB13)="PROJECT",IFERROR(INDEX(Projects!$D:$D,MATCH(INDEX(FTE_Allocation!$E$2:$E$201,$AB13),Projects!$A:$A,0))&"","#PROJECT?"),INDEX(FTE_Allocation!$E$2:$E$201,$AB13)&""),""))) | F13: =IF($Z13="C",INDEX(Contracts!$Q$2:$Q$151,$AB13)&"",IF($Z13="A",INDEX(Fixed_Assets!$L$2:$L$201,$AB13)&"",IF($Z13="F",INDEX(Workforce!$K$2:$K$151,MATCH(INDEX(FTE_Allocation!$A$2:$A$201,$AB13),Workforce!$A$2:$A$151,0))&"",""))) | G13: =IF($Z13="C",INDEX(Contracts!$F$2:$F$151,$AB13)&" / "&INDEX(Contracts!$G$2:$G$151,$AB13),IF($Z13="A",INDEX(Fixed_Assets!$E$2:$E$201,$AB13)&"",IF($Z13="F","Personnel "&INDEX(FTE_Allocation!$A$2:$A$201,$AB13)&IF(INDEX(FTE_Allocation!$D$2:$D$201,$AB13)="PROJECT"," ("&INDEX(FTE_Allocation!$E$2:$E$201,$AB13)&")",""),""))) | H13: =IF($Z13="C","CONTRACT",IF($Z13="A","ASSET",IF($Z13="F","WORKFORCE",""))) | I13: =IF($Z13="C",INDEX(Contracts!$L$2:$L$151,$AB13)&"",IF($Z13="A",INDEX(Fixed_Assets!$I$2:$I$201,$AB13)&"",IF($Z13="F",INDEX(Workforce!$G$2:$G$151,MATCH(INDEX(FTE_Allocation!$A$2:$A$201,$AB13),Workforce!$A$2:$A$151,0))&"",""))) | J13: =IF($Z13="","",IF(AND(DATE($AD13,1,1)>=$AE13,DATE($AD13,1,1)<=$AF13),ROUND($AG13,2),0)) | K13: =IF($Z13="","",IF(AND(DATE($AD13,2,1)>=$AE13,DATE($AD13,2,1)<=$AF13),ROUND($AG13,2),0)) | L13: =IF($Z13="","",IF(AND(DATE($AD13,3,1)>=$AE13,DATE($AD13,3,1)<=$AF13),ROUND($AG13,2),0)) | M13: =IF($Z13="","",IF(AND(DATE($AD13,4,1)>=$AE13,DATE($AD13,4,1)<=$AF13),ROUND($AG13,2),0)) | N13: =IF($Z13="","",IF(AND(DATE($AD13,5,1)>=$AE13,DATE($AD13,5,1)<=$AF13),ROUND($AG13,2),0)) | O13: =IF($Z13="","",IF(AND(DATE($AD13,6,1)>=$AE13,DATE($AD13,6,1)<=$AF13),ROUND($AG13,2),0)) | P13: =IF($Z13="","",IF(AND(DATE($AD13,7,1)>=$AE13,DATE($AD13,7,1)<=$AF13),ROUND($AG13,2),0)) | Q13: =IF($Z13="","",IF(AND(DATE($AD13,8,1)>=$AE13,DATE($AD13,8,1)<=$AF13),ROUND($AG13,2),0)) | R13: =IF($Z13="","",IF(AND(DATE($AD13,9,1)>=$AE13,DATE($AD13,9,1)<=$AF13),ROUND($AG13,2),0)) | S13: =IF($Z13="","",IF(AND(DATE($AD13,10,1)>=$AE13,DATE($AD13,10,1)<=$AF13),ROUND($AG13,2),0)) | T13: =IF($Z13="","",IF(AND(DATE($AD13,11,1)>=$AE13,DATE($AD13,11,1)<=$AF13),ROUND($AG13,2),0)) | U13: =IF($Z13="","",IF(AND(DATE($AD13,12,1)>=$AE13,DATE($AD13,12,1)<=$AF13),ROUND($AG13,2),0)) | V13: =IF($Z13="C","Generated from "&INDEX(Contracts!$A$2:$A$151,$AB13),IF($Z13="A","Generated from "&INDEX(Fixed_Assets!$A$2:$A$201,$AB13),IF($Z13="F","Generated from "&INDEX(FTE_Allocation!$A$2:$A$201,$AB13),""))) | X13: =IF($Z13="","",SUM(J13:U13)) | Y13: =ROW()-1 | Z13: =IF($Y13<=Settings!$B$4*3,"C",IF($Y13<=(Settings!$B$4+Settings!$B$5)*3,"A",IF($Y13<=(Settings!$B$4+Settings!$B$5+Settings!$B$6)*3,"F",""))) | AA13: =IF($Z13="C",$Y13,IF($Z13="A",$Y13-Settings!$B$4*3,IF($Z13="F",$Y13-(Settings!$B$4+Settings!$B$5)*3,""))) | AB13: =IF($Z13="","",INT(($AA13-1)/3)+1) | AC13: =IF($Z13="","",MOD($AA13-1,3)+1) | AD13: =IF($Z13="","",Settings!$B$2+$AC13-1) | AE13: =IF($Z13="C",DATE(YEAR(INDEX(Contracts!$J$2:$J$151,$AB13)),MONTH(INDEX(Contracts!$J$2:$J$151,$AB13)),1),IF($Z13="A",DATE(YEAR(INDEX(Fixed_Assets!$G$2:$G$201,$AB13)),MONTH(INDEX(Fixed_Assets!$G$2:$G$201,$AB13)),1),IF($Z13="F",DATE(YEAR(MAX(N(INDEX(Workforce!$I$2:$I$151,MATCH(INDEX(FTE_Allocation!$A$2:$A$201,$AB13),Workforce!$A$2:$A$151,0))),N(INDEX(FTE_Allocation!$I$2:$I$201,$AB13)))),MONTH(MAX(N(INDEX(Workforce!$I$2:$I$151,MATCH(INDEX(FTE_Allocation!$A$2:$A$201,$AB13),Workforce!$A$2:$A$151,0))),N(INDEX(FTE_Allocation!$I$2:$I$201,$AB13)))),1),""))) | AF13: =IF($Z13="C",IF(INDEX(Contracts!$I$2:$I$151,$AB13)="PREPAID",EDATE(DATE(YEAR(INDEX(Contracts!$J$2:$J$151,$AB13)),MONTH(INDEX(Contracts!$J$2:$J$151,$AB13)),1),IF(INDEX(Contracts!$N$2:$N$151,$AB13)="",12,INDEX(Contracts!$N$2:$N$151,$AB13))-1),IF(INDEX(Contracts!$I$2:$I$151,$AB13)="MONTHLY",IF(INDEX(Contracts!$K$2:$K$151,$AB13)="",2958101,INDEX(Contracts!$K$2:$K$151,$AB13)),0)),IF($Z13="A",EDATE(DATE(YEAR(INDEX(Fixed_Assets!$G$2:$G$201,$AB13)),MONTH(INDEX(Fixed_Assets!$G$2:$G$201,$AB13)),1),INDEX(Fixed_Assets!$J$2:$J$201,$AB13)-1),IF($Z13="F",MIN(IF(INDEX(Workforce!$J$2:$J$151,MATCH(INDEX(FTE_Allocation!$A$2:$A$201,$AB13),Workforce!$A$2:$A$151,0))="",2958101,INDEX(Workforce!$J$2:$J$151,MATCH(INDEX(FTE_Allocation!$A$2:$A$201,$AB13),Workforce!$A$2:$A$151,0))),IF(INDEX(FTE_Allocation!$J$2:$J$201,$AB13)="",2958101,INDEX(FTE_Allocation!$J$2:$J$201,$AB13))),""))) | AG13: =IF($Z13="C",IF(INDEX(Contracts!$I$2:$I$151,$AB13)="PREPAID",INDEX(Contracts!$M$2:$M$151,$AB13)/IF(INDEX(Contracts!$N$2:$N$151,$AB13)="",12,INDEX(Contracts!$N$2:$N$151,$AB13)),IF(INDEX(Contracts!$I$2:$I$151,$AB13)="MONTHLY",INDEX(Contracts!$M$2:$M$151,$AB13),0))*(1-N(INDEX(Contracts!$O$2:$O$151,$AB13))),IF($Z13="A",INDEX(Fixed_Assets!$H$2:$H$201,$AB13)/INDEX(Fixed_Assets!$J$2:$J$201,$AB13),IF($Z13="F",INDEX(Workforce!$F$2:$F$151,MATCH(INDEX(FTE_Allocation!$A$2:$A$201,$AB13),Workforce!$A$2:$A$151,0))*N(INDEX(FTE_Allocation!$F$2:$H$201,$AB13,$AC13)),"")))
... A1651: =IF($Z1651="","",$AD1651) | B1651: =IF($Z1651="C",INDEX(Contracts!$D$2:$D$151,$AB1651)&"",IF($Z1651="A",INDEX(Fixed_Assets!$C$2:$C$201,$AB1651)&"",IF($Z1651="F",INDEX(Workforce!$B$2:$B$151,MATCH(INDEX(FTE_Allocation!$A$2:$A$201,$AB1651),Workforce!$A$2:$A$151,0))&"",""))) | C1651: =IF($Z1651="C",INDEX(Contracts!$E$2:$E$151,$AB1651)&"",IF($Z1651="A",INDEX(Fixed_Assets!$D$2:$D$201,$AB1651)&"",IF($Z1651="F",INDEX(FTE_Allocation!$C$2:$C$201,$AB1651)&"",""))) | D1651: =IF($Z1651="C",INDEX(Contracts!$B$2:$B$151,$AB1651)&"",IF($Z1651="A",INDEX(Fixed_Assets!$B$2:$B$201,$AB1651)&"",IF($Z1651="F",INDEX(FTE_Allocation!$B$2:$B$201,$AB1651)&"",""))) | E1651: =IF($Z1651="C",INDEX(Contracts!$P$2:$P$151,$AB1651)&"",IF($Z1651="A",INDEX(Fixed_Assets!$K$2:$K$201,$AB1651)&"",IF($Z1651="F",IF(INDEX(FTE_Allocation!$D$2:$D$201,$AB1651)="PROJECT",IFERROR(INDEX(Projects!$D:$D,MATCH(INDEX(FTE_Allocation!$E$2:$E$201,$AB1651),Projects!$A:$A,0))&"","#PROJECT?"),INDEX(FTE_Allocation!$E$2:$E$201,$AB1651)&""),""))) | F1651: =IF($Z1651="C",INDEX(Contracts!$Q$2:$Q$151,$AB1651)&"",IF($Z1651="A",INDEX(Fixed_Assets!$L$2:$L$201,$AB1651)&"",IF($Z1651="F",INDEX(Workforce!$K$2:$K$151,MATCH(INDEX(FTE_Allocation!$A$2:$A$201,$AB1651),Workforce!$A$2:$A$151,0))&"",""))) | G1651: =IF($Z1651="C",INDEX(Contracts!$F$2:$F$151,$AB1651)&" / "&INDEX(Contracts!$G$2:$G$151,$AB1651),IF($Z1651="A",INDEX(Fixed_Assets!$E$2:$E$201,$AB1651)&"",IF($Z1651="F","Personnel "&INDEX(FTE_Allocation!$A$2:$A$201,$AB1651)&IF(INDEX(FTE_Allocation!$D$2:$D$201,$AB1651)="PROJECT"," ("&INDEX(FTE_Allocation!$E$2:$E$201,$AB1651)&")",""),""))) | H1651: =IF($Z1651="C","CONTRACT",IF($Z1651="A","ASSET",IF($Z1651="F","WORKFORCE",""))) | I1651: =IF($Z1651="C",INDEX(Contracts!$L$2:$L$151,$AB1651)&"",IF($Z1651="A",INDEX(Fixed_Assets!$I$2:$I$201,$AB1651)&"",IF($Z1651="F",INDEX(Workforce!$G$2:$G$151,MATCH(INDEX(FTE_Allocation!$A$2:$A$201,$AB1651),Workforce!$A$2:$A$151,0))&"",""))) | J1651: =IF($Z1651="","",IF(AND(DATE($AD1651,1,1)>=$AE1651,DATE($AD1651,1,1)<=$AF1651),ROUND($AG1651,2),0)) | K1651: =IF($Z1651="","",IF(AND(DATE($AD1651,2,1)>=$AE1651,DATE($AD1651,2,1)<=$AF1651),ROUND($AG1651,2),0)) | L1651: =IF($Z1651="","",IF(AND(DATE($AD1651,3,1)>=$AE1651,DATE($AD1651,3,1)<=$AF1651),ROUND($AG1651,2),0)) | M1651: =IF($Z1651="","",IF(AND(DATE($AD1651,4,1)>=$AE1651,DATE($AD1651,4,1)<=$AF1651),ROUND($AG1651,2),0)) | N1651: =IF($Z1651="","",IF(AND(DATE($AD1651,5,1)>=$AE1651,DATE($AD1651,5,1)<=$AF1651),ROUND($AG1651,2),0)) | O1651: =IF($Z1651="","",IF(AND(DATE($AD1651,6,1)>=$AE1651,DATE($AD1651,6,1)<=$AF1651),ROUND($AG1651,2),0)) | P1651: =IF($Z1651="","",IF(AND(DATE($AD1651,7,1)>=$AE1651,DATE($AD1651,7,1)<=$AF1651),ROUND($AG1651,2),0)) | Q1651: =IF($Z1651="","",IF(AND(DATE($AD1651,8,1)>=$AE1651,DATE($AD1651,8,1)<=$AF1651),ROUND($AG1651,2),0)) | R1651: =IF($Z1651="","",IF(AND(DATE($AD1651,9,1)>=$AE1651,DATE($AD1651,9,1)<=$AF1651),ROUND($AG1651,2),0)) | S1651: =IF($Z1651="","",IF(AND(DATE($AD1651,10,1)>=$AE1651,DATE($AD1651,10,1)<=$AF1651),ROUND($AG1651,2),0)) | T1651: =IF($Z1651="","",IF(AND(DATE($AD1651,11,1)>=$AE1651,DATE($AD1651,11,1)<=$AF1651),ROUND($AG1651,2),0)) | U1651: =IF($Z1651="","",IF(AND(DATE($AD1651,12,1)>=$AE1651,DATE($AD1651,12,1)<=$AF1651),ROUND($AG1651,2),0)) | V1651: =IF($Z1651="C","Generated from "&INDEX(Contracts!$A$2:$A$151,$AB1651),IF($Z1651="A","Generated from "&INDEX(Fixed_Assets!$A$2:$A$201,$AB1651),IF($Z1651="F","Generated from "&INDEX(FTE_Allocation!$A$2:$A$201,$AB1651),""))) | X1651: =IF($Z1651="","",SUM(J1651:U1651)) | Y1651: =ROW()-1 | Z1651: =IF($Y1651<=Settings!$B$4*3,"C",IF($Y1651<=(Settings!$B$4+Settings!$B$5)*3,"A",IF($Y1651<=(Settings!$B$4+Settings!$B$5+Settings!$B$6)*3,"F",""))) | AA1651: =IF($Z1651="C",$Y1651,IF($Z1651="A",$Y1651-Settings!$B$4*3,IF($Z1651="F",$Y1651-(Settings!$B$4+Settings!$B$5)*3,""))) | AB1651: =IF($Z1651="","",INT(($AA1651-1)/3)+1) | AC1651: =IF($Z1651="","",MOD($AA1651-1,3)+1) | AD1651: =IF($Z1651="","",Settings!$B$2+$AC1651-1) | AE1651: =IF($Z1651="C",DATE(YEAR(INDEX(Contracts!$J$2:$J$151,$AB1651)),MONTH(INDEX(Contracts!$J$2:$J$151,$AB1651)),1),IF($Z1651="A",DATE(YEAR(INDEX(Fixed_Assets!$G$2:$G$201,$AB1651)),MONTH(INDEX(Fixed_Assets!$G$2:$G$201,$AB1651)),1),IF($Z1651="F",DATE(YEAR(MAX(N(INDEX(Workforce!$I$2:$I$151,MATCH(INDEX(FTE_Allocation!$A$2:$A$201,$AB1651),Workforce!$A$2:$A$151,0))),N(INDEX(FTE_Allocation!$I$2:$I$201,$AB1651)))),MONTH(MAX(N(INDEX(Workforce!$I$2:$I$151,MATCH(INDEX(FTE_Allocation!$A$2:$A$201,$AB1651),Workforce!$A$2:$A$151,0))),N(INDEX(FTE_Allocation!$I$2:$I$201,$AB1651)))),1),""))) | AF1651: =IF($Z1651="C",IF(INDEX(Contracts!$I$2:$I$151,$AB1651)="PREPAID",EDATE(DATE(YEAR(INDEX(Contracts!$J$2:$J$151,$AB1651)),MONTH(INDEX(Contracts!$J$2:$J$151,$AB1651)),1),IF(INDEX(Contracts!$N$2:$N$151,$AB1651)="",12,INDEX(Contracts!$N$2:$N$151,$AB1651))-1),IF(INDEX(Contracts!$I$2:$I$151,$AB1651)="MONTHLY",IF(INDEX(Contracts!$K$2:$K$151,$AB1651)="",2958101,INDEX(Contracts!$K$2:$K$151,$AB1651)),0)),IF($Z1651="A",EDATE(DATE(YEAR(INDEX(Fixed_Assets!$G$2:$G$201,$AB1651)),MONTH(INDEX(Fixed_Assets!$G$2:$G$201,$AB1651)),1),INDEX(Fixed_Assets!$J$2:$J$201,$AB1651)-1),IF($Z1651="F",MIN(IF(INDEX(Workforce!$J$2:$J$151,MATCH(INDEX(FTE_Allocation!$A$2:$A$201,$AB1651),Workforce!$A$2:$A$151,0))="",2958101,INDEX(Workforce!$J$2:$J$151,MATCH(INDEX(FTE_Allocation!$A$2:$A$201,$AB1651),Workforce!$A$2:$A$151,0))),IF(INDEX(FTE_Allocation!$J$2:$J$201,$AB1651)="",2958101,INDEX(FTE_Allocation!$J$2:$J$201,$AB1651))),""))) | AG1651: =IF($Z1651="C",IF(INDEX(Contracts!$I$2:$I$151,$AB1651)="PREPAID",INDEX(Contracts!$M$2:$M$151,$AB1651)/IF(INDEX(Contracts!$N$2:$N$151,$AB1651)="",12,INDEX(Contracts!$N$2:$N$151,$AB1651)),IF(INDEX(Contracts!$I$2:$I$151,$AB1651)="MONTHLY",INDEX(Contracts!$M$2:$M$151,$AB1651),0))*(1-N(INDEX(Contracts!$O$2:$O$151,$AB1651))),IF($Z1651="A",INDEX(Fixed_Assets!$H$2:$H$201,$AB1651)/INDEX(Fixed_Assets!$J$2:$J$201,$AB1651),IF($Z1651="F",INDEX(Workforce!$F$2:$F$151,MATCH(INDEX(FTE_Allocation!$A$2:$A$201,$AB1651),Workforce!$A$2:$A$151,0))*N(INDEX(FTE_Allocation!$F$2:$H$201,$AB1651,$AC1651)),"")))

Sheet Settings
A1: setting | B1: value | C1: Description (EN) | D1: 説明（日本語）
A2: first_fiscal_year | B2: 2027 | C2: First fiscal year. Must match the first FTE column in FTE_Allocation. | D2: 初年度。FTE_Allocationの最初のFTE列と一致させる
A3: years | B3: 3 | C3: Number of years (fixed). | D3: 年数（固定）
A4: contracts_rows | B4: =COUNTA(Contracts!$A$2:$A$151) | C4: Rows entered in Contracts. | D4: Contractsの入力行数
A5: assets_rows | B5: =COUNTA(Fixed_Assets!$A$2:$A$201) | C5: Rows entered in Fixed_Assets. | D5: Fixed_Assetsの入力行数
A6: fte_rows | B6: =COUNTA(FTE_Allocation!$A$2:$A$201) | C6: Rows entered in FTE_Allocation. | D6: FTE_Allocationの入力行数

Sheet Cost_Centers
A1: cost_center_code | B1: cost_center_name | C1: region | D1: function | E1: sub_function | F1: active

Sheet Accounts
A1: account_key | B1: region | C1: local_account_code | D1: local_account_name | E1: global_coa_code | F1: global_coa_name | G1: mgmt_category

Sheet Projects
A1: project_code | B1: project_name | C1: region | D1: bearing_cost_center_code | E1: start_month | F1: end_month

Sheet Lists
A1: region | B1: currency | C1: contract_type | D1: employment_type | E1: allocation_type | F1: source_type | G1: rate_type | H1: yes_no
A2: JP | B2: JPY | C2: PREPAID | D2: EMPLOYEE | E2: COST_CENTER | F2: MANUAL | G2: BUDGET | H2: Y
A3: NA | B3: USD | C3: MONTHLY | D3: EXTERNAL | E3: PROJECT | F3: CONTRACT | H3: N
A4: EMEA | B4: EUR | C4: RATE_REF | F4: ASSET
B5: GBP | F5: WORKFORCE
