Workbook

Sheet バリューストリーム
A1: バリューストリーム（L1〜L4）
A2: 対象：希少疾患向け新規バイオ医薬品（抗体医薬）／米国基準（FDA・BLA・21 CFR）。1行1項目。L1〜L4列の●がその行のレベル。出口はL2、入力・出力情報・GxP区分・主な関与者はL4の項目。 入力情報・出力情報はVS定義の過程で得られる正本（直接入力する）。情報オブジェクトはこれを取りまとめて一覧化したもの。
A3: ID | B3: L1 | C3: L2 | D3: L3 | E3: L4 | F3: VS項目名 | G3: VSの定義 | H3: 出口（ゲート） | I3: 入力情報 | J3: 出力情報 | K3: GxP区分 | L3: 主な関与者（社内／外部）
A4: VS | B4: ● | F4: Target-to-Patient | G4: 希少疾患の標的探索から、FDA承認・上市を経て、少数の患者へ確実に届け、市販後に価値を最大化するまで
A5: 01 | C5: ● | F5: 創薬研究 | G5: 疾患の原因を理解して標的を定め、抗体を創出・最適化し、開発候補品を1つに絞り込む段階 | H5: 開発候補品（DC）決定
A6: 01-01 | D6: ● | F6: 標的探索・検証 | G6: 患者団体・専門医の知見と遺伝学的解析から病態を理解し、抗体で狙う標的を選んで検証する
A7: 01-01-01 | E7: ● | F7: ★患者団体・専門医との連携による疾患理解 | I7: — | J7: 疾患知見 | K7: 非GxP | L7: 研究・メディカル／患者団体、専門医
A8: 01-01-02 | E8: ● | F8: 疾患生物学の調査・標的仮説の立案 | I8: 疾患知見、遺伝子・オミクスデータ | J8: 標的 | K8: 非GxP | L8: 研究／アカデミア
A9: 01-01-03 | E9: ● | F9: ★遺伝学的原因の解析（単一遺伝子疾患等、患者ゲノム・検体データ） | I9: 疾患知見 | J9: 遺伝子・オミクスデータ、標的 | K9: 非GxP | L9: 研究（ゲノム解析）／アカデミア、専門医
A10: 01-01-04 | E10: ● | F10: 標的の機能検証（遺伝子ノックダウン、in vitro／in vivo） | I10: 標的 | J10: 研究実験データ | K10: 非GxP | L10: 研究／—
A11: 01-01-05 | E11: ● | F11: 抗体モダリティ適合性評価（細胞外・膜タンパクか、組織発現分布） | I11: 標的、研究実験データ | J11: 標的 | K11: 非GxP | L11: 研究／—
A12: 01-01-06 | E12: ● | F12: 標的選定（競合・知財〔FTO〕調査を含む） | I12: 標的、特許・独占期間 | J12: 標的、目標製品プロファイル（TPP）、開発判定記録、適応症 | K12: 非GxP | L12: 研究・知財／—
A13: 01-02 | D13: ● | F13: ヒット・リード創出 | G13: 抗原・評価系を整え、抗体を取得・選別して、目的の機能を持つリード抗体を得る
A14: 01-02-01 | E14: ● | F14: 抗原・評価系（アッセイ）の準備 | I14: 標的 | J14: 抗原・試薬、アッセイ（評価系） | K14: 非GxP | L14: 研究／試薬メーカー
A15: 01-02-02 | E15: ● | F15: 抗体取得（動物免疫／ヒト抗体産生動物／ディスプレイライブラリ） | I15: 抗原・試薬 | J15: 抗体分子 | K15: 非GxP | L15: 研究／受託研究機関（免疫・ライブラリ）
A16: 01-02-03 | E16: ● | F16: 一次スクリーニング（結合性） | I16: 抗体分子、アッセイ（評価系） | J16: 抗体分子、研究実験データ | K16: 非GxP | L16: 研究／—
A17: 01-02-04 | E17: ● | F17: 機能評価（中和活性、ADCC等のエフェクター機能） | I17: 抗体分子、アッセイ（評価系） | J17: 研究実験データ | K17: 非GxP | L17: 研究／—
A18: 01-02-05 | E18: ● | F18: リード抗体の選定 | I18: 研究実験データ | J18: 抗体分子、開発判定記録 | K18: 非GxP | L18: 研究／—
A19: 01-03 | D19: ● | F19: リード最適化 | G19: ヒト化・親和性成熟・Fc設計でリード抗体を改良し、開発適性・免疫原性リスク・薬効を評価する
A20: 01-03-01 | E20: ● | F20: ヒト化（動物由来抗体の場合） | I20: 抗体分子 | J20: 抗体分子 | K20: 非GxP | L20: 研究（抗体工学）／—
A21: 01-03-02 | E21: ● | F21: 親和性成熟 | I21: 抗体分子 | J21: 抗体分子 | K21: 非GxP | L21: 研究（抗体工学）／—
A22: 01-03-03 | E22: ● | F22: Fc設計（エフェクター機能・血中半減期の調整） | I22: 抗体分子 | J22: 抗体分子 | K22: 非GxP | L22: 研究（抗体工学）／—
A23: 01-03-04 | E23: ● | F23: 開発適性評価（凝集性・安定性・発現性・粘度） | I23: 抗体分子 | J23: 研究実験データ | K23: 非GxP | L23: 研究・CMC（分析）／—
A24: 01-03-05 | E24: ● | F24: 免疫原性リスクの予測（in silico／in vitro） | I24: 抗体分子 | J24: 免疫原性リスク評価 | K24: 非GxP | L24: 研究（トランスレーショナル）／—
A25: 01-03-06 | E25: ● | F25: ★疾患モデルの構築・薬効評価（遺伝子改変動物・患者由来細胞） | I25: 抗体分子、遺伝子・オミクスデータ | J25: 疾患モデル、in vivo薬効データ | K25: 非GxP | L25: 研究（薬理）／受託研究機関
A26: 01-04 | D26: ● | F26: 開発候補品選定 | G26: TPPと照らして候補を比較し、患者数の確認と特許出願を経て、開発候補品を決定する
A27: 01-04-01 | E27: ● | F27: 目標製品プロファイル（TPP）との照合・候補比較 | I27: 目標製品プロファイル（TPP）、研究実験データ、in vivo薬効データ、免疫原性リスク評価 | J27: 目標製品プロファイル（TPP）、開発判定記録 | K27: 非GxP | L27: 研究・開発企画／—
A28: 01-04-02 | E28: ● | F28: ★患者数・疫学の確認（米国で20万人未満の根拠） | I28: 疾患知見、適応症 | J28: 疫学データ | K28: 非GxP | L28: メディカル（疫学）／データ提供事業者
A29: 01-04-03 | E29: ● | F29: 物質特許の出願 | I29: 抗体分子 | J29: 特許・独占期間 | K29: 非GxP | L29: 知財／特許事務所、USPTO
A30: 01-04-04 | E30: ● | F30: 開発移行判定会議 | I30: 開発判定記録、目標製品プロファイル（TPP）、疫学データ、特許・独占期間 | J30: 開発判定記録、製品マスタ | K30: 非GxP | L30: 経営（ポートフォリオ委員会）／—
A31: 02 | C31: ● | F31: 非臨床開発 | G31: 開発候補品をヒトに初めて投与できるよう、薬理・体内動態・安全性を非臨床で評価し、INDを発効させる段階 | H31: IND発効（臨床試験の開始が可能）
A32: 02-01 | D32: ● | F32: 非臨床薬理 | G32: 作用機序と用量反応を明らかにし、安全性薬理を評価する
A33: 02-01-01 | E33: ● | F33: 作用機序（MoA）の解明 | I33: 抗体分子、研究実験データ | J33: 非臨床試験報告書 | K33: 非GxP | L33: 研究（トランスレーショナル）／—
A34: 02-01-02 | E34: ● | F34: 薬効薬理試験（用量反応） | I34: 疾患モデル | J34: 非臨床試験データ、非臨床試験報告書 | K34: 非GxP | L34: 非臨床（薬理）／—
A35: 02-01-03 | E35: ● | F35: 安全性薬理評価（毒性試験への組込みが一般的） | I35: 非臨床試験計画 | J35: 非臨床試験データ | K35: GLP | L35: 非臨床（安全性）／受託試験機関
A36: 02-02 | D36: ● | F36: 薬物動態・免疫原性評価 | G36: PK・ADAの測定法を確立し、動物での体内動態・免疫原性を評価して、ヒトPKを予測する
A37: 02-02-01 | E37: ● | F37: PK／TK測定法（リガンド結合法）の確立 | I37: 抗体分子 | J37: 生体試料分析法 | K37: GLP | L37: 非臨床（バイオアナリシス）／受託試験機関
A38: 02-02-02 | E38: ● | F38: 動物PK試験 | I38: 非臨床試験計画、生体試料分析法 | J38: 非臨床試験データ | K38: 非GxP | L38: 非臨床（薬物動態）／受託試験機関
A39: 02-02-03 | E39: ● | F39: 抗薬物抗体（ADA）測定法の確立・動物での評価 | I39: 生体試料分析法 | J39: 生体試料分析法、非臨床試験データ | K39: GLP | L39: 非臨床（バイオアナリシス）／受託試験機関
A40: 02-02-04 | E40: ● | F40: ヒトPKの予測 | I40: 非臨床試験データ | J40: PK/PDモデル・解析結果 | K40: 非GxP | L40: 臨床薬理（ファーマコメトリクス）／—
A41: 02-03 | D41: ● | F41: 安全性評価 | G41: 関連動物種を選び、GLP毒性試験などでヒト投与の安全性を評価する
A42: 02-03-01 | E42: ● | F42: 関連動物種の選定（交差反応性・薬理活性の確認） | I42: 抗体分子、研究実験データ | J42: 非臨床試験報告書 | K42: 非GxP | L42: 非臨床（安全性）／—
A43: 02-03-02 | E43: ● | F43: 組織交差反応性試験（ヒト・動物組織） | I43: 非臨床試験計画 | J43: 非臨床試験データ、非臨床試験報告書 | K43: GLP | L43: 非臨床（安全性）／受託試験機関
A44: 02-03-03 | E44: ● | F44: GLP反復投与毒性試験 | I44: 非臨床試験計画、ロット | J44: 非臨床試験データ、非臨床試験報告書 | K44: GLP | L44: 非臨床（安全性）／受託試験機関
A45: 02-03-04 | E45: ● | F45: サイトカイン放出評価（免疫賦活作用がある場合） | I45: 抗体分子 | J45: 非臨床試験データ | K45: 非GxP | L45: 非臨床（安全性）／—
A46: 02-03-05 | E46: ● | F46: 開発段階に応じた追加試験の計画（生殖発生毒性等） | I46: 非臨床試験報告書 | J46: 非臨床試験計画 | K46: 非GxP | L46: 非臨床（安全性）／—
A47: 02-04 | D47: ● | F47: 初回ヒト投与量の設定・IND申請 | G47: 初回投与量を設定し、IB・指定申請を含めてINDを提出し、30日の待機期間を経て治験を開始できる状態にする
A48: 02-04-01 | E48: ● | F48: 初回投与量の設定（NOAEL／MABEL） | I48: 非臨床試験報告書、PK/PDモデル・解析結果 | J48: PK/PDモデル・解析結果 | K48: 非GxP | L48: 臨床薬理・非臨床／—
A49: 02-04-02 | E49: ● | F49: 治験薬概要書（IB）の作成 | I49: 非臨床試験報告書、規格 | J49: 治験薬概要書（IB） | K49: GCP | L49: 臨床開発・非臨床／—
A50: 02-04-03 | E50: ● | F50: Pre-INDミーティング（FDA） | I50: 非臨床試験報告書、治験薬概要書（IB） | J50: 当局コミュニケーション記録 | K50: 薬事 | L50: 薬事／FDA
A51: 02-04-04 | E51: ● | F51: ★Orphan Drug指定の申請（FDA OOPD。税額控除・ユーザーフィー免除・7年独占の前提） | I51: 疫学データ、非臨床試験報告書、適応症 | J51: 指定・インセンティブ | K51: 薬事 | L51: 薬事／FDA（OOPD）
A52: 02-04-05 | E52: ● | F52: ★希少小児疾患指定の申請（該当する場合。承認時の優先審査バウチャーの前提） | I52: 疫学データ、非臨床試験報告書、適応症 | J52: 指定・インセンティブ | K52: 薬事 | L52: 薬事／FDA（OOPD）
A53: 02-04-06 | E53: ● | F53: IND申請（Form FDA 1571、GLP試験報告書を含む） | I53: 非臨床試験報告書、治験実施計画書、治験薬概要書（IB）、規格、CMC技術報告書 | J53: IND | K53: 薬事 | L53: 薬事・臨床開発・CMC／FDA
A54: 02-04-07 | E54: ● | F54: 30日待機期間（クリニカルホールドの有無の確認） | I54: IND | J54: 当局コミュニケーション記録、開発判定記録 | K54: 薬事 | L54: 薬事／FDA
A55: 03 | C55: ● | F55: CMC開発（臨床と並行） | G55: 候補品を安定して生産し品質を保証できる細胞株・製造プロセス・製剤・分析法を確立し、治験薬を供給し、商用プロセスをバリデーションする段階 | H55: プロセスバリデーション完了
A56: 03-01 | D56: ● | F56: 細胞株構築・セルバンク | G56: 生産細胞株を構築し、MCB／WCBを作製して、その特性と安全性を確認する
A57: 03-01-01 | E57: ● | F57: 発現ベクターの設計・構築 | I57: 抗体分子 | J57: 発現ベクター・細胞株 | K57: 非GxP | L57: CMC（細胞株開発）／—
A58: 03-01-02 | E58: ● | F58: 宿主細胞（CHO等）への導入・クローン選択 | I58: 発現ベクター・細胞株 | J58: 発現ベクター・細胞株 | K58: 非GxP | L58: CMC（細胞株開発）／CDMO
A59: 03-01-03 | E59: ● | F59: クローン評価（生産性・品質・安定性、単一クローン由来の確認） | I59: 発現ベクター・細胞株 | J59: 発現ベクター・細胞株、プロセス開発データ | K59: 非GxP | L59: CMC（細胞株開発）／CDMO
A60: 03-01-04 | E60: ● | F60: マスター／ワーキングセルバンク（MCB／WCB）の作製 | I60: 発現ベクター・細胞株 | J60: セルバンク、バッチ記録 | K60: GMP | L60: CMC・製造／CDMO
A61: 03-01-05 | E61: ● | F61: セルバンクの特性解析・ウイルス等安全性試験 | I61: セルバンク | J61: CMC技術報告書 | K61: GMP | L61: QC／受託試験機関
A62: 03-02 | D62: ● | F62: 原薬プロセス開発 | G62: 培養・精製・ウイルス除去の工程を開発し、治験薬の製造スケールに拡大する
A63: 03-02-01 | E63: ● | F63: 培養プロセス開発（培地・流加条件） | I63: 発現ベクター・細胞株 | J63: プロセス定義、プロセス開発データ | K63: 非GxP | L63: CMC（プロセス開発）／CDMO
A64: 03-02-02 | E64: ● | F64: ハーベスト・精製プロセス開発（プロテインA、イオン交換等） | I64: プロセス定義 | J64: プロセス定義、プロセス開発データ | K64: 非GxP | L64: CMC（プロセス開発）／CDMO
A65: 03-02-03 | E65: ● | F65: ウイルスクリアランス評価（除去・不活化工程） | I65: プロセス定義 | J65: CMC技術報告書 | K65: 非GxP | L65: CMC（プロセス開発）／受託試験機関
A66: 03-02-04 | E66: ● | F66: 治験薬スケールへのスケールアップ | I66: プロセス定義、セルバンク | J66: プロセス定義、マスターバッチレコード | K66: GMP | L66: CMC・製造／CDMO
A67: 03-03 | D67: ● | F67: 製剤開発 | G67: 処方・剤形・容器・投与デバイスを開発し、製剤の安定性を評価する
A68: 03-03-01 | E68: ● | F68: 処方設計（緩衝液・安定化剤、高濃度化） | I68: 研究実験データ | J68: 処方・製剤仕様 | K68: 非GxP | L68: CMC（製剤開発）／—
A69: 03-03-02 | E69: ● | F69: 剤形・容器の選定（バイアル／プレフィルドシリンジ等） | I69: 処方・製剤仕様 | J69: 処方・製剤仕様 | K69: 非GxP | L69: CMC（製剤開発）／容器メーカー
A70: 03-03-03 | E70: ● | F70: 製剤の安定性評価（加速・苛酷・長期） | I70: 処方・製剤仕様、分析法 | J70: 安定性データ | K70: 非GxP | L70: CMC（製剤開発）／—
A71: 03-03-04 | E71: ● | F71: 投与デバイスの開発（必要な場合） | I71: 処方・製剤仕様 | J71: 処方・製剤仕様 | K71: QMSR | L71: CMC（製剤開発）／デバイスメーカー
A72: 03-04 | D72: ● | F72: 分析法開発・特性解析 | G72: 重要品質特性（CQA）を特定し、分析法・標準物質・規格を確立する
A73: 03-04-01 | E73: ● | F73: 重要品質特性（CQA）の特定 | I73: 抗体分子、プロセス開発データ | J73: 重要品質特性（CQA） | K73: 非GxP | L73: CMC（分析開発）／—
A74: 03-04-02 | E74: ● | F74: 分析法の開発（構造・純度・糖鎖・電荷・生物活性） | I74: 重要品質特性（CQA） | J74: 分析法 | K74: 非GxP | L74: CMC（分析開発）／—
A75: 03-04-03 | E75: ● | F75: 分析法バリデーション | I75: 分析法 | J75: 分析法、CMC技術報告書 | K75: GMP | L75: CMC（分析開発）・QC／—
A76: 03-04-04 | E76: ● | F76: 標準物質の確立 | I76: ロット | J76: 標準物質 | K76: GMP | L76: CMC（分析開発）・QC／—
A77: 03-04-05 | E77: ● | F77: 規格の設定 | I77: 重要品質特性（CQA）、分析法、試験成績 | J77: 規格 | K77: GMP | L77: CMC（分析開発）・QA／—
A78: 03-05 | D78: ● | F78: 治験薬GMP製造・供給 | G78: 治験薬をGMPで製造・試験して施設へ供給する。製法を変更したときは同等性を評価する
A79: 03-05-01 | E79: ● | F79: 治験薬（原薬・製剤）の製造 | I79: マスターバッチレコード、セルバンク、原材料・資材 | J79: バッチ記録、ロット | K79: GMP | L79: CMC・製造／CDMO
A80: 03-05-02 | E80: ● | F80: 品質試験・出荷判定 | I80: ロット、規格、分析法、標準物質 | J80: 試験成績、出荷判定記録 | K80: GMP | L80: QC・QA／CDMO
A81: 03-05-03 | E81: ● | F81: 安定性モニタリング | I81: ロット | J81: 安定性データ | K81: GMP | L81: QC／CDMO
A82: 03-05-04 | E82: ● | F82: 包装・表示・実施医療機関への供給 | I82: ロット、治験実施計画書、包装表示（アートワーク） | J82: 治験薬供給記録、包装表示（アートワーク） | K82: GMP・GCP | L82: CMC（臨床供給）／包装業者、実施医療機関
A83: 03-05-05 | E83: ● | F83: 製法変更時の同等性／同質性評価 | I83: プロセス定義、試験成績、安定性データ | J83: CMC技術報告書 | K83: GMP | L83: CMC（分析開発）・QA／—
A84: 03-06 | D84: ● | F84: 後期プロセス開発・スケールアップ・技術移転 | G84: 工程を特性解析して管理戦略を確立し、商用の製造規模を定めて製造所へ移転する
A85: 03-06-01 | E85: ● | F85: プロセス特性解析（リスク評価・実験計画法） | I85: プロセス定義、プロセス開発データ、重要品質特性（CQA） | J85: プロセス定義、プロセス開発データ | K85: 非GxP | L85: CMC（プロセス開発）／CDMO
A86: 03-06-02 | E86: ● | F86: 管理戦略の確立 | I86: 重要品質特性（CQA）、プロセス定義、規格 | J86: 管理戦略 | K86: GMP | L86: CMC・QA／—
A87: 03-06-03 | E87: ● | F87: ★需要に見合う製造規模の設定（小ロット、臨床と同規模のまま商用化する場合あり） | I87: 疫学データ、プロセス定義 | J87: プロセス定義 | K87: 非GxP | L87: CMC・SCM／CDMO
A88: 03-06-04 | E88: ● | F88: 商用製造所への技術移転 | I88: プロセス定義、管理戦略、分析法 | J88: マスターバッチレコード、CMC技術報告書 | K88: GMP | L88: CMC・製造／CDMO（商用製造所）
A89: 03-07 | D89: ● | F89: プロセスバリデーション（PPQ） | G89: 設備・洗浄バリデーションとPPQにより、商用プロセスが一貫した品質で製造できることを示す
A90: 03-07-01 | E90: ● | F90: 設備・洗浄バリデーション | I90: — | J90: バリデーション計画・報告 | K90: GMP | L90: 製造（エンジニアリング）・QA／CDMO
A91: 03-07-02 | E91: ● | F91: プロセスバリデーション計画の策定 | I91: 管理戦略、マスターバッチレコード | J91: バリデーション計画・報告 | K91: GMP | L91: 製造・QA／CDMO
A92: 03-07-03 | E92: ● | F92: PPQバッチの製造（複数ロット） | I92: バリデーション計画・報告、マスターバッチレコード、セルバンク、原材料・資材 | J92: バッチ記録、ロット、工程データ、試験成績 | K92: GMP | L92: 製造・QC／CDMO
A93: 03-07-04 | E93: ● | F93: 工程性能の評価・報告 | I93: バッチ記録、工程データ、試験成績 | J93: バリデーション計画・報告 | K93: GMP | L93: 製造・QA／CDMO
A94: 04 | C94: ● | F94: 臨床開発 | G94: 自然歴研究で疾患を把握し、患者での臨床試験を通じて、安全性・有効性のエビデンスを確立する段階 | H94: 申請に足る臨床データ
A95: 04-01 | D95: ● | F95: ★自然歴研究・患者特定 | G95: 疾患の自然経過・患者レジストリ・評価指標を整え、候補患者を特定して、臨床試験の基盤をつくる
A96: 04-01-01 | E96: ● | F96: ★自然歴研究の実施（外部対照・評価項目設定の基礎） | I96: 疾患知見、患者レジストリデータ、患者・被験者 | J96: 自然歴データ、臨床試験 | K96: 非GxP | L96: メディカル（疫学）／専門医、アカデミア、患者団体
A97: 04-01-02 | E97: ● | F97: ★患者レジストリの構築（患者団体と連携） | I97: 疾患知見 | J97: 患者レジストリデータ、患者・被験者 | K97: 非GxP | L97: メディカル／患者団体、レジストリ運営者
A98: 04-01-03 | E98: ● | F98: ★診断・患者特定の支援（遺伝子検査プログラム等） | I98: 患者レジストリデータ、遺伝子・オミクスデータ | J98: 候補患者情報、患者・被験者 | K98: 非GxP | L98: メディカル／遺伝子検査機関、専門医
A99: 04-01-04 | E99: ● | F99: ★臨床評価指標（COA）・バイオマーカーの開発・検証 | I99: 自然歴データ、疾患知見 | J99: 臨床評価指標・バイオマーカー定義 | K99: 非GxP | L99: 臨床開発・研究（トランスレーショナル）／患者団体、FDA
A100: 04-02 | D100: ● | F100: ★第I/II相（患者での安全性・PK・PoC） | G100: 患者を対象に安全性・PK・PoCを確認し、ピボタル試験のデザインについてFDAと合意する
...

Sheet ケイパビリティマップ
A1: ビジネス・ケイパビリティマップ（L1〜L3）
A2: 対象：希少疾患向け新規バイオ医薬品（抗体医薬）／米国基準（FDA・BLA・21 CFR）。1行1項目。L1〜L3列の●がその行のレベル。区分はL1、範囲・アウトカムはL3の項目。★＝希少疾患に限定したことで追加・強調した能力。
A3: ID | B3: L1 | C3: L2 | D3: L3 | E3: ケイパビリティ名 | F3: ケイパビリティの定義 | G3: 区分 | H3: 範囲（含む） | I3: 範囲（含まない） | J3: アウトカム
A4: C01 | B4: ● | E4: 戦略・ガバナンス | F4: 研究開発の方向性・資源配分と、知財・外部パートナーを通じた事業基盤を統制する能力 | G4: 戦略
A5: C01-01 | C5: ● | E5: 研究開発ポートフォリオ管理 | F5: パイプラインの価値・リスクを評価し、資源配分と段階移行を判断する
A6: C01-01-01 | D6: ● | E6: パイプライン評価・優先順位付け | F6: 開発品の価値・成功確率・必要資源を評価し、優先順位と資源配分を決める | H6: 価値評価（rNPV等）、成功確率の推定、資源配分 | I6: 価格戦略・設定（C11-01-01） | J6: 資源が優先度に沿って配分されたパイプライン
A7: C01-01-02 | D7: ● | E7: 段階移行判定 | F7: 開発候補品決定・Go／No-Goなど、段階移行の判断基準を定め、判断を下す | H7: 判断基準の設定、判定会議の運営、判断記録 | I7: 科学的評価そのもの（各ケイパビリティが担う） | J7: 根拠が明確で一貫した移行判断
A8: C01-01-03 | D8: ● | E8: 目標製品プロファイル（TPP）管理 | F8: 開発品が目指す製品像（適応・用法・有効性・安全性・剤形）を設定し、更新する | H8: TPPの設定・改訂、機能横断での共有 | I8: 試験デザイン★（C05-01-02） | J8: 全機能で共有された、根拠のある製品像
A9: C01-01-04 | D9: ● | E9: 開発プロジェクト管理 | F9: 開発品ごとに、機能横断の統合計画・進捗・リスクを管理する | H9: 統合スケジュール、課題・リスク管理、部門間調整 | I9: モニタリング・施設管理（C05-04-02） | J9: 計画どおりに進む、見通しの立つ開発
A10: C01-02 | C10: ● | E10: 知財・独占期間管理 | F10: 特許と規制上の独占期間により、製品の排他性を確保・維持する
A11: C01-02-01 | D11: ● | E11: 特許戦略・調査 | F11: 物質・製法・用途の特許の出願・権利化と、他者特許の調査（FTO）を行う | H11: 特許出願・権利化、FTO調査、競合知財の監視 | I11: 規制上の独占期間管理（C01-02-02） | J11: 事業化の自由度と排他権の確保
A12: C01-02-02 | D12: ● | E12: 規制上の独占期間管理 | F12: Orphan 7年・生物製剤12年の独占期間の範囲を確認し、維持する | H12: 独占範囲の確認、Purple Bookの掲載情報の確認 | I12: 指定制度・インセンティブ管理★（C06-01-03） | J12: 最大限に確保された独占期間
A13: C01-02-03 | D13: ● | E13: バイオシミラー対応 | F13: 後続のバイオシミラー申請者との特許情報交換（BPCIA）と紛争に対応する | H13: 特許情報の交換手続き、訴訟対応 | I13: 特許戦略・調査（C01-02-01） | J13: 後続品参入に対する権利の適切な行使
A14: C01-03 | C14: ● | E14: 外部パートナー管理 | F14: CRO・CDMO・受託機関・提携先を選び、契約し、委託業務を監督する
A15: C01-03-01 | D15: ● | E15: パートナー選定・評価 | F15: 委託先・提携先の能力・リスクを評価し、選定する | H15: 候補の調査・評価、選定判断 | I15: 内部監査・パートナー監査（C08-04-02） | J15: 目的に合った委託先・提携先
A16: C01-03-02 | D16: ● | E16: 委託業務の契約・監督 | F16: 業務契約・品質取決めを結び、委託業務の実績・課題を管理する（責任はスポンサーに残る） | H16: 業務契約、品質取決め、実績・KPIの管理 | I16: 保険者・PBM契約（C11-01-03）、流通ネットワーク設計・パートナー管理（C12-02-01） | J16: 委託しても品質・期限が守られる状態
A17: C01-03-03 | D17: ● | E17: 提携・ライセンス管理 | F17: 共同開発・導入・導出の契約と、提携関係を管理する | H17: 提携交渉・契約、提携先との共同運営 | I17: — | J17: 価値を生む提携関係
A18: C02 | B18: ● | E18: 研究（創薬） | F18: 疾患を理解し、標的に対する抗体を創出・最適化して開発候補品を生み出す能力 | G18: コア
A19: C02-01 | C19: ● | E19: 疾患・標的研究★ | F19: 遺伝学的原因を起点に疾患を理解し、抗体で狙う標的を探索・検証する
A20: C02-01-01 | D20: ● | E20: 病態・遺伝学的原因の解析★ | F20: 患者ゲノム・検体データや疾患生物学から、病態と原因遺伝子・経路を明らかにする | H20: 遺伝学的解析、病態メカニズムの解明、標的仮説の立案 | I20: 患者団体との協働★（C10-01-01） | J20: 根拠のある標的仮説
A21: C02-01-02 | D21: ● | E21: 標的検証 | F21: 標的の関与を実験的に検証する | H21: 遺伝子ノックダウン等の機能検証、in vitro／in vivoでの検証 | I21: in vitro／in vivo薬効評価（C02-04-02） | J21: 検証された標的
A22: C02-01-03 | D22: ● | E22: モダリティ適合性評価 | F22: 標的が抗体で狙えるか（細胞外・膜タンパクか、発現分布など）を評価する | H22: 標的の局在・発現分布の評価、モダリティ選択 | I22: — | J22: 抗体で狙うことの妥当性
A23: C02-02 | C23: ● | E23: 抗体創出 | F23: 抗原・評価系を整え、抗体を取得して選別する
A24: C02-02-01 | D24: ● | E24: 抗原・アッセイ開発 | F24: 抗体取得・評価に使う抗原と評価系（アッセイ）をつくる | H24: 抗原タンパク・細胞の調製、結合・機能アッセイの構築 | I24: 分析法開発・バリデーション（C04-04-02） | J24: 信頼できる抗原と評価系
A25: C02-02-02 | D25: ● | E25: 抗体取得 | F25: 動物免疫・ヒト抗体産生動物・ディスプレイライブラリから抗体を得る | H25: 免疫、ライブラリ構築・パニング、配列取得 | I25: — | J25: 多様な抗体クローン群
A26: C02-02-03 | D26: ● | E26: スクリーニング・機能評価 | F26: 抗体を結合性・機能（中和・エフェクター機能）で選別する | H26: 一次スクリーニング、機能評価、ヒット・リードの選定 | I26: — | J26: 目的の機能を持つリード抗体
A27: C02-03 | C27: ● | E27: 抗体エンジニアリング | F27: 抗体分子を改変し、医薬品として最適化する
A28: C02-03-01 | D28: ● | E28: ヒト化 | F28: 動物由来抗体をヒト型に改変し、免疫原性を下げる | H28: CDR移植、フレームワーク最適化 | I28: — | J28: ヒトに投与できる抗体配列
A29: C02-03-02 | D29: ● | E29: 親和性成熟 | F29: 標的への結合力・特異性を高める | H29: 変異導入・選択 | I29: — | J29: 最適な結合特性
A30: C02-03-03 | D30: ● | E30: Fcエンジニアリング | F30: Fc領域を設計し、エフェクター機能・血中半減期を調整する | H30: エフェクター機能の増強・低減、半減期延長 | I30: — | J30: 目的に合った作用・体内動態
A31: C02-04 | C31: ● | E31: 疾患モデル・薬効評価 | F31: 疾患モデルを構築し、候補抗体の薬効を評価する
A32: C02-04-01 | D32: ● | E32: 疾患モデル構築★ | F32: 遺伝子改変動物・患者由来細胞などで疾患を再現するモデルをつくる | H32: モデルの作製・特性評価・維持 | I32: — | J32: 疾患を反映した評価系
A33: C02-04-02 | D33: ● | E33: in vitro／in vivo薬効評価 | F33: 候補選定のために、疾患モデルで候補抗体の薬効を比較評価する | H33: 候補間の薬効比較 | I33: 作用機序・薬効薬理評価（C03-01-01） | J33: 候補選定の根拠となる薬効データ
A34: C02-05 | C34: ● | E34: 開発適性・免疫原性リスク評価 | F34: 医薬品として開発・製造できるか、免疫原性のリスクはどうかを早期に評価する
A35: C02-05-01 | D35: ● | E35: 開発適性評価 | F35: 凝集性・安定性・発現性・粘度など、開発・製造上の適性を評価する | H35: 開発適性の各種評価、配列上のリスク部位の特定 | I35: 処方開発（C04-03-01） | J35: 開発・製造で問題が起きにくい候補
A36: C02-05-02 | D36: ● | E36: 免疫原性リスク予測 | F36: in silico／in vitroで免疫原性（抗薬物抗体の発生）のリスクを予測する | H36: T細胞エピトープ予測、in vitro評価 | I36: 測定法開発・バリデーション（C03-03-01） | J36: 免疫原性リスクの低い候補
A37: C03 | B37: ● | E37: 非臨床・臨床薬理 | F37: ヒトへの投与を可能にし、用法用量を裏づける薬理・安全性・体内動態の知見を生み出す能力 | G37: コア
A38: C03-01 | C38: ● | E38: 非臨床薬理評価 | F38: 作用機序と薬効・安全性薬理を明らかにする
A39: C03-01-01 | D39: ● | E39: 作用機序・薬効薬理評価 | F39: 作用機序を明らかにし、用量反応を含む薬効薬理を評価する | H39: 作用機序解析、用量反応試験 | I39: in vitro／in vivo薬効評価（C02-04-02） | J39: 臨床での作用・用量を裏づける薬理データ
A40: C03-01-02 | D40: ● | E40: 安全性薬理評価 | F40: 主要な生理機能への影響を評価する（毒性試験に組み込むことが多い） | H40: 心血管・呼吸・中枢神経系への影響評価 | I40: — | J40: 安全性薬理の知見
A41: C03-02 | C41: ● | E41: 非臨床安全性評価 | F41: 抗体医薬の特性に合わせて、ヒト投与の安全性を非臨床で評価する
A42: C03-02-01 | D42: ● | E42: 毒性試験戦略・動物種選定 | F42: 抗体医薬の指針に沿い、関連動物種と必要な試験を決める | H42: 関連動物種の選定、試験パッケージの設計（生殖発生毒性の要否を含む） | I42: — | J42: 妥当で過不足のない非臨床安全性パッケージ
A43: C03-02-02 | D43: ● | E43: GLP毒性試験 | F43: GLPに従い、反復投与毒性などの試験を実施・監督する | H43: 試験計画、受託試験機関での実施の監督、報告書 | I43: — | J43: 信頼できる毒性評価
A44: C03-02-03 | D44: ● | E44: in vitro安全性評価 | F44: 組織交差反応性・サイトカイン放出など、in vitroで安全性を評価する | H44: 組織交差反応性試験、サイトカイン放出評価 | I44: — | J44: 想定外の結合・免疫反応のリスク把握
A45: C03-03 | C45: ● | E45: バイオアナリシス | F45: PK・抗薬物抗体（ADA）・バイオマーカーを測定する（非臨床から臨床まで）
A46: C03-03-01 | D46: ● | E46: 測定法開発・バリデーション | F46: PK・ADA・中和抗体・バイオマーカーの測定法をつくり、バリデーションする | H46: リガンド結合法の開発、測定法バリデーション | I46: 分析法開発・バリデーション（C04-04-02） | J46: 規制要件を満たす測定法
A47: C03-03-02 | D47: ● | E47: 検体測定 | F47: 非臨床・臨床の検体を測定し、結果を報告する | H47: 検体受領・測定・結果報告、中央検査機関の管理 | I47: — | J47: 信頼できる測定データ
A48: C03-04 | C48: ● | E48: 臨床薬理・ファーマコメトリクス | F48: 体内動態をモデル化し、投与量と用法用量の根拠を構築する
A49: C03-04-01 | D49: ● | E49: ヒトPK予測・初回投与量設定 | F49: 非臨床データからヒトPKを予測し、初回投与量（NOAEL／MABEL）を設定する | H49: PK予測、初回投与量の根拠 | I49: — | J49: 安全な初回投与量
A50: C03-04-02 | D50: ● | E50: 母集団PK・曝露反応解析 | F50: 臨床データで母集団PK・曝露反応を解析し、用法用量の根拠を構築する | H50: モデル構築・シミュレーション、用法用量の根拠 | I50: 統計解析（C05-05-02） | J50: 根拠ある用法用量
A51: C04 | B51: ● | E51: CMC開発 | F51: 生細胞で抗体を安定して生産し、品質を保証できる製造プロセス・製剤・分析法を開発する能力 | G51: コア
A52: C04-01 | C52: ● | E52: 細胞株開発・セルバンク管理 | F52: 生産細胞株を構築し、マスター／ワーキングセルバンクを作製・維持する
A53: C04-01-01 | D53: ● | E53: 細胞株構築・クローン選択 | F53: 発現ベクターを構築し、生産性・品質の高い単一クローン由来の細胞株を選ぶ | H53: ベクター設計、宿主細胞への導入、クローン評価、単一クローン性の証明 | I53: — | J53: 高生産で安定な生産細胞株
A54: C04-01-02 | D54: ● | E54: セルバンク作製・管理 | F54: MCB／WCBを作製し、特性解析・安全性試験を行い、保管・使用を管理する | H54: セルバンク作製、特性解析・ウイルス等安全性試験、保管・払出し | I54: — | J54: 長期に供給可能で安全なセルバンク
A55: C04-02 | C55: ● | E55: 原薬プロセス開発 | F55: 培養・精製の工程を設計し、ウイルス安全性と管理戦略を確立する
A56: C04-02-01 | D56: ● | E56: 培養プロセス開発 | F56: 培地・流加条件など培養工程を開発する | H56: 培養条件の最適化、小スケール評価 | I56: — | J56: 生産性・品質が安定した培養工程
A57: C04-02-02 | D57: ● | E57: 精製プロセス開発 | F57: ハーベストから精製（プロテインA、イオン交換等）までの工程を開発する | H57: 精製工程の設計・最適化 | I57: — | J57: 不純物を除去できる精製工程
A58: C04-02-03 | D58: ● | E58: ウイルス安全性評価 | F58: ウイルスの除去・不活化工程を評価し、ウイルス安全性を保証する | H58: ウイルスクリアランス試験 | I58: セルバンク作製・管理（C04-01-02） | J58: ウイルス安全性の保証
A59: C04-02-04 | D59: ● | E59: プロセス特性解析・管理戦略 | F59: リスク評価・実験計画法で工程を特性解析し、管理戦略を確立する | H59: パラメータの許容範囲、管理戦略 | I59: — | J59: 品質を一貫して保証できる工程
A60: C04-03 | C60: ● | E60: 製剤・デバイス開発 | F60: 処方・容器・投与デバイスを設計する
A61: C04-03-01 | D61: ● | E61: 処方開発 | F61: 緩衝液・安定化剤などの処方を設計する（高濃度化を含む） | H61: 処方設計、処方の安定性評価 | I61: 開発適性評価（C02-05-01） | J61: 安定で投与しやすい製剤
A62: C04-03-02 | D62: ● | E62: 容器・包装設計 | F62: バイアル・プレフィルドシリンジなどの一次容器と包装を設計する | H62: 容器選定、容器完全性の評価 | I62: — | J62: 品質を守る容器・包装
A63: C04-03-03 | D63: ● | E63: 投与デバイス開発 | F63: コンビネーション製品として投与デバイスを設計する（設計管理） | H63: デバイス設計、ヒューマンファクター評価 | I63: — | J63: 患者が安全に使えるデバイス
A64: C04-04 | C64: ● | E64: 分析法開発・品質特性評価 | F64: 品質特性を評価し、分析法・規格を定め、製法変更時の同等性を評価する
A65: C04-04-01 | D65: ● | E65: 品質特性評価 | F65: 構造・糖鎖・電荷・生物活性などの品質特性を解析し、CQAを特定する | H65: 特性解析、CQAのリスク評価 | I65: — | J65: 製品品質の科学的な理解
A66: C04-04-02 | D66: ● | E66: 分析法開発・バリデーション | F66: 品質試験の分析法を開発し、バリデーションする | H66: 分析法の開発・バリデーション・移管 | I66: 試験実施（原材料・工程内・出荷）（C08-01-01）、測定法開発・バリデーション（C03-03-01） | J66: 信頼できる品質試験法
A67: C04-04-03 | D67: ● | E67: 規格・有効期間設定 | F67: 規格・標準物質と、安定性試験の計画・有効期間を設定する | H67: 規格設定、標準物質の確立、安定性試験計画 | I67: 安定性試験の実施（C08-01-02） | J67: 根拠ある規格と有効期間
A68: C04-04-04 | D68: ● | E68: 同等性／同質性評価 | F68: 製法変更の前後で、品質が同等であることを評価する | H68: 変更前後の比較評価 | I68: 変更の報告区分判定・申請（C06-04-02） | J68: 製法変更後も品質が変わらないことの証明
A69: C04-05 | C69: ● | E69: 技術移転・製造規模管理 | F69: 製造規模と製造拠点を設計し、技術を移転する
A70: C04-05-01 | D70: ● | E70: 製造規模設定★ | F70: 需要に見合う製造規模を設定し、必要なスケールアップを行う（小規模のまま商用化する場合あり） | H70: 規模の設定、スケールアップ | I70: — | J70: 需要に見合う、無駄のない製造規模
A71: C04-05-02 | D71: ● | E71: 製造ネットワーク設計 | F71: 原薬・充填・包装の拠点構成（自社／CDMO）を設計する | H71: 拠点構成・二重化の判断 | I71: パートナー選定・評価（C01-03-01） | J71: 供給を確保できる製造拠点構成
A72: C04-05-03 | D72: ● | E72: 技術移転 | F72: 開発から製造所へ、または製造所間でプロセスを移転する | H72: 移転計画、マスターバッチレコードの作成 | I72: — | J72: 移転先で同じ品質を再現できる状態
A73: C05 | B73: ● | E73: 臨床開発 | F73: 少ない患者で、ヒトでの安全性・有効性の確かなエビデンスを生み出す能力 | G73: コア
A74: C05-01 | C74: ● | E74: 臨床開発戦略・試験デザイン | F74: 臨床開発計画を立て、エビデンス要件を満たす試験を設計する
A75: C05-01-01 | D75: ● | E75: 臨床開発計画 | F75: 承認までの臨床試験の全体計画を立てる | H75: 臨床開発計画の策定・改訂 | I75: 規制戦略立案（C06-01-01） | J75: 承認に至る道筋が明確な開発計画
A76: C05-01-02 | D76: ● | E76: 試験デザイン★ | F76: 単一ピボタル試験＋確認的エビデンス、外部対照、適応的デザインを含め、試験を設計する（統計的設計を含む） | H76: 試験デザイン、症例数設計、統計解析計画 | I76: 統計解析（C05-05-02） | J76: 少数例でも結論を出せる試験
A77: C05-01-03 | D77: ● | E77: 評価項目・COA開発★ | F77: 臨床アウトカム評価（COA）・バイオマーカーなどの評価項目を開発・検証する | H77: 評価項目の選定、COAの開発・検証 | I77: 患者団体との協働★（C10-01-01） | J77: 患者にとって意味があり、当局が受け入れる評価項目
A78: C05-02 | C78: ● | E78: 患者エビデンス管理★ | F78: 自然歴研究・患者レジストリ・リアルワールドデータを構築・活用し、患者数を推計する
A79: C05-02-01 | D79: ● | E79: 自然歴研究 | F79: 疾患の自然経過を記録し、外部対照・評価項目設定の基礎を作る | H79: 研究計画、データ収集・解析 | I79: — | J79: 外部対照に使える自然歴データ
A80: C05-02-02 | D80: ● | E80: 患者レジストリ運営 | F80: 患者団体等と協力してレジストリを構築・運営する（市販後の長期追跡を含む） | H80: レジストリの設計・運営、データ品質管理 | I80: — | J80: 長期に利用できる患者データ基盤
A81: C05-02-03 | D81: ● | E81: 外部データ活用 | F81: リアルワールドデータ・外部対照データの品質を確保し、エビデンスとして活用する | H81: データの適合性評価、外部対照の構築 | I81: — | J81: 当局に受け入れられる外部エビデンス
A82: C05-02-04 | D82: ● | E82: 疫学評価 | F82: 対象疾患の患者数・有病率・患者の分布を推計する（Orphan Drug指定の根拠、事業性・需要の評価の基礎） | H82: 有病率・患者数の推計、文献・データベースの調査 | I82: 外部データ活用（C05-02-03）、需要予測★（C12-01-01） | J82: 根拠ある患者数の推計
A83: C05-03 | C83: ● | E83: 患者特定・組入れ★ | F83: 候補患者を見つけ、試験への参加を実現する
A84: C05-03-01 | D84: ● | E84: 候補患者特定 | F84: 診断・遺伝子検査の情報を通じて、試験の候補患者を特定する | H84: 遺伝子検査プログラムとの連携、紹介経路の活用 | I84: 遺伝子検査プログラム★（C10-03-02） | J84: 試験に参加できる候補患者の把握
A85: C05-03-02 | D85: ● | E85: 施設・紹介ネットワーク | F85: 少数の専門施設と、施設間の患者紹介のネットワークを構築する | H85: 専門施設の特定、国際共同の施設網 | I85: 専門施設ネットワーク構築★（C10-03-03） | J85: 患者に届く試験実施体制
A86: C05-03-03 | D86: ● | E86: 参加負担の軽減 | F86: 患者・家族の参加負担を減らす（旅費支援、在宅・分散型の要素） | H86: 旅費・宿泊支援、在宅訪問、遠隔評価 | I86: — | J86: 参加・継続しやすい試験
A87: C05-04 | C87: ● | E87: 臨床試験運営 | F87: 施設を立ち上げ、試験をGCPに従って実施・管理する
A88: C05-04-01 | D88: ● | E88: 施設立ち上げ | F88: 実施医療機関の選定・契約・IRB審査を行う | H88: 施設選定、契約、IRB対応 | I88: — | J88: すぐに組入れを始められる施設
A89: C05-04-02 | D89: ● | E89: モニタリング・施設管理 | F89: リスクに基づくモニタリングで、施設の実施状況と症例を管理する | H89: モニタリング、施設課題の管理 | I89: — | J89: GCPに適合した試験の実施
A90: C05-04-03 | D90: ● | E90: 試験文書・登録管理 | F90: 治験マスターファイル（TMF）を管理し、ClinicalTrials.govへの登録・結果公開を行う | H90: TMF管理、試験登録・結果報告 | I90: 文書管理（C13-02-01） | J90: いつでも査察に耐える試験記録
A91: C05-05 | C91: ● | E91: 臨床データマネジメント・統計解析 | F91: 臨床データを収集・固定し、解析して報告する
A92: C05-05-01 | D92: ● | E92: データマネジメント | F92: EDCでデータを収集・クリーニングし、CDISC標準に整えて固定する | H92: データ収集・クリーニング、SDTM／ADaMの作成、データベース固定 | I92: — | J92: 解析に使える、信頼できるデータ
A93: C05-05-02 | D93: ● | E93: 統計解析 | F93: 統計解析計画に沿って解析し、図表・リストを作成する | H93: 統計解析、結果の解釈 | I93: 試験デザイン★（C05-01-02） | J93: 正確な解析結果
A94: C05-05-03 | D94: ● | E94: 臨床文書作成 | F94: 総括報告書（CSR）・統合解析などの臨床文書を作成する | H94: CSR、統合安全性・有効性解析の文書 | I94: 申請資料の作成・統合（C06-02-01） | J94: 申請に使える臨床文書
A95: C05-06 | C95: ● | E95: 治験薬供給管理 | F95: 治験薬を必要な施設・患者に、必要な時に届ける
A96: C05-06-01 | D96: ● | E96: 治験薬需給・割付 | F96: 治験薬の需給を計画し、割付・施設への供給・在庫を管理する | H96: 需給計画、IRTによる割付・供給 | I96: — | J96: 欠品・無駄のない治験薬供給
A97: C05-06-02 | D97: ● | E97: 治験薬の包装・表示 | F97: 治験薬の包装・表示（盲検化を含む）を行う | H97: 包装・表示、盲検化 | I97: — | J97: 試験の要件を満たす治験薬
A98: C06 | B98: ● | E98: 薬事 | F98: FDAとの対話を通じて、開発を承認に導き、承認後も製品を適法に維持する能力 | G98: コア
A99: C06-01 | C99: ● | E99: 薬事戦略・当局対応 | F99: 規制戦略を立て、FDAと対話し、指定制度を活用する
A100: C06-01-01 | D100: ● | E100: 規制戦略立案 | F100: 米国での承認経路と迅速化制度の活用を含め、規制戦略を立てる | H100: 承認経路の選択、迅速化制度の活用方針 | I100: 臨床開発計画（C05-01-01） | J100: 最短で確実な承認経路
...

Sheet ケイパビリティレベル
A1: ケイパビリティの成熟度レベル（L2ごとの定義）
A2: 対象：希少疾患向け新規バイオ医薬品（抗体医薬）／米国基準（FDA・BLA・21 CFR）。評価の対象はL2。規制上の最低水準：GxP・法令が関わるL2はレベル3が事実上の最低水準。
A3: レベル | B3: 名称 | C3: 共通定義
A4: 1 | B4: 初期 | C4: 属人的・場当たり的。成果が個人に依存し、再現できない
A5: 2 | B5: 管理された | C5: 案件（製品・試験・プロジェクト）ごとに計画・管理され、再現できる。ただし方法は案件・部門で異なる
A6: 3 | B6: 定義された | C6: 全社標準のプロセス・役割・データ定義があり、一貫して運用される
A7: 4 | B7: 定量的に管理された | C7: 指標で成果・品質を測定し、データに基づいて管理・予測する
A8: 5 | B8: 最適化された | C8: 継続的な改善と先進的な手法により、変化に先回りし、業界をリードする
A10: L2 ID | B10: ケイパビリティL1 | C10: ケイパビリティL2 | D10: 規制上の最低水準 | E10: レベル1 初期 | F10: レベル2 管理された | G10: レベル3 定義された | H10: レベル4 定量的に管理された | I10: レベル5 最適化された
A11: C01-01 | B11: 戦略・ガバナンス | C11: 研究開発ポートフォリオ管理 | D11: — | E11: 優先順位が個人の判断で決まり、根拠が残らない | F11: 開発品ごとに価値・リスクを評価するが、方法が案件ごとに異なる | G11: 全社共通の評価基準と判定プロセスで、全開発品を比較・判断する | H11: 成功確率・価値の予測を実績で検証し、資源配分を定量的に最適化する | I11: ポートフォリオ全体のシナリオ分析で、環境変化に先回りして組み替える
A12: C01-02 | C12: 知財・独占期間管理 | D12: — | E12: 特許出願が研究者任せで、独占期間を把握していない | F12: 主要製品ごとに特許・独占期間を管理している | G12: 特許と規制上の独占期間を一元管理し、全製品で戦略的に出願・維持する | H12: 独占期間の残りと競合参入リスクを定量的に監視し、製品戦略に反映する | I12: 知財と規制上の独占を組み合わせ、製品価値を最大化する戦略を先導する
A13: C01-03 | C13: 外部パートナー管理 | D13: — | E13: 委託先の選定・監督が担当者任せ | F13: 委託案件ごとに契約・品質取決めを結び、進捗を管理する | G13: 全社標準の選定基準・契約・監督の仕組みで、委託先を一元管理する | H13: 委託先の実績をKPIで評価し、選定・更新に反映する | I13: 戦略的パートナーと共同で改善し、委託ネットワーク全体を最適化する
A14: C02-01 | B14: 研究（創薬） | C14: 疾患・標的研究★ | D14: — | E14: 公開情報が中心で、標的仮説の根拠が限られる | F14: プロジェクトごとに遺伝学的解析・標的検証を行う | G14: 遺伝学的データと患者団体・専門医の知見を体系的に使う、標準的な探索・検証の流れがある | H14: 標的の検証成功率・臨床移行率を測定し、標的選定を改善する | I14: 独自の患者データ・解析基盤により、他社に先んじて新しい標的を見出す
A15: C02-02 | C15: 抗体創出 | D15: — | E15: 外部技術に依存し、取得・選別が場当たり的 | F15: 標準的な取得法・アッセイを持ち、案件ごとに運用する | G15: 複数の取得プラットフォームと、標準化されたスクリーニング体系を持つ | H15: ヒット率・期間を測定し、自動化で効率を管理する | I15: 独自のプラットフォームで、難しい標的にも抗体を創出できる
A16: C02-03 | C16: 抗体エンジニアリング | D16: — | E16: 改変を外部に依存している | F16: ヒト化・親和性成熟を案件ごとに実施できる | G16: ヒト化・親和性成熟・Fc設計を標準手法として社内で実施する | H16: 設計の成功率を測定し、構造・計算手法で予測精度を高める | I16: AI・計算設計などで、独自の分子設計により差別化する
A17: C02-04 | C17: 疾患モデル・薬効評価 | D17: — | E17: 既存モデルに依存し、疾患の再現性が不十分 | F17: 案件ごとにモデルを構築・評価する | G17: 疾患ごとに検証済みのモデル群を持ち、標準的に評価する | H17: モデルの予測性（臨床結果との相関）を検証し、改善する | I17: 患者由来細胞などの独自モデルで、臨床予測性の高い評価を先導する
A18: C02-05 | C18: 開発適性・免疫原性リスク評価 | D18: — | E18: 評価をせず、後工程で問題が発覚する | F18: 候補選定時に一部の評価を行う | G18: 標準的な評価項目で全候補を評価し、選定基準に組み込む | H18: 評価結果と後工程（製造性・ADA発生）の相関を測定し、基準を改善する | I18: 予測モデルにより、設計段階からリスクを回避する
A19: C03-01 | B19: 非臨床・臨床薬理 | C19: 非臨床薬理評価 | D19: — | E19: 試験が場当たり的で、臨床の用量設定に結びつかない | F19: 開発品ごとに計画して実施する | G19: 標準的な試験構成で、臨床の作用・用量の根拠を体系的に作る | H19: 非臨床と臨床の結果の整合を検証し、試験設計を改善する | I19: トランスレーショナルな指標で、臨床結果を高い精度で予測する
A20: C03-02 | C20: 非臨床安全性評価 | D20: レベル3（GLP） | E20: 試験構成が指針に沿わず、追加試験が発生する | F20: 開発品ごとに受託試験機関と試験を設計・実施する | G20: 抗体医薬の指針（ICH S6）に沿った標準戦略で、過不足のない試験構成を組む | H20: 当局からの指摘・追加試験の発生を測定し、戦略を改善する | I20: 動物試験に代わる新しい手法を活用し、効率と予測性を高める
A21: C03-03 | C21: バイオアナリシス | D21: レベル3（GLP・GCP） | E21: 測定法が安定せず、データの信頼性に課題がある | F21: 開発品ごとに測定法を確立・運用する | G21: 規制ガイダンスに沿った標準的な測定法の開発・バリデーションと、検査機関の管理を行う | H21: 再測定率・納期を測定し、管理する | I21: 新しいバイオマーカー・高感度測定を先導する
A22: C03-04 | C22: 臨床薬理・ファーマコメトリクス | D22: — | E22: 経験則で用量を決める | F22: 開発品ごとにPK解析を行う | G22: モデルに基づく医薬品開発（MIDD）を標準的に適用する | H22: モデルの予測と実績の差を検証し、意思決定に定量的に活用する | I22: モデルで試験を代替・縮小し、当局と合意する（少数例の希少疾患で特に有効）
A23: C04-01 | B23: CMC開発 | C23: 細胞株開発・セルバンク管理 | D23: レベル3（GMP：セルバンク） | E23: 細胞株構築をCDMOに全面依存し、記録が不十分 | F23: 案件ごとに細胞株を構築し、セルバンクを管理する | G23: 標準的な細胞株開発プラットフォームと、セルバンクの一元管理を持つ | H23: 生産性・安定性を指標で管理し、開発期間を短縮する | I23: 独自の高生産プラットフォームで、開発期間・コストの優位に立つ
A24: C04-02 | C24: 原薬プロセス開発 | D24: — | E24: 工程が経験則で、スケールを変えると問題が起きる | F24: 開発品ごとに工程を開発する | G24: プラットフォーム工程とQbD（リスク評価・管理戦略）を標準的に適用する | H24: 工程性能・収率を指標で管理し、データに基づいて最適化する | I24: 連続生産などの先進的な工程技術を導入し、業界をリードする
A25: C04-03 | C25: 製剤・デバイス開発 | D25: — | E25: 既存処方の流用のみ | F25: 開発品ごとに処方・容器を開発する | G25: 標準的な処方開発・容器評価と、デバイスの設計管理を運用する | H25: 安定性・使いやすさの指標で設計を最適化する | I25: 高濃度製剤・在宅自己投与デバイスなど、患者中心の製剤で差別化する
A26: C04-04 | C26: 分析法開発・品質特性評価 | D26: レベル3（GMP） | E26: 特性解析が不十分で、規格の根拠が弱い | F26: 開発品ごとに分析法・規格を設定する | G26: 標準的な特性解析・分析法バリデーション・同等性評価の手順を持つ | H26: 分析法の性能と同等性判断の実績を指標で管理する | I26: 高度な分析技術で品質を深く理解し、製法変更を迅速にする
A27: C04-05 | C27: 技術移転・製造規模管理 | D27: レベル3（GMP） | E27: 移転のたびに問題が起き、規模の判断が場当たり的 | F27: 案件ごとに移転計画を作り、実施する | G27: 標準的な移転手順と、需要に基づく規模・拠点の判断基準を持つ | H27: 移転の期間・成功率を指標で管理する | I27: 需要の変動に柔軟に対応できる製造ネットワークを先回りして構築する
A28: C05-01 | B28: 臨床開発 | C28: 臨床開発戦略・試験デザイン | D28: — | E28: 一般的な第I〜III相の流用のみ | F28: 開発品ごとに計画・設計する | G28: 希少疾患向けの設計手法（単一ピボタル、外部対照、適応的デザイン）を標準的に検討・適用する | H28: 設計の妥当性（当局合意・成功率）を検証し、改善する | I28: 革新的なデザインで当局と合意を形成し、開発期間を大幅に短縮する
A29: C05-02 | C29: 患者エビデンス管理★ | D29: — | E29: 自然歴データがなく、外部対照を作れない | F29: 開発品ごとに自然歴研究・レジストリを行う | G29: 疾患ごとに標準化された自然歴研究・レジストリを運営し、データ品質を管理する | H29: データの完全性・利用実績を指標で管理し、当局提出に使える品質を維持する | I29: 患者団体・業界と共有するデータ基盤を主導し、疾患領域のエビデンスを先導する
A30: C05-03 | C30: 患者特定・組入れ★ | D30: — | E30: 施設任せで、組入れが遅れる | F30: 試験ごとに組入れ計画・施設網をつくる | G30: 遺伝子検査・紹介ネットワーク・負担軽減策を組み合わせた、標準的な組入れ戦略を持つ | H30: 組入れ速度・脱落率を指標で管理し、予測する | I30: 患者コミュニティと一体となり、世界規模で迅速に組み入れる
A31: C05-04 | C31: 臨床試験運営 | D31: レベル3（GCP） | E31: CRO任せで、スポンサーとしての監督が弱い | F31: 試験ごとに運営計画を立て、監督する | G31: 標準的な立ち上げ・リスクに基づくモニタリング・TMF管理を運用する | H31: 立ち上げ期間・品質指標を管理する | I31: 分散型試験などの先進的な運営で、患者と施設の負担を最小にする
A32: C05-05 | C32: 臨床データマネジメント・統計解析 | D32: レベル3（GCP） | E32: データ品質の問題で、データベース固定が遅れる | F32: 試験ごとにデータマネジメント・解析を行う | G32: CDISC標準と、標準的なデータマネジメント・解析・文書作成の手順を持つ | H32: データベース固定までの期間・データ品質を指標で管理する | I32: 自動化とデータの再利用で、解析・報告を大幅に短縮する
A33: C05-06 | C33: 治験薬供給管理 | D33: レベル3（GCP・GMP） | E33: 欠品・廃棄が頻発する | F33: 試験ごとに供給計画を立てる | G33: IRTを用いた標準的な需給・割付・供給管理を行う | H33: 廃棄率・欠品を指標で管理する | I33: 需要予測に基づく動的な供給で、少量・多国間の供給を最適化する
A34: C06-01 | B34: 薬事 | C34: 薬事戦略・当局対応 | D34: — | E34: 当局対応が場当たり的で、合意が得られない | F34: 開発品ごとに規制戦略を立て、会議に臨む | G34: 標準的な規制戦略の立案・会議準備と、指定制度の体系的な活用 | H34: 当局との合意事項の達成率・審査期間を指標で管理する | I34: 規制動向を先取りし、新しい制度・枠組みの活用を先導する
A35: C06-02 | C35: 申請資料作成・管理 | D35: レベル3（法令） | E35: 申請資料の作成が遅れ、技術的な不備がある | F35: 申請ごとに作成・提出する | G35: 標準的なテンプレート・パブリッシング・提出管理を持つ | H35: 作成期間・照会件数を指標で管理する | I35: 構造化データにより、申請資料を自動生成する
A36: C06-03 | C36: ラベリング管理 | D36: レベル3（法令） | E36: 改訂の反映漏れがある | F36: 製品ごとに表示を管理する | G36: 標準的な作成・改訂・関連資材への反映の手順を持つ | H36: 改訂の期間・整合性を指標で管理する | I36: 構造化された表示情報で、改訂を迅速かつ一貫して反映する
A37: C06-04 | C37: 市販後薬事コンプライアンス | D37: レベル3（法令） | E37: 期限の遅れ・報告漏れがある | F37: 製品ごとに要求事項・期限を管理する | G37: 全製品の市販後要求・変更・報告を一元管理する | H37: 期限の遵守率を指標で管理する | I37: 規制の変化を先取りし、負担を最小にした運用を行う
A38: C07-01 | B38: 製造 | C38: 生産計画・製造実行管理 | D38: レベル3（GMP） | E38: 紙の記録と場当たり的な計画 | F38: 製造所ごとに計画・記録を管理する | G38: 標準的な計画プロセスと電子バッチ記録を持つ | H38: 計画の遵守率・記録の不備率を指標で管理する | I38: 需要と連動した動的な計画と、記録照査の自動化を行う
A39: C07-02 | C39: 原薬製造 | D39: レベル3（GMP） | E39: ロット間のばらつきが大きく、失敗ロットが多い | F39: 製造所ごとに安定して製造できる | G39: 標準化された製造と工程データの監視で、一貫した品質を保つ | H39: 収率・成功率を統計的に管理する | I39: リアルタイムの工程制御など先進的な製造技術で、業界をリードする
A40: C07-03 | C40: 製剤化・無菌充填・包装 | D40: レベル3（GMP） | E40: 無菌性の問題・不良が発生する | F40: 製造所ごとに管理する | G40: 標準化された無菌操作と、シリアル化を含む包装を行う | H40: 不良率・無菌性の指標を管理する | I40: 自動化・閉鎖系の技術で、無菌保証の水準を高める
A41: C07-04 | C41: 設備・環境管理 | D41: レベル3（GMP） | E41: 故障への対応が中心 | F41: 設備ごとに保全計画を持つ | G41: 標準的な予防保全・環境モニタリングを行う | H41: 稼働率・環境の傾向を指標で管理する | I41: 予知保全・リアルタイム監視を行う
A42: C08-01 | B42: 品質 | C42: 品質管理（試験・安定性） | D42: レベル3（GMP） | E42: 試験の遅れ・規格外結果が多い | F42: 試験室ごとに運用する | G42: 標準的な試験・安定性試験・OOS調査の手順と、データ完全性の管理を持つ | H42: 試験の所要時間・OOS率を管理する | I42: 自動化・リアルタイム出荷試験など先進的な手法を用いる
A43: C08-02 | C43: 品質保証（出荷判定・逸脱・変更） | D43: レベル3（GMP） | E43: 逸脱・苦情の処理が遅く、再発する | F43: 製造所ごとに運用する | G43: 標準的な出荷判定・逸脱・変更・苦情処理の品質システムを持つ | H43: 逸脱の再発率・CAPAの有効性などの品質指標で管理する | I43: 品質データの分析で問題を予防し、品質文化が定着している
A44: C08-03 | C44: バリデーション管理 | D44: レベル3（GMP） | E44: 文書が不備で、査察で指摘される | F44: 対象ごとにバリデーションを行う | G44: リスクに基づく標準的なバリデーション手法（CSAを含む）を持つ | H44: バリデーション状態・期間を指標で管理する | I44: 継続的な工程確認とデータに基づく検証で、効率化する
A45: C08-04 | C45: 品質システム・監査管理 | D45: レベル3（GxP） | E45: 監査・査察への対応が場当たり的 | F45: 年次計画で監査を行う | G45: リスクに基づく監査計画と、常に査察に対応できる品質システムを持つ | H45: 監査の指摘・査察結果を指標で管理し、改善する | I45: 品質システムが事業の改善を先導する
A46: C09-01 | B46: ファーマコビジランス（安全性） | C46: 有害事象管理 | D46: レベル3（PV） | E46: 収集漏れ・報告遅延がある | F46: 製品ごとに運用する | G46: 標準的な収集・評価・報告のプロセスと、安全性データベースを持つ | H46: 報告期限の遵守率・品質を指標で管理する | I46: 受付・コーディングの自動化で処理を効率化する
A47: C09-02 | C47: 安全性シグナル・リスク管理 | D47: レベル3（PV） | E47: シグナルの検出が場当たり的 | F47: 製品ごとに定期的に評価する | G47: 標準的なシグナル管理・ベネフィット・リスク評価・REMSの運用を持つ | H47: シグナル評価の期間・REMSの有効性を指標で管理する | I47: レジストリ・リアルワールドデータを統合した先進的なリスク評価を行う
A48: C10-01 | B48: メディカル・患者エンゲージメント | C48: 患者団体・専門医連携★ | D48: — | E48: 関係が個人的なつながりに依存する | F48: 製品ごとに関係を構築する | G48: 全社の方針・倫理基準に基づき、継続的に協働する | H48: 関係の質と成果（参画件数、意見の反映）を評価する | I48: 患者コミュニティに信頼されるパートナーとして、疾患領域を共に先導する
A49: C10-02 | C49: メディカルアフェアーズ | D49: — | E49: 問い合わせへの対応が中心 | F49: 製品ごとにMSL活動・学術活動を計画する | G49: 標準的な科学的情報提供・問い合わせ対応・学術活動を行う | H49: 活動の質・影響を指標で評価する | I49: エビデンス創出を先導し、疾患領域の科学的議論をリードする
A50: C10-03 | C50: 疾患啓発・診断支援★ | D50: — | E50: 啓発活動がない | F50: 製品ごとに啓発・検査プログラムを行う | G50: 啓発・遺伝子検査・専門施設網を組み合わせた、標準的な診断支援を行う | H50: 診断率・診断までの期間を指標で管理する | I50: 学会・業界と連携し、疾患の診断環境そのものを変える
A51: C10-04 | C51: 患者支援サービス★ | D51: — | E51: 個別に対応している | F51: ハブ事業者に委託して運用する | G51: 標準的なサービス設計・品質管理・個人情報保護のもとで運営する | H51: 治療開始までの期間・継続率を指標で管理する | I51: 患者体験に基づき、先回りした個別の支援を行う
A52: C11-01 | B52: 市場アクセス・商業 | C52: 価格・保険者契約管理 | D52: — | E52: 価値の根拠が弱く、償還が得られない | F52: 製品ごとに価格・契約を検討する | G52: 価値エビデンスに基づく標準的な価格設定・契約プロセスを持つ | H52: 償還率・契約の成果を指標で管理する | I52: 成果連動型など革新的な契約モデルを先導する
A53: C11-02 | C53: 政府価格報告・政策対応 | D53: レベル3（法令） | E53: 報告の誤り・遅延がある | F53: 担当者が手作業で算定・報告する | G53: 標準化された算定方法と統制のもとで報告する | H53: 報告の精度・期限を指標で管理する | I53: 政策の変化を先取りして戦略的に対応する
A54: C11-03 | C54: 販促・商業コンプライアンス | D54: レベル3（法令） | E54: 審査が不十分 | F54: 資材ごとに審査する | G54: 標準的な審査・提出・支払報告の手順を持つ | H54: 審査期間・指摘件数を指標で管理する | I54: コンプライアンスが迅速な市場展開を支えている
A55: C11-04 | C55: 営業・顧客管理 | D55: — | E55: 担当者任せ | F55: 製品ごとに対象施設を定めて活動する | G55: 標準的な顧客の区分と活動管理を行う | H55: 活動の成果を指標で管理する | I55: データに基づき、施設ごとに最適化された活動を行う
A56: C12-01 | B56: サプライチェーン | C56: 需給計画 | D56: — | E56: 経験則の予測で、欠品・廃棄が発生する | F56: 製品ごとに計画する | G56: 患者単位の需要データに基づく、標準的な需給計画（S&OP）を持つ | H56: 予測精度・在庫指標を管理する | I56: リアルタイムの需要データで動的に計画する
A57: C12-02 | C57: 流通ネットワーク管理★ | D57: — | E57: 流通の状況が見えない | F57: パートナーごとに契約・管理する | G57: 標準的なネットワーク設計・パートナー管理・データ連携を行う | H57: 流通パートナーの実績・データ品質を指標で管理する | I57: 患者体験を中心に流通網を最適化する
A58: C12-03 | C58: コールドチェーン物流 | D58: レベル3（GMP） | E58: 温度逸脱が頻発する | F58: 輸送ごとに温度を記録する | G58: 検証済みの梱包・輸送と、標準的な逸脱対応を持つ | H58: 温度逸脱率を指標で管理する | I58: リアルタイム監視と予測で逸脱を未然に防ぐ
A59: C12-04 | C59: トレーサビリティ | D59: レベル3（法令：DSCSA） | E59: 規制への対応が不十分 | F59: 最低限の対応を個別に行う | G59: DSCSAに準拠した標準的なシリアル化・取引情報の交換を行う | H59: データの整合性・照会への対応を指標で管理する | I59: 追跡データを需要・品質の管理にも活用する
A60: C12-05 | C60: 供給継続・回収管理 | D60: レベル3（GMP・法令） | E60: 供給中断・回収に場当たり的に対応する | F60: 製品ごとにリスクを把握する | G60: 標準的なリスク評価・事業継続計画・回収手順を持つ | H60: リスク指標を監視し、訓練で有効性を検証する | I60: サプライチェーン全体の強靭性を先回りして設計する
A61: C13-01 | B61: 共通基盤 | C61: 情報・データ管理 | D61: — | E61: データが部門ごとに分散している | F61: 部門ごとにマスタ・データを管理する | G61: 全社のデータガバナンス・マスタ管理・個人情報保護の仕組みを持つ | H61: データ品質を指標で管理する | I61: データを戦略的な資産として活用する
A62: C13-02 | C62: GxP文書・記録管理 | D62: レベル3（GxP・Part 11） | E62: 紙・個人による管理 | F62: 部門ごとに文書を管理する | G62: 全社標準の電子文書管理（Part 11準拠）を持つ | H62: 文書の改訂期間・記録の検索性を指標で管理する | I62: 構造化コンテンツで文書を再利用・自動化する
A63: C13-03 | C63: GxP教育・資格管理 | D63: レベル3（GxP） | E63: 教育記録に不備がある | F63: 部門ごとに教育を管理する | G63: 役割に基づく標準的な教育・資格管理を持つ | H63: 教育の完了率・有効性を指標で管理する | I63: 業務の変化に先回りした能力開発を行う

Sheet VS×ケイパビリティ関係
A1: VS×ケイパビリティ関係（正本：VS L4 × ケイパビリティL3）
A2: 1行1関係。区分は「主」（そのL4の中核）か「支援」（下支え）。マトリクスはこのシートから数式で集計する。関係の追加・変更はこのシートで行う。灰色の列は数式（編集しない）。
A3: VS L4 ID | B3: VS L4 | C3: ケイパビリティL3 ID | D3: ケイパビリティL3 | E3: 区分 | F3: VS L3 ID | G3: ケイパビリティL2 ID
A4: 01-01-01 | B4: ★患者団体・専門医との連携による疾患理解 | C4: C10-01-01 | D4: {=IFERROR(INDEX('ケイパビリティマップ'!$E:$E,MATCH(C4,'ケイパビリティマップ'!$A:$A,0)),"（IDなし）")} -> 患者団体との協働★ | E4: 主 | F4: =LEFT(A4,5) -> 01-01 | G4: =LEFT(C4,6) -> C10-01
A5: 01-01-01 | B5: ★患者団体・専門医との連携による疾患理解 | C5: C10-01-02 | D5: {=IFERROR(INDEX('ケイパビリティマップ'!$E:$E,MATCH(C5,'ケイパビリティマップ'!$A:$A,0)),"（IDなし）")} -> 専門医との関係構築 | E5: 支援 | F5: =LEFT(A5,5) -> 01-01 | G5: =LEFT(C5,6) -> C10-01
A6: 01-01-01 | B6: ★患者団体・専門医との連携による疾患理解 | C6: C02-01-01 | D6: {=IFERROR(INDEX('ケイパビリティマップ'!$E:$E,MATCH(C6,'ケイパビリティマップ'!$A:$A,0)),"（IDなし）")} -> 病態・遺伝学的原因の解析★ | E6: 支援 | F6: =LEFT(A6,5) -> 01-01 | G6: =LEFT(C6,6) -> C02-01
A7: 01-01-02 | B7: 疾患生物学の調査・標的仮説の立案 | C7: C02-01-01 | D7: {=IFERROR(INDEX('ケイパビリティマップ'!$E:$E,MATCH(C7,'ケイパビリティマップ'!$A:$A,0)),"（IDなし）")} -> 病態・遺伝学的原因の解析★ | E7: 主 | F7: =LEFT(A7,5) -> 01-01 | G7: =LEFT(C7,6) -> C02-01
A8: 01-01-03 | B8: ★遺伝学的原因の解析（単一遺伝子疾患等、患者ゲノム・検体データ） | C8: C02-01-01 | D8: {=IFERROR(INDEX('ケイパビリティマップ'!$E:$E,MATCH(C8,'ケイパビリティマップ'!$A:$A,0)),"（IDなし）")} -> 病態・遺伝学的原因の解析★ | E8: 主 | F8: =LEFT(A8,5) -> 01-01 | G8: =LEFT(C8,6) -> C02-01
A9: 01-01-03 | B9: ★遺伝学的原因の解析（単一遺伝子疾患等、患者ゲノム・検体データ） | C9: C13-01-03 | D9: {=IFERROR(INDEX('ケイパビリティマップ'!$E:$E,MATCH(C9,'ケイパビリティマップ'!$A:$A,0)),"（IDなし）")} -> 個人情報保護 | E9: 支援 | F9: =LEFT(A9,5) -> 01-01 | G9: =LEFT(C9,6) -> C13-01
A10: 01-01-04 | B10: 標的の機能検証（遺伝子ノックダウン、in vitro／in vivo） | C10: C02-01-02 | D10: {=IFERROR(INDEX('ケイパビリティマップ'!$E:$E,MATCH(C10,'ケイパビリティマップ'!$A:$A,0)),"（IDなし）")} -> 標的検証 | E10: 主 | F10: =LEFT(A10,5) -> 01-01 | G10: =LEFT(C10,6) -> C02-01
A11: 01-01-05 | B11: 抗体モダリティ適合性評価（細胞外・膜タンパクか、組織発現分布） | C11: C02-01-03 | D11: {=IFERROR(INDEX('ケイパビリティマップ'!$E:$E,MATCH(C11,'ケイパビリティマップ'!$A:$A,0)),"（IDなし）")} -> モダリティ適合性評価 | E11: 主 | F11: =LEFT(A11,5) -> 01-01 | G11: =LEFT(C11,6) -> C02-01
A12: 01-01-06 | B12: 標的選定（競合・知財〔FTO〕調査を含む） | C12: C02-01-02 | D12: {=IFERROR(INDEX('ケイパビリティマップ'!$E:$E,MATCH(C12,'ケイパビリティマップ'!$A:$A,0)),"（IDなし）")} -> 標的検証 | E12: 主 | F12: =LEFT(A12,5) -> 01-01 | G12: =LEFT(C12,6) -> C02-01
A13: 01-01-06 | B13: 標的選定（競合・知財〔FTO〕調査を含む） | C13: C01-02-01 | D13: {=IFERROR(INDEX('ケイパビリティマップ'!$E:$E,MATCH(C13,'ケイパビリティマップ'!$A:$A,0)),"（IDなし）")} -> 特許戦略・調査 | E13: 支援 | F13: =LEFT(A13,5) -> 01-01 | G13: =LEFT(C13,6) -> C01-02
A14: 01-01-06 | B14: 標的選定（競合・知財〔FTO〕調査を含む） | C14: C01-01-03 | D14: {=IFERROR(INDEX('ケイパビリティマップ'!$E:$E,MATCH(C14,'ケイパビリティマップ'!$A:$A,0)),"（IDなし）")} -> 目標製品プロファイル（TPP）管理 | E14: 支援 | F14: =LEFT(A14,5) -> 01-01 | G14: =LEFT(C14,6) -> C01-01
A15: 01-02-01 | B15: 抗原・評価系（アッセイ）の準備 | C15: C02-02-01 | D15: {=IFERROR(INDEX('ケイパビリティマップ'!$E:$E,MATCH(C15,'ケイパビリティマップ'!$A:$A,0)),"（IDなし）")} -> 抗原・アッセイ開発 | E15: 主 | F15: =LEFT(A15,5) -> 01-02 | G15: =LEFT(C15,6) -> C02-02
... A294: 09-03-05 | B294: ★Medicare価格交渉の除外要件の管理（希少疾病のみの適応の場合、IRA） | C294: C11-02-03 | D294: {=IFERROR(INDEX('ケイパビリティマップ'!$E:$E,MATCH(C294,'ケイパビリティマップ'!$A:$A,0)),"（IDなし）")} -> 薬価政策対応 | E294: 主 | F294: =LEFT(A294,5) -> 09-03 | G294: =LEFT(C294,6) -> C11-02
D295: {=IF(C295="","",IFERROR(INDEX('ケイパビリティマップ'!$E:$E,MATCH(C295,'ケイパビリティマップ'!$A:$A,0)),"（IDなし）"))} | F295: =IF(A295="","",LEFT(A295,5)) | G295: =IF(C295="","",LEFT(C295,6))
D296: {=IF(C296="","",IFERROR(INDEX('ケイパビリティマップ'!$E:$E,MATCH(C296,'ケイパビリティマップ'!$A:$A,0)),"（IDなし）"))} | F296: =IF(A296="","",LEFT(A296,5)) | G296: =IF(C296="","",LEFT(C296,6))
D297: {=IF(C297="","",IFERROR(INDEX('ケイパビリティマップ'!$E:$E,MATCH(C297,'ケイパビリティマップ'!$A:$A,0)),"（IDなし）"))} | F297: =IF(A297="","",LEFT(A297,5)) | G297: =IF(C297="","",LEFT(C297,6))
D298: {=IF(C298="","",IFERROR(INDEX('ケイパビリティマップ'!$E:$E,MATCH(C298,'ケイパビリティマップ'!$A:$A,0)),"（IDなし）"))} | F298: =IF(A298="","",LEFT(A298,5)) | G298: =IF(C298="","",LEFT(C298,6))
D299: {=IF(C299="","",IFERROR(INDEX('ケイパビリティマップ'!$E:$E,MATCH(C299,'ケイパビリティマップ'!$A:$A,0)),"（IDなし）"))} | F299: =IF(A299="","",LEFT(A299,5)) | G299: =IF(C299="","",LEFT(C299,6))
D300: {=IF(C300="","",IFERROR(INDEX('ケイパビリティマップ'!$E:$E,MATCH(C300,'ケイパビリティマップ'!$A:$A,0)),"（IDなし）"))} | F300: =IF(A300="","",LEFT(A300,5)) | G300: =IF(C300="","",LEFT(C300,6))
D301: {=IF(C301="","",IFERROR(INDEX('ケイパビリティマップ'!$E:$E,MATCH(C301,'ケイパビリティマップ'!$A:$A,0)),"（IDなし）"))} | F301: =IF(A301="","",LEFT(A301,5)) | G301: =IF(C301="","",LEFT(C301,6))
D302: {=IF(C302="","",IFERROR(INDEX('ケイパビリティマップ'!$E:$E,MATCH(C302,'ケイパビリティマップ'!$A:$A,0)),"（IDなし）"))} | F302: =IF(A302="","",LEFT(A302,5)) | G302: =IF(C302="","",LEFT(C302,6))
D303: {=IF(C303="","",IFERROR(INDEX('ケイパビリティマップ'!$E:$E,MATCH(C303,'ケイパビリティマップ'!$A:$A,0)),"（IDなし）"))} | F303: =IF(A303="","",LEFT(A303,5)) | G303: =IF(C303="","",LEFT(C303,6))
D304: {=IF(C304="","",IFERROR(INDEX('ケイパビリティマップ'!$E:$E,MATCH(C304,'ケイパビリティマップ'!$A:$A,0)),"（IDなし）"))} | F304: =IF(A304="","",LEFT(A304,5)) | G304: =IF(C304="","",LEFT(C304,6))
D305: {=IF(C305="","",IFERROR(INDEX('ケイパビリティマップ'!$E:$E,MATCH(C305,'ケイパビリティマップ'!$A:$A,0)),"（IDなし）"))} | F305: =IF(A305="","",LEFT(A305,5)) | G305: =IF(C305="","",LEFT(C305,6))
D306: {=IF(C306="","",IFERROR(INDEX('ケイパビリティマップ'!$E:$E,MATCH(C306,'ケイパビリティマップ'!$A:$A,0)),"（IDなし）"))} | F306: =IF(A306="","",LEFT(A306,5)) | G306: =IF(C306="","",LEFT(C306,6))
... D494: {=IF(C494="","",IFERROR(INDEX('ケイパビリティマップ'!$E:$E,MATCH(C494,'ケイパビリティマップ'!$A:$A,0)),"（IDなし）"))} | F494: =IF(A494="","",LEFT(A494,5)) | G494: =IF(C494="","",LEFT(C494,6))

Sheet VS×ケイパビリティ
A1: バリューストリーム×ケイパビリティマップ（行：バリューストリームL3 × 列：ケイパビリティL2）
A2: ●＝主（配下のL4×L3の関係に「主」が1つ以上） ○＝支援のみ 空欄＝関係なし。各セルは「VS×ケイパビリティ関係」シートから数式で集計（直接入力しない）。
A4: VS L2 | B4: L3 ID | C4: VS L3 | D4: C01 戦略・ガバナンス | G4: C02 研究（創薬） | L4: C03 非臨床・臨床薬理 | P4: C04 CMC開発 | U4: C05 臨床開発 | AA4: C06 薬事 | AE4: C07 製造 | AI4: C08 品質 | AM4: C09 ファーマコビジランス（安全性） | AO4: C10 メディカル・患者エンゲージメント | AS4: C11 市場アクセス・商業 | AW4: C12 サプライチェーン | BB4: C13 共通基盤 | BE4: ●の数 | BF4: ○の数
D5: C01-01 | E5: C01-02 | F5: C01-03 | G5: C02-01 | H5: C02-02 | I5: C02-03 | J5: C02-04 | K5: C02-05 | L5: C03-01 | M5: C03-02 | N5: C03-03 | O5: C03-04 | P5: C04-01 | Q5: C04-02 | R5: C04-03 | S5: C04-04 | T5: C04-05 | U5: C05-01 | V5: C05-02 | W5: C05-03 | X5: C05-04 | Y5: C05-05 | Z5: C05-06 | AA5: C06-01 | AB5: C06-02 | AC5: C06-03 | AD5: C06-04 | AE5: C07-01 | AF5: C07-02 | AG5: C07-03 | AH5: C07-04 | AI5: C08-01 | AJ5: C08-02 | AK5: C08-03 | AL5: C08-04 | AM5: C09-01 | AN5: C09-02 | AO5: C10-01 | AP5: C10-02 | AQ5: C10-03 | AR5: C10-04 | AS5: C11-01 | AT5: C11-02 | AU5: C11-03 | AV5: C11-04 | AW5: C12-01 | AX5: C12-02 | AY5: C12-03 | AZ5: C12-04 | BA5: C12-05 | BB5: C13-01 | BC5: C13-02 | BD5: C13-03
D6: 研究開発ポートフォリオ管理 | E6: 知財・独占期間管理 | F6: 外部パートナー管理 | G6: 疾患・標的研究★ | H6: 抗体創出 | I6: 抗体エンジニアリング | J6: 疾患モデル・薬効評価 | K6: 開発適性・免疫原性リスク評価 | L6: 非臨床薬理評価 | M6: 非臨床安全性評価 | N6: バイオアナリシス | O6: 臨床薬理・ファーマコメトリクス | P6: 細胞株開発・セルバンク管理 | Q6: 原薬プロセス開発 | R6: 製剤・デバイス開発 | S6: 分析法開発・品質特性評価 | T6: 技術移転・製造規模管理 | U6: 臨床開発戦略・試験デザイン | V6: 患者エビデンス管理★ | W6: 患者特定・組入れ★ | X6: 臨床試験運営 | Y6: 臨床データマネジメント・統計解析 | Z6: 治験薬供給管理 | AA6: 薬事戦略・当局対応 | AB6: 申請資料作成・管理 | AC6: ラベリング管理 | AD6: 市販後薬事コンプライアンス | AE6: 生産計画・製造実行管理 | AF6: 原薬製造 | AG6: 製剤化・無菌充填・包装 | AH6: 設備・環境管理 | AI6: 品質管理（試験・安定性） | AJ6: 品質保証（出荷判定・逸脱・変更） | AK6: バリデーション管理 | AL6: 品質システム・監査管理 | AM6: 有害事象管理 | AN6: 安全性シグナル・リスク管理 | AO6: 患者団体・専門医連携★ | AP6: メディカルアフェアーズ | AQ6: 疾患啓発・診断支援★ | AR6: 患者支援サービス★ | AS6: 価格・保険者契約管理 | AT6: 政府価格報告・政策対応 | AU6: 販促・商業コンプライアンス | AV6: 営業・顧客管理 | AW6: 需給計画 | AX6: 流通ネットワーク管理★ | AY6: コールドチェーン物流 | AZ6: トレーサビリティ | BA6: 供給継続・回収管理 | BB6: 情報・データ管理 | BC6: GxP文書・記録管理 | BD6: GxP教育・資格管理
A7: 01 創薬研究 | B7: 01-01 | C7: 標的探索・検証 | D7: =IF(COUNTIFS('VS×ケイパビリティ関係'!$F$4:$F$494,$B7,'VS×ケイパビリティ関係'!$G$4:$G$494,D$5,'VS×ケイパビリティ関係'!$E$4:$E$494,"主")>0,"●",IF(COUNTIFS('VS×ケイパビリティ関係'!$F$4:$F$494,$B7,'VS×ケイパビリティ関係'!$G$4:$G$494,D$5,'VS×ケイパビリティ関係'!$E$4:$E$494,"支援")>0,"○","")) -> ○ | E7: =IF(COUNTIFS('VS×ケイパビリティ関係'!$F$4:$F$494,$B7,'VS×ケイパビリティ関係'!$G$4:$G$494,E$5,'VS×ケイパビリティ関係'!$E$4:$E$494,"主")>0,"●",IF(COUNTIFS('VS×ケイパビリティ関係'!$F$4:$F$494,$B7,'VS×ケイパビリティ関係'!$G$4:$G$494,E$5,'VS×ケイパビリティ関係'!$E$4:$E$494,"支援")>0,"○","")) -> ○ | F7: =IF(COUNTIFS('VS×ケイパビリティ関係'!$F$4:$F$494,$B7,'VS×ケイパビリティ関係'!$G$4:$G$494,F$5,'VS×ケイパビリティ関係'!$E$4:$E$494,"主")>0,"●",IF(COUNTIFS('VS×ケイパビリティ関係'!$F$4:$F$494,$B7,'VS×ケイパビリティ関係'!$G$4:$G$494,F$5,'VS×ケイパビリティ関係'!$E$4:$E$494,"支援")>0,"○","")) | G7: =IF(COUNTIFS('VS×ケイパビリティ関係'!$F$4:$F$494,$B7,'VS×ケイパビリティ関係'!$G$4:$G$494,G$5,'VS×ケイパビリティ関係'!$E$4:$E$494,"主")>0,"●",IF(COUNTIFS('VS×ケイパビリティ関係'!$F$4:$F$494,$B7,'VS×ケイパビリティ関係'!$G$4:$G$494,G$5,'VS×ケイパビリティ関係'!$E$4:$E$494,"支援")>0,"○","")) -> ● | H7: =IF(COUNTIFS('VS×ケイパビリティ関係'!$F$4:$F$494,$B7,'VS×ケイパビリティ関係'!$G$4:$G$494,H$5,'VS×ケイパビリティ関係'!$E$4:$E$494,"主")>0,"●",IF(COUNTIFS('VS×ケイパビリティ関係'!$F$4:$F$494,$B7,'VS×ケイパビリティ関係'!$G$4:$G$494,H$5,'VS×ケイパビリティ関係'!$E$4:$E$494,"支援")>0,"○","")) | I7: =IF(COUNTIFS('VS×ケイパビリティ関係'!$F$4:$F$494,$B7,'VS×ケイパビリティ関係'!$G$4:$G$494,I$5,'VS×ケイパビリティ関係'!$E$4:$E$494,"主")>0,"●",IF(COUNTIFS('VS×ケイパビリティ関係'!$F$4:$F$494,$B7,'VS×ケイパビリティ関係'!$G$4:$G$494,I$5,'VS×ケイパビリティ関係'!$E$4:$E$494,"支援")>0,"○","")) | J7: =IF(COUNTIFS('VS×ケイパビリティ関係'!$F$4:$F$494,$B7,'VS×ケイパビリティ関係'!$G$4:$G$494,J$5,'VS×ケイパビリティ関係'!$E$4:$E$494,"主")>0,"●",IF(COUNTIFS('VS×ケイパビリティ関係'!$F$4:$F$494,$B7,'VS×ケイパビリティ関係'!$G$4:$G$494,J$5,'VS×ケイパビリティ関係'!$E$4:$E$494,"支援")>0,"○","")) | K7: =IF(COUNTIFS('VS×ケイパビリティ関係'!$F$4:$F$494,$B7,'VS×ケイパビリティ関係'!$G$4:$G$494,K$5,'VS×ケイパビリティ関係'!$E$4:$E$494,"主")>0,"●",IF(COUNTIFS('VS×ケイパビリティ関係'!$F$4:$F$494,$B7,'VS×ケイパビリティ関係'!$G$4:$G$494,K$5,'VS×ケイパビリティ関係'!$E$4:$E$494,"支援")>0,"○","")) | ... BD7: =IF(COUNTIFS('VS×ケイパビリティ関係'!$F$4:$F$494,$B7,'VS×ケイパビリティ関係'!$G$4:$G$494,BD$5,'VS×ケイパビリティ関係'!$E$4:$E$494,"主")>0,"●",IF(COUNTIFS('VS×ケイパビリティ関係'!$F$4:$F$494,$B7,'VS×ケイパビリティ関係'!$G$4:$G$494,BD$5,'VS×ケイパビリティ関係'!$E$4:$E$494,"支援")>0,"○","")) | BE7: =COUNTIF(D7:BD7,"●") -> 2 | BF7: =COUNTIF(D7:BD7,"○") -> 3
B8: 01-02 | C8: ヒット・リード創出 | D8: =IF(COUNTIFS('VS×ケイパビリティ関係'!$F$4:$F$494,$B8,'VS×ケイパビリティ関係'!$G$4:$G$494,D$5,'VS×ケイパビリティ関係'!$E$4:$E$494,"主")>0,"●",IF(COUNTIFS('VS×ケイパビリティ関係'!$F$4:$F$494,$B8,'VS×ケイパビリティ関係'!$G$4:$G$494,D$5,'VS×ケイパビリティ関係'!$E$4:$E$494,"支援")>0,"○","")) -> ○ | E8: =IF(COUNTIFS('VS×ケイパビリティ関係'!$F$4:$F$494,$B8,'VS×ケイパビリティ関係'!$G$4:$G$494,E$5,'VS×ケイパビリティ関係'!$E$4:$E$494,"主")>0,"●",IF(COUNTIFS('VS×ケイパビリティ関係'!$F$4:$F$494,$B8,'VS×ケイパビリティ関係'!$G$4:$G$494,E$5,'VS×ケイパビリティ関係'!$E$4:$E$494,"支援")>0,"○","")) | F8: =IF(COUNTIFS('VS×ケイパビリティ関係'!$F$4:$F$494,$B8,'VS×ケイパビリティ関係'!$G$4:$G$494,F$5,'VS×ケイパビリティ関係'!$E$4:$E$494,"主")>0,"●",IF(COUNTIFS('VS×ケイパビリティ関係'!$F$4:$F$494,$B8,'VS×ケイパビリティ関係'!$G$4:$G$494,F$5,'VS×ケイパビリティ関係'!$E$4:$E$494,"支援")>0,"○","")) -> ○ | G8: =IF(COUNTIFS('VS×ケイパビリティ関係'!$F$4:$F$494,$B8,'VS×ケイパビリティ関係'!$G$4:$G$494,G$5,'VS×ケイパビリティ関係'!$E$4:$E$494,"主")>0,"●",IF(COUNTIFS('VS×ケイパビリティ関係'!$F$4:$F$494,$B8,'VS×ケイパビリティ関係'!$G$4:$G$494,G$5,'VS×ケイパビリティ関係'!$E$4:$E$494,"支援")>0,"○","")) | H8: =IF(COUNTIFS('VS×ケイパビリティ関係'!$F$4:$F$494,$B8,'VS×ケイパビリティ関係'!$G$4:$G$494,H$5,'VS×ケイパビリティ関係'!$E$4:$E$494,"主")>0,"●",IF(COUNTIFS('VS×ケイパビリティ関係'!$F$4:$F$494,$B8,'VS×ケイパビリティ関係'!$G$4:$G$494,H$5,'VS×ケイパビリティ関係'!$E$4:$E$494,"支援")>0,"○","")) -> ● | I8: =IF(COUNTIFS('VS×ケイパビリティ関係'!$F$4:$F$494,$B8,'VS×ケイパビリティ関係'!$G$4:$G$494,I$5,'VS×ケイパビリティ関係'!$E$4:$E$494,"主")>0,"●",IF(COUNTIFS('VS×ケイパビリティ関係'!$F$4:$F$494,$B8,'VS×ケイパビリティ関係'!$G$4:$G$494,I$5,'VS×ケイパビリティ関係'!$E$4:$E$494,"支援")>0,"○","")) | J8: =IF(COUNTIFS('VS×ケイパビリティ関係'!$F$4:$F$494,$B8,'VS×ケイパビリティ関係'!$G$4:$G$494,J$5,'VS×ケイパビリティ関係'!$E$4:$E$494,"主")>0,"●",IF(COUNTIFS('VS×ケイパビリティ関係'!$F$4:$F$494,$B8,'VS×ケイパビリティ関係'!$G$4:$G$494,J$5,'VS×ケイパビリティ関係'!$E$4:$E$494,"支援")>0,"○","")) | K8: =IF(COUNTIFS('VS×ケイパビリティ関係'!$F$4:$F$494,$B8,'VS×ケイパビリティ関係'!$G$4:$G$494,K$5,'VS×ケイパビリティ関係'!$E$4:$E$494,"主")>0,"●",IF(COUNTIFS('VS×ケイパビリティ関係'!$F$4:$F$494,$B8,'VS×ケイパビリティ関係'!$G$4:$G$494,K$5,'VS×ケイパビリティ関係'!$E$4:$E$494,"支援")>0,"○","")) | ... BD8: =IF(COUNTIFS('VS×ケイパビリティ関係'!$F$4:$F$494,$B8,'VS×ケイパビリティ関係'!$G$4:$G$494,BD$5,'VS×ケイパビリティ関係'!$E$4:$E$494,"主")>0,"●",IF(COUNTIFS('VS×ケイパビリティ関係'!$F$4:$F$494,$B8,'VS×ケイパビリティ関係'!$G$4:$G$494,BD$5,'VS×ケイパビリティ関係'!$E$4:$E$494,"支援")>0,"○","")) | BE8: =COUNTIF(D8:BD8,"●") -> 1 | BF8: =COUNTIF(D8:BD8,"○") -> 2
B9: 01-03 | C9: リード最適化 | D9: =IF(COUNTIFS('VS×ケイパビリティ関係'!$F$4:$F$494,$B9,'VS×ケイパビリティ関係'!$G$4:$G$494,D$5,'VS×ケイパビリティ関係'!$E$4:$E$494,"主")>0,"●",IF(COUNTIFS('VS×ケイパビリティ関係'!$F$4:$F$494,$B9,'VS×ケイパビリティ関係'!$G$4:$G$494,D$5,'VS×ケイパビリティ関係'!$E$4:$E$494,"支援")>0,"○","")) | E9: =IF(COUNTIFS('VS×ケイパビリティ関係'!$F$4:$F$494,$B9,'VS×ケイパビリティ関係'!$G$4:$G$494,E$5,'VS×ケイパビリティ関係'!$E$4:$E$494,"主")>0,"●",IF(COUNTIFS('VS×ケイパビリティ関係'!$F$4:$F$494,$B9,'VS×ケイパビリティ関係'!$G$4:$G$494,E$5,'VS×ケイパビリティ関係'!$E$4:$E$494,"支援")>0,"○","")) | F9: =IF(COUNTIFS('VS×ケイパビリティ関係'!$F$4:$F$494,$B9,'VS×ケイパビリティ関係'!$G$4:$G$494,F$5,'VS×ケイパビリティ関係'!$E$4:$E$494,"主")>0,"●",IF(COUNTIFS('VS×ケイパビリティ関係'!$F$4:$F$494,$B9,'VS×ケイパビリティ関係'!$G$4:$G$494,F$5,'VS×ケイパビリティ関係'!$E$4:$E$494,"支援")>0,"○","")) | G9: =IF(COUNTIFS('VS×ケイパビリティ関係'!$F$4:$F$494,$B9,'VS×ケイパビリティ関係'!$G$4:$G$494,G$5,'VS×ケイパビリティ関係'!$E$4:$E$494,"主")>0,"●",IF(COUNTIFS('VS×ケイパビリティ関係'!$F$4:$F$494,$B9,'VS×ケイパビリティ関係'!$G$4:$G$494,G$5,'VS×ケイパビリティ関係'!$E$4:$E$494,"支援")>0,"○","")) | H9: =IF(COUNTIFS('VS×ケイパビリティ関係'!$F$4:$F$494,$B9,'VS×ケイパビリティ関係'!$G$4:$G$494,H$5,'VS×ケイパビリティ関係'!$E$4:$E$494,"主")>0,"●",IF(COUNTIFS('VS×ケイパビリティ関係'!$F$4:$F$494,$B9,'VS×ケイパビリティ関係'!$G$4:$G$494,H$5,'VS×ケイパビリティ関係'!$E$4:$E$494,"支援")>0,"○","")) | I9: =IF(COUNTIFS('VS×ケイパビリティ関係'!$F$4:$F$494,$B9,'VS×ケイパビリティ関係'!$G$4:$G$494,I$5,'VS×ケイパビリティ関係'!$E$4:$E$494,"主")>0,"●",IF(COUNTIFS('VS×ケイパビリティ関係'!$F$4:$F$494,$B9,'VS×ケイパビリティ関係'!$G$4:$G$494,I$5,'VS×ケイパビリティ関係'!$E$4:$E$494,"支援")>0,"○","")) -> ● | J9: =IF(COUNTIFS('VS×ケイパビリティ関係'!$F$4:$F$494,$B9,'VS×ケイパビリティ関係'!$G$4:$G$494,J$5,'VS×ケイパビリティ関係'!$E$4:$E$494,"主")>0,"●",IF(COUNTIFS('VS×ケイパビリティ関係'!$F$4:$F$494,$B9,'VS×ケイパビリティ関係'!$G$4:$G$494,J$5,'VS×ケイパビリティ関係'!$E$4:$E$494,"支援")>0,"○","")) -> ● | K9: =IF(COUNTIFS('VS×ケイパビリティ関係'!$F$4:$F$494,$B9,'VS×ケイパビリティ関係'!$G$4:$G$494,K$5,'VS×ケイパビリティ関係'!$E$4:$E$494,"主")>0,"●",IF(COUNTIFS('VS×ケイパビリティ関係'!$F$4:$F$494,$B9,'VS×ケイパビリティ関係'!$G$4:$G$494,K$5,'VS×ケイパビリティ関係'!$E$4:$E$494,"支援")>0,"○","")) -> ● | ... BD9: =IF(COUNTIFS('VS×ケイパビリティ関係'!$F$4:$F$494,$B9,'VS×ケイパビリティ関係'!$G$4:$G$494,BD$5,'VS×ケイパビリティ関係'!$E$4:$E$494,"主")>0,"●",IF(COUNTIFS('VS×ケイパビリティ関係'!$F$4:$F$494,$B9,'VS×ケイパビリティ関係'!$G$4:$G$494,BD$5,'VS×ケイパビリティ関係'!$E$4:$E$494,"支援")>0,"○","")) | BE9: =COUNTIF(D9:BD9,"●") -> 3 | BF9: =COUNTIF(D9:BD9,"○") -> 1
B10: 01-04 | C10: 開発候補品選定 | D10: =IF(COUNTIFS('VS×ケイパビリティ関係'!$F$4:$F$494,$B10,'VS×ケイパビリティ関係'!$G$4:$G$494,D$5,'VS×ケイパビリティ関係'!$E$4:$E$494,"主")>0,"●",IF(COUNTIFS('VS×ケイパビリティ関係'!$F$4:$F$494,$B10,'VS×ケイパビリティ関係'!$G$4:$G$494,D$5,'VS×ケイパビリティ関係'!$E$4:$E$494,"支援")>0,"○","")) -> ● | E10: =IF(COUNTIFS('VS×ケイパビリティ関係'!$F$4:$F$494,$B10,'VS×ケイパビリティ関係'!$G$4:$G$494,E$5,'VS×ケイパビリティ関係'!$E$4:$E$494,"主")>0,"●",IF(COUNTIFS('VS×ケイパビリティ関係'!$F$4:$F$494,$B10,'VS×ケイパビリティ関係'!$G$4:$G$494,E$5,'VS×ケイパビリティ関係'!$E$4:$E$494,"支援")>0,"○","")) -> ● | F10: =IF(COUNTIFS('VS×ケイパビリティ関係'!$F$4:$F$494,$B10,'VS×ケイパビリティ関係'!$G$4:$G$494,F$5,'VS×ケイパビリティ関係'!$E$4:$E$494,"主")>0,"●",IF(COUNTIFS('VS×ケイパビリティ関係'!$F$4:$F$494,$B10,'VS×ケイパビリティ関係'!$G$4:$G$494,F$5,'VS×ケイパビリティ関係'!$E$4:$E$494,"支援")>0,"○","")) | G10: =IF(COUNTIFS('VS×ケイパビリティ関係'!$F$4:$F$494,$B10,'VS×ケイパビリティ関係'!$G$4:$G$494,G$5,'VS×ケイパビリティ関係'!$E$4:$E$494,"主")>0,"●",IF(COUNTIFS('VS×ケイパビリティ関係'!$F$4:$F$494,$B10,'VS×ケイパビリティ関係'!$G$4:$G$494,G$5,'VS×ケイパビリティ関係'!$E$4:$E$494,"支援")>0,"○","")) | H10: =IF(COUNTIFS('VS×ケイパビリティ関係'!$F$4:$F$494,$B10,'VS×ケイパビリティ関係'!$G$4:$G$494,H$5,'VS×ケイパビリティ関係'!$E$4:$E$494,"主")>0,"●",IF(COUNTIFS('VS×ケイパビリティ関係'!$F$4:$F$494,$B10,'VS×ケイパビリティ関係'!$G$4:$G$494,H$5,'VS×ケイパビリティ関係'!$E$4:$E$494,"支援")>0,"○","")) | I10: =IF(COUNTIFS('VS×ケイパビリティ関係'!$F$4:$F$494,$B10,'VS×ケイパビリティ関係'!$G$4:$G$494,I$5,'VS×ケイパビリティ関係'!$E$4:$E$494,"主")>0,"●",IF(COUNTIFS('VS×ケイパビリティ関係'!$F$4:$F$494,$B10,'VS×ケイパビリティ関係'!$G$4:$G$494,I$5,'VS×ケイパビリティ関係'!$E$4:$E$494,"支援")>0,"○","")) | J10: =IF(COUNTIFS('VS×ケイパビリティ関係'!$F$4:$F$494,$B10,'VS×ケイパビリティ関係'!$G$4:$G$494,J$5,'VS×ケイパビリティ関係'!$E$4:$E$494,"主")>0,"●",IF(COUNTIFS('VS×ケイパビリティ関係'!$F$4:$F$494,$B10,'VS×ケイパビリティ関係'!$G$4:$G$494,J$5,'VS×ケイパビリティ関係'!$E$4:$E$494,"支援")>0,"○","")) | K10: =IF(COUNTIFS('VS×ケイパビリティ関係'!$F$4:$F$494,$B10,'VS×ケイパビリティ関係'!$G$4:$G$494,K$5,'VS×ケイパビリティ関係'!$E$4:$E$494,"主")>0,"●",IF(COUNTIFS('VS×ケイパビリティ関係'!$F$4:$F$494,$B10,'VS×ケイパビリティ関係'!$G$4:$G$494,K$5,'VS×ケイパビリティ関係'!$E$4:$E$494,"支援")>0,"○","")) | ... BD10: =IF(COUNTIFS('VS×ケイパビリティ関係'!$F$4:$F$494,$B10,'VS×ケイパビリティ関係'!$G$4:$G$494,BD$5,'VS×ケイパビリティ関係'!$E$4:$E$494,"主")>0,"●",IF(COUNTIFS('VS×ケイパビリティ関係'!$F$4:$F$494,$B10,'VS×ケイパビリティ関係'!$G$4:$G$494,BD$5,'VS×ケイパビリティ関係'!$E$4:$E$494,"支援")>0,"○","")) | BE10: =COUNTIF(D10:BD10,"●") -> 3 | BF10: =COUNTIF(D10:BD10,"○") -> 1
A11: 02 非臨床開発 | B11: 02-01 | C11: 非臨床薬理 | D11: =IF(COUNTIFS('VS×ケイパビリティ関係'!$F$4:$F$494,$B11,'VS×ケイパビリティ関係'!$G$4:$G$494,D$5,'VS×ケイパビリティ関係'!$E$4:$E$494,"主")>0,"●",IF(COUNTIFS('VS×ケイパビリティ関係'!$F$4:$F$494,$B11,'VS×ケイパビリティ関係'!$G$4:$G$494,D$5,'VS×ケイパビリティ関係'!$E$4:$E$494,"支援")>0,"○","")) | E11: =IF(COUNTIFS('VS×ケイパビリティ関係'!$F$4:$F$494,$B11,'VS×ケイパビリティ関係'!$G$4:$G$494,E$5,'VS×ケイパビリティ関係'!$E$4:$E$494,"主")>0,"●",IF(COUNTIFS('VS×ケイパビリティ関係'!$F$4:$F$494,$B11,'VS×ケイパビリティ関係'!$G$4:$G$494,E$5,'VS×ケイパビリティ関係'!$E$4:$E$494,"支援")>0,"○","")) | F11: =IF(COUNTIFS('VS×ケイパビリティ関係'!$F$4:$F$494,$B11,'VS×ケイパビリティ関係'!$G$4:$G$494,F$5,'VS×ケイパビリティ関係'!$E$4:$E$494,"主")>0,"●",IF(COUNTIFS('VS×ケイパビリティ関係'!$F$4:$F$494,$B11,'VS×ケイパビリティ関係'!$G$4:$G$494,F$5,'VS×ケイパビリティ関係'!$E$4:$E$494,"支援")>0,"○","")) -> ○ | G11: =IF(COUNTIFS('VS×ケイパビリティ関係'!$F$4:$F$494,$B11,'VS×ケイパビリティ関係'!$G$4:$G$494,G$5,'VS×ケイパビリティ関係'!$E$4:$E$494,"主")>0,"●",IF(COUNTIFS('VS×ケイパビリティ関係'!$F$4:$F$494,$B11,'VS×ケイパビリティ関係'!$G$4:$G$494,G$5,'VS×ケイパビリティ関係'!$E$4:$E$494,"支援")>0,"○","")) | H11: =IF(COUNTIFS('VS×ケイパビリティ関係'!$F$4:$F$494,$B11,'VS×ケイパビリティ関係'!$G$4:$G$494,H$5,'VS×ケイパビリティ関係'!$E$4:$E$494,"主")>0,"●",IF(COUNTIFS('VS×ケイパビリティ関係'!$F$4:$F$494,$B11,'VS×ケイパビリティ関係'!$G$4:$G$494,H$5,'VS×ケイパビリティ関係'!$E$4:$E$494,"支援")>0,"○","")) | I11: =IF(COUNTIFS('VS×ケイパビリティ関係'!$F$4:$F$494,$B11,'VS×ケイパビリティ関係'!$G$4:$G$494,I$5,'VS×ケイパビリティ関係'!$E$4:$E$494,"主")>0,"●",IF(COUNTIFS('VS×ケイパビリティ関係'!$F$4:$F$494,$B11,'VS×ケイパビリティ関係'!$G$4:$G$494,I$5,'VS×ケイパビリティ関係'!$E$4:$E$494,"支援")>0,"○","")) | J11: =IF(COUNTIFS('VS×ケイパビリティ関係'!$F$4:$F$494,$B11,'VS×ケイパビリティ関係'!$G$4:$G$494,J$5,'VS×ケイパビリティ関係'!$E$4:$E$494,"主")>0,"●",IF(COUNTIFS('VS×ケイパビリティ関係'!$F$4:$F$494,$B11,'VS×ケイパビリティ関係'!$G$4:$G$494,J$5,'VS×ケイパビリティ関係'!$E$4:$E$494,"支援")>0,"○","")) -> ○ | K11: =IF(COUNTIFS('VS×ケイパビリティ関係'!$F$4:$F$494,$B11,'VS×ケイパビリティ関係'!$G$4:$G$494,K$5,'VS×ケイパビリティ関係'!$E$4:$E$494,"主")>0,"●",IF(COUNTIFS('VS×ケイパビリティ関係'!$F$4:$F$494,$B11,'VS×ケイパビリティ関係'!$G$4:$G$494,K$5,'VS×ケイパビリティ関係'!$E$4:$E$494,"支援")>0,"○","")) | ... BD11: =IF(COUNTIFS('VS×ケイパビリティ関係'!$F$4:$F$494,$B11,'VS×ケイパビリティ関係'!$G$4:$G$494,BD$5,'VS×ケイパビリティ関係'!$E$4:$E$494,"主")>0,"●",IF(COUNTIFS('VS×ケイパビリティ関係'!$F$4:$F$494,$B11,'VS×ケイパビリティ関係'!$G$4:$G$494,BD$5,'VS×ケイパビリティ関係'!$E$4:$E$494,"支援")>0,"○","")) | BE11: =COUNTIF(D11:BD11,"●") -> 1 | BF11: =COUNTIF(D11:BD11,"○") -> 2
B12: 02-02 | C12: 薬物動態・免疫原性評価 | D12: =IF(COUNTIFS('VS×ケイパビリティ関係'!$F$4:$F$494,$B12,'VS×ケイパビリティ関係'!$G$4:$G$494,D$5,'VS×ケイパビリティ関係'!$E$4:$E$494,"主")>0,"●",IF(COUNTIFS('VS×ケイパビリティ関係'!$F$4:$F$494,$B12,'VS×ケイパビリティ関係'!$G$4:$G$494,D$5,'VS×ケイパビリティ関係'!$E$4:$E$494,"支援")>0,"○","")) | E12: =IF(COUNTIFS('VS×ケイパビリティ関係'!$F$4:$F$494,$B12,'VS×ケイパビリティ関係'!$G$4:$G$494,E$5,'VS×ケイパビリティ関係'!$E$4:$E$494,"主")>0,"●",IF(COUNTIFS('VS×ケイパビリティ関係'!$F$4:$F$494,$B12,'VS×ケイパビリティ関係'!$G$4:$G$494,E$5,'VS×ケイパビリティ関係'!$E$4:$E$494,"支援")>0,"○","")) | F12: =IF(COUNTIFS('VS×ケイパビリティ関係'!$F$4:$F$494,$B12,'VS×ケイパビリティ関係'!$G$4:$G$494,F$5,'VS×ケイパビリティ関係'!$E$4:$E$494,"主")>0,"●",IF(COUNTIFS('VS×ケイパビリティ関係'!$F$4:$F$494,$B12,'VS×ケイパビリティ関係'!$G$4:$G$494,F$5,'VS×ケイパビリティ関係'!$E$4:$E$494,"支援")>0,"○","")) -> ○ | G12: =IF(COUNTIFS('VS×ケイパビリティ関係'!$F$4:$F$494,$B12,'VS×ケイパビリティ関係'!$G$4:$G$494,G$5,'VS×ケイパビリティ関係'!$E$4:$E$494,"主")>0,"●",IF(COUNTIFS('VS×ケイパビリティ関係'!$F$4:$F$494,$B12,'VS×ケイパビリティ関係'!$G$4:$G$494,G$5,'VS×ケイパビリティ関係'!$E$4:$E$494,"支援")>0,"○","")) | H12: =IF(COUNTIFS('VS×ケイパビリティ関係'!$F$4:$F$494,$B12,'VS×ケイパビリティ関係'!$G$4:$G$494,H$5,'VS×ケイパビリティ関係'!$E$4:$E$494,"主")>0,"●",IF(COUNTIFS('VS×ケイパビリティ関係'!$F$4:$F$494,$B12,'VS×ケイパビリティ関係'!$G$4:$G$494,H$5,'VS×ケイパビリティ関係'!$E$4:$E$494,"支援")>0,"○","")) | I12: =IF(COUNTIFS('VS×ケイパビリティ関係'!$F$4:$F$494,$B12,'VS×ケイパビリティ関係'!$G$4:$G$494,I$5,'VS×ケイパビリティ関係'!$E$4:$E$494,"主")>0,"●",IF(COUNTIFS('VS×ケイパビリティ関係'!$F$4:$F$494,$B12,'VS×ケイパビリティ関係'!$G$4:$G$494,I$5,'VS×ケイパビリティ関係'!$E$4:$E$494,"支援")>0,"○","")) | J12: =IF(COUNTIFS('VS×ケイパビリティ関係'!$F$4:$F$494,$B12,'VS×ケイパビリティ関係'!$G$4:$G$494,J$5,'VS×ケイパビリティ関係'!$E$4:$E$494,"主")>0,"●",IF(COUNTIFS('VS×ケイパビリティ関係'!$F$4:$F$494,$B12,'VS×ケイパビリティ関係'!$G$4:$G$494,J$5,'VS×ケイパビリティ関係'!$E$4:$E$494,"支援")>0,"○","")) | K12: =IF(COUNTIFS('VS×ケイパビリティ関係'!$F$4:$F$494,$B12,'VS×ケイパビリティ関係'!$G$4:$G$494,K$5,'VS×ケイパビリティ関係'!$E$4:$E$494,"主")>0,"●",IF(COUNTIFS('VS×ケイパビリティ関係'!$F$4:$F$494,$B12,'VS×ケイパビリティ関係'!$G$4:$G$494,K$5,'VS×ケイパビリティ関係'!$E$4:$E$494,"支援")>0,"○","")) | ... BD12: =IF(COUNTIFS('VS×ケイパビリティ関係'!$F$4:$F$494,$B12,'VS×ケイパビリティ関係'!$G$4:$G$494,BD$5,'VS×ケイパビリティ関係'!$E$4:$E$494,"主")>0,"●",IF(COUNTIFS('VS×ケイパビリティ関係'!$F$4:$F$494,$B12,'VS×ケイパビリティ関係'!$G$4:$G$494,BD$5,'VS×ケイパビリティ関係'!$E$4:$E$494,"支援")>0,"○","")) | BE12: =COUNTIF(D12:BD12,"●") -> 2 | BF12: =COUNTIF(D12:BD12,"○") -> 1
B13: 02-03 | C13: 安全性評価 | D13: =IF(COUNTIFS('VS×ケイパビリティ関係'!$F$4:$F$494,$B13,'VS×ケイパビリティ関係'!$G$4:$G$494,D$5,'VS×ケイパビリティ関係'!$E$4:$E$494,"主")>0,"●",IF(COUNTIFS('VS×ケイパビリティ関係'!$F$4:$F$494,$B13,'VS×ケイパビリティ関係'!$G$4:$G$494,D$5,'VS×ケイパビリティ関係'!$E$4:$E$494,"支援")>0,"○","")) | E13: =IF(COUNTIFS('VS×ケイパビリティ関係'!$F$4:$F$494,$B13,'VS×ケイパビリティ関係'!$G$4:$G$494,E$5,'VS×ケイパビリティ関係'!$E$4:$E$494,"主")>0,"●",IF(COUNTIFS('VS×ケイパビリティ関係'!$F$4:$F$494,$B13,'VS×ケイパビリティ関係'!$G$4:$G$494,E$5,'VS×ケイパビリティ関係'!$E$4:$E$494,"支援")>0,"○","")) | F13: =IF(COUNTIFS('VS×ケイパビリティ関係'!$F$4:$F$494,$B13,'VS×ケイパビリティ関係'!$G$4:$G$494,F$5,'VS×ケイパビリティ関係'!$E$4:$E$494,"主")>0,"●",IF(COUNTIFS('VS×ケイパビリティ関係'!$F$4:$F$494,$B13,'VS×ケイパビリティ関係'!$G$4:$G$494,F$5,'VS×ケイパビリティ関係'!$E$4:$E$494,"支援")>0,"○","")) -> ○ | G13: =IF(COUNTIFS('VS×ケイパビリティ関係'!$F$4:$F$494,$B13,'VS×ケイパビリティ関係'!$G$4:$G$494,G$5,'VS×ケイパビリティ関係'!$E$4:$E$494,"主")>0,"●",IF(COUNTIFS('VS×ケイパビリティ関係'!$F$4:$F$494,$B13,'VS×ケイパビリティ関係'!$G$4:$G$494,G$5,'VS×ケイパビリティ関係'!$E$4:$E$494,"支援")>0,"○","")) | H13: =IF(COUNTIFS('VS×ケイパビリティ関係'!$F$4:$F$494,$B13,'VS×ケイパビリティ関係'!$G$4:$G$494,H$5,'VS×ケイパビリティ関係'!$E$4:$E$494,"主")>0,"●",IF(COUNTIFS('VS×ケイパビリティ関係'!$F$4:$F$494,$B13,'VS×ケイパビリティ関係'!$G$4:$G$494,H$5,'VS×ケイパビリティ関係'!$E$4:$E$494,"支援")>0,"○","")) | I13: =IF(COUNTIFS('VS×ケイパビリティ関係'!$F$4:$F$494,$B13,'VS×ケイパビリティ関係'!$G$4:$G$494,I$5,'VS×ケイパビリティ関係'!$E$4:$E$494,"主")>0,"●",IF(COUNTIFS('VS×ケイパビリティ関係'!$F$4:$F$494,$B13,'VS×ケイパビリティ関係'!$G$4:$G$494,I$5,'VS×ケイパビリティ関係'!$E$4:$E$494,"支援")>0,"○","")) | J13: =IF(COUNTIFS('VS×ケイパビリティ関係'!$F$4:$F$494,$B13,'VS×ケイパビリティ関係'!$G$4:$G$494,J$5,'VS×ケイパビリティ関係'!$E$4:$E$494,"主")>0,"●",IF(COUNTIFS('VS×ケイパビリティ関係'!$F$4:$F$494,$B13,'VS×ケイパビリティ関係'!$G$4:$G$494,J$5,'VS×ケイパビリティ関係'!$E$4:$E$494,"支援")>0,"○","")) | K13: =IF(COUNTIFS('VS×ケイパビリティ関係'!$F$4:$F$494,$B13,'VS×ケイパビリティ関係'!$G$4:$G$494,K$5,'VS×ケイパビリティ関係'!$E$4:$E$494,"主")>0,"●",IF(COUNTIFS('VS×ケイパビリティ関係'!$F$4:$F$494,$B13,'VS×ケイパビリティ関係'!$G$4:$G$494,K$5,'VS×ケイパビリティ関係'!$E$4:$E$494,"支援")>0,"○","")) | ... BD13: =IF(COUNTIFS('VS×ケイパビリティ関係'!$F$4:$F$494,$B13,'VS×ケイパビリティ関係'!$G$4:$G$494,BD$5,'VS×ケイパビリティ関係'!$E$4:$E$494,"主")>0,"●",IF(COUNTIFS('VS×ケイパビリティ関係'!$F$4:$F$494,$B13,'VS×ケイパビリティ関係'!$G$4:$G$494,BD$5,'VS×ケイパビリティ関係'!$E$4:$E$494,"支援")>0,"○","")) | BE13: =COUNTIF(D13:BD13,"●") -> 1 | BF13: =COUNTIF(D13:BD13,"○") -> 2
B14: 02-04 | C14: 初回ヒト投与量の設定・IND申請 | D14: =IF(COUNTIFS('VS×ケイパビリティ関係'!$F$4:$F$494,$B14,'VS×ケイパビリティ関係'!$G$4:$G$494,D$5,'VS×ケイパビリティ関係'!$E$4:$E$494,"主")>0,"●",IF(COUNTIFS('VS×ケイパビリティ関係'!$F$4:$F$494,$B14,'VS×ケイパビリティ関係'!$G$4:$G$494,D$5,'VS×ケイパビリティ関係'!$E$4:$E$494,"支援")>0,"○","")) -> ○ | E14: =IF(COUNTIFS('VS×ケイパビリティ関係'!$F$4:$F$494,$B14,'VS×ケイパビリティ関係'!$G$4:$G$494,E$5,'VS×ケイパビリティ関係'!$E$4:$E$494,"主")>0,"●",IF(COUNTIFS('VS×ケイパビリティ関係'!$F$4:$F$494,$B14,'VS×ケイパビリティ関係'!$G$4:$G$494,E$5,'VS×ケイパビリティ関係'!$E$4:$E$494,"支援")>0,"○","")) | F14: =IF(COUNTIFS('VS×ケイパビリティ関係'!$F$4:$F$494,$B14,'VS×ケイパビリティ関係'!$G$4:$G$494,F$5,'VS×ケイパビリティ関係'!$E$4:$E$494,"主")>0,"●",IF(COUNTIFS('VS×ケイパビリティ関係'!$F$4:$F$494,$B14,'VS×ケイパビリティ関係'!$G$4:$G$494,F$5,'VS×ケイパビリティ関係'!$E$4:$E$494,"支援")>0,"○","")) | G14: =IF(COUNTIFS('VS×ケイパビリティ関係'!$F$4:$F$494,$B14,'VS×ケイパビリティ関係'!$G$4:$G$494,G$5,'VS×ケイパビリティ関係'!$E$4:$E$494,"主")>0,"●",IF(COUNTIFS('VS×ケイパビリティ関係'!$F$4:$F$494,$B14,'VS×ケイパビリティ関係'!$G$4:$G$494,G$5,'VS×ケイパビリティ関係'!$E$4:$E$494,"支援")>0,"○","")) | H14: =IF(COUNTIFS('VS×ケイパビリティ関係'!$F$4:$F$494,$B14,'VS×ケイパビリティ関係'!$G$4:$G$494,H$5,'VS×ケイパビリティ関係'!$E$4:$E$494,"主")>0,"●",IF(COUNTIFS('VS×ケイパビリティ関係'!$F$4:$F$494,$B14,'VS×ケイパビリティ関係'!$G$4:$G$494,H$5,'VS×ケイパビリティ関係'!$E$4:$E$494,"支援")>0,"○","")) | I14: =IF(COUNTIFS('VS×ケイパビリティ関係'!$F$4:$F$494,$B14,'VS×ケイパビリティ関係'!$G$4:$G$494,I$5,'VS×ケイパビリティ関係'!$E$4:$E$494,"主")>0,"●",IF(COUNTIFS('VS×ケイパビリティ関係'!$F$4:$F$494,$B14,'VS×ケイパビリティ関係'!$G$4:$G$494,I$5,'VS×ケイパビリティ関係'!$E$4:$E$494,"支援")>0,"○","")) | J14: =IF(COUNTIFS('VS×ケイパビリティ関係'!$F$4:$F$494,$B14,'VS×ケイパビリティ関係'!$G$4:$G$494,J$5,'VS×ケイパビリティ関係'!$E$4:$E$494,"主")>0,"●",IF(COUNTIFS('VS×ケイパビリティ関係'!$F$4:$F$494,$B14,'VS×ケイパビリティ関係'!$G$4:$G$494,J$5,'VS×ケイパビリティ関係'!$E$4:$E$494,"支援")>0,"○","")) | K14: =IF(COUNTIFS('VS×ケイパビリティ関係'!$F$4:$F$494,$B14,'VS×ケイパビリティ関係'!$G$4:$G$494,K$5,'VS×ケイパビリティ関係'!$E$4:$E$494,"主")>0,"●",IF(COUNTIFS('VS×ケイパビリティ関係'!$F$4:$F$494,$B14,'VS×ケイパビリティ関係'!$G$4:$G$494,K$5,'VS×ケイパビリティ関係'!$E$4:$E$494,"支援")>0,"○","")) | ... BD14: =IF(COUNTIFS('VS×ケイパビリティ関係'!$F$4:$F$494,$B14,'VS×ケイパビリティ関係'!$G$4:$G$494,BD$5,'VS×ケイパビリティ関係'!$E$4:$E$494,"主")>0,"●",IF(COUNTIFS('VS×ケイパビリティ関係'!$F$4:$F$494,$B14,'VS×ケイパビリティ関係'!$G$4:$G$494,BD$5,'VS×ケイパビリティ関係'!$E$4:$E$494,"支援")>0,"○","")) | BE14: =COUNTIF(D14:BD14,"●") -> 4 | BF14: =COUNTIF(D14:BD14,"○") -> 2
A15: 03 CMC開発（臨床と並行） | B15: 03-01 | C15: 細胞株構築・セルバンク | D15: =IF(COUNTIFS('VS×ケイパビリティ関係'!$F$4:$F$494,$B15,'VS×ケイパビリティ関係'!$G$4:$G$494,D$5,'VS×ケイパビリティ関係'!$E$4:$E$494,"主")>0,"●",IF(COUNTIFS('VS×ケイパビリティ関係'!$F$4:$F$494,$B15,'VS×ケイパビリティ関係'!$G$4:$G$494,D$5,'VS×ケイパビリティ関係'!$E$4:$E$494,"支援")>0,"○","")) | E15: =IF(COUNTIFS('VS×ケイパビリティ関係'!$F$4:$F$494,$B15,'VS×ケイパビリティ関係'!$G$4:$G$494,E$5,'VS×ケイパビリティ関係'!$E$4:$E$494,"主")>0,"●",IF(COUNTIFS('VS×ケイパビリティ関係'!$F$4:$F$494,$B15,'VS×ケイパビリティ関係'!$G$4:$G$494,E$5,'VS×ケイパビリティ関係'!$E$4:$E$494,"支援")>0,"○","")) | F15: =IF(COUNTIFS('VS×ケイパビリティ関係'!$F$4:$F$494,$B15,'VS×ケイパビリティ関係'!$G$4:$G$494,F$5,'VS×ケイパビリティ関係'!$E$4:$E$494,"主")>0,"●",IF(COUNTIFS('VS×ケイパビリティ関係'!$F$4:$F$494,$B15,'VS×ケイパビリティ関係'!$G$4:$G$494,F$5,'VS×ケイパビリティ関係'!$E$4:$E$494,"支援")>0,"○","")) -> ○ | G15: =IF(COUNTIFS('VS×ケイパビリティ関係'!$F$4:$F$494,$B15,'VS×ケイパビリティ関係'!$G$4:$G$494,G$5,'VS×ケイパビリティ関係'!$E$4:$E$494,"主")>0,"●",IF(COUNTIFS('VS×ケイパビリティ関係'!$F$4:$F$494,$B15,'VS×ケイパビリティ関係'!$G$4:$G$494,G$5,'VS×ケイパビリティ関係'!$E$4:$E$494,"支援")>0,"○","")) | H15: =IF(COUNTIFS('VS×ケイパビリティ関係'!$F$4:$F$494,$B15,'VS×ケイパビリティ関係'!$G$4:$G$494,H$5,'VS×ケイパビリティ関係'!$E$4:$E$494,"主")>0,"●",IF(COUNTIFS('VS×ケイパビリティ関係'!$F$4:$F$494,$B15,'VS×ケイパビリティ関係'!$G$4:$G$494,H$5,'VS×ケイパビリティ関係'!$E$4:$E$494,"支援")>0,"○","")) | I15: =IF(COUNTIFS('VS×ケイパビリティ関係'!$F$4:$F$494,$B15,'VS×ケイパビリティ関係'!$G$4:$G$494,I$5,'VS×ケイパビリティ関係'!$E$4:$E$494,"主")>0,"●",IF(COUNTIFS('VS×ケイパビリティ関係'!$F$4:$F$494,$B15,'VS×ケイパビリティ関係'!$G$4:$G$494,I$5,'VS×ケイパビリティ関係'!$E$4:$E$494,"支援")>0,"○","")) | J15: =IF(COUNTIFS('VS×ケイパビリティ関係'!$F$4:$F$494,$B15,'VS×ケイパビリティ関係'!$G$4:$G$494,J$5,'VS×ケイパビリティ関係'!$E$4:$E$494,"主")>0,"●",IF(COUNTIFS('VS×ケイパビリティ関係'!$F$4:$F$494,$B15,'VS×ケイパビリティ関係'!$G$4:$G$494,J$5,'VS×ケイパビリティ関係'!$E$4:$E$494,"支援")>0,"○","")) | K15: =IF(COUNTIFS('VS×ケイパビリティ関係'!$F$4:$F$494,$B15,'VS×ケイパビリティ関係'!$G$4:$G$494,K$5,'VS×ケイパビリティ関係'!$E$4:$E$494,"主")>0,"●",IF(COUNTIFS('VS×ケイパビリティ関係'!$F$4:$F$494,$B15,'VS×ケイパビリティ関係'!$G$4:$G$494,K$5,'VS×ケイパビリティ関係'!$E$4:$E$494,"支援")>0,"○","")) | ... BD15: =IF(COUNTIFS('VS×ケイパビリティ関係'!$F$4:$F$494,$B15,'VS×ケイパビリティ関係'!$G$4:$G$494,BD$5,'VS×ケイパビリティ関係'!$E$4:$E$494,"主")>0,"●",IF(COUNTIFS('VS×ケイパビリティ関係'!$F$4:$F$494,$B15,'VS×ケイパビリティ関係'!$G$4:$G$494,BD$5,'VS×ケイパビリティ関係'!$E$4:$E$494,"支援")>0,"○","")) | BE15: =COUNTIF(D15:BD15,"●") -> 1 | BF15: =COUNTIF(D15:BD15,"○") -> 3
B16: 03-02 | C16: 原薬プロセス開発 | D16: =IF(COUNTIFS('VS×ケイパビリティ関係'!$F$4:$F$494,$B16,'VS×ケイパビリティ関係'!$G$4:$G$494,D$5,'VS×ケイパビリティ関係'!$E$4:$E$494,"主")>0,"●",IF(COUNTIFS('VS×ケイパビリティ関係'!$F$4:$F$494,$B16,'VS×ケイパビリティ関係'!$G$4:$G$494,D$5,'VS×ケイパビリティ関係'!$E$4:$E$494,"支援")>0,"○","")) | E16: =IF(COUNTIFS('VS×ケイパビリティ関係'!$F$4:$F$494,$B16,'VS×ケイパビリティ関係'!$G$4:$G$494,E$5,'VS×ケイパビリティ関係'!$E$4:$E$494,"主")>0,"●",IF(COUNTIFS('VS×ケイパビリティ関係'!$F$4:$F$494,$B16,'VS×ケイパビリティ関係'!$G$4:$G$494,E$5,'VS×ケイパビリティ関係'!$E$4:$E$494,"支援")>0,"○","")) | F16: =IF(COUNTIFS('VS×ケイパビリティ関係'!$F$4:$F$494,$B16,'VS×ケイパビリティ関係'!$G$4:$G$494,F$5,'VS×ケイパビリティ関係'!$E$4:$E$494,"主")>0,"●",IF(COUNTIFS('VS×ケイパビリティ関係'!$F$4:$F$494,$B16,'VS×ケイパビリティ関係'!$G$4:$G$494,F$5,'VS×ケイパビリティ関係'!$E$4:$E$494,"支援")>0,"○","")) | G16: =IF(COUNTIFS('VS×ケイパビリティ関係'!$F$4:$F$494,$B16,'VS×ケイパビリティ関係'!$G$4:$G$494,G$5,'VS×ケイパビリティ関係'!$E$4:$E$494,"主")>0,"●",IF(COUNTIFS('VS×ケイパビリティ関係'!$F$4:$F$494,$B16,'VS×ケイパビリティ関係'!$G$4:$G$494,G$5,'VS×ケイパビリティ関係'!$E$4:$E$494,"支援")>0,"○","")) | H16: =IF(COUNTIFS('VS×ケイパビリティ関係'!$F$4:$F$494,$B16,'VS×ケイパビリティ関係'!$G$4:$G$494,H$5,'VS×ケイパビリティ関係'!$E$4:$E$494,"主")>0,"●",IF(COUNTIFS('VS×ケイパビリティ関係'!$F$4:$F$494,$B16,'VS×ケイパビリティ関係'!$G$4:$G$494,H$5,'VS×ケイパビリティ関係'!$E$4:$E$494,"支援")>0,"○","")) | I16: =IF(COUNTIFS('VS×ケイパビリティ関係'!$F$4:$F$494,$B16,'VS×ケイパビリティ関係'!$G$4:$G$494,I$5,'VS×ケイパビリティ関係'!$E$4:$E$494,"主")>0,"●",IF(COUNTIFS('VS×ケイパビリティ関係'!$F$4:$F$494,$B16,'VS×ケイパビリティ関係'!$G$4:$G$494,I$5,'VS×ケイパビリティ関係'!$E$4:$E$494,"支援")>0,"○","")) | J16: =IF(COUNTIFS('VS×ケイパビリティ関係'!$F$4:$F$494,$B16,'VS×ケイパビリティ関係'!$G$4:$G$494,J$5,'VS×ケイパビリティ関係'!$E$4:$E$494,"主")>0,"●",IF(COUNTIFS('VS×ケイパビリティ関係'!$F$4:$F$494,$B16,'VS×ケイパビリティ関係'!$G$4:$G$494,J$5,'VS×ケイパビリティ関係'!$E$4:$E$494,"支援")>0,"○","")) | K16: =IF(COUNTIFS('VS×ケイパビリティ関係'!$F$4:$F$494,$B16,'VS×ケイパビリティ関係'!$G$4:$G$494,K$5,'VS×ケイパビリティ関係'!$E$4:$E$494,"主")>0,"●",IF(COUNTIFS('VS×ケイパビリティ関係'!$F$4:$F$494,$B16,'VS×ケイパビリティ関係'!$G$4:$G$494,K$5,'VS×ケイパビリティ関係'!$E$4:$E$494,"支援")>0,"○","")) | ... BD16: =IF(COUNTIFS('VS×ケイパビリティ関係'!$F$4:$F$494,$B16,'VS×ケイパビリティ関係'!$G$4:$G$494,BD$5,'VS×ケイパビリティ関係'!$E$4:$E$494,"主")>0,"●",IF(COUNTIFS('VS×ケイパビリティ関係'!$F$4:$F$494,$B16,'VS×ケイパビリティ関係'!$G$4:$G$494,BD$5,'VS×ケイパビリティ関係'!$E$4:$E$494,"支援")>0,"○","")) | BE16: =COUNTIF(D16:BD16,"●") -> 2 | BF16: =COUNTIF(D16:BD16,"○") -> 0
B17: 03-03 | C17: 製剤開発 | D17: =IF(COUNTIFS('VS×ケイパビリティ関係'!$F$4:$F$494,$B17,'VS×ケイパビリティ関係'!$G$4:$G$494,D$5,'VS×ケイパビリティ関係'!$E$4:$E$494,"主")>0,"●",IF(COUNTIFS('VS×ケイパビリティ関係'!$F$4:$F$494,$B17,'VS×ケイパビリティ関係'!$G$4:$G$494,D$5,'VS×ケイパビリティ関係'!$E$4:$E$494,"支援")>0,"○","")) | E17: =IF(COUNTIFS('VS×ケイパビリティ関係'!$F$4:$F$494,$B17,'VS×ケイパビリティ関係'!$G$4:$G$494,E$5,'VS×ケイパビリティ関係'!$E$4:$E$494,"主")>0,"●",IF(COUNTIFS('VS×ケイパビリティ関係'!$F$4:$F$494,$B17,'VS×ケイパビリティ関係'!$G$4:$G$494,E$5,'VS×ケイパビリティ関係'!$E$4:$E$494,"支援")>0,"○","")) | F17: =IF(COUNTIFS('VS×ケイパビリティ関係'!$F$4:$F$494,$B17,'VS×ケイパビリティ関係'!$G$4:$G$494,F$5,'VS×ケイパビリティ関係'!$E$4:$E$494,"主")>0,"●",IF(COUNTIFS('VS×ケイパビリティ関係'!$F$4:$F$494,$B17,'VS×ケイパビリティ関係'!$G$4:$G$494,F$5,'VS×ケイパビリティ関係'!$E$4:$E$494,"支援")>0,"○","")) | G17: =IF(COUNTIFS('VS×ケイパビリティ関係'!$F$4:$F$494,$B17,'VS×ケイパビリティ関係'!$G$4:$G$494,G$5,'VS×ケイパビリティ関係'!$E$4:$E$494,"主")>0,"●",IF(COUNTIFS('VS×ケイパビリティ関係'!$F$4:$F$494,$B17,'VS×ケイパビリティ関係'!$G$4:$G$494,G$5,'VS×ケイパビリティ関係'!$E$4:$E$494,"支援")>0,"○","")) | H17: =IF(COUNTIFS('VS×ケイパビリティ関係'!$F$4:$F$494,$B17,'VS×ケイパビリティ関係'!$G$4:$G$494,H$5,'VS×ケイパビリティ関係'!$E$4:$E$494,"主")>0,"●",IF(COUNTIFS('VS×ケイパビリティ関係'!$F$4:$F$494,$B17,'VS×ケイパビリティ関係'!$G$4:$G$494,H$5,'VS×ケイパビリティ関係'!$E$4:$E$494,"支援")>0,"○","")) | I17: =IF(COUNTIFS('VS×ケイパビリティ関係'!$F$4:$F$494,$B17,'VS×ケイパビリティ関係'!$G$4:$G$494,I$5,'VS×ケイパビリティ関係'!$E$4:$E$494,"主")>0,"●",IF(COUNTIFS('VS×ケイパビリティ関係'!$F$4:$F$494,$B17,'VS×ケイパビリティ関係'!$G$4:$G$494,I$5,'VS×ケイパビリティ関係'!$E$4:$E$494,"支援")>0,"○","")) | J17: =IF(COUNTIFS('VS×ケイパビリティ関係'!$F$4:$F$494,$B17,'VS×ケイパビリティ関係'!$G$4:$G$494,J$5,'VS×ケイパビリティ関係'!$E$4:$E$494,"主")>0,"●",IF(COUNTIFS('VS×ケイパビリティ関係'!$F$4:$F$494,$B17,'VS×ケイパビリティ関係'!$G$4:$G$494,J$5,'VS×ケイパビリティ関係'!$E$4:$E$494,"支援")>0,"○","")) | K17: =IF(COUNTIFS('VS×ケイパビリティ関係'!$F$4:$F$494,$B17,'VS×ケイパビリティ関係'!$G$4:$G$494,K$5,'VS×ケイパビリティ関係'!$E$4:$E$494,"主")>0,"●",IF(COUNTIFS('VS×ケイパビリティ関係'!$F$4:$F$494,$B17,'VS×ケイパビリティ関係'!$G$4:$G$494,K$5,'VS×ケイパビリティ関係'!$E$4:$E$494,"支援")>0,"○","")) | ... BD17: =IF(COUNTIFS('VS×ケイパビリティ関係'!$F$4:$F$494,$B17,'VS×ケイパビリティ関係'!$G$4:$G$494,BD$5,'VS×ケイパビリティ関係'!$E$4:$E$494,"主")>0,"●",IF(COUNTIFS('VS×ケイパビリティ関係'!$F$4:$F$494,$B17,'VS×ケイパビリティ関係'!$G$4:$G$494,BD$5,'VS×ケイパビリティ関係'!$E$4:$E$494,"支援")>0,"○","")) | BE17: =COUNTIF(D17:BD17,"●") -> 1 | BF17: =COUNTIF(D17:BD17,"○") -> 1
B18: 03-04 | C18: 分析法開発・特性解析 | D18: =IF(COUNTIFS('VS×ケイパビリティ関係'!$F$4:$F$494,$B18,'VS×ケイパビリティ関係'!$G$4:$G$494,D$5,'VS×ケイパビリティ関係'!$E$4:$E$494,"主")>0,"●",IF(COUNTIFS('VS×ケイパビリティ関係'!$F$4:$F$494,$B18,'VS×ケイパビリティ関係'!$G$4:$G$494,D$5,'VS×ケイパビリティ関係'!$E$4:$E$494,"支援")>0,"○","")) | E18: =IF(COUNTIFS('VS×ケイパビリティ関係'!$F$4:$F$494,$B18,'VS×ケイパビリティ関係'!$G$4:$G$494,E$5,'VS×ケイパビリティ関係'!$E$4:$E$494,"主")>0,"●",IF(COUNTIFS('VS×ケイパビリティ関係'!$F$4:$F$494,$B18,'VS×ケイパビリティ関係'!$G$4:$G$494,E$5,'VS×ケイパビリティ関係'!$E$4:$E$494,"支援")>0,"○","")) | F18: =IF(COUNTIFS('VS×ケイパビリティ関係'!$F$4:$F$494,$B18,'VS×ケイパビリティ関係'!$G$4:$G$494,F$5,'VS×ケイパビリティ関係'!$E$4:$E$494,"主")>0,"●",IF(COUNTIFS('VS×ケイパビリティ関係'!$F$4:$F$494,$B18,'VS×ケイパビリティ関係'!$G$4:$G$494,F$5,'VS×ケイパビリティ関係'!$E$4:$E$494,"支援")>0,"○","")) | G18: =IF(COUNTIFS('VS×ケイパビリティ関係'!$F$4:$F$494,$B18,'VS×ケイパビリティ関係'!$G$4:$G$494,G$5,'VS×ケイパビリティ関係'!$E$4:$E$494,"主")>0,"●",IF(COUNTIFS('VS×ケイパビリティ関係'!$F$4:$F$494,$B18,'VS×ケイパビリティ関係'!$G$4:$G$494,G$5,'VS×ケイパビリティ関係'!$E$4:$E$494,"支援")>0,"○","")) | H18: =IF(COUNTIFS('VS×ケイパビリティ関係'!$F$4:$F$494,$B18,'VS×ケイパビリティ関係'!$G$4:$G$494,H$5,'VS×ケイパビリティ関係'!$E$4:$E$494,"主")>0,"●",IF(COUNTIFS('VS×ケイパビリティ関係'!$F$4:$F$494,$B18,'VS×ケイパビリティ関係'!$G$4:$G$494,H$5,'VS×ケイパビリティ関係'!$E$4:$E$494,"支援")>0,"○","")) | I18: =IF(COUNTIFS('VS×ケイパビリティ関係'!$F$4:$F$494,$B18,'VS×ケイパビリティ関係'!$G$4:$G$494,I$5,'VS×ケイパビリティ関係'!$E$4:$E$494,"主")>0,"●",IF(COUNTIFS('VS×ケイパビリティ関係'!$F$4:$F$494,$B18,'VS×ケイパビリティ関係'!$G$4:$G$494,I$5,'VS×ケイパビリティ関係'!$E$4:$E$494,"支援")>0,"○","")) | J18: =IF(COUNTIFS('VS×ケイパビリティ関係'!$F$4:$F$494,$B18,'VS×ケイパビリティ関係'!$G$4:$G$494,J$5,'VS×ケイパビリティ関係'!$E$4:$E$494,"主")>0,"●",IF(COUNTIFS('VS×ケイパビリティ関係'!$F$4:$F$494,$B18,'VS×ケイパビリティ関係'!$G$4:$G$494,J$5,'VS×ケイパビリティ関係'!$E$4:$E$494,"支援")>0,"○","")) | K18: =IF(COUNTIFS('VS×ケイパビリティ関係'!$F$4:$F$494,$B18,'VS×ケイパビリティ関係'!$G$4:$G$494,K$5,'VS×ケイパビリティ関係'!$E$4:$E$494,"主")>0,"●",IF(COUNTIFS('VS×ケイパビリティ関係'!$F$4:$F$494,$B18,'VS×ケイパビリティ関係'!$G$4:$G$494,K$5,'VS×ケイパビリティ関係'!$E$4:$E$494,"支援")>0,"○","")) | ... BD18: =IF(COUNTIFS('VS×ケイパビリティ関係'!$F$4:$F$494,$B18,'VS×ケイパビリティ関係'!$G$4:$G$494,BD$5,'VS×ケイパビリティ関係'!$E$4:$E$494,"主")>0,"●",IF(COUNTIFS('VS×ケイパビリティ関係'!$F$4:$F$494,$B18,'VS×ケイパビリティ関係'!$G$4:$G$494,BD$5,'VS×ケイパビリティ関係'!$E$4:$E$494,"支援")>0,"○","")) | BE18: =COUNTIF(D18:BD18,"●") -> 1 | BF18: =COUNTIF(D18:BD18,"○") -> 0
B19: 03-05 | C19: 治験薬GMP製造・供給 | D19: =IF(COUNTIFS('VS×ケイパビリティ関係'!$F$4:$F$494,$B19,'VS×ケイパビリティ関係'!$G$4:$G$494,D$5,'VS×ケイパビリティ関係'!$E$4:$E$494,"主")>0,"●",IF(COUNTIFS('VS×ケイパビリティ関係'!$F$4:$F$494,$B19,'VS×ケイパビリティ関係'!$G$4:$G$494,D$5,'VS×ケイパビリティ関係'!$E$4:$E$494,"支援")>0,"○","")) | E19: =IF(COUNTIFS('VS×ケイパビリティ関係'!$F$4:$F$494,$B19,'VS×ケイパビリティ関係'!$G$4:$G$494,E$5,'VS×ケイパビリティ関係'!$E$4:$E$494,"主")>0,"●",IF(COUNTIFS('VS×ケイパビリティ関係'!$F$4:$F$494,$B19,'VS×ケイパビリティ関係'!$G$4:$G$494,E$5,'VS×ケイパビリティ関係'!$E$4:$E$494,"支援")>0,"○","")) | F19: =IF(COUNTIFS('VS×ケイパビリティ関係'!$F$4:$F$494,$B19,'VS×ケイパビリティ関係'!$G$4:$G$494,F$5,'VS×ケイパビリティ関係'!$E$4:$E$494,"主")>0,"●",IF(COUNTIFS('VS×ケイパビリティ関係'!$F$4:$F$494,$B19,'VS×ケイパビリティ関係'!$G$4:$G$494,F$5,'VS×ケイパビリティ関係'!$E$4:$E$494,"支援")>0,"○","")) -> ○ | G19: =IF(COUNTIFS('VS×ケイパビリティ関係'!$F$4:$F$494,$B19,'VS×ケイパビリティ関係'!$G$4:$G$494,G$5,'VS×ケイパビリティ関係'!$E$4:$E$494,"主")>0,"●",IF(COUNTIFS('VS×ケイパビリティ関係'!$F$4:$F$494,$B19,'VS×ケイパビリティ関係'!$G$4:$G$494,G$5,'VS×ケイパビリティ関係'!$E$4:$E$494,"支援")>0,"○","")) | H19: =IF(COUNTIFS('VS×ケイパビリティ関係'!$F$4:$F$494,$B19,'VS×ケイパビリティ関係'!$G$4:$G$494,H$5,'VS×ケイパビリティ関係'!$E$4:$E$494,"主")>0,"●",IF(COUNTIFS('VS×ケイパビリティ関係'!$F$4:$F$494,$B19,'VS×ケイパビリティ関係'!$G$4:$G$494,H$5,'VS×ケイパビリティ関係'!$E$4:$E$494,"支援")>0,"○","")) | I19: =IF(COUNTIFS('VS×ケイパビリティ関係'!$F$4:$F$494,$B19,'VS×ケイパビリティ関係'!$G$4:$G$494,I$5,'VS×ケイパビリティ関係'!$E$4:$E$494,"主")>0,"●",IF(COUNTIFS('VS×ケイパビリティ関係'!$F$4:$F$494,$B19,'VS×ケイパビリティ関係'!$G$4:$G$494,I$5,'VS×ケイパビリティ関係'!$E$4:$E$494,"支援")>0,"○","")) | J19: =IF(COUNTIFS('VS×ケイパビリティ関係'!$F$4:$F$494,$B19,'VS×ケイパビリティ関係'!$G$4:$G$494,J$5,'VS×ケイパビリティ関係'!$E$4:$E$494,"主")>0,"●",IF(COUNTIFS('VS×ケイパビリティ関係'!$F$4:$F$494,$B19,'VS×ケイパビリティ関係'!$G$4:$G$494,J$5,'VS×ケイパビリティ関係'!$E$4:$E$494,"支援")>0,"○","")) | K19: =IF(COUNTIFS('VS×ケイパビリティ関係'!$F$4:$F$494,$B19,'VS×ケイパビリティ関係'!$G$4:$G$494,K$5,'VS×ケイパビリティ関係'!$E$4:$E$494,"主")>0,"●",IF(COUNTIFS('VS×ケイパビリティ関係'!$F$4:$F$494,$B19,'VS×ケイパビリティ関係'!$G$4:$G$494,K$5,'VS×ケイパビリティ関係'!$E$4:$E$494,"支援")>0,"○","")) | ... BD19: =IF(COUNTIFS('VS×ケイパビリティ関係'!$F$4:$F$494,$B19,'VS×ケイパビリティ関係'!$G$4:$G$494,BD$5,'VS×ケイパビリティ関係'!$E$4:$E$494,"主")>0,"●",IF(COUNTIFS('VS×ケイパビリティ関係'!$F$4:$F$494,$B19,'VS×ケイパビリティ関係'!$G$4:$G$494,BD$5,'VS×ケイパビリティ関係'!$E$4:$E$494,"支援")>0,"○","")) | BE19: =COUNTIF(D19:BD19,"●") -> 6 | BF19: =COUNTIF(D19:BD19,"○") -> 2
B20: 03-06 | C20: 後期プロセス開発・スケールアップ・技術移転 | D20: =IF(COUNTIFS('VS×ケイパビリティ関係'!$F$4:$F$494,$B20,'VS×ケイパビリティ関係'!$G$4:$G$494,D$5,'VS×ケイパビリティ関係'!$E$4:$E$494,"主")>0,"●",IF(COUNTIFS('VS×ケイパビリティ関係'!$F$4:$F$494,$B20,'VS×ケイパビリティ関係'!$G$4:$G$494,D$5,'VS×ケイパビリティ関係'!$E$4:$E$494,"支援")>0,"○","")) | E20: =IF(COUNTIFS('VS×ケイパビリティ関係'!$F$4:$F$494,$B20,'VS×ケイパビリティ関係'!$G$4:$G$494,E$5,'VS×ケイパビリティ関係'!$E$4:$E$494,"主")>0,"●",IF(COUNTIFS('VS×ケイパビリティ関係'!$F$4:$F$494,$B20,'VS×ケイパビリティ関係'!$G$4:$G$494,E$5,'VS×ケイパビリティ関係'!$E$4:$E$494,"支援")>0,"○","")) | F20: =IF(COUNTIFS('VS×ケイパビリティ関係'!$F$4:$F$494,$B20,'VS×ケイパビリティ関係'!$G$4:$G$494,F$5,'VS×ケイパビリティ関係'!$E$4:$E$494,"主")>0,"●",IF(COUNTIFS('VS×ケイパビリティ関係'!$F$4:$F$494,$B20,'VS×ケイパビリティ関係'!$G$4:$G$494,F$5,'VS×ケイパビリティ関係'!$E$4:$E$494,"支援")>0,"○","")) -> ○ | G20: =IF(COUNTIFS('VS×ケイパビリティ関係'!$F$4:$F$494,$B20,'VS×ケイパビリティ関係'!$G$4:$G$494,G$5,'VS×ケイパビリティ関係'!$E$4:$E$494,"主")>0,"●",IF(COUNTIFS('VS×ケイパビリティ関係'!$F$4:$F$494,$B20,'VS×ケイパビリティ関係'!$G$4:$G$494,G$5,'VS×ケイパビリティ関係'!$E$4:$E$494,"支援")>0,"○","")) | H20: =IF(COUNTIFS('VS×ケイパビリティ関係'!$F$4:$F$494,$B20,'VS×ケイパビリティ関係'!$G$4:$G$494,H$5,'VS×ケイパビリティ関係'!$E$4:$E$494,"主")>0,"●",IF(COUNTIFS('VS×ケイパビリティ関係'!$F$4:$F$494,$B20,'VS×ケイパビリティ関係'!$G$4:$G$494,H$5,'VS×ケイパビリティ関係'!$E$4:$E$494,"支援")>0,"○","")) | I20: =IF(COUNTIFS('VS×ケイパビリティ関係'!$F$4:$F$494,$B20,'VS×ケイパビリティ関係'!$G$4:$G$494,I$5,'VS×ケイパビリティ関係'!$E$4:$E$494,"主")>0,"●",IF(COUNTIFS('VS×ケイパビリティ関係'!$F$4:$F$494,$B20,'VS×ケイパビリティ関係'!$G$4:$G$494,I$5,'VS×ケイパビリティ関係'!$E$4:$E$494,"支援")>0,"○","")) | J20: =IF(COUNTIFS('VS×ケイパビリティ関係'!$F$4:$F$494,$B20,'VS×ケイパビリティ関係'!$G$4:$G$494,J$5,'VS×ケイパビリティ関係'!$E$4:$E$494,"主")>0,"●",IF(COUNTIFS('VS×ケイパビリティ関係'!$F$4:$F$494,$B20,'VS×ケイパビリティ関係'!$G$4:$G$494,J$5,'VS×ケイパビリティ関係'!$E$4:$E$494,"支援")>0,"○","")) | K20: =IF(COUNTIFS('VS×ケイパビリティ関係'!$F$4:$F$494,$B20,'VS×ケイパビリティ関係'!$G$4:$G$494,K$5,'VS×ケイパビリティ関係'!$E$4:$E$494,"主")>0,"●",IF(COUNTIFS('VS×ケイパビリティ関係'!$F$4:$F$494,$B20,'VS×ケイパビリティ関係'!$G$4:$G$494,K$5,'VS×ケイパビリティ関係'!$E$4:$E$494,"支援")>0,"○","")) | ... BD20: =IF(COUNTIFS('VS×ケイパビリティ関係'!$F$4:$F$494,$B20,'VS×ケイパビリティ関係'!$G$4:$G$494,BD$5,'VS×ケイパビリティ関係'!$E$4:$E$494,"主")>0,"●",IF(COUNTIFS('VS×ケイパビリティ関係'!$F$4:$F$494,$B20,'VS×ケイパビリティ関係'!$G$4:$G$494,BD$5,'VS×ケイパビリティ関係'!$E$4:$E$494,"支援")>0,"○","")) | BE20: =COUNTIF(D20:BD20,"●") -> 2 | BF20: =COUNTIF(D20:BD20,"○") -> 4
B21: 03-07 | C21: プロセスバリデーション（PPQ） | D21: =IF(COUNTIFS('VS×ケイパビリティ関係'!$F$4:$F$494,$B21,'VS×ケイパビリティ関係'!$G$4:$G$494,D$5,'VS×ケイパビリティ関係'!$E$4:$E$494,"主")>0,"●",IF(COUNTIFS('VS×ケイパビリティ関係'!$F$4:$F$494,$B21,'VS×ケイパビリティ関係'!$G$4:$G$494,D$5,'VS×ケイパビリティ関係'!$E$4:$E$494,"支援")>0,"○","")) | E21: =IF(COUNTIFS('VS×ケイパビリティ関係'!$F$4:$F$494,$B21,'VS×ケイパビリティ関係'!$G$4:$G$494,E$5,'VS×ケイパビリティ関係'!$E$4:$E$494,"主")>0,"●",IF(COUNTIFS('VS×ケイパビリティ関係'!$F$4:$F$494,$B21,'VS×ケイパビリティ関係'!$G$4:$G$494,E$5,'VS×ケイパビリティ関係'!$E$4:$E$494,"支援")>0,"○","")) | F21: =IF(COUNTIFS('VS×ケイパビリティ関係'!$F$4:$F$494,$B21,'VS×ケイパビリティ関係'!$G$4:$G$494,F$5,'VS×ケイパビリティ関係'!$E$4:$E$494,"主")>0,"●",IF(COUNTIFS('VS×ケイパビリティ関係'!$F$4:$F$494,$B21,'VS×ケイパビリティ関係'!$G$4:$G$494,F$5,'VS×ケイパビリティ関係'!$E$4:$E$494,"支援")>0,"○","")) | G21: =IF(COUNTIFS('VS×ケイパビリティ関係'!$F$4:$F$494,$B21,'VS×ケイパビリティ関係'!$G$4:$G$494,G$5,'VS×ケイパビリティ関係'!$E$4:$E$494,"主")>0,"●",IF(COUNTIFS('VS×ケイパビリティ関係'!$F$4:$F$494,$B21,'VS×ケイパビリティ関係'!$G$4:$G$494,G$5,'VS×ケイパビリティ関係'!$E$4:$E$494,"支援")>0,"○","")) | H21: =IF(COUNTIFS('VS×ケイパビリティ関係'!$F$4:$F$494,$B21,'VS×ケイパビリティ関係'!$G$4:$G$494,H$5,'VS×ケイパビリティ関係'!$E$4:$E$494,"主")>0,"●",IF(COUNTIFS('VS×ケイパビリティ関係'!$F$4:$F$494,$B21,'VS×ケイパビリティ関係'!$G$4:$G$494,H$5,'VS×ケイパビリティ関係'!$E$4:$E$494,"支援")>0,"○","")) | I21: =IF(COUNTIFS('VS×ケイパビリティ関係'!$F$4:$F$494,$B21,'VS×ケイパビリティ関係'!$G$4:$G$494,I$5,'VS×ケイパビリティ関係'!$E$4:$E$494,"主")>0,"●",IF(COUNTIFS('VS×ケイパビリティ関係'!$F$4:$F$494,$B21,'VS×ケイパビリティ関係'!$G$4:$G$494,I$5,'VS×ケイパビリティ関係'!$E$4:$E$494,"支援")>0,"○","")) | J21: =IF(COUNTIFS('VS×ケイパビリティ関係'!$F$4:$F$494,$B21,'VS×ケイパビリティ関係'!$G$4:$G$494,J$5,'VS×ケイパビリティ関係'!$E$4:$E$494,"主")>0,"●",IF(COUNTIFS('VS×ケイパビリティ関係'!$F$4:$F$494,$B21,'VS×ケイパビリティ関係'!$G$4:$G$494,J$5,'VS×ケイパビリティ関係'!$E$4:$E$494,"支援")>0,"○","")) | K21: =IF(COUNTIFS('VS×ケイパビリティ関係'!$F$4:$F$494,$B21,'VS×ケイパビリティ関係'!$G$4:$G$494,K$5,'VS×ケイパビリティ関係'!$E$4:$E$494,"主")>0,"●",IF(COUNTIFS('VS×ケイパビリティ関係'!$F$4:$F$494,$B21,'VS×ケイパビリティ関係'!$G$4:$G$494,K$5,'VS×ケイパビリティ関係'!$E$4:$E$494,"支援")>0,"○","")) | ... BD21: =IF(COUNTIFS('VS×ケイパビリティ関係'!$F$4:$F$494,$B21,'VS×ケイパビリティ関係'!$G$4:$G$494,BD$5,'VS×ケイパビリティ関係'!$E$4:$E$494,"主")>0,"●",IF(COUNTIFS('VS×ケイパビリティ関係'!$F$4:$F$494,$B21,'VS×ケイパビリティ関係'!$G$4:$G$494,BD$5,'VS×ケイパビリティ関係'!$E$4:$E$494,"支援")>0,"○","")) | BE21: =COUNTIF(D21:BD21,"●") -> 1 | BF21: =COUNTIF(D21:BD21,"○") -> 3
A22: 04 臨床開発 | B22: 04-01 | C22: ★自然歴研究・患者特定 | D22: =IF(COUNTIFS('VS×ケイパビリティ関係'!$F$4:$F$494,$B22,'VS×ケイパビリティ関係'!$G$4:$G$494,D$5,'VS×ケイパビリティ関係'!$E$4:$E$494,"主")>0,"●",IF(COUNTIFS('VS×ケイパビリティ関係'!$F$4:$F$494,$B22,'VS×ケイパビリティ関係'!$G$4:$G$494,D$5,'VS×ケイパビリティ関係'!$E$4:$E$494,"支援")>0,"○","")) | E22: =IF(COUNTIFS('VS×ケイパビリティ関係'!$F$4:$F$494,$B22,'VS×ケイパビリティ関係'!$G$4:$G$494,E$5,'VS×ケイパビリティ関係'!$E$4:$E$494,"主")>0,"●",IF(COUNTIFS('VS×ケイパビリティ関係'!$F$4:$F$494,$B22,'VS×ケイパビリティ関係'!$G$4:$G$494,E$5,'VS×ケイパビリティ関係'!$E$4:$E$494,"支援")>0,"○","")) | F22: =IF(COUNTIFS('VS×ケイパビリティ関係'!$F$4:$F$494,$B22,'VS×ケイパビリティ関係'!$G$4:$G$494,F$5,'VS×ケイパビリティ関係'!$E$4:$E$494,"主")>0,"●",IF(COUNTIFS('VS×ケイパビリティ関係'!$F$4:$F$494,$B22,'VS×ケイパビリティ関係'!$G$4:$G$494,F$5,'VS×ケイパビリティ関係'!$E$4:$E$494,"支援")>0,"○","")) | G22: =IF(COUNTIFS('VS×ケイパビリティ関係'!$F$4:$F$494,$B22,'VS×ケイパビリティ関係'!$G$4:$G$494,G$5,'VS×ケイパビリティ関係'!$E$4:$E$494,"主")>0,"●",IF(COUNTIFS('VS×ケイパビリティ関係'!$F$4:$F$494,$B22,'VS×ケイパビリティ関係'!$G$4:$G$494,G$5,'VS×ケイパビリティ関係'!$E$4:$E$494,"支援")>0,"○","")) | H22: =IF(COUNTIFS('VS×ケイパビリティ関係'!$F$4:$F$494,$B22,'VS×ケイパビリティ関係'!$G$4:$G$494,H$5,'VS×ケイパビリティ関係'!$E$4:$E$494,"主")>0,"●",IF(COUNTIFS('VS×ケイパビリティ関係'!$F$4:$F$494,$B22,'VS×ケイパビリティ関係'!$G$4:$G$494,H$5,'VS×ケイパビリティ関係'!$E$4:$E$494,"支援")>0,"○","")) | I22: =IF(COUNTIFS('VS×ケイパビリティ関係'!$F$4:$F$494,$B22,'VS×ケイパビリティ関係'!$G$4:$G$494,I$5,'VS×ケイパビリティ関係'!$E$4:$E$494,"主")>0,"●",IF(COUNTIFS('VS×ケイパビリティ関係'!$F$4:$F$494,$B22,'VS×ケイパビリティ関係'!$G$4:$G$494,I$5,'VS×ケイパビリティ関係'!$E$4:$E$494,"支援")>0,"○","")) | J22: =IF(COUNTIFS('VS×ケイパビリティ関係'!$F$4:$F$494,$B22,'VS×ケイパビリティ関係'!$G$4:$G$494,J$5,'VS×ケイパビリティ関係'!$E$4:$E$494,"主")>0,"●",IF(COUNTIFS('VS×ケイパビリティ関係'!$F$4:$F$494,$B22,'VS×ケイパビリティ関係'!$G$4:$G$494,J$5,'VS×ケイパビリティ関係'!$E$4:$E$494,"支援")>0,"○","")) | K22: =IF(COUNTIFS('VS×ケイパビリティ関係'!$F$4:$F$494,$B22,'VS×ケイパビリティ関係'!$G$4:$G$494,K$5,'VS×ケイパビリティ関係'!$E$4:$E$494,"主")>0,"●",IF(COUNTIFS('VS×ケイパビリティ関係'!$F$4:$F$494,$B22,'VS×ケイパビリティ関係'!$G$4:$G$494,K$5,'VS×ケイパビリティ関係'!$E$4:$E$494,"支援")>0,"○","")) | ... BD22: =IF(COUNTIFS('VS×ケイパビリティ関係'!$F$4:$F$494,$B22,'VS×ケイパビリティ関係'!$G$4:$G$494,BD$5,'VS×ケイパビリティ関係'!$E$4:$E$494,"主")>0,"●",IF(COUNTIFS('VS×ケイパビリティ関係'!$F$4:$F$494,$B22,'VS×ケイパビリティ関係'!$G$4:$G$494,BD$5,'VS×ケイパビリティ関係'!$E$4:$E$494,"支援")>0,"○","")) | BE22: =COUNTIF(D22:BD22,"●") -> 3 | BF22: =COUNTIF(D22:BD22,"○") -> 3
B23: 04-02 | C23: ★第I/II相（患者での安全性・PK・PoC） | D23: =IF(COUNTIFS('VS×ケイパビリティ関係'!$F$4:$F$494,$B23,'VS×ケイパビリティ関係'!$G$4:$G$494,D$5,'VS×ケイパビリティ関係'!$E$4:$E$494,"主")>0,"●",IF(COUNTIFS('VS×ケイパビリティ関係'!$F$4:$F$494,$B23,'VS×ケイパビリティ関係'!$G$4:$G$494,D$5,'VS×ケイパビリティ関係'!$E$4:$E$494,"支援")>0,"○","")) -> ○ | E23: =IF(COUNTIFS('VS×ケイパビリティ関係'!$F$4:$F$494,$B23,'VS×ケイパビリティ関係'!$G$4:$G$494,E$5,'VS×ケイパビリティ関係'!$E$4:$E$494,"主")>0,"●",IF(COUNTIFS('VS×ケイパビリティ関係'!$F$4:$F$494,$B23,'VS×ケイパビリティ関係'!$G$4:$G$494,E$5,'VS×ケイパビリティ関係'!$E$4:$E$494,"支援")>0,"○","")) | F23: =IF(COUNTIFS('VS×ケイパビリティ関係'!$F$4:$F$494,$B23,'VS×ケイパビリティ関係'!$G$4:$G$494,F$5,'VS×ケイパビリティ関係'!$E$4:$E$494,"主")>0,"●",IF(COUNTIFS('VS×ケイパビリティ関係'!$F$4:$F$494,$B23,'VS×ケイパビリティ関係'!$G$4:$G$494,F$5,'VS×ケイパビリティ関係'!$E$4:$E$494,"支援")>0,"○","")) -> ○ | G23: =IF(COUNTIFS('VS×ケイパビリティ関係'!$F$4:$F$494,$B23,'VS×ケイパビリティ関係'!$G$4:$G$494,G$5,'VS×ケイパビリティ関係'!$E$4:$E$494,"主")>0,"●",IF(COUNTIFS('VS×ケイパビリティ関係'!$F$4:$F$494,$B23,'VS×ケイパビリティ関係'!$G$4:$G$494,G$5,'VS×ケイパビリティ関係'!$E$4:$E$494,"支援")>0,"○","")) | H23: =IF(COUNTIFS('VS×ケイパビリティ関係'!$F$4:$F$494,$B23,'VS×ケイパビリティ関係'!$G$4:$G$494,H$5,'VS×ケイパビリティ関係'!$E$4:$E$494,"主")>0,"●",IF(COUNTIFS('VS×ケイパビリティ関係'!$F$4:$F$494,$B23,'VS×ケイパビリティ関係'!$G$4:$G$494,H$5,'VS×ケイパビリティ関係'!$E$4:$E$494,"支援")>0,"○","")) | I23: =IF(COUNTIFS('VS×ケイパビリティ関係'!$F$4:$F$494,$B23,'VS×ケイパビリティ関係'!$G$4:$G$494,I$5,'VS×ケイパビリティ関係'!$E$4:$E$494,"主")>0,"●",IF(COUNTIFS('VS×ケイパビリティ関係'!$F$4:$F$494,$B23,'VS×ケイパビリティ関係'!$G$4:$G$494,I$5,'VS×ケイパビリティ関係'!$E$4:$E$494,"支援")>0,"○","")) | J23: =IF(COUNTIFS('VS×ケイパビリティ関係'!$F$4:$F$494,$B23,'VS×ケイパビリティ関係'!$G$4:$G$494,J$5,'VS×ケイパビリティ関係'!$E$4:$E$494,"主")>0,"●",IF(COUNTIFS('VS×ケイパビリティ関係'!$F$4:$F$494,$B23,'VS×ケイパビリティ関係'!$G$4:$G$494,J$5,'VS×ケイパビリティ関係'!$E$4:$E$494,"支援")>0,"○","")) | K23: =IF(COUNTIFS('VS×ケイパビリティ関係'!$F$4:$F$494,$B23,'VS×ケイパビリティ関係'!$G$4:$G$494,K$5,'VS×ケイパビリティ関係'!$E$4:$E$494,"主")>0,"●",IF(COUNTIFS('VS×ケイパビリティ関係'!$F$4:$F$494,$B23,'VS×ケイパビリティ関係'!$G$4:$G$494,K$5,'VS×ケイパビリティ関係'!$E$4:$E$494,"支援")>0,"○","")) | ... BD23: =IF(COUNTIFS('VS×ケイパビリティ関係'!$F$4:$F$494,$B23,'VS×ケイパビリティ関係'!$G$4:$G$494,BD$5,'VS×ケイパビリティ関係'!$E$4:$E$494,"主")>0,"●",IF(COUNTIFS('VS×ケイパビリティ関係'!$F$4:$F$494,$B23,'VS×ケイパビリティ関係'!$G$4:$G$494,BD$5,'VS×ケイパビリティ関係'!$E$4:$E$494,"支援")>0,"○","")) | BE23: =COUNTIF(D23:BD23,"●") -> 4 | BF23: =COUNTIF(D23:BD23,"○") -> 6
B24: 04-03 | C24: ★ピボタル試験（検証的試験） | D24: =IF(COUNTIFS('VS×ケイパビリティ関係'!$F$4:$F$494,$B24,'VS×ケイパビリティ関係'!$G$4:$G$494,D$5,'VS×ケイパビリティ関係'!$E$4:$E$494,"主")>0,"●",IF(COUNTIFS('VS×ケイパビリティ関係'!$F$4:$F$494,$B24,'VS×ケイパビリティ関係'!$G$4:$G$494,D$5,'VS×ケイパビリティ関係'!$E$4:$E$494,"支援")>0,"○","")) | E24: =IF(COUNTIFS('VS×ケイパビリティ関係'!$F$4:$F$494,$B24,'VS×ケイパビリティ関係'!$G$4:$G$494,E$5,'VS×ケイパビリティ関係'!$E$4:$E$494,"主")>0,"●",IF(COUNTIFS('VS×ケイパビリティ関係'!$F$4:$F$494,$B24,'VS×ケイパビリティ関係'!$G$4:$G$494,E$5,'VS×ケイパビリティ関係'!$E$4:$E$494,"支援")>0,"○","")) | F24: =IF(COUNTIFS('VS×ケイパビリティ関係'!$F$4:$F$494,$B24,'VS×ケイパビリティ関係'!$G$4:$G$494,F$5,'VS×ケイパビリティ関係'!$E$4:$E$494,"主")>0,"●",IF(COUNTIFS('VS×ケイパビリティ関係'!$F$4:$F$494,$B24,'VS×ケイパビリティ関係'!$G$4:$G$494,F$5,'VS×ケイパビリティ関係'!$E$4:$E$494,"支援")>0,"○","")) | G24: =IF(COUNTIFS('VS×ケイパビリティ関係'!$F$4:$F$494,$B24,'VS×ケイパビリティ関係'!$G$4:$G$494,G$5,'VS×ケイパビリティ関係'!$E$4:$E$494,"主")>0,"●",IF(COUNTIFS('VS×ケイパビリティ関係'!$F$4:$F$494,$B24,'VS×ケイパビリティ関係'!$G$4:$G$494,G$5,'VS×ケイパビリティ関係'!$E$4:$E$494,"支援")>0,"○","")) | H24: =IF(COUNTIFS('VS×ケイパビリティ関係'!$F$4:$F$494,$B24,'VS×ケイパビリティ関係'!$G$4:$G$494,H$5,'VS×ケイパビリティ関係'!$E$4:$E$494,"主")>0,"●",IF(COUNTIFS('VS×ケイパビリティ関係'!$F$4:$F$494,$B24,'VS×ケイパビリティ関係'!$G$4:$G$494,H$5,'VS×ケイパビリティ関係'!$E$4:$E$494,"支援")>0,"○","")) | I24: =IF(COUNTIFS('VS×ケイパビリティ関係'!$F$4:$F$494,$B24,'VS×ケイパビリティ関係'!$G$4:$G$494,I$5,'VS×ケイパビリティ関係'!$E$4:$E$494,"主")>0,"●",IF(COUNTIFS('VS×ケイパビリティ関係'!$F$4:$F$494,$B24,'VS×ケイパビリティ関係'!$G$4:$G$494,I$5,'VS×ケイパビリティ関係'!$E$4:$E$494,"支援")>0,"○","")) | J24: =IF(COUNTIFS('VS×ケイパビリティ関係'!$F$4:$F$494,$B24,'VS×ケイパビリティ関係'!$G$4:$G$494,J$5,'VS×ケイパビリティ関係'!$E$4:$E$494,"主")>0,"●",IF(COUNTIFS('VS×ケイパビリティ関係'!$F$4:$F$494,$B24,'VS×ケイパビリティ関係'!$G$4:$G$494,J$5,'VS×ケイパビリティ関係'!$E$4:$E$494,"支援")>0,"○","")) | K24: =IF(COUNTIFS('VS×ケイパビリティ関係'!$F$4:$F$494,$B24,'VS×ケイパビリティ関係'!$G$4:$G$494,K$5,'VS×ケイパビリティ関係'!$E$4:$E$494,"主")>0,"●",IF(COUNTIFS('VS×ケイパビリティ関係'!$F$4:$F$494,$B24,'VS×ケイパビリティ関係'!$G$4:$G$494,K$5,'VS×ケイパビリティ関係'!$E$4:$E$494,"支援")>0,"○","")) | ... BD24: =IF(COUNTIFS('VS×ケイパビリティ関係'!$F$4:$F$494,$B24,'VS×ケイパビリティ関係'!$G$4:$G$494,BD$5,'VS×ケイパビリティ関係'!$E$4:$E$494,"主")>0,"●",IF(COUNTIFS('VS×ケイパビリティ関係'!$F$4:$F$494,$B24,'VS×ケイパビリティ関係'!$G$4:$G$494,BD$5,'VS×ケイパビリティ関係'!$E$4:$E$494,"支援")>0,"○","")) | BE24: =COUNTIF(D24:BD24,"●") -> 3 | BF24: =COUNTIF(D24:BD24,"○") -> 5
B25: 04-04 | C25: 臨床データの統合・評価 | D25: =IF(COUNTIFS('VS×ケイパビリティ関係'!$F$4:$F$494,$B25,'VS×ケイパビリティ関係'!$G$4:$G$494,D$5,'VS×ケイパビリティ関係'!$E$4:$E$494,"主")>0,"●",IF(COUNTIFS('VS×ケイパビリティ関係'!$F$4:$F$494,$B25,'VS×ケイパビリティ関係'!$G$4:$G$494,D$5,'VS×ケイパビリティ関係'!$E$4:$E$494,"支援")>0,"○","")) | E25: =IF(COUNTIFS('VS×ケイパビリティ関係'!$F$4:$F$494,$B25,'VS×ケイパビリティ関係'!$G$4:$G$494,E$5,'VS×ケイパビリティ関係'!$E$4:$E$494,"主")>0,"●",IF(COUNTIFS('VS×ケイパビリティ関係'!$F$4:$F$494,$B25,'VS×ケイパビリティ関係'!$G$4:$G$494,E$5,'VS×ケイパビリティ関係'!$E$4:$E$494,"支援")>0,"○","")) | F25: =IF(COUNTIFS('VS×ケイパビリティ関係'!$F$4:$F$494,$B25,'VS×ケイパビリティ関係'!$G$4:$G$494,F$5,'VS×ケイパビリティ関係'!$E$4:$E$494,"主")>0,"●",IF(COUNTIFS('VS×ケイパビリティ関係'!$F$4:$F$494,$B25,'VS×ケイパビリティ関係'!$G$4:$G$494,F$5,'VS×ケイパビリティ関係'!$E$4:$E$494,"支援")>0,"○","")) | G25: =IF(COUNTIFS('VS×ケイパビリティ関係'!$F$4:$F$494,$B25,'VS×ケイパビリティ関係'!$G$4:$G$494,G$5,'VS×ケイパビリティ関係'!$E$4:$E$494,"主")>0,"●",IF(COUNTIFS('VS×ケイパビリティ関係'!$F$4:$F$494,$B25,'VS×ケイパビリティ関係'!$G$4:$G$494,G$5,'VS×ケイパビリティ関係'!$E$4:$E$494,"支援")>0,"○","")) | H25: =IF(COUNTIFS('VS×ケイパビリティ関係'!$F$4:$F$494,$B25,'VS×ケイパビリティ関係'!$G$4:$G$494,H$5,'VS×ケイパビリティ関係'!$E$4:$E$494,"主")>0,"●",IF(COUNTIFS('VS×ケイパビリティ関係'!$F$4:$F$494,$B25,'VS×ケイパビリティ関係'!$G$4:$G$494,H$5,'VS×ケイパビリティ関係'!$E$4:$E$494,"支援")>0,"○","")) | I25: =IF(COUNTIFS('VS×ケイパビリティ関係'!$F$4:$F$494,$B25,'VS×ケイパビリティ関係'!$G$4:$G$494,I$5,'VS×ケイパビリティ関係'!$E$4:$E$494,"主")>0,"●",IF(COUNTIFS('VS×ケイパビリティ関係'!$F$4:$F$494,$B25,'VS×ケイパビリティ関係'!$G$4:$G$494,I$5,'VS×ケイパビリティ関係'!$E$4:$E$494,"支援")>0,"○","")) | J25: =IF(COUNTIFS('VS×ケイパビリティ関係'!$F$4:$F$494,$B25,'VS×ケイパビリティ関係'!$G$4:$G$494,J$5,'VS×ケイパビリティ関係'!$E$4:$E$494,"主")>0,"●",IF(COUNTIFS('VS×ケイパビリティ関係'!$F$4:$F$494,$B25,'VS×ケイパビリティ関係'!$G$4:$G$494,J$5,'VS×ケイパビリティ関係'!$E$4:$E$494,"支援")>0,"○","")) | K25: =IF(COUNTIFS('VS×ケイパビリティ関係'!$F$4:$F$494,$B25,'VS×ケイパビリティ関係'!$G$4:$G$494,K$5,'VS×ケイパビリティ関係'!$E$4:$E$494,"主")>0,"●",IF(COUNTIFS('VS×ケイパビリティ関係'!$F$4:$F$494,$B25,'VS×ケイパビリティ関係'!$G$4:$G$494,K$5,'VS×ケイパビリティ関係'!$E$4:$E$494,"支援")>0,"○","")) | ... BD25: =IF(COUNTIFS('VS×ケイパビリティ関係'!$F$4:$F$494,$B25,'VS×ケイパビリティ関係'!$G$4:$G$494,BD$5,'VS×ケイパビリティ関係'!$E$4:$E$494,"主")>0,"●",IF(COUNTIFS('VS×ケイパビリティ関係'!$F$4:$F$494,$B25,'VS×ケイパビリティ関係'!$G$4:$G$494,BD$5,'VS×ケイパビリティ関係'!$E$4:$E$494,"支援")>0,"○","")) | BE25: =COUNTIF(D25:BD25,"●") -> 4 | BF25: =COUNTIF(D25:BD25,"○") -> 3
A26: 05 BLA申請・審査 | B26: 05-01 | C26: 申請資料（CTD）の作成 | D26: =IF(COUNTIFS('VS×ケイパビリティ関係'!$F$4:$F$494,$B26,'VS×ケイパビリティ関係'!$G$4:$G$494,D$5,'VS×ケイパビリティ関係'!$E$4:$E$494,"主")>0,"●",IF(COUNTIFS('VS×ケイパビリティ関係'!$F$4:$F$494,$B26,'VS×ケイパビリティ関係'!$G$4:$G$494,D$5,'VS×ケイパビリティ関係'!$E$4:$E$494,"支援")>0,"○","")) | E26: =IF(COUNTIFS('VS×ケイパビリティ関係'!$F$4:$F$494,$B26,'VS×ケイパビリティ関係'!$G$4:$G$494,E$5,'VS×ケイパビリティ関係'!$E$4:$E$494,"主")>0,"●",IF(COUNTIFS('VS×ケイパビリティ関係'!$F$4:$F$494,$B26,'VS×ケイパビリティ関係'!$G$4:$G$494,E$5,'VS×ケイパビリティ関係'!$E$4:$E$494,"支援")>0,"○","")) | F26: =IF(COUNTIFS('VS×ケイパビリティ関係'!$F$4:$F$494,$B26,'VS×ケイパビリティ関係'!$G$4:$G$494,F$5,'VS×ケイパビリティ関係'!$E$4:$E$494,"主")>0,"●",IF(COUNTIFS('VS×ケイパビリティ関係'!$F$4:$F$494,$B26,'VS×ケイパビリティ関係'!$G$4:$G$494,F$5,'VS×ケイパビリティ関係'!$E$4:$E$494,"支援")>0,"○","")) | G26: =IF(COUNTIFS('VS×ケイパビリティ関係'!$F$4:$F$494,$B26,'VS×ケイパビリティ関係'!$G$4:$G$494,G$5,'VS×ケイパビリティ関係'!$E$4:$E$494,"主")>0,"●",IF(COUNTIFS('VS×ケイパビリティ関係'!$F$4:$F$494,$B26,'VS×ケイパビリティ関係'!$G$4:$G$494,G$5,'VS×ケイパビリティ関係'!$E$4:$E$494,"支援")>0,"○","")) | H26: =IF(COUNTIFS('VS×ケイパビリティ関係'!$F$4:$F$494,$B26,'VS×ケイパビリティ関係'!$G$4:$G$494,H$5,'VS×ケイパビリティ関係'!$E$4:$E$494,"主")>0,"●",IF(COUNTIFS('VS×ケイパビリティ関係'!$F$4:$F$494,$B26,'VS×ケイパビリティ関係'!$G$4:$G$494,H$5,'VS×ケイパビリティ関係'!$E$4:$E$494,"支援")>0,"○","")) | I26: =IF(COUNTIFS('VS×ケイパビリティ関係'!$F$4:$F$494,$B26,'VS×ケイパビリティ関係'!$G$4:$G$494,I$5,'VS×ケイパビリティ関係'!$E$4:$E$494,"主")>0,"●",IF(COUNTIFS('VS×ケイパビリティ関係'!$F$4:$F$494,$B26,'VS×ケイパビリティ関係'!$G$4:$G$494,I$5,'VS×ケイパビリティ関係'!$E$4:$E$494,"支援")>0,"○","")) | J26: =IF(COUNTIFS('VS×ケイパビリティ関係'!$F$4:$F$494,$B26,'VS×ケイパビリティ関係'!$G$4:$G$494,J$5,'VS×ケイパビリティ関係'!$E$4:$E$494,"主")>0,"●",IF(COUNTIFS('VS×ケイパビリティ関係'!$F$4:$F$494,$B26,'VS×ケイパビリティ関係'!$G$4:$G$494,J$5,'VS×ケイパビリティ関係'!$E$4:$E$494,"支援")>0,"○","")) | K26: =IF(COUNTIFS('VS×ケイパビリティ関係'!$F$4:$F$494,$B26,'VS×ケイパビリティ関係'!$G$4:$G$494,K$5,'VS×ケイパビリティ関係'!$E$4:$E$494,"主")>0,"●",IF(COUNTIFS('VS×ケイパビリティ関係'!$F$4:$F$494,$B26,'VS×ケイパビリティ関係'!$G$4:$G$494,K$5,'VS×ケイパビリティ関係'!$E$4:$E$494,"支援")>0,"○","")) | ... BD26: =IF(COUNTIFS('VS×ケイパビリティ関係'!$F$4:$F$494,$B26,'VS×ケイパビリティ関係'!$G$4:$G$494,BD$5,'VS×ケイパビリティ関係'!$E$4:$E$494,"主")>0,"●",IF(COUNTIFS('VS×ケイパビリティ関係'!$F$4:$F$494,$B26,'VS×ケイパビリティ関係'!$G$4:$G$494,BD$5,'VS×ケイパビリティ関係'!$E$4:$E$494,"支援")>0,"○","")) | BE26: =COUNTIF(D26:BD26,"●") -> 2 | BF26: =COUNTIF(D26:BD26,"○") -> 3
B27: 05-02 | C27: 審査対応 | D27: =IF(COUNTIFS('VS×ケイパビリティ関係'!$F$4:$F$494,$B27,'VS×ケイパビリティ関係'!$G$4:$G$494,D$5,'VS×ケイパビリティ関係'!$E$4:$E$494,"主")>0,"●",IF(COUNTIFS('VS×ケイパビリティ関係'!$F$4:$F$494,$B27,'VS×ケイパビリティ関係'!$G$4:$G$494,D$5,'VS×ケイパビリティ関係'!$E$4:$E$494,"支援")>0,"○","")) | E27: =IF(COUNTIFS('VS×ケイパビリティ関係'!$F$4:$F$494,$B27,'VS×ケイパビリティ関係'!$G$4:$G$494,E$5,'VS×ケイパビリティ関係'!$E$4:$E$494,"主")>0,"●",IF(COUNTIFS('VS×ケイパビリティ関係'!$F$4:$F$494,$B27,'VS×ケイパビリティ関係'!$G$4:$G$494,E$5,'VS×ケイパビリティ関係'!$E$4:$E$494,"支援")>0,"○","")) | F27: =IF(COUNTIFS('VS×ケイパビリティ関係'!$F$4:$F$494,$B27,'VS×ケイパビリティ関係'!$G$4:$G$494,F$5,'VS×ケイパビリティ関係'!$E$4:$E$494,"主")>0,"●",IF(COUNTIFS('VS×ケイパビリティ関係'!$F$4:$F$494,$B27,'VS×ケイパビリティ関係'!$G$4:$G$494,F$5,'VS×ケイパビリティ関係'!$E$4:$E$494,"支援")>0,"○","")) -> ○ | G27: =IF(COUNTIFS('VS×ケイパビリティ関係'!$F$4:$F$494,$B27,'VS×ケイパビリティ関係'!$G$4:$G$494,G$5,'VS×ケイパビリティ関係'!$E$4:$E$494,"主")>0,"●",IF(COUNTIFS('VS×ケイパビリティ関係'!$F$4:$F$494,$B27,'VS×ケイパビリティ関係'!$G$4:$G$494,G$5,'VS×ケイパビリティ関係'!$E$4:$E$494,"支援")>0,"○","")) | H27: =IF(COUNTIFS('VS×ケイパビリティ関係'!$F$4:$F$494,$B27,'VS×ケイパビリティ関係'!$G$4:$G$494,H$5,'VS×ケイパビリティ関係'!$E$4:$E$494,"主")>0,"●",IF(COUNTIFS('VS×ケイパビリティ関係'!$F$4:$F$494,$B27,'VS×ケイパビリティ関係'!$G$4:$G$494,H$5,'VS×ケイパビリティ関係'!$E$4:$E$494,"支援")>0,"○","")) | I27: =IF(COUNTIFS('VS×ケイパビリティ関係'!$F$4:$F$494,$B27,'VS×ケイパビリティ関係'!$G$4:$G$494,I$5,'VS×ケイパビリティ関係'!$E$4:$E$494,"主")>0,"●",IF(COUNTIFS('VS×ケイパビリティ関係'!$F$4:$F$494,$B27,'VS×ケイパビリティ関係'!$G$4:$G$494,I$5,'VS×ケイパビリティ関係'!$E$4:$E$494,"支援")>0,"○","")) | J27: =IF(COUNTIFS('VS×ケイパビリティ関係'!$F$4:$F$494,$B27,'VS×ケイパビリティ関係'!$G$4:$G$494,J$5,'VS×ケイパビリティ関係'!$E$4:$E$494,"主")>0,"●",IF(COUNTIFS('VS×ケイパビリティ関係'!$F$4:$F$494,$B27,'VS×ケイパビリティ関係'!$G$4:$G$494,J$5,'VS×ケイパビリティ関係'!$E$4:$E$494,"支援")>0,"○","")) | K27: =IF(COUNTIFS('VS×ケイパビリティ関係'!$F$4:$F$494,$B27,'VS×ケイパビリティ関係'!$G$4:$G$494,K$5,'VS×ケイパビリティ関係'!$E$4:$E$494,"主")>0,"●",IF(COUNTIFS('VS×ケイパビリティ関係'!$F$4:$F$494,$B27,'VS×ケイパビリティ関係'!$G$4:$G$494,K$5,'VS×ケイパビリティ関係'!$E$4:$E$494,"支援")>0,"○","")) | ... BD27: =IF(COUNTIFS('VS×ケイパビリティ関係'!$F$4:$F$494,$B27,'VS×ケイパビリティ関係'!$G$4:$G$494,BD$5,'VS×ケイパビリティ関係'!$E$4:$E$494,"主")>0,"●",IF(COUNTIFS('VS×ケイパビリティ関係'!$F$4:$F$494,$B27,'VS×ケイパビリティ関係'!$G$4:$G$494,BD$5,'VS×ケイパビリティ関係'!$E$4:$E$494,"支援")>0,"○","")) | BE27: =COUNTIF(D27:BD27,"●") -> 2 | BF27: =COUNTIF(D27:BD27,"○") -> 4
B28: 05-03 | C28: 承認取得 | D28: =IF(COUNTIFS('VS×ケイパビリティ関係'!$F$4:$F$494,$B28,'VS×ケイパビリティ関係'!$G$4:$G$494,D$5,'VS×ケイパビリティ関係'!$E$4:$E$494,"主")>0,"●",IF(COUNTIFS('VS×ケイパビリティ関係'!$F$4:$F$494,$B28,'VS×ケイパビリティ関係'!$G$4:$G$494,D$5,'VS×ケイパビリティ関係'!$E$4:$E$494,"支援")>0,"○","")) | E28: =IF(COUNTIFS('VS×ケイパビリティ関係'!$F$4:$F$494,$B28,'VS×ケイパビリティ関係'!$G$4:$G$494,E$5,'VS×ケイパビリティ関係'!$E$4:$E$494,"主")>0,"●",IF(COUNTIFS('VS×ケイパビリティ関係'!$F$4:$F$494,$B28,'VS×ケイパビリティ関係'!$G$4:$G$494,E$5,'VS×ケイパビリティ関係'!$E$4:$E$494,"支援")>0,"○","")) | F28: =IF(COUNTIFS('VS×ケイパビリティ関係'!$F$4:$F$494,$B28,'VS×ケイパビリティ関係'!$G$4:$G$494,F$5,'VS×ケイパビリティ関係'!$E$4:$E$494,"主")>0,"●",IF(COUNTIFS('VS×ケイパビリティ関係'!$F$4:$F$494,$B28,'VS×ケイパビリティ関係'!$G$4:$G$494,F$5,'VS×ケイパビリティ関係'!$E$4:$E$494,"支援")>0,"○","")) | G28: =IF(COUNTIFS('VS×ケイパビリティ関係'!$F$4:$F$494,$B28,'VS×ケイパビリティ関係'!$G$4:$G$494,G$5,'VS×ケイパビリティ関係'!$E$4:$E$494,"主")>0,"●",IF(COUNTIFS('VS×ケイパビリティ関係'!$F$4:$F$494,$B28,'VS×ケイパビリティ関係'!$G$4:$G$494,G$5,'VS×ケイパビリティ関係'!$E$4:$E$494,"支援")>0,"○","")) | H28: =IF(COUNTIFS('VS×ケイパビリティ関係'!$F$4:$F$494,$B28,'VS×ケイパビリティ関係'!$G$4:$G$494,H$5,'VS×ケイパビリティ関係'!$E$4:$E$494,"主")>0,"●",IF(COUNTIFS('VS×ケイパビリティ関係'!$F$4:$F$494,$B28,'VS×ケイパビリティ関係'!$G$4:$G$494,H$5,'VS×ケイパビリティ関係'!$E$4:$E$494,"支援")>0,"○","")) | I28: =IF(COUNTIFS('VS×ケイパビリティ関係'!$F$4:$F$494,$B28,'VS×ケイパビリティ関係'!$G$4:$G$494,I$5,'VS×ケイパビリティ関係'!$E$4:$E$494,"主")>0,"●",IF(COUNTIFS('VS×ケイパビリティ関係'!$F$4:$F$494,$B28,'VS×ケイパビリティ関係'!$G$4:$G$494,I$5,'VS×ケイパビリティ関係'!$E$4:$E$494,"支援")>0,"○","")) | J28: =IF(COUNTIFS('VS×ケイパビリティ関係'!$F$4:$F$494,$B28,'VS×ケイパビリティ関係'!$G$4:$G$494,J$5,'VS×ケイパビリティ関係'!$E$4:$E$494,"主")>0,"●",IF(COUNTIFS('VS×ケイパビリティ関係'!$F$4:$F$494,$B28,'VS×ケイパビリティ関係'!$G$4:$G$494,J$5,'VS×ケイパビリティ関係'!$E$4:$E$494,"支援")>0,"○","")) | K28: =IF(COUNTIFS('VS×ケイパビリティ関係'!$F$4:$F$494,$B28,'VS×ケイパビリティ関係'!$G$4:$G$494,K$5,'VS×ケイパビリティ関係'!$E$4:$E$494,"主")>0,"●",IF(COUNTIFS('VS×ケイパビリティ関係'!$F$4:$F$494,$B28,'VS×ケイパビリティ関係'!$G$4:$G$494,K$5,'VS×ケイパビリティ関係'!$E$4:$E$494,"支援")>0,"○","")) | ... BD28: =IF(COUNTIFS('VS×ケイパビリティ関係'!$F$4:$F$494,$B28,'VS×ケイパビリティ関係'!$G$4:$G$494,BD$5,'VS×ケイパビリティ関係'!$E$4:$E$494,"主")>0,"●",IF(COUNTIFS('VS×ケイパビリティ関係'!$F$4:$F$494,$B28,'VS×ケイパビリティ関係'!$G$4:$G$494,BD$5,'VS×ケイパビリティ関係'!$E$4:$E$494,"支援")>0,"○","")) | BE28: =COUNTIF(D28:BD28,"●") -> 4 | BF28: =COUNTIF(D28:BD28,"○") -> 1
A29: 06 商用製造（継続） | B29: 06-01 | C29: 原薬製造（培養・精製） | D29: =IF(COUNTIFS('VS×ケイパビリティ関係'!$F$4:$F$494,$B29,'VS×ケイパビリティ関係'!$G$4:$G$494,D$5,'VS×ケイパビリティ関係'!$E$4:$E$494,"主")>0,"●",IF(COUNTIFS('VS×ケイパビリティ関係'!$F$4:$F$494,$B29,'VS×ケイパビリティ関係'!$G$4:$G$494,D$5,'VS×ケイパビリティ関係'!$E$4:$E$494,"支援")>0,"○","")) | E29: =IF(COUNTIFS('VS×ケイパビリティ関係'!$F$4:$F$494,$B29,'VS×ケイパビリティ関係'!$G$4:$G$494,E$5,'VS×ケイパビリティ関係'!$E$4:$E$494,"主")>0,"●",IF(COUNTIFS('VS×ケイパビリティ関係'!$F$4:$F$494,$B29,'VS×ケイパビリティ関係'!$G$4:$G$494,E$5,'VS×ケイパビリティ関係'!$E$4:$E$494,"支援")>0,"○","")) | F29: =IF(COUNTIFS('VS×ケイパビリティ関係'!$F$4:$F$494,$B29,'VS×ケイパビリティ関係'!$G$4:$G$494,F$5,'VS×ケイパビリティ関係'!$E$4:$E$494,"主")>0,"●",IF(COUNTIFS('VS×ケイパビリティ関係'!$F$4:$F$494,$B29,'VS×ケイパビリティ関係'!$G$4:$G$494,F$5,'VS×ケイパビリティ関係'!$E$4:$E$494,"支援")>0,"○","")) | G29: =IF(COUNTIFS('VS×ケイパビリティ関係'!$F$4:$F$494,$B29,'VS×ケイパビリティ関係'!$G$4:$G$494,G$5,'VS×ケイパビリティ関係'!$E$4:$E$494,"主")>0,"●",IF(COUNTIFS('VS×ケイパビリティ関係'!$F$4:$F$494,$B29,'VS×ケイパビリティ関係'!$G$4:$G$494,G$5,'VS×ケイパビリティ関係'!$E$4:$E$494,"支援")>0,"○","")) | H29: =IF(COUNTIFS('VS×ケイパビリティ関係'!$F$4:$F$494,$B29,'VS×ケイパビリティ関係'!$G$4:$G$494,H$5,'VS×ケイパビリティ関係'!$E$4:$E$494,"主")>0,"●",IF(COUNTIFS('VS×ケイパビリティ関係'!$F$4:$F$494,$B29,'VS×ケイパビリティ関係'!$G$4:$G$494,H$5,'VS×ケイパビリティ関係'!$E$4:$E$494,"支援")>0,"○","")) | I29: =IF(COUNTIFS('VS×ケイパビリティ関係'!$F$4:$F$494,$B29,'VS×ケイパビリティ関係'!$G$4:$G$494,I$5,'VS×ケイパビリティ関係'!$E$4:$E$494,"主")>0,"●",IF(COUNTIFS('VS×ケイパビリティ関係'!$F$4:$F$494,$B29,'VS×ケイパビリティ関係'!$G$4:$G$494,I$5,'VS×ケイパビリティ関係'!$E$4:$E$494,"支援")>0,"○","")) | J29: =IF(COUNTIFS('VS×ケイパビリティ関係'!$F$4:$F$494,$B29,'VS×ケイパビリティ関係'!$G$4:$G$494,J$5,'VS×ケイパビリティ関係'!$E$4:$E$494,"主")>0,"●",IF(COUNTIFS('VS×ケイパビリティ関係'!$F$4:$F$494,$B29,'VS×ケイパビリティ関係'!$G$4:$G$494,J$5,'VS×ケイパビリティ関係'!$E$4:$E$494,"支援")>0,"○","")) | K29: =IF(COUNTIFS('VS×ケイパビリティ関係'!$F$4:$F$494,$B29,'VS×ケイパビリティ関係'!$G$4:$G$494,K$5,'VS×ケイパビリティ関係'!$E$4:$E$494,"主")>0,"●",IF(COUNTIFS('VS×ケイパビリティ関係'!$F$4:$F$494,$B29,'VS×ケイパビリティ関係'!$G$4:$G$494,K$5,'VS×ケイパビリティ関係'!$E$4:$E$494,"支援")>0,"○","")) | ... BD29: =IF(COUNTIFS('VS×ケイパビリティ関係'!$F$4:$F$494,$B29,'VS×ケイパビリティ関係'!$G$4:$G$494,BD$5,'VS×ケイパビリティ関係'!$E$4:$E$494,"主")>0,"●",IF(COUNTIFS('VS×ケイパビリティ関係'!$F$4:$F$494,$B29,'VS×ケイパビリティ関係'!$G$4:$G$494,BD$5,'VS×ケイパビリティ関係'!$E$4:$E$494,"支援")>0,"○","")) | BE29: =COUNTIF(D29:BD29,"●") -> 2 | BF29: =COUNTIF(D29:BD29,"○") -> 2
B30: 06-02 | C30: 製剤化・充填・包装 | D30: =IF(COUNTIFS('VS×ケイパビリティ関係'!$F$4:$F$494,$B30,'VS×ケイパビリティ関係'!$G$4:$G$494,D$5,'VS×ケイパビリティ関係'!$E$4:$E$494,"主")>0,"●",IF(COUNTIFS('VS×ケイパビリティ関係'!$F$4:$F$494,$B30,'VS×ケイパビリティ関係'!$G$4:$G$494,D$5,'VS×ケイパビリティ関係'!$E$4:$E$494,"支援")>0,"○","")) | E30: =IF(COUNTIFS('VS×ケイパビリティ関係'!$F$4:$F$494,$B30,'VS×ケイパビリティ関係'!$G$4:$G$494,E$5,'VS×ケイパビリティ関係'!$E$4:$E$494,"主")>0,"●",IF(COUNTIFS('VS×ケイパビリティ関係'!$F$4:$F$494,$B30,'VS×ケイパビリティ関係'!$G$4:$G$494,E$5,'VS×ケイパビリティ関係'!$E$4:$E$494,"支援")>0,"○","")) | F30: =IF(COUNTIFS('VS×ケイパビリティ関係'!$F$4:$F$494,$B30,'VS×ケイパビリティ関係'!$G$4:$G$494,F$5,'VS×ケイパビリティ関係'!$E$4:$E$494,"主")>0,"●",IF(COUNTIFS('VS×ケイパビリティ関係'!$F$4:$F$494,$B30,'VS×ケイパビリティ関係'!$G$4:$G$494,F$5,'VS×ケイパビリティ関係'!$E$4:$E$494,"支援")>0,"○","")) | G30: =IF(COUNTIFS('VS×ケイパビリティ関係'!$F$4:$F$494,$B30,'VS×ケイパビリティ関係'!$G$4:$G$494,G$5,'VS×ケイパビリティ関係'!$E$4:$E$494,"主")>0,"●",IF(COUNTIFS('VS×ケイパビリティ関係'!$F$4:$F$494,$B30,'VS×ケイパビリティ関係'!$G$4:$G$494,G$5,'VS×ケイパビリティ関係'!$E$4:$E$494,"支援")>0,"○","")) | H30: =IF(COUNTIFS('VS×ケイパビリティ関係'!$F$4:$F$494,$B30,'VS×ケイパビリティ関係'!$G$4:$G$494,H$5,'VS×ケイパビリティ関係'!$E$4:$E$494,"主")>0,"●",IF(COUNTIFS('VS×ケイパビリティ関係'!$F$4:$F$494,$B30,'VS×ケイパビリティ関係'!$G$4:$G$494,H$5,'VS×ケイパビリティ関係'!$E$4:$E$494,"支援")>0,"○","")) | I30: =IF(COUNTIFS('VS×ケイパビリティ関係'!$F$4:$F$494,$B30,'VS×ケイパビリティ関係'!$G$4:$G$494,I$5,'VS×ケイパビリティ関係'!$E$4:$E$494,"主")>0,"●",IF(COUNTIFS('VS×ケイパビリティ関係'!$F$4:$F$494,$B30,'VS×ケイパビリティ関係'!$G$4:$G$494,I$5,'VS×ケイパビリティ関係'!$E$4:$E$494,"支援")>0,"○","")) | J30: =IF(COUNTIFS('VS×ケイパビリティ関係'!$F$4:$F$494,$B30,'VS×ケイパビリティ関係'!$G$4:$G$494,J$5,'VS×ケイパビリティ関係'!$E$4:$E$494,"主")>0,"●",IF(COUNTIFS('VS×ケイパビリティ関係'!$F$4:$F$494,$B30,'VS×ケイパビリティ関係'!$G$4:$G$494,J$5,'VS×ケイパビリティ関係'!$E$4:$E$494,"支援")>0,"○","")) | K30: =IF(COUNTIFS('VS×ケイパビリティ関係'!$F$4:$F$494,$B30,'VS×ケイパビリティ関係'!$G$4:$G$494,K$5,'VS×ケイパビリティ関係'!$E$4:$E$494,"主")>0,"●",IF(COUNTIFS('VS×ケイパビリティ関係'!$F$4:$F$494,$B30,'VS×ケイパビリティ関係'!$G$4:$G$494,K$5,'VS×ケイパビリティ関係'!$E$4:$E$494,"支援")>0,"○","")) | ... BD30: =IF(COUNTIFS('VS×ケイパビリティ関係'!$F$4:$F$494,$B30,'VS×ケイパビリティ関係'!$G$4:$G$494,BD$5,'VS×ケイパビリティ関係'!$E$4:$E$494,"主")>0,"●",IF(COUNTIFS('VS×ケイパビリティ関係'!$F$4:$F$494,$B30,'VS×ケイパビリティ関係'!$G$4:$G$494,BD$5,'VS×ケイパビリティ関係'!$E$4:$E$494,"支援")>0,"○","")) | BE30: =COUNTIF(D30:BD30,"●") -> 1 | BF30: =COUNTIF(D30:BD30,"○") -> 2
B31: 06-03 | C31: 品質試験・出荷判定 | D31: =IF(COUNTIFS('VS×ケイパビリティ関係'!$F$4:$F$494,$B31,'VS×ケイパビリティ関係'!$G$4:$G$494,D$5,'VS×ケイパビリティ関係'!$E$4:$E$494,"主")>0,"●",IF(COUNTIFS('VS×ケイパビリティ関係'!$F$4:$F$494,$B31,'VS×ケイパビリティ関係'!$G$4:$G$494,D$5,'VS×ケイパビリティ関係'!$E$4:$E$494,"支援")>0,"○","")) | E31: =IF(COUNTIFS('VS×ケイパビリティ関係'!$F$4:$F$494,$B31,'VS×ケイパビリティ関係'!$G$4:$G$494,E$5,'VS×ケイパビリティ関係'!$E$4:$E$494,"主")>0,"●",IF(COUNTIFS('VS×ケイパビリティ関係'!$F$4:$F$494,$B31,'VS×ケイパビリティ関係'!$G$4:$G$494,E$5,'VS×ケイパビリティ関係'!$E$4:$E$494,"支援")>0,"○","")) | F31: =IF(COUNTIFS('VS×ケイパビリティ関係'!$F$4:$F$494,$B31,'VS×ケイパビリティ関係'!$G$4:$G$494,F$5,'VS×ケイパビリティ関係'!$E$4:$E$494,"主")>0,"●",IF(COUNTIFS('VS×ケイパビリティ関係'!$F$4:$F$494,$B31,'VS×ケイパビリティ関係'!$G$4:$G$494,F$5,'VS×ケイパビリティ関係'!$E$4:$E$494,"支援")>0,"○","")) | G31: =IF(COUNTIFS('VS×ケイパビリティ関係'!$F$4:$F$494,$B31,'VS×ケイパビリティ関係'!$G$4:$G$494,G$5,'VS×ケイパビリティ関係'!$E$4:$E$494,"主")>0,"●",IF(COUNTIFS('VS×ケイパビリティ関係'!$F$4:$F$494,$B31,'VS×ケイパビリティ関係'!$G$4:$G$494,G$5,'VS×ケイパビリティ関係'!$E$4:$E$494,"支援")>0,"○","")) | H31: =IF(COUNTIFS('VS×ケイパビリティ関係'!$F$4:$F$494,$B31,'VS×ケイパビリティ関係'!$G$4:$G$494,H$5,'VS×ケイパビリティ関係'!$E$4:$E$494,"主")>0,"●",IF(COUNTIFS('VS×ケイパビリティ関係'!$F$4:$F$494,$B31,'VS×ケイパビリティ関係'!$G$4:$G$494,H$5,'VS×ケイパビリティ関係'!$E$4:$E$494,"支援")>0,"○","")) | I31: =IF(COUNTIFS('VS×ケイパビリティ関係'!$F$4:$F$494,$B31,'VS×ケイパビリティ関係'!$G$4:$G$494,I$5,'VS×ケイパビリティ関係'!$E$4:$E$494,"主")>0,"●",IF(COUNTIFS('VS×ケイパビリティ関係'!$F$4:$F$494,$B31,'VS×ケイパビリティ関係'!$G$4:$G$494,I$5,'VS×ケイパビリティ関係'!$E$4:$E$494,"支援")>0,"○","")) | J31: =IF(COUNTIFS('VS×ケイパビリティ関係'!$F$4:$F$494,$B31,'VS×ケイパビリティ関係'!$G$4:$G$494,J$5,'VS×ケイパビリティ関係'!$E$4:$E$494,"主")>0,"●",IF(COUNTIFS('VS×ケイパビリティ関係'!$F$4:$F$494,$B31,'VS×ケイパビリティ関係'!$G$4:$G$494,J$5,'VS×ケイパビリティ関係'!$E$4:$E$494,"支援")>0,"○","")) | K31: =IF(COUNTIFS('VS×ケイパビリティ関係'!$F$4:$F$494,$B31,'VS×ケイパビリティ関係'!$G$4:$G$494,K$5,'VS×ケイパビリティ関係'!$E$4:$E$494,"主")>0,"●",IF(COUNTIFS('VS×ケイパビリティ関係'!$F$4:$F$494,$B31,'VS×ケイパビリティ関係'!$G$4:$G$494,K$5,'VS×ケイパビリティ関係'!$E$4:$E$494,"支援")>0,"○","")) | ... BD31: =IF(COUNTIFS('VS×ケイパビリティ関係'!$F$4:$F$494,$B31,'VS×ケイパビリティ関係'!$G$4:$G$494,BD$5,'VS×ケイパビリティ関係'!$E$4:$E$494,"主")>0,"●",IF(COUNTIFS('VS×ケイパビリティ関係'!$F$4:$F$494,$B31,'VS×ケイパビリティ関係'!$G$4:$G$494,BD$5,'VS×ケイパビリティ関係'!$E$4:$E$494,"支援")>0,"○","")) | BE31: =COUNTIF(D31:BD31,"●") -> 2 | BF31: =COUNTIF(D31:BD31,"○") -> 2
A32: 07 上市（1回きり） | B32: 07-01 | C32: 価格設定・市場アクセス | D32: =IF(COUNTIFS('VS×ケイパビリティ関係'!$F$4:$F$494,$B32,'VS×ケイパビリティ関係'!$G$4:$G$494,D$5,'VS×ケイパビリティ関係'!$E$4:$E$494,"主")>0,"●",IF(COUNTIFS('VS×ケイパビリティ関係'!$F$4:$F$494,$B32,'VS×ケイパビリティ関係'!$G$4:$G$494,D$5,'VS×ケイパビリティ関係'!$E$4:$E$494,"支援")>0,"○","")) | E32: =IF(COUNTIFS('VS×ケイパビリティ関係'!$F$4:$F$494,$B32,'VS×ケイパビリティ関係'!$G$4:$G$494,E$5,'VS×ケイパビリティ関係'!$E$4:$E$494,"主")>0,"●",IF(COUNTIFS('VS×ケイパビリティ関係'!$F$4:$F$494,$B32,'VS×ケイパビリティ関係'!$G$4:$G$494,E$5,'VS×ケイパビリティ関係'!$E$4:$E$494,"支援")>0,"○","")) | F32: =IF(COUNTIFS('VS×ケイパビリティ関係'!$F$4:$F$494,$B32,'VS×ケイパビリティ関係'!$G$4:$G$494,F$5,'VS×ケイパビリティ関係'!$E$4:$E$494,"主")>0,"●",IF(COUNTIFS('VS×ケイパビリティ関係'!$F$4:$F$494,$B32,'VS×ケイパビリティ関係'!$G$4:$G$494,F$5,'VS×ケイパビリティ関係'!$E$4:$E$494,"支援")>0,"○","")) | G32: =IF(COUNTIFS('VS×ケイパビリティ関係'!$F$4:$F$494,$B32,'VS×ケイパビリティ関係'!$G$4:$G$494,G$5,'VS×ケイパビリティ関係'!$E$4:$E$494,"主")>0,"●",IF(COUNTIFS('VS×ケイパビリティ関係'!$F$4:$F$494,$B32,'VS×ケイパビリティ関係'!$G$4:$G$494,G$5,'VS×ケイパビリティ関係'!$E$4:$E$494,"支援")>0,"○","")) | H32: =IF(COUNTIFS('VS×ケイパビリティ関係'!$F$4:$F$494,$B32,'VS×ケイパビリティ関係'!$G$4:$G$494,H$5,'VS×ケイパビリティ関係'!$E$4:$E$494,"主")>0,"●",IF(COUNTIFS('VS×ケイパビリティ関係'!$F$4:$F$494,$B32,'VS×ケイパビリティ関係'!$G$4:$G$494,H$5,'VS×ケイパビリティ関係'!$E$4:$E$494,"支援")>0,"○","")) | I32: =IF(COUNTIFS('VS×ケイパビリティ関係'!$F$4:$F$494,$B32,'VS×ケイパビリティ関係'!$G$4:$G$494,I$5,'VS×ケイパビリティ関係'!$E$4:$E$494,"主")>0,"●",IF(COUNTIFS('VS×ケイパビリティ関係'!$F$4:$F$494,$B32,'VS×ケイパビリティ関係'!$G$4:$G$494,I$5,'VS×ケイパビリティ関係'!$E$4:$E$494,"支援")>0,"○","")) | J32: =IF(COUNTIFS('VS×ケイパビリティ関係'!$F$4:$F$494,$B32,'VS×ケイパビリティ関係'!$G$4:$G$494,J$5,'VS×ケイパビリティ関係'!$E$4:$E$494,"主")>0,"●",IF(COUNTIFS('VS×ケイパビリティ関係'!$F$4:$F$494,$B32,'VS×ケイパビリティ関係'!$G$4:$G$494,J$5,'VS×ケイパビリティ関係'!$E$4:$E$494,"支援")>0,"○","")) | K32: =IF(COUNTIFS('VS×ケイパビリティ関係'!$F$4:$F$494,$B32,'VS×ケイパビリティ関係'!$G$4:$G$494,K$5,'VS×ケイパビリティ関係'!$E$4:$E$494,"主")>0,"●",IF(COUNTIFS('VS×ケイパビリティ関係'!$F$4:$F$494,$B32,'VS×ケイパビリティ関係'!$G$4:$G$494,K$5,'VS×ケイパビリティ関係'!$E$4:$E$494,"支援")>0,"○","")) | ... BD32: =IF(COUNTIFS('VS×ケイパビリティ関係'!$F$4:$F$494,$B32,'VS×ケイパビリティ関係'!$G$4:$G$494,BD$5,'VS×ケイパビリティ関係'!$E$4:$E$494,"主")>0,"●",IF(COUNTIFS('VS×ケイパビリティ関係'!$F$4:$F$494,$B32,'VS×ケイパビリティ関係'!$G$4:$G$494,BD$5,'VS×ケイパビリティ関係'!$E$4:$E$494,"支援")>0,"○","")) | BE32: =COUNTIF(D32:BD32,"●") -> 3 | BF32: =COUNTIF(D32:BD32,"○") -> 2
B33: 07-02 | C33: 上市準備 | D33: =IF(COUNTIFS('VS×ケイパビリティ関係'!$F$4:$F$494,$B33,'VS×ケイパビリティ関係'!$G$4:$G$494,D$5,'VS×ケイパビリティ関係'!$E$4:$E$494,"主")>0,"●",IF(COUNTIFS('VS×ケイパビリティ関係'!$F$4:$F$494,$B33,'VS×ケイパビリティ関係'!$G$4:$G$494,D$5,'VS×ケイパビリティ関係'!$E$4:$E$494,"支援")>0,"○","")) | E33: =IF(COUNTIFS('VS×ケイパビリティ関係'!$F$4:$F$494,$B33,'VS×ケイパビリティ関係'!$G$4:$G$494,E$5,'VS×ケイパビリティ関係'!$E$4:$E$494,"主")>0,"●",IF(COUNTIFS('VS×ケイパビリティ関係'!$F$4:$F$494,$B33,'VS×ケイパビリティ関係'!$G$4:$G$494,E$5,'VS×ケイパビリティ関係'!$E$4:$E$494,"支援")>0,"○","")) | F33: =IF(COUNTIFS('VS×ケイパビリティ関係'!$F$4:$F$494,$B33,'VS×ケイパビリティ関係'!$G$4:$G$494,F$5,'VS×ケイパビリティ関係'!$E$4:$E$494,"主")>0,"●",IF(COUNTIFS('VS×ケイパビリティ関係'!$F$4:$F$494,$B33,'VS×ケイパビリティ関係'!$G$4:$G$494,F$5,'VS×ケイパビリティ関係'!$E$4:$E$494,"支援")>0,"○","")) | G33: =IF(COUNTIFS('VS×ケイパビリティ関係'!$F$4:$F$494,$B33,'VS×ケイパビリティ関係'!$G$4:$G$494,G$5,'VS×ケイパビリティ関係'!$E$4:$E$494,"主")>0,"●",IF(COUNTIFS('VS×ケイパビリティ関係'!$F$4:$F$494,$B33,'VS×ケイパビリティ関係'!$G$4:$G$494,G$5,'VS×ケイパビリティ関係'!$E$4:$E$494,"支援")>0,"○","")) | H33: =IF(COUNTIFS('VS×ケイパビリティ関係'!$F$4:$F$494,$B33,'VS×ケイパビリティ関係'!$G$4:$G$494,H$5,'VS×ケイパビリティ関係'!$E$4:$E$494,"主")>0,"●",IF(COUNTIFS('VS×ケイパビリティ関係'!$F$4:$F$494,$B33,'VS×ケイパビリティ関係'!$G$4:$G$494,H$5,'VS×ケイパビリティ関係'!$E$4:$E$494,"支援")>0,"○","")) | I33: =IF(COUNTIFS('VS×ケイパビリティ関係'!$F$4:$F$494,$B33,'VS×ケイパビリティ関係'!$G$4:$G$494,I$5,'VS×ケイパビリティ関係'!$E$4:$E$494,"主")>0,"●",IF(COUNTIFS('VS×ケイパビリティ関係'!$F$4:$F$494,$B33,'VS×ケイパビリティ関係'!$G$4:$G$494,I$5,'VS×ケイパビリティ関係'!$E$4:$E$494,"支援")>0,"○","")) | J33: =IF(COUNTIFS('VS×ケイパビリティ関係'!$F$4:$F$494,$B33,'VS×ケイパビリティ関係'!$G$4:$G$494,J$5,'VS×ケイパビリティ関係'!$E$4:$E$494,"主")>0,"●",IF(COUNTIFS('VS×ケイパビリティ関係'!$F$4:$F$494,$B33,'VS×ケイパビリティ関係'!$G$4:$G$494,J$5,'VS×ケイパビリティ関係'!$E$4:$E$494,"支援")>0,"○","")) | K33: =IF(COUNTIFS('VS×ケイパビリティ関係'!$F$4:$F$494,$B33,'VS×ケイパビリティ関係'!$G$4:$G$494,K$5,'VS×ケイパビリティ関係'!$E$4:$E$494,"主")>0,"●",IF(COUNTIFS('VS×ケイパビリティ関係'!$F$4:$F$494,$B33,'VS×ケイパビリティ関係'!$G$4:$G$494,K$5,'VS×ケイパビリティ関係'!$E$4:$E$494,"支援")>0,"○","")) | ... BD33: =IF(COUNTIFS('VS×ケイパビリティ関係'!$F$4:$F$494,$B33,'VS×ケイパビリティ関係'!$G$4:$G$494,BD$5,'VS×ケイパビリティ関係'!$E$4:$E$494,"主")>0,"●",IF(COUNTIFS('VS×ケイパビリティ関係'!$F$4:$F$494,$B33,'VS×ケイパビリティ関係'!$G$4:$G$494,BD$5,'VS×ケイパビリティ関係'!$E$4:$E$494,"支援")>0,"○","")) | BE33: =COUNTIF(D33:BD33,"●") -> 5 | BF33: =COUNTIF(D33:BD33,"○") -> 2
A34: 08 供給・流通（継続） | B34: 08-01 | C34: 受注・需給調整 | D34: =IF(COUNTIFS('VS×ケイパビリティ関係'!$F$4:$F$494,$B34,'VS×ケイパビリティ関係'!$G$4:$G$494,D$5,'VS×ケイパビリティ関係'!$E$4:$E$494,"主")>0,"●",IF(COUNTIFS('VS×ケイパビリティ関係'!$F$4:$F$494,$B34,'VS×ケイパビリティ関係'!$G$4:$G$494,D$5,'VS×ケイパビリティ関係'!$E$4:$E$494,"支援")>0,"○","")) | E34: =IF(COUNTIFS('VS×ケイパビリティ関係'!$F$4:$F$494,$B34,'VS×ケイパビリティ関係'!$G$4:$G$494,E$5,'VS×ケイパビリティ関係'!$E$4:$E$494,"主")>0,"●",IF(COUNTIFS('VS×ケイパビリティ関係'!$F$4:$F$494,$B34,'VS×ケイパビリティ関係'!$G$4:$G$494,E$5,'VS×ケイパビリティ関係'!$E$4:$E$494,"支援")>0,"○","")) | F34: =IF(COUNTIFS('VS×ケイパビリティ関係'!$F$4:$F$494,$B34,'VS×ケイパビリティ関係'!$G$4:$G$494,F$5,'VS×ケイパビリティ関係'!$E$4:$E$494,"主")>0,"●",IF(COUNTIFS('VS×ケイパビリティ関係'!$F$4:$F$494,$B34,'VS×ケイパビリティ関係'!$G$4:$G$494,F$5,'VS×ケイパビリティ関係'!$E$4:$E$494,"支援")>0,"○","")) | G34: =IF(COUNTIFS('VS×ケイパビリティ関係'!$F$4:$F$494,$B34,'VS×ケイパビリティ関係'!$G$4:$G$494,G$5,'VS×ケイパビリティ関係'!$E$4:$E$494,"主")>0,"●",IF(COUNTIFS('VS×ケイパビリティ関係'!$F$4:$F$494,$B34,'VS×ケイパビリティ関係'!$G$4:$G$494,G$5,'VS×ケイパビリティ関係'!$E$4:$E$494,"支援")>0,"○","")) | H34: =IF(COUNTIFS('VS×ケイパビリティ関係'!$F$4:$F$494,$B34,'VS×ケイパビリティ関係'!$G$4:$G$494,H$5,'VS×ケイパビリティ関係'!$E$4:$E$494,"主")>0,"●",IF(COUNTIFS('VS×ケイパビリティ関係'!$F$4:$F$494,$B34,'VS×ケイパビリティ関係'!$G$4:$G$494,H$5,'VS×ケイパビリティ関係'!$E$4:$E$494,"支援")>0,"○","")) | I34: =IF(COUNTIFS('VS×ケイパビリティ関係'!$F$4:$F$494,$B34,'VS×ケイパビリティ関係'!$G$4:$G$494,I$5,'VS×ケイパビリティ関係'!$E$4:$E$494,"主")>0,"●",IF(COUNTIFS('VS×ケイパビリティ関係'!$F$4:$F$494,$B34,'VS×ケイパビリティ関係'!$G$4:$G$494,I$5,'VS×ケイパビリティ関係'!$E$4:$E$494,"支援")>0,"○","")) | J34: =IF(COUNTIFS('VS×ケイパビリティ関係'!$F$4:$F$494,$B34,'VS×ケイパビリティ関係'!$G$4:$G$494,J$5,'VS×ケイパビリティ関係'!$E$4:$E$494,"主")>0,"●",IF(COUNTIFS('VS×ケイパビリティ関係'!$F$4:$F$494,$B34,'VS×ケイパビリティ関係'!$G$4:$G$494,J$5,'VS×ケイパビリティ関係'!$E$4:$E$494,"支援")>0,"○","")) | K34: =IF(COUNTIFS('VS×ケイパビリティ関係'!$F$4:$F$494,$B34,'VS×ケイパビリティ関係'!$G$4:$G$494,K$5,'VS×ケイパビリティ関係'!$E$4:$E$494,"主")>0,"●",IF(COUNTIFS('VS×ケイパビリティ関係'!$F$4:$F$494,$B34,'VS×ケイパビリティ関係'!$G$4:$G$494,K$5,'VS×ケイパビリティ関係'!$E$4:$E$494,"支援")>0,"○","")) | ... BD34: =IF(COUNTIFS('VS×ケイパビリティ関係'!$F$4:$F$494,$B34,'VS×ケイパビリティ関係'!$G$4:$G$494,BD$5,'VS×ケイパビリティ関係'!$E$4:$E$494,"主")>0,"●",IF(COUNTIFS('VS×ケイパビリティ関係'!$F$4:$F$494,$B34,'VS×ケイパビリティ関係'!$G$4:$G$494,BD$5,'VS×ケイパビリティ関係'!$E$4:$E$494,"支援")>0,"○","")) | BE34: =COUNTIF(D34:BD34,"●") -> 2 | BF34: =COUNTIF(D34:BD34,"○") -> 2
B35: 08-02 | C35: コールドチェーン流通 | D35: =IF(COUNTIFS('VS×ケイパビリティ関係'!$F$4:$F$494,$B35,'VS×ケイパビリティ関係'!$G$4:$G$494,D$5,'VS×ケイパビリティ関係'!$E$4:$E$494,"主")>0,"●",IF(COUNTIFS('VS×ケイパビリティ関係'!$F$4:$F$494,$B35,'VS×ケイパビリティ関係'!$G$4:$G$494,D$5,'VS×ケイパビリティ関係'!$E$4:$E$494,"支援")>0,"○","")) | E35: =IF(COUNTIFS('VS×ケイパビリティ関係'!$F$4:$F$494,$B35,'VS×ケイパビリティ関係'!$G$4:$G$494,E$5,'VS×ケイパビリティ関係'!$E$4:$E$494,"主")>0,"●",IF(COUNTIFS('VS×ケイパビリティ関係'!$F$4:$F$494,$B35,'VS×ケイパビリティ関係'!$G$4:$G$494,E$5,'VS×ケイパビリティ関係'!$E$4:$E$494,"支援")>0,"○","")) | F35: =IF(COUNTIFS('VS×ケイパビリティ関係'!$F$4:$F$494,$B35,'VS×ケイパビリティ関係'!$G$4:$G$494,F$5,'VS×ケイパビリティ関係'!$E$4:$E$494,"主")>0,"●",IF(COUNTIFS('VS×ケイパビリティ関係'!$F$4:$F$494,$B35,'VS×ケイパビリティ関係'!$G$4:$G$494,F$5,'VS×ケイパビリティ関係'!$E$4:$E$494,"支援")>0,"○","")) | G35: =IF(COUNTIFS('VS×ケイパビリティ関係'!$F$4:$F$494,$B35,'VS×ケイパビリティ関係'!$G$4:$G$494,G$5,'VS×ケイパビリティ関係'!$E$4:$E$494,"主")>0,"●",IF(COUNTIFS('VS×ケイパビリティ関係'!$F$4:$F$494,$B35,'VS×ケイパビリティ関係'!$G$4:$G$494,G$5,'VS×ケイパビリティ関係'!$E$4:$E$494,"支援")>0,"○","")) | H35: =IF(COUNTIFS('VS×ケイパビリティ関係'!$F$4:$F$494,$B35,'VS×ケイパビリティ関係'!$G$4:$G$494,H$5,'VS×ケイパビリティ関係'!$E$4:$E$494,"主")>0,"●",IF(COUNTIFS('VS×ケイパビリティ関係'!$F$4:$F$494,$B35,'VS×ケイパビリティ関係'!$G$4:$G$494,H$5,'VS×ケイパビリティ関係'!$E$4:$E$494,"支援")>0,"○","")) | I35: =IF(COUNTIFS('VS×ケイパビリティ関係'!$F$4:$F$494,$B35,'VS×ケイパビリティ関係'!$G$4:$G$494,I$5,'VS×ケイパビリティ関係'!$E$4:$E$494,"主")>0,"●",IF(COUNTIFS('VS×ケイパビリティ関係'!$F$4:$F$494,$B35,'VS×ケイパビリティ関係'!$G$4:$G$494,I$5,'VS×ケイパビリティ関係'!$E$4:$E$494,"支援")>0,"○","")) | J35: =IF(COUNTIFS('VS×ケイパビリティ関係'!$F$4:$F$494,$B35,'VS×ケイパビリティ関係'!$G$4:$G$494,J$5,'VS×ケイパビリティ関係'!$E$4:$E$494,"主")>0,"●",IF(COUNTIFS('VS×ケイパビリティ関係'!$F$4:$F$494,$B35,'VS×ケイパビリティ関係'!$G$4:$G$494,J$5,'VS×ケイパビリティ関係'!$E$4:$E$494,"支援")>0,"○","")) | K35: =IF(COUNTIFS('VS×ケイパビリティ関係'!$F$4:$F$494,$B35,'VS×ケイパビリティ関係'!$G$4:$G$494,K$5,'VS×ケイパビリティ関係'!$E$4:$E$494,"主")>0,"●",IF(COUNTIFS('VS×ケイパビリティ関係'!$F$4:$F$494,$B35,'VS×ケイパビリティ関係'!$G$4:$G$494,K$5,'VS×ケイパビリティ関係'!$E$4:$E$494,"支援")>0,"○","")) | ... BD35: =IF(COUNTIFS('VS×ケイパビリティ関係'!$F$4:$F$494,$B35,'VS×ケイパビリティ関係'!$G$4:$G$494,BD$5,'VS×ケイパビリティ関係'!$E$4:$E$494,"主")>0,"●",IF(COUNTIFS('VS×ケイパビリティ関係'!$F$4:$F$494,$B35,'VS×ケイパビリティ関係'!$G$4:$G$494,BD$5,'VS×ケイパビリティ関係'!$E$4:$E$494,"支援")>0,"○","")) | BE35: =COUNTIF(D35:BD35,"●") -> 1 | BF35: =COUNTIF(D35:BD35,"○") -> 2
B36: 08-03 | C36: 医療機関・薬局への納入 | D36: =IF(COUNTIFS('VS×ケイパビリティ関係'!$F$4:$F$494,$B36,'VS×ケイパビリティ関係'!$G$4:$G$494,D$5,'VS×ケイパビリティ関係'!$E$4:$E$494,"主")>0,"●",IF(COUNTIFS('VS×ケイパビリティ関係'!$F$4:$F$494,$B36,'VS×ケイパビリティ関係'!$G$4:$G$494,D$5,'VS×ケイパビリティ関係'!$E$4:$E$494,"支援")>0,"○","")) | E36: =IF(COUNTIFS('VS×ケイパビリティ関係'!$F$4:$F$494,$B36,'VS×ケイパビリティ関係'!$G$4:$G$494,E$5,'VS×ケイパビリティ関係'!$E$4:$E$494,"主")>0,"●",IF(COUNTIFS('VS×ケイパビリティ関係'!$F$4:$F$494,$B36,'VS×ケイパビリティ関係'!$G$4:$G$494,E$5,'VS×ケイパビリティ関係'!$E$4:$E$494,"支援")>0,"○","")) | F36: =IF(COUNTIFS('VS×ケイパビリティ関係'!$F$4:$F$494,$B36,'VS×ケイパビリティ関係'!$G$4:$G$494,F$5,'VS×ケイパビリティ関係'!$E$4:$E$494,"主")>0,"●",IF(COUNTIFS('VS×ケイパビリティ関係'!$F$4:$F$494,$B36,'VS×ケイパビリティ関係'!$G$4:$G$494,F$5,'VS×ケイパビリティ関係'!$E$4:$E$494,"支援")>0,"○","")) | G36: =IF(COUNTIFS('VS×ケイパビリティ関係'!$F$4:$F$494,$B36,'VS×ケイパビリティ関係'!$G$4:$G$494,G$5,'VS×ケイパビリティ関係'!$E$4:$E$494,"主")>0,"●",IF(COUNTIFS('VS×ケイパビリティ関係'!$F$4:$F$494,$B36,'VS×ケイパビリティ関係'!$G$4:$G$494,G$5,'VS×ケイパビリティ関係'!$E$4:$E$494,"支援")>0,"○","")) | H36: =IF(COUNTIFS('VS×ケイパビリティ関係'!$F$4:$F$494,$B36,'VS×ケイパビリティ関係'!$G$4:$G$494,H$5,'VS×ケイパビリティ関係'!$E$4:$E$494,"主")>0,"●",IF(COUNTIFS('VS×ケイパビリティ関係'!$F$4:$F$494,$B36,'VS×ケイパビリティ関係'!$G$4:$G$494,H$5,'VS×ケイパビリティ関係'!$E$4:$E$494,"支援")>0,"○","")) | I36: =IF(COUNTIFS('VS×ケイパビリティ関係'!$F$4:$F$494,$B36,'VS×ケイパビリティ関係'!$G$4:$G$494,I$5,'VS×ケイパビリティ関係'!$E$4:$E$494,"主")>0,"●",IF(COUNTIFS('VS×ケイパビリティ関係'!$F$4:$F$494,$B36,'VS×ケイパビリティ関係'!$G$4:$G$494,I$5,'VS×ケイパビリティ関係'!$E$4:$E$494,"支援")>0,"○","")) | J36: =IF(COUNTIFS('VS×ケイパビリティ関係'!$F$4:$F$494,$B36,'VS×ケイパビリティ関係'!$G$4:$G$494,J$5,'VS×ケイパビリティ関係'!$E$4:$E$494,"主")>0,"●",IF(COUNTIFS('VS×ケイパビリティ関係'!$F$4:$F$494,$B36,'VS×ケイパビリティ関係'!$G$4:$G$494,J$5,'VS×ケイパビリティ関係'!$E$4:$E$494,"支援")>0,"○","")) | K36: =IF(COUNTIFS('VS×ケイパビリティ関係'!$F$4:$F$494,$B36,'VS×ケイパビリティ関係'!$G$4:$G$494,K$5,'VS×ケイパビリティ関係'!$E$4:$E$494,"主")>0,"●",IF(COUNTIFS('VS×ケイパビリティ関係'!$F$4:$F$494,$B36,'VS×ケイパビリティ関係'!$G$4:$G$494,K$5,'VS×ケイパビリティ関係'!$E$4:$E$494,"支援")>0,"○","")) | ... BD36: =IF(COUNTIFS('VS×ケイパビリティ関係'!$F$4:$F$494,$B36,'VS×ケイパビリティ関係'!$G$4:$G$494,BD$5,'VS×ケイパビリティ関係'!$E$4:$E$494,"主")>0,"●",IF(COUNTIFS('VS×ケイパビリティ関係'!$F$4:$F$494,$B36,'VS×ケイパビリティ関係'!$G$4:$G$494,BD$5,'VS×ケイパビリティ関係'!$E$4:$E$494,"支援")>0,"○","")) | BE36: =COUNTIF(D36:BD36,"●") -> 3 | BF36: =COUNTIF(D36:BD36,"○") -> 1
A37: 09 市販後 | B37: 09-01 | C37: 安全性監視（ファーマコビジランス） | D37: =IF(COUNTIFS('VS×ケイパビリティ関係'!$F$4:$F$494,$B37,'VS×ケイパビリティ関係'!$G$4:$G$494,D$5,'VS×ケイパビリティ関係'!$E$4:$E$494,"主")>0,"●",IF(COUNTIFS('VS×ケイパビリティ関係'!$F$4:$F$494,$B37,'VS×ケイパビリティ関係'!$G$4:$G$494,D$5,'VS×ケイパビリティ関係'!$E$4:$E$494,"支援")>0,"○","")) | E37: =IF(COUNTIFS('VS×ケイパビリティ関係'!$F$4:$F$494,$B37,'VS×ケイパビリティ関係'!$G$4:$G$494,E$5,'VS×ケイパビリティ関係'!$E$4:$E$494,"主")>0,"●",IF(COUNTIFS('VS×ケイパビリティ関係'!$F$4:$F$494,$B37,'VS×ケイパビリティ関係'!$G$4:$G$494,E$5,'VS×ケイパビリティ関係'!$E$4:$E$494,"支援")>0,"○","")) | F37: =IF(COUNTIFS('VS×ケイパビリティ関係'!$F$4:$F$494,$B37,'VS×ケイパビリティ関係'!$G$4:$G$494,F$5,'VS×ケイパビリティ関係'!$E$4:$E$494,"主")>0,"●",IF(COUNTIFS('VS×ケイパビリティ関係'!$F$4:$F$494,$B37,'VS×ケイパビリティ関係'!$G$4:$G$494,F$5,'VS×ケイパビリティ関係'!$E$4:$E$494,"支援")>0,"○","")) | G37: =IF(COUNTIFS('VS×ケイパビリティ関係'!$F$4:$F$494,$B37,'VS×ケイパビリティ関係'!$G$4:$G$494,G$5,'VS×ケイパビリティ関係'!$E$4:$E$494,"主")>0,"●",IF(COUNTIFS('VS×ケイパビリティ関係'!$F$4:$F$494,$B37,'VS×ケイパビリティ関係'!$G$4:$G$494,G$5,'VS×ケイパビリティ関係'!$E$4:$E$494,"支援")>0,"○","")) | H37: =IF(COUNTIFS('VS×ケイパビリティ関係'!$F$4:$F$494,$B37,'VS×ケイパビリティ関係'!$G$4:$G$494,H$5,'VS×ケイパビリティ関係'!$E$4:$E$494,"主")>0,"●",IF(COUNTIFS('VS×ケイパビリティ関係'!$F$4:$F$494,$B37,'VS×ケイパビリティ関係'!$G$4:$G$494,H$5,'VS×ケイパビリティ関係'!$E$4:$E$494,"支援")>0,"○","")) | I37: =IF(COUNTIFS('VS×ケイパビリティ関係'!$F$4:$F$494,$B37,'VS×ケイパビリティ関係'!$G$4:$G$494,I$5,'VS×ケイパビリティ関係'!$E$4:$E$494,"主")>0,"●",IF(COUNTIFS('VS×ケイパビリティ関係'!$F$4:$F$494,$B37,'VS×ケイパビリティ関係'!$G$4:$G$494,I$5,'VS×ケイパビリティ関係'!$E$4:$E$494,"支援")>0,"○","")) | J37: =IF(COUNTIFS('VS×ケイパビリティ関係'!$F$4:$F$494,$B37,'VS×ケイパビリティ関係'!$G$4:$G$494,J$5,'VS×ケイパビリティ関係'!$E$4:$E$494,"主")>0,"●",IF(COUNTIFS('VS×ケイパビリティ関係'!$F$4:$F$494,$B37,'VS×ケイパビリティ関係'!$G$4:$G$494,J$5,'VS×ケイパビリティ関係'!$E$4:$E$494,"支援")>0,"○","")) | K37: =IF(COUNTIFS('VS×ケイパビリティ関係'!$F$4:$F$494,$B37,'VS×ケイパビリティ関係'!$G$4:$G$494,K$5,'VS×ケイパビリティ関係'!$E$4:$E$494,"主")>0,"●",IF(COUNTIFS('VS×ケイパビリティ関係'!$F$4:$F$494,$B37,'VS×ケイパビリティ関係'!$G$4:$G$494,K$5,'VS×ケイパビリティ関係'!$E$4:$E$494,"支援")>0,"○","")) | ... BD37: =IF(COUNTIFS('VS×ケイパビリティ関係'!$F$4:$F$494,$B37,'VS×ケイパビリティ関係'!$G$4:$G$494,BD$5,'VS×ケイパビリティ関係'!$E$4:$E$494,"主")>0,"●",IF(COUNTIFS('VS×ケイパビリティ関係'!$F$4:$F$494,$B37,'VS×ケイパビリティ関係'!$G$4:$G$494,BD$5,'VS×ケイパビリティ関係'!$E$4:$E$494,"支援")>0,"○","")) | BE37: =COUNTIF(D37:BD37,"●") -> 2 | BF37: =COUNTIF(D37:BD37,"○") -> 4
B38: 09-02 | C38: 市販後要求・コミットメント（PMR／PMC） | D38: =IF(COUNTIFS('VS×ケイパビリティ関係'!$F$4:$F$494,$B38,'VS×ケイパビリティ関係'!$G$4:$G$494,D$5,'VS×ケイパビリティ関係'!$E$4:$E$494,"主")>0,"●",IF(COUNTIFS('VS×ケイパビリティ関係'!$F$4:$F$494,$B38,'VS×ケイパビリティ関係'!$G$4:$G$494,D$5,'VS×ケイパビリティ関係'!$E$4:$E$494,"支援")>0,"○","")) | E38: =IF(COUNTIFS('VS×ケイパビリティ関係'!$F$4:$F$494,$B38,'VS×ケイパビリティ関係'!$G$4:$G$494,E$5,'VS×ケイパビリティ関係'!$E$4:$E$494,"主")>0,"●",IF(COUNTIFS('VS×ケイパビリティ関係'!$F$4:$F$494,$B38,'VS×ケイパビリティ関係'!$G$4:$G$494,E$5,'VS×ケイパビリティ関係'!$E$4:$E$494,"支援")>0,"○","")) | F38: =IF(COUNTIFS('VS×ケイパビリティ関係'!$F$4:$F$494,$B38,'VS×ケイパビリティ関係'!$G$4:$G$494,F$5,'VS×ケイパビリティ関係'!$E$4:$E$494,"主")>0,"●",IF(COUNTIFS('VS×ケイパビリティ関係'!$F$4:$F$494,$B38,'VS×ケイパビリティ関係'!$G$4:$G$494,F$5,'VS×ケイパビリティ関係'!$E$4:$E$494,"支援")>0,"○","")) | G38: =IF(COUNTIFS('VS×ケイパビリティ関係'!$F$4:$F$494,$B38,'VS×ケイパビリティ関係'!$G$4:$G$494,G$5,'VS×ケイパビリティ関係'!$E$4:$E$494,"主")>0,"●",IF(COUNTIFS('VS×ケイパビリティ関係'!$F$4:$F$494,$B38,'VS×ケイパビリティ関係'!$G$4:$G$494,G$5,'VS×ケイパビリティ関係'!$E$4:$E$494,"支援")>0,"○","")) | H38: =IF(COUNTIFS('VS×ケイパビリティ関係'!$F$4:$F$494,$B38,'VS×ケイパビリティ関係'!$G$4:$G$494,H$5,'VS×ケイパビリティ関係'!$E$4:$E$494,"主")>0,"●",IF(COUNTIFS('VS×ケイパビリティ関係'!$F$4:$F$494,$B38,'VS×ケイパビリティ関係'!$G$4:$G$494,H$5,'VS×ケイパビリティ関係'!$E$4:$E$494,"支援")>0,"○","")) | I38: =IF(COUNTIFS('VS×ケイパビリティ関係'!$F$4:$F$494,$B38,'VS×ケイパビリティ関係'!$G$4:$G$494,I$5,'VS×ケイパビリティ関係'!$E$4:$E$494,"主")>0,"●",IF(COUNTIFS('VS×ケイパビリティ関係'!$F$4:$F$494,$B38,'VS×ケイパビリティ関係'!$G$4:$G$494,I$5,'VS×ケイパビリティ関係'!$E$4:$E$494,"支援")>0,"○","")) | J38: =IF(COUNTIFS('VS×ケイパビリティ関係'!$F$4:$F$494,$B38,'VS×ケイパビリティ関係'!$G$4:$G$494,J$5,'VS×ケイパビリティ関係'!$E$4:$E$494,"主")>0,"●",IF(COUNTIFS('VS×ケイパビリティ関係'!$F$4:$F$494,$B38,'VS×ケイパビリティ関係'!$G$4:$G$494,J$5,'VS×ケイパビリティ関係'!$E$4:$E$494,"支援")>0,"○","")) | K38: =IF(COUNTIFS('VS×ケイパビリティ関係'!$F$4:$F$494,$B38,'VS×ケイパビリティ関係'!$G$4:$G$494,K$5,'VS×ケイパビリティ関係'!$E$4:$E$494,"主")>0,"●",IF(COUNTIFS('VS×ケイパビリティ関係'!$F$4:$F$494,$B38,'VS×ケイパビリティ関係'!$G$4:$G$494,K$5,'VS×ケイパビリティ関係'!$E$4:$E$494,"支援")>0,"○","")) | ... BD38: =IF(COUNTIFS('VS×ケイパビリティ関係'!$F$4:$F$494,$B38,'VS×ケイパビリティ関係'!$G$4:$G$494,BD$5,'VS×ケイパビリティ関係'!$E$4:$E$494,"主")>0,"●",IF(COUNTIFS('VS×ケイパビリティ関係'!$F$4:$F$494,$B38,'VS×ケイパビリティ関係'!$G$4:$G$494,BD$5,'VS×ケイパビリティ関係'!$E$4:$E$494,"支援")>0,"○","")) | BE38: =COUNTIF(D38:BD38,"●") -> 3 | BF38: =COUNTIF(D38:BD38,"○") -> 3
B39: 09-03 | C39: ライフサイクル管理 | D39: =IF(COUNTIFS('VS×ケイパビリティ関係'!$F$4:$F$494,$B39,'VS×ケイパビリティ関係'!$G$4:$G$494,D$5,'VS×ケイパビリティ関係'!$E$4:$E$494,"主")>0,"●",IF(COUNTIFS('VS×ケイパビリティ関係'!$F$4:$F$494,$B39,'VS×ケイパビリティ関係'!$G$4:$G$494,D$5,'VS×ケイパビリティ関係'!$E$4:$E$494,"支援")>0,"○","")) | E39: =IF(COUNTIFS('VS×ケイパビリティ関係'!$F$4:$F$494,$B39,'VS×ケイパビリティ関係'!$G$4:$G$494,E$5,'VS×ケイパビリティ関係'!$E$4:$E$494,"主")>0,"●",IF(COUNTIFS('VS×ケイパビリティ関係'!$F$4:$F$494,$B39,'VS×ケイパビリティ関係'!$G$4:$G$494,E$5,'VS×ケイパビリティ関係'!$E$4:$E$494,"支援")>0,"○","")) -> ● | F39: =IF(COUNTIFS('VS×ケイパビリティ関係'!$F$4:$F$494,$B39,'VS×ケイパビリティ関係'!$G$4:$G$494,F$5,'VS×ケイパビリティ関係'!$E$4:$E$494,"主")>0,"●",IF(COUNTIFS('VS×ケイパビリティ関係'!$F$4:$F$494,$B39,'VS×ケイパビリティ関係'!$G$4:$G$494,F$5,'VS×ケイパビリティ関係'!$E$4:$E$494,"支援")>0,"○","")) | G39: =IF(COUNTIFS('VS×ケイパビリティ関係'!$F$4:$F$494,$B39,'VS×ケイパビリティ関係'!$G$4:$G$494,G$5,'VS×ケイパビリティ関係'!$E$4:$E$494,"主")>0,"●",IF(COUNTIFS('VS×ケイパビリティ関係'!$F$4:$F$494,$B39,'VS×ケイパビリティ関係'!$G$4:$G$494,G$5,'VS×ケイパビリティ関係'!$E$4:$E$494,"支援")>0,"○","")) | H39: =IF(COUNTIFS('VS×ケイパビリティ関係'!$F$4:$F$494,$B39,'VS×ケイパビリティ関係'!$G$4:$G$494,H$5,'VS×ケイパビリティ関係'!$E$4:$E$494,"主")>0,"●",IF(COUNTIFS('VS×ケイパビリティ関係'!$F$4:$F$494,$B39,'VS×ケイパビリティ関係'!$G$4:$G$494,H$5,'VS×ケイパビリティ関係'!$E$4:$E$494,"支援")>0,"○","")) | I39: =IF(COUNTIFS('VS×ケイパビリティ関係'!$F$4:$F$494,$B39,'VS×ケイパビリティ関係'!$G$4:$G$494,I$5,'VS×ケイパビリティ関係'!$E$4:$E$494,"主")>0,"●",IF(COUNTIFS('VS×ケイパビリティ関係'!$F$4:$F$494,$B39,'VS×ケイパビリティ関係'!$G$4:$G$494,I$5,'VS×ケイパビリティ関係'!$E$4:$E$494,"支援")>0,"○","")) | J39: =IF(COUNTIFS('VS×ケイパビリティ関係'!$F$4:$F$494,$B39,'VS×ケイパビリティ関係'!$G$4:$G$494,J$5,'VS×ケイパビリティ関係'!$E$4:$E$494,"主")>0,"●",IF(COUNTIFS('VS×ケイパビリティ関係'!$F$4:$F$494,$B39,'VS×ケイパビリティ関係'!$G$4:$G$494,J$5,'VS×ケイパビリティ関係'!$E$4:$E$494,"支援")>0,"○","")) | K39: =IF(COUNTIFS('VS×ケイパビリティ関係'!$F$4:$F$494,$B39,'VS×ケイパビリティ関係'!$G$4:$G$494,K$5,'VS×ケイパビリティ関係'!$E$4:$E$494,"主")>0,"●",IF(COUNTIFS('VS×ケイパビリティ関係'!$F$4:$F$494,$B39,'VS×ケイパビリティ関係'!$G$4:$G$494,K$5,'VS×ケイパビリティ関係'!$E$4:$E$494,"支援")>0,"○","")) | ... BD39: =IF(COUNTIFS('VS×ケイパビリティ関係'!$F$4:$F$494,$B39,'VS×ケイパビリティ関係'!$G$4:$G$494,BD$5,'VS×ケイパビリティ関係'!$E$4:$E$494,"主")>0,"●",IF(COUNTIFS('VS×ケイパビリティ関係'!$F$4:$F$494,$B39,'VS×ケイパビリティ関係'!$G$4:$G$494,BD$5,'VS×ケイパビリティ関係'!$E$4:$E$494,"支援")>0,"○","")) | BE39: =COUNTIF(D39:BD39,"●") -> 4 | BF39: =COUNTIF(D39:BD39,"○") -> 5

Sheet 情報オブジェクト
A1: 情報オブジェクト（正本：用語集と分類）
A2: 1行1オブジェクト。業務上ひとまとまりで管理される情報の単位（状態の違いは属性として扱う）。名称・分類・オーナーはこのシートで編集する。灰色の列は数式（編集しない）。分類の定義は解説書5章。
A3: ID | B3: 領域 | C3: 情報オブジェクト | D3: 英語名 | E3: 説明 | F3: データ種別 | G3: 規制区分 | H3: 電子記録の規制対象 | I3: 個人情報 | J3: オーナー ケイパビリティL2 ID | K3: オーナー ケイパビリティL2 | L3: 作成する ケイパビリティL2の数 | M3: 利用する ケイパビリティL2の数
A4: COM-01 | B4: 共通・マスタ | C4: 製品マスタ | D4: Product Master | E4: 開発コードから、承認後の製品名・NDC・GTINまでを一貫して管理する製品の基本情報 | F4: マスタ | G4: 薬事 | H4: =IF(G4="非GxP","—","対象候補") -> 対象候補 | I4: なし | J4: C13-01 | K4: {=IFERROR(INDEX('ケイパビリティマップ'!$E:$E,MATCH(J4,'ケイパビリティマップ'!$A:$A,0)),"（IDなし）")} -> 情報・データ管理 | L4: =COUNTIF('ケイパビリティ×情報オブジェクト'!D$6:D$58,"C") -> 3 | M4: =COUNTIF('ケイパビリティ×情報オブジェクト'!D$6:D$58,"R") -> 1
A5: COM-02 | B5: 共通・マスタ | C5: 開発判定記録 | D5: Governance Decision | E5: DC決定・Go/No-Goなど、段階移行の判断とその根拠資料 | F5: トランザクション | G5: 非GxP | H5: =IF(G5="非GxP","—","対象候補") -> — | I5: なし | J5: C01-01 | K5: {=IFERROR(INDEX('ケイパビリティマップ'!$E:$E,MATCH(J5,'ケイパビリティマップ'!$A:$A,0)),"（IDなし）")} -> 研究開発ポートフォリオ管理 | L5: =COUNTIF('ケイパビリティ×情報オブジェクト'!E$6:E$58,"C") -> 4 | M5: =COUNTIF('ケイパビリティ×情報オブジェクト'!E$6:E$58,"R") -> 0
A6: COM-03 | B6: 共通・マスタ | C6: 特許・独占期間 | D6: IP & Exclusivity | E6: 物質特許・FTO調査、Orphan 7年／生物製剤12年の独占期間 | F6: マスタ | G6: 非GxP | H6: =IF(G6="非GxP","—","対象候補") -> — | I6: なし | J6: C01-02 | K6: {=IFERROR(INDEX('ケイパビリティマップ'!$E:$E,MATCH(J6,'ケイパビリティマップ'!$A:$A,0)),"（IDなし）")} -> 知財・独占期間管理 | L6: =COUNTIF('ケイパビリティ×情報オブジェクト'!F$6:F$58,"C") -> 1 | M6: =COUNTIF('ケイパビリティ×情報オブジェクト'!F$6:F$58,"R") -> 2
A7: COM-04 | B7: 共通・マスタ | C7: 取引先・施設マスタ | D7: Partner & Site Master | E7: CRO・CDMO・受託試験機関・実施医療機関・流通業者など外部組織の基本情報 | F7: マスタ | G7: 非GxP | H7: =IF(G7="非GxP","—","対象候補") -> — | I7: なし | J7: C01-03 | K7: {=IFERROR(INDEX('ケイパビリティマップ'!$E:$E,MATCH(J7,'ケイパビリティマップ'!$A:$A,0)),"（IDなし）")} -> 外部パートナー管理 | L7: =COUNTIF('ケイパビリティ×情報オブジェクト'!G$6:G$58,"C") -> 2 | M7: =COUNTIF('ケイパビリティ×情報オブジェクト'!G$6:G$58,"R") -> 1
A8: COM-05 | B8: 共通・マスタ | C8: 契約 | D8: Contract | E8: CRO・CDMO・実施医療機関・流通業者・ハブ事業者などとの契約 | F8: トランザクション | G8: GCP・GMP | H8: =IF(G8="非GxP","—","対象候補") -> 対象候補 | I8: なし | J8: C01-03 | K8: {=IFERROR(INDEX('ケイパビリティマップ'!$E:$E,MATCH(J8,'ケイパビリティマップ'!$A:$A,0)),"（IDなし）")} -> 外部パートナー管理 | L8: =COUNTIF('ケイパビリティ×情報オブジェクト'!H$6:H$58,"C") -> 4 | M8: =COUNTIF('ケイパビリティ×情報オブジェクト'!H$6:H$58,"R") -> 1
A9: COM-06 | B9: 共通・マスタ | C9: 適応症 | D9: Indication | E9: 製品が対象とする疾患・適応。Orphan指定・臨床試験・承認・表示が共通して参照する単位 | F9: マスタ | G9: 薬事 | H9: =IF(G9="非GxP","—","対象候補") -> 対象候補 | I9: なし | J9: C01-01 | K9: {=IFERROR(INDEX('ケイパビリティマップ'!$E:$E,MATCH(J9,'ケイパビリティマップ'!$A:$A,0)),"（IDなし）")} -> 研究開発ポートフォリオ管理 | L9: =COUNTIF('ケイパビリティ×情報オブジェクト'!I$6:I$58,"C") -> 3 | M9: =COUNTIF('ケイパビリティ×情報オブジェクト'!I$6:I$58,"R") -> 4
A10: RES-01 | B10: 研究 | C10: 疾患知見 | D10: Disease Knowledge | E10: 病態・アンメットニーズ・患者の声（患者団体・専門医から得た知見を含む） | F10: 分析・評価 | G10: 非GxP | H10: =IF(G10="非GxP","—","対象候補") -> — | I10: なし | J10: C10-01 | K10: {=IFERROR(INDEX('ケイパビリティマップ'!$E:$E,MATCH(J10,'ケイパビリティマップ'!$A:$A,0)),"（IDなし）")} -> 患者団体・専門医連携★ | L10: =COUNTIF('ケイパビリティ×情報オブジェクト'!J$6:J$58,"C") -> 1 | M10: =COUNTIF('ケイパビリティ×情報オブジェクト'!J$6:J$58,"R") -> 3
A11: RES-02 | B11: 研究 | C11: 遺伝子・オミクスデータ | D11: Genomic & Omics Data | E11: 患者ゲノム・検体由来のデータ、原因遺伝子の解析結果 | F11: 測定データ | G11: 非GxP | H11: =IF(G11="非GxP","—","対象候補") -> — | I11: 患者（仮名化） | J11: C02-01 | K11: {=IFERROR(INDEX('ケイパビリティマップ'!$E:$E,MATCH(J11,'ケイパビリティマップ'!$A:$A,0)),"（IDなし）")} -> 疾患・標的研究★ | L11: =COUNTIF('ケイパビリティ×情報オブジェクト'!K$6:K$58,"C") -> 1 | M11: =COUNTIF('ケイパビリティ×情報オブジェクト'!K$6:K$58,"R") -> 2
A12: RES-03 | B12: 研究 | C12: 標的 | D12: Target | E12: 標的分子。仮説・検証状況・モダリティ適合性・選定結果を属性に持つ | F12: マスタ | G12: 非GxP | H12: =IF(G12="非GxP","—","対象候補") -> — | I12: なし | J12: C02-01 | K12: {=IFERROR(INDEX('ケイパビリティマップ'!$E:$E,MATCH(J12,'ケイパビリティマップ'!$A:$A,0)),"（IDなし）")} -> 疾患・標的研究★ | L12: =COUNTIF('ケイパビリティ×情報オブジェクト'!L$6:L$58,"C") -> 1 | M12: =COUNTIF('ケイパビリティ×情報オブジェクト'!L$6:L$58,"R") -> 1
A13: RES-04 | B13: 研究 | C13: 抗原・試薬 | D13: Antigen & Reagent | E13: 抗体取得・評価に用いる抗原タンパク・細胞・試薬 | F13: マスタ | G13: 非GxP | H13: =IF(G13="非GxP","—","対象候補") -> — | I13: なし | J13: C02-02 | K13: {=IFERROR(INDEX('ケイパビリティマップ'!$E:$E,MATCH(J13,'ケイパビリティマップ'!$A:$A,0)),"（IDなし）")} -> 抗体創出 | L13: =COUNTIF('ケイパビリティ×情報オブジェクト'!M$6:M$58,"C") -> 1 | M13: =COUNTIF('ケイパビリティ×情報オブジェクト'!M$6:M$58,"R") -> 0
A14: RES-05 | B14: 研究 | C14: アッセイ（評価系） | D14: Assay | E14: 結合性・機能・開発適性などの評価方法 | F14: 定義・仕様 | G14: 非GxP | H14: =IF(G14="非GxP","—","対象候補") -> — | I14: なし | J14: C02-02 | K14: {=IFERROR(INDEX('ケイパビリティマップ'!$E:$E,MATCH(J14,'ケイパビリティマップ'!$A:$A,0)),"（IDなし）")} -> 抗体創出 | L14: =COUNTIF('ケイパビリティ×情報オブジェクト'!N$6:N$58,"C") -> 1 | M14: =COUNTIF('ケイパビリティ×情報オブジェクト'!N$6:N$58,"R") -> 0
A15: RES-06 | B15: 研究 | C15: 抗体分子 | D15: Antibody Molecule | E15: 配列・クローン。ヒット→リード→最適化→候補品と状態が遷移する中心エンティティ | F15: マスタ | G15: 非GxP | H15: =IF(G15="非GxP","—","対象候補") -> — | I15: なし | J15: C02-02 | K15: {=IFERROR(INDEX('ケイパビリティマップ'!$E:$E,MATCH(J15,'ケイパビリティマップ'!$A:$A,0)),"（IDなし）")} -> 抗体創出 | L15: =COUNTIF('ケイパビリティ×情報オブジェクト'!O$6:O$58,"C") -> 2 | M15: =COUNTIF('ケイパビリティ×情報オブジェクト'!O$6:O$58,"R") -> 8
A16: RES-07 | B16: 研究 | C16: 研究実験データ | D16: Research Assay Result | E16: 標的検証・スクリーニング・機能評価・開発適性評価の結果 | F16: 測定データ | G16: 非GxP | H16: =IF(G16="非GxP","—","対象候補") -> — | I16: なし | J16: C02-02 | K16: {=IFERROR(INDEX('ケイパビリティマップ'!$E:$E,MATCH(J16,'ケイパビリティマップ'!$A:$A,0)),"（IDなし）")} -> 抗体創出 | L16: =COUNTIF('ケイパビリティ×情報オブジェクト'!P$6:P$58,"C") -> 3 | M16: =COUNTIF('ケイパビリティ×情報オブジェクト'!P$6:P$58,"R") -> 4
A17: RES-08 | B17: 研究 | C17: 疾患モデル | D17: Disease Model | E17: 遺伝子改変動物・患者由来細胞など | F17: マスタ | G17: 非GxP | H17: =IF(G17="非GxP","—","対象候補") -> — | I17: なし | J17: C02-04 | K17: {=IFERROR(INDEX('ケイパビリティマップ'!$E:$E,MATCH(J17,'ケイパビリティマップ'!$A:$A,0)),"（IDなし）")} -> 疾患モデル・薬効評価 | L17: =COUNTIF('ケイパビリティ×情報オブジェクト'!Q$6:Q$58,"C") -> 1 | M17: =COUNTIF('ケイパビリティ×情報オブジェクト'!Q$6:Q$58,"R") -> 1
A18: RES-09 | B18: 研究 | C18: in vivo薬効データ | D18: In Vivo Efficacy Data | E18: 疾患モデルでの薬効評価結果 | F18: 測定データ | G18: 非GxP | H18: =IF(G18="非GxP","—","対象候補") -> — | I18: なし | J18: C02-04 | K18: {=IFERROR(INDEX('ケイパビリティマップ'!$E:$E,MATCH(J18,'ケイパビリティマップ'!$A:$A,0)),"（IDなし）")} -> 疾患モデル・薬効評価 | L18: =COUNTIF('ケイパビリティ×情報オブジェクト'!R$6:R$58,"C") -> 1 | M18: =COUNTIF('ケイパビリティ×情報オブジェクト'!R$6:R$58,"R") -> 1
A19: RES-10 | B19: 研究 | C19: 免疫原性リスク評価 | D19: Immunogenicity Risk Assessment | E19: in silico／in vitroでの免疫原性予測 | F19: 分析・評価 | G19: 非GxP | H19: =IF(G19="非GxP","—","対象候補") -> — | I19: なし | J19: C02-05 | K19: {=IFERROR(INDEX('ケイパビリティマップ'!$E:$E,MATCH(J19,'ケイパビリティマップ'!$A:$A,0)),"（IDなし）")} -> 開発適性・免疫原性リスク評価 | L19: =COUNTIF('ケイパビリティ×情報オブジェクト'!S$6:S$58,"C") -> 1 | M19: =COUNTIF('ケイパビリティ×情報オブジェクト'!S$6:S$58,"R") -> 1
A20: RES-11 | B20: 研究 | C20: 目標製品プロファイル（TPP） | D20: Target Product Profile | E20: 目指す適応・用法・有効性・安全性・剤形 | F20: 定義・仕様 | G20: 非GxP | H20: =IF(G20="非GxP","—","対象候補") -> — | I20: なし | J20: C01-01 | K20: {=IFERROR(INDEX('ケイパビリティマップ'!$E:$E,MATCH(J20,'ケイパビリティマップ'!$A:$A,0)),"（IDなし）")} -> 研究開発ポートフォリオ管理 | L20: =COUNTIF('ケイパビリティ×情報オブジェクト'!T$6:T$58,"C") -> 2 | M20: =COUNTIF('ケイパビリティ×情報オブジェクト'!T$6:T$58,"R") -> 0
A21: RES-12 | B21: 研究 | C21: 疫学データ | D21: Epidemiology Data | E21: 米国の患者数（20万人未満の根拠）・有病率 | F21: 分析・評価 | G21: 非GxP | H21: =IF(G21="非GxP","—","対象候補") -> — | I21: なし | J21: C05-02 | K21: {=IFERROR(INDEX('ケイパビリティマップ'!$E:$E,MATCH(J21,'ケイパビリティマップ'!$A:$A,0)),"（IDなし）")} -> 患者エビデンス管理★ | L21: =COUNTIF('ケイパビリティ×情報オブジェクト'!U$6:U$58,"C") -> 1 | M21: =COUNTIF('ケイパビリティ×情報オブジェクト'!U$6:U$58,"R") -> 4
A22: NCL-01 | B22: 非臨床 | C22: 非臨床試験計画 | D22: Nonclinical Study Plan | E22: 試験計画書（GLP試験を含む） | F22: 文書 | G22: GLP | H22: =IF(G22="非GxP","—","対象候補") -> 対象候補 | I22: なし | J22: C03-02 | K22: {=IFERROR(INDEX('ケイパビリティマップ'!$E:$E,MATCH(J22,'ケイパビリティマップ'!$A:$A,0)),"（IDなし）")} -> 非臨床安全性評価 | L22: =COUNTIF('ケイパビリティ×情報オブジェクト'!V$6:V$58,"C") -> 1 | M22: =COUNTIF('ケイパビリティ×情報オブジェクト'!V$6:V$58,"R") -> 2
A23: NCL-02 | B23: 非臨床 | C23: 非臨床試験データ | D23: Nonclinical Study Data | E23: 薬理・PK・毒性試験の生データと結果 | F23: 測定データ | G23: GLP | H23: =IF(G23="非GxP","—","対象候補") -> 対象候補 | I23: なし | J23: C03-02 | K23: {=IFERROR(INDEX('ケイパビリティマップ'!$E:$E,MATCH(J23,'ケイパビリティマップ'!$A:$A,0)),"（IDなし）")} -> 非臨床安全性評価 | L23: =COUNTIF('ケイパビリティ×情報オブジェクト'!W$6:W$58,"C") -> 3 | M23: =COUNTIF('ケイパビリティ×情報オブジェクト'!W$6:W$58,"R") -> 1
A24: NCL-03 | B24: 非臨床 | C24: 非臨床試験報告書 | D24: Nonclinical Study Report | E24: MoA・動物種選定根拠を含む試験報告書 | F24: 文書 | G24: GLP | H24: =IF(G24="非GxP","—","対象候補") -> 対象候補 | I24: なし | J24: C03-02 | K24: {=IFERROR(INDEX('ケイパビリティマップ'!$E:$E,MATCH(J24,'ケイパビリティマップ'!$A:$A,0)),"（IDなし）")} -> 非臨床安全性評価 | L24: =COUNTIF('ケイパビリティ×情報オブジェクト'!X$6:X$58,"C") -> 2 | M24: =COUNTIF('ケイパビリティ×情報オブジェクト'!X$6:X$58,"R") -> 4
A25: NCL-04 | B25: 非臨床 | C25: 生体試料分析法 | D25: Bioanalytical Method | E25: PK/TK・ADAの測定法（リガンド結合法）。臨床でも使用 | F25: 定義・仕様 | G25: GLP・GCP | H25: =IF(G25="非GxP","—","対象候補") -> 対象候補 | I25: なし | J25: C03-03 | K25: {=IFERROR(INDEX('ケイパビリティマップ'!$E:$E,MATCH(J25,'ケイパビリティマップ'!$A:$A,0)),"（IDなし）")} -> バイオアナリシス | L25: =COUNTIF('ケイパビリティ×情報オブジェクト'!Y$6:Y$58,"C") -> 1 | M25: =COUNTIF('ケイパビリティ×情報オブジェクト'!Y$6:Y$58,"R") -> 0
A26: CMC-01 | B26: CMC開発 | C26: 発現ベクター・細胞株 | D26: Vector & Cell Line | E26: 発現ベクター、候補クローン、生産細胞株と由来記録 | F26: マスタ | G26: 非GxP | H26: =IF(G26="非GxP","—","対象候補") -> — | I26: なし | J26: C04-01 | K26: {=IFERROR(INDEX('ケイパビリティマップ'!$E:$E,MATCH(J26,'ケイパビリティマップ'!$A:$A,0)),"（IDなし）")} -> 細胞株開発・セルバンク管理 | L26: =COUNTIF('ケイパビリティ×情報オブジェクト'!Z$6:Z$58,"C") -> 1 | M26: =COUNTIF('ケイパビリティ×情報オブジェクト'!Z$6:Z$58,"R") -> 1
A27: CMC-02 | B27: CMC開発 | C27: セルバンク | D27: Cell Bank | E27: MCB／WCB。在庫・使用履歴を含む | F27: マスタ | G27: GMP | H27: =IF(G27="非GxP","—","対象候補") -> 対象候補 | I27: なし | J27: C04-01 | K27: {=IFERROR(INDEX('ケイパビリティマップ'!$E:$E,MATCH(J27,'ケイパビリティマップ'!$A:$A,0)),"（IDなし）")} -> 細胞株開発・セルバンク管理 | L27: =COUNTIF('ケイパビリティ×情報オブジェクト'!AA$6:AA$58,"C") -> 1 | M27: =COUNTIF('ケイパビリティ×情報オブジェクト'!AA$6:AA$58,"R") -> 4
A28: CMC-03 | B28: CMC開発 | C28: プロセス定義 | D28: Process Definition | E28: 培養・精製工程、工程パラメータと許容範囲、製造規模 | F28: 定義・仕様 | G28: GMP | H28: =IF(G28="非GxP","—","対象候補") -> 対象候補 | I28: なし | J28: C04-02 | K28: {=IFERROR(INDEX('ケイパビリティマップ'!$E:$E,MATCH(J28,'ケイパビリティマップ'!$A:$A,0)),"（IDなし）")} -> 原薬プロセス開発 | L28: =COUNTIF('ケイパビリティ×情報オブジェクト'!AB$6:AB$58,"C") -> 2 | M28: =COUNTIF('ケイパビリティ×情報オブジェクト'!AB$6:AB$58,"R") -> 2
A29: CMC-04 | B29: CMC開発 | C29: プロセス開発データ | D29: Process Development Data | E29: 開発ラン・実験計画法（DoE）の結果 | F29: 測定データ | G29: 非GxP | H29: =IF(G29="非GxP","—","対象候補") -> — | I29: なし | J29: C04-02 | K29: {=IFERROR(INDEX('ケイパビリティマップ'!$E:$E,MATCH(J29,'ケイパビリティマップ'!$A:$A,0)),"（IDなし）")} -> 原薬プロセス開発 | L29: =COUNTIF('ケイパビリティ×情報オブジェクト'!AC$6:AC$58,"C") -> 2 | M29: =COUNTIF('ケイパビリティ×情報オブジェクト'!AC$6:AC$58,"R") -> 1
A30: CMC-05 | B30: CMC開発 | C30: 処方・製剤仕様 | D30: Formulation & Presentation | E30: 処方、剤形・容器、投与デバイスの仕様 | F30: 定義・仕様 | G30: GMP・QMSR | H30: =IF(G30="非GxP","—","対象候補") -> 対象候補 | I30: なし | J30: C04-03 | K30: {=IFERROR(INDEX('ケイパビリティマップ'!$E:$E,MATCH(J30,'ケイパビリティマップ'!$A:$A,0)),"（IDなし）")} -> 製剤・デバイス開発 | L30: =COUNTIF('ケイパビリティ×情報オブジェクト'!AD$6:AD$58,"C") -> 1 | M30: =COUNTIF('ケイパビリティ×情報オブジェクト'!AD$6:AD$58,"R") -> 2
A31: CMC-06 | B31: CMC開発 | C31: 重要品質特性（CQA） | D31: Critical Quality Attribute | E31: 品質に影響する特性とそのリスク評価 | F31: 定義・仕様 | G31: GMP | H31: =IF(G31="非GxP","—","対象候補") -> 対象候補 | I31: なし | J31: C04-04 | K31: {=IFERROR(INDEX('ケイパビリティマップ'!$E:$E,MATCH(J31,'ケイパビリティマップ'!$A:$A,0)),"（IDなし）")} -> 分析法開発・品質特性評価 | L31: =COUNTIF('ケイパビリティ×情報オブジェクト'!AE$6:AE$58,"C") -> 1 | M31: =COUNTIF('ケイパビリティ×情報オブジェクト'!AE$6:AE$58,"R") -> 1
A32: CMC-07 | B32: CMC開発 | C32: 分析法 | D32: Analytical Method | E32: 構造・純度・糖鎖・電荷・生物活性の試験法とバリデーション状態 | F32: 定義・仕様 | G32: GMP | H32: =IF(G32="非GxP","—","対象候補") -> 対象候補 | I32: なし | J32: C04-04 | K32: {=IFERROR(INDEX('ケイパビリティマップ'!$E:$E,MATCH(J32,'ケイパビリティマップ'!$A:$A,0)),"（IDなし）")} -> 分析法開発・品質特性評価 | L32: =COUNTIF('ケイパビリティ×情報オブジェクト'!AF$6:AF$58,"C") -> 1 | M32: =COUNTIF('ケイパビリティ×情報オブジェクト'!AF$6:AF$58,"R") -> 4
A33: CMC-08 | B33: CMC開発 | C33: 標準物質 | D33: Reference Standard | E33: 試験の基準となる物質とその特性 | F33: マスタ | G33: GMP | H33: =IF(G33="非GxP","—","対象候補") -> 対象候補 | I33: なし | J33: C04-04 | K33: {=IFERROR(INDEX('ケイパビリティマップ'!$E:$E,MATCH(J33,'ケイパビリティマップ'!$A:$A,0)),"（IDなし）")} -> 分析法開発・品質特性評価 | L33: =COUNTIF('ケイパビリティ×情報オブジェクト'!AG$6:AG$58,"C") -> 1 | M33: =COUNTIF('ケイパビリティ×情報オブジェクト'!AG$6:AG$58,"R") -> 2
A34: CMC-09 | B34: CMC開発 | C34: 規格 | D34: Specification | E34: 原薬・製剤の規格項目と判定基準 | F34: 定義・仕様 | G34: GMP | H34: =IF(G34="非GxP","—","対象候補") -> 対象候補 | I34: なし | J34: C04-04 | K34: {=IFERROR(INDEX('ケイパビリティマップ'!$E:$E,MATCH(J34,'ケイパビリティマップ'!$A:$A,0)),"（IDなし）")} -> 分析法開発・品質特性評価 | L34: =COUNTIF('ケイパビリティ×情報オブジェクト'!AH$6:AH$58,"C") -> 1 | M34: =COUNTIF('ケイパビリティ×情報オブジェクト'!AH$6:AH$58,"R") -> 5
A35: CMC-10 | B35: CMC開発 | C35: 管理戦略 | D35: Control Strategy | E35: CQAを保証するための工程管理・試験の組合せ | F35: 定義・仕様 | G35: GMP | H35: =IF(G35="非GxP","—","対象候補") -> 対象候補 | I35: なし | J35: C04-02 | K35: {=IFERROR(INDEX('ケイパビリティマップ'!$E:$E,MATCH(J35,'ケイパビリティマップ'!$A:$A,0)),"（IDなし）")} -> 原薬プロセス開発 | L35: =COUNTIF('ケイパビリティ×情報オブジェクト'!AI$6:AI$58,"C") -> 1 | M35: =COUNTIF('ケイパビリティ×情報オブジェクト'!AI$6:AI$58,"R") -> 3
A36: CMC-11 | B36: CMC開発 | C36: 安定性データ | D36: Stability Data | E36: 安定性試験の計画と結果（開発・治験薬・商用） | F36: 測定データ | G36: GMP | H36: =IF(G36="非GxP","—","対象候補") -> 対象候補 | I36: なし | J36: C08-01 | K36: {=IFERROR(INDEX('ケイパビリティマップ'!$E:$E,MATCH(J36,'ケイパビリティマップ'!$A:$A,0)),"（IDなし）")} -> 品質管理（試験・安定性） | L36: =COUNTIF('ケイパビリティ×情報オブジェクト'!AJ$6:AJ$58,"C") -> 3 | M36: =COUNTIF('ケイパビリティ×情報オブジェクト'!AJ$6:AJ$58,"R") -> 2
A37: CMC-12 | B37: CMC開発 | C37: CMC技術報告書 | D37: CMC Technical Report | E37: セルバンク試験・ウイルスクリアランス・分析法バリデーション・同等性評価・技術移転などの報告書 | F37: 文書 | G37: GMP | H37: =IF(G37="非GxP","—","対象候補") -> 対象候補 | I37: なし | J37: C04-04 | K37: {=IFERROR(INDEX('ケイパビリティマップ'!$E:$E,MATCH(J37,'ケイパビリティマップ'!$A:$A,0)),"（IDなし）")} -> 分析法開発・品質特性評価 | L37: =COUNTIF('ケイパビリティ×情報オブジェクト'!AK$6:AK$58,"C") -> 4 | M37: =COUNTIF('ケイパビリティ×情報オブジェクト'!AK$6:AK$58,"R") -> 4
A38: CMC-13 | B38: CMC開発 | C38: マスターバッチレコード | D38: Master Batch Record | E38: 製造所で使う製造指図の原本 | F38: 定義・仕様 | G38: GMP | H38: =IF(G38="非GxP","—","対象候補") -> 対象候補 | I38: なし | J38: C04-05 | K38: {=IFERROR(INDEX('ケイパビリティマップ'!$E:$E,MATCH(J38,'ケイパビリティマップ'!$A:$A,0)),"（IDなし）")} -> 技術移転・製造規模管理 | L38: =COUNTIF('ケイパビリティ×情報オブジェクト'!AL$6:AL$58,"C") -> 1 | M38: =COUNTIF('ケイパビリティ×情報オブジェクト'!AL$6:AL$58,"R") -> 3
A39: MFG-01 | B39: 製造・品質 | C39: 生産計画 | D39: Production Plan | E39: 原薬・製剤の生産スケジュール | F39: トランザクション | G39: 非GxP | H39: =IF(G39="非GxP","—","対象候補") -> — | I39: なし | J39: C07-01 | K39: {=IFERROR(INDEX('ケイパビリティマップ'!$E:$E,MATCH(J39,'ケイパビリティマップ'!$A:$A,0)),"（IDなし）")} -> 生産計画・製造実行管理 | L39: =COUNTIF('ケイパビリティ×情報オブジェクト'!AM$6:AM$58,"C") -> 1 | M39: =COUNTIF('ケイパビリティ×情報オブジェクト'!AM$6:AM$58,"R") -> 2
A40: MFG-02 | B40: 製造・品質 | C40: 原材料・資材 | D40: Material | E40: 培地・レジン・容器などの原材料・資材とそのロット | F40: マスタ | G40: GMP | H40: =IF(G40="非GxP","—","対象候補") -> 対象候補 | I40: なし | J40: C07-01 | K40: {=IFERROR(INDEX('ケイパビリティマップ'!$E:$E,MATCH(J40,'ケイパビリティマップ'!$A:$A,0)),"（IDなし）")} -> 生産計画・製造実行管理 | L40: =COUNTIF('ケイパビリティ×情報オブジェクト'!AN$6:AN$58,"C") -> 1 | M40: =COUNTIF('ケイパビリティ×情報オブジェクト'!AN$6:AN$58,"R") -> 3
A41: MFG-03 | B41: 製造・品質 | C41: バッチ記録 | D41: Executed Batch Record | E41: 実行された製造記録（培養・精製・充填・包装） | F41: トランザクション | G41: GMP | H41: =IF(G41="非GxP","—","対象候補") -> 対象候補 | I41: なし | J41: C07-01 | K41: {=IFERROR(INDEX('ケイパビリティマップ'!$E:$E,MATCH(J41,'ケイパビリティマップ'!$A:$A,0)),"（IDなし）")} -> 生産計画・製造実行管理 | L41: =COUNTIF('ケイパビリティ×情報オブジェクト'!AO$6:AO$58,"C") -> 5 | M41: =COUNTIF('ケイパビリティ×情報オブジェクト'!AO$6:AO$58,"R") -> 2
A42: MFG-04 | B42: 製造・品質 | C42: ロット | D42: Lot | E42: 原薬・製剤・製品のロットと系譜（治験薬・PPQロットを含む） | F42: トランザクション | G42: GMP | H42: =IF(G42="非GxP","—","対象候補") -> 対象候補 | I42: なし | J42: C07-01 | K42: {=IFERROR(INDEX('ケイパビリティマップ'!$E:$E,MATCH(J42,'ケイパビリティマップ'!$A:$A,0)),"（IDなし）")} -> 生産計画・製造実行管理 | L42: =COUNTIF('ケイパビリティ×情報オブジェクト'!AP$6:AP$58,"C") -> 4 | M42: =COUNTIF('ケイパビリティ×情報オブジェクト'!AP$6:AP$58,"R") -> 5
A43: MFG-05 | B43: 製造・品質 | C43: 工程データ | D43: Process Data | E43: バイオリアクター等の運転・監視データ | F43: 測定データ | G43: GMP | H43: =IF(G43="非GxP","—","対象候補") -> 対象候補 | I43: なし | J43: C07-02 | K43: {=IFERROR(INDEX('ケイパビリティマップ'!$E:$E,MATCH(J43,'ケイパビリティマップ'!$A:$A,0)),"（IDなし）")} -> 原薬製造 | L43: =COUNTIF('ケイパビリティ×情報オブジェクト'!AQ$6:AQ$58,"C") -> 2 | M43: =COUNTIF('ケイパビリティ×情報オブジェクト'!AQ$6:AQ$58,"R") -> 0
A44: MFG-06 | B44: 製造・品質 | C44: 試験成績 | D44: QC Test Result | E44: 工程内試験・規格試験の結果、試験成績書（CoA） | F44: 測定データ | G44: GMP | H44: =IF(G44="非GxP","—","対象候補") -> 対象候補 | I44: なし | J44: C08-01 | K44: {=IFERROR(INDEX('ケイパビリティマップ'!$E:$E,MATCH(J44,'ケイパビリティマップ'!$A:$A,0)),"（IDなし）")} -> 品質管理（試験・安定性） | L44: =COUNTIF('ケイパビリティ×情報オブジェクト'!AR$6:AR$58,"C") -> 3 | M44: =COUNTIF('ケイパビリティ×情報オブジェクト'!AR$6:AR$58,"R") -> 1
A45: MFG-07 | B45: 製造・品質 | C45: 逸脱・CAPA | D45: Deviation & CAPA | E45: 逸脱、原因調査、是正・予防措置（温度逸脱を含む） | F45: トランザクション | G45: GMP | H45: =IF(G45="非GxP","—","対象候補") -> 対象候補 | I45: なし | J45: C08-02 | K45: {=IFERROR(INDEX('ケイパビリティマップ'!$E:$E,MATCH(J45,'ケイパビリティマップ'!$A:$A,0)),"（IDなし）")} -> 品質保証（出荷判定・逸脱・変更） | L45: =COUNTIF('ケイパビリティ×情報オブジェクト'!AS$6:AS$58,"C") -> 2 | M45: =COUNTIF('ケイパビリティ×情報オブジェクト'!AS$6:AS$58,"R") -> 2
A46: MFG-08 | B46: 製造・品質 | C46: 変更管理記録 | D46: Change Control | E46: 変更の評価と、21 CFR 601.12の報告区分の判定 | F46: トランザクション | G46: GMP | H46: =IF(G46="非GxP","—","対象候補") -> 対象候補 | I46: なし | J46: C08-02 | K46: {=IFERROR(INDEX('ケイパビリティマップ'!$E:$E,MATCH(J46,'ケイパビリティマップ'!$A:$A,0)),"（IDなし）")} -> 品質保証（出荷判定・逸脱・変更） | L46: =COUNTIF('ケイパビリティ×情報オブジェクト'!AT$6:AT$58,"C") -> 1 | M46: =COUNTIF('ケイパビリティ×情報オブジェクト'!AT$6:AT$58,"R") -> 2
A47: MFG-09 | B47: 製造・品質 | C47: 出荷判定記録 | D47: Lot Disposition | E47: 品質部門によるロットの出荷可否判定 | F47: トランザクション | G47: GMP | H47: =IF(G47="非GxP","—","対象候補") -> 対象候補 | I47: なし | J47: C08-02 | K47: {=IFERROR(INDEX('ケイパビリティマップ'!$E:$E,MATCH(J47,'ケイパビリティマップ'!$A:$A,0)),"（IDなし）")} -> 品質保証（出荷判定・逸脱・変更） | L47: =COUNTIF('ケイパビリティ×情報オブジェクト'!AU$6:AU$58,"C") -> 2 | M47: =COUNTIF('ケイパビリティ×情報オブジェクト'!AU$6:AU$58,"R") -> 2
A48: MFG-10 | B48: 製造・品質 | C48: バリデーション計画・報告 | D48: Validation Plan & Report | E48: 設備・洗浄・プロセス（PPQ）のバリデーション | F48: 文書 | G48: GMP | H48: =IF(G48="非GxP","—","対象候補") -> 対象候補 | I48: なし | J48: C08-03 | K48: {=IFERROR(INDEX('ケイパビリティマップ'!$E:$E,MATCH(J48,'ケイパビリティマップ'!$A:$A,0)),"（IDなし）")} -> バリデーション管理 | L48: =COUNTIF('ケイパビリティ×情報オブジェクト'!AV$6:AV$58,"C") -> 1 | M48: =COUNTIF('ケイパビリティ×情報オブジェクト'!AV$6:AV$58,"R") -> 2
A49: MFG-11 | B49: 製造・品質 | C49: 設備・環境モニタリングデータ | D49: Equipment & Environmental Monitoring | E49: 無菌環境・設備の監視データ | F49: 測定データ | G49: GMP | H49: =IF(G49="非GxP","—","対象候補") -> 対象候補 | I49: なし | J49: C07-04 | K49: {=IFERROR(INDEX('ケイパビリティマップ'!$E:$E,MATCH(J49,'ケイパビリティマップ'!$A:$A,0)),"（IDなし）")} -> 設備・環境管理 | L49: =COUNTIF('ケイパビリティ×情報オブジェクト'!AW$6:AW$58,"C") -> 2 | M49: =COUNTIF('ケイパビリティ×情報オブジェクト'!AW$6:AW$58,"R") -> 0
A50: MFG-12 | B50: 製造・品質 | C50: 年次製品照査（APR） | D50: Annual Product Review | E50: 年次の品質傾向レビュー | F50: 文書 | G50: GMP | H50: =IF(G50="非GxP","—","対象候補") -> 対象候補 | I50: なし | J50: C08-02 | K50: {=IFERROR(INDEX('ケイパビリティマップ'!$E:$E,MATCH(J50,'ケイパビリティマップ'!$A:$A,0)),"（IDなし）")} -> 品質保証（出荷判定・逸脱・変更） | L50: =COUNTIF('ケイパビリティ×情報オブジェクト'!AX$6:AX$58,"C") -> 2 | M50: =COUNTIF('ケイパビリティ×情報オブジェクト'!AX$6:AX$58,"R") -> 1
A51: MFG-13 | B51: 製造・品質 | C51: 包装表示（アートワーク） | D51: Label Artwork | E51: 治験薬・商用製品のラベル・包装デザイン | F51: 定義・仕様 | G51: GMP・GCP | H51: =IF(G51="非GxP","—","対象候補") -> 対象候補 | I51: なし | J51: C06-03 | K51: {=IFERROR(INDEX('ケイパビリティマップ'!$E:$E,MATCH(J51,'ケイパビリティマップ'!$A:$A,0)),"（IDなし）")} -> ラベリング管理 | L51: =COUNTIF('ケイパビリティ×情報オブジェクト'!AY$6:AY$58,"C") -> 2 | M51: =COUNTIF('ケイパビリティ×情報オブジェクト'!AY$6:AY$58,"R") -> 1
A52: CLN-01 | B52: 臨床 | C52: 自然歴データ | D52: Natural History Data | E52: 疾患の自然経過データ。外部対照・評価項目設定の基礎 | F52: 測定データ | G52: 非GxP | H52: =IF(G52="非GxP","—","対象候補") -> — | I52: 患者（仮名化） | J52: C05-02 | K52: {=IFERROR(INDEX('ケイパビリティマップ'!$E:$E,MATCH(J52,'ケイパビリティマップ'!$A:$A,0)),"（IDなし）")} -> 患者エビデンス管理★ | L52: =COUNTIF('ケイパビリティ×情報オブジェクト'!AZ$6:AZ$58,"C") -> 1 | M52: =COUNTIF('ケイパビリティ×情報オブジェクト'!AZ$6:AZ$58,"R") -> 3
A53: CLN-02 | B53: 臨床 | C53: 患者レジストリデータ | D53: Patient Registry Data | E53: 患者団体等と構築するレジストリ。市販後の長期追跡にも使用（個人情報を含む） | F53: 測定データ | G53: PV | H53: =IF(G53="非GxP","—","対象候補") -> 対象候補 | I53: 患者 | J53: C05-02 | K53: {=IFERROR(INDEX('ケイパビリティマップ'!$E:$E,MATCH(J53,'ケイパビリティマップ'!$A:$A,0)),"（IDなし）")} -> 患者エビデンス管理★ | L53: =COUNTIF('ケイパビリティ×情報オブジェクト'!BA$6:BA$58,"C") -> 1 | M53: =COUNTIF('ケイパビリティ×情報オブジェクト'!BA$6:BA$58,"R") -> 2
A54: CLN-03 | B54: 臨床 | C54: 候補患者情報 | D54: Patient Identification | E54: 診断・遺伝子検査結果に基づく候補患者の情報（個人情報を含む） | F54: トランザクション | G54: 非GxP | H54: =IF(G54="非GxP","—","対象候補") -> — | I54: 患者 | J54: C05-03 | K54: {=IFERROR(INDEX('ケイパビリティマップ'!$E:$E,MATCH(J54,'ケイパビリティマップ'!$A:$A,0)),"（IDなし）")} -> 患者特定・組入れ★ | L54: =COUNTIF('ケイパビリティ×情報オブジェクト'!BB$6:BB$58,"C") -> 1 | M54: =COUNTIF('ケイパビリティ×情報オブジェクト'!BB$6:BB$58,"R") -> 2
A55: CLN-04 | B55: 臨床 | C55: 臨床評価指標・バイオマーカー定義 | D55: COA & Biomarker Definition | E55: 臨床アウトカム評価（COA）・バイオマーカーの定義と検証結果 | F55: 定義・仕様 | G55: 非GxP | H55: =IF(G55="非GxP","—","対象候補") -> — | I55: なし | J55: C05-01 | K55: {=IFERROR(INDEX('ケイパビリティマップ'!$E:$E,MATCH(J55,'ケイパビリティマップ'!$A:$A,0)),"（IDなし）")} -> 臨床開発戦略・試験デザイン | L55: =COUNTIF('ケイパビリティ×情報オブジェクト'!BC$6:BC$58,"C") -> 1 | M55: =COUNTIF('ケイパビリティ×情報オブジェクト'!BC$6:BC$58,"R") -> 1
A56: CLN-05 | B56: 臨床 | C56: 治験実施計画書 | D56: Clinical Protocol | E56: 試験デザイン・評価項目・症例数（市販後試験を含む） | F56: 文書 | G56: GCP | H56: =IF(G56="非GxP","—","対象候補") -> 対象候補 | I56: なし | J56: C05-01 | K56: {=IFERROR(INDEX('ケイパビリティマップ'!$E:$E,MATCH(J56,'ケイパビリティマップ'!$A:$A,0)),"（IDなし）")} -> 臨床開発戦略・試験デザイン | L56: =COUNTIF('ケイパビリティ×情報オブジェクト'!BD$6:BD$58,"C") -> 2 | M56: =COUNTIF('ケイパビリティ×情報オブジェクト'!BD$6:BD$58,"R") -> 2
A57: CLN-06 | B57: 臨床 | C57: 治験薬概要書（IB） | D57: Investigator's Brochure | E57: 非臨床・臨床の知見をまとめた治験責任医師向け資料 | F57: 文書 | G57: GCP | H57: =IF(G57="非GxP","—","対象候補") -> 対象候補 | I57: なし | J57: C05-01 | K57: {=IFERROR(INDEX('ケイパビリティマップ'!$E:$E,MATCH(J57,'ケイパビリティマップ'!$A:$A,0)),"（IDなし）")} -> 臨床開発戦略・試験デザイン | L57: =COUNTIF('ケイパビリティ×情報オブジェクト'!BE$6:BE$58,"C") -> 2 | M57: =COUNTIF('ケイパビリティ×情報オブジェクト'!BE$6:BE$58,"R") -> 2
A58: CLN-07 | B58: 臨床 | C58: 試験実施体制 | D58: Study Site & Start-up | E58: 実施医療機関・治験責任医師・IRB承認・施設の立ち上げ状況 | F58: トランザクション | G58: GCP | H58: =IF(G58="非GxP","—","対象候補") -> 対象候補 | I58: 医療従事者 | J58: C05-04 | K58: {=IFERROR(INDEX('ケイパビリティマップ'!$E:$E,MATCH(J58,'ケイパビリティマップ'!$A:$A,0)),"（IDなし）")} -> 臨床試験運営 | L58: =COUNTIF('ケイパビリティ×情報オブジェクト'!BF$6:BF$58,"C") -> 1 | M58: =COUNTIF('ケイパビリティ×情報オブジェクト'!BF$6:BF$58,"R") -> 1
A59: CLN-08 | B59: 臨床 | C59: 試験登録情報 | D59: Trial Registration | E59: ClinicalTrials.govへの登録・結果報告 | F59: トランザクション | G59: GCP・薬事 | H59: =IF(G59="非GxP","—","対象候補") -> 対象候補 | I59: なし | J59: C05-04 | K59: {=IFERROR(INDEX('ケイパビリティマップ'!$E:$E,MATCH(J59,'ケイパビリティマップ'!$A:$A,0)),"（IDなし）")} -> 臨床試験運営 | L59: =COUNTIF('ケイパビリティ×情報オブジェクト'!BG$6:BG$58,"C") -> 1 | M59: =COUNTIF('ケイパビリティ×情報オブジェクト'!BG$6:BG$58,"R") -> 0
A60: CLN-09 | B60: 臨床 | C60: 症例データ | D60: Subject & Case Data | E60: 被験者の登録・投与・評価データ（EDC。個人情報は仮名化） | F60: 測定データ | G60: GCP | H60: =IF(G60="非GxP","—","対象候補") -> 対象候補 | I60: 患者（仮名化） | J60: C05-05 | K60: {=IFERROR(INDEX('ケイパビリティマップ'!$E:$E,MATCH(J60,'ケイパビリティマップ'!$A:$A,0)),"（IDなし）")} -> 臨床データマネジメント・統計解析 | L60: =COUNTIF('ケイパビリティ×情報オブジェクト'!BH$6:BH$58,"C") -> 2 | M60: =COUNTIF('ケイパビリティ×情報オブジェクト'!BH$6:BH$58,"R") -> 3
A61: CLN-10 | B61: 臨床 | C61: 臨床検体分析データ | D61: Clinical Bioanalytical Data | E61: PK・ADA・バイオマーカーの測定結果 | F61: 測定データ | G61: GCP | H61: =IF(G61="非GxP","—","対象候補") -> 対象候補 | I61: 患者（仮名化） | J61: C03-03 | K61: {=IFERROR(INDEX('ケイパビリティマップ'!$E:$E,MATCH(J61,'ケイパビリティマップ'!$A:$A,0)),"（IDなし）")} -> バイオアナリシス | L61: =COUNTIF('ケイパビリティ×情報オブジェクト'!BI$6:BI$58,"C") -> 2 | M61: =COUNTIF('ケイパビリティ×情報オブジェクト'!BI$6:BI$58,"R") -> 3
A62: CLN-11 | B62: 臨床 | C62: 臨床データセット | D62: Clinical Dataset | E62: 固定済みデータ（SDTM／ADaM） | F62: 測定データ | G62: GCP | H62: =IF(G62="非GxP","—","対象候補") -> 対象候補 | I62: 患者（仮名化） | J62: C05-05 | K62: {=IFERROR(INDEX('ケイパビリティマップ'!$E:$E,MATCH(J62,'ケイパビリティマップ'!$A:$A,0)),"（IDなし）")} -> 臨床データマネジメント・統計解析 | L62: =COUNTIF('ケイパビリティ×情報オブジェクト'!BJ$6:BJ$58,"C") -> 1 | M62: =COUNTIF('ケイパビリティ×情報オブジェクト'!BJ$6:BJ$58,"R") -> 1
A63: CLN-12 | B63: 臨床 | C63: 統計解析結果 | D63: Statistical Output | E63: 図表・リスト（TLF） | F63: 分析・評価 | G63: GCP | H63: =IF(G63="非GxP","—","対象候補") -> 対象候補 | I63: なし | J63: C05-05 | K63: {=IFERROR(INDEX('ケイパビリティマップ'!$E:$E,MATCH(J63,'ケイパビリティマップ'!$A:$A,0)),"（IDなし）")} -> 臨床データマネジメント・統計解析 | L63: =COUNTIF('ケイパビリティ×情報オブジェクト'!BK$6:BK$58,"C") -> 1 | M63: =COUNTIF('ケイパビリティ×情報オブジェクト'!BK$6:BK$58,"R") -> 0
A64: CLN-13 | B64: 臨床 | C64: 総括報告書（CSR） | D64: Clinical Study Report | E64: 試験ごとの総括報告書 | F64: 文書 | G64: GCP | H64: =IF(G64="非GxP","—","対象候補") -> 対象候補 | I64: なし | J64: C05-05 | K64: {=IFERROR(INDEX('ケイパビリティマップ'!$E:$E,MATCH(J64,'ケイパビリティマップ'!$A:$A,0)),"（IDなし）")} -> 臨床データマネジメント・統計解析 | L64: =COUNTIF('ケイパビリティ×情報オブジェクト'!BL$6:BL$58,"C") -> 2 | M64: =COUNTIF('ケイパビリティ×情報オブジェクト'!BL$6:BL$58,"R") -> 3
A65: CLN-14 | B65: 臨床 | C65: 統合解析 | D65: Integrated Analysis | E65: 統合安全性・統合有効性・曝露反応・免疫原性の統合解析 | F65: 分析・評価 | G65: GCP | H65: =IF(G65="非GxP","—","対象候補") -> 対象候補 | I65: なし | J65: C05-05 | K65: {=IFERROR(INDEX('ケイパビリティマップ'!$E:$E,MATCH(J65,'ケイパビリティマップ'!$A:$A,0)),"（IDなし）")} -> 臨床データマネジメント・統計解析 | L65: =COUNTIF('ケイパビリティ×情報オブジェクト'!BM$6:BM$58,"C") -> 2 | M65: =COUNTIF('ケイパビリティ×情報オブジェクト'!BM$6:BM$58,"R") -> 4
A66: CLN-15 | B66: 臨床 | C66: ベネフィット・リスク評価 | D66: Benefit-Risk Assessment | E66: 承認判断・価格設定の根拠となる評価 | F66: 分析・評価 | G66: 薬事 | H66: =IF(G66="非GxP","—","対象候補") -> 対象候補 | I66: なし | J66: C09-02 | K66: {=IFERROR(INDEX('ケイパビリティマップ'!$E:$E,MATCH(J66,'ケイパビリティマップ'!$A:$A,0)),"（IDなし）")} -> 安全性シグナル・リスク管理 | L66: =COUNTIF('ケイパビリティ×情報オブジェクト'!BN$6:BN$58,"C") -> 1 | M66: =COUNTIF('ケイパビリティ×情報オブジェクト'!BN$6:BN$58,"R") -> 4
A67: CLN-16 | B67: 臨床 | C67: 治験薬供給記録 | D67: Clinical Supply Record | E67: 治験薬の割付・出荷・施設在庫（IRT） | F67: トランザクション | G67: GMP・GCP | H67: =IF(G67="非GxP","—","対象候補") -> 対象候補 | I67: なし | J67: C05-06 | K67: {=IFERROR(INDEX('ケイパビリティマップ'!$E:$E,MATCH(J67,'ケイパビリティマップ'!$A:$A,0)),"（IDなし）")} -> 治験薬供給管理 | L67: =COUNTIF('ケイパビリティ×情報オブジェクト'!BO$6:BO$58,"C") -> 1 | M67: =COUNTIF('ケイパビリティ×情報オブジェクト'!BO$6:BO$58,"R") -> 1
A68: CLN-17 | B68: 臨床 | C68: PK/PDモデル・解析結果 | D68: PK/PD Model | E68: ヒトPK予測・初回投与量根拠・母集団PK・曝露反応モデル | F68: 分析・評価 | G68: GCP | H68: =IF(G68="非GxP","—","対象候補") -> 対象候補 | I68: なし | J68: C03-04 | K68: {=IFERROR(INDEX('ケイパビリティマップ'!$E:$E,MATCH(J68,'ケイパビリティマップ'!$A:$A,0)),"（IDなし）")} -> 臨床薬理・ファーマコメトリクス | L68: =COUNTIF('ケイパビリティ×情報オブジェクト'!BP$6:BP$58,"C") -> 1 | M68: =COUNTIF('ケイパビリティ×情報オブジェクト'!BP$6:BP$58,"R") -> 1
A69: CLN-18 | B69: 臨床 | C69: 臨床試験 | D69: Clinical Study | E69: 個々の臨床試験・研究（自然歴研究・市販後試験を含む）。試験番号・相・状態を持ち、実施計画書・症例データ・治験薬供給を束ねる | F69: マスタ | G69: GCP | H69: =IF(G69="非GxP","—","対象候補") -> 対象候補 | I69: なし | J69: C05-04 | K69: {=IFERROR(INDEX('ケイパビリティマップ'!$E:$E,MATCH(J69,'ケイパビリティマップ'!$A:$A,0)),"（IDなし）")} -> 臨床試験運営 | L69: =COUNTIF('ケイパビリティ×情報オブジェクト'!BQ$6:BQ$58,"C") -> 3 | M69: =COUNTIF('ケイパビリティ×情報オブジェクト'!BQ$6:BQ$58,"R") -> 2
A70: CLN-19 | B70: 臨床 | C70: 患者・被験者 | D70: Patient / Subject | E70: レジストリ参加者・候補患者・被験者・治療中の患者を同一人物として識別する情報。試験・レジストリ・患者支援・有害事象をつなぐ（個人情報を含む） | F70: マスタ | G70: GCP・PV | H70: =IF(G70="非GxP","—","対象候補") -> 対象候補 | I70: 患者 | J70: C13-01 | K70: {=IFERROR(INDEX('ケイパビリティマップ'!$E:$E,MATCH(J70,'ケイパビリティマップ'!$A:$A,0)),"（IDなし）")} -> 情報・データ管理 | L70: =COUNTIF('ケイパビリティ×情報オブジェクト'!BR$6:BR$58,"C") -> 4 | M70: =COUNTIF('ケイパビリティ×情報オブジェクト'!BR$6:BR$58,"R") -> 2
A71: REG-01 | B71: 薬事 | C71: 当局コミュニケーション記録 | D71: Health Authority Interaction | E71: FDAとの会議資料・議事録・照会（IR）・回答・通知 | F71: トランザクション | G71: 薬事 | H71: =IF(G71="非GxP","—","対象候補") -> 対象候補 | I71: なし | J71: C06-01 | K71: {=IFERROR(INDEX('ケイパビリティマップ'!$E:$E,MATCH(J71,'ケイパビリティマップ'!$A:$A,0)),"（IDなし）")} -> 薬事戦略・当局対応 | L71: =COUNTIF('ケイパビリティ×情報オブジェクト'!BS$6:BS$58,"C") -> 2 | M71: =COUNTIF('ケイパビリティ×情報オブジェクト'!BS$6:BS$58,"R") -> 1
A72: REG-02 | B72: 薬事 | C72: 指定・インセンティブ | D72: Designation & Incentive | E72: Orphan Drug、希少小児疾患、Fast Track、Breakthrough Therapy、優先審査バウチャー | F72: トランザクション | G72: 薬事 | H72: =IF(G72="非GxP","—","対象候補") -> 対象候補 | I72: なし | J72: C06-01 | K72: {=IFERROR(INDEX('ケイパビリティマップ'!$E:$E,MATCH(J72,'ケイパビリティマップ'!$A:$A,0)),"（IDなし）")} -> 薬事戦略・当局対応 | L72: =COUNTIF('ケイパビリティ×情報オブジェクト'!BT$6:BT$58,"C") -> 1 | M72: =COUNTIF('ケイパビリティ×情報オブジェクト'!BT$6:BT$58,"R") -> 3
A73: REG-03 | B73: 薬事 | C73: IND | D73: IND | E73: IND申請と、その後の修正・年次報告 | F73: 文書 | G73: 薬事 | H73: =IF(G73="非GxP","—","対象候補") -> 対象候補 | I73: なし | J73: C06-02 | K73: {=IFERROR(INDEX('ケイパビリティマップ'!$E:$E,MATCH(J73,'ケイパビリティマップ'!$A:$A,0)),"（IDなし）")} -> 申請資料作成・管理 | L73: =COUNTIF('ケイパビリティ×情報オブジェクト'!BU$6:BU$58,"C") -> 1 | M73: =COUNTIF('ケイパビリティ×情報オブジェクト'!BU$6:BU$58,"R") -> 1
A74: REG-04 | B74: 薬事 | C74: 申請資料 | D74: Submission Dossier | E74: BLA（eCTD Module 1〜5）と補足申請（sBLA・製法変更） | F74: 文書 | G74: 薬事 | H74: =IF(G74="非GxP","—","対象候補") -> 対象候補 | I74: なし | J74: C06-02 | K74: {=IFERROR(INDEX('ケイパビリティマップ'!$E:$E,MATCH(J74,'ケイパビリティマップ'!$A:$A,0)),"（IDなし）")} -> 申請資料作成・管理 | L74: =COUNTIF('ケイパビリティ×情報オブジェクト'!BV$6:BV$58,"C") -> 5 | M74: =COUNTIF('ケイパビリティ×情報オブジェクト'!BV$6:BV$58,"R") -> 0
A75: REG-05 | B75: 薬事 | C75: 承認・許可 | D75: License & Approval | E75: BLA承認通知、承認条件、審査完了通知（CRL） | F75: トランザクション | G75: 薬事 | H75: =IF(G75="非GxP","—","対象候補") -> 対象候補 | I75: なし | J75: C06-02 | K75: {=IFERROR(INDEX('ケイパビリティマップ'!$E:$E,MATCH(J75,'ケイパビリティマップ'!$A:$A,0)),"（IDなし）")} -> 申請資料作成・管理 | L75: =COUNTIF('ケイパビリティ×情報オブジェクト'!BW$6:BW$58,"C") -> 3 | M75: =COUNTIF('ケイパビリティ×情報オブジェクト'!BW$6:BW$58,"R") -> 3
A76: REG-06 | B76: 薬事 | C76: 表示（USPI） | D76: Labeling | E76: 添付文書（USPI）・患者向け資料 | F76: 定義・仕様 | G76: 薬事 | H76: =IF(G76="非GxP","—","対象候補") -> 対象候補 | I76: なし | J76: C06-03 | K76: {=IFERROR(INDEX('ケイパビリティマップ'!$E:$E,MATCH(J76,'ケイパビリティマップ'!$A:$A,0)),"（IDなし）")} -> ラベリング管理 | L76: =COUNTIF('ケイパビリティ×情報オブジェクト'!BX$6:BX$58,"C") -> 2 | M76: =COUNTIF('ケイパビリティ×情報オブジェクト'!BX$6:BX$58,"R") -> 4
A77: REG-07 | B77: 薬事 | C77: 市販後要求・コミットメント（PMR／PMC） | D77: PMR/PMC | E77: 承認時に合意した市販後の試験・調査とその状況 | F77: トランザクション | G77: 薬事 | H77: =IF(G77="非GxP","—","対象候補") -> 対象候補 | I77: なし | J77: C06-04 | K77: {=IFERROR(INDEX('ケイパビリティマップ'!$E:$E,MATCH(J77,'ケイパビリティマップ'!$A:$A,0)),"（IDなし）")} -> 市販後薬事コンプライアンス | L77: =COUNTIF('ケイパビリティ×情報オブジェクト'!BY$6:BY$58,"C") -> 2 | M77: =COUNTIF('ケイパビリティ×情報オブジェクト'!BY$6:BY$58,"R") -> 1
A78: REG-08 | B78: 薬事 | C78: REMS | D78: REMS | E78: リスク評価・緩和戦略とその評価報告 | F78: 文書 | G78: 薬事・PV | H78: =IF(G78="非GxP","—","対象候補") -> 対象候補 | I78: なし | J78: C09-02 | K78: {=IFERROR(INDEX('ケイパビリティマップ'!$E:$E,MATCH(J78,'ケイパビリティマップ'!$A:$A,0)),"（IDなし）")} -> 安全性シグナル・リスク管理 | L78: =COUNTIF('ケイパビリティ×情報オブジェクト'!BZ$6:BZ$58,"C") -> 2 | M78: =COUNTIF('ケイパビリティ×情報オブジェクト'!BZ$6:BZ$58,"R") -> 0
A79: REG-09 | B79: 薬事 | C79: 査察記録 | D79: Inspection Record | E79: 承認前査察（PLI）・BIMO査察の記録と指摘事項 | F79: トランザクション | G79: GMP・GCP | H79: =IF(G79="非GxP","—","対象候補") -> 対象候補 | I79: なし | J79: C08-04 | K79: {=IFERROR(INDEX('ケイパビリティマップ'!$E:$E,MATCH(J79,'ケイパビリティマップ'!$A:$A,0)),"（IDなし）")} -> 品質システム・監査管理 | L79: =COUNTIF('ケイパビリティ×情報オブジェクト'!CA$6:CA$58,"C") -> 1 | M79: =COUNTIF('ケイパビリティ×情報オブジェクト'!CA$6:CA$58,"R") -> 0
A80: REG-10 | B80: 薬事 | C80: 当局年次報告 | D80: Annual Report to FDA | E80: PMR／PMC年次状況報告などの定期提出物 | F80: 文書 | G80: 薬事 | H80: =IF(G80="非GxP","—","対象候補") -> 対象候補 | I80: なし | J80: C06-04 | K80: {=IFERROR(INDEX('ケイパビリティマップ'!$E:$E,MATCH(J80,'ケイパビリティマップ'!$A:$A,0)),"（IDなし）")} -> 市販後薬事コンプライアンス | L80: =COUNTIF('ケイパビリティ×情報オブジェクト'!CB$6:CB$58,"C") -> 1 | M80: =COUNTIF('ケイパビリティ×情報オブジェクト'!CB$6:CB$58,"R") -> 0
A81: SAF-01 | B81: 安全性 | C81: 有害事象症例 | D81: Adverse Event Case | E81: 治験中・市販後の有害事象の個別症例（ICSR。個人情報を含む） | F81: トランザクション | G81: GCP・PV | H81: =IF(G81="非GxP","—","対象候補") -> 対象候補 | I81: 患者 | J81: C09-01 | K81: {=IFERROR(INDEX('ケイパビリティマップ'!$E:$E,MATCH(J81,'ケイパビリティマップ'!$A:$A,0)),"（IDなし）")} -> 有害事象管理 | L81: =COUNTIF('ケイパビリティ×情報オブジェクト'!CC$6:CC$58,"C") -> 2 | M81: =COUNTIF('ケイパビリティ×情報オブジェクト'!CC$6:CC$58,"R") -> 2
A82: SAF-02 | B82: 安全性 | C82: 安全性シグナル評価 | D82: Safety Signal Assessment | E82: シグナル検出・評価の結果 | F82: 分析・評価 | G82: PV | H82: =IF(G82="非GxP","—","対象候補") -> 対象候補 | I82: なし | J82: C09-02 | K82: {=IFERROR(INDEX('ケイパビリティマップ'!$E:$E,MATCH(J82,'ケイパビリティマップ'!$A:$A,0)),"（IDなし）")} -> 安全性シグナル・リスク管理 | L82: =COUNTIF('ケイパビリティ×情報オブジェクト'!CD$6:CD$58,"C") -> 1 | M82: =COUNTIF('ケイパビリティ×情報オブジェクト'!CD$6:CD$58,"R") -> 3
A83: SAF-03 | B83: 安全性 | C83: 安全性報告 | D83: Safety Report | E83: 15日アラート報告・定期報告 | F83: 文書 | G83: PV | H83: =IF(G83="非GxP","—","対象候補") -> 対象候補 | I83: なし | J83: C09-01 | K83: {=IFERROR(INDEX('ケイパビリティマップ'!$E:$E,MATCH(J83,'ケイパビリティマップ'!$A:$A,0)),"（IDなし）")} -> 有害事象管理 | L83: =COUNTIF('ケイパビリティ×情報オブジェクト'!CE$6:CE$58,"C") -> 1 | M83: =COUNTIF('ケイパビリティ×情報オブジェクト'!CE$6:CE$58,"R") -> 0
A84: MKT-01 | B84: 市場アクセス・商業 | C84: 価格 | D84: Price | E84: WACと価格改定履歴 | F84: マスタ | G84: 非GxP | H84: =IF(G84="非GxP","—","対象候補") -> — | I84: なし | J84: C11-01 | K84: {=IFERROR(INDEX('ケイパビリティマップ'!$E:$E,MATCH(J84,'ケイパビリティマップ'!$A:$A,0)),"（IDなし）")} -> 価格・保険者契約管理 | L84: =COUNTIF('ケイパビリティ×情報オブジェクト'!CF$6:CF$58,"C") -> 1 | M84: =COUNTIF('ケイパビリティ×情報オブジェクト'!CF$6:CF$58,"R") -> 1
A85: MKT-02 | B85: 市場アクセス・商業 | C85: 保険者契約 | D85: Payer Contract | E85: Medicaid薬剤リベート契約、PBM・民間保険との契約（成果連動型を含む） | F85: トランザクション | G85: 非GxP | H85: =IF(G85="非GxP","—","対象候補") -> — | I85: なし | J85: C11-01 | K85: {=IFERROR(INDEX('ケイパビリティマップ'!$E:$E,MATCH(J85,'ケイパビリティマップ'!$A:$A,0)),"（IDなし）")} -> 価格・保険者契約管理 | L85: =COUNTIF('ケイパビリティ×情報オブジェクト'!CG$6:CG$58,"C") -> 2 | M85: =COUNTIF('ケイパビリティ×情報オブジェクト'!CG$6:CG$58,"R") -> 1
A86: MKT-03 | B86: 市場アクセス・商業 | C86: 償還コード | D86: Reimbursement Code | E86: HCPCSコードなどの償還情報 | F86: マスタ | G86: 非GxP | H86: =IF(G86="非GxP","—","対象候補") -> — | I86: なし | J86: C11-02 | K86: {=IFERROR(INDEX('ケイパビリティマップ'!$E:$E,MATCH(J86,'ケイパビリティマップ'!$A:$A,0)),"（IDなし）")} -> 政府価格報告・政策対応 | L86: =COUNTIF('ケイパビリティ×情報オブジェクト'!CH$6:CH$58,"C") -> 1 | M86: =COUNTIF('ケイパビリティ×情報オブジェクト'!CH$6:CH$58,"R") -> 1
A87: MKT-04 | B87: 市場アクセス・商業 | C87: 患者支援ケース | D87: Patient Services Case | E87: ハブ経由の患者登録・保険確認・治療開始状況（個人情報を含む） | F87: トランザクション | G87: 非GxP | H87: =IF(G87="非GxP","—","対象候補") -> — | I87: 患者 | J87: C10-04 | K87: {=IFERROR(INDEX('ケイパビリティマップ'!$E:$E,MATCH(J87,'ケイパビリティマップ'!$A:$A,0)),"（IDなし）")} -> 患者支援サービス★ | L87: =COUNTIF('ケイパビリティ×情報オブジェクト'!CI$6:CI$58,"C") -> 1 | M87: =COUNTIF('ケイパビリティ×情報オブジェクト'!CI$6:CI$58,"R") -> 2
A88: MKT-05 | B88: 市場アクセス・商業 | C88: 販促・医療情報資材 | D88: Promotional & Medical Material | E88: 販促資材（Form FDA 2253）・疾患啓発資材 | F88: 文書 | G88: 薬事 | H88: =IF(G88="非GxP","—","対象候補") -> 対象候補 | I88: なし | J88: C11-03 | K88: {=IFERROR(INDEX('ケイパビリティマップ'!$E:$E,MATCH(J88,'ケイパビリティマップ'!$A:$A,0)),"（IDなし）")} -> 販促・商業コンプライアンス | L88: =COUNTIF('ケイパビリティ×情報オブジェクト'!CJ$6:CJ$58,"C") -> 2 | M88: =COUNTIF('ケイパビリティ×情報オブジェクト'!CJ$6:CJ$58,"R") -> 1
A89: MKT-06 | B89: 市場アクセス・商業 | C89: 医療機関・医療従事者マスタ | D89: HCP/HCO Master | E89: 専門施設ネットワーク・専門医の情報 | F89: マスタ | G89: 非GxP | H89: =IF(G89="非GxP","—","対象候補") -> — | I89: 医療従事者 | J89: C10-03 | K89: {=IFERROR(INDEX('ケイパビリティマップ'!$E:$E,MATCH(J89,'ケイパビリティマップ'!$A:$A,0)),"（IDなし）")} -> 疾患啓発・診断支援★ | L89: =COUNTIF('ケイパビリティ×情報オブジェクト'!CK$6:CK$58,"C") -> 1 | M89: =COUNTIF('ケイパビリティ×情報オブジェクト'!CK$6:CK$58,"R") -> 0
A90: MKT-07 | B90: 市場アクセス・商業 | C90: 教育記録 | D90: Field Training Record | E90: MSL・営業担当の教育記録 | F90: トランザクション | G90: 非GxP | H90: =IF(G90="非GxP","—","対象候補") -> — | I90: 従業員 | J90: C11-04 | K90: {=IFERROR(INDEX('ケイパビリティマップ'!$E:$E,MATCH(J90,'ケイパビリティマップ'!$A:$A,0)),"（IDなし）")} -> 営業・顧客管理 | L90: =COUNTIF('ケイパビリティ×情報オブジェクト'!CL$6:CL$58,"C") -> 1 | M90: =COUNTIF('ケイパビリティ×情報オブジェクト'!CL$6:CL$58,"R") -> 0
A91: MKT-08 | B91: 市場アクセス・商業 | C91: 政府価格報告 | D91: Government Price Reporting | E91: AMP・Best Price・ASPなどの報告データ | F91: トランザクション | G91: 非GxP | H91: =IF(G91="非GxP","—","対象候補") -> — | I91: なし | J91: C11-02 | K91: {=IFERROR(INDEX('ケイパビリティマップ'!$E:$E,MATCH(J91,'ケイパビリティマップ'!$A:$A,0)),"（IDなし）")} -> 政府価格報告・政策対応 | L91: =COUNTIF('ケイパビリティ×情報オブジェクト'!CM$6:CM$58,"C") -> 1 | M91: =COUNTIF('ケイパビリティ×情報オブジェクト'!CM$6:CM$58,"R") -> 0
A92: MKT-09 | B92: 市場アクセス・商業 | C92: Medicare価格交渉対象判定 | D92: IRA Negotiation Status | E92: IRAの交渉対象・除外要件の判定と記録 | F92: 分析・評価 | G92: 非GxP | H92: =IF(G92="非GxP","—","対象候補") -> — | I92: なし | J92: C11-02 | K92: {=IFERROR(INDEX('ケイパビリティマップ'!$E:$E,MATCH(J92,'ケイパビリティマップ'!$A:$A,0)),"（IDなし）")} -> 政府価格報告・政策対応 | L92: =COUNTIF('ケイパビリティ×情報オブジェクト'!CN$6:CN$58,"C") -> 1 | M92: =COUNTIF('ケイパビリティ×情報オブジェクト'!CN$6:CN$58,"R") -> 0
A93: SCM-01 | B93: 供給・流通 | C93: 需給計画 | D93: Demand & Supply Plan | E93: 需要予測・在庫計画（患者単位の需要を含む） | F93: トランザクション | G93: 非GxP | H93: =IF(G93="非GxP","—","対象候補") -> — | I93: なし | J93: C12-01 | K93: {=IFERROR(INDEX('ケイパビリティマップ'!$E:$E,MATCH(J93,'ケイパビリティマップ'!$A:$A,0)),"（IDなし）")} -> 需給計画 | L93: =COUNTIF('ケイパビリティ×情報オブジェクト'!CO$6:CO$58,"C") -> 1 | M93: =COUNTIF('ケイパビリティ×情報オブジェクト'!CO$6:CO$58,"R") -> 2
A94: SCM-02 | B94: 供給・流通 | C94: 在庫 | D94: Inventory | E94: 製品・原薬の在庫（拠点別） | F94: トランザクション | G94: GMP・流通 | H94: =IF(G94="非GxP","—","対象候補") -> 対象候補 | I94: なし | J94: C12-01 | K94: {=IFERROR(INDEX('ケイパビリティマップ'!$E:$E,MATCH(J94,'ケイパビリティマップ'!$A:$A,0)),"（IDなし）")} -> 需給計画 | L94: =COUNTIF('ケイパビリティ×情報オブジェクト'!CP$6:CP$58,"C") -> 3 | M94: =COUNTIF('ケイパビリティ×情報オブジェクト'!CP$6:CP$58,"R") -> 2
A95: SCM-03 | B95: 供給・流通 | C95: 受注・出荷 | D95: Order & Shipment | E95: 受注、出荷、配送、納品 | F95: トランザクション | G95: GMP・流通 | H95: =IF(G95="非GxP","—","対象候補") -> 対象候補 | I95: なし | J95: C12-01 | K95: {=IFERROR(INDEX('ケイパビリティマップ'!$E:$E,MATCH(J95,'ケイパビリティマップ'!$A:$A,0)),"（IDなし）")} -> 需給計画 | L95: =COUNTIF('ケイパビリティ×情報オブジェクト'!CQ$6:CQ$58,"C") -> 3 | M95: =COUNTIF('ケイパビリティ×情報オブジェクト'!CQ$6:CQ$58,"R") -> 1
A96: SCM-04 | B96: 供給・流通 | C96: 温度記録 | D96: Temperature Log | E96: 保管・輸送中の温度データ | F96: 測定データ | G96: GMP・流通 | H96: =IF(G96="非GxP","—","対象候補") -> 対象候補 | I96: なし | J96: C12-03 | K96: {=IFERROR(INDEX('ケイパビリティマップ'!$E:$E,MATCH(J96,'ケイパビリティマップ'!$A:$A,0)),"（IDなし）")} -> コールドチェーン物流 | L96: =COUNTIF('ケイパビリティ×情報オブジェクト'!CR$6:CR$58,"C") -> 1 | M96: =COUNTIF('ケイパビリティ×情報オブジェクト'!CR$6:CR$58,"R") -> 0
A97: SCM-05 | B97: 供給・流通 | C97: 製品識別子・取引情報（DSCSA） | D97: Serialization & Transaction Data | E97: シリアル番号、取引情報の電子的な記録・交換 | F97: トランザクション | G97: 流通 | H97: =IF(G97="非GxP","—","対象候補") -> 対象候補 | I97: なし | J97: C12-04 | K97: {=IFERROR(INDEX('ケイパビリティマップ'!$E:$E,MATCH(J97,'ケイパビリティマップ'!$A:$A,0)),"（IDなし）")} -> トレーサビリティ | L97: =COUNTIF('ケイパビリティ×情報オブジェクト'!CS$6:CS$58,"C") -> 2 | M97: =COUNTIF('ケイパビリティ×情報オブジェクト'!CS$6:CS$58,"R") -> 1
A98: SCM-06 | B98: 供給・流通 | C98: 回収記録 | D98: Recall Record | E98: 回収の範囲・実施状況 | F98: トランザクション | G98: GMP・薬事 | H98: =IF(G98="非GxP","—","対象候補") -> 対象候補 | I98: なし | J98: C12-05 | K98: {=IFERROR(INDEX('ケイパビリティマップ'!$E:$E,MATCH(J98,'ケイパビリティマップ'!$A:$A,0)),"（IDなし）")} -> 供給継続・回収管理 | L98: =COUNTIF('ケイパビリティ×情報オブジェクト'!CT$6:CT$58,"C") -> 1 | M98: =COUNTIF('ケイパビリティ×情報オブジェクト'!CT$6:CT$58,"R") -> 0
A99: SCM-07 | B99: 供給・流通 | C99: 供給継続計画 | D99: Supply Continuity Plan | E99: 供給リスクと対応策、FDAへの事前通知 | F99: 文書 | G99: 薬事 | H99: =IF(G99="非GxP","—","対象候補") -> 対象候補 | I99: なし | J99: C12-05 | K99: {=IFERROR(INDEX('ケイパビリティマップ'!$E:$E,MATCH(J99,'ケイパビリティマップ'!$A:$A,0)),"（IDなし）")} -> 供給継続・回収管理 | L99: =COUNTIF('ケイパビリティ×情報オブジェクト'!CU$6:CU$58,"C") -> 1 | M99: =COUNTIF('ケイパビリティ×情報オブジェクト'!CU$6:CU$58,"R") -> 0

Sheet ケイパビリティ×情報オブジェクト
A1: ケイパビリティ×情報オブジェクト（正本：行＝ケイパビリティL2 × 列＝情報オブジェクト）
A2: C＝作成・更新（その能力の中で生み出す／維持する情報。オーナーのL2は必ずC） R＝利用（その能力が入力として参照する情報） 空欄＝関係なし
A4: ケイパビリティL1 | B4: L2 ID | C4: ケイパビリティL2 | D4: 共通・マスタ | J4: 研究 | V4: 非臨床 | Z4: CMC開発 | AM4: 製造・品質 | AZ4: 臨床 | BS4: 薬事 | CC4: 安全性 | CF4: 市場アクセス・商業 | CO4: 供給・流通 | CV4: Cの数 | CW4: Rの数
D5: ='情報オブジェクト'!C4 -> 製品マスタ | E5: ='情報オブジェクト'!C5 -> 開発判定記録 | F5: ='情報オブジェクト'!C6 -> 特許・独占期間 | G5: ='情報オブジェクト'!C7 -> 取引先・施設マスタ | H5: ='情報オブジェクト'!C8 -> 契約 | I5: ='情報オブジェクト'!C9 -> 適応症 | J5: ='情報オブジェクト'!C10 -> 疾患知見 | K5: ='情報オブジェクト'!C11 -> 遺伝子・オミクスデータ | L5: ='情報オブジェクト'!C12 -> 標的 | M5: ='情報オブジェクト'!C13 -> 抗原・試薬 | N5: ='情報オブジェクト'!C14 -> アッセイ（評価系） | O5: ='情報オブジェクト'!C15 -> 抗体分子 | P5: ='情報オブジェクト'!C16 -> 研究実験データ | Q5: ='情報オブジェクト'!C17 -> 疾患モデル | R5: ='情報オブジェクト'!C18 -> in vivo薬効データ | S5: ='情報オブジェクト'!C19 -> 免疫原性リスク評価 | T5: ='情報オブジェクト'!C20 -> 目標製品プロファイル（TPP） | U5: ='情報オブジェクト'!C21 -> 疫学データ | V5: ='情報オブジェクト'!C22 -> 非臨床試験計画 | W5: ='情報オブジェクト'!C23 -> 非臨床試験データ | X5: ='情報オブジェクト'!C24 -> 非臨床試験報告書 | Y5: ='情報オブジェクト'!C25 -> 生体試料分析法 | Z5: ='情報オブジェクト'!C26 -> 発現ベクター・細胞株 | AA5: ='情報オブジェクト'!C27 -> セルバンク | AB5: ='情報オブジェクト'!C28 -> プロセス定義 | AC5: ='情報オブジェクト'!C29 -> プロセス開発データ | AD5: ='情報オブジェクト'!C30 -> 処方・製剤仕様 | AE5: ='情報オブジェクト'!C31 -> 重要品質特性（CQA） | AF5: ='情報オブジェクト'!C32 -> 分析法 | AG5: ='情報オブジェクト'!C33 -> 標準物質 | AH5: ='情報オブジェクト'!C34 -> 規格 | AI5: ='情報オブジェクト'!C35 -> 管理戦略 | AJ5: ='情報オブジェクト'!C36 -> 安定性データ | AK5: ='情報オブジェクト'!C37 -> CMC技術報告書 | AL5: ='情報オブジェクト'!C38 -> マスターバッチレコード | AM5: ='情報オブジェクト'!C39 -> 生産計画 | AN5: ='情報オブジェクト'!C40 -> 原材料・資材 | AO5: ='情報オブジェクト'!C41 -> バッチ記録 | AP5: ='情報オブジェクト'!C42 -> ロット | AQ5: ='情報オブジェクト'!C43 -> 工程データ | AR5: ='情報オブジェクト'!C44 -> 試験成績 | AS5: ='情報オブジェクト'!C45 -> 逸脱・CAPA | AT5: ='情報オブジェクト'!C46 -> 変更管理記録 | AU5: ='情報オブジェクト'!C47 -> 出荷判定記録 | AV5: ='情報オブジェクト'!C48 -> バリデーション計画・報告 | AW5: ='情報オブジェクト'!C49 -> 設備・環境モニタリングデータ | AX5: ='情報オブジェクト'!C50 -> 年次製品照査（APR） | AY5: ='情報オブジェクト'!C51 -> 包装表示（アートワーク） | AZ5: ='情報オブジェクト'!C52 -> 自然歴データ | BA5: ='情報オブジェクト'!C53 -> 患者レジストリデータ | BB5: ='情報オブジェクト'!C54 -> 候補患者情報 | BC5: ='情報オブジェクト'!C55 -> 臨床評価指標・バイオマーカー定義 | BD5: ='情報オブジェクト'!C56 -> 治験実施計画書 | BE5: ='情報オブジェクト'!C57 -> 治験薬概要書（IB） | BF5: ='情報オブジェクト'!C58 -> 試験実施体制 | BG5: ='情報オブジェクト'!C59 -> 試験登録情報 | BH5: ='情報オブジェクト'!C60 -> 症例データ | BI5: ='情報オブジェクト'!C61 -> 臨床検体分析データ | BJ5: ='情報オブジェクト'!C62 -> 臨床データセット | BK5: ='情報オブジェクト'!C63 -> 統計解析結果 | BL5: ='情報オブジェクト'!C64 -> 総括報告書（CSR） | BM5: ='情報オブジェクト'!C65 -> 統合解析 | BN5: ='情報オブジェクト'!C66 -> ベネフィット・リスク評価 | BO5: ='情報オブジェクト'!C67 -> 治験薬供給記録 | BP5: ='情報オブジェクト'!C68 -> PK/PDモデル・解析結果 | BQ5: ='情報オブジェクト'!C69 -> 臨床試験 | BR5: ='情報オブジェクト'!C70 -> 患者・被験者 | BS5: ='情報オブジェクト'!C71 -> 当局コミュニケーション記録 | BT5: ='情報オブジェクト'!C72 -> 指定・インセンティブ | BU5: ='情報オブジェクト'!C73 -> IND | BV5: ='情報オブジェクト'!C74 -> 申請資料 | BW5: ='情報オブジェクト'!C75 -> 承認・許可 | BX5: ='情報オブジェクト'!C76 -> 表示（USPI） | BY5: ='情報オブジェクト'!C77 -> 市販後要求・コミットメント（PMR／PMC） | BZ5: ='情報オブジェクト'!C78 -> REMS | CA5: ='情報オブジェクト'!C79 -> 査察記録 | CB5: ='情報オブジェクト'!C80 -> 当局年次報告 | CC5: ='情報オブジェクト'!C81 -> 有害事象症例 | CD5: ='情報オブジェクト'!C82 -> 安全性シグナル評価 | CE5: ='情報オブジェクト'!C83 -> 安全性報告 | CF5: ='情報オブジェクト'!C84 -> 価格 | CG5: ='情報オブジェクト'!C85 -> 保険者契約 | CH5: ='情報オブジェクト'!C86 -> 償還コード | CI5: ='情報オブジェクト'!C87 -> 患者支援ケース | CJ5: ='情報オブジェクト'!C88 -> 販促・医療情報資材 | CK5: ='情報オブジェクト'!C89 -> 医療機関・医療従事者マスタ | CL5: ='情報オブジェクト'!C90 -> 教育記録 | CM5: ='情報オブジェクト'!C91 -> 政府価格報告 | CN5: ='情報オブジェクト'!C92 -> Medicare価格交渉対象判定 | CO5: ='情報オブジェクト'!C93 -> 需給計画 | CP5: ='情報オブジェクト'!C94 -> 在庫 | CQ5: ='情報オブジェクト'!C95 -> 受注・出荷 | CR5: ='情報オブジェクト'!C96 -> 温度記録 | CS5: ='情報オブジェクト'!C97 -> 製品識別子・取引情報（DSCSA） | CT5: ='情報オブジェクト'!C98 -> 回収記録 | CU5: ='情報オブジェクト'!C99 -> 供給継続計画
A6: C01 戦略・ガバナンス | B6: C01-01 | C6: {=IFERROR(INDEX('ケイパビリティマップ'!$E:$E,MATCH(B6,'ケイパビリティマップ'!$A:$A,0)),"（IDなし）")} -> 研究開発ポートフォリオ管理 | D6: C | E6: C | F6: R | I6: C | P6: R | R6: R | S6: R | T6: C | U6: R | CV6: =COUNTIF(D6:CU6,"C") -> 4 | CW6: =COUNTIF(D6:CU6,"R") -> 5
B7: C01-02 | C7: {=IFERROR(INDEX('ケイパビリティマップ'!$E:$E,MATCH(B7,'ケイパビリティマップ'!$A:$A,0)),"（IDなし）")} -> 知財・独占期間管理 | F7: C | O7: R | BT7: R | BW7: R | CV7: =COUNTIF(D7:CU7,"C") -> 1 | CW7: =COUNTIF(D7:CU7,"R") -> 3
B8: C01-03 | C8: {=IFERROR(INDEX('ケイパビリティマップ'!$E:$E,MATCH(B8,'ケイパビリティマップ'!$A:$A,0)),"（IDなし）")} -> 外部パートナー管理 | G8: C | H8: C | CV8: =COUNTIF(D8:CU8,"C") -> 2 | CW8: =COUNTIF(D8:CU8,"R") -> 0
A9: C02 研究（創薬） | B9: C02-01 | C9: {=IFERROR(INDEX('ケイパビリティマップ'!$E:$E,MATCH(B9,'ケイパビリティマップ'!$A:$A,0)),"（IDなし）")} -> 疾患・標的研究★ | E9: C | F9: R | I9: C | J9: R | K9: C | L9: C | P9: C | T9: C | CV9: =COUNTIF(D9:CU9,"C") -> 6 | CW9: =COUNTIF(D9:CU9,"R") -> 2
B10: C02-02 | C10: {=IFERROR(INDEX('ケイパビリティマップ'!$E:$E,MATCH(B10,'ケイパビリティマップ'!$A:$A,0)),"（IDなし）")} -> 抗体創出 | E10: C | L10: R | M10: C | N10: C | O10: C | P10: C | CV10: =COUNTIF(D10:CU10,"C") -> 5 | CW10: =COUNTIF(D10:CU10,"R") -> 1
B11: C02-03 | C11: {=IFERROR(INDEX('ケイパビリティマップ'!$E:$E,MATCH(B11,'ケイパビリティマップ'!$A:$A,0)),"（IDなし）")} -> 抗体エンジニアリング | O11: C | CV11: =COUNTIF(D11:CU11,"C") -> 1 | CW11: =COUNTIF(D11:CU11,"R") -> 0
B12: C02-04 | C12: {=IFERROR(INDEX('ケイパビリティマップ'!$E:$E,MATCH(B12,'ケイパビリティマップ'!$A:$A,0)),"（IDなし）")} -> 疾患モデル・薬効評価 | K12: R | O12: R | Q12: C | R12: C | CV12: =COUNTIF(D12:CU12,"C") -> 2 | CW12: =COUNTIF(D12:CU12,"R") -> 2
B13: C02-05 | C13: {=IFERROR(INDEX('ケイパビリティマップ'!$E:$E,MATCH(B13,'ケイパビリティマップ'!$A:$A,0)),"（IDなし）")} -> 開発適性・免疫原性リスク評価 | O13: R | P13: C | S13: C | CV13: =COUNTIF(D13:CU13,"C") -> 2 | CW13: =COUNTIF(D13:CU13,"R") -> 1
A14: C03 非臨床・臨床薬理 | B14: C03-01 | C14: {=IFERROR(INDEX('ケイパビリティマップ'!$E:$E,MATCH(B14,'ケイパビリティマップ'!$A:$A,0)),"（IDなし）")} -> 非臨床薬理評価 | O14: R | P14: R | Q14: R | V14: R | W14: C | X14: C | CV14: =COUNTIF(D14:CU14,"C") -> 2 | CW14: =COUNTIF(D14:CU14,"R") -> 4
B15: C03-02 | C15: {=IFERROR(INDEX('ケイパビリティマップ'!$E:$E,MATCH(B15,'ケイパビリティマップ'!$A:$A,0)),"（IDなし）")} -> 非臨床安全性評価 | O15: R | P15: R | V15: C | W15: C | X15: C | AP15: R | CV15: =COUNTIF(D15:CU15,"C") -> 3 | CW15: =COUNTIF(D15:CU15,"R") -> 3
B16: C03-03 | C16: {=IFERROR(INDEX('ケイパビリティマップ'!$E:$E,MATCH(B16,'ケイパビリティマップ'!$A:$A,0)),"（IDなし）")} -> バイオアナリシス | O16: R | V16: R | W16: C | Y16: C | BH16: R | BI16: C | CV16: =COUNTIF(D16:CU16,"C") -> 3 | CW16: =COUNTIF(D16:CU16,"R") -> 3
B17: C03-04 | C17: {=IFERROR(INDEX('ケイパビリティマップ'!$E:$E,MATCH(B17,'ケイパビリティマップ'!$A:$A,0)),"（IDなし）")} -> 臨床薬理・ファーマコメトリクス | W17: R | X17: R | BI17: R | BJ17: R | BM17: C | BP17: C | CV17: =COUNTIF(D17:CU17,"C") -> 2 | CW17: =COUNTIF(D17:CU17,"R") -> 4
A18: C04 CMC開発 | B18: C04-01 | C18: {=IFERROR(INDEX('ケイパビリティマップ'!$E:$E,MATCH(B18,'ケイパビリティマップ'!$A:$A,0)),"（IDなし）")} -> 細胞株開発・セルバンク管理 | O18: R | Z18: C | AA18: C | AC18: C | AK18: C | AO18: C | CV18: =COUNTIF(D18:CU18,"C") -> 5 | CW18: =COUNTIF(D18:CU18,"R") -> 1
B19: C04-02 | C19: {=IFERROR(INDEX('ケイパビリティマップ'!$E:$E,MATCH(B19,'ケイパビリティマップ'!$A:$A,0)),"（IDなし）")} -> 原薬プロセス開発 | Z19: R | AB19: C | AC19: C | AE19: R | AH19: R | AI19: C | AK19: C | CV19: =COUNTIF(D19:CU19,"C") -> 4 | CW19: =COUNTIF(D19:CU19,"R") -> 3
B20: C04-03 | C20: {=IFERROR(INDEX('ケイパビリティマップ'!$E:$E,MATCH(B20,'ケイパビリティマップ'!$A:$A,0)),"（IDなし）")} -> 製剤・デバイス開発 | P20: R | AD20: C | AF20: R | AJ20: C | CV20: =COUNTIF(D20:CU20,"C") -> 2 | CW20: =COUNTIF(D20:CU20,"R") -> 2
B21: C04-04 | C21: {=IFERROR(INDEX('ケイパビリティマップ'!$E:$E,MATCH(B21,'ケイパビリティマップ'!$A:$A,0)),"（IDなし）")} -> 分析法開発・品質特性評価 | O21: R | AB21: R | AC21: R | AE21: C | AF21: C | AG21: C | AH21: C | AJ21: R | AK21: C | AP21: R | AR21: R | CV21: =COUNTIF(D21:CU21,"C") -> 5 | CW21: =COUNTIF(D21:CU21,"R") -> 6
B22: C04-05 | C22: {=IFERROR(INDEX('ケイパビリティマップ'!$E:$E,MATCH(B22,'ケイパビリティマップ'!$A:$A,0)),"（IDなし）")} -> 技術移転・製造規模管理 | U22: R | AA22: R | AB22: C | AF22: R | AI22: R | AK22: C | AL22: C | CV22: =COUNTIF(D22:CU22,"C") -> 3 | CW22: =COUNTIF(D22:CU22,"R") -> 4
A23: C05 臨床開発 | B23: C05-01 | C23: {=IFERROR(INDEX('ケイパビリティマップ'!$E:$E,MATCH(B23,'ケイパビリティマップ'!$A:$A,0)),"（IDなし）")} -> 臨床開発戦略・試験デザイン | I23: R | J23: R | AZ23: R | BC23: C | BD23: C | BE23: C | BP23: R | BQ23: C | BS23: R | CV23: =COUNTIF(D23:CU23,"C") -> 4 | CW23: =COUNTIF(D23:CU23,"R") -> 5
B24: C05-02 | C24: {=IFERROR(INDEX('ケイパビリティマップ'!$E:$E,MATCH(B24,'ケイパビリティマップ'!$A:$A,0)),"（IDなし）")} -> 患者エビデンス管理★ | I24: R | J24: R | U24: C | AZ24: C | BA24: C | BQ24: C | BR24: C | CV24: =COUNTIF(D24:CU24,"C") -> 5 | CW24: =COUNTIF(D24:CU24,"R") -> 2
B25: C05-03 | C25: {=IFERROR(INDEX('ケイパビリティマップ'!$E:$E,MATCH(B25,'ケイパビリティマップ'!$A:$A,0)),"（IDなし）")} -> 患者特定・組入れ★ | K25: R | BA25: R | BB25: C | BR25: C | CV25: =COUNTIF(D25:CU25,"C") -> 2 | CW25: =COUNTIF(D25:CU25,"R") -> 2
B26: C05-04 | C26: {=IFERROR(INDEX('ケイパビリティマップ'!$E:$E,MATCH(B26,'ケイパビリティマップ'!$A:$A,0)),"（IDなし）")} -> 臨床試験運営 | G26: R | H26: C | BB26: R | BD26: C | BF26: C | BG26: C | BH26: C | BI26: C | BL26: C | BO26: R | BQ26: C | BR26: C | BV26: C | BY26: R | CC26: C | CV26: =COUNTIF(D26:CU26,"C") -> 11 | CW26: =COUNTIF(D26:CU26,"R") -> 4
B27: C05-05 | C27: {=IFERROR(INDEX('ケイパビリティマップ'!$E:$E,MATCH(B27,'ケイパビリティマップ'!$A:$A,0)),"（IDなし）")} -> 臨床データマネジメント・統計解析 | X27: R | AH27: R | AZ27: R | BE27: C | BH27: C | BI27: R | BJ27: C | BK27: C | BL27: C | BM27: C | BQ27: R | CC27: R | CV27: =COUNTIF(D27:CU27,"C") -> 6 | CW27: =COUNTIF(D27:CU27,"R") -> 6
B28: C05-06 | C28: {=IFERROR(INDEX('ケイパビリティマップ'!$E:$E,MATCH(B28,'ケイパビリティマップ'!$A:$A,0)),"（IDなし）")} -> 治験薬供給管理 | AP28: R | AY28: C | BD28: R | BO28: C | CV28: =COUNTIF(D28:CU28,"C") -> 2 | CW28: =COUNTIF(D28:CU28,"R") -> 2
A29: C06 薬事 | B29: C06-01 | C29: {=IFERROR(INDEX('ケイパビリティマップ'!$E:$E,MATCH(B29,'ケイパビリティマップ'!$A:$A,0)),"（IDなし）")} -> 薬事戦略・当局対応 | D29: C | E29: C | I29: R | U29: R | X29: R | AK29: R | AZ29: R | BC29: R | BE29: R | BH29: R | BI29: R | BL29: R | BM29: R | BN29: R | BS29: C | BT29: C | BU29: R | BV29: C | BW29: C | CV29: =COUNTIF(D29:CU29,"C") -> 6 | CW29: =COUNTIF(D29:CU29,"R") -> 13
B30: C06-02 | C30: {=IFERROR(INDEX('ケイパビリティマップ'!$E:$E,MATCH(B30,'ケイパビリティマップ'!$A:$A,0)),"（IDなし）")} -> 申請資料作成・管理 | I30: C | X30: R | AB30: R | AD30: R | AH30: R | AI30: R | AJ30: R | AK30: R | AV30: R | BD30: R | BE30: R | BL30: R | BM30: R | BN30: R | BT30: R | BU30: C | BV30: C | BW30: C | BX30: C | CV30: =COUNTIF(D30:CU30,"C") -> 5 | CW30: =COUNTIF(D30:CU30,"R") -> 14
B31: C06-03 | C31: {=IFERROR(INDEX('ケイパビリティマップ'!$E:$E,MATCH(B31,'ケイパビリティマップ'!$A:$A,0)),"（IDなし）")} -> ラベリング管理 | AY31: C | BM31: R | BX31: C | CV31: =COUNTIF(D31:CU31,"C") -> 2 | CW31: =COUNTIF(D31:CU31,"R") -> 1
B32: C06-04 | C32: {=IFERROR(INDEX('ケイパビリティマップ'!$E:$E,MATCH(B32,'ケイパビリティマップ'!$A:$A,0)),"（IDなし）")} -> 市販後薬事コンプライアンス | AK32: R | AT32: R | AX32: R | BN32: R | BV32: C | BW32: C | BY32: C | BZ32: C | CB32: C | CD32: R | CV32: =COUNTIF(D32:CU32,"C") -> 5 | CW32: =COUNTIF(D32:CU32,"R") -> 5
A33: C07 製造 | B33: C07-01 | C33: {=IFERROR(INDEX('ケイパビリティマップ'!$E:$E,MATCH(B33,'ケイパビリティマップ'!$A:$A,0)),"（IDなし）")} -> 生産計画・製造実行管理 | AM33: C | AN33: C | AO33: C | AP33: C | CO33: R | CP33: R | CV33: =COUNTIF(D33:CU33,"C") -> 4 | CW33: =COUNTIF(D33:CU33,"R") -> 2
B34: C07-02 | C34: {=IFERROR(INDEX('ケイパビリティマップ'!$E:$E,MATCH(B34,'ケイパビリティマップ'!$A:$A,0)),"（IDなし）")} -> 原薬製造 | AA34: R | AL34: R | AM34: R | AN34: R | AO34: C | AP34: C | AQ34: C | CP34: C | CV34: =COUNTIF(D34:CU34,"C") -> 4 | CW34: =COUNTIF(D34:CU34,"R") -> 4
B35: C07-03 | C35: {=IFERROR(INDEX('ケイパビリティマップ'!$E:$E,MATCH(B35,'ケイパビリティマップ'!$A:$A,0)),"（IDなし）")} -> 製剤化・無菌充填・包装 | D35: R | AA35: R | AD35: R | AL35: R | AN35: R | AO35: C | AP35: C | AW35: C | AY35: R | CS35: C | CV35: =COUNTIF(D35:CU35,"C") -> 4 | CW35: =COUNTIF(D35:CU35,"R") -> 6
B36: C07-04 | C36: {=IFERROR(INDEX('ケイパビリティマップ'!$E:$E,MATCH(B36,'ケイパビリティマップ'!$A:$A,0)),"（IDなし）")} -> 設備・環境管理 | AW36: C | CV36: =COUNTIF(D36:CU36,"C") -> 1 | CW36: =COUNTIF(D36:CU36,"R") -> 0
A37: C08 品質 | B37: C08-01 | C37: {=IFERROR(INDEX('ケイパビリティマップ'!$E:$E,MATCH(B37,'ケイパビリティマップ'!$A:$A,0)),"（IDなし）")} -> 品質管理（試験・安定性） | AF37: R | AG37: R | AH37: R | AJ37: C | AP37: R | AR37: C | AS37: R | AT37: R | AU37: C | AX37: C | CV37: =COUNTIF(D37:CU37,"C") -> 4 | CW37: =COUNTIF(D37:CU37,"R") -> 6
B38: C08-02 | C38: {=IFERROR(INDEX('ケイパビリティマップ'!$E:$E,MATCH(B38,'ケイパビリティマップ'!$A:$A,0)),"（IDなし）")} -> 品質保証（出荷判定・逸脱・変更） | AF38: R | AG38: R | AH38: R | AJ38: C | AO38: R | AP38: R | AR38: C | AS38: C | AT38: C | AU38: C | AX38: C | BV38: C | CV38: =COUNTIF(D38:CU38,"C") -> 7 | CW38: =COUNTIF(D38:CU38,"R") -> 5
B39: C08-03 | C39: {=IFERROR(INDEX('ケイパビリティマップ'!$E:$E,MATCH(B39,'ケイパビリティマップ'!$A:$A,0)),"（IDなし）")} -> バリデーション管理 | AA39: R | AI39: R | AL39: R | AN39: R | AO39: C | AP39: C | AQ39: C | AR39: C | AV39: C | CV39: =COUNTIF(D39:CU39,"C") -> 5 | CW39: =COUNTIF(D39:CU39,"R") -> 4
B40: C08-04 | C40: {=IFERROR(INDEX('ケイパビリティマップ'!$E:$E,MATCH(B40,'ケイパビリティマップ'!$A:$A,0)),"（IDなし）")} -> 品質システム・監査管理 | AK40: R | AO40: R | AV40: R | BF40: R | BH40: R | BQ40: R | CA40: C | CV40: =COUNTIF(D40:CU40,"C") -> 1 | CW40: =COUNTIF(D40:CU40,"R") -> 6
A41: C09 ファーマコビジランス（安全性） | B41: C09-01 | C41: {=IFERROR(INDEX('ケイパビリティマップ'!$E:$E,MATCH(B41,'ケイパビリティマップ'!$A:$A,0)),"（IDなし）")} -> 有害事象管理 | BR41: R | CC41: C | CD41: R | CE41: C | CI41: R | CV41: =COUNTIF(D41:CU41,"C") -> 2 | CW41: =COUNTIF(D41:CU41,"R") -> 3
B42: C09-02 | C42: {=IFERROR(INDEX('ケイパビリティマップ'!$E:$E,MATCH(B42,'ケイパビリティマップ'!$A:$A,0)),"（IDなし）")} -> 安全性シグナル・リスク管理 | BA42: R | BL42: R | BM42: R | BN42: C | BY42: C | BZ42: C | CC42: R | CD42: C | CV42: =COUNTIF(D42:CU42,"C") -> 4 | CW42: =COUNTIF(D42:CU42,"R") -> 4
A43: C10 メディカル・患者エンゲージメント | B43: C10-01 | C43: {=IFERROR(INDEX('ケイパビリティマップ'!$E:$E,MATCH(B43,'ケイパビリティマップ'!$A:$A,0)),"（IDなし）")} -> 患者団体・専門医連携★ | J43: C | CV43: =COUNTIF(D43:CU43,"C") -> 1 | CW43: =COUNTIF(D43:CU43,"R") -> 0
B44: C10-02 | C44: {=IFERROR(INDEX('ケイパビリティマップ'!$E:$E,MATCH(B44,'ケイパビリティマップ'!$A:$A,0)),"（IDなし）")} -> メディカルアフェアーズ | CV44: =COUNTIF(D44:CU44,"C") -> 0 | CW44: =COUNTIF(D44:CU44,"R") -> 0
B45: C10-03 | C45: {=IFERROR(INDEX('ケイパビリティマップ'!$E:$E,MATCH(B45,'ケイパビリティマップ'!$A:$A,0)),"（IDなし）")} -> 疾患啓発・診断支援★ | BB45: R | CJ45: C | CK45: C | CV45: =COUNTIF(D45:CU45,"C") -> 2 | CW45: =COUNTIF(D45:CU45,"R") -> 1
B46: C10-04 | C46: {=IFERROR(INDEX('ケイパビリティマップ'!$E:$E,MATCH(B46,'ケイパビリティマップ'!$A:$A,0)),"（IDなし）")} -> 患者支援サービス★ | H46: C | CG46: R | CH46: R | CI46: C | CV46: =COUNTIF(D46:CU46,"C") -> 2 | CW46: =COUNTIF(D46:CU46,"R") -> 2
A47: C11 市場アクセス・商業 | B47: C11-01 | C47: {=IFERROR(INDEX('ケイパビリティマップ'!$E:$E,MATCH(B47,'ケイパビリティマップ'!$A:$A,0)),"（IDなし）")} -> 価格・保険者契約管理 | U47: R | BN47: R | BX47: R | CF47: C | CG47: C | CV47: =COUNTIF(D47:CU47,"C") -> 2 | CW47: =COUNTIF(D47:CU47,"R") -> 3
B48: C11-02 | C48: {=IFERROR(INDEX('ケイパビリティマップ'!$E:$E,MATCH(B48,'ケイパビリティマップ'!$A:$A,0)),"（IDなし）")} -> 政府価格報告・政策対応 | I48: R | BT48: R | BW48: R | BX48: R | CF48: R | CG48: C | CH48: C | CM48: C | CN48: C | CV48: =COUNTIF(D48:CU48,"C") -> 4 | CW48: =COUNTIF(D48:CU48,"R") -> 5
B49: C11-03 | C49: {=IFERROR(INDEX('ケイパビリティマップ'!$E:$E,MATCH(B49,'ケイパビリティマップ'!$A:$A,0)),"（IDなし）")} -> 販促・商業コンプライアンス | BX49: R | CJ49: C | CV49: =COUNTIF(D49:CU49,"C") -> 1 | CW49: =COUNTIF(D49:CU49,"R") -> 1
B50: C11-04 | C50: {=IFERROR(INDEX('ケイパビリティマップ'!$E:$E,MATCH(B50,'ケイパビリティマップ'!$A:$A,0)),"（IDなし）")} -> 営業・顧客管理 | BX50: R | CJ50: R | CL50: C | CV50: =COUNTIF(D50:CU50,"C") -> 1 | CW50: =COUNTIF(D50:CU50,"R") -> 2
A51: C12 サプライチェーン | B51: C12-01 | C51: {=IFERROR(INDEX('ケイパビリティマップ'!$E:$E,MATCH(B51,'ケイパビリティマップ'!$A:$A,0)),"（IDなし）")} -> 需給計画 | H51: R | AU51: R | BR51: R | BW51: R | CI51: R | CO51: C | CP51: C | CQ51: C | CV51: =COUNTIF(D51:CU51,"C") -> 3 | CW51: =COUNTIF(D51:CU51,"R") -> 5
B52: C12-02 | C52: {=IFERROR(INDEX('ケイパビリティマップ'!$E:$E,MATCH(B52,'ケイパビリティマップ'!$A:$A,0)),"（IDなし）")} -> 流通ネットワーク管理★ | G52: C | H52: C | CQ52: C | CV52: =COUNTIF(D52:CU52,"C") -> 3 | CW52: =COUNTIF(D52:CU52,"R") -> 0
B53: C12-03 | C53: {=IFERROR(INDEX('ケイパビリティマップ'!$E:$E,MATCH(B53,'ケイパビリティマップ'!$A:$A,0)),"（IDなし）")} -> コールドチェーン物流 | AS53: C | AU53: R | CP53: C | CQ53: C | CR53: C | CV53: =COUNTIF(D53:CU53,"C") -> 4 | CW53: =COUNTIF(D53:CU53,"R") -> 1
B54: C12-04 | C54: {=IFERROR(INDEX('ケイパビリティマップ'!$E:$E,MATCH(B54,'ケイパビリティマップ'!$A:$A,0)),"（IDなし）")} -> トレーサビリティ | CQ54: R | CS54: C | CV54: =COUNTIF(D54:CU54,"C") -> 1 | CW54: =COUNTIF(D54:CU54,"R") -> 1
B55: C12-05 | C55: {=IFERROR(INDEX('ケイパビリティマップ'!$E:$E,MATCH(B55,'ケイパビリティマップ'!$A:$A,0)),"（IDなし）")} -> 供給継続・回収管理 | AM55: R | AS55: R | BS55: C | CD55: R | CO55: R | CP55: R | CS55: R | CT55: C | CU55: C | CV55: =COUNTIF(D55:CU55,"C") -> 3 | CW55: =COUNTIF(D55:CU55,"R") -> 6
A56: C13 共通基盤 | B56: C13-01 | C56: {=IFERROR(INDEX('ケイパビリティマップ'!$E:$E,MATCH(B56,'ケイパビリティマップ'!$A:$A,0)),"（IDなし）")} -> 情報・データ管理 | D56: C | BR56: C | CV56: =COUNTIF(D56:CU56,"C") -> 2 | CW56: =COUNTIF(D56:CU56,"R") -> 0
B57: C13-02 | C57: {=IFERROR(INDEX('ケイパビリティマップ'!$E:$E,MATCH(B57,'ケイパビリティマップ'!$A:$A,0)),"（IDなし）")} -> GxP文書・記録管理 | CV57: =COUNTIF(D57:CU57,"C") -> 0 | CW57: =COUNTIF(D57:CU57,"R") -> 0
B58: C13-03 | C58: {=IFERROR(INDEX('ケイパビリティマップ'!$E:$E,MATCH(B58,'ケイパビリティマップ'!$A:$A,0)),"（IDなし）")} -> GxP教育・資格管理 | CV58: =COUNTIF(D58:CU58,"C") -> 0 | CW58: =COUNTIF(D58:CU58,"R") -> 0
C59: Cの数 | D59: =COUNTIF(D$6:D$58,"C") -> 3 | E59: =COUNTIF(E$6:E$58,"C") -> 4 | F59: =COUNTIF(F$6:F$58,"C") -> 1 | G59: =COUNTIF(G$6:G$58,"C") -> 2 | H59: =COUNTIF(H$6:H$58,"C") -> 4 | I59: =COUNTIF(I$6:I$58,"C") -> 3 | J59: =COUNTIF(J$6:J$58,"C") -> 1 | K59: =COUNTIF(K$6:K$58,"C") -> 1 | ... CU59: =COUNTIF(CU$6:CU$58,"C") -> 1
C60: Rの数 | D60: =COUNTIF(D$6:D$58,"R") -> 1 | E60: =COUNTIF(E$6:E$58,"R") -> 0 | F60: =COUNTIF(F$6:F$58,"R") -> 2 | G60: =COUNTIF(G$6:G$58,"R") -> 1 | H60: =COUNTIF(H$6:H$58,"R") -> 1 | I60: =COUNTIF(I$6:I$58,"R") -> 4 | J60: =COUNTIF(J$6:J$58,"R") -> 3 | K60: =COUNTIF(K$6:K$58,"R") -> 2 | ... CU60: =COUNTIF(CU$6:CU$58,"R") -> 0

Sheet アプリケーション
A1: アプリケーション（正本：種類の単位）
A2: 1行1種類。製品名ではなく、機能のまとまり（種類）で定義する。現状のシステム名との対応は別の工程で行う。灰色の列は数式（編集しない）。規制区分がGxP・薬事・流通・PVに当たるものは、コンピュータ化システムバリデーションの対象候補。
A3: ID | B3: 領域 | C3: アプリケーション種類 | D3: 略称・通称 | E3: 主な機能 | F3: 規制区分 | G3: 主に支える ケイパビリティ数 | H3: 部分的に支える ケイパビリティ数
A4: APP-01 | B4: 研究 | C4: 電子実験ノート | D4: ELN | E4: 研究・プロセス開発の実験計画・記録・結果を管理する | F4: 非GxP | G4: =COUNTIF('ケイパビリティ×アプリケーション'!D$6:D$58,"●") -> 9 | H4: =COUNTIF('ケイパビリティ×アプリケーション'!D$6:D$58,"○") -> 1
A5: APP-02 | B5: 研究 | C5: 生物学的物質登録 | D5: バイオレジストリ | E5: 標的・抗原・抗体分子・細胞株などの物質を一意に登録し、系譜と状態を管理する | F5: 非GxP | G5: =COUNTIF('ケイパビリティ×アプリケーション'!E$6:E$58,"●") -> 2 | H5: =COUNTIF('ケイパビリティ×アプリケーション'!E$6:E$58,"○") -> 1
A6: APP-03 | B6: 研究 | C6: 科学データ解析基盤 | D6: バイオインフォマティクス基盤 | E6: ゲノム・オミクス・スクリーニングデータの解析と、in silico予測を行う | F6: 非GxP | G6: =COUNTIF('ケイパビリティ×アプリケーション'!F$6:F$58,"●") -> 2 | H6: =COUNTIF('ケイパビリティ×アプリケーション'!F$6:F$58,"○") -> 3
A7: APP-04 | B7: 非臨床 | C7: 非臨床試験管理 | D7: 毒性試験管理（SEND対応） | E7: GLP試験の計画・実施・データ収集と、SEND形式のデータ作成を行う | F7: GLP | G7: =COUNTIF('ケイパビリティ×アプリケーション'!G$6:G$58,"●") -> 2 | H7: =COUNTIF('ケイパビリティ×アプリケーション'!G$6:G$58,"○") -> 0
A8: APP-05 | B8: 臨床 | C8: PK/PD解析・モデリング | D8: ファーマコメトリクス環境 | E8: PK/PD解析、母集団PK、曝露反応モデルを実行する | F8: GCP | G8: =COUNTIF('ケイパビリティ×アプリケーション'!H$6:H$58,"●") -> 1 | H8: =COUNTIF('ケイパビリティ×アプリケーション'!H$6:H$58,"○") -> 0
A9: APP-06 | B9: 臨床 | C9: 臨床試験管理 | D9: CTMS | E9: 試験・施設・進捗・モニタリング・予算を管理する | F9: GCP | G9: =COUNTIF('ケイパビリティ×アプリケーション'!I$6:I$58,"●") -> 1 | H9: =COUNTIF('ケイパビリティ×アプリケーション'!I$6:I$58,"○") -> 1
A10: APP-07 | B10: 臨床 | C10: 臨床データ収集 | D10: EDC（eCOA／ePRO含む） | E10: 症例データと患者報告アウトカムを電子的に収集する | F10: GCP | G10: =COUNTIF('ケイパビリティ×アプリケーション'!J$6:J$58,"●") -> 1 | H10: =COUNTIF('ケイパビリティ×アプリケーション'!J$6:J$58,"○") -> 1
A11: APP-08 | B11: 臨床 | C11: 無作為化・治験薬供給 | D11: IRT | E11: 無作為化、治験薬の割付・出荷・施設在庫を管理する | F11: GCP・GMP | G11: =COUNTIF('ケイパビリティ×アプリケーション'!K$6:K$58,"●") -> 1 | H11: =COUNTIF('ケイパビリティ×アプリケーション'!K$6:K$58,"○") -> 0
A12: APP-09 | B12: 臨床 | C12: 電子治験マスターファイル | D12: eTMF | E12: 治験の必須文書を収集・保管する | F12: GCP | G12: =COUNTIF('ケイパビリティ×アプリケーション'!L$6:L$58,"●") -> 1 | H12: =COUNTIF('ケイパビリティ×アプリケーション'!L$6:L$58,"○") -> 1
A13: APP-10 | B13: 臨床 | C13: 統計解析環境 | D13: SCE | E13: 臨床データセット（SDTM／ADaM）の作成と統計解析を行う | F13: GCP | G13: =COUNTIF('ケイパビリティ×アプリケーション'!M$6:M$58,"●") -> 1 | H13: =COUNTIF('ケイパビリティ×アプリケーション'!M$6:M$58,"○") -> 2
A14: APP-11 | B14: 臨床 | C14: 患者レジストリ・RWD基盤 | D14: レジストリ／RWDプラットフォーム | E14: 患者レジストリ・自然歴・リアルワールドデータを収集・管理する | F14: 非GxP・PV | G14: =COUNTIF('ケイパビリティ×アプリケーション'!N$6:N$58,"●") -> 2 | H14: =COUNTIF('ケイパビリティ×アプリケーション'!N$6:N$58,"○") -> 2
A15: APP-12 | B15: 薬事 | C15: 薬事情報管理 | D15: RIM | E15: 当局とのやり取り、申請・承認・指定・約束事項、表示の版を管理する | F15: 薬事 | G15: =COUNTIF('ケイパビリティ×アプリケーション'!O$6:O$58,"●") -> 3 | H15: =COUNTIF('ケイパビリティ×アプリケーション'!O$6:O$58,"○") -> 2
A16: APP-13 | B16: 薬事 | C16: 申請出版 | D16: eCTD出版 | E16: 申請資料をeCTD形式に編集し、FDAへ提出する | F16: 薬事 | G16: =COUNTIF('ケイパビリティ×アプリケーション'!P$6:P$58,"●") -> 1 | H16: =COUNTIF('ケイパビリティ×アプリケーション'!P$6:P$58,"○") -> 0
A17: APP-14 | B17: 安全性 | C17: 安全性データベース | D17: 安全性DB（ICSR） | E17: 有害事象症例の収集・評価・当局報告を行う | F17: PV | G17: =COUNTIF('ケイパビリティ×アプリケーション'!Q$6:Q$58,"●") -> 1 | H17: =COUNTIF('ケイパビリティ×アプリケーション'!Q$6:Q$58,"○") -> 3
A18: APP-15 | B18: 安全性 | C18: シグナル検出 | D18: シグナル管理 | E18: 安全性データからシグナルを検出・評価し、リスク管理につなげる | F18: PV | G18: =COUNTIF('ケイパビリティ×アプリケーション'!R$6:R$58,"●") -> 1 | H18: =COUNTIF('ケイパビリティ×アプリケーション'!R$6:R$58,"○") -> 0
A19: APP-16 | B19: 製造 | C19: 製造実行システム | D19: MES（電子バッチ記録） | E19: 製造指図（MBR）を管理し、製造を指図・記録する | F19: GMP | G19: =COUNTIF('ケイパビリティ×アプリケーション'!S$6:S$58,"●") -> 4 | H19: =COUNTIF('ケイパビリティ×アプリケーション'!S$6:S$58,"○") -> 1
A20: APP-17 | B20: 製造 | C20: 工程データ管理 | D20: プロセスヒストリアン | E20: バイオリアクター等の運転・監視データを収集・保存する | F20: GMP | G20: =COUNTIF('ケイパビリティ×アプリケーション'!T$6:T$58,"●") -> 1 | H20: =COUNTIF('ケイパビリティ×アプリケーション'!T$6:T$58,"○") -> 2
A21: APP-18 | B21: 製造 | C21: 設備・環境管理 | D21: CMMS／環境モニタリング | E21: 設備の保全・校正と、無菌環境のモニタリングを管理する | F21: GMP | G21: =COUNTIF('ケイパビリティ×アプリケーション'!U$6:U$58,"●") -> 1 | H21: =COUNTIF('ケイパビリティ×アプリケーション'!U$6:U$58,"○") -> 1
A22: APP-19 | B22: 製造 | C22: ラベル・アートワーク管理 | D22: アートワーク管理 | E22: 治験薬・商用製品のラベルと包装デザインの作成・承認・版を管理する | F22: GMP・GCP | G22: =COUNTIF('ケイパビリティ×アプリケーション'!V$6:V$58,"●") -> 1 | H22: =COUNTIF('ケイパビリティ×アプリケーション'!V$6:V$58,"○") -> 1
A23: APP-20 | B23: 品質 | C23: 品質マネジメントシステム | D23: eQMS | E23: 逸脱・CAPA・変更管理・監査・苦情・回収・供給者管理を管理する | F23: GMP・GCP・GLP | G23: =COUNTIF('ケイパビリティ×アプリケーション'!W$6:W$58,"●") -> 3 | H23: =COUNTIF('ケイパビリティ×アプリケーション'!W$6:W$58,"○") -> 2
A24: APP-21 | B24: 品質 | C24: バリデーション管理 | D24: バリデーションライフサイクル管理 | E24: 設備・プロセス・洗浄・コンピュータ化システムのバリデーションの計画・実行・記録を電子的に行う | F24: GMP | G24: =COUNTIF('ケイパビリティ×アプリケーション'!X$6:X$58,"●") -> 1 | H24: =COUNTIF('ケイパビリティ×アプリケーション'!X$6:X$58,"○") -> 0
A25: APP-22 | B25: 品質 | C25: 試験室情報管理 | D25: LIMS | E25: 検体・試験・結果・規格判定・安定性試験を管理する（生体試料分析、品質管理試験） | F25: GMP・GLP・GCP | G25: =COUNTIF('ケイパビリティ×アプリケーション'!Y$6:Y$58,"●") -> 3 | H25: =COUNTIF('ケイパビリティ×アプリケーション'!Y$6:Y$58,"○") -> 2
A26: APP-23 | B26: 供給 | C26: 需給計画 | D26: APS／S&OP | E26: 需要予測・供給計画・在庫計画を立てる | F26: 非GxP | G26: =COUNTIF('ケイパビリティ×アプリケーション'!Z$6:Z$58,"●") -> 1 | H26: =COUNTIF('ケイパビリティ×アプリケーション'!Z$6:Z$58,"○") -> 2
A27: APP-24 | B27: 供給 | C27: 倉庫・物流管理 | D27: WMS／TMS（温度監視含む） | E27: 保管・輸送と、輸送中の温度データを管理する | F27: GMP・流通 | G27: =COUNTIF('ケイパビリティ×アプリケーション'!AA$6:AA$58,"●") -> 1 | H27: =COUNTIF('ケイパビリティ×アプリケーション'!AA$6:AA$58,"○") -> 0
A28: APP-25 | B28: 供給 | C28: シリアライゼーション | D28: DSCSA対応システム | E28: 製品識別子の付番と、取引情報の電子的な記録・交換を行う | F28: 流通 | G28: =COUNTIF('ケイパビリティ×アプリケーション'!AB$6:AB$58,"●") -> 1 | H28: =COUNTIF('ケイパビリティ×アプリケーション'!AB$6:AB$58,"○") -> 2
A29: APP-26 | B29: 商業 | C29: 顧客関係管理 | D29: CRM | E29: 医療機関・医療従事者・患者団体との関係と、MSL・営業の活動を管理する | F29: 非GxP | G29: =COUNTIF('ケイパビリティ×アプリケーション'!AC$6:AC$58,"●") -> 4 | H29: =COUNTIF('ケイパビリティ×アプリケーション'!AC$6:AC$58,"○") -> 2
A30: APP-27 | B30: 商業 | C30: 患者支援（ハブ） | D30: ハブサービスシステム | E30: 患者の登録・保険確認・自己負担支援・治療開始を管理する | F30: 非GxP | G30: =COUNTIF('ケイパビリティ×アプリケーション'!AD$6:AD$58,"●") -> 1 | H30: =COUNTIF('ケイパビリティ×アプリケーション'!AD$6:AD$58,"○") -> 0
A31: APP-28 | B31: 商業 | C31: 価格・契約・政府価格報告 | D31: GTN／リベート管理 | E31: 価格、保険者契約、リベート、政府価格報告（AMP・Best Price・ASP）を管理する | F31: 非GxP | G31: =COUNTIF('ケイパビリティ×アプリケーション'!AE$6:AE$58,"●") -> 2 | H31: =COUNTIF('ケイパビリティ×アプリケーション'!AE$6:AE$58,"○") -> 1
A32: APP-29 | B32: 商業 | C32: 販促資材審査 | D32: MLRレビュー | E32: 販促・医療情報資材の医学・法務・薬事の審査と承認、FDAへの提出を管理する | F32: 薬事 | G32: =COUNTIF('ケイパビリティ×アプリケーション'!AF$6:AF$58,"●") -> 1 | H32: =COUNTIF('ケイパビリティ×アプリケーション'!AF$6:AF$58,"○") -> 2
A33: APP-30 | B33: 共通 | C33: ERP | D33: ERP | E33: 財務・購買・在庫・受注・出荷を一元管理する基幹システム | F33: GMP・流通 | G33: =COUNTIF('ケイパビリティ×アプリケーション'!AG$6:AG$58,"●") -> 3 | H33: =COUNTIF('ケイパビリティ×アプリケーション'!AG$6:AG$58,"○") -> 4
A34: APP-31 | B34: 共通 | C34: マスタデータ管理 | D34: MDM | E34: 製品・取引先・医療機関などのマスタを統合し、段階をまたぐ一貫した識別子を管理する | F34: 非GxP | G34: =COUNTIF('ケイパビリティ×アプリケーション'!AH$6:AH$58,"●") -> 1 | H34: =COUNTIF('ケイパビリティ×アプリケーション'!AH$6:AH$58,"○") -> 3
A35: APP-32 | B35: 共通 | C35: GxP文書管理 | D35: eDMS | E35: SOP・報告書・申請用文書を版管理し、承認と電子署名を行う | F35: GxP全般 | G35: =COUNTIF('ケイパビリティ×アプリケーション'!AI$6:AI$58,"●") -> 3 | H35: =COUNTIF('ケイパビリティ×アプリケーション'!AI$6:AI$58,"○") -> 5
A36: APP-33 | B36: 共通 | C36: 教育管理 | D36: LMS | E36: 教育の計画・実施・記録と、資格認定を管理する | F36: GxP全般 | G36: =COUNTIF('ケイパビリティ×アプリケーション'!AJ$6:AJ$58,"●") -> 1 | H36: =COUNTIF('ケイパビリティ×アプリケーション'!AJ$6:AJ$58,"○") -> 1
A37: APP-34 | B37: 共通 | C37: データ・分析基盤 | D37: データレイク／DWH／BI | E37: 領域をまたいでデータを集約し、分析・可視化・AI活用に使う | F37: 非GxP | G37: =COUNTIF('ケイパビリティ×アプリケーション'!AK$6:AK$58,"●") -> 1 | H37: =COUNTIF('ケイパビリティ×アプリケーション'!AK$6:AK$58,"○") -> 3
A38: APP-35 | B38: 共通 | C38: ポートフォリオ・プロジェクト管理 | D38: PPM | E38: 開発品のポートフォリオ、開発計画、資源配分、段階移行の判断を管理する | F38: 非GxP | G38: =COUNTIF('ケイパビリティ×アプリケーション'!AL$6:AL$58,"●") -> 1 | H38: =COUNTIF('ケイパビリティ×アプリケーション'!AL$6:AL$58,"○") -> 0
A39: APP-36 | B39: 共通 | C39: 契約管理 | D39: CLM | E39: CRO・CDMO・医療機関・流通業者などとの契約の作成・承認・履行を管理する | F39: 非GxP | G39: =COUNTIF('ケイパビリティ×アプリケーション'!AM$6:AM$58,"●") -> 1 | H39: =COUNTIF('ケイパビリティ×アプリケーション'!AM$6:AM$58,"○") -> 1
A40: APP-37 | B40: 共通 | C40: 知財管理 | D40: IPMS | E40: 特許の出願・権利化・期限と、独占期間を管理する | F40: 非GxP | G40: =COUNTIF('ケイパビリティ×アプリケーション'!AN$6:AN$58,"●") -> 1 | H40: =COUNTIF('ケイパビリティ×アプリケーション'!AN$6:AN$58,"○") -> 0

Sheet 製品一覧
A1: 製品一覧（正本：製品の単位）
A2: 1行1製品。technology/veeva-data-system の資料から読み取れる製品（Veeva製品は公式サイト2026年10月時点の名称・区分）。日本での提供の「—」は未確認。灰色の列は数式（編集しない）。アプリケーション種類との対応は「アプリケーション×製品」シートで記入する。出典：https://www.veeva.com/products/
A3: ID | B3: 提供元 | C3: 分類 | D3: 製品名 | E3: 旧名称・別名 | F3: 主な機能 | G3: 日本での提供 | H3: 資料の章 | I3: 主に対応する アプリケーション数 | J3: 部分的に対応する アプリケーション数
A4: PRD-01 | B4: Veeva | C4: 臨床 | D4: Veeva CTMS | E4: Vault CTMS | F4: 治験の試験・施設・被験者登録・モニタリング訪問の進捗を管理する | G4: — | H4: 02 | I4: =COUNTIF('アプリケーション×製品'!D$6:D$42,"●") -> 1 | J4: =COUNTIF('アプリケーション×製品'!D$6:D$42,"○") -> 0
A5: PRD-02 | B5: Veeva | C5: 臨床 | D5: Veeva eTMF | E5: Vault eTMF | F5: 治験の必須文書（TMF）を電子的に管理し、査察に対応する | G5: — | H5: 02 | I5: =COUNTIF('アプリケーション×製品'!E$6:E$42,"●") -> 1 | J5: =COUNTIF('アプリケーション×製品'!E$6:E$42,"○") -> 0
A6: PRD-03 | B6: Veeva | C6: 臨床 | D6: Veeva Study Startup | E6: Vault Study Startup | F6: 施設選定・契約・IRB・必須文書の収集により治験施設を立ち上げる | G6: — | H6: 02 | I6: =COUNTIF('アプリケーション×製品'!F$6:F$42,"●") -> 0 | J6: =COUNTIF('アプリケーション×製品'!F$6:F$42,"○") -> 3
A7: PRD-04 | B7: Veeva | C7: 臨床 | D7: Veeva Payments | F7: 治験施設への支払いを管理する | G7: — | H7: 02 | I7: =COUNTIF('アプリケーション×製品'!G$6:G$42,"●") -> 0 | J7: =COUNTIF('アプリケーション×製品'!G$6:G$42,"○") -> 1
A8: PRD-05 | B8: Veeva | C8: 臨床 | D8: Veeva Site Connect | F8: 依頼者と治験施設の間の文書・情報のやり取りを自動化する | G8: — | H8: 02 | I8: =COUNTIF('アプリケーション×製品'!H$6:H$42,"●") -> 0 | J8: =COUNTIF('アプリケーション×製品'!H$6:H$42,"○") -> 2
A9: PRD-06 | B9: Veeva | C9: 臨床 | D9: Veeva Study Training | F9: 治験責任医師・施設スタッフのトレーニングを管理する | G9: — | H9: 02 | I9: =COUNTIF('アプリケーション×製品'!I$6:I$42,"●") -> 0 | J9: =COUNTIF('アプリケーション×製品'!I$6:I$42,"○") -> 1
A10: PRD-07 | B10: Veeva | C10: 臨床 | D10: Veeva Disclosures | F10: 治験情報の公開（レジストリ登録・結果公開）を管理する | G10: — | H10: 02 | I10: =COUNTIF('アプリケーション×製品'!J$6:J$42,"●") -> 0 | J10: =COUNTIF('アプリケーション×製品'!J$6:J$42,"○") -> 1
A11: PRD-08 | B11: Veeva | C11: 臨床 | D11: Veeva OpenData Clinical | F11: 治験責任医師・施設のリファレンスデータ | G11: — | H11: 02, 05 | I11: =COUNTIF('アプリケーション×製品'!K$6:K$42,"●") -> 0 | J11: =COUNTIF('アプリケーション×製品'!K$6:K$42,"○") -> 1
A12: PRD-09 | B12: Veeva | C12: 臨床 | D12: Veeva EDC | E12: Vault EDC | F12: 症例データを電子的に収集・検証する | G12: — | H12: 02 | I12: =COUNTIF('アプリケーション×製品'!L$6:L$42,"●") -> 1 | J12: =COUNTIF('アプリケーション×製品'!L$6:L$42,"○") -> 0
A13: PRD-10 | B13: Veeva | C13: 臨床 | D13: Veeva DQS | F13: 試験データを集約し、クリーニングする | G13: — | H13: 02 | I13: =COUNTIF('アプリケーション×製品'!M$6:M$42,"●") -> 0 | J13: =COUNTIF('アプリケーション×製品'!M$6:M$42,"○") -> 2
A14: PRD-11 | B14: Veeva | C14: 臨床 | D14: Veeva eCOA | F14: 患者報告アウトカム等を電子的に収集する | G14: — | H14: 02 | I14: =COUNTIF('アプリケーション×製品'!N$6:N$42,"●") -> 1 | J14: =COUNTIF('アプリケーション×製品'!N$6:N$42,"○") -> 0
A15: PRD-12 | B15: Veeva | C15: 臨床 | D15: Veeva RTSM | F15: 無作為化割付と治験薬供給を管理する | G15: — | H15: 02 | I15: =COUNTIF('アプリケーション×製品'!O$6:O$42,"●") -> 1 | J15: =COUNTIF('アプリケーション×製品'!O$6:O$42,"○") -> 0
A16: PRD-13 | B16: Veeva | C16: 薬事 | D16: Veeva Registrations | E16: Vault RIM Registrations | F16: 製品×国ごとの承認状況、当局とのやり取り・コミットメントを管理する | G16: — | H16: 02 | I16: =COUNTIF('アプリケーション×製品'!P$6:P$42,"●") -> 1 | J16: =COUNTIF('アプリケーション×製品'!P$6:P$42,"○") -> 0
A17: PRD-14 | B17: Veeva | C17: 薬事 | D17: Veeva Submissions | E17: Vault Submissions | F17: 申請コンテンツ（CTD）の計画・収集・レビュー・承認を行う | G17: — | H17: 02 | I17: =COUNTIF('アプリケーション×製品'!Q$6:Q$42,"●") -> 0 | J17: =COUNTIF('アプリケーション×製品'!Q$6:Q$42,"○") -> 3
A18: PRD-15 | B18: Veeva | C18: 薬事 | D18: Veeva Submissions Publishing | E18: Vault Submissions Publishing | F18: 申請資料をeCTD形式に組み上げ、当局へ電子提出する | G18: — | H18: 02 | I18: =COUNTIF('アプリケーション×製品'!R$6:R$42,"●") -> 1 | J18: =COUNTIF('アプリケーション×製品'!R$6:R$42,"○") -> 0
A19: PRD-16 | B19: Veeva | C19: 薬事 | D19: Veeva Submissions Archive | E19: Vault Submissions Archive | F19: 過去の申請物・当局との往復文書を保管・参照する | G19: — | H19: 02 | I19: =COUNTIF('アプリケーション×製品'!S$6:S$42,"●") -> 0 | J19: =COUNTIF('アプリケーション×製品'!S$6:S$42,"○") -> 2
A20: PRD-17 | B20: Veeva | C20: 安全性 | D20: Veeva Safety | E20: Vault Safety | F20: 有害事象の受付・症例登録・評価・ICSR作成・当局への電子送信を行う | G20: — | H20: 02 | I20: =COUNTIF('アプリケーション×製品'!T$6:T$42,"●") -> 1 | J20: =COUNTIF('アプリケーション×製品'!T$6:T$42,"○") -> 0
A21: PRD-18 | B21: Veeva | C21: 安全性 | D21: Veeva SafetyDocs | E21: Vault SafetyDocs | F21: PSMF・RMP・PSUR等の安全性文書を作成・レビュー・保管する | G21: — | H21: 02 | I21: =COUNTIF('アプリケーション×製品'!U$6:U$42,"●") -> 0 | J21: =COUNTIF('アプリケーション×製品'!U$6:U$42,"○") -> 2
A22: PRD-19 | B22: Veeva | C22: 安全性 | D22: Veeva Safety Workbench | F22: 安全性データを集計・分析し、定期報告の作成を支援する | G22: — | H22: 02 | I22: =COUNTIF('アプリケーション×製品'!V$6:V$42,"●") -> 0 | J22: =COUNTIF('アプリケーション×製品'!V$6:V$42,"○") -> 2
A23: PRD-20 | B23: Veeva | C23: 安全性 | D23: Veeva Safety Signal | F23: 安全性シグナルを検出・評価・追跡する | G23: — | H23: 02 | I23: =COUNTIF('アプリケーション×製品'!W$6:W$42,"●") -> 1 | J23: =COUNTIF('アプリケーション×製品'!W$6:W$42,"○") -> 0
A24: PRD-21 | B24: Veeva | C24: 品質 | D24: Veeva QMS | E24: Vault QMS | F24: 逸脱・CAPA・変更管理・苦情・監査・サプライヤー品質を管理する | G24: — | H24: 02 | I24: =COUNTIF('アプリケーション×製品'!X$6:X$42,"●") -> 1 | J24: =COUNTIF('アプリケーション×製品'!X$6:X$42,"○") -> 0
A25: PRD-22 | B25: Veeva | C25: 品質 | D25: Veeva QualityDocs | E25: Vault QualityDocs | F25: SOP・手順書などGxP文書のライフサイクルを管理する | G25: — | H25: 02 | I25: =COUNTIF('アプリケーション×製品'!Y$6:Y$42,"●") -> 1 | J25: =COUNTIF('アプリケーション×製品'!Y$6:Y$42,"○") -> 0
A26: PRD-23 | B26: Veeva | C26: 品質 | D26: Veeva Training | E26: Vault Training | F26: ロール別の教育・資格を管理する | G26: — | H26: 02 | I26: =COUNTIF('アプリケーション×製品'!Z$6:Z$42,"●") -> 1 | J26: =COUNTIF('アプリケーション×製品'!Z$6:Z$42,"○") -> 0
A27: PRD-24 | B27: Veeva | C27: 品質 | D27: Veeva Validation Management | E27: Vault Validation Management | F27: バリデーションをペーパーレスで計画・実行・記録する | G27: — | H27: 02 | I27: =COUNTIF('アプリケーション×製品'!AA$6:AA$42,"●") -> 1 | J27: =COUNTIF('アプリケーション×製品'!AA$6:AA$42,"○") -> 0
A28: PRD-25 | B28: Veeva | C28: 品質 | D28: Veeva Batch Release | F28: 出荷判定に必要な情報を集約し、判定を迅速化する | G28: — | H28: 02 | I28: =COUNTIF('アプリケーション×製品'!AB$6:AB$42,"●") -> 0 | J28: =COUNTIF('アプリケーション×製品'!AB$6:AB$42,"○") -> 2
A29: PRD-26 | B29: Veeva | C29: 品質 | D29: Veeva LIMS | E29: Vault LIMS | F29: 品質管理試験室の検体・試験・結果・安定性試験を管理する | G29: — | H29: 02 | I29: =COUNTIF('アプリケーション×製品'!AC$6:AC$42,"●") -> 1 | J29: =COUNTIF('アプリケーション×製品'!AC$6:AC$42,"○") -> 0
A30: PRD-27 | B30: Veeva | C30: 品質 | D30: Veeva Station Manager | F30: 製造現場の端末に最新版の文書を配信する | G30: — | H30: 02 | I30: =COUNTIF('アプリケーション×製品'!AD$6:AD$42,"●") -> 0 | J30: =COUNTIF('アプリケーション×製品'!AD$6:AD$42,"○") -> 2
A31: PRD-28 | B31: Veeva | C31: 品質 | D31: Veeva Product Surveillance | F31: 医療機器の市販後調査（不具合・苦情）を管理する | G31: — | H31: 02 | I31: =COUNTIF('アプリケーション×製品'!AE$6:AE$42,"●") -> 0 | J31: =COUNTIF('アプリケーション×製品'!AE$6:AE$42,"○") -> 1
A32: PRD-29 | B32: Veeva | C32: 品質 | D32: Veeva EHS | F32: 環境・安全衛生プロセスを管理する | G32: — | H32: 02 | I32: =COUNTIF('アプリケーション×製品'!AF$6:AF$42,"●") -> 0 | J32: =COUNTIF('アプリケーション×製品'!AF$6:AF$42,"○") -> 0
A33: PRD-30 | B33: Veeva | C33: 治験施設 | D33: SiteVault | E33: SiteVault CTMS / eISF / eConsent | F33: 医療機関側の治験管理・電子ISF・電子同意 | G33: — | H33: 02 | I33: =COUNTIF('アプリケーション×製品'!AG$6:AG$42,"●") -> 0 | J33: =COUNTIF('アプリケーション×製品'!AG$6:AG$42,"○") -> 2
A34: PRD-31 | B34: Veeva | C34: 治験施設 | D34: Veeva eSource | F34: 医療機関での治験データ収集とEDCへの連携 | G34: — | H34: 02 | I34: =COUNTIF('アプリケーション×製品'!AH$6:AH$42,"●") -> 0 | J34: =COUNTIF('アプリケーション×製品'!AH$6:AH$42,"○") -> 1
A35: PRD-32 | B35: Veeva | C35: メディカル | D35: Medical CRM | E35: Vault CRM（メディカル機能） | F35: MSLのKOL交流の計画・記録、インサイト入力 | G35: — | H35: 03 | I35: =COUNTIF('アプリケーション×製品'!AI$6:AI$42,"●") -> 1 | J35: =COUNTIF('アプリケーション×製品'!AI$6:AI$42,"○") -> 0
A36: PRD-33 | B36: Veeva | C36: メディカル | D36: Veeva MedInquiry | E36: Vault MedInquiry | F36: 医療関係者からの問い合わせの受付・回答・追跡 | G36: — | H36: 03 | I36: =COUNTIF('アプリケーション×製品'!AJ$6:AJ$42,"●") -> 0 | J36: =COUNTIF('アプリケーション×製品'!AJ$6:AJ$42,"○") -> 1
A37: PRD-34 | B37: Veeva | C37: メディカル | D37: Veeva MedComms | E37: Vault MedComms | F37: メディカルコンテンツ（標準回答文書・学術資料）の作成・承認・配信 | G37: — | H37: 03 | I37: =COUNTIF('アプリケーション×製品'!AK$6:AK$42,"●") -> 1 | J37: =COUNTIF('アプリケーション×製品'!AK$6:AK$42,"○") -> 0
A38: PRD-35 | B38: Veeva | C38: メディカル | D38: Veeva Publications | F38: 論文・学会発表の計画・執筆・管理 | G38: — | H38: 03 | I38: =COUNTIF('アプリケーション×製品'!AL$6:AL$42,"●") -> 0 | J38: =COUNTIF('アプリケーション×製品'!AL$6:AL$42,"○") -> 0
A39: PRD-36 | B39: Veeva | C39: メディカル | D39: Veeva Link Key People | F39: KOLの詳細データ（研究・発表・ネットワーク） | G39: — | H39: 03 | I39: =COUNTIF('アプリケーション×製品'!AM$6:AM$42,"●") -> 0 | J39: =COUNTIF('アプリケーション×製品'!AM$6:AM$42,"○") -> 2
A40: PRD-37 | B40: Veeva | C40: メディカル | D40: Veeva Link Workflow | F40: KOLエンゲージメント・学会対応の計画 | G40: — | H40: 03 | I40: =COUNTIF('アプリケーション×製品'!AN$6:AN$42,"●") -> 0 | J40: =COUNTIF('アプリケーション×製品'!AN$6:AN$42,"○") -> 1
A41: PRD-38 | B41: Veeva | C41: メディカル | D41: Veeva Link Medical Insights | E41: Veeva Medical Insights | F41: MSLの現場インサイトを収集し、AIでテーマ化して社内共有する | G41: — | H41: 03 | I41: =COUNTIF('アプリケーション×製品'!AO$6:AO$42,"●") -> 0 | J41: =COUNTIF('アプリケーション×製品'!AO$6:AO$42,"○") -> 2
A42: PRD-39 | B42: Veeva | C42: 営業・マーケティング | D42: Vault CRM | E42: Veeva CRM（旧Salesforce基盤版の後継） | F42: HCP/HCO管理・活動計画・面談記録・サンプリング。CLM・Approved Email・Engageを含む | G42: 提供あり | H42: 04 | I42: =COUNTIF('アプリケーション×製品'!AP$6:AP$42,"●") -> 1 | J42: =COUNTIF('アプリケーション×製品'!AP$6:AP$42,"○") -> 0
A43: PRD-40 | B43: Veeva | C43: 営業・マーケティング | D43: Campaign Manager | F43: 対面と非対面を統合したキャンペーンの設計・実行 | G43: 提供あり | H43: 04 | I43: =COUNTIF('アプリケーション×製品'!AQ$6:AQ$42,"●") -> 0 | J43: =COUNTIF('アプリケーション×製品'!AQ$6:AQ$42,"○") -> 1
A44: PRD-41 | B44: Veeva | C44: 営業・マーケティング | D44: Events Management | F44: 講演会・学術イベントの企画・招待・参加・コンプライアンス管理 | G44: 提供あり | H44: 04 | I44: =COUNTIF('アプリケーション×製品'!AR$6:AR$42,"●") -> 0 | J44: =COUNTIF('アプリケーション×製品'!AR$6:AR$42,"○") -> 1
A45: PRD-42 | B45: Veeva | C45: 営業・マーケティング | D45: Service Center | F45: インバウンド／アウトバウンドのリモート対応 | G45: 提供あり | H45: 04 | I45: =COUNTIF('アプリケーション×製品'!AS$6:AS$42,"●") -> 0 | J45: =COUNTIF('アプリケーション×製品'!AS$6:AS$42,"○") -> 1
A46: PRD-43 | B46: Veeva | C46: 営業・マーケティング | D46: Align / Align+ | F46: テリトリー設計、担当者割当、エンゲージメント計画 | G46: 提供あり | H46: 04 | I46: =COUNTIF('アプリケーション×製品'!AT$6:AT$42,"●") -> 0 | J46: =COUNTIF('アプリケーション×製品'!AT$6:AT$42,"○") -> 1
A47: PRD-44 | B47: Veeva | C47: 営業・マーケティング | D47: Patient CRM | F47: 患者支援プログラムの管理 | G47: — | H47: 04 | I47: =COUNTIF('アプリケーション×製品'!AU$6:AU$42,"●") -> 1 | J47: =COUNTIF('アプリケーション×製品'!AU$6:AU$42,"○") -> 0
A48: PRD-45 | B48: Veeva | C48: 営業・マーケティング | D48: Ostro | F48: 患者・医療従事者の質問にAIが即時回答する | G48: — | H48: 04 | I48: =COUNTIF('アプリケーション×製品'!AV$6:AV$42,"●") -> 0 | J48: =COUNTIF('アプリケーション×製品'!AV$6:AV$42,"○") -> 1
A49: PRD-46 | B49: Veeva | C49: 営業・マーケティング | D49: Veeva PromoMats | E49: Vault PromoMats | F49: 販促資料のMLRレビュー・承認・配信・失効を管理する | G49: — | H49: 04 | I49: =COUNTIF('アプリケーション×製品'!AW$6:AW$42,"●") -> 1 | J49: =COUNTIF('アプリケーション×製品'!AW$6:AW$42,"○") -> 0
A50: PRD-47 | B50: Veeva | C50: 営業・マーケティング | D50: Veeva Nitro | F50: CRM活動データと外部データを統合するコマーシャルデータウェアハウス | G50: 提供あり（導入事例） | H50: 05 | I50: =COUNTIF('アプリケーション×製品'!AX$6:AX$42,"●") -> 1 | J50: =COUNTIF('アプリケーション×製品'!AX$6:AX$42,"○") -> 0
A51: PRD-48 | B51: Veeva | C51: 営業・マーケティング | D51: Marketing Analytics | F51: キャンペーン効果測定・顧客インサイト | G51: — | H51: 05 | I51: =COUNTIF('アプリケーション×製品'!AY$6:AY$42,"●") -> 0 | J51: =COUNTIF('アプリケーション×製品'!AY$6:AY$42,"○") -> 1
A52: PRD-49 | B52: Veeva | C52: データ | D52: Veeva Network | E52: Network MDM | F52: HCP/HCOの顧客マスタデータを統合・重複排除・配信する | G52: 提供あり | H52: 05 | I52: =COUNTIF('アプリケーション×製品'!AZ$6:AZ$42,"●") -> 1 | J52: =COUNTIF('アプリケーション×製品'!AZ$6:AZ$42,"○") -> 0
A53: PRD-50 | B53: Veeva | C53: データ | D53: Veeva OpenData Commercial | E53: Veeva OpenData | F53: Veevaが整備するHCP/HCOのリファレンスデータ | G53: なし（Ultmarcで代替） | H53: 05 | I53: =COUNTIF('アプリケーション×製品'!BA$6:BA$42,"●") -> 0 | J53: =COUNTIF('アプリケーション×製品'!BA$6:BA$42,"○") -> 1
A54: PRD-51 | B54: Veeva | C54: データ | D54: Veeva HCP Access | F54: 医療従事者への業界横断アクセス指標 | G54: 提供あり | H54: 05 | I54: =COUNTIF('アプリケーション×製品'!BB$6:BB$42,"●") -> 0 | J54: =COUNTIF('アプリケーション×製品'!BB$6:BB$42,"○") -> 1
A55: PRD-52 | B55: Veeva | C55: データ | D55: Veeva Link Key Accounts | F55: 主要アカウントと意思決定者のデータ | G55: 米国向け | H55: 05 | I55: =COUNTIF('アプリケーション×製品'!BC$6:BC$42,"●") -> 0 | J55: =COUNTIF('アプリケーション×製品'!BC$6:BC$42,"○") -> 2
A56: PRD-53 | B56: Veeva | C56: データ | D56: Veeva Compass | E56: Compass Patient / Prescriber / National | F56: 匿名化患者データ・処方データ | G56: 米国中心 | H56: 05 | I56: =COUNTIF('アプリケーション×製品'!BD$6:BD$42,"●") -> 0 | J56: =COUNTIF('アプリケーション×製品'!BD$6:BD$42,"○") -> 2
A57: PRD-54 | B57: Veeva | C57: AI・基盤 | D57: Vault Platform | F57: 全アプリケーションの共通クラウド基盤 | G57: — | H57: 00, 06 | I57: =COUNTIF('アプリケーション×製品'!BE$6:BE$42,"●") -> 0 | J57: =COUNTIF('アプリケーション×製品'!BE$6:BE$42,"○") -> 0
A58: PRD-55 | B58: Veeva | C58: AI・基盤 | D58: Veeva Connections | E58: Connections Hub | F58: Veevaアプリ間・外部との製品化された連携 | G58: — | H58: 06 | I58: =COUNTIF('アプリケーション×製品'!BF$6:BF$42,"●") -> 0 | J58: =COUNTIF('アプリケーション×製品'!BF$6:BF$42,"○") -> 0
A59: PRD-56 | B59: Veeva | C59: AI・基盤 | D59: Vault AI | E59: Veeva AI | F59: 各アプリに組み込まれたAIエージェント（CRM・PromoMats・Safety・Quality等） | G59: — | H59: 06 | I59: =COUNTIF('アプリケーション×製品'!BG$6:BG$42,"●") -> 0 | J59: =COUNTIF('アプリケーション×製品'!BG$6:BG$42,"○") -> 0
A60: PRD-57 | B60: Veeva | C60: AI・基盤 | D60: Falcon Clinical | E60: Veeva Falcon | F60: 治験データの受付・品質チェックを自動化するエージェント | G60: — | H60: 06 | I60: =COUNTIF('アプリケーション×製品'!BH$6:BH$42,"●") -> 0 | J60: =COUNTIF('アプリケーション×製品'!BH$6:BH$42,"○") -> 1
A61: PRD-58 | B61: Veeva | C61: AI・基盤 | D61: Falcon Regulatory | E61: Veeva Falcon | F61: 申請文書作成・当局対応を行うエージェント | G61: — | H61: 06 | I61: =COUNTIF('アプリケーション×製品'!BI$6:BI$42,"●") -> 0 | J61: =COUNTIF('アプリケーション×製品'!BI$6:BI$42,"○") -> 2
A62: PRD-59 | B62: Veeva | C62: AI・基盤 | D62: Falcon Safety | E62: Veeva Falcon | F62: 症例受付・トリアージを自動化するエージェント | G62: — | H62: 06 | I62: =COUNTIF('アプリケーション×製品'!BJ$6:BJ$42,"●") -> 0 | J62: =COUNTIF('アプリケーション×製品'!BJ$6:BJ$42,"○") -> 1
A63: PRD-60 | B63: Veeva | C63: AI・基盤 | D63: Falcon MLR | E63: Veeva Falcon | F63: 販促資料の審査を自動化するエージェント | G63: — | H63: 04, 06 | I63: =COUNTIF('アプリケーション×製品'!BK$6:BK$42,"●") -> 0 | J63: =COUNTIF('アプリケーション×製品'!BK$6:BK$42,"○") -> 1
A64: PRD-61 | B64: Veeva | C64: AI・基盤 | D64: Veeva Basics | F64: 新興バイオ企業向けのパッケージ | G64: — | H64: 00 | I64: =COUNTIF('アプリケーション×製品'!BL$6:BL$42,"●") -> 0 | J64: =COUNTIF('アプリケーション×製品'!BL$6:BL$42,"○") -> 0
A65: PRD-62 | B65: Veeva | C65: 旧製品 | D65: Veeva CRM（Salesforce基盤） | F65: Vault CRMの前身。サポート終了は2029年12月31日 | G65: 提供あり（移行中） | H65: 00, C | I65: =COUNTIF('アプリケーション×製品'!BM$6:BM$42,"●") -> 1 | J65: =COUNTIF('アプリケーション×製品'!BM$6:BM$42,"○") -> 0
A66: PRD-63 | B66: Ultmarc | C66: データ | D66: Ultmarc MDB | E66: DCF・DSF・PCF | F66: 日本の医療施設・医師・薬局・病院薬剤師のマスタファイル（業界共同メンテナンス） | G66: 日本のみ | H66: 05, B | I66: =COUNTIF('アプリケーション×製品'!BN$6:BN$42,"●") -> 0 | J66: =COUNTIF('アプリケーション×製品'!BN$6:BN$42,"○") -> 1
A67: PRD-64 | B67: Salesforce | C67: 競合 | D67: Salesforce Life Sciences Cloud | F67: ライフサイエンス向けCRM・患者支援 | G67: — | H67: C | I67: =COUNTIF('アプリケーション×製品'!BO$6:BO$42,"●") -> 1 | J67: =COUNTIF('アプリケーション×製品'!BO$6:BO$42,"○") -> 1
A68: PRD-65 | B68: Salesforce | C68: 競合 | D68: Agentforce Life Sciences | F68: HCPスケジューリング等を行うAIエージェント | G68: — | H68: C | I68: =COUNTIF('アプリケーション×製品'!BP$6:BP$42,"●") -> 0 | J68: =COUNTIF('アプリケーション×製品'!BP$6:BP$42,"○") -> 1
A69: PRD-66 | B69: Salesforce | C69: 競合 | D69: Salesforce Data Cloud | F69: 外部データ（IQVIA・EMR・患者データ等）の統合 | G69: — | H69: C | I69: =COUNTIF('アプリケーション×製品'!BQ$6:BQ$42,"●") -> 0 | J69: =COUNTIF('アプリケーション×製品'!BQ$6:BQ$42,"○") -> 2
A70: PRD-67 | B70: MasterControl | C70: 代替製品 | D70: MasterControl | F70: 品質マネジメント・文書管理 | G70: — | H70: D | I70: =COUNTIF('アプリケーション×製品'!BR$6:BR$42,"●") -> 2 | J70: =COUNTIF('アプリケーション×製品'!BR$6:BR$42,"○") -> 0
A71: PRD-68 | B71: OpenText | C71: 代替製品 | D71: Documentum | F71: 文書管理 | G71: — | H71: D | I71: =COUNTIF('アプリケーション×製品'!BS$6:BS$42,"●") -> 1 | J71: =COUNTIF('アプリケーション×製品'!BS$6:BS$42,"○") -> 0
A72: PRD-69 | B72: EXTEDO | C72: 代替製品 | D72: EXTEDO | F72: eCTD申請に特化した薬事システム | G72: — | H72: D | I72: =COUNTIF('アプリケーション×製品'!BT$6:BT$42,"●") -> 1 | J72: =COUNTIF('アプリケーション×製品'!BT$6:BT$42,"○") -> 1
A73: PRD-70 | B73: Oracle | C73: 代替製品 | D73: Oracle Argus | F73: 安全性データベース | G73: — | H73: D | I73: =COUNTIF('アプリケーション×製品'!BU$6:BU$42,"●") -> 1 | J73: =COUNTIF('アプリケーション×製品'!BU$6:BU$42,"○") -> 0
A74: PRD-71 | B74: ArisGlobal | C74: 代替製品 | D74: ARISg | F74: 安全性データベース | G74: — | H74: D | I74: =COUNTIF('アプリケーション×製品'!BV$6:BV$42,"●") -> 1 | J74: =COUNTIF('アプリケーション×製品'!BV$6:BV$42,"○") -> 0
A75: PRD-72 | B75: Medidata | C75: 代替製品 | D75: Medidata | F75: 臨床試験の製品群（EDC等） | G75: — | H75: D | I75: =COUNTIF('アプリケーション×製品'!BW$6:BW$42,"●") -> 1 | J75: =COUNTIF('アプリケーション×製品'!BW$6:BW$42,"○") -> 1

Sheet ケイパビリティ×アプリケーション
A1: ケイパビリティ×アプリケーション（正本：行＝ケイパビリティL2 × 列＝アプリケーション種類）
A2: ●＝主に支える（その能力の中核の業務を実行するシステム） ○＝部分的に支える（一部の業務やデータの受け渡しで使う） 空欄＝関係なし。このシートに直接記入する。右端と最下行の数は数式。
A4: ケイパビリティL1 | B4: L2 ID | C4: ケイパビリティL2 | D4: 研究 | G4: 非臨床 | H4: 臨床 | O4: 薬事 | Q4: 安全性 | S4: 製造 | W4: 品質 | Z4: 供給 | AC4: 商業 | AG4: 共通 | AO4: ●の数 | AP4: ○の数
D5: ='アプリケーション'!C4 -> 電子実験ノート | E5: ='アプリケーション'!C5 -> 生物学的物質登録 | F5: ='アプリケーション'!C6 -> 科学データ解析基盤 | G5: ='アプリケーション'!C7 -> 非臨床試験管理 | H5: ='アプリケーション'!C8 -> PK/PD解析・モデリング | I5: ='アプリケーション'!C9 -> 臨床試験管理 | J5: ='アプリケーション'!C10 -> 臨床データ収集 | K5: ='アプリケーション'!C11 -> 無作為化・治験薬供給 | L5: ='アプリケーション'!C12 -> 電子治験マスターファイル | M5: ='アプリケーション'!C13 -> 統計解析環境 | N5: ='アプリケーション'!C14 -> 患者レジストリ・RWD基盤 | O5: ='アプリケーション'!C15 -> 薬事情報管理 | P5: ='アプリケーション'!C16 -> 申請出版 | Q5: ='アプリケーション'!C17 -> 安全性データベース | R5: ='アプリケーション'!C18 -> シグナル検出 | S5: ='アプリケーション'!C19 -> 製造実行システム | T5: ='アプリケーション'!C20 -> 工程データ管理 | U5: ='アプリケーション'!C21 -> 設備・環境管理 | V5: ='アプリケーション'!C22 -> ラベル・アートワーク管理 | W5: ='アプリケーション'!C23 -> 品質マネジメントシステム | X5: ='アプリケーション'!C24 -> バリデーション管理 | Y5: ='アプリケーション'!C25 -> 試験室情報管理 | Z5: ='アプリケーション'!C26 -> 需給計画 | AA5: ='アプリケーション'!C27 -> 倉庫・物流管理 | AB5: ='アプリケーション'!C28 -> シリアライゼーション | AC5: ='アプリケーション'!C29 -> 顧客関係管理 | AD5: ='アプリケーション'!C30 -> 患者支援（ハブ） | AE5: ='アプリケーション'!C31 -> 価格・契約・政府価格報告 | AF5: ='アプリケーション'!C32 -> 販促資材審査 | AG5: ='アプリケーション'!C33 -> ERP | AH5: ='アプリケーション'!C34 -> マスタデータ管理 | AI5: ='アプリケーション'!C35 -> GxP文書管理 | AJ5: ='アプリケーション'!C36 -> 教育管理 | AK5: ='アプリケーション'!C37 -> データ・分析基盤 | AL5: ='アプリケーション'!C38 -> ポートフォリオ・プロジェクト管理 | AM5: ='アプリケーション'!C39 -> 契約管理 | AN5: ='アプリケーション'!C40 -> 知財管理
A6: C01 戦略・ガバナンス | B6: C01-01 | C6: {=IFERROR(INDEX('ケイパビリティマップ'!$E:$E,MATCH(B6,'ケイパビリティマップ'!$A:$A,0)),"（IDなし）")} -> 研究開発ポートフォリオ管理 | AK6: ○ | AL6: ● | AO6: =COUNTIF(D6:AN6,"●") -> 1 | AP6: =COUNTIF(D6:AN6,"○") -> 1
B7: C01-02 | C7: {=IFERROR(INDEX('ケイパビリティマップ'!$E:$E,MATCH(B7,'ケイパビリティマップ'!$A:$A,0)),"（IDなし）")} -> 知財・独占期間管理 | O7: ○ | AN7: ● | AO7: =COUNTIF(D7:AN7,"●") -> 1 | AP7: =COUNTIF(D7:AN7,"○") -> 1
B8: C01-03 | C8: {=IFERROR(INDEX('ケイパビリティマップ'!$E:$E,MATCH(B8,'ケイパビリティマップ'!$A:$A,0)),"（IDなし）")} -> 外部パートナー管理 | W8: ○ | AG8: ○ | AM8: ● | AO8: =COUNTIF(D8:AN8,"●") -> 1 | AP8: =COUNTIF(D8:AN8,"○") -> 2
