Workbook

Sheet 前提
A1: 競争見積もり施策 インパクト試算モデル ― 前提条件
A2: 青字セルが変更可能なパラメータ。黄色は合意対象の仮説値(合意相手を明記)。金額単位: 百万円
B4: 全社パラメータ
B5: 年間IT支出 (百万円) | C5: 8000 | D5: 事実(財務データ)
B6: 随意契約比率 | C6: 0.8 | D6: 事実(契約マスタ)
B7: WACC (割引率) | C7: 0.06 | D7: 財務部門の標準値
B8: 評価期間 (年) | C8: 3 | D8: 経営合意事項
B10: 投資・コストパラメータ
B11: 準備費用 (Y0前・今回承認対象) | C11: 20 | D11: 仮説値: VMO見積 ※今回の承認対象
B12: VMO立ち上げ初期投資 (Y0) | C12: 150 | D12: 仮説値: VMO見積(体制/プロセス/ツール整備)
B13: VMO運営費 (年間・人件費等) | C13: 80 | D13: 仮説値: VMO見積(専任体制の固定費)
B14: RFP実行コスト Y1 | C14: 120 | D14: 仮説値: VMO見積(案件変動費・初年度)
B15: RFP実行コスト Y2 | C15: 90 | D15: 仮説値: VMO見積(標準化により逓減)
B16: RFP実行コスト Y3 | C16: 60 | D16: 仮説値: VMO見積
B19: カテゴリ別パラメータ
B20: カテゴリ | C20: 支出比率 | D20: 競争可能割合 (現場と合意) | E20: 削減率:保守 (調達と合意) | F20: 削減率:中位 (調達と合意) | G20: 削減率:楽観 (調達と合意) | H20: 平均契約年数
B21: 既存システム保守運用費 | C21: 0.35 | D21: 0.55 | E21: 0.08 | F21: 0.12 | G21: 0.16 | H21: 3
B22: システム構築・導入費 | C22: 0.2 | D22: 0.65 | E22: 0.1 | F22: 0.15 | G22: 0.2 | H22: 1
B23: ソフトウェアライセンス費 | C23: 0.15 | D23: 0.45 | E23: 0.05 | F23: 0.08 | G23: 0.12 | H23: 2
B24: クラウド利用料 | C24: 0.12 | D24: 0.4 | E24: 0.06 | F24: 0.1 | G24: 0.14 | H24: 1
B25: ネットワーク機器・回線 | C25: 0.1 | D25: 0.7 | E25: 0.09 | F25: 0.14 | G25: 0.18 | H25: 4
B26: EUC(PC/スマホ)レンタル | C26: 0.08 | D26: 0.75 | E26: 0.07 | F26: 0.11 | G26: 0.15 | H26: 3
B27: 合計(支出比率=100%確認) | C27: =SUM(C21:C26) -> 1
B29: 合意相手の整理: 競争可能割合=現場(除外条件の類型判定) / 削減率レンジ=調達・購買(市場相場/入札実績) / 投資・コスト=VMO自身(保守的に厚めに設定)

Sheet 計算
A1: 計算シート ― 事実→仮説の段階計算と年次立ち上がり
A3: カテゴリ | B3: 支出額 | C3: 随意契約額 (事実) | D3: 競争対象額 (合意割合) | E3: 年間削減:保守 | F3: 年間削減:中位 | G3: 年間削減:楽観 | H3: グロス削減Y1 (中位) | I3: グロス削減Y2 (中位) | J3: グロス削減Y3 (中位)
A4: =前提!B21 -> 既存システム保守運用費 | B4: =前提!$C$5*前提!C21 -> 2800 | C4: =B4*前提!$C$6 -> 2240 | D4: =C4*前提!D21 -> 1232 | E4: =D4*前提!E21 -> 98.56 | F4: =D4*前提!F21 -> 147.84 | G4: =D4*前提!G21 -> 197.12 | H4: =F4*MIN(1/前提!H21,1) -> 49.28 | I4: =F4*MIN(2/前提!H21,1) -> 98.56 | J4: =F4*MIN(3/前提!H21,1) -> 147.84
A5: =前提!B22 -> システム構築・導入費 | B5: =前提!$C$5*前提!C22 -> 1600 | C5: =B5*前提!$C$6 -> 1280 | D5: =C5*前提!D22 -> 832 | E5: =D5*前提!E22 -> 83.2 | F5: =D5*前提!F22 -> 124.8 | G5: =D5*前提!G22 -> 166.4 | H5: =F5*MIN(1/前提!H22,1) -> 124.8 | I5: =F5*MIN(2/前提!H22,1) -> 124.8 | J5: =F5*MIN(3/前提!H22,1) -> 124.8
A6: =前提!B23 -> ソフトウェアライセンス費 | B6: =前提!$C$5*前提!C23 -> 1200 | C6: =B6*前提!$C$6 -> 960 | D6: =C6*前提!D23 -> 432 | E6: =D6*前提!E23 -> 21.6 | F6: =D6*前提!F23 -> 34.56 | G6: =D6*前提!G23 -> 51.84 | H6: =F6*MIN(1/前提!H23,1) -> 17.28 | I6: =F6*MIN(2/前提!H23,1) -> 34.56 | J6: =F6*MIN(3/前提!H23,1) -> 34.56
A7: =前提!B24 -> クラウド利用料 | B7: =前提!$C$5*前提!C24 -> 960 | C7: =B7*前提!$C$6 -> 768 | D7: =C7*前提!D24 -> 307.2 | E7: =D7*前提!E24 -> 18.432 | F7: =D7*前提!F24 -> 30.72 | G7: =D7*前提!G24 -> 43.008 | H7: =F7*MIN(1/前提!H24,1) -> 30.72 | I7: =F7*MIN(2/前提!H24,1) -> 30.72 | J7: =F7*MIN(3/前提!H24,1) -> 30.72
A8: =前提!B25 -> ネットワーク機器・回線 | B8: =前提!$C$5*前提!C25 -> 800 | C8: =B8*前提!$C$6 -> 640 | D8: =C8*前提!D25 -> 448 | E8: =D8*前提!E25 -> 40.32 | F8: =D8*前提!F25 -> 62.72 | G8: =D8*前提!G25 -> 80.64 | H8: =F8*MIN(1/前提!H25,1) -> 15.68 | I8: =F8*MIN(2/前提!H25,1) -> 31.36 | J8: =F8*MIN(3/前提!H25,1) -> 47.04
A9: =前提!B26 -> EUC(PC/スマホ)レンタル | B9: =前提!$C$5*前提!C26 -> 640 | C9: =B9*前提!$C$6 -> 512 | D9: =C9*前提!D26 -> 384 | E9: =D9*前提!E26 -> 26.88 | F9: =D9*前提!F26 -> 42.24 | G9: =D9*前提!G26 -> 57.6 | H9: =F9*MIN(1/前提!H26,1) -> 14.08 | I9: =F9*MIN(2/前提!H26,1) -> 28.16 | J9: =F9*MIN(3/前提!H26,1) -> 42.24
A10: 合計 | B10: =SUM(B4:B9) -> 8000 | C10: =SUM(C4:C9) -> 6400 | D10: =SUM(D4:D9) -> 3635.2 | E10: =SUM(E4:E9) -> 288.992 | F10: =SUM(F4:F9) -> 442.88 | G10: =SUM(G4:G9) -> 596.608 | H10: =SUM(H4:H9) -> 251.84 | I10: =SUM(I4:I9) -> 348.16 | J10: =SUM(J4:J9) -> 427.2
A12: ※グロス削減の年次立ち上がりは「契約更新の到来に沿って min(経過年/平均契約年数, 1) の割合で効果が積み上がる」近似。実データ(契約単位の更新月)投入時は契約別に置換可能

Sheet 投資評価
A1: 投資評価 ― NPV / IRR (3年・真のネットCF)
A2: VMO運営費(人件費)まで控除した保守評価。準備費用(今回承認対象20百万)は初期投資に含めて評価
A4: 項目 | B4: Y0 | C4: Y1 | D4: Y2 | E4: Y3 | G4: (参考)無制約グロス
A5: グロス削減(キャパ制約後) | C5: =計算!H10*キャパシティ!C29 -> 221.46867 | D5: =計算!I10*キャパシティ!D29 -> 348.16 | E5: =計算!J10*キャパシティ!E29 -> 427.2 | G5: =計算!H10 -> 251.84 | H5: =計算!I10 -> 348.16 | I5: =計算!J10 -> 427.2
A6: RFP実行コスト(−) | C6: =-前提!C14 -> -120 | D6: =-前提!C15 -> -90 | E6: =-前提!C16 -> -60
A7: VMO運営費(−) | C7: =-前提!C13 -> -80 | D7: =-前提!C13 -> -80 | E7: =-前提!C13 -> -80
A8: 初期投資(準備費用込)(−) | B8: =-(前提!C11+前提!C12) -> -170
A9: ネットCF | B9: =SUM(B5:B8) -> -170 | C9: =SUM(C5:C8) -> 21.468672 | D9: =SUM(D5:D8) -> 178.16 | E9: =SUM(E5:E8) -> 287.2
A10: 割引係数 | B10: =1/(1+前提!$C$7)^0 -> 1 | C10: =1/(1+前提!$C$7)^1 -> 0.94339623 | D10: =1/(1+前提!$C$7)^2 -> 0.88999644 | E10: =1/(1+前提!$C$7)^3 -> 0.83961928
A11: 割引後CF | B11: =B9*B10 -> -170 | C11: =C9*C10 -> 20.253464 | D11: =D9*D10 -> 158.56177 | E11: =E9*E10 -> 241.13866
A12: 累積NPV | B12: =B11 -> -170 | C12: =B12+C11 -> -149.74654 | D12: =C12+D11 -> 8.8152301 | E12: =D12+E11 -> 249.95389
A15: 投資評価指標
A16: NPV (評価期間・WACC) | B16: =E12 -> 249.95389
A17: IRR | B17: =IRR(B9:E9) -> 0.53123323
A18: 収益性指数 PI | B18: =(E12+ABS(B9))/ABS(B9) -> 2.470317
A19: 累積ネット(割引前・Y1-Y3) | B19: =SUM(C9:E9) -> 486.82867
A21: 感度メモ: 削減率を「保守」に切替える場合は、計算シートのF列参照を E列(保守) に変更。前提シートの黄色セルを更新すれば全て自動再計算

Sheet キャパシティ
A1: VMO キャパシティ・プランニング ― 需給と年次スループット
A2: 供給=実効工数(人月/年)、需要=階層別件数×工数原単位。処理可能割合をグロス削減のクリップ係数として投資評価へ連携
B4: 【供給側】実効工数 (人月/年)
B5: 要員 | C5: Y1 | D5: Y2 | E5: Y3 | F5: 備考
B6: マネジャー(パートタイム0.5FTE) | C6: 3.5 | D6: 3.5 | E6: 3.5 | F6: 統括・品質レビュー中心、管理控除後
B7: メンバー2名 | C7: 12 | D7: 18 | E7: 20 | F7: 育成期は生産性逓増→2年目自立→定常
B8: 外部コンサル1名 | C8: 8.5 | D8: 9 | E8: 6 | F8: 実務+育成。メンバー自立に伴い実務比重は逓減
B9: 実効供給 合計 | C9: =SUM(C6:C8) -> 24 | D9: =SUM(D6:D8) -> 30.5 | E9: =SUM(E6:E8) -> 29.5
B11: 【需要側】工数原単位 (人月/件)
B12: 階層 | C12: 工数原単位 | D12: 根拠
B13: 大型 | C13: 6 | D13: 3〜6ヶ月。保守側(6ヶ月)を採用
B14: 中型 | C14: 1.2 | D14: 約1ヶ月+バッファ
B15: 小型 | C15: 0.3 | D15: 約1週間+バッファ
B17: 【需要側】年次必要工数 (最悪複合シナリオ=保守)
B18: 項目 | C18: Y1 | D18: Y2 | E18: Y3 | F18: 算定根拠
B19: 更新到来額(百万円) | C19: 2860 | D19: 1800 | E19: 1160 | F19: 更新時期分布(事実・要実データ確定)
B20: ×随意比率×競争可能割合(加重) | C20: =C19*(前提!C6*SUMPRODUCT(前提!C21:C26,前提!D21:D26)/SUM(前提!C21:C26)) -> 1299.584 | D20: =D19*(前提!C6*SUMPRODUCT(前提!C21:C26,前提!D21:D26)/SUM(前提!C21:C26)) -> 817.92 | E20: =E19*(前提!C6*SUMPRODUCT(前提!C21:C26,前提!D21:D26)/SUM(前提!C21:C26)) -> 527.104 | F20: 競争対象額に換算
B21: 階層ミックス 大型/中型/小型(金額) | C21: 0.55 | D21: 0.35 | E21: 0.1 | F21: 最悪複合(大型偏重)。金額構成比
B22: 平均契約額 大型/中型/小型(百万) | C22: 300 | D22: 60 | E22: 10 | F22: 最悪複合(小さめ=件数増)。要実データ
B23: 必要工数 合計(人月) | C23: =C20*($C$21/$C$22*$C$13+$D$21/$D$22*$C$14+$E$21/$E$22*$C$15) -> 27.291264 | D23: =D20*($C$21/$C$22*$C$13+$D$21/$D$22*$C$14+$E$21/$E$22*$C$15) -> 17.17632 | E23: =E20*($C$21/$C$22*$C$13+$D$21/$D$22*$C$14+$E$21/$E$22*$C$15) -> 11.069184
B25: 【需給判定】
B26: 項目 | C26: Y1 | D26: Y2 | E26: Y3
B27: 実効供給(人月) | C27: =C9 -> 24 | D27: =D9 -> 30.5 | E27: =E9 -> 29.5
B28: 必要工数(人月) | C28: =C23 -> 27.291264 | D28: =D23 -> 17.17632 | E28: =E23 -> 11.069184
B29: 処理可能割合(クリップ係数) | C29: =MIN(C9/C23,1) -> 0.87940229 | D29: =MIN(D9/D23,1) -> 1 | E29: =MIN(E9/E23,1) -> 1
A31: ※処理可能割合<100%の年は、その割合でグロス削減をクリップ(=キャパ律速)。供給に余裕がある年は100%。
A32: ※小型が件数を押し上げるため、初年度は大型・中型を優先し小型は翌期繰越とする運営規律で品質を担保。
