Workbook

Sheet バリューストリーム
A1: バリューストリーム（L1〜L4）
A2: 対象：日本の製薬会社（研究開発型。GxP規制下のコンピュータ化システムを持ち、IT機能は内製と外部委託を併用）／日本の規制・法令基準（GMP省令・ER/ES指針・コンピュータ化システム適正管理ガイドライン・個人情報保護法・金商法〔J-SOX〕・取適法ほか）。1行1項目。L1〜L4列の●がその行のレベル。L2はIT4IT（The Open Group）の4つのバリューストリーム（S2P・R2D・R2F・D2C）に対応する。出口はL2、入力・出力情報・関連法令・規制・主な関与者はL4の項目。 入力情報・出力情報はVS定義の過程で得られる正本（直接入力する）。情報オブジェクトはこれを取りまとめて一覧化したもの。★＝製薬のGxP規制、または日本のIT外部委託（請負・準委任、取適法）・IT全般統制（J-SOX）に固有の項目。
A3: ID | B3: L1 | C3: L2 | D3: L3 | E3: L4 | F3: VS項目名 | G3: VSの定義 | H3: 出口（ゲート） | I3: 入力情報 | J3: 出力情報 | K3: 関連法令・規制 | L3: 主な関与者（社内／外部）
A4: VS | B4: ● | F4: Manage IT / Digital Solutions | G4: 事業戦略をIT投資とポートフォリオに変換し、要件からデジタルソリューションを開発・配備して、利用者の申請に応じて提供し、運用の中で障害を検知・是正するまで。事業に必要なデジタル機能とシステム資産を、GxP・法令に適合した状態で供給し続ける
A5: 01 | C5: ● | F5: 戦略・ポートフォリオ（S2P） | G5: 事業戦略をIT戦略とアーキテクチャに落とし込み、事業部門の需要を評価して、投資する案件をポートフォリオとして決める段階 | H5: 投資の承認（ポートフォリオへの組入れ）
A6: 01-01 | D6: ● | F6: IT戦略・アーキテクチャの策定 | G6: 事業戦略・DX方針を受けて、IT戦略・ロードマップ、将来のアーキテクチャ、技術標準とIT規程を定める
A7: 01-01-01 | E7: ● | F7: 事業戦略・DX方針の把握とIT課題の整理 | I7: 事業戦略・DX方針、アプリケーション台帳 | J7: IT戦略・ロードマップ | K7: なし | L7: CIO・IT企画／経営企画
A8: 01-01-02 | E8: ● | F8: IT戦略・ロードマップの策定 | I8: 事業戦略・DX方針、ITポートフォリオ、ITリスク登録簿 | J8: IT戦略・ロードマップ | K8: なし | L8: CIO・IT企画／経営層
A9: 01-01-03 | E9: ● | F9: 現状・将来アーキテクチャの策定（業務・アプリケーション・データ・技術） | I9: IT戦略・ロードマップ、アプリケーション台帳、構成情報 | J9: エンタープライズアーキテクチャ、データ定義・データカタログ | K9: なし | L9: ITアーキテクト／—
A10: 01-01-04 | E10: ● | F10: 技術標準の策定（クラウド・セキュリティ・連携の標準） | I10: エンタープライズアーキテクチャ、ITリスク登録簿 | J10: 技術標準 | K10: なし | L10: ITアーキテクト・ITセキュリティ／—
A11: 01-01-05 | E11: ● | F11: ★IT規程・標準手順書の制定（CSV・IT全般統制・セキュリティ） | I11: 技術標準、ITリスク登録簿 | J11: IT規程・手順書 | K11: GxP・金商法 | L11: IT企画・品質保証（QA）・内部統制／—
A12: 01-02 | D12: ● | F12: 需要管理・構想 | G12: 事業部門の需要を受け付け、構想・概算見積・ソーシング方針とGxP該当性をまとめて投資要求にする
A13: 01-02-01 | E13: ● | F13: 事業部門の需要（IT投資要求）の受付 | I13: 事業戦略・DX方針 | J13: IT投資要求 | K13: なし | L13: 事業部門・ITビジネスパートナー／—
A14: 01-02-02 | E14: ● | F14: 構想・概算見積・ビジネスケースの作成 | I14: IT投資要求、エンタープライズアーキテクチャ、技術標準 | J14: ビジネスケース | K14: なし | L14: ITビジネスパートナー・事業部門／SIer（概算見積）
A15: 01-02-03 | E15: ● | F15: ★GxP該当性の初期判定（システム分類） | I15: IT投資要求、IT規程・手順書 | J15: GxP該当性評価 | K15: GxP | L15: システムオーナー・品質保証（QA）・IT／—
A16: 01-02-04 | E16: ● | F16: ★ソーシング方針の判断（内製・外部委託・SaaS） | I16: ビジネスケース、IT人材・スキル情報、ベンダー情報 | J16: ビジネスケース | K16: なし | L16: IT企画・調達／—
A17: 01-03 | D17: ● | F17: ポートフォリオ・投資判断 | G17: 案件を評価して優先順位を付け、予算を配分し、既存のシステムを含むポートフォリオを見直す
A18: 01-03-01 | E18: ● | F18: 投資案件の評価・優先順位付け | I18: ビジネスケース、ITポートフォリオ、ITリスク登録簿 | J18: ITポートフォリオ | K18: なし | L18: IT企画・経営層／—
A19: 01-03-02 | E19: ● | F19: IT予算の配分・承認 | I19: ITポートフォリオ、IT予算・費用実績 | J19: IT予算・費用実績 | K19: なし | L19: CIO・経理・経営層／—
A20: 01-03-03 | E20: ● | F20: ポートフォリオの見直し（継続・統合・廃止） | I20: アプリケーション台帳、サービスレベル実績、IT予算・費用実績 | J20: ITポートフォリオ、アプリケーション台帳 | K20: なし | L20: IT企画・システムオーナー／—
A21: 02 | C21: ● | F21: 要件定義・開発・配備（R2D） | G21: 承認された案件について、要件を定義し、設計・開発・テスト・バリデーションを行って本番環境に配備し、運用へ引き継ぐ段階 | H21: 本番稼働の承認（リリース判定）
A22: 02-01 | D22: ● | F22: プロジェクト立上げ・委託 | G22: 計画と体制を決め、委託先を選んで契約し、GxPのリスクに応じたバリデーションの計画を立てる
A23: 02-01-01 | E23: ● | F23: プロジェクト計画・体制の決定（内製と委託の役割分担） | I23: ビジネスケース、ITポートフォリオ、IT人材・スキル情報 | J23: プロジェクト計画 | K23: なし | L23: PM・システムオーナー／—
A24: 02-01-02 | E24: ● | F24: ★委託先の選定と契約（請負・準委任の区別、発注内容の明示） | I24: ビジネスケース、ベンダー情報、ベンダー評価記録 | J24: 委託契約・発注書 | K24: 取適法・派遣法 | L24: PM・調達・法務／SIer・ベンダー
A25: 02-01-03 | E25: ● | F25: ★リスクアセスメントとバリデーション計画（GxP・データインテグリティ） | I25: GxP該当性評価、プロジェクト計画 | J25: リスクアセスメント、バリデーション計画書 | K25: GxP | L25: PM・品質保証（QA）・システムオーナー／SIer
A26: 02-02 | D26: ● | F26: 要件定義・設計 | G26: 利用者の要求を仕様にまとめ、機能・構成を設計する。アクセス制御・監査証跡・電子署名などの要件を組み込む
A27: 02-02-01 | E27: ● | F27: ユーザー要求仕様（URS）の作成 | I27: ビジネスケース、リスクアセスメント | J27: 要求仕様書（URS） | K27: GxP | L27: システムオーナー・業務部門／—
A28: 02-02-02 | E28: ● | F28: 機能仕様・設計仕様の作成 | I28: 要求仕様書（URS）、技術標準、エンタープライズアーキテクチャ、データ定義・データカタログ | J28: 設計書（機能・設計仕様） | K28: GxP | L28: ITアーキテクト・PM／SIer
A29: 02-02-03 | E29: ● | F29: ★セキュリティ・データインテグリティ要件の設計（アクセス制御・監査証跡・電子署名・個人情報） | I29: 要求仕様書（URS）、リスクアセスメント、IT規程・手順書 | J29: 設計書（機能・設計仕様）、個人情報取扱台帳 | K29: GxP・個人情報保護法 | L29: ITセキュリティ・品質保証（QA）／SIer
A30: 02-03 | D30: ● | F30: 開発・構成・テスト | G30: アプリケーションを開発し、パッケージ・SaaSを設定してシステムを連携し、テストして委託先の成果物を検収する
A31: 02-03-01 | E31: ● | F31: アプリケーション開発・パッケージ／SaaSの設定 | I31: 設計書（機能・設計仕様）、技術標準 | J31: ソースコード・構成設定 | K31: なし | L31: 開発チーム／SIer
A32: 02-03-02 | E32: ● | F32: システム連携とデータ移行の準備 | I32: 設計書（機能・設計仕様）、データ定義・データカタログ | J32: ソースコード・構成設定、リリース・移行計画 | K32: なし | L32: 開発チーム・ITアーキテクト／SIer
A33: 02-03-03 | E33: ● | F33: テストの実施（単体・結合・システム） | I33: 設計書（機能・設計仕様）、ソースコード・構成設定 | J33: テスト記録 | K33: なし | L33: 開発チーム・PM／SIer
A34: 02-03-04 | E34: ● | F34: ★委託先の成果物の検収 | I34: 委託契約・発注書、テスト記録 | J34: 検収記録 | K34: 取適法 | L34: PM・調達／SIer
A35: 02-04 | D35: ● | F35: バリデーション・リリース | G35: 適格性を確認してデータを移行し、バリデーションの結果をもとにリリースを判定して、本番に配備し運用へ引き継ぐ
A36: 02-04-01 | E36: ● | F36: ★据付時・運用時の適格性確認（IQ・OQ） | I36: バリデーション計画書、設計書（機能・設計仕様）、テスト記録 | J36: テスト記録 | K36: GxP | L36: 品質保証（QA）・IT／SIer
A37: 02-04-02 | E37: ● | F37: ★ユーザー受入テスト・性能適格性確認（UAT・PQ） | I37: 要求仕様書（URS）、バリデーション計画書 | J37: テスト記録 | K37: GxP | L37: システムオーナー・業務部門・品質保証（QA）／—
A38: 02-04-03 | E38: ● | F38: データ移行と移行結果の検証 | I38: リリース・移行計画、データ定義・データカタログ | J38: テスト記録 | K38: GxP | L38: IT・業務部門／SIer
A39: 02-04-04 | E39: ● | F39: ★バリデーション報告とリリース判定 | I39: テスト記録、要求仕様書（URS）、バリデーション計画書 | J39: バリデーション報告書 | K39: GxP | L39: 品質保証（QA）・システムオーナー・PM／—
A40: 02-04-05 | E40: ● | F40: 本番配備と運用への引継ぎ（台帳・構成情報・カタログへの登録） | I40: バリデーション報告書、リリース・移行計画 | J40: 構成情報、アプリケーション台帳、ITサービスカタログ | K40: GxP | L40: IT運用・PM／SIer・運用委託先
A41: 02-04-06 | E41: ● | F41: 利用者教育と手順書の整備 | I41: IT規程・手順書、設計書（機能・設計仕様） | J41: 教育記録 | K41: GxP | L41: システムオーナー・業務部門／—
A42: 03 | C42: ● | F42: 利用申請・提供（R2F） | G42: 利用者がカタログからITサービスを申請し、承認を経て、アカウント・端末・ソフトウェア・クラウド資源などを提供し、利用と費用を管理する段階 | H42: 提供の完了（利用開始）
A43: 03-01 | D43: ● | F43: サービスカタログの公開 | G43: 提供するITサービスを定義してカタログに載せ、サービスレベルと利用条件を合意する
A44: 03-01-01 | E44: ● | F44: サービスの定義とカタログへの掲載 | I44: アプリケーション台帳、構成情報 | J44: ITサービスカタログ | K44: なし | L44: ITサービス管理／—
A45: 03-01-02 | E45: ● | F45: サービスレベル・利用条件の合意 | I45: ITサービスカタログ | J45: サービスレベル合意（SLA） | K45: なし | L45: ITサービス管理・事業部門／運用委託先
A46: 03-02 | D46: ● | F46: 申請・承認 | G46: 利用者の申請を受け付け、上長・システムオーナーが職務分掌を確かめて承認する
A47: 03-02-01 | E47: ● | F47: サービス要求（利用申請）の受付 | I47: ITサービスカタログ | J47: サービス要求 | K47: なし | L47: 利用者・サービスデスク／運用委託先
A48: 03-02-02 | E48: ● | F48: ★申請の承認（上長・システムオーナー、職務分掌の確認） | I48: サービス要求、ID・アカウント情報 | J48: サービス要求 | K48: GxP・金商法 | L48: 上長・システムオーナー／—
A49: 03-03 | D49: ● | F49: 提供 | G49: アカウントとアクセス権を付与し、端末・ソフトウェア・クラウド資源を提供して、完了を記録する
A50: 03-03-01 | E50: ● | F50: ★アカウントの作成・アクセス権の付与 | I50: サービス要求、ID・アカウント情報 | J50: ID・アカウント情報、アクセス権記録 | K50: GxP・金商法 | L50: IT運用・サービスデスク／運用委託先
A51: 03-03-02 | E51: ● | F51: 端末・ソフトウェアの提供（キッティング・ライセンスの割当） | I51: サービス要求、IT資産・ライセンス台帳 | J51: IT資産・ライセンス台帳 | K51: なし | L51: サービスデスク／運用委託先
A52: 03-03-03 | E52: ● | F52: クラウド資源・環境の提供 | I52: サービス要求、技術標準 | J52: 構成情報 | K52: なし | L52: インフラ担当／クラウド事業者
A53: 03-03-04 | E53: ● | F53: 提供の記録と完了通知 | I53: サービス要求 | J53: サービス要求 | K53: なし | L53: サービスデスク／運用委託先
A54: 03-04 | D54: ● | F54: 利用・費用管理 | G54: 利用状況とライセンスを把握して費用を配賦し、アクセス権を定期的に見直す
A55: 03-04-01 | E55: ● | F55: 利用状況・ライセンスの把握 | I55: IT資産・ライセンス台帳、ID・アカウント情報 | J55: 利用実績・費用配賦 | K55: なし | L55: IT資産管理／—
A56: 03-04-02 | E56: ● | F56: IT費用の部門への配賦 | I56: 利用実績・費用配賦、IT予算・費用実績 | J56: IT予算・費用実績 | K56: なし | L56: IT企画・経理／—
A57: 03-04-03 | E57: ● | F57: ★アクセス権の定期棚卸（異動・退職の反映） | I57: ID・アカウント情報、アクセス権記録 | J57: アクセス権記録 | K57: GxP・金商法 | L57: システムオーナー・IT運用／—
A58: 04 | C58: ● | F58: 検知・是正（D2C） | G58: ITサービスを監視して異常を検知し、インシデントから復旧させ、問題の根本原因を変更によって是正し、定期的に評価して改善につなげる段階 | H58: 是正の完了（問題のクローズ）
A59: 04-01 | D59: ● | F59: 監視・検知 | G59: システムの稼働・性能・セキュリティを監視し、ジョブとバックアップを運用して、異常を検知する
A60: 04-01-01 | E60: ● | F60: 稼働・性能・容量の監視 | I60: 構成情報、サービスレベル合意（SLA） | J60: 監視イベント | K60: なし | L60: IT運用／運用委託先
A61: 04-01-02 | E61: ● | F61: ★ジョブ・バックアップの運用（GxP記録の保護） | I61: 構成情報、IT規程・手順書 | J61: 運用記録 | K61: GxP | L61: IT運用／運用委託先
A62: 04-01-03 | E62: ● | F62: セキュリティ監視（SOC） | I62: 構成情報、脆弱性情報 | J62: 監視イベント | K62: なし | L62: ITセキュリティ／SOC事業者
A63: 04-02 | D63: ● | F63: インシデント対応 | G63: インシデントを記録・分類して復旧させる。GxPへの影響と個人情報の漏えいを評価し、必要な報告を行う
A64: 04-02-01 | E64: ● | F64: インシデントの記録・分類・優先度付け | I64: 監視イベント、サービス要求 | J64: インシデント記録 | K64: なし | L64: サービスデスク／運用委託先
A65: 04-02-02 | E65: ● | F65: 切り分け・復旧（回避策の適用） | I65: インシデント記録、構成情報、ナレッジ記事 | J65: インシデント記録、ナレッジ記事 | K65: なし | L65: IT運用・サービスデスク／運用委託先・ベンダー
A66: 04-02-03 | E66: ● | F66: ★GxPシステムの障害によるデータへの影響評価（品質部門の逸脱処理と連携） | I66: インシデント記録、監査証跡・電子署名記録 | J66: インシデント記録 | K66: GxP | L66: システムオーナー・品質保証（QA）／—
A67: 04-02-04 | E67: ● | F67: ★セキュリティインシデントの対応と報告（個人情報の漏えい等の報告を含む） | I67: 監視イベント、インシデント記録、個人情報取扱台帳 | J67: セキュリティインシデント記録 | K67: 個人情報保護法 | L67: CSIRT・法務・広報／外部専門事業者・個人情報保護委員会（報告先）
A68: 04-02-05 | E68: ● | F68: 大規模障害・災害からの復旧（IT-BCP） | I68: IT事業継続計画、構成情報 | J68: インシデント記録 | K68: なし | L68: IT運用・経営層／運用委託先・クラウド事業者
A69: 04-03 | D69: ● | F69: 問題・変更管理 | G69: 問題の根本原因を分析し、影響を評価した変更で是正する。GxPシステムは変更に応じて再バリデーションする
A70: 04-03-01 | E70: ● | F70: 問題の根本原因分析 | I70: インシデント記録、構成情報 | J70: 問題記録 | K70: なし | L70: IT運用・開発チーム／ベンダー
A71: 04-03-02 | E71: ● | F71: ★変更要求と影響評価（GxP・データインテグリティ・セキュリティ） | I71: 問題記録、脆弱性情報、構成情報 | J71: 変更記録 | K71: GxP・金商法 | L71: 変更諮問委員会（CAB）・品質保証（QA）／—
A72: 04-03-03 | E72: ● | F72: ★変更の実施と再バリデーション | I72: 変更記録、バリデーション計画書 | J72: 変更記録、テスト記録、構成情報 | K72: GxP | L72: IT運用・開発チーム・品質保証（QA）／SIer
A73: 04-03-04 | E73: ● | F73: 脆弱性への対応（パッチの適用） | I73: 脆弱性情報、構成情報 | J73: 脆弱性情報、変更記録 | K73: なし | L73: ITセキュリティ・IT運用／ベンダー
A74: 04-04 | D74: ● | F74: 定期評価・継続的改善 | G74: サービスレベル・GxPシステム・委託先・IT全般統制を定期的に評価し、廃止と改善の要求を次の投資判断につなげる
A75: 04-04-01 | E75: ● | F75: サービスレベル実績の報告・評価 | I75: 監視イベント、インシデント記録、サービスレベル合意（SLA） | J75: サービスレベル実績 | K75: なし | L75: ITサービス管理・事業部門／運用委託先
A76: 04-04-02 | E76: ● | F76: ★GxPシステムの定期レビュー | I76: 変更記録、インシデント記録、アクセス権記録、監査証跡・電子署名記録 | J76: 定期レビュー記録 | K76: GxP | L76: システムオーナー・品質保証（QA）／—
A77: 04-04-03 | E77: ● | F77: ★委託先の評価・監督（SLA実績・監査・価格協議） | I77: サービスレベル実績、委託契約・発注書 | J77: ベンダー評価記録 | K77: GxP・取適法 | L77: IT企画・調達・品質保証（QA）／SIer・運用委託先
A78: 04-04-04 | E78: ● | F78: ★IT全般統制の評価と監査への対応 | I78: 変更記録、アクセス権記録、運用記録 | J78: ITリスク登録簿 | K78: 金商法 | L78: IT企画・内部監査／監査法人
A79: 04-04-05 | E79: ● | F79: ★システムの廃止とGxP記録の保存（アーカイブ） | I79: ITポートフォリオ、アプリケーション台帳、データ定義・データカタログ | J79: 記録保存・アーカイブ記録、アプリケーション台帳 | K79: GxP | L79: システムオーナー・品質保証（QA）・IT運用／—
A80: 04-04-06 | E80: ● | F80: 改善の提案（次の投資要求へ） | I80: 問題記録、サービスレベル実績、ITリスク登録簿 | J80: IT投資要求 | K80: なし | L80: IT企画・ITサービス管理／—

Sheet ケイパビリティマップ
A1: ビジネス・ケイパビリティマップ（L1〜L3）
A2: 対象：日本の製薬会社（研究開発型。GxP規制下のコンピュータ化システムを持ち、IT機能は内製と外部委託を併用）／日本の規制・法令基準（GMP省令・ER/ES指針・コンピュータ化システム適正管理ガイドライン・個人情報保護法・金商法〔J-SOX〕・取適法ほか）。1行1項目。L1〜L3列の●がその行のレベル。区分はL1、範囲・アウトカムはL3の項目。★＝製薬のGxP規制、または日本のIT外部委託（請負・準委任、取適法）・IT全般統制（J-SOX）に固有、または特に強調する能力。
A3: ID | B3: L1 | C3: L2 | D3: L3 | E3: ケイパビリティ名 | F3: ケイパビリティの定義 | G3: 区分 | H3: 範囲（含む） | I3: 範囲（含まない） | J3: アウトカム
A4: C01 | B4: ● | E4: IT戦略・ガバナンス | F4: 事業戦略からIT戦略・アーキテクチャ・投資の方針を定め、規程・リスク・統制・予算でIT全体を統制する能力 | G4: 戦略
A5: C01-01 | C5: ● | E5: IT戦略・DX企画 | F5: 事業戦略を受けてIT戦略とロードマップを定め、デジタル技術による業務・事業の変革を企画する
A6: C01-01-01 | D6: ● | E6: IT戦略・ロードマップ策定 | F6: 事業戦略・DX方針から、ITの目標・重点施策・中長期の実行計画を定める | H6: IT戦略、ロードマップ、重点施策 | I6: 個別案件の評価（C01-03-02） | J6: 事業の方向とそろったIT投資
A7: C01-01-02 | D7: ● | E7: DX・デジタル企画 | F7: データ・AI・クラウドなどを使った業務・事業の変革を企画し、事業部門と構想を描く | H7: DXテーマの探索、構想、効果の仮説 | I7: 案件ごとの概算見積（C01-03-01） | J7: 事業部門と共有された変革の構想
A8: C01-02 | C8: ● | E8: エンタープライズアーキテクチャ | F8: 業務・アプリケーション・データ・技術の現状と将来像を描き、技術標準とアプリケーションの全体を管理する
A9: C01-02-01 | D9: ● | E9: アーキテクチャ設計（現状・将来像） | F9: 業務・アプリケーション・データ・技術の現状と将来像、移行の道筋を描く | H9: 現状・将来のアーキテクチャ、移行計画 | I9: 個別システムの設計（C02-02-02） | J9: 全体として整合したシステム構成
A10: C01-02-02 | D10: ● | E10: 技術標準・アーキテクチャレビュー | F10: 採用する技術・製品・連携方式の標準を定め、案件の設計が標準に沿うかを審査する | H10: 技術標準、設計レビュー、例外の承認 | I10: セキュリティの方針（C05-01-01） | J10: 重複や乱立のない技術基盤
A11: C01-02-03 | D11: ● | E11: アプリケーションポートフォリオ管理 | F11: すべてのアプリケーションを台帳で管理し、価値・技術・コストの面から継続・統合・廃止を評価する | H11: アプリケーション台帳、ライフサイクルの状態、評価 | I11: 投資案件の優先順位付け（C01-03-02） | J11: 把握され、整理されたアプリケーション群
A12: C01-03 | C12: ● | E12: ITポートフォリオ・需要管理 | F12: 事業部門の需要を受け付けて構想にまとめ、投資案件を評価・選択し、ポートフォリオ全体を監視する
A13: C01-03-01 | D13: ● | E13: 需要管理 | F13: 事業部門のIT需要を一つの窓口で受け付け、構想・概算見積・ビジネスケースにまとめる | H13: 需要の受付、構想、ビジネスケース | I13: 予算の承認（C01-05-01） | J13: 見える化され、比較できる需要
A14: C01-03-02 | D14: ● | E14: 投資評価・優先順位付け | F14: 共通の基準で投資案件を評価し、優先順位を付けて、実施する案件を決める | H14: 評価基準、優先順位、投資判断 | I14: 個別プロジェクトの進捗管理（C02-01-01） | J14: 価値の高い案件への資源の集中
A15: C01-03-03 | D15: ● | E15: ポートフォリオの監視・見直し | F15: 実行中の案件と既存システムの成果を監視し、継続・中止・統合を見直す | H15: 案件の監視、効果の検証、見直し | I15: アプリケーション台帳の維持（C01-02-03） | J15: 成果に応じて組み替えられるポートフォリオ
A16: C01-04 | C16: ● | E16: ITガバナンス・リスク管理★ | F16: IT規程と標準手順を定め、ITのリスクを管理し、IT全般統制を整備・評価する
A17: C01-04-01 | D17: ● | E17: IT規程・標準手順★ | F17: IT規程と、CSV・変更管理・アクセス管理などの標準手順書（SOP）を定め、改訂する | H17: IT規程、IT標準手順書、GxP関連のSOP | I17: 個別システムの運用手順書（C07-03-01） | J17: 規制と社内ルールに沿った一貫したIT業務
A18: C01-04-02 | D18: ● | E18: テクノロジーリスク管理 | F18: ITに関するリスク（老朽化・ベンダー依存・障害・サイバーなど）を洗い出し、評価して対策を管理する | H18: ITリスク登録簿、リスク評価、対策の管理 | I18: サイバーセキュリティの詳細なリスク評価（C05-01-01） | J18: 経営が把握し、管理されたITリスク
A19: C01-04-03 | D19: ● | E19: IT全般統制・監査対応★ | F19: 財務報告に関わるシステムのIT全般統制（開発・変更・運用・アクセス）を整備し、評価と監査に対応する | H19: IT全般統制、統制の評価、監査対応 | I19: GxPの定期レビュー（C06-01-03） | J19: 有効性を説明できるIT統制
A20: C01-05 | C20: ● | E20: IT財務管理 | F20: IT予算を立てて配分し、費用の実績を把握して部門に配賦する
A21: C01-05-01 | D21: ● | E21: IT予算管理 | F21: IT予算を立てて案件・サービスに配分し、実績と比較する | H21: IT予算、予実管理、概算見積の確認 | I21: 投資案件の評価（C01-03-02） | J21: 予算内に管理されたIT支出
A22: C01-05-02 | D22: ● | E22: IT費用の配賦・分析 | F22: ITの費用をサービス・部門に配賦し、総保有コストを分析する | H22: 費用の配賦、TCO分析 | I22: ライセンスの利用把握（C04-04-02） | J22: 説明できるITのコスト
A23: C02 | B23: ● | E23: ソリューション開発・導入 | F23: 承認された案件を、要件定義・設計・開発・テスト・リリースを通じて、内製と外部委託の組み合わせで実現する能力 | G23: コア
A24: C02-01 | C24: ● | E24: プロジェクト管理★ | F24: プロジェクトの計画・体制・進捗・品質を管理し、委託先の作業を監督する
A25: C02-01-01 | D25: ● | E25: プロジェクト計画・進捗管理 | F25: プロジェクトの計画・体制・スケジュールを立て、進捗・課題・リスクを管理する | H25: 計画、体制、進捗、課題・リスク | I25: ポートフォリオ全体の監視（C01-03-03） | J25: 計画どおりに完了するプロジェクト
A26: C02-01-02 | D26: ● | E26: 委託先の開発管理★ | F26: 委託先の作業範囲・進捗・品質を監督し、成果物を検収する。請負と準委任の違いに応じて指揮の範囲を守る | H26: 作業範囲の管理、進捗・品質の監督、成果物の検収 | I26: 委託先の選定・契約（C07-01-02） | J26: 丸投げにならず、中身を説明できる開発
A27: C02-02 | C27: ● | E27: 要件定義・設計 | F27: 利用者の要求を仕様にまとめ、機能・構成・連携を設計する
A28: C02-02-01 | D28: ● | E28: 要件定義 | F28: 業務の要求をユーザー要求仕様（URS）にまとめ、優先度と受入の基準を定める | H28: ユーザー要求仕様、非機能要件、受入の基準 | I28: 構想・概算見積（C01-03-01） | J28: 検証できる形でそろった要求
A29: C02-02-02 | D29: ● | E29: 設計（機能・設計仕様） | F29: 要求を満たす機能・データ・画面・構成を設計し、機能仕様書・設計仕様書にまとめる | H29: 機能仕様、設計仕様、データ設計 | I29: 全社のアーキテクチャ（C01-02-01） | J29: 要求を追跡できる設計
A30: C02-03 | C30: ● | E30: 開発・構成 | F30: アプリケーションを開発し、パッケージ・SaaSを設定して、システム間を連携する
A31: C02-03-01 | D31: ● | E31: アプリケーション開発 | F31: アプリケーションをコーディングし、ソースコードを版管理する | H31: コーディング、ソースコード管理、コードレビュー | I31: テスト（C02-04-01） | J31: 保守できる品質のソフトウェア
A32: C02-03-02 | D32: ● | E32: パッケージ・SaaSの設定 | F32: パッケージ・SaaSを標準機能中心に設定し、設定内容を記録する | H32: パラメータ設定、アドオンの抑制、設定の記録 | I32: SaaSの契約（C04-04-02） | J32: 標準に近く、更新しやすいシステム
A33: C02-03-03 | D33: ● | E33: システム連携 | F33: システム間のデータ連携・インターフェースを開発する | H33: API、ファイル連携、連携基盤 | I33: 連携方式の標準（C01-02-02） | J33: 正確で追跡できるデータ連携
A34: C02-04 | C34: ● | E34: テスト・リリース | F34: テストを計画・実施し、データを移行して、本番環境に配備する
A35: C02-04-01 | D35: ● | E35: テスト管理 | F35: テストを計画・実施し、不具合を記録して是正を確認する | H35: テスト計画、テスト記録、不具合管理 | I35: GxPの適格性確認（C06-01-02） | J35: 不具合が取り除かれたシステム
A36: C02-04-02 | D36: ● | E36: データ移行 | F36: 旧システムのデータを移行し、件数・内容の正しさを検証する | H36: 移行計画、移行、移行結果の検証 | I36: マスタの定義（C06-03-01） | J36: 欠落・改変のない移行データ
A37: C02-04-03 | D37: ● | E37: リリース・配備 | F37: リリースを計画して本番環境に配備し、運用へ引き継ぐ | H37: リリース計画、配備、運用への引継ぎ | I37: 変更の承認（C03-05-01） | J37: 安全に本番へ移行されたシステム
A38: C03 | B38: ● | E38: ITサービス管理・運用 | F38: ITサービスを定義して提供し、日々の運用・監視と、インシデント・問題・変更の管理で、合意したサービスレベルを保つ能力 | G38: コア
A39: C03-01 | C39: ● | E39: サービスカタログ・サービスレベル管理 | F39: ITサービスを定義してカタログに載せ、サービスレベルを合意し、実績を報告する
A40: C03-01-01 | D40: ● | E40: サービスカタログ管理 | F40: 提供するITサービスの内容・条件・申請方法を定め、カタログとして公開する | H40: サービスの定義、カタログの公開・改訂 | I40: 申請の処理（C03-02-02） | J40: 利用者が選んで申請できるサービス
A41: C03-01-02 | D41: ● | E41: サービスレベル管理 | F41: サービスレベルを事業部門・委託先と合意し、実績を測定・報告する | H41: SLA、実績の測定・報告、改善 | I41: 委託先の契約上の評価（C07-01-03） | J41: 合意した水準で提供されるサービス
A42: C03-02 | C42: ● | E42: サービスデスク・要求実現 | F42: 利用者の問合せと申請を一つの窓口で受け付け、処理する
A43: C03-02-01 | D43: ● | E43: サービスデスク | F43: 利用者からの問合せ・障害の連絡を受け付け、一次対応する | H43: 受付、一次対応、エスカレーション | I43: 障害の復旧（C03-04-01） | J43: つながりやすく、すぐ解決する窓口
A44: C03-02-02 | D44: ● | E44: 要求実現 | F44: カタログからの利用申請を、承認を経て処理し、完了を記録する | H44: 申請の受付・承認の確認・処理・完了 | I44: アクセス権の設定の基準（C05-02-02） | J44: 待たずに使い始められるサービス
A45: C03-03 | C45: ● | E45: IT運用・監視 | F45: システムの稼働を監視し、ジョブ・バックアップを運用して、容量と可用性を管理する
A46: C03-03-01 | D46: ● | E46: 監視・イベント管理 | F46: システムの稼働・性能を監視し、イベントを検知・分類する | H46: 稼働・性能の監視、イベントの検知 | I46: セキュリティの監視（C05-03-02） | J46: 利用者より先に異常に気づく運用
A47: C03-03-02 | D47: ● | E47: ジョブ・バックアップ運用 | F47: ジョブを運用し、データをバックアップして、復元できることを確かめる | H47: ジョブ運用、バックアップ、復元テスト | I47: 記録の長期保存（C06-02-03） | J47: 失われないデータ
A48: C03-03-03 | D48: ● | E48: キャパシティ・可用性管理 | F48: 性能・容量の需要を予測し、必要な可用性を確保する | H48: 容量計画、可用性の設計・測定 | I48: 災害時の復旧（C03-04-03） | J48: 必要なときに使えるシステム
A49: C03-04 | C49: ● | E49: インシデント・問題管理 | F49: インシデントから早く復旧させ、根本原因を取り除き、大規模な障害・災害に備える
A50: C03-04-01 | D50: ● | E50: インシデント管理 | F50: インシデントを記録・分類し、回避策で早くサービスを復旧させる | H50: 記録、分類・優先度、復旧、エスカレーション | I50: セキュリティインシデント（C05-03-03） | J50: 短い停止時間
A51: C03-04-02 | D51: ● | E51: 問題管理 | F51: インシデントの根本原因を分析し、再発を防ぐ対策を決める | H51: 根本原因分析、既知の誤り、再発防止 | I51: 変更の実施（C03-05-01） | J51: 繰り返さない障害
A52: C03-04-03 | D52: ● | E52: IT事業継続・災害復旧 | F52: 大規模な障害・災害に備えて復旧の計画を立て、訓練する | H52: IT事業継続計画、災害復旧、訓練 | I52: 全社の事業継続計画 | J52: 決めた時間内に戻るシステム
A53: C03-05 | C53: ● | E53: 変更・構成管理★ | F53: 変更の影響を評価して承認・実施し、システムの構成を正確に管理する
A54: C03-05-01 | D54: ● | E54: 変更管理★ | F54: 変更を記録し、GxP・データインテグリティ・セキュリティへの影響を評価して承認し、実施を確認する | H54: 変更要求、影響評価、承認、実施の確認 | I54: 再バリデーションの実施（C06-01-02） | J54: 管理された状態を保つ変更
A55: C03-05-02 | D55: ● | E55: 構成管理 | F55: システムを構成する要素と関係を構成情報（CMDB）として正確に管理する | H55: 構成情報、関係、最新性の点検 | I55: IT資産の台帳（C04-04-01） | J55: 正確に分かるシステムの構成
A56: C04 | B56: ● | E56: ITプラットフォーム | F56: クラウド・サーバー・ネットワーク・端末などの基盤を提供し、IT資産とライセンスを管理する能力 | G56: コア
A57: C04-01 | C57: ● | E57: クラウド・データセンター | F57: クラウドとサーバー・ストレージの基盤を構築・運用する
A58: C04-01-01 | D58: ● | E58: クラウド基盤管理 | F58: クラウドの環境・アカウント・利用量を標準に沿って提供・管理する | H58: クラウド環境の提供、設定の標準、利用量 | I58: クラウドの契約（C07-01-02） | J58: 速く安全に使えるクラウド
A59: C04-01-02 | D59: ● | E59: サーバー・ストレージ管理 | F59: オンプレミスのサーバー・ストレージを構築・運用・更新する | H59: 構築、運用、保守期限の管理 | I59: 監視（C03-03-01） | J59: 保守期限内で安定した基盤
A60: C04-02 | C60: ● | E60: ネットワーク | F60: 社内・拠点のネットワークと、外部との接続を構築・運用する
A61: C04-02-01 | D61: ● | E61: 社内・拠点ネットワーク | F61: 本社・研究所・工場などの拠点のネットワークを構築・運用する | H61: LAN・WAN・無線、拠点間の接続 | I61: 工場の制御系ネットワークの設計 | J61: 止まらない拠点間の通信
A62: C04-02-02 | D62: ● | E62: リモートアクセス・外部接続 | F62: 社外からの接続と、委託先・クラウドとの接続を安全に提供する | H62: リモートアクセス、委託先・クラウドとの接続 | I62: アクセス権の付与（C05-02-02） | J62: 場所を問わず安全に使える環境
A63: C04-03 | C63: ● | E63: エンドユーザー環境 | F63: 端末とコラボレーションの環境を提供・管理する
A64: C04-03-01 | D64: ● | E64: 端末管理 | F64: PC・モバイル端末を調達・設定・配布し、更新と回収を管理する | H64: キッティング、構成の管理、更新・回収 | I64: 端末の資産管理（C04-04-01） | J64: すぐに使え、安全な端末
A65: C04-03-02 | D65: ● | E65: コラボレーション環境 | F65: メール・会議・ファイル共有などの共同作業の環境を提供する | H65: メール、会議、ファイル共有、チャット | I65: GxP文書の管理（C07-03-01） | J65: 社内外と円滑に協働できる環境
A66: C04-04 | C66: ● | E66: IT資産・ライセンス管理 | F66: ハードウェアとソフトウェアの資産・ライセンスを台帳で管理する
A67: C04-04-01 | D67: ● | E67: ハードウェア資産管理 | F67: 端末・機器を台帳で管理し、所在・利用者・保守期限を把握する | H67: 資産台帳、所在、廃棄 | I67: 構成情報（C03-05-02） | J67: 所在の分かるIT資産
A68: C04-04-02 | D68: ● | E68: ソフトウェアライセンス・SaaS管理 | F68: ライセンスとSaaSの契約・割当・利用状況を管理し、過不足をなくす | H68: ライセンスの割当、利用状況、SaaSの棚卸 | I68: ベンダーとの契約交渉（C07-01-02） | J68: 過不足も違反もないライセンス
A69: C05 | B69: ● | E69: サイバーセキュリティ | F69: セキュリティの方針と教育、IDとアクセス権の管理、脅威の監視と対応で、情報資産を守る能力 | G69: コア
A70: C05-01 | C70: ● | E70: セキュリティガバナンス | F70: セキュリティの方針を定め、リスクを評価し、教育・訓練を行う
A71: C05-01-01 | D71: ● | E71: セキュリティ方針・リスク評価 | F71: セキュリティの方針・基準を定め、システムと委託先のセキュリティのリスクを評価する | H71: 方針・基準、リスク評価、委託先の評価 | I71: ITリスク全体の管理（C01-04-02） | J71: 把握され、下げられたセキュリティリスク
A72: C05-01-02 | D72: ● | E72: セキュリティ教育・訓練 | F72: 従業員と委託先に教育を行い、標的型メールなどの訓練を行う | H72: 教育、訓練、理解度の確認 | I72: GxPの教育（C07-02-03） | J72: 攻撃にだまされない従業員
A73: C05-02 | C73: ● | E73: ID・アクセス管理★ | F73: IDのライフサイクルとアクセス権を管理し、特権IDを統制する
A74: C05-02-01 | D74: ● | E74: ID管理（入社・異動・退職） | F74: 人事の情報と連携して、IDを作成・変更・無効化する | H74: IDの作成・変更・無効化、人事との連携 | I74: 人事情報の管理 | J74: 在籍者だけが持つID
A75: C05-02-02 | D75: ● | E75: アクセス権管理・定期棚卸★ | F75: 職務分掌に沿ってアクセス権を付与し、GxPシステムと財務報告に関わるシステムの権限を定期的に棚卸しする | H75: 権限の付与・変更・削除、職務分掌、定期棚卸 | I75: 特権IDの管理（C05-02-03） | J75: 必要最小限で説明できるアクセス権
A76: C05-02-03 | D76: ● | E76: 特権ID管理 | F76: 管理者権限の付与と利用を記録・監視する | H76: 特権IDの申請・貸出・記録・点検 | I76: 委託先の作業の監督（C02-01-02） | J76: 悪用も改ざんもできない管理者権限
A77: C05-03 | C77: ● | E77: セキュリティ運用 | F77: 脆弱性を管理し、脅威を監視し、セキュリティインシデントに対応する
A78: C05-03-01 | D78: ● | E78: 脆弱性管理 | F78: 脆弱性の情報を集め、影響を評価して、パッチの適用と対策を管理する | H78: 脆弱性の収集・評価、対策の管理 | I78: 変更の承認（C03-05-01） | J78: 悪用される前に塞がれた脆弱性
A79: C05-03-02 | D79: ● | E79: 脅威監視（SOC） | F79: ログと端末を監視して、攻撃の兆候を検知・分析する | H79: ログ監視、端末の監視、脅威の分析 | I79: システムの稼働監視（C03-03-01） | J79: 早く見つかる攻撃
A80: C05-03-03 | D80: ● | E80: セキュリティインシデント対応（CSIRT） | F80: セキュリティインシデントを封じ込め、復旧させ、社内外へ報告する | H80: 封じ込め、調査、復旧、報告 | I80: 通常の障害の対応（C03-04-01） | J80: 被害が小さく、説明責任を果たせる対応
A81: C06 | B81: ● | E81: データ・GxPコンプライアンス | F81: GxPに関わるシステムをバリデートし、電子記録の完全性を保ち、データと個人情報を管理する能力 | G81: コア
A82: C06-01 | C82: ● | E82: GxPシステム管理（CSV）★ | F82: GxPに関わるシステムを特定し、リスクに応じてバリデートし、バリデートされた状態を保つ
A83: C06-01-01 | D83: ● | E83: GxP該当性評価・システム分類★ | F83: システムがGxPに該当するかを判定し、カテゴリとリスクの大きさを分類する | H83: GxP該当性の判定、ソフトウェアのカテゴリ、GxPシステムの一覧 | I83: IT投資の評価（C01-03-02） | J83: 漏れのないGxPシステムの把握
A84: C06-01-02 | D84: ● | E84: バリデーション（CSV）★ | F84: リスクに応じてバリデーションを計画し、適格性を確認して報告する | H84: リスクアセスメント、バリデーション計画、IQ・OQ・PQ、トレーサビリティ、報告 | I84: 一般のテスト（C02-04-01） | J84: 意図どおりに動くことを示せるシステム
A85: C06-01-03 | D85: ● | E85: 定期レビュー★ | F85: GxPシステムの変更・障害・アクセス権・監査証跡を定期的に見直し、バリデートされた状態を確かめる | H85: 定期レビュー、是正の要否の判断 | I85: IT全般統制の評価（C01-04-03） | J85: 使い続ける間も保たれる適格性
A86: C06-02 | C86: ● | E86: データインテグリティ★ | F86: GxPの電子記録を、作成から廃棄まで完全・正確・追跡できる状態に保つ
A87: C06-02-01 | D87: ● | E87: データインテグリティ管理（ALCOA+）★ | F87: データのライフサイクル全体で、ALCOA+の原則に沿って記録の信頼性を確保する | H87: データのリスク評価、ALCOA+の確保、障害時の影響評価 | I87: 個別システムのバリデーション（C06-01-02） | J87: 当局に説明できる記録の信頼性
A88: C06-02-02 | D88: ● | E88: 監査証跡・電子署名★ | F88: 監査証跡と電子署名の要件を設計し、監査証跡を定期的に確認する | H88: 監査証跡、電子署名、確認の手順 | I88: アクセス権の付与（C05-02-02） | J88: 誰がいつ何をしたか追える記録
A89: C06-02-03 | D89: ● | E89: 記録の保存・アーカイブ★ | F89: GxPの電子記録を保存期間の間、読める状態で保存し、システムの廃止時に移行・アーカイブする | H89: 保存期間、アーカイブ、廃止時のデータ移行 | I89: 日々のバックアップ（C03-03-02） | J89: システムがなくなっても読める記録
A90: C06-03 | C90: ● | E90: データ管理 | F90: マスタデータとデータの定義・品質を管理し、データ・分析の基盤を提供する
A91: C06-03-01 | D91: ● | E91: マスタデータ管理 | F91: 全社で共通に使うマスタデータの定義と正本を管理する | H91: マスタの定義、正本、品質 | I91: 個別システムのデータ設計（C02-02-02） | J91: 一つに定まったマスタ
A92: C06-03-02 | D92: ● | E92: データ品質・データカタログ | F92: データの定義・所在・責任者をカタログにまとめ、品質を測定・改善する | H92: データカタログ、データの責任者、品質の測定 | I92: マスタの維持（C06-03-01） | J92: 探せて信頼できるデータ
A93: C06-03-03 | D93: ● | E93: データ・分析基盤 | F93: データを集約して分析・可視化・AI活用に使える基盤を提供する | H93: データ基盤、BI、分析環境 | I93: 業務システムの開発（C02-03-01） | J93: すぐに使える分析用のデータ
A94: C06-04 | C94: ● | E94: 個人情報・データ保護 | F94: 個人情報を法令に沿って取り扱い、情報の分類と持出しを管理する
A95: C06-04-01 | D95: ● | E95: 個人情報保護 | F95: 被験者・患者・従業員などの個人情報の取扱いを台帳で管理し、漏えい等の報告に対応する | H95: 取扱台帳、安全管理措置、漏えい等の報告 | I95: サイバー攻撃への技術的な対応（C05-03-03） | J95: 法令に沿って守られた個人情報
A96: C06-04-02 | D96: ● | E96: 情報の分類・持出し管理 | F96: 情報を機密度で分類し、持出し・共有・外部送信を管理する | H96: 情報の分類、持出しの管理、DLP | I96: コラボレーション環境の提供（C04-03-02） | J96: 機密度に応じて守られた情報
A97: C07 | B97: ● | E97: IT組織・ソーシング基盤 | F97: 内製と外部委託の組み合わせを決め、委託先とIT人材を管理し、IT文書とナレッジを蓄積する能力 | G97: 支援
A98: C07-01 | C98: ● | E98: ITソーシング・ベンダー管理★ | F98: 内製と外部委託の方針を決め、委託先を選定・契約し、評価・監督する
A99: C07-01-01 | D99: ● | E99: ソーシング方針（内製・委託）★ | F99: どの業務・技術を社内に持ち、どこを委託・SaaSにするかを決める | H99: 内製・委託の判断基準、コア技術の特定 | I99: 個別案件の委託先の選定（C07-01-02） | J99: ベンダーに依存しすぎない体制
A100: C07-01-02 | D100: ● | E100: 委託先の選定・契約★ | F100: 委託先を比較して選び、請負・準委任などの契約形態と発注内容を明示して契約する | H100: RFP、見積比較、契約形態、発注内容の明示 | I100: 委託先の作業の監督（C02-01-02） | J100: 公正で責任の明確な委託
...

Sheet ケイパビリティレベル
A1: ケイパビリティの成熟度レベル（L2ごとの定義）
A2: 対象：日本の製薬会社（研究開発型。GxP規制下のコンピュータ化システムを持ち、IT機能は内製と外部委託を併用）／日本の規制・法令基準（GMP省令・ER/ES指針・コンピュータ化システム適正管理ガイドライン・個人情報保護法・金商法〔J-SOX〕・取適法ほか）。評価の対象はL2。規制上の最低水準：GxP・法令（GMP省令・ER/ES指針・金商法〔J-SOX〕・個人情報保護法・取適法など）が関わるL2はレベル3が事実上の最低水準。
A3: レベル | B3: 名称 | C3: 共通定義
A4: 1 | B4: 初期 | C4: 属人的・場当たり的。成果が個人に依存し、再現できない
A5: 2 | B5: 管理された | C5: 案件・システムごとに計画・管理され、再現できる。ただし方法は案件・部門・委託先で異なる
A6: 3 | B6: 定義された | C6: 全社標準のプロセス・役割・データ定義があり、一貫して運用される
A7: 4 | B7: 定量的に管理された | C7: 指標で成果・品質を測定し、データに基づいて管理・予測する
A8: 5 | B8: 最適化された | C8: 継続的な改善と先進的な手法により、変化に先回りし、先進的な水準にある
A10: L2 ID | B10: ケイパビリティL1 | C10: ケイパビリティL2 | D10: 規制上の最低水準 | E10: レベル1 初期 | F10: レベル2 管理された | G10: レベル3 定義された | H10: レベル4 定量的に管理された | I10: レベル5 最適化された
A11: C01-01 | B11: IT戦略・ガバナンス | C11: IT戦略・DX企画 | D11: — | E11: ITの計画が年度予算の積み上げで、事業戦略との関係が説明できない | F11: 重点システムについて中期の計画を立てる | G11: 事業戦略とそろえたIT戦略・ロードマップを全社共通の方法で策定し、毎年見直す | H11: IT施策の事業への効果を指標で測定し、戦略に反映する | I11: 事業部門と一体でデジタルによる事業の変革を先導する
A12: C01-02 | C12: エンタープライズアーキテクチャ | D12: — | E12: システムの全体像を誰も把握していない | F12: 主要システムの構成図と一覧を部門ごとに持つ | G12: 全社のアプリケーション台帳・技術標準・将来像を持ち、案件を標準に照らして審査する | H12: 重複・老朽化・標準からの逸脱を指標で監視する | I12: アーキテクチャが事業の変化に先回りして組み替えられる
A13: C01-03 | C13: ITポートフォリオ・需要管理 | D13: — | E13: 声の大きい部門の要求から着手する | F13: 案件ごとに稟議で投資を判断する | G13: 全社共通の受付窓口と評価基準で、案件を比較して優先順位を決める | H13: 投資の効果を事後に検証し、評価基準を改善する | I13: ポートフォリオ全体の価値とリスクを最適化し続ける
A14: C01-04 | C14: ITガバナンス・リスク管理★ | D14: レベル3（GMP省令・コンピュータ化システム適正管理ガイドライン・金商法） | E14: IT規程がなく、担当者の判断で作業する | F14: IT規程はあるが、手順書の整備と運用が部門・委託先ごとに異なる | G14: IT規程・標準手順書・IT全般統制を全社標準で整備し、一貫して運用する | H14: 統制の不備・逸脱・リスクを指標で監視し、早期に是正する | I14: リスクの変化に先回りして、統制と手順を見直す
A15: C01-05 | C15: IT財務管理 | D15: — | E15: IT費用の全体を把握していない | F15: IT部門の予算と実績を年度で管理する | G15: 案件・サービス別に予算と実績を管理し、部門へ配賦する | H15: 総保有コストと単価を指標で管理し、比較する | I15: 費用とサービスの価値を結び付けて投資配分を最適化する
A16: C02-01 | B16: ソリューション開発・導入 | C16: プロジェクト管理★ | D16: — | E16: 計画がなく、委託先に任せきりで進捗が分からない | F16: 案件ごとに計画を立て、委託先から報告を受ける | G16: 全社標準のプロジェクト管理と委託先の監督の方法で、請負・準委任の区別を守って管理する | H16: 品質・進捗・コストの実績を指標で管理し、予測する | I16: 内製と委託を組み合わせ、変化に強い進め方を選べる
A17: C02-02 | C17: 要件定義・設計 | D17: レベル3（GMP省令・コンピュータ化システム適正管理ガイドライン） | E17: 要件が口頭や会議のメモだけで決まる | F17: 案件ごとに要件定義書を作るが、形式と粒度がばらばら | G17: 全社標準のURS・設計書の様式で、要求から設計まで追跡できる | H17: 要件の変更・漏れを指標で管理する | I17: 利用者と短い周期で要求を確かめながら設計する
A18: C02-03 | C18: 開発・構成 | D18: — | E18: 個人の書き方で開発し、ソースや設定の所在が分からない | F18: 案件ごとにソースと設定を管理する | G18: 全社標準のリポジトリ・コーディング規約・設定の記録で、版を管理する | H18: 品質指標（不具合密度・レビューの指摘）で管理する | I18: 自動化されたパイプラインで、速く安全に変更できる
A19: C02-04 | C19: テスト・リリース | D19: レベル3（GMP省令・コンピュータ化システム適正管理ガイドライン） | E19: テストが担当者任せで、記録が残らない | F19: 案件ごとにテストを計画し、結果を記録する | G19: 全社標準のテスト・移行・リリースの手順で、判定基準を満たしてから本番に出す | H19: 不具合の流出・リリース後の障害を指標で管理する | I19: テストと配備が自動化され、小さく頻繁にリリースできる
A20: C03-01 | B20: ITサービス管理・運用 | C20: サービスカタログ・サービスレベル管理 | D20: — | E20: 提供するサービスの範囲と水準が決まっていない | F20: 主要なシステムについて運用時間・連絡先を決める | G20: 全社のサービスカタログとSLAを持ち、実績を定期的に報告する | H20: SLAの実績を指標で管理し、改善につなげる | I20: 利用者の体験を測り、サービスを先回りして改善する
A21: C03-02 | C21: サービスデスク・要求実現 | D21: — | E21: 問合せ先がシステムごとに異なり、記録が残らない | F21: 主要な窓口を決めて問合せを記録する | G21: 全社で一つの窓口とカタログからの申請で、受付から完了まで記録する | H21: 解決までの時間・一次解決率を指標で管理する | I21: セルフサービスと自動化で、待たずに解決する
A22: C03-03 | C22: IT運用・監視 | D22: レベル3（GMP省令〔バックアップ〕・金商法） | E22: 障害が利用者からの連絡で分かる | F22: 主要なシステムを監視し、バックアップを取る | G22: 全社標準の監視・ジョブ・バックアップと復元テストの手順で運用する | H22: 稼働率・容量の傾向を指標で管理し、予測する | I22: 異常を予兆で検知し、自動で回復する
A23: C03-04 | C23: インシデント・問題管理 | D23: レベル3（GMP省令） | E23: 障害のたびに担当者が個別に対応し、記録が残らない | F23: インシデントを記録し、重大な障害は報告する | G23: 全社標準のインシデント・問題管理とIT事業継続計画で対応し、GxPへの影響を評価する | H23: 復旧時間・再発件数を指標で管理する | I23: 傾向の分析で障害を未然に防ぐ
A24: C03-05 | C24: 変更・構成管理★ | D24: レベル3（GMP省令・コンピュータ化システム適正管理ガイドライン・金商法） | E24: 本番環境を担当者が承認なしに変更する | F24: 変更を申請・承認するが、影響評価と構成情報が不十分 | G24: 全社標準の変更管理で、GxP・統制への影響を評価して承認し、構成情報を最新に保つ | H24: 変更による障害・緊急変更の割合を指標で管理する | I24: 自動化された検証で、安全な変更を速く行う
A25: C04-01 | B25: ITプラットフォーム | C25: クラウド・データセンター | D25: — | E25: サーバーやクラウドを部門が個別に用意する | F25: IT部門が基盤を用意するが、構成が案件ごとに異なる | G25: 全社標準の構成で、クラウドとサーバーを提供・運用する | H25: 利用率・費用・保守期限を指標で管理する | I25: 需要に応じて自動で拡張・最適化される
A26: C04-02 | C26: ネットワーク | D26: — | E26: 拠点ごとにネットワークを構築し、全体の構成が分からない | F26: 主要な拠点のネットワークを管理する | G26: 全社標準の構成で拠点と外部の接続を管理する | H26: 通信の品質・障害を指標で管理する | I26: 場所に依存しない安全な接続（ゼロトラスト）を実現する
A27: C04-03 | C27: エンドユーザー環境 | D27: — | E27: 端末を利用者が個別に設定する | F27: 端末の設定と配布を手順化する | G27: 全社標準の構成と管理ツールで、端末とコラボレーション環境を提供する | H27: 更新の適用率・問合せ件数を指標で管理する | I27: 利用者が自分で準備でき、どこでも同じ環境で働ける
A28: C04-04 | C28: IT資産・ライセンス管理 | D28: — | E28: 資産とライセンスの台帳がない | F28: 資産台帳を持つが、所在・利用者が最新でない | G28: 全社の台帳で資産とライセンス・SaaSを管理し、定期的に棚卸しする | H28: 利用率・過不足・保守期限を指標で管理する | I28: 利用データに応じてライセンスを自動で最適化する
A29: C05-01 | B29: サイバーセキュリティ | C29: セキュリティガバナンス | D29: レベル3（個人情報保護法〔安全管理措置〕） | E29: セキュリティの方針がない | F29: 方針はあるが、リスク評価と教育が年1回の形式にとどまる | G29: 全社標準の方針・リスク評価・教育で、委託先を含めて管理する | H29: リスクと訓練の結果を指標で管理する | I29: 脅威の変化に先回りして対策を組み替える
A30: C05-02 | C30: ID・アクセス管理★ | D30: レベル3（GMP省令・ER/ES指針・金商法） | E30: IDを共有し、退職者のIDが残る | F30: システムごとに申請書で権限を付与する | G30: 人事と連携したID管理と、職務分掌に沿った権限付与・定期棚卸を全社標準で行う | H30: 不要な権限・棚卸の指摘を指標で管理する | I30: 権限の付与と見直しを自動化し、常に最小の権限に保つ
A31: C05-03 | C31: セキュリティ運用 | D31: レベル3（個人情報保護法〔漏えい等の報告〕） | E31: 攻撃や脆弱性に気づかない | F31: 主要な機器のパッチを当て、ウイルス対策を行う | G31: 全社標準の脆弱性管理・監視・CSIRTの手順で対応する | H31: 検知・対応の時間と未対応の脆弱性を指標で管理する | I31: 脅威情報を使って攻撃を先回りして防ぐ
A32: C06-01 | B32: データ・GxPコンプライアンス | C32: GxPシステム管理（CSV）★ | D32: レベル3（GMP省令・コンピュータ化システム適正管理ガイドライン） | E32: GxPに該当するシステムを把握していない | F32: 案件ごとにバリデーション文書を作るが、方法と量がばらばら | G32: 全社標準のGxP該当性評価と、リスクに応じたバリデーション・定期レビューを行う | H32: バリデーションの工数・指摘・逸脱を指標で管理する | I32: 重要な機能に集中した合理的な保証（CSA）で、速く確実に使い始められる
A33: C06-02 | C33: データインテグリティ★ | D33: レベル3（GMP省令・ER/ES指針） | E33: 紙と電子の記録が混在し、元の記録が分からない | F33: システムごとに監査証跡と保存を設定する | G33: 全社標準のデータインテグリティの方針で、監査証跡・電子署名・保存・アーカイブを管理する | H33: データインテグリティの指摘・監査証跡の確認結果を指標で管理する | I33: データのライフサイクル全体でリスクを先回りして管理する
A34: C06-03 | C34: データ管理 | D34: — | E34: マスタとデータの定義がシステムごとに異なる | F34: 主要なマスタを部門ごとに管理する | G34: 全社標準のマスタの正本・データカタログ・品質の基準で管理する | H34: データの品質を指標で管理し、改善する | I34: データを全社の資産として活用し、新しい価値を生む
A35: C06-04 | C35: 個人情報・データ保護 | D35: レベル3（個人情報保護法） | E35: どのシステムで個人情報を扱うか分からない | F35: 主要なシステムについて個人情報の取扱いを確認する | G35: 全社の取扱台帳と情報の分類で管理し、漏えい等の報告の手順を持つ | H35: 持出し・誤送信などの件数を指標で管理する | I35: プライバシーを設計段階から組み込む（プライバシー・バイ・デザイン）
A36: C07-01 | B36: IT組織・ソーシング基盤 | C36: ITソーシング・ベンダー管理★ | D36: レベル3（取適法・派遣法・GMP省令〔供給者管理〕） | E36: 特定のベンダーに任せきりで、比較も評価もしない | F36: 案件ごとに見積を比較し、契約書を結ぶ | G36: 全社標準のソーシング方針・選定・契約・評価の手順で、請負・準委任の区別と取適法を守る | H36: 委託先の品質・SLA・コストを指標で比較・管理する | I36: 戦略的なパートナーと、内製の力を保ちながら共同で改善する
A37: C07-02 | C37: IT人材・組織★ | D37: レベル3（GMP省令〔教育訓練〕） | E37: ITの役割とスキルが定義されておらず、ベンダー頼み | F37: 主要な役割について担当者を育成する | G37: 全社標準の役割定義・スキル評価・教育記録で、内製すべき力を計画的に育てる | H37: スキルの充足・育成の効果を指標で管理する | I37: 必要な人材を先回りして育成・採用し、内製の力で変化に対応する
A38: C07-03 | C38: ITナレッジ・文書管理 | D38: — | E38: 手順書が個人のPCにあり、最新版が分からない | F38: システムごとに手順書を管理する | G38: 全社標準の文書管理とナレッジの仕組みで、承認・版・共有を管理する | H38: ナレッジの利用率・更新の状況を指標で管理する | I38: ナレッジが自動で集まり、誰でも使える

Sheet VS×ケイパビリティ関係
A1: VS×ケイパビリティ関係（正本：VS L4 × ケイパビリティL3）
A2: 1行1関係。区分は「主」（そのL4の中核）か「支援」（下支え）。マトリクスはこのシートから数式で集計する。関係の追加・変更はこのシートで行う。灰色の列は数式（編集しない）。
A3: VS L4 ID | B3: VS L4 | C3: ケイパビリティL3 ID | D3: ケイパビリティL3 | E3: 区分 | F3: VS L3 ID | G3: ケイパビリティL2 ID
A4: 01-01-01 | B4: 事業戦略・DX方針の把握とIT課題の整理 | C4: C01-01-01 | D4: =IFERROR(INDEX(ケイパビリティマップ!$E:$E,MATCH(C4,ケイパビリティマップ!$A:$A,0)),"（IDなし）") | E4: 主 | F4: =LEFT(A4,5) | G4: =LEFT(C4,6)
A5: 01-01-01 | B5: 事業戦略・DX方針の把握とIT課題の整理 | C5: C01-01-02 | D5: =IFERROR(INDEX(ケイパビリティマップ!$E:$E,MATCH(C5,ケイパビリティマップ!$A:$A,0)),"（IDなし）") | E5: 支援 | F5: =LEFT(A5,5) | G5: =LEFT(C5,6)
A6: 01-01-01 | B6: 事業戦略・DX方針の把握とIT課題の整理 | C6: C01-02-03 | D6: =IFERROR(INDEX(ケイパビリティマップ!$E:$E,MATCH(C6,ケイパビリティマップ!$A:$A,0)),"（IDなし）") | E6: 支援 | F6: =LEFT(A6,5) | G6: =LEFT(C6,6)
A7: 01-01-02 | B7: IT戦略・ロードマップの策定 | C7: C01-01-01 | D7: =IFERROR(INDEX(ケイパビリティマップ!$E:$E,MATCH(C7,ケイパビリティマップ!$A:$A,0)),"（IDなし）") | E7: 主 | F7: =LEFT(A7,5) | G7: =LEFT(C7,6)
A8: 01-01-02 | B8: IT戦略・ロードマップの策定 | C8: C01-01-02 | D8: =IFERROR(INDEX(ケイパビリティマップ!$E:$E,MATCH(C8,ケイパビリティマップ!$A:$A,0)),"（IDなし）") | E8: 主 | F8: =LEFT(A8,5) | G8: =LEFT(C8,6)
A9: 01-01-02 | B9: IT戦略・ロードマップの策定 | C9: C07-01-01 | D9: =IFERROR(INDEX(ケイパビリティマップ!$E:$E,MATCH(C9,ケイパビリティマップ!$A:$A,0)),"（IDなし）") | E9: 支援 | F9: =LEFT(A9,5) | G9: =LEFT(C9,6)
A10: 01-01-03 | B10: 現状・将来アーキテクチャの策定（業務・アプリケーション・データ・技術） | C10: C01-02-01 | D10: =IFERROR(INDEX(ケイパビリティマップ!$E:$E,MATCH(C10,ケイパビリティマップ!$A:$A,0)),"（IDなし）") | E10: 主 | F10: =LEFT(A10,5) | G10: =LEFT(C10,6)
A11: 01-01-03 | B11: 現状・将来アーキテクチャの策定（業務・アプリケーション・データ・技術） | C11: C01-02-03 | D11: =IFERROR(INDEX(ケイパビリティマップ!$E:$E,MATCH(C11,ケイパビリティマップ!$A:$A,0)),"（IDなし）") | E11: 支援 | F11: =LEFT(A11,5) | G11: =LEFT(C11,6)
A12: 01-01-03 | B12: 現状・将来アーキテクチャの策定（業務・アプリケーション・データ・技術） | C12: C06-03-02 | D12: =IFERROR(INDEX(ケイパビリティマップ!$E:$E,MATCH(C12,ケイパビリティマップ!$A:$A,0)),"（IDなし）") | E12: 支援 | F12: =LEFT(A12,5) | G12: =LEFT(C12,6)
A13: 01-01-04 | B13: 技術標準の策定（クラウド・セキュリティ・連携の標準） | C13: C01-02-02 | D13: =IFERROR(INDEX(ケイパビリティマップ!$E:$E,MATCH(C13,ケイパビリティマップ!$A:$A,0)),"（IDなし）") | E13: 主 | F13: =LEFT(A13,5) | G13: =LEFT(C13,6)
A14: 01-01-04 | B14: 技術標準の策定（クラウド・セキュリティ・連携の標準） | C14: C05-01-01 | D14: =IFERROR(INDEX(ケイパビリティマップ!$E:$E,MATCH(C14,ケイパビリティマップ!$A:$A,0)),"（IDなし）") | E14: 支援 | F14: =LEFT(A14,5) | G14: =LEFT(C14,6)
A15: 01-01-05 | B15: ★IT規程・標準手順書の制定（CSV・IT全般統制・セキュリティ） | C15: C01-04-01 | D15: =IFERROR(INDEX(ケイパビリティマップ!$E:$E,MATCH(C15,ケイパビリティマップ!$A:$A,0)),"（IDなし）") | E15: 主 | F15: =LEFT(A15,5) | G15: =LEFT(C15,6)
... A141: 04-04-06 | B141: 改善の提案（次の投資要求へ） | C141: C01-04-02 | D141: =IFERROR(INDEX(ケイパビリティマップ!$E:$E,MATCH(C141,ケイパビリティマップ!$A:$A,0)),"（IDなし）") | E141: 支援 | F141: =LEFT(A141,5) | G141: =LEFT(C141,6)
D142: =IF(C142="","",IFERROR(INDEX(ケイパビリティマップ!$E:$E,MATCH(C142,ケイパビリティマップ!$A:$A,0)),"（IDなし）")) | F142: =IF(A142="","",LEFT(A142,5)) | G142: =IF(C142="","",LEFT(C142,6))
D143: =IF(C143="","",IFERROR(INDEX(ケイパビリティマップ!$E:$E,MATCH(C143,ケイパビリティマップ!$A:$A,0)),"（IDなし）")) | F143: =IF(A143="","",LEFT(A143,5)) | G143: =IF(C143="","",LEFT(C143,6))
D144: =IF(C144="","",IFERROR(INDEX(ケイパビリティマップ!$E:$E,MATCH(C144,ケイパビリティマップ!$A:$A,0)),"（IDなし）")) | F144: =IF(A144="","",LEFT(A144,5)) | G144: =IF(C144="","",LEFT(C144,6))
D145: =IF(C145="","",IFERROR(INDEX(ケイパビリティマップ!$E:$E,MATCH(C145,ケイパビリティマップ!$A:$A,0)),"（IDなし）")) | F145: =IF(A145="","",LEFT(A145,5)) | G145: =IF(C145="","",LEFT(C145,6))
D146: =IF(C146="","",IFERROR(INDEX(ケイパビリティマップ!$E:$E,MATCH(C146,ケイパビリティマップ!$A:$A,0)),"（IDなし）")) | F146: =IF(A146="","",LEFT(A146,5)) | G146: =IF(C146="","",LEFT(C146,6))
D147: =IF(C147="","",IFERROR(INDEX(ケイパビリティマップ!$E:$E,MATCH(C147,ケイパビリティマップ!$A:$A,0)),"（IDなし）")) | F147: =IF(A147="","",LEFT(A147,5)) | G147: =IF(C147="","",LEFT(C147,6))
D148: =IF(C148="","",IFERROR(INDEX(ケイパビリティマップ!$E:$E,MATCH(C148,ケイパビリティマップ!$A:$A,0)),"（IDなし）")) | F148: =IF(A148="","",LEFT(A148,5)) | G148: =IF(C148="","",LEFT(C148,6))
D149: =IF(C149="","",IFERROR(INDEX(ケイパビリティマップ!$E:$E,MATCH(C149,ケイパビリティマップ!$A:$A,0)),"（IDなし）")) | F149: =IF(A149="","",LEFT(A149,5)) | G149: =IF(C149="","",LEFT(C149,6))
D150: =IF(C150="","",IFERROR(INDEX(ケイパビリティマップ!$E:$E,MATCH(C150,ケイパビリティマップ!$A:$A,0)),"（IDなし）")) | F150: =IF(A150="","",LEFT(A150,5)) | G150: =IF(C150="","",LEFT(C150,6))
D151: =IF(C151="","",IFERROR(INDEX(ケイパビリティマップ!$E:$E,MATCH(C151,ケイパビリティマップ!$A:$A,0)),"（IDなし）")) | F151: =IF(A151="","",LEFT(A151,5)) | G151: =IF(C151="","",LEFT(C151,6))
D152: =IF(C152="","",IFERROR(INDEX(ケイパビリティマップ!$E:$E,MATCH(C152,ケイパビリティマップ!$A:$A,0)),"（IDなし）")) | F152: =IF(A152="","",LEFT(A152,5)) | G152: =IF(C152="","",LEFT(C152,6))
D153: =IF(C153="","",IFERROR(INDEX(ケイパビリティマップ!$E:$E,MATCH(C153,ケイパビリティマップ!$A:$A,0)),"（IDなし）")) | F153: =IF(A153="","",LEFT(A153,5)) | G153: =IF(C153="","",LEFT(C153,6))
... D341: =IF(C341="","",IFERROR(INDEX(ケイパビリティマップ!$E:$E,MATCH(C341,ケイパビリティマップ!$A:$A,0)),"（IDなし）")) | F341: =IF(A341="","",LEFT(A341,5)) | G341: =IF(C341="","",LEFT(C341,6))

Sheet VS×ケイパビリティ
A1: バリューストリーム×ケイパビリティマップ（行：バリューストリームL3 × 列：ケイパビリティL2）
A2: ●＝主（配下のL4×L3の関係に「主」が1つ以上） ○＝支援のみ 空欄＝関係なし。各セルは「VS×ケイパビリティ関係」シートから数式で集計（直接入力しない）。
A4: VS L2 | B4: L3 ID | C4: VS L3 | D4: C01 IT戦略・ガバナンス | I4: C02 ソリューション開発・導入 | M4: C03 ITサービス管理・運用 | R4: C04 ITプラットフォーム | V4: C05 サイバーセキュリティ | Y4: C06 データ・GxPコンプライアンス | AC4: C07 IT組織・ソーシング基盤 | AF4: ●の数 | AG4: ○の数
D5: C01-01 | E5: C01-02 | F5: C01-03 | G5: C01-04 | H5: C01-05 | I5: C02-01 | J5: C02-02 | K5: C02-03 | L5: C02-04 | M5: C03-01 | N5: C03-02 | O5: C03-03 | P5: C03-04 | Q5: C03-05 | R5: C04-01 | S5: C04-02 | T5: C04-03 | U5: C04-04 | V5: C05-01 | W5: C05-02 | X5: C05-03 | Y5: C06-01 | Z5: C06-02 | AA5: C06-03 | AB5: C06-04 | AC5: C07-01 | AD5: C07-02 | AE5: C07-03
D6: IT戦略・DX企画 | E6: エンタープライズアーキテクチャ | F6: ITポートフォリオ・需要管理 | G6: ITガバナンス・リスク管理★ | H6: IT財務管理 | I6: プロジェクト管理★ | J6: 要件定義・設計 | K6: 開発・構成 | L6: テスト・リリース | M6: サービスカタログ・サービスレベル管理 | N6: サービスデスク・要求実現 | O6: IT運用・監視 | P6: インシデント・問題管理 | Q6: 変更・構成管理★ | R6: クラウド・データセンター | S6: ネットワーク | T6: エンドユーザー環境 | U6: IT資産・ライセンス管理 | V6: セキュリティガバナンス | W6: ID・アクセス管理★ | X6: セキュリティ運用 | Y6: GxPシステム管理（CSV）★ | Z6: データインテグリティ★ | AA6: データ管理 | AB6: 個人情報・データ保護 | AC6: ITソーシング・ベンダー管理★ | AD6: IT人材・組織★ | AE6: ITナレッジ・文書管理
A7: 01 戦略・ポートフォリオ（S2P） | B7: 01-01 | C7: IT戦略・アーキテクチャの策定 | D7: =IF(COUNTIFS('VS×ケイパビリティ関係'!$F$4:$F$341,$B7,'VS×ケイパビリティ関係'!$G$4:$G$341,D$5,'VS×ケイパビリティ関係'!$E$4:$E$341,"主")>0,"●",IF(COUNTIFS('VS×ケイパビリティ関係'!$F$4:$F$341,$B7,'VS×ケイパビリティ関係'!$G$4:$G$341,D$5,'VS×ケイパビリティ関係'!$E$4:$E$341,"支援")>0,"○","")) | E7: =IF(COUNTIFS('VS×ケイパビリティ関係'!$F$4:$F$341,$B7,'VS×ケイパビリティ関係'!$G$4:$G$341,E$5,'VS×ケイパビリティ関係'!$E$4:$E$341,"主")>0,"●",IF(COUNTIFS('VS×ケイパビリティ関係'!$F$4:$F$341,$B7,'VS×ケイパビリティ関係'!$G$4:$G$341,E$5,'VS×ケイパビリティ関係'!$E$4:$E$341,"支援")>0,"○","")) | F7: =IF(COUNTIFS('VS×ケイパビリティ関係'!$F$4:$F$341,$B7,'VS×ケイパビリティ関係'!$G$4:$G$341,F$5,'VS×ケイパビリティ関係'!$E$4:$E$341,"主")>0,"●",IF(COUNTIFS('VS×ケイパビリティ関係'!$F$4:$F$341,$B7,'VS×ケイパビリティ関係'!$G$4:$G$341,F$5,'VS×ケイパビリティ関係'!$E$4:$E$341,"支援")>0,"○","")) | G7: =IF(COUNTIFS('VS×ケイパビリティ関係'!$F$4:$F$341,$B7,'VS×ケイパビリティ関係'!$G$4:$G$341,G$5,'VS×ケイパビリティ関係'!$E$4:$E$341,"主")>0,"●",IF(COUNTIFS('VS×ケイパビリティ関係'!$F$4:$F$341,$B7,'VS×ケイパビリティ関係'!$G$4:$G$341,G$5,'VS×ケイパビリティ関係'!$E$4:$E$341,"支援")>0,"○","")) | H7: =IF(COUNTIFS('VS×ケイパビリティ関係'!$F$4:$F$341,$B7,'VS×ケイパビリティ関係'!$G$4:$G$341,H$5,'VS×ケイパビリティ関係'!$E$4:$E$341,"主")>0,"●",IF(COUNTIFS('VS×ケイパビリティ関係'!$F$4:$F$341,$B7,'VS×ケイパビリティ関係'!$G$4:$G$341,H$5,'VS×ケイパビリティ関係'!$E$4:$E$341,"支援")>0,"○","")) | I7: =IF(COUNTIFS('VS×ケイパビリティ関係'!$F$4:$F$341,$B7,'VS×ケイパビリティ関係'!$G$4:$G$341,I$5,'VS×ケイパビリティ関係'!$E$4:$E$341,"主")>0,"●",IF(COUNTIFS('VS×ケイパビリティ関係'!$F$4:$F$341,$B7,'VS×ケイパビリティ関係'!$G$4:$G$341,I$5,'VS×ケイパビリティ関係'!$E$4:$E$341,"支援")>0,"○","")) | J7: =IF(COUNTIFS('VS×ケイパビリティ関係'!$F$4:$F$341,$B7,'VS×ケイパビリティ関係'!$G$4:$G$341,J$5,'VS×ケイパビリティ関係'!$E$4:$E$341,"主")>0,"●",IF(COUNTIFS('VS×ケイパビリティ関係'!$F$4:$F$341,$B7,'VS×ケイパビリティ関係'!$G$4:$G$341,J$5,'VS×ケイパビリティ関係'!$E$4:$E$341,"支援")>0,"○","")) | K7: =IF(COUNTIFS('VS×ケイパビリティ関係'!$F$4:$F$341,$B7,'VS×ケイパビリティ関係'!$G$4:$G$341,K$5,'VS×ケイパビリティ関係'!$E$4:$E$341,"主")>0,"●",IF(COUNTIFS('VS×ケイパビリティ関係'!$F$4:$F$341,$B7,'VS×ケイパビリティ関係'!$G$4:$G$341,K$5,'VS×ケイパビリティ関係'!$E$4:$E$341,"支援")>0,"○","")) | ... AE7: =IF(COUNTIFS('VS×ケイパビリティ関係'!$F$4:$F$341,$B7,'VS×ケイパビリティ関係'!$G$4:$G$341,AE$5,'VS×ケイパビリティ関係'!$E$4:$E$341,"主")>0,"●",IF(COUNTIFS('VS×ケイパビリティ関係'!$F$4:$F$341,$B7,'VS×ケイパビリティ関係'!$G$4:$G$341,AE$5,'VS×ケイパビリティ関係'!$E$4:$E$341,"支援")>0,"○","")) | AF7: =COUNTIF(D7:AE7,"●") | AG7: =COUNTIF(D7:AE7,"○")
B8: 01-02 | C8: 需要管理・構想 | D8: =IF(COUNTIFS('VS×ケイパビリティ関係'!$F$4:$F$341,$B8,'VS×ケイパビリティ関係'!$G$4:$G$341,D$5,'VS×ケイパビリティ関係'!$E$4:$E$341,"主")>0,"●",IF(COUNTIFS('VS×ケイパビリティ関係'!$F$4:$F$341,$B8,'VS×ケイパビリティ関係'!$G$4:$G$341,D$5,'VS×ケイパビリティ関係'!$E$4:$E$341,"支援")>0,"○","")) | E8: =IF(COUNTIFS('VS×ケイパビリティ関係'!$F$4:$F$341,$B8,'VS×ケイパビリティ関係'!$G$4:$G$341,E$5,'VS×ケイパビリティ関係'!$E$4:$E$341,"主")>0,"●",IF(COUNTIFS('VS×ケイパビリティ関係'!$F$4:$F$341,$B8,'VS×ケイパビリティ関係'!$G$4:$G$341,E$5,'VS×ケイパビリティ関係'!$E$4:$E$341,"支援")>0,"○","")) | F8: =IF(COUNTIFS('VS×ケイパビリティ関係'!$F$4:$F$341,$B8,'VS×ケイパビリティ関係'!$G$4:$G$341,F$5,'VS×ケイパビリティ関係'!$E$4:$E$341,"主")>0,"●",IF(COUNTIFS('VS×ケイパビリティ関係'!$F$4:$F$341,$B8,'VS×ケイパビリティ関係'!$G$4:$G$341,F$5,'VS×ケイパビリティ関係'!$E$4:$E$341,"支援")>0,"○","")) | G8: =IF(COUNTIFS('VS×ケイパビリティ関係'!$F$4:$F$341,$B8,'VS×ケイパビリティ関係'!$G$4:$G$341,G$5,'VS×ケイパビリティ関係'!$E$4:$E$341,"主")>0,"●",IF(COUNTIFS('VS×ケイパビリティ関係'!$F$4:$F$341,$B8,'VS×ケイパビリティ関係'!$G$4:$G$341,G$5,'VS×ケイパビリティ関係'!$E$4:$E$341,"支援")>0,"○","")) | H8: =IF(COUNTIFS('VS×ケイパビリティ関係'!$F$4:$F$341,$B8,'VS×ケイパビリティ関係'!$G$4:$G$341,H$5,'VS×ケイパビリティ関係'!$E$4:$E$341,"主")>0,"●",IF(COUNTIFS('VS×ケイパビリティ関係'!$F$4:$F$341,$B8,'VS×ケイパビリティ関係'!$G$4:$G$341,H$5,'VS×ケイパビリティ関係'!$E$4:$E$341,"支援")>0,"○","")) | I8: =IF(COUNTIFS('VS×ケイパビリティ関係'!$F$4:$F$341,$B8,'VS×ケイパビリティ関係'!$G$4:$G$341,I$5,'VS×ケイパビリティ関係'!$E$4:$E$341,"主")>0,"●",IF(COUNTIFS('VS×ケイパビリティ関係'!$F$4:$F$341,$B8,'VS×ケイパビリティ関係'!$G$4:$G$341,I$5,'VS×ケイパビリティ関係'!$E$4:$E$341,"支援")>0,"○","")) | J8: =IF(COUNTIFS('VS×ケイパビリティ関係'!$F$4:$F$341,$B8,'VS×ケイパビリティ関係'!$G$4:$G$341,J$5,'VS×ケイパビリティ関係'!$E$4:$E$341,"主")>0,"●",IF(COUNTIFS('VS×ケイパビリティ関係'!$F$4:$F$341,$B8,'VS×ケイパビリティ関係'!$G$4:$G$341,J$5,'VS×ケイパビリティ関係'!$E$4:$E$341,"支援")>0,"○","")) | K8: =IF(COUNTIFS('VS×ケイパビリティ関係'!$F$4:$F$341,$B8,'VS×ケイパビリティ関係'!$G$4:$G$341,K$5,'VS×ケイパビリティ関係'!$E$4:$E$341,"主")>0,"●",IF(COUNTIFS('VS×ケイパビリティ関係'!$F$4:$F$341,$B8,'VS×ケイパビリティ関係'!$G$4:$G$341,K$5,'VS×ケイパビリティ関係'!$E$4:$E$341,"支援")>0,"○","")) | ... AE8: =IF(COUNTIFS('VS×ケイパビリティ関係'!$F$4:$F$341,$B8,'VS×ケイパビリティ関係'!$G$4:$G$341,AE$5,'VS×ケイパビリティ関係'!$E$4:$E$341,"主")>0,"●",IF(COUNTIFS('VS×ケイパビリティ関係'!$F$4:$F$341,$B8,'VS×ケイパビリティ関係'!$G$4:$G$341,AE$5,'VS×ケイパビリティ関係'!$E$4:$E$341,"支援")>0,"○","")) | AF8: =COUNTIF(D8:AE8,"●") | AG8: =COUNTIF(D8:AE8,"○")
B9: 01-03 | C9: ポートフォリオ・投資判断 | D9: =IF(COUNTIFS('VS×ケイパビリティ関係'!$F$4:$F$341,$B9,'VS×ケイパビリティ関係'!$G$4:$G$341,D$5,'VS×ケイパビリティ関係'!$E$4:$E$341,"主")>0,"●",IF(COUNTIFS('VS×ケイパビリティ関係'!$F$4:$F$341,$B9,'VS×ケイパビリティ関係'!$G$4:$G$341,D$5,'VS×ケイパビリティ関係'!$E$4:$E$341,"支援")>0,"○","")) | E9: =IF(COUNTIFS('VS×ケイパビリティ関係'!$F$4:$F$341,$B9,'VS×ケイパビリティ関係'!$G$4:$G$341,E$5,'VS×ケイパビリティ関係'!$E$4:$E$341,"主")>0,"●",IF(COUNTIFS('VS×ケイパビリティ関係'!$F$4:$F$341,$B9,'VS×ケイパビリティ関係'!$G$4:$G$341,E$5,'VS×ケイパビリティ関係'!$E$4:$E$341,"支援")>0,"○","")) | F9: =IF(COUNTIFS('VS×ケイパビリティ関係'!$F$4:$F$341,$B9,'VS×ケイパビリティ関係'!$G$4:$G$341,F$5,'VS×ケイパビリティ関係'!$E$4:$E$341,"主")>0,"●",IF(COUNTIFS('VS×ケイパビリティ関係'!$F$4:$F$341,$B9,'VS×ケイパビリティ関係'!$G$4:$G$341,F$5,'VS×ケイパビリティ関係'!$E$4:$E$341,"支援")>0,"○","")) | G9: =IF(COUNTIFS('VS×ケイパビリティ関係'!$F$4:$F$341,$B9,'VS×ケイパビリティ関係'!$G$4:$G$341,G$5,'VS×ケイパビリティ関係'!$E$4:$E$341,"主")>0,"●",IF(COUNTIFS('VS×ケイパビリティ関係'!$F$4:$F$341,$B9,'VS×ケイパビリティ関係'!$G$4:$G$341,G$5,'VS×ケイパビリティ関係'!$E$4:$E$341,"支援")>0,"○","")) | H9: =IF(COUNTIFS('VS×ケイパビリティ関係'!$F$4:$F$341,$B9,'VS×ケイパビリティ関係'!$G$4:$G$341,H$5,'VS×ケイパビリティ関係'!$E$4:$E$341,"主")>0,"●",IF(COUNTIFS('VS×ケイパビリティ関係'!$F$4:$F$341,$B9,'VS×ケイパビリティ関係'!$G$4:$G$341,H$5,'VS×ケイパビリティ関係'!$E$4:$E$341,"支援")>0,"○","")) | I9: =IF(COUNTIFS('VS×ケイパビリティ関係'!$F$4:$F$341,$B9,'VS×ケイパビリティ関係'!$G$4:$G$341,I$5,'VS×ケイパビリティ関係'!$E$4:$E$341,"主")>0,"●",IF(COUNTIFS('VS×ケイパビリティ関係'!$F$4:$F$341,$B9,'VS×ケイパビリティ関係'!$G$4:$G$341,I$5,'VS×ケイパビリティ関係'!$E$4:$E$341,"支援")>0,"○","")) | J9: =IF(COUNTIFS('VS×ケイパビリティ関係'!$F$4:$F$341,$B9,'VS×ケイパビリティ関係'!$G$4:$G$341,J$5,'VS×ケイパビリティ関係'!$E$4:$E$341,"主")>0,"●",IF(COUNTIFS('VS×ケイパビリティ関係'!$F$4:$F$341,$B9,'VS×ケイパビリティ関係'!$G$4:$G$341,J$5,'VS×ケイパビリティ関係'!$E$4:$E$341,"支援")>0,"○","")) | K9: =IF(COUNTIFS('VS×ケイパビリティ関係'!$F$4:$F$341,$B9,'VS×ケイパビリティ関係'!$G$4:$G$341,K$5,'VS×ケイパビリティ関係'!$E$4:$E$341,"主")>0,"●",IF(COUNTIFS('VS×ケイパビリティ関係'!$F$4:$F$341,$B9,'VS×ケイパビリティ関係'!$G$4:$G$341,K$5,'VS×ケイパビリティ関係'!$E$4:$E$341,"支援")>0,"○","")) | ... AE9: =IF(COUNTIFS('VS×ケイパビリティ関係'!$F$4:$F$341,$B9,'VS×ケイパビリティ関係'!$G$4:$G$341,AE$5,'VS×ケイパビリティ関係'!$E$4:$E$341,"主")>0,"●",IF(COUNTIFS('VS×ケイパビリティ関係'!$F$4:$F$341,$B9,'VS×ケイパビリティ関係'!$G$4:$G$341,AE$5,'VS×ケイパビリティ関係'!$E$4:$E$341,"支援")>0,"○","")) | AF9: =COUNTIF(D9:AE9,"●") | AG9: =COUNTIF(D9:AE9,"○")
A10: 02 要件定義・開発・配備（R2D） | B10: 02-01 | C10: プロジェクト立上げ・委託 | D10: =IF(COUNTIFS('VS×ケイパビリティ関係'!$F$4:$F$341,$B10,'VS×ケイパビリティ関係'!$G$4:$G$341,D$5,'VS×ケイパビリティ関係'!$E$4:$E$341,"主")>0,"●",IF(COUNTIFS('VS×ケイパビリティ関係'!$F$4:$F$341,$B10,'VS×ケイパビリティ関係'!$G$4:$G$341,D$5,'VS×ケイパビリティ関係'!$E$4:$E$341,"支援")>0,"○","")) | E10: =IF(COUNTIFS('VS×ケイパビリティ関係'!$F$4:$F$341,$B10,'VS×ケイパビリティ関係'!$G$4:$G$341,E$5,'VS×ケイパビリティ関係'!$E$4:$E$341,"主")>0,"●",IF(COUNTIFS('VS×ケイパビリティ関係'!$F$4:$F$341,$B10,'VS×ケイパビリティ関係'!$G$4:$G$341,E$5,'VS×ケイパビリティ関係'!$E$4:$E$341,"支援")>0,"○","")) | F10: =IF(COUNTIFS('VS×ケイパビリティ関係'!$F$4:$F$341,$B10,'VS×ケイパビリティ関係'!$G$4:$G$341,F$5,'VS×ケイパビリティ関係'!$E$4:$E$341,"主")>0,"●",IF(COUNTIFS('VS×ケイパビリティ関係'!$F$4:$F$341,$B10,'VS×ケイパビリティ関係'!$G$4:$G$341,F$5,'VS×ケイパビリティ関係'!$E$4:$E$341,"支援")>0,"○","")) | G10: =IF(COUNTIFS('VS×ケイパビリティ関係'!$F$4:$F$341,$B10,'VS×ケイパビリティ関係'!$G$4:$G$341,G$5,'VS×ケイパビリティ関係'!$E$4:$E$341,"主")>0,"●",IF(COUNTIFS('VS×ケイパビリティ関係'!$F$4:$F$341,$B10,'VS×ケイパビリティ関係'!$G$4:$G$341,G$5,'VS×ケイパビリティ関係'!$E$4:$E$341,"支援")>0,"○","")) | H10: =IF(COUNTIFS('VS×ケイパビリティ関係'!$F$4:$F$341,$B10,'VS×ケイパビリティ関係'!$G$4:$G$341,H$5,'VS×ケイパビリティ関係'!$E$4:$E$341,"主")>0,"●",IF(COUNTIFS('VS×ケイパビリティ関係'!$F$4:$F$341,$B10,'VS×ケイパビリティ関係'!$G$4:$G$341,H$5,'VS×ケイパビリティ関係'!$E$4:$E$341,"支援")>0,"○","")) | I10: =IF(COUNTIFS('VS×ケイパビリティ関係'!$F$4:$F$341,$B10,'VS×ケイパビリティ関係'!$G$4:$G$341,I$5,'VS×ケイパビリティ関係'!$E$4:$E$341,"主")>0,"●",IF(COUNTIFS('VS×ケイパビリティ関係'!$F$4:$F$341,$B10,'VS×ケイパビリティ関係'!$G$4:$G$341,I$5,'VS×ケイパビリティ関係'!$E$4:$E$341,"支援")>0,"○","")) | J10: =IF(COUNTIFS('VS×ケイパビリティ関係'!$F$4:$F$341,$B10,'VS×ケイパビリティ関係'!$G$4:$G$341,J$5,'VS×ケイパビリティ関係'!$E$4:$E$341,"主")>0,"●",IF(COUNTIFS('VS×ケイパビリティ関係'!$F$4:$F$341,$B10,'VS×ケイパビリティ関係'!$G$4:$G$341,J$5,'VS×ケイパビリティ関係'!$E$4:$E$341,"支援")>0,"○","")) | K10: =IF(COUNTIFS('VS×ケイパビリティ関係'!$F$4:$F$341,$B10,'VS×ケイパビリティ関係'!$G$4:$G$341,K$5,'VS×ケイパビリティ関係'!$E$4:$E$341,"主")>0,"●",IF(COUNTIFS('VS×ケイパビリティ関係'!$F$4:$F$341,$B10,'VS×ケイパビリティ関係'!$G$4:$G$341,K$5,'VS×ケイパビリティ関係'!$E$4:$E$341,"支援")>0,"○","")) | ... AE10: =IF(COUNTIFS('VS×ケイパビリティ関係'!$F$4:$F$341,$B10,'VS×ケイパビリティ関係'!$G$4:$G$341,AE$5,'VS×ケイパビリティ関係'!$E$4:$E$341,"主")>0,"●",IF(COUNTIFS('VS×ケイパビリティ関係'!$F$4:$F$341,$B10,'VS×ケイパビリティ関係'!$G$4:$G$341,AE$5,'VS×ケイパビリティ関係'!$E$4:$E$341,"支援")>0,"○","")) | AF10: =COUNTIF(D10:AE10,"●") | AG10: =COUNTIF(D10:AE10,"○")
B11: 02-02 | C11: 要件定義・設計 | D11: =IF(COUNTIFS('VS×ケイパビリティ関係'!$F$4:$F$341,$B11,'VS×ケイパビリティ関係'!$G$4:$G$341,D$5,'VS×ケイパビリティ関係'!$E$4:$E$341,"主")>0,"●",IF(COUNTIFS('VS×ケイパビリティ関係'!$F$4:$F$341,$B11,'VS×ケイパビリティ関係'!$G$4:$G$341,D$5,'VS×ケイパビリティ関係'!$E$4:$E$341,"支援")>0,"○","")) | E11: =IF(COUNTIFS('VS×ケイパビリティ関係'!$F$4:$F$341,$B11,'VS×ケイパビリティ関係'!$G$4:$G$341,E$5,'VS×ケイパビリティ関係'!$E$4:$E$341,"主")>0,"●",IF(COUNTIFS('VS×ケイパビリティ関係'!$F$4:$F$341,$B11,'VS×ケイパビリティ関係'!$G$4:$G$341,E$5,'VS×ケイパビリティ関係'!$E$4:$E$341,"支援")>0,"○","")) | F11: =IF(COUNTIFS('VS×ケイパビリティ関係'!$F$4:$F$341,$B11,'VS×ケイパビリティ関係'!$G$4:$G$341,F$5,'VS×ケイパビリティ関係'!$E$4:$E$341,"主")>0,"●",IF(COUNTIFS('VS×ケイパビリティ関係'!$F$4:$F$341,$B11,'VS×ケイパビリティ関係'!$G$4:$G$341,F$5,'VS×ケイパビリティ関係'!$E$4:$E$341,"支援")>0,"○","")) | G11: =IF(COUNTIFS('VS×ケイパビリティ関係'!$F$4:$F$341,$B11,'VS×ケイパビリティ関係'!$G$4:$G$341,G$5,'VS×ケイパビリティ関係'!$E$4:$E$341,"主")>0,"●",IF(COUNTIFS('VS×ケイパビリティ関係'!$F$4:$F$341,$B11,'VS×ケイパビリティ関係'!$G$4:$G$341,G$5,'VS×ケイパビリティ関係'!$E$4:$E$341,"支援")>0,"○","")) | H11: =IF(COUNTIFS('VS×ケイパビリティ関係'!$F$4:$F$341,$B11,'VS×ケイパビリティ関係'!$G$4:$G$341,H$5,'VS×ケイパビリティ関係'!$E$4:$E$341,"主")>0,"●",IF(COUNTIFS('VS×ケイパビリティ関係'!$F$4:$F$341,$B11,'VS×ケイパビリティ関係'!$G$4:$G$341,H$5,'VS×ケイパビリティ関係'!$E$4:$E$341,"支援")>0,"○","")) | I11: =IF(COUNTIFS('VS×ケイパビリティ関係'!$F$4:$F$341,$B11,'VS×ケイパビリティ関係'!$G$4:$G$341,I$5,'VS×ケイパビリティ関係'!$E$4:$E$341,"主")>0,"●",IF(COUNTIFS('VS×ケイパビリティ関係'!$F$4:$F$341,$B11,'VS×ケイパビリティ関係'!$G$4:$G$341,I$5,'VS×ケイパビリティ関係'!$E$4:$E$341,"支援")>0,"○","")) | J11: =IF(COUNTIFS('VS×ケイパビリティ関係'!$F$4:$F$341,$B11,'VS×ケイパビリティ関係'!$G$4:$G$341,J$5,'VS×ケイパビリティ関係'!$E$4:$E$341,"主")>0,"●",IF(COUNTIFS('VS×ケイパビリティ関係'!$F$4:$F$341,$B11,'VS×ケイパビリティ関係'!$G$4:$G$341,J$5,'VS×ケイパビリティ関係'!$E$4:$E$341,"支援")>0,"○","")) | K11: =IF(COUNTIFS('VS×ケイパビリティ関係'!$F$4:$F$341,$B11,'VS×ケイパビリティ関係'!$G$4:$G$341,K$5,'VS×ケイパビリティ関係'!$E$4:$E$341,"主")>0,"●",IF(COUNTIFS('VS×ケイパビリティ関係'!$F$4:$F$341,$B11,'VS×ケイパビリティ関係'!$G$4:$G$341,K$5,'VS×ケイパビリティ関係'!$E$4:$E$341,"支援")>0,"○","")) | ... AE11: =IF(COUNTIFS('VS×ケイパビリティ関係'!$F$4:$F$341,$B11,'VS×ケイパビリティ関係'!$G$4:$G$341,AE$5,'VS×ケイパビリティ関係'!$E$4:$E$341,"主")>0,"●",IF(COUNTIFS('VS×ケイパビリティ関係'!$F$4:$F$341,$B11,'VS×ケイパビリティ関係'!$G$4:$G$341,AE$5,'VS×ケイパビリティ関係'!$E$4:$E$341,"支援")>0,"○","")) | AF11: =COUNTIF(D11:AE11,"●") | AG11: =COUNTIF(D11:AE11,"○")
B12: 02-03 | C12: 開発・構成・テスト | D12: =IF(COUNTIFS('VS×ケイパビリティ関係'!$F$4:$F$341,$B12,'VS×ケイパビリティ関係'!$G$4:$G$341,D$5,'VS×ケイパビリティ関係'!$E$4:$E$341,"主")>0,"●",IF(COUNTIFS('VS×ケイパビリティ関係'!$F$4:$F$341,$B12,'VS×ケイパビリティ関係'!$G$4:$G$341,D$5,'VS×ケイパビリティ関係'!$E$4:$E$341,"支援")>0,"○","")) | E12: =IF(COUNTIFS('VS×ケイパビリティ関係'!$F$4:$F$341,$B12,'VS×ケイパビリティ関係'!$G$4:$G$341,E$5,'VS×ケイパビリティ関係'!$E$4:$E$341,"主")>0,"●",IF(COUNTIFS('VS×ケイパビリティ関係'!$F$4:$F$341,$B12,'VS×ケイパビリティ関係'!$G$4:$G$341,E$5,'VS×ケイパビリティ関係'!$E$4:$E$341,"支援")>0,"○","")) | F12: =IF(COUNTIFS('VS×ケイパビリティ関係'!$F$4:$F$341,$B12,'VS×ケイパビリティ関係'!$G$4:$G$341,F$5,'VS×ケイパビリティ関係'!$E$4:$E$341,"主")>0,"●",IF(COUNTIFS('VS×ケイパビリティ関係'!$F$4:$F$341,$B12,'VS×ケイパビリティ関係'!$G$4:$G$341,F$5,'VS×ケイパビリティ関係'!$E$4:$E$341,"支援")>0,"○","")) | G12: =IF(COUNTIFS('VS×ケイパビリティ関係'!$F$4:$F$341,$B12,'VS×ケイパビリティ関係'!$G$4:$G$341,G$5,'VS×ケイパビリティ関係'!$E$4:$E$341,"主")>0,"●",IF(COUNTIFS('VS×ケイパビリティ関係'!$F$4:$F$341,$B12,'VS×ケイパビリティ関係'!$G$4:$G$341,G$5,'VS×ケイパビリティ関係'!$E$4:$E$341,"支援")>0,"○","")) | H12: =IF(COUNTIFS('VS×ケイパビリティ関係'!$F$4:$F$341,$B12,'VS×ケイパビリティ関係'!$G$4:$G$341,H$5,'VS×ケイパビリティ関係'!$E$4:$E$341,"主")>0,"●",IF(COUNTIFS('VS×ケイパビリティ関係'!$F$4:$F$341,$B12,'VS×ケイパビリティ関係'!$G$4:$G$341,H$5,'VS×ケイパビリティ関係'!$E$4:$E$341,"支援")>0,"○","")) | I12: =IF(COUNTIFS('VS×ケイパビリティ関係'!$F$4:$F$341,$B12,'VS×ケイパビリティ関係'!$G$4:$G$341,I$5,'VS×ケイパビリティ関係'!$E$4:$E$341,"主")>0,"●",IF(COUNTIFS('VS×ケイパビリティ関係'!$F$4:$F$341,$B12,'VS×ケイパビリティ関係'!$G$4:$G$341,I$5,'VS×ケイパビリティ関係'!$E$4:$E$341,"支援")>0,"○","")) | J12: =IF(COUNTIFS('VS×ケイパビリティ関係'!$F$4:$F$341,$B12,'VS×ケイパビリティ関係'!$G$4:$G$341,J$5,'VS×ケイパビリティ関係'!$E$4:$E$341,"主")>0,"●",IF(COUNTIFS('VS×ケイパビリティ関係'!$F$4:$F$341,$B12,'VS×ケイパビリティ関係'!$G$4:$G$341,J$5,'VS×ケイパビリティ関係'!$E$4:$E$341,"支援")>0,"○","")) | K12: =IF(COUNTIFS('VS×ケイパビリティ関係'!$F$4:$F$341,$B12,'VS×ケイパビリティ関係'!$G$4:$G$341,K$5,'VS×ケイパビリティ関係'!$E$4:$E$341,"主")>0,"●",IF(COUNTIFS('VS×ケイパビリティ関係'!$F$4:$F$341,$B12,'VS×ケイパビリティ関係'!$G$4:$G$341,K$5,'VS×ケイパビリティ関係'!$E$4:$E$341,"支援")>0,"○","")) | ... AE12: =IF(COUNTIFS('VS×ケイパビリティ関係'!$F$4:$F$341,$B12,'VS×ケイパビリティ関係'!$G$4:$G$341,AE$5,'VS×ケイパビリティ関係'!$E$4:$E$341,"主")>0,"●",IF(COUNTIFS('VS×ケイパビリティ関係'!$F$4:$F$341,$B12,'VS×ケイパビリティ関係'!$G$4:$G$341,AE$5,'VS×ケイパビリティ関係'!$E$4:$E$341,"支援")>0,"○","")) | AF12: =COUNTIF(D12:AE12,"●") | AG12: =COUNTIF(D12:AE12,"○")
B13: 02-04 | C13: バリデーション・リリース | D13: =IF(COUNTIFS('VS×ケイパビリティ関係'!$F$4:$F$341,$B13,'VS×ケイパビリティ関係'!$G$4:$G$341,D$5,'VS×ケイパビリティ関係'!$E$4:$E$341,"主")>0,"●",IF(COUNTIFS('VS×ケイパビリティ関係'!$F$4:$F$341,$B13,'VS×ケイパビリティ関係'!$G$4:$G$341,D$5,'VS×ケイパビリティ関係'!$E$4:$E$341,"支援")>0,"○","")) | E13: =IF(COUNTIFS('VS×ケイパビリティ関係'!$F$4:$F$341,$B13,'VS×ケイパビリティ関係'!$G$4:$G$341,E$5,'VS×ケイパビリティ関係'!$E$4:$E$341,"主")>0,"●",IF(COUNTIFS('VS×ケイパビリティ関係'!$F$4:$F$341,$B13,'VS×ケイパビリティ関係'!$G$4:$G$341,E$5,'VS×ケイパビリティ関係'!$E$4:$E$341,"支援")>0,"○","")) | F13: =IF(COUNTIFS('VS×ケイパビリティ関係'!$F$4:$F$341,$B13,'VS×ケイパビリティ関係'!$G$4:$G$341,F$5,'VS×ケイパビリティ関係'!$E$4:$E$341,"主")>0,"●",IF(COUNTIFS('VS×ケイパビリティ関係'!$F$4:$F$341,$B13,'VS×ケイパビリティ関係'!$G$4:$G$341,F$5,'VS×ケイパビリティ関係'!$E$4:$E$341,"支援")>0,"○","")) | G13: =IF(COUNTIFS('VS×ケイパビリティ関係'!$F$4:$F$341,$B13,'VS×ケイパビリティ関係'!$G$4:$G$341,G$5,'VS×ケイパビリティ関係'!$E$4:$E$341,"主")>0,"●",IF(COUNTIFS('VS×ケイパビリティ関係'!$F$4:$F$341,$B13,'VS×ケイパビリティ関係'!$G$4:$G$341,G$5,'VS×ケイパビリティ関係'!$E$4:$E$341,"支援")>0,"○","")) | H13: =IF(COUNTIFS('VS×ケイパビリティ関係'!$F$4:$F$341,$B13,'VS×ケイパビリティ関係'!$G$4:$G$341,H$5,'VS×ケイパビリティ関係'!$E$4:$E$341,"主")>0,"●",IF(COUNTIFS('VS×ケイパビリティ関係'!$F$4:$F$341,$B13,'VS×ケイパビリティ関係'!$G$4:$G$341,H$5,'VS×ケイパビリティ関係'!$E$4:$E$341,"支援")>0,"○","")) | I13: =IF(COUNTIFS('VS×ケイパビリティ関係'!$F$4:$F$341,$B13,'VS×ケイパビリティ関係'!$G$4:$G$341,I$5,'VS×ケイパビリティ関係'!$E$4:$E$341,"主")>0,"●",IF(COUNTIFS('VS×ケイパビリティ関係'!$F$4:$F$341,$B13,'VS×ケイパビリティ関係'!$G$4:$G$341,I$5,'VS×ケイパビリティ関係'!$E$4:$E$341,"支援")>0,"○","")) | J13: =IF(COUNTIFS('VS×ケイパビリティ関係'!$F$4:$F$341,$B13,'VS×ケイパビリティ関係'!$G$4:$G$341,J$5,'VS×ケイパビリティ関係'!$E$4:$E$341,"主")>0,"●",IF(COUNTIFS('VS×ケイパビリティ関係'!$F$4:$F$341,$B13,'VS×ケイパビリティ関係'!$G$4:$G$341,J$5,'VS×ケイパビリティ関係'!$E$4:$E$341,"支援")>0,"○","")) | K13: =IF(COUNTIFS('VS×ケイパビリティ関係'!$F$4:$F$341,$B13,'VS×ケイパビリティ関係'!$G$4:$G$341,K$5,'VS×ケイパビリティ関係'!$E$4:$E$341,"主")>0,"●",IF(COUNTIFS('VS×ケイパビリティ関係'!$F$4:$F$341,$B13,'VS×ケイパビリティ関係'!$G$4:$G$341,K$5,'VS×ケイパビリティ関係'!$E$4:$E$341,"支援")>0,"○","")) | ... AE13: =IF(COUNTIFS('VS×ケイパビリティ関係'!$F$4:$F$341,$B13,'VS×ケイパビリティ関係'!$G$4:$G$341,AE$5,'VS×ケイパビリティ関係'!$E$4:$E$341,"主")>0,"●",IF(COUNTIFS('VS×ケイパビリティ関係'!$F$4:$F$341,$B13,'VS×ケイパビリティ関係'!$G$4:$G$341,AE$5,'VS×ケイパビリティ関係'!$E$4:$E$341,"支援")>0,"○","")) | AF13: =COUNTIF(D13:AE13,"●") | AG13: =COUNTIF(D13:AE13,"○")
A14: 03 利用申請・提供（R2F） | B14: 03-01 | C14: サービスカタログの公開 | D14: =IF(COUNTIFS('VS×ケイパビリティ関係'!$F$4:$F$341,$B14,'VS×ケイパビリティ関係'!$G$4:$G$341,D$5,'VS×ケイパビリティ関係'!$E$4:$E$341,"主")>0,"●",IF(COUNTIFS('VS×ケイパビリティ関係'!$F$4:$F$341,$B14,'VS×ケイパビリティ関係'!$G$4:$G$341,D$5,'VS×ケイパビリティ関係'!$E$4:$E$341,"支援")>0,"○","")) | E14: =IF(COUNTIFS('VS×ケイパビリティ関係'!$F$4:$F$341,$B14,'VS×ケイパビリティ関係'!$G$4:$G$341,E$5,'VS×ケイパビリティ関係'!$E$4:$E$341,"主")>0,"●",IF(COUNTIFS('VS×ケイパビリティ関係'!$F$4:$F$341,$B14,'VS×ケイパビリティ関係'!$G$4:$G$341,E$5,'VS×ケイパビリティ関係'!$E$4:$E$341,"支援")>0,"○","")) | F14: =IF(COUNTIFS('VS×ケイパビリティ関係'!$F$4:$F$341,$B14,'VS×ケイパビリティ関係'!$G$4:$G$341,F$5,'VS×ケイパビリティ関係'!$E$4:$E$341,"主")>0,"●",IF(COUNTIFS('VS×ケイパビリティ関係'!$F$4:$F$341,$B14,'VS×ケイパビリティ関係'!$G$4:$G$341,F$5,'VS×ケイパビリティ関係'!$E$4:$E$341,"支援")>0,"○","")) | G14: =IF(COUNTIFS('VS×ケイパビリティ関係'!$F$4:$F$341,$B14,'VS×ケイパビリティ関係'!$G$4:$G$341,G$5,'VS×ケイパビリティ関係'!$E$4:$E$341,"主")>0,"●",IF(COUNTIFS('VS×ケイパビリティ関係'!$F$4:$F$341,$B14,'VS×ケイパビリティ関係'!$G$4:$G$341,G$5,'VS×ケイパビリティ関係'!$E$4:$E$341,"支援")>0,"○","")) | H14: =IF(COUNTIFS('VS×ケイパビリティ関係'!$F$4:$F$341,$B14,'VS×ケイパビリティ関係'!$G$4:$G$341,H$5,'VS×ケイパビリティ関係'!$E$4:$E$341,"主")>0,"●",IF(COUNTIFS('VS×ケイパビリティ関係'!$F$4:$F$341,$B14,'VS×ケイパビリティ関係'!$G$4:$G$341,H$5,'VS×ケイパビリティ関係'!$E$4:$E$341,"支援")>0,"○","")) | I14: =IF(COUNTIFS('VS×ケイパビリティ関係'!$F$4:$F$341,$B14,'VS×ケイパビリティ関係'!$G$4:$G$341,I$5,'VS×ケイパビリティ関係'!$E$4:$E$341,"主")>0,"●",IF(COUNTIFS('VS×ケイパビリティ関係'!$F$4:$F$341,$B14,'VS×ケイパビリティ関係'!$G$4:$G$341,I$5,'VS×ケイパビリティ関係'!$E$4:$E$341,"支援")>0,"○","")) | J14: =IF(COUNTIFS('VS×ケイパビリティ関係'!$F$4:$F$341,$B14,'VS×ケイパビリティ関係'!$G$4:$G$341,J$5,'VS×ケイパビリティ関係'!$E$4:$E$341,"主")>0,"●",IF(COUNTIFS('VS×ケイパビリティ関係'!$F$4:$F$341,$B14,'VS×ケイパビリティ関係'!$G$4:$G$341,J$5,'VS×ケイパビリティ関係'!$E$4:$E$341,"支援")>0,"○","")) | K14: =IF(COUNTIFS('VS×ケイパビリティ関係'!$F$4:$F$341,$B14,'VS×ケイパビリティ関係'!$G$4:$G$341,K$5,'VS×ケイパビリティ関係'!$E$4:$E$341,"主")>0,"●",IF(COUNTIFS('VS×ケイパビリティ関係'!$F$4:$F$341,$B14,'VS×ケイパビリティ関係'!$G$4:$G$341,K$5,'VS×ケイパビリティ関係'!$E$4:$E$341,"支援")>0,"○","")) | ... AE14: =IF(COUNTIFS('VS×ケイパビリティ関係'!$F$4:$F$341,$B14,'VS×ケイパビリティ関係'!$G$4:$G$341,AE$5,'VS×ケイパビリティ関係'!$E$4:$E$341,"主")>0,"●",IF(COUNTIFS('VS×ケイパビリティ関係'!$F$4:$F$341,$B14,'VS×ケイパビリティ関係'!$G$4:$G$341,AE$5,'VS×ケイパビリティ関係'!$E$4:$E$341,"支援")>0,"○","")) | AF14: =COUNTIF(D14:AE14,"●") | AG14: =COUNTIF(D14:AE14,"○")
B15: 03-02 | C15: 申請・承認 | D15: =IF(COUNTIFS('VS×ケイパビリティ関係'!$F$4:$F$341,$B15,'VS×ケイパビリティ関係'!$G$4:$G$341,D$5,'VS×ケイパビリティ関係'!$E$4:$E$341,"主")>0,"●",IF(COUNTIFS('VS×ケイパビリティ関係'!$F$4:$F$341,$B15,'VS×ケイパビリティ関係'!$G$4:$G$341,D$5,'VS×ケイパビリティ関係'!$E$4:$E$341,"支援")>0,"○","")) | E15: =IF(COUNTIFS('VS×ケイパビリティ関係'!$F$4:$F$341,$B15,'VS×ケイパビリティ関係'!$G$4:$G$341,E$5,'VS×ケイパビリティ関係'!$E$4:$E$341,"主")>0,"●",IF(COUNTIFS('VS×ケイパビリティ関係'!$F$4:$F$341,$B15,'VS×ケイパビリティ関係'!$G$4:$G$341,E$5,'VS×ケイパビリティ関係'!$E$4:$E$341,"支援")>0,"○","")) | F15: =IF(COUNTIFS('VS×ケイパビリティ関係'!$F$4:$F$341,$B15,'VS×ケイパビリティ関係'!$G$4:$G$341,F$5,'VS×ケイパビリティ関係'!$E$4:$E$341,"主")>0,"●",IF(COUNTIFS('VS×ケイパビリティ関係'!$F$4:$F$341,$B15,'VS×ケイパビリティ関係'!$G$4:$G$341,F$5,'VS×ケイパビリティ関係'!$E$4:$E$341,"支援")>0,"○","")) | G15: =IF(COUNTIFS('VS×ケイパビリティ関係'!$F$4:$F$341,$B15,'VS×ケイパビリティ関係'!$G$4:$G$341,G$5,'VS×ケイパビリティ関係'!$E$4:$E$341,"主")>0,"●",IF(COUNTIFS('VS×ケイパビリティ関係'!$F$4:$F$341,$B15,'VS×ケイパビリティ関係'!$G$4:$G$341,G$5,'VS×ケイパビリティ関係'!$E$4:$E$341,"支援")>0,"○","")) | H15: =IF(COUNTIFS('VS×ケイパビリティ関係'!$F$4:$F$341,$B15,'VS×ケイパビリティ関係'!$G$4:$G$341,H$5,'VS×ケイパビリティ関係'!$E$4:$E$341,"主")>0,"●",IF(COUNTIFS('VS×ケイパビリティ関係'!$F$4:$F$341,$B15,'VS×ケイパビリティ関係'!$G$4:$G$341,H$5,'VS×ケイパビリティ関係'!$E$4:$E$341,"支援")>0,"○","")) | I15: =IF(COUNTIFS('VS×ケイパビリティ関係'!$F$4:$F$341,$B15,'VS×ケイパビリティ関係'!$G$4:$G$341,I$5,'VS×ケイパビリティ関係'!$E$4:$E$341,"主")>0,"●",IF(COUNTIFS('VS×ケイパビリティ関係'!$F$4:$F$341,$B15,'VS×ケイパビリティ関係'!$G$4:$G$341,I$5,'VS×ケイパビリティ関係'!$E$4:$E$341,"支援")>0,"○","")) | J15: =IF(COUNTIFS('VS×ケイパビリティ関係'!$F$4:$F$341,$B15,'VS×ケイパビリティ関係'!$G$4:$G$341,J$5,'VS×ケイパビリティ関係'!$E$4:$E$341,"主")>0,"●",IF(COUNTIFS('VS×ケイパビリティ関係'!$F$4:$F$341,$B15,'VS×ケイパビリティ関係'!$G$4:$G$341,J$5,'VS×ケイパビリティ関係'!$E$4:$E$341,"支援")>0,"○","")) | K15: =IF(COUNTIFS('VS×ケイパビリティ関係'!$F$4:$F$341,$B15,'VS×ケイパビリティ関係'!$G$4:$G$341,K$5,'VS×ケイパビリティ関係'!$E$4:$E$341,"主")>0,"●",IF(COUNTIFS('VS×ケイパビリティ関係'!$F$4:$F$341,$B15,'VS×ケイパビリティ関係'!$G$4:$G$341,K$5,'VS×ケイパビリティ関係'!$E$4:$E$341,"支援")>0,"○","")) | ... AE15: =IF(COUNTIFS('VS×ケイパビリティ関係'!$F$4:$F$341,$B15,'VS×ケイパビリティ関係'!$G$4:$G$341,AE$5,'VS×ケイパビリティ関係'!$E$4:$E$341,"主")>0,"●",IF(COUNTIFS('VS×ケイパビリティ関係'!$F$4:$F$341,$B15,'VS×ケイパビリティ関係'!$G$4:$G$341,AE$5,'VS×ケイパビリティ関係'!$E$4:$E$341,"支援")>0,"○","")) | AF15: =COUNTIF(D15:AE15,"●") | AG15: =COUNTIF(D15:AE15,"○")
B16: 03-03 | C16: 提供 | D16: =IF(COUNTIFS('VS×ケイパビリティ関係'!$F$4:$F$341,$B16,'VS×ケイパビリティ関係'!$G$4:$G$341,D$5,'VS×ケイパビリティ関係'!$E$4:$E$341,"主")>0,"●",IF(COUNTIFS('VS×ケイパビリティ関係'!$F$4:$F$341,$B16,'VS×ケイパビリティ関係'!$G$4:$G$341,D$5,'VS×ケイパビリティ関係'!$E$4:$E$341,"支援")>0,"○","")) | E16: =IF(COUNTIFS('VS×ケイパビリティ関係'!$F$4:$F$341,$B16,'VS×ケイパビリティ関係'!$G$4:$G$341,E$5,'VS×ケイパビリティ関係'!$E$4:$E$341,"主")>0,"●",IF(COUNTIFS('VS×ケイパビリティ関係'!$F$4:$F$341,$B16,'VS×ケイパビリティ関係'!$G$4:$G$341,E$5,'VS×ケイパビリティ関係'!$E$4:$E$341,"支援")>0,"○","")) | F16: =IF(COUNTIFS('VS×ケイパビリティ関係'!$F$4:$F$341,$B16,'VS×ケイパビリティ関係'!$G$4:$G$341,F$5,'VS×ケイパビリティ関係'!$E$4:$E$341,"主")>0,"●",IF(COUNTIFS('VS×ケイパビリティ関係'!$F$4:$F$341,$B16,'VS×ケイパビリティ関係'!$G$4:$G$341,F$5,'VS×ケイパビリティ関係'!$E$4:$E$341,"支援")>0,"○","")) | G16: =IF(COUNTIFS('VS×ケイパビリティ関係'!$F$4:$F$341,$B16,'VS×ケイパビリティ関係'!$G$4:$G$341,G$5,'VS×ケイパビリティ関係'!$E$4:$E$341,"主")>0,"●",IF(COUNTIFS('VS×ケイパビリティ関係'!$F$4:$F$341,$B16,'VS×ケイパビリティ関係'!$G$4:$G$341,G$5,'VS×ケイパビリティ関係'!$E$4:$E$341,"支援")>0,"○","")) | H16: =IF(COUNTIFS('VS×ケイパビリティ関係'!$F$4:$F$341,$B16,'VS×ケイパビリティ関係'!$G$4:$G$341,H$5,'VS×ケイパビリティ関係'!$E$4:$E$341,"主")>0,"●",IF(COUNTIFS('VS×ケイパビリティ関係'!$F$4:$F$341,$B16,'VS×ケイパビリティ関係'!$G$4:$G$341,H$5,'VS×ケイパビリティ関係'!$E$4:$E$341,"支援")>0,"○","")) | I16: =IF(COUNTIFS('VS×ケイパビリティ関係'!$F$4:$F$341,$B16,'VS×ケイパビリティ関係'!$G$4:$G$341,I$5,'VS×ケイパビリティ関係'!$E$4:$E$341,"主")>0,"●",IF(COUNTIFS('VS×ケイパビリティ関係'!$F$4:$F$341,$B16,'VS×ケイパビリティ関係'!$G$4:$G$341,I$5,'VS×ケイパビリティ関係'!$E$4:$E$341,"支援")>0,"○","")) | J16: =IF(COUNTIFS('VS×ケイパビリティ関係'!$F$4:$F$341,$B16,'VS×ケイパビリティ関係'!$G$4:$G$341,J$5,'VS×ケイパビリティ関係'!$E$4:$E$341,"主")>0,"●",IF(COUNTIFS('VS×ケイパビリティ関係'!$F$4:$F$341,$B16,'VS×ケイパビリティ関係'!$G$4:$G$341,J$5,'VS×ケイパビリティ関係'!$E$4:$E$341,"支援")>0,"○","")) | K16: =IF(COUNTIFS('VS×ケイパビリティ関係'!$F$4:$F$341,$B16,'VS×ケイパビリティ関係'!$G$4:$G$341,K$5,'VS×ケイパビリティ関係'!$E$4:$E$341,"主")>0,"●",IF(COUNTIFS('VS×ケイパビリティ関係'!$F$4:$F$341,$B16,'VS×ケイパビリティ関係'!$G$4:$G$341,K$5,'VS×ケイパビリティ関係'!$E$4:$E$341,"支援")>0,"○","")) | ... AE16: =IF(COUNTIFS('VS×ケイパビリティ関係'!$F$4:$F$341,$B16,'VS×ケイパビリティ関係'!$G$4:$G$341,AE$5,'VS×ケイパビリティ関係'!$E$4:$E$341,"主")>0,"●",IF(COUNTIFS('VS×ケイパビリティ関係'!$F$4:$F$341,$B16,'VS×ケイパビリティ関係'!$G$4:$G$341,AE$5,'VS×ケイパビリティ関係'!$E$4:$E$341,"支援")>0,"○","")) | AF16: =COUNTIF(D16:AE16,"●") | AG16: =COUNTIF(D16:AE16,"○")
B17: 03-04 | C17: 利用・費用管理 | D17: =IF(COUNTIFS('VS×ケイパビリティ関係'!$F$4:$F$341,$B17,'VS×ケイパビリティ関係'!$G$4:$G$341,D$5,'VS×ケイパビリティ関係'!$E$4:$E$341,"主")>0,"●",IF(COUNTIFS('VS×ケイパビリティ関係'!$F$4:$F$341,$B17,'VS×ケイパビリティ関係'!$G$4:$G$341,D$5,'VS×ケイパビリティ関係'!$E$4:$E$341,"支援")>0,"○","")) | E17: =IF(COUNTIFS('VS×ケイパビリティ関係'!$F$4:$F$341,$B17,'VS×ケイパビリティ関係'!$G$4:$G$341,E$5,'VS×ケイパビリティ関係'!$E$4:$E$341,"主")>0,"●",IF(COUNTIFS('VS×ケイパビリティ関係'!$F$4:$F$341,$B17,'VS×ケイパビリティ関係'!$G$4:$G$341,E$5,'VS×ケイパビリティ関係'!$E$4:$E$341,"支援")>0,"○","")) | F17: =IF(COUNTIFS('VS×ケイパビリティ関係'!$F$4:$F$341,$B17,'VS×ケイパビリティ関係'!$G$4:$G$341,F$5,'VS×ケイパビリティ関係'!$E$4:$E$341,"主")>0,"●",IF(COUNTIFS('VS×ケイパビリティ関係'!$F$4:$F$341,$B17,'VS×ケイパビリティ関係'!$G$4:$G$341,F$5,'VS×ケイパビリティ関係'!$E$4:$E$341,"支援")>0,"○","")) | G17: =IF(COUNTIFS('VS×ケイパビリティ関係'!$F$4:$F$341,$B17,'VS×ケイパビリティ関係'!$G$4:$G$341,G$5,'VS×ケイパビリティ関係'!$E$4:$E$341,"主")>0,"●",IF(COUNTIFS('VS×ケイパビリティ関係'!$F$4:$F$341,$B17,'VS×ケイパビリティ関係'!$G$4:$G$341,G$5,'VS×ケイパビリティ関係'!$E$4:$E$341,"支援")>0,"○","")) | H17: =IF(COUNTIFS('VS×ケイパビリティ関係'!$F$4:$F$341,$B17,'VS×ケイパビリティ関係'!$G$4:$G$341,H$5,'VS×ケイパビリティ関係'!$E$4:$E$341,"主")>0,"●",IF(COUNTIFS('VS×ケイパビリティ関係'!$F$4:$F$341,$B17,'VS×ケイパビリティ関係'!$G$4:$G$341,H$5,'VS×ケイパビリティ関係'!$E$4:$E$341,"支援")>0,"○","")) | I17: =IF(COUNTIFS('VS×ケイパビリティ関係'!$F$4:$F$341,$B17,'VS×ケイパビリティ関係'!$G$4:$G$341,I$5,'VS×ケイパビリティ関係'!$E$4:$E$341,"主")>0,"●",IF(COUNTIFS('VS×ケイパビリティ関係'!$F$4:$F$341,$B17,'VS×ケイパビリティ関係'!$G$4:$G$341,I$5,'VS×ケイパビリティ関係'!$E$4:$E$341,"支援")>0,"○","")) | J17: =IF(COUNTIFS('VS×ケイパビリティ関係'!$F$4:$F$341,$B17,'VS×ケイパビリティ関係'!$G$4:$G$341,J$5,'VS×ケイパビリティ関係'!$E$4:$E$341,"主")>0,"●",IF(COUNTIFS('VS×ケイパビリティ関係'!$F$4:$F$341,$B17,'VS×ケイパビリティ関係'!$G$4:$G$341,J$5,'VS×ケイパビリティ関係'!$E$4:$E$341,"支援")>0,"○","")) | K17: =IF(COUNTIFS('VS×ケイパビリティ関係'!$F$4:$F$341,$B17,'VS×ケイパビリティ関係'!$G$4:$G$341,K$5,'VS×ケイパビリティ関係'!$E$4:$E$341,"主")>0,"●",IF(COUNTIFS('VS×ケイパビリティ関係'!$F$4:$F$341,$B17,'VS×ケイパビリティ関係'!$G$4:$G$341,K$5,'VS×ケイパビリティ関係'!$E$4:$E$341,"支援")>0,"○","")) | ... AE17: =IF(COUNTIFS('VS×ケイパビリティ関係'!$F$4:$F$341,$B17,'VS×ケイパビリティ関係'!$G$4:$G$341,AE$5,'VS×ケイパビリティ関係'!$E$4:$E$341,"主")>0,"●",IF(COUNTIFS('VS×ケイパビリティ関係'!$F$4:$F$341,$B17,'VS×ケイパビリティ関係'!$G$4:$G$341,AE$5,'VS×ケイパビリティ関係'!$E$4:$E$341,"支援")>0,"○","")) | AF17: =COUNTIF(D17:AE17,"●") | AG17: =COUNTIF(D17:AE17,"○")
A18: 04 検知・是正（D2C） | B18: 04-01 | C18: 監視・検知 | D18: =IF(COUNTIFS('VS×ケイパビリティ関係'!$F$4:$F$341,$B18,'VS×ケイパビリティ関係'!$G$4:$G$341,D$5,'VS×ケイパビリティ関係'!$E$4:$E$341,"主")>0,"●",IF(COUNTIFS('VS×ケイパビリティ関係'!$F$4:$F$341,$B18,'VS×ケイパビリティ関係'!$G$4:$G$341,D$5,'VS×ケイパビリティ関係'!$E$4:$E$341,"支援")>0,"○","")) | E18: =IF(COUNTIFS('VS×ケイパビリティ関係'!$F$4:$F$341,$B18,'VS×ケイパビリティ関係'!$G$4:$G$341,E$5,'VS×ケイパビリティ関係'!$E$4:$E$341,"主")>0,"●",IF(COUNTIFS('VS×ケイパビリティ関係'!$F$4:$F$341,$B18,'VS×ケイパビリティ関係'!$G$4:$G$341,E$5,'VS×ケイパビリティ関係'!$E$4:$E$341,"支援")>0,"○","")) | F18: =IF(COUNTIFS('VS×ケイパビリティ関係'!$F$4:$F$341,$B18,'VS×ケイパビリティ関係'!$G$4:$G$341,F$5,'VS×ケイパビリティ関係'!$E$4:$E$341,"主")>0,"●",IF(COUNTIFS('VS×ケイパビリティ関係'!$F$4:$F$341,$B18,'VS×ケイパビリティ関係'!$G$4:$G$341,F$5,'VS×ケイパビリティ関係'!$E$4:$E$341,"支援")>0,"○","")) | G18: =IF(COUNTIFS('VS×ケイパビリティ関係'!$F$4:$F$341,$B18,'VS×ケイパビリティ関係'!$G$4:$G$341,G$5,'VS×ケイパビリティ関係'!$E$4:$E$341,"主")>0,"●",IF(COUNTIFS('VS×ケイパビリティ関係'!$F$4:$F$341,$B18,'VS×ケイパビリティ関係'!$G$4:$G$341,G$5,'VS×ケイパビリティ関係'!$E$4:$E$341,"支援")>0,"○","")) | H18: =IF(COUNTIFS('VS×ケイパビリティ関係'!$F$4:$F$341,$B18,'VS×ケイパビリティ関係'!$G$4:$G$341,H$5,'VS×ケイパビリティ関係'!$E$4:$E$341,"主")>0,"●",IF(COUNTIFS('VS×ケイパビリティ関係'!$F$4:$F$341,$B18,'VS×ケイパビリティ関係'!$G$4:$G$341,H$5,'VS×ケイパビリティ関係'!$E$4:$E$341,"支援")>0,"○","")) | I18: =IF(COUNTIFS('VS×ケイパビリティ関係'!$F$4:$F$341,$B18,'VS×ケイパビリティ関係'!$G$4:$G$341,I$5,'VS×ケイパビリティ関係'!$E$4:$E$341,"主")>0,"●",IF(COUNTIFS('VS×ケイパビリティ関係'!$F$4:$F$341,$B18,'VS×ケイパビリティ関係'!$G$4:$G$341,I$5,'VS×ケイパビリティ関係'!$E$4:$E$341,"支援")>0,"○","")) | J18: =IF(COUNTIFS('VS×ケイパビリティ関係'!$F$4:$F$341,$B18,'VS×ケイパビリティ関係'!$G$4:$G$341,J$5,'VS×ケイパビリティ関係'!$E$4:$E$341,"主")>0,"●",IF(COUNTIFS('VS×ケイパビリティ関係'!$F$4:$F$341,$B18,'VS×ケイパビリティ関係'!$G$4:$G$341,J$5,'VS×ケイパビリティ関係'!$E$4:$E$341,"支援")>0,"○","")) | K18: =IF(COUNTIFS('VS×ケイパビリティ関係'!$F$4:$F$341,$B18,'VS×ケイパビリティ関係'!$G$4:$G$341,K$5,'VS×ケイパビリティ関係'!$E$4:$E$341,"主")>0,"●",IF(COUNTIFS('VS×ケイパビリティ関係'!$F$4:$F$341,$B18,'VS×ケイパビリティ関係'!$G$4:$G$341,K$5,'VS×ケイパビリティ関係'!$E$4:$E$341,"支援")>0,"○","")) | ... AE18: =IF(COUNTIFS('VS×ケイパビリティ関係'!$F$4:$F$341,$B18,'VS×ケイパビリティ関係'!$G$4:$G$341,AE$5,'VS×ケイパビリティ関係'!$E$4:$E$341,"主")>0,"●",IF(COUNTIFS('VS×ケイパビリティ関係'!$F$4:$F$341,$B18,'VS×ケイパビリティ関係'!$G$4:$G$341,AE$5,'VS×ケイパビリティ関係'!$E$4:$E$341,"支援")>0,"○","")) | AF18: =COUNTIF(D18:AE18,"●") | AG18: =COUNTIF(D18:AE18,"○")
B19: 04-02 | C19: インシデント対応 | D19: =IF(COUNTIFS('VS×ケイパビリティ関係'!$F$4:$F$341,$B19,'VS×ケイパビリティ関係'!$G$4:$G$341,D$5,'VS×ケイパビリティ関係'!$E$4:$E$341,"主")>0,"●",IF(COUNTIFS('VS×ケイパビリティ関係'!$F$4:$F$341,$B19,'VS×ケイパビリティ関係'!$G$4:$G$341,D$5,'VS×ケイパビリティ関係'!$E$4:$E$341,"支援")>0,"○","")) | E19: =IF(COUNTIFS('VS×ケイパビリティ関係'!$F$4:$F$341,$B19,'VS×ケイパビリティ関係'!$G$4:$G$341,E$5,'VS×ケイパビリティ関係'!$E$4:$E$341,"主")>0,"●",IF(COUNTIFS('VS×ケイパビリティ関係'!$F$4:$F$341,$B19,'VS×ケイパビリティ関係'!$G$4:$G$341,E$5,'VS×ケイパビリティ関係'!$E$4:$E$341,"支援")>0,"○","")) | F19: =IF(COUNTIFS('VS×ケイパビリティ関係'!$F$4:$F$341,$B19,'VS×ケイパビリティ関係'!$G$4:$G$341,F$5,'VS×ケイパビリティ関係'!$E$4:$E$341,"主")>0,"●",IF(COUNTIFS('VS×ケイパビリティ関係'!$F$4:$F$341,$B19,'VS×ケイパビリティ関係'!$G$4:$G$341,F$5,'VS×ケイパビリティ関係'!$E$4:$E$341,"支援")>0,"○","")) | G19: =IF(COUNTIFS('VS×ケイパビリティ関係'!$F$4:$F$341,$B19,'VS×ケイパビリティ関係'!$G$4:$G$341,G$5,'VS×ケイパビリティ関係'!$E$4:$E$341,"主")>0,"●",IF(COUNTIFS('VS×ケイパビリティ関係'!$F$4:$F$341,$B19,'VS×ケイパビリティ関係'!$G$4:$G$341,G$5,'VS×ケイパビリティ関係'!$E$4:$E$341,"支援")>0,"○","")) | H19: =IF(COUNTIFS('VS×ケイパビリティ関係'!$F$4:$F$341,$B19,'VS×ケイパビリティ関係'!$G$4:$G$341,H$5,'VS×ケイパビリティ関係'!$E$4:$E$341,"主")>0,"●",IF(COUNTIFS('VS×ケイパビリティ関係'!$F$4:$F$341,$B19,'VS×ケイパビリティ関係'!$G$4:$G$341,H$5,'VS×ケイパビリティ関係'!$E$4:$E$341,"支援")>0,"○","")) | I19: =IF(COUNTIFS('VS×ケイパビリティ関係'!$F$4:$F$341,$B19,'VS×ケイパビリティ関係'!$G$4:$G$341,I$5,'VS×ケイパビリティ関係'!$E$4:$E$341,"主")>0,"●",IF(COUNTIFS('VS×ケイパビリティ関係'!$F$4:$F$341,$B19,'VS×ケイパビリティ関係'!$G$4:$G$341,I$5,'VS×ケイパビリティ関係'!$E$4:$E$341,"支援")>0,"○","")) | J19: =IF(COUNTIFS('VS×ケイパビリティ関係'!$F$4:$F$341,$B19,'VS×ケイパビリティ関係'!$G$4:$G$341,J$5,'VS×ケイパビリティ関係'!$E$4:$E$341,"主")>0,"●",IF(COUNTIFS('VS×ケイパビリティ関係'!$F$4:$F$341,$B19,'VS×ケイパビリティ関係'!$G$4:$G$341,J$5,'VS×ケイパビリティ関係'!$E$4:$E$341,"支援")>0,"○","")) | K19: =IF(COUNTIFS('VS×ケイパビリティ関係'!$F$4:$F$341,$B19,'VS×ケイパビリティ関係'!$G$4:$G$341,K$5,'VS×ケイパビリティ関係'!$E$4:$E$341,"主")>0,"●",IF(COUNTIFS('VS×ケイパビリティ関係'!$F$4:$F$341,$B19,'VS×ケイパビリティ関係'!$G$4:$G$341,K$5,'VS×ケイパビリティ関係'!$E$4:$E$341,"支援")>0,"○","")) | ... AE19: =IF(COUNTIFS('VS×ケイパビリティ関係'!$F$4:$F$341,$B19,'VS×ケイパビリティ関係'!$G$4:$G$341,AE$5,'VS×ケイパビリティ関係'!$E$4:$E$341,"主")>0,"●",IF(COUNTIFS('VS×ケイパビリティ関係'!$F$4:$F$341,$B19,'VS×ケイパビリティ関係'!$G$4:$G$341,AE$5,'VS×ケイパビリティ関係'!$E$4:$E$341,"支援")>0,"○","")) | AF19: =COUNTIF(D19:AE19,"●") | AG19: =COUNTIF(D19:AE19,"○")
B20: 04-03 | C20: 問題・変更管理 | D20: =IF(COUNTIFS('VS×ケイパビリティ関係'!$F$4:$F$341,$B20,'VS×ケイパビリティ関係'!$G$4:$G$341,D$5,'VS×ケイパビリティ関係'!$E$4:$E$341,"主")>0,"●",IF(COUNTIFS('VS×ケイパビリティ関係'!$F$4:$F$341,$B20,'VS×ケイパビリティ関係'!$G$4:$G$341,D$5,'VS×ケイパビリティ関係'!$E$4:$E$341,"支援")>0,"○","")) | E20: =IF(COUNTIFS('VS×ケイパビリティ関係'!$F$4:$F$341,$B20,'VS×ケイパビリティ関係'!$G$4:$G$341,E$5,'VS×ケイパビリティ関係'!$E$4:$E$341,"主")>0,"●",IF(COUNTIFS('VS×ケイパビリティ関係'!$F$4:$F$341,$B20,'VS×ケイパビリティ関係'!$G$4:$G$341,E$5,'VS×ケイパビリティ関係'!$E$4:$E$341,"支援")>0,"○","")) | F20: =IF(COUNTIFS('VS×ケイパビリティ関係'!$F$4:$F$341,$B20,'VS×ケイパビリティ関係'!$G$4:$G$341,F$5,'VS×ケイパビリティ関係'!$E$4:$E$341,"主")>0,"●",IF(COUNTIFS('VS×ケイパビリティ関係'!$F$4:$F$341,$B20,'VS×ケイパビリティ関係'!$G$4:$G$341,F$5,'VS×ケイパビリティ関係'!$E$4:$E$341,"支援")>0,"○","")) | G20: =IF(COUNTIFS('VS×ケイパビリティ関係'!$F$4:$F$341,$B20,'VS×ケイパビリティ関係'!$G$4:$G$341,G$5,'VS×ケイパビリティ関係'!$E$4:$E$341,"主")>0,"●",IF(COUNTIFS('VS×ケイパビリティ関係'!$F$4:$F$341,$B20,'VS×ケイパビリティ関係'!$G$4:$G$341,G$5,'VS×ケイパビリティ関係'!$E$4:$E$341,"支援")>0,"○","")) | H20: =IF(COUNTIFS('VS×ケイパビリティ関係'!$F$4:$F$341,$B20,'VS×ケイパビリティ関係'!$G$4:$G$341,H$5,'VS×ケイパビリティ関係'!$E$4:$E$341,"主")>0,"●",IF(COUNTIFS('VS×ケイパビリティ関係'!$F$4:$F$341,$B20,'VS×ケイパビリティ関係'!$G$4:$G$341,H$5,'VS×ケイパビリティ関係'!$E$4:$E$341,"支援")>0,"○","")) | I20: =IF(COUNTIFS('VS×ケイパビリティ関係'!$F$4:$F$341,$B20,'VS×ケイパビリティ関係'!$G$4:$G$341,I$5,'VS×ケイパビリティ関係'!$E$4:$E$341,"主")>0,"●",IF(COUNTIFS('VS×ケイパビリティ関係'!$F$4:$F$341,$B20,'VS×ケイパビリティ関係'!$G$4:$G$341,I$5,'VS×ケイパビリティ関係'!$E$4:$E$341,"支援")>0,"○","")) | J20: =IF(COUNTIFS('VS×ケイパビリティ関係'!$F$4:$F$341,$B20,'VS×ケイパビリティ関係'!$G$4:$G$341,J$5,'VS×ケイパビリティ関係'!$E$4:$E$341,"主")>0,"●",IF(COUNTIFS('VS×ケイパビリティ関係'!$F$4:$F$341,$B20,'VS×ケイパビリティ関係'!$G$4:$G$341,J$5,'VS×ケイパビリティ関係'!$E$4:$E$341,"支援")>0,"○","")) | K20: =IF(COUNTIFS('VS×ケイパビリティ関係'!$F$4:$F$341,$B20,'VS×ケイパビリティ関係'!$G$4:$G$341,K$5,'VS×ケイパビリティ関係'!$E$4:$E$341,"主")>0,"●",IF(COUNTIFS('VS×ケイパビリティ関係'!$F$4:$F$341,$B20,'VS×ケイパビリティ関係'!$G$4:$G$341,K$5,'VS×ケイパビリティ関係'!$E$4:$E$341,"支援")>0,"○","")) | ... AE20: =IF(COUNTIFS('VS×ケイパビリティ関係'!$F$4:$F$341,$B20,'VS×ケイパビリティ関係'!$G$4:$G$341,AE$5,'VS×ケイパビリティ関係'!$E$4:$E$341,"主")>0,"●",IF(COUNTIFS('VS×ケイパビリティ関係'!$F$4:$F$341,$B20,'VS×ケイパビリティ関係'!$G$4:$G$341,AE$5,'VS×ケイパビリティ関係'!$E$4:$E$341,"支援")>0,"○","")) | AF20: =COUNTIF(D20:AE20,"●") | AG20: =COUNTIF(D20:AE20,"○")
B21: 04-04 | C21: 定期評価・継続的改善 | D21: =IF(COUNTIFS('VS×ケイパビリティ関係'!$F$4:$F$341,$B21,'VS×ケイパビリティ関係'!$G$4:$G$341,D$5,'VS×ケイパビリティ関係'!$E$4:$E$341,"主")>0,"●",IF(COUNTIFS('VS×ケイパビリティ関係'!$F$4:$F$341,$B21,'VS×ケイパビリティ関係'!$G$4:$G$341,D$5,'VS×ケイパビリティ関係'!$E$4:$E$341,"支援")>0,"○","")) | E21: =IF(COUNTIFS('VS×ケイパビリティ関係'!$F$4:$F$341,$B21,'VS×ケイパビリティ関係'!$G$4:$G$341,E$5,'VS×ケイパビリティ関係'!$E$4:$E$341,"主")>0,"●",IF(COUNTIFS('VS×ケイパビリティ関係'!$F$4:$F$341,$B21,'VS×ケイパビリティ関係'!$G$4:$G$341,E$5,'VS×ケイパビリティ関係'!$E$4:$E$341,"支援")>0,"○","")) | F21: =IF(COUNTIFS('VS×ケイパビリティ関係'!$F$4:$F$341,$B21,'VS×ケイパビリティ関係'!$G$4:$G$341,F$5,'VS×ケイパビリティ関係'!$E$4:$E$341,"主")>0,"●",IF(COUNTIFS('VS×ケイパビリティ関係'!$F$4:$F$341,$B21,'VS×ケイパビリティ関係'!$G$4:$G$341,F$5,'VS×ケイパビリティ関係'!$E$4:$E$341,"支援")>0,"○","")) | G21: =IF(COUNTIFS('VS×ケイパビリティ関係'!$F$4:$F$341,$B21,'VS×ケイパビリティ関係'!$G$4:$G$341,G$5,'VS×ケイパビリティ関係'!$E$4:$E$341,"主")>0,"●",IF(COUNTIFS('VS×ケイパビリティ関係'!$F$4:$F$341,$B21,'VS×ケイパビリティ関係'!$G$4:$G$341,G$5,'VS×ケイパビリティ関係'!$E$4:$E$341,"支援")>0,"○","")) | H21: =IF(COUNTIFS('VS×ケイパビリティ関係'!$F$4:$F$341,$B21,'VS×ケイパビリティ関係'!$G$4:$G$341,H$5,'VS×ケイパビリティ関係'!$E$4:$E$341,"主")>0,"●",IF(COUNTIFS('VS×ケイパビリティ関係'!$F$4:$F$341,$B21,'VS×ケイパビリティ関係'!$G$4:$G$341,H$5,'VS×ケイパビリティ関係'!$E$4:$E$341,"支援")>0,"○","")) | I21: =IF(COUNTIFS('VS×ケイパビリティ関係'!$F$4:$F$341,$B21,'VS×ケイパビリティ関係'!$G$4:$G$341,I$5,'VS×ケイパビリティ関係'!$E$4:$E$341,"主")>0,"●",IF(COUNTIFS('VS×ケイパビリティ関係'!$F$4:$F$341,$B21,'VS×ケイパビリティ関係'!$G$4:$G$341,I$5,'VS×ケイパビリティ関係'!$E$4:$E$341,"支援")>0,"○","")) | J21: =IF(COUNTIFS('VS×ケイパビリティ関係'!$F$4:$F$341,$B21,'VS×ケイパビリティ関係'!$G$4:$G$341,J$5,'VS×ケイパビリティ関係'!$E$4:$E$341,"主")>0,"●",IF(COUNTIFS('VS×ケイパビリティ関係'!$F$4:$F$341,$B21,'VS×ケイパビリティ関係'!$G$4:$G$341,J$5,'VS×ケイパビリティ関係'!$E$4:$E$341,"支援")>0,"○","")) | K21: =IF(COUNTIFS('VS×ケイパビリティ関係'!$F$4:$F$341,$B21,'VS×ケイパビリティ関係'!$G$4:$G$341,K$5,'VS×ケイパビリティ関係'!$E$4:$E$341,"主")>0,"●",IF(COUNTIFS('VS×ケイパビリティ関係'!$F$4:$F$341,$B21,'VS×ケイパビリティ関係'!$G$4:$G$341,K$5,'VS×ケイパビリティ関係'!$E$4:$E$341,"支援")>0,"○","")) | ... AE21: =IF(COUNTIFS('VS×ケイパビリティ関係'!$F$4:$F$341,$B21,'VS×ケイパビリティ関係'!$G$4:$G$341,AE$5,'VS×ケイパビリティ関係'!$E$4:$E$341,"主")>0,"●",IF(COUNTIFS('VS×ケイパビリティ関係'!$F$4:$F$341,$B21,'VS×ケイパビリティ関係'!$G$4:$G$341,AE$5,'VS×ケイパビリティ関係'!$E$4:$E$341,"支援")>0,"○","")) | AF21: =COUNTIF(D21:AE21,"●") | AG21: =COUNTIF(D21:AE21,"○")

Sheet 情報オブジェクト
A1: 情報オブジェクト（正本：用語集と分類）
A2: 1行1オブジェクト。業務上ひとまとまりで管理される情報の単位（状態の違いは属性として扱う）。名称・分類・オーナーはこのシートで編集する。灰色の列は数式（編集しない）。GxP記録の対象：関連法令・規制にGxPを含むもの。ER/ES指針の要件（監査証跡・電子署名・保存）を満たすべき電子記録の候補。
A3: ID | B3: 領域 | C3: 情報オブジェクト | D3: 英語名 | E3: 説明 | F3: データ種別 | G3: 関連法令・規制 | H3: GxP記録 の対象 | I3: 個人情報 | J3: オーナー ケイパビリティL2 ID | K3: オーナー ケイパビリティL2 | L3: 作成する ケイパビリティL2の数 | M3: 利用する ケイパビリティL2の数
A4: MST-01 | B4: 共通・マスタ | C4: アプリケーション台帳 | D4: Application Inventory | E4: 全アプリケーションの名称・オーナー・GxP区分・ライフサイクルの状態・委託先 | F4: マスタ | G4: GxP | H4: =IF(ISNUMBER(SEARCH("GxP",G4)),"対象候補","—") | I4: なし | J4: C01-02 | K4: =IFERROR(INDEX(ケイパビリティマップ!$E:$E,MATCH(J4,ケイパビリティマップ!$A:$A,0)),"（IDなし）") | L4: =COUNTIF('ケイパビリティ×情報オブジェクト'!D$6:D$33,"C") | M4: =COUNTIF('ケイパビリティ×情報オブジェクト'!D$6:D$33,"R")
A5: MST-02 | B5: 共通・マスタ | C5: 構成情報 | D5: Configuration Item (CMDB) | E5: システムを構成するサーバー・ソフトウェア・設定・連携と、その関係 | F5: マスタ | G5: 金商法 | H5: =IF(ISNUMBER(SEARCH("GxP",G5)),"対象候補","—") | I5: なし | J5: C03-05 | K5: =IFERROR(INDEX(ケイパビリティマップ!$E:$E,MATCH(J5,ケイパビリティマップ!$A:$A,0)),"（IDなし）") | L5: =COUNTIF('ケイパビリティ×情報オブジェクト'!E$6:E$33,"C") | M5: =COUNTIF('ケイパビリティ×情報オブジェクト'!E$6:E$33,"R")
A6: MST-03 | B6: 共通・マスタ | C6: IT資産・ライセンス台帳 | D6: IT Asset & License Register | E6: 端末・機器の所在・利用者と、ソフトウェアライセンス・SaaSの契約・割当 | F6: マスタ | G6: なし | H6: =IF(ISNUMBER(SEARCH("GxP",G6)),"対象候補","—") | I6: 従業員 | J6: C04-04 | K6: =IFERROR(INDEX(ケイパビリティマップ!$E:$E,MATCH(J6,ケイパビリティマップ!$A:$A,0)),"（IDなし）") | L6: =COUNTIF('ケイパビリティ×情報オブジェクト'!F$6:F$33,"C") | M6: =COUNTIF('ケイパビリティ×情報オブジェクト'!F$6:F$33,"R")
A7: MST-04 | B7: 共通・マスタ | C7: ITサービスカタログ | D7: IT Service Catalog | E7: 提供するITサービスの内容・条件・申請方法・承認者 | F7: 定義・仕様 | G7: なし | H7: =IF(ISNUMBER(SEARCH("GxP",G7)),"対象候補","—") | I7: なし | J7: C03-01 | K7: =IFERROR(INDEX(ケイパビリティマップ!$E:$E,MATCH(J7,ケイパビリティマップ!$A:$A,0)),"（IDなし）") | L7: =COUNTIF('ケイパビリティ×情報オブジェクト'!G$6:G$33,"C") | M7: =COUNTIF('ケイパビリティ×情報オブジェクト'!G$6:G$33,"R")
A8: MST-05 | B8: 共通・マスタ | C8: ID・アカウント情報 | D8: Identity & Account | E8: 利用者のID・所属・雇用状態と、各システムのアカウント | F8: マスタ | G8: GxP・金商法 | H8: =IF(ISNUMBER(SEARCH("GxP",G8)),"対象候補","—") | I8: 従業員 | J8: C05-02 | K8: =IFERROR(INDEX(ケイパビリティマップ!$E:$E,MATCH(J8,ケイパビリティマップ!$A:$A,0)),"（IDなし）") | L8: =COUNTIF('ケイパビリティ×情報オブジェクト'!H$6:H$33,"C") | M8: =COUNTIF('ケイパビリティ×情報オブジェクト'!H$6:H$33,"R")
A9: MST-06 | B9: 共通・マスタ | C9: データ定義・データカタログ | D9: Data Definition & Catalog | E9: データ項目の定義・所在・正本・責任者と、マスタデータの定義 | F9: 定義・仕様 | G9: なし | H9: =IF(ISNUMBER(SEARCH("GxP",G9)),"対象候補","—") | I9: なし | J9: C06-03 | K9: =IFERROR(INDEX(ケイパビリティマップ!$E:$E,MATCH(J9,ケイパビリティマップ!$A:$A,0)),"（IDなし）") | L9: =COUNTIF('ケイパビリティ×情報オブジェクト'!I$6:I$33,"C") | M9: =COUNTIF('ケイパビリティ×情報オブジェクト'!I$6:I$33,"R")
A10: MST-07 | B10: 共通・マスタ | C10: ベンダー情報 | D10: Vendor Profile | E10: 委託先・SaaS事業者の名称・取引の区分（取適法の対象か）・担当範囲・資格 | F10: マスタ | G10: 取適法 | H10: =IF(ISNUMBER(SEARCH("GxP",G10)),"対象候補","—") | I10: なし | J10: C07-01 | K10: =IFERROR(INDEX(ケイパビリティマップ!$E:$E,MATCH(J10,ケイパビリティマップ!$A:$A,0)),"（IDなし）") | L10: =COUNTIF('ケイパビリティ×情報オブジェクト'!J$6:J$33,"C") | M10: =COUNTIF('ケイパビリティ×情報オブジェクト'!J$6:J$33,"R")
A11: STR-01 | B11: 戦略・投資 | C11: 事業戦略・DX方針 | D11: Business Strategy & DX Policy | E11: 中期経営計画、事業部門の戦略、DXの方針（ITが受け取る入力） | F11: 文書 | G11: なし | H11: =IF(ISNUMBER(SEARCH("GxP",G11)),"対象候補","—") | I11: なし | J11: C01-01 | K11: =IFERROR(INDEX(ケイパビリティマップ!$E:$E,MATCH(J11,ケイパビリティマップ!$A:$A,0)),"（IDなし）") | L11: =COUNTIF('ケイパビリティ×情報オブジェクト'!K$6:K$33,"C") | M11: =COUNTIF('ケイパビリティ×情報オブジェクト'!K$6:K$33,"R")
A12: STR-02 | B12: 戦略・投資 | C12: IT戦略・ロードマップ | D12: IT Strategy & Roadmap | E12: ITの目標・重点施策と、中長期の実行計画 | F12: 文書 | G12: なし | H12: =IF(ISNUMBER(SEARCH("GxP",G12)),"対象候補","—") | I12: なし | J12: C01-01 | K12: =IFERROR(INDEX(ケイパビリティマップ!$E:$E,MATCH(J12,ケイパビリティマップ!$A:$A,0)),"（IDなし）") | L12: =COUNTIF('ケイパビリティ×情報オブジェクト'!L$6:L$33,"C") | M12: =COUNTIF('ケイパビリティ×情報オブジェクト'!L$6:L$33,"R")
A13: STR-03 | B13: 戦略・投資 | C13: エンタープライズアーキテクチャ | D13: Enterprise Architecture | E13: 業務・アプリケーション・データ・技術の現状と将来像、移行の道筋 | F13: 定義・仕様 | G13: なし | H13: =IF(ISNUMBER(SEARCH("GxP",G13)),"対象候補","—") | I13: なし | J13: C01-02 | K13: =IFERROR(INDEX(ケイパビリティマップ!$E:$E,MATCH(J13,ケイパビリティマップ!$A:$A,0)),"（IDなし）") | L13: =COUNTIF('ケイパビリティ×情報オブジェクト'!M$6:M$33,"C") | M13: =COUNTIF('ケイパビリティ×情報オブジェクト'!M$6:M$33,"R")
A14: STR-04 | B14: 戦略・投資 | C14: 技術標準 | D14: Technology Standards | E14: 採用する技術・製品・連携方式の標準と、例外の記録 | F14: 定義・仕様 | G14: なし | H14: =IF(ISNUMBER(SEARCH("GxP",G14)),"対象候補","—") | I14: なし | J14: C01-02 | K14: =IFERROR(INDEX(ケイパビリティマップ!$E:$E,MATCH(J14,ケイパビリティマップ!$A:$A,0)),"（IDなし）") | L14: =COUNTIF('ケイパビリティ×情報オブジェクト'!N$6:N$33,"C") | M14: =COUNTIF('ケイパビリティ×情報オブジェクト'!N$6:N$33,"R")
A15: STR-05 | B15: 戦略・投資 | C15: IT規程・手順書 | D15: IT Policies & SOPs | E15: IT規程と、CSV・変更管理・アクセス管理・バックアップなどの標準手順書 | F15: 文書 | G15: GxP・金商法 | H15: =IF(ISNUMBER(SEARCH("GxP",G15)),"対象候補","—") | I15: なし | J15: C01-04 | K15: =IFERROR(INDEX(ケイパビリティマップ!$E:$E,MATCH(J15,ケイパビリティマップ!$A:$A,0)),"（IDなし）") | L15: =COUNTIF('ケイパビリティ×情報オブジェクト'!O$6:O$33,"C") | M15: =COUNTIF('ケイパビリティ×情報オブジェクト'!O$6:O$33,"R")
A16: STR-06 | B16: 戦略・投資 | C16: IT投資要求 | D16: IT Demand Request | E16: 事業部門からのIT需要・改善要求（目的・範囲・期限） | F16: トランザクション | G16: なし | H16: =IF(ISNUMBER(SEARCH("GxP",G16)),"対象候補","—") | I16: なし | J16: C01-03 | K16: =IFERROR(INDEX(ケイパビリティマップ!$E:$E,MATCH(J16,ケイパビリティマップ!$A:$A,0)),"（IDなし）") | L16: =COUNTIF('ケイパビリティ×情報オブジェクト'!P$6:P$33,"C") | M16: =COUNTIF('ケイパビリティ×情報オブジェクト'!P$6:P$33,"R")
A17: STR-07 | B17: 戦略・投資 | C17: ビジネスケース | D17: Business Case | E17: 構想・概算見積・効果・リスクと、内製・委託・SaaSのソーシング方針 | F17: 文書 | G17: なし | H17: =IF(ISNUMBER(SEARCH("GxP",G17)),"対象候補","—") | I17: なし | J17: C01-03 | K17: =IFERROR(INDEX(ケイパビリティマップ!$E:$E,MATCH(J17,ケイパビリティマップ!$A:$A,0)),"（IDなし）") | L17: =COUNTIF('ケイパビリティ×情報オブジェクト'!Q$6:Q$33,"C") | M17: =COUNTIF('ケイパビリティ×情報オブジェクト'!Q$6:Q$33,"R")
A18: STR-08 | B18: 戦略・投資 | C18: ITポートフォリオ | D18: IT Portfolio | E18: 投資案件と既存システムの一覧・評価・優先順位・継続／廃止の判断 | F18: 分析・評価 | G18: なし | H18: =IF(ISNUMBER(SEARCH("GxP",G18)),"対象候補","—") | I18: なし | J18: C01-03 | K18: =IFERROR(INDEX(ケイパビリティマップ!$E:$E,MATCH(J18,ケイパビリティマップ!$A:$A,0)),"（IDなし）") | L18: =COUNTIF('ケイパビリティ×情報オブジェクト'!R$6:R$33,"C") | M18: =COUNTIF('ケイパビリティ×情報オブジェクト'!R$6:R$33,"R")
A19: STR-09 | B19: 戦略・投資 | C19: IT予算・費用実績 | D19: IT Budget & Actuals | E19: IT予算の配分と、案件・サービス別の費用の実績 | F19: トランザクション | G19: なし | H19: =IF(ISNUMBER(SEARCH("GxP",G19)),"対象候補","—") | I19: なし | J19: C01-05 | K19: =IFERROR(INDEX(ケイパビリティマップ!$E:$E,MATCH(J19,ケイパビリティマップ!$A:$A,0)),"（IDなし）") | L19: =COUNTIF('ケイパビリティ×情報オブジェクト'!S$6:S$33,"C") | M19: =COUNTIF('ケイパビリティ×情報オブジェクト'!S$6:S$33,"R")
A20: STR-10 | B20: 戦略・投資 | C20: 利用実績・費用配賦 | D20: Usage & Chargeback | E20: サービス・ライセンスの利用量と、部門への費用の配賦 | F20: 分析・評価 | G20: なし | H20: =IF(ISNUMBER(SEARCH("GxP",G20)),"対象候補","—") | I20: なし | J20: C01-05 | K20: =IFERROR(INDEX(ケイパビリティマップ!$E:$E,MATCH(J20,ケイパビリティマップ!$A:$A,0)),"（IDなし）") | L20: =COUNTIF('ケイパビリティ×情報オブジェクト'!T$6:T$33,"C") | M20: =COUNTIF('ケイパビリティ×情報オブジェクト'!T$6:T$33,"R")
A21: STR-11 | B21: 戦略・投資 | C21: ITリスク登録簿 | D21: IT Risk Register | E21: ITリスク（老朽化・ベンダー依存・統制の不備など）の評価と対策の状況 | F21: 分析・評価 | G21: 金商法 | H21: =IF(ISNUMBER(SEARCH("GxP",G21)),"対象候補","—") | I21: なし | J21: C01-04 | K21: =IFERROR(INDEX(ケイパビリティマップ!$E:$E,MATCH(J21,ケイパビリティマップ!$A:$A,0)),"（IDなし）") | L21: =COUNTIF('ケイパビリティ×情報オブジェクト'!U$6:U$33,"C") | M21: =COUNTIF('ケイパビリティ×情報オブジェクト'!U$6:U$33,"R")
A22: DEV-01 | B22: 開発・導入 | C22: プロジェクト計画 | D22: Project Plan | E22: 範囲・体制（内製と委託の分担）・スケジュール・課題・リスク | F22: 文書 | G22: なし | H22: =IF(ISNUMBER(SEARCH("GxP",G22)),"対象候補","—") | I22: なし | J22: C02-01 | K22: =IFERROR(INDEX(ケイパビリティマップ!$E:$E,MATCH(J22,ケイパビリティマップ!$A:$A,0)),"（IDなし）") | L22: =COUNTIF('ケイパビリティ×情報オブジェクト'!V$6:V$33,"C") | M22: =COUNTIF('ケイパビリティ×情報オブジェクト'!V$6:V$33,"R")
A23: DEV-02 | B23: 開発・導入 | C23: 要求仕様書（URS） | D23: User Requirements Specification | E23: 業務の要求、GxP・データインテグリティの要求、受入の基準 | F23: 定義・仕様 | G23: GxP | H23: =IF(ISNUMBER(SEARCH("GxP",G23)),"対象候補","—") | I23: なし | J23: C02-02 | K23: =IFERROR(INDEX(ケイパビリティマップ!$E:$E,MATCH(J23,ケイパビリティマップ!$A:$A,0)),"（IDなし）") | L23: =COUNTIF('ケイパビリティ×情報オブジェクト'!W$6:W$33,"C") | M23: =COUNTIF('ケイパビリティ×情報オブジェクト'!W$6:W$33,"R")
A24: DEV-03 | B24: 開発・導入 | C24: 設計書（機能・設計仕様） | D24: Functional & Design Specification | E24: 機能・データ・画面・構成・連携と、アクセス制御・監査証跡・電子署名の設計 | F24: 定義・仕様 | G24: GxP | H24: =IF(ISNUMBER(SEARCH("GxP",G24)),"対象候補","—") | I24: なし | J24: C02-02 | K24: =IFERROR(INDEX(ケイパビリティマップ!$E:$E,MATCH(J24,ケイパビリティマップ!$A:$A,0)),"（IDなし）") | L24: =COUNTIF('ケイパビリティ×情報オブジェクト'!X$6:X$33,"C") | M24: =COUNTIF('ケイパビリティ×情報オブジェクト'!X$6:X$33,"R")
A25: DEV-04 | B25: 開発・導入 | C25: ソースコード・構成設定 | D25: Source Code & Configuration | E25: ソースコードと、パッケージ・SaaSの設定値（版の管理を含む） | F25: 定義・仕様 | G25: なし | H25: =IF(ISNUMBER(SEARCH("GxP",G25)),"対象候補","—") | I25: なし | J25: C02-03 | K25: =IFERROR(INDEX(ケイパビリティマップ!$E:$E,MATCH(J25,ケイパビリティマップ!$A:$A,0)),"（IDなし）") | L25: =COUNTIF('ケイパビリティ×情報オブジェクト'!Y$6:Y$33,"C") | M25: =COUNTIF('ケイパビリティ×情報オブジェクト'!Y$6:Y$33,"R")
A26: DEV-05 | B26: 開発・導入 | C26: テスト記録 | D26: Test Records | E26: テストの手順・結果・不具合と、IQ・OQ・PQ・UATの実施記録 | F26: 測定データ | G26: GxP | H26: =IF(ISNUMBER(SEARCH("GxP",G26)),"対象候補","—") | I26: なし | J26: C02-04 | K26: =IFERROR(INDEX(ケイパビリティマップ!$E:$E,MATCH(J26,ケイパビリティマップ!$A:$A,0)),"（IDなし）") | L26: =COUNTIF('ケイパビリティ×情報オブジェクト'!Z$6:Z$33,"C") | M26: =COUNTIF('ケイパビリティ×情報オブジェクト'!Z$6:Z$33,"R")
A27: DEV-06 | B27: 開発・導入 | C27: リリース・移行計画 | D27: Release & Migration Plan | E27: リリースの手順・判定基準と、データ移行の方法・検証方法 | F27: 文書 | G27: GxP | H27: =IF(ISNUMBER(SEARCH("GxP",G27)),"対象候補","—") | I27: なし | J27: C02-04 | K27: =IFERROR(INDEX(ケイパビリティマップ!$E:$E,MATCH(J27,ケイパビリティマップ!$A:$A,0)),"（IDなし）") | L27: =COUNTIF('ケイパビリティ×情報オブジェクト'!AA$6:AA$33,"C") | M27: =COUNTIF('ケイパビリティ×情報オブジェクト'!AA$6:AA$33,"R")
A28: GXP-01 | B28: GxP・データ | C28: GxP該当性評価 | D28: GxP Assessment & System Classification | E28: GxPへの該当性、ソフトウェアのカテゴリ、影響する記録・業務 | F28: 分析・評価 | G28: GxP | H28: =IF(ISNUMBER(SEARCH("GxP",G28)),"対象候補","—") | I28: なし | J28: C06-01 | K28: =IFERROR(INDEX(ケイパビリティマップ!$E:$E,MATCH(J28,ケイパビリティマップ!$A:$A,0)),"（IDなし）") | L28: =COUNTIF('ケイパビリティ×情報オブジェクト'!AB$6:AB$33,"C") | M28: =COUNTIF('ケイパビリティ×情報オブジェクト'!AB$6:AB$33,"R")
A29: GXP-02 | B29: GxP・データ | C29: リスクアセスメント | D29: Risk Assessment | E29: 機能ごとの患者安全・製品品質・データインテグリティへのリスクと、管理策 | F29: 分析・評価 | G29: GxP | H29: =IF(ISNUMBER(SEARCH("GxP",G29)),"対象候補","—") | I29: なし | J29: C06-01 | K29: =IFERROR(INDEX(ケイパビリティマップ!$E:$E,MATCH(J29,ケイパビリティマップ!$A:$A,0)),"（IDなし）") | L29: =COUNTIF('ケイパビリティ×情報オブジェクト'!AC$6:AC$33,"C") | M29: =COUNTIF('ケイパビリティ×情報オブジェクト'!AC$6:AC$33,"R")
A30: GXP-03 | B30: GxP・データ | C30: バリデーション計画書 | D30: Validation Plan | E30: バリデーションの範囲・方法・体制・受入の基準 | F30: 文書 | G30: GxP | H30: =IF(ISNUMBER(SEARCH("GxP",G30)),"対象候補","—") | I30: なし | J30: C06-01 | K30: =IFERROR(INDEX(ケイパビリティマップ!$E:$E,MATCH(J30,ケイパビリティマップ!$A:$A,0)),"（IDなし）") | L30: =COUNTIF('ケイパビリティ×情報オブジェクト'!AD$6:AD$33,"C") | M30: =COUNTIF('ケイパビリティ×情報オブジェクト'!AD$6:AD$33,"R")
A31: GXP-04 | B31: GxP・データ | C31: バリデーション報告書 | D31: Validation Report | E31: 適格性確認の結果・逸脱・トレーサビリティと、使用可否の結論 | F31: 文書 | G31: GxP | H31: =IF(ISNUMBER(SEARCH("GxP",G31)),"対象候補","—") | I31: なし | J31: C06-01 | K31: =IFERROR(INDEX(ケイパビリティマップ!$E:$E,MATCH(J31,ケイパビリティマップ!$A:$A,0)),"（IDなし）") | L31: =COUNTIF('ケイパビリティ×情報オブジェクト'!AE$6:AE$33,"C") | M31: =COUNTIF('ケイパビリティ×情報オブジェクト'!AE$6:AE$33,"R")
A32: GXP-05 | B32: GxP・データ | C32: 定期レビュー記録 | D32: Periodic Review Record | E32: GxPシステムの変更・障害・アクセス権・監査証跡の見直しの結果と是正 | F32: 分析・評価 | G32: GxP | H32: =IF(ISNUMBER(SEARCH("GxP",G32)),"対象候補","—") | I32: なし | J32: C06-01 | K32: =IFERROR(INDEX(ケイパビリティマップ!$E:$E,MATCH(J32,ケイパビリティマップ!$A:$A,0)),"（IDなし）") | L32: =COUNTIF('ケイパビリティ×情報オブジェクト'!AF$6:AF$33,"C") | M32: =COUNTIF('ケイパビリティ×情報オブジェクト'!AF$6:AF$33,"R")
A33: GXP-06 | B33: GxP・データ | C33: 監査証跡・電子署名記録 | D33: Audit Trail & E-Signature | E33: 電子記録の作成・変更・削除の履歴と、電子署名（誰が・いつ・何を・なぜ） | F33: トランザクション | G33: GxP | H33: =IF(ISNUMBER(SEARCH("GxP",G33)),"対象候補","—") | I33: 従業員 | J33: C06-02 | K33: =IFERROR(INDEX(ケイパビリティマップ!$E:$E,MATCH(J33,ケイパビリティマップ!$A:$A,0)),"（IDなし）") | L33: =COUNTIF('ケイパビリティ×情報オブジェクト'!AG$6:AG$33,"C") | M33: =COUNTIF('ケイパビリティ×情報オブジェクト'!AG$6:AG$33,"R")
A34: GXP-07 | B34: GxP・データ | C34: 記録保存・アーカイブ記録 | D34: Record Retention & Archive | E34: 保存期間・保存場所・移行やアーカイブの方法と、読み出しの確認の記録 | F34: 文書 | G34: GxP | H34: =IF(ISNUMBER(SEARCH("GxP",G34)),"対象候補","—") | I34: なし | J34: C06-02 | K34: =IFERROR(INDEX(ケイパビリティマップ!$E:$E,MATCH(J34,ケイパビリティマップ!$A:$A,0)),"（IDなし）") | L34: =COUNTIF('ケイパビリティ×情報オブジェクト'!AH$6:AH$33,"C") | M34: =COUNTIF('ケイパビリティ×情報オブジェクト'!AH$6:AH$33,"R")
A35: GXP-08 | B35: GxP・データ | C35: 個人情報取扱台帳 | D35: Personal Data Inventory | E35: システムごとに扱う個人情報の種類・目的・保存場所・委託先・安全管理措置 | F35: 定義・仕様 | G35: 個人情報保護法 | H35: =IF(ISNUMBER(SEARCH("GxP",G35)),"対象候補","—") | I35: なし | J35: C06-04 | K35: =IFERROR(INDEX(ケイパビリティマップ!$E:$E,MATCH(J35,ケイパビリティマップ!$A:$A,0)),"（IDなし）") | L35: =COUNTIF('ケイパビリティ×情報オブジェクト'!AI$6:AI$33,"C") | M35: =COUNTIF('ケイパビリティ×情報オブジェクト'!AI$6:AI$33,"R")
A36: SVC-01 | B36: サービス提供 | C36: サービスレベル合意（SLA） | D36: Service Level Agreement | E36: サービスの提供時間・可用性・応答・復旧の目標と、測定の方法 | F36: 定義・仕様 | G36: なし | H36: =IF(ISNUMBER(SEARCH("GxP",G36)),"対象候補","—") | I36: なし | J36: C03-01 | K36: =IFERROR(INDEX(ケイパビリティマップ!$E:$E,MATCH(J36,ケイパビリティマップ!$A:$A,0)),"（IDなし）") | L36: =COUNTIF('ケイパビリティ×情報オブジェクト'!AJ$6:AJ$33,"C") | M36: =COUNTIF('ケイパビリティ×情報オブジェクト'!AJ$6:AJ$33,"R")
A37: SVC-02 | B37: サービス提供 | C37: サービス要求 | D37: Service Request | E37: 利用者の申請（アカウント・端末・ソフトウェア・環境など）と承認・処理の記録 | F37: トランザクション | G37: なし | H37: =IF(ISNUMBER(SEARCH("GxP",G37)),"対象候補","—") | I37: 従業員 | J37: C03-02 | K37: =IFERROR(INDEX(ケイパビリティマップ!$E:$E,MATCH(J37,ケイパビリティマップ!$A:$A,0)),"（IDなし）") | L37: =COUNTIF('ケイパビリティ×情報オブジェクト'!AK$6:AK$33,"C") | M37: =COUNTIF('ケイパビリティ×情報オブジェクト'!AK$6:AK$33,"R")
A38: SVC-03 | B38: サービス提供 | C38: アクセス権記録 | D38: Access Rights Record | E38: システムごとのアクセス権の付与・変更・削除と、定期棚卸の結果 | F38: トランザクション | G38: GxP・金商法 | H38: =IF(ISNUMBER(SEARCH("GxP",G38)),"対象候補","—") | I38: 従業員 | J38: C05-02 | K38: =IFERROR(INDEX(ケイパビリティマップ!$E:$E,MATCH(J38,ケイパビリティマップ!$A:$A,0)),"（IDなし）") | L38: =COUNTIF('ケイパビリティ×情報オブジェクト'!AL$6:AL$33,"C") | M38: =COUNTIF('ケイパビリティ×情報オブジェクト'!AL$6:AL$33,"R")
A39: SVC-04 | B39: サービス提供 | C39: ナレッジ記事 | D39: Knowledge Article | E39: 障害の対処・問合せへの回答・回避策の手順 | F39: 文書 | G39: なし | H39: =IF(ISNUMBER(SEARCH("GxP",G39)),"対象候補","—") | I39: なし | J39: C07-03 | K39: =IFERROR(INDEX(ケイパビリティマップ!$E:$E,MATCH(J39,ケイパビリティマップ!$A:$A,0)),"（IDなし）") | L39: =COUNTIF('ケイパビリティ×情報オブジェクト'!AM$6:AM$33,"C") | M39: =COUNTIF('ケイパビリティ×情報オブジェクト'!AM$6:AM$33,"R")
A40: OPS-01 | B40: 運用 | C40: 監視イベント | D40: Monitoring Event | E40: 稼働・性能・容量・セキュリティの監視で検知したイベントとアラート | F40: 測定データ | G40: なし | H40: =IF(ISNUMBER(SEARCH("GxP",G40)),"対象候補","—") | I40: なし | J40: C03-03 | K40: =IFERROR(INDEX(ケイパビリティマップ!$E:$E,MATCH(J40,ケイパビリティマップ!$A:$A,0)),"（IDなし）") | L40: =COUNTIF('ケイパビリティ×情報オブジェクト'!AN$6:AN$33,"C") | M40: =COUNTIF('ケイパビリティ×情報オブジェクト'!AN$6:AN$33,"R")
A41: OPS-02 | B41: 運用 | C41: 運用記録 | D41: Operations Log | E41: ジョブの実行結果、バックアップの取得・復元テストの記録 | F41: 測定データ | G41: GxP・金商法 | H41: =IF(ISNUMBER(SEARCH("GxP",G41)),"対象候補","—") | I41: なし | J41: C03-03 | K41: =IFERROR(INDEX(ケイパビリティマップ!$E:$E,MATCH(J41,ケイパビリティマップ!$A:$A,0)),"（IDなし）") | L41: =COUNTIF('ケイパビリティ×情報オブジェクト'!AO$6:AO$33,"C") | M41: =COUNTIF('ケイパビリティ×情報オブジェクト'!AO$6:AO$33,"R")
A42: OPS-03 | B42: 運用 | C42: インシデント記録 | D42: Incident Record | E42: インシデントの内容・影響・対応・復旧と、GxPデータへの影響評価 | F42: トランザクション | G42: GxP | H42: =IF(ISNUMBER(SEARCH("GxP",G42)),"対象候補","—") | I42: なし | J42: C03-04 | K42: =IFERROR(INDEX(ケイパビリティマップ!$E:$E,MATCH(J42,ケイパビリティマップ!$A:$A,0)),"（IDなし）") | L42: =COUNTIF('ケイパビリティ×情報オブジェクト'!AP$6:AP$33,"C") | M42: =COUNTIF('ケイパビリティ×情報オブジェクト'!AP$6:AP$33,"R")
A43: OPS-04 | B43: 運用 | C43: 問題記録 | D43: Problem Record | E43: 根本原因・既知の誤り・再発防止策 | F43: トランザクション | G43: なし | H43: =IF(ISNUMBER(SEARCH("GxP",G43)),"対象候補","—") | I43: なし | J43: C03-04 | K43: =IFERROR(INDEX(ケイパビリティマップ!$E:$E,MATCH(J43,ケイパビリティマップ!$A:$A,0)),"（IDなし）") | L43: =COUNTIF('ケイパビリティ×情報オブジェクト'!AQ$6:AQ$33,"C") | M43: =COUNTIF('ケイパビリティ×情報オブジェクト'!AQ$6:AQ$33,"R")
A44: OPS-05 | B44: 運用 | C44: 変更記録 | D44: Change Record | E44: 変更要求・影響評価・承認・実施・検証の記録 | F44: トランザクション | G44: GxP・金商法 | H44: =IF(ISNUMBER(SEARCH("GxP",G44)),"対象候補","—") | I44: なし | J44: C03-05 | K44: =IFERROR(INDEX(ケイパビリティマップ!$E:$E,MATCH(J44,ケイパビリティマップ!$A:$A,0)),"（IDなし）") | L44: =COUNTIF('ケイパビリティ×情報オブジェクト'!AR$6:AR$33,"C") | M44: =COUNTIF('ケイパビリティ×情報オブジェクト'!AR$6:AR$33,"R")
A45: OPS-06 | B45: 運用 | C45: サービスレベル実績 | D45: Service Level Report | E45: SLAに対する実績（可用性・応答・復旧）と改善の状況 | F45: 分析・評価 | G45: なし | H45: =IF(ISNUMBER(SEARCH("GxP",G45)),"対象候補","—") | I45: なし | J45: C03-01 | K45: =IFERROR(INDEX(ケイパビリティマップ!$E:$E,MATCH(J45,ケイパビリティマップ!$A:$A,0)),"（IDなし）") | L45: =COUNTIF('ケイパビリティ×情報オブジェクト'!AS$6:AS$33,"C") | M45: =COUNTIF('ケイパビリティ×情報オブジェクト'!AS$6:AS$33,"R")
A46: OPS-07 | B46: 運用 | C46: IT事業継続計画 | D46: IT Continuity & DR Plan | E46: 重要システムの目標復旧時間・復旧手順・代替手段と訓練の結果 | F46: 文書 | G46: なし | H46: =IF(ISNUMBER(SEARCH("GxP",G46)),"対象候補","—") | I46: なし | J46: C03-04 | K46: =IFERROR(INDEX(ケイパビリティマップ!$E:$E,MATCH(J46,ケイパビリティマップ!$A:$A,0)),"（IDなし）") | L46: =COUNTIF('ケイパビリティ×情報オブジェクト'!AT$6:AT$33,"C") | M46: =COUNTIF('ケイパビリティ×情報オブジェクト'!AT$6:AT$33,"R")
A47: SEC-01 | B47: セキュリティ | C47: 脆弱性情報 | D47: Vulnerability Record | E47: 脆弱性の情報・影響を受ける構成・深刻度・対応状況 | F47: トランザクション | G47: なし | H47: =IF(ISNUMBER(SEARCH("GxP",G47)),"対象候補","—") | I47: なし | J47: C05-03 | K47: =IFERROR(INDEX(ケイパビリティマップ!$E:$E,MATCH(J47,ケイパビリティマップ!$A:$A,0)),"（IDなし）") | L47: =COUNTIF('ケイパビリティ×情報オブジェクト'!AU$6:AU$33,"C") | M47: =COUNTIF('ケイパビリティ×情報オブジェクト'!AU$6:AU$33,"R")
A48: SEC-02 | B48: セキュリティ | C48: セキュリティインシデント記録 | D48: Security Incident Record | E48: 攻撃・漏えいの内容・影響範囲・対応と、当局・本人への報告 | F48: トランザクション | G48: 個人情報保護法 | H48: =IF(ISNUMBER(SEARCH("GxP",G48)),"対象候補","—") | I48: なし | J48: C05-03 | K48: =IFERROR(INDEX(ケイパビリティマップ!$E:$E,MATCH(J48,ケイパビリティマップ!$A:$A,0)),"（IDなし）") | L48: =COUNTIF('ケイパビリティ×情報オブジェクト'!AV$6:AV$33,"C") | M48: =COUNTIF('ケイパビリティ×情報オブジェクト'!AV$6:AV$33,"R")
A49: SRC-01 | B49: ソーシング・人材 | C49: 委託契約・発注書 | D49: Outsourcing Contract & Order | E49: 契約形態（請負・準委任）・作業範囲・成果物・代金・支払期日・SLA・品質取決め | F49: 文書 | G49: 取適法・派遣法 | H49: =IF(ISNUMBER(SEARCH("GxP",G49)),"対象候補","—") | I49: なし | J49: C07-01 | K49: =IFERROR(INDEX(ケイパビリティマップ!$E:$E,MATCH(J49,ケイパビリティマップ!$A:$A,0)),"（IDなし）") | L49: =COUNTIF('ケイパビリティ×情報オブジェクト'!AW$6:AW$33,"C") | M49: =COUNTIF('ケイパビリティ×情報オブジェクト'!AW$6:AW$33,"R")
A50: SRC-02 | B50: ソーシング・人材 | C50: 検収記録 | D50: Acceptance Record | E50: 委託先の成果物の検査結果と検収日 | F50: トランザクション | G50: 取適法 | H50: =IF(ISNUMBER(SEARCH("GxP",G50)),"対象候補","—") | I50: なし | J50: C07-01 | K50: =IFERROR(INDEX(ケイパビリティマップ!$E:$E,MATCH(J50,ケイパビリティマップ!$A:$A,0)),"（IDなし）") | L50: =COUNTIF('ケイパビリティ×情報オブジェクト'!AX$6:AX$33,"C") | M50: =COUNTIF('ケイパビリティ×情報オブジェクト'!AX$6:AX$33,"R")
A51: SRC-03 | B51: ソーシング・人材 | C51: ベンダー評価記録 | D51: Vendor Evaluation & Audit | E51: 委託先の品質・SLA・コストの評価と、GxPの供給者監査の結果 | F51: 分析・評価 | G51: GxP | H51: =IF(ISNUMBER(SEARCH("GxP",G51)),"対象候補","—") | I51: なし | J51: C07-01 | K51: =IFERROR(INDEX(ケイパビリティマップ!$E:$E,MATCH(J51,ケイパビリティマップ!$A:$A,0)),"（IDなし）") | L51: =COUNTIF('ケイパビリティ×情報オブジェクト'!AY$6:AY$33,"C") | M51: =COUNTIF('ケイパビリティ×情報オブジェクト'!AY$6:AY$33,"R")
A52: SRC-04 | B52: ソーシング・人材 | C52: IT人材・スキル情報 | D52: IT Workforce & Skills | E52: ITの役割・人員・スキルの評価と、内製・委託の分担 | F52: マスタ | G52: なし | H52: =IF(ISNUMBER(SEARCH("GxP",G52)),"対象候補","—") | I52: 従業員 | J52: C07-02 | K52: =IFERROR(INDEX(ケイパビリティマップ!$E:$E,MATCH(J52,ケイパビリティマップ!$A:$A,0)),"（IDなし）") | L52: =COUNTIF('ケイパビリティ×情報オブジェクト'!AZ$6:AZ$33,"C") | M52: =COUNTIF('ケイパビリティ×情報オブジェクト'!AZ$6:AZ$33,"R")
A53: SRC-05 | B53: ソーシング・人材 | C53: 教育記録 | D53: Training Record | E53: GxP・システム操作・セキュリティの教育の受講と資格 | F53: トランザクション | G53: GxP | H53: =IF(ISNUMBER(SEARCH("GxP",G53)),"対象候補","—") | I53: 従業員 | J53: C07-02 | K53: =IFERROR(INDEX(ケイパビリティマップ!$E:$E,MATCH(J53,ケイパビリティマップ!$A:$A,0)),"（IDなし）") | L53: =COUNTIF('ケイパビリティ×情報オブジェクト'!BA$6:BA$33,"C") | M53: =COUNTIF('ケイパビリティ×情報オブジェクト'!BA$6:BA$33,"R")

Sheet ケイパビリティ×情報オブジェクト
A1: ケイパビリティ×情報オブジェクト（正本：行＝ケイパビリティL2 × 列＝情報オブジェクト）
A2: C＝作成・更新（その能力の中で生み出す／維持する情報。オーナーのL2は必ずC） R＝利用（その能力が入力として参照する情報） 空欄＝関係なし。VSのL4の入力情報（R）・出力情報（主の能力はC、支援の能力はR）から導いたうえで、オーナーのL2をCとした。
A4: ケイパビリティL1 | B4: L2 ID | C4: ケイパビリティL2 | D4: 共通・マスタ | K4: 戦略・投資 | V4: 開発・導入 | AB4: GxP・データ | AJ4: サービス提供 | AN4: 運用 | AU4: セキュリティ | AW4: ソーシング・人材 | BB4: Cの数 | BC4: Rの数
D5: =情報オブジェクト!C4 | E5: =情報オブジェクト!C5 | F5: =情報オブジェクト!C6 | G5: =情報オブジェクト!C7 | H5: =情報オブジェクト!C8 | I5: =情報オブジェクト!C9 | J5: =情報オブジェクト!C10 | K5: =情報オブジェクト!C11 | L5: =情報オブジェクト!C12 | M5: =情報オブジェクト!C13 | N5: =情報オブジェクト!C14 | O5: =情報オブジェクト!C15 | P5: =情報オブジェクト!C16 | Q5: =情報オブジェクト!C17 | R5: =情報オブジェクト!C18 | S5: =情報オブジェクト!C19 | T5: =情報オブジェクト!C20 | U5: =情報オブジェクト!C21 | V5: =情報オブジェクト!C22 | W5: =情報オブジェクト!C23 | X5: =情報オブジェクト!C24 | Y5: =情報オブジェクト!C25 | Z5: =情報オブジェクト!C26 | AA5: =情報オブジェクト!C27 | AB5: =情報オブジェクト!C28 | AC5: =情報オブジェクト!C29 | AD5: =情報オブジェクト!C30 | AE5: =情報オブジェクト!C31 | AF5: =情報オブジェクト!C32 | AG5: =情報オブジェクト!C33 | AH5: =情報オブジェクト!C34 | AI5: =情報オブジェクト!C35 | AJ5: =情報オブジェクト!C36 | AK5: =情報オブジェクト!C37 | AL5: =情報オブジェクト!C38 | AM5: =情報オブジェクト!C39 | AN5: =情報オブジェクト!C40 | AO5: =情報オブジェクト!C41 | AP5: =情報オブジェクト!C42 | AQ5: =情報オブジェクト!C43 | AR5: =情報オブジェクト!C44 | AS5: =情報オブジェクト!C45 | AT5: =情報オブジェクト!C46 | AU5: =情報オブジェクト!C47 | AV5: =情報オブジェクト!C48 | AW5: =情報オブジェクト!C49 | AX5: =情報オブジェクト!C50 | AY5: =情報オブジェクト!C51 | AZ5: =情報オブジェクト!C52 | BA5: =情報オブジェクト!C53
A6: C01 IT戦略・ガバナンス | B6: C01-01 | C6: =IFERROR(INDEX(ケイパビリティマップ!$E:$E,MATCH(B6,ケイパビリティマップ!$A:$A,0)),"（IDなし）") | D6: R | K6: C | L6: C | P6: R | R6: R | U6: R | BB6: =COUNTIF(D6:BA6,"C") | BC6: =COUNTIF(D6:BA6,"R")
B7: C01-02 | C7: =IFERROR(INDEX(ケイパビリティマップ!$E:$E,MATCH(B7,ケイパビリティマップ!$A:$A,0)),"（IDなし）") | D7: C | E7: R | I7: C | K7: R | L7: R | M7: C | N7: C | P7: R | Q7: R | R7: C | S7: R | U7: R | W7: R | X7: R | AH7: R | AS7: R | BB7: =COUNTIF(D7:BA7,"C") | BC7: =COUNTIF(D7:BA7,"R")
B8: C01-03 | C8: =IFERROR(INDEX(ケイパビリティマップ!$E:$E,MATCH(B8,ケイパビリティマップ!$A:$A,0)),"（IDなし）") | D8: C | J8: R | K8: R | M8: R | N8: R | O8: R | P8: C | Q8: C | R8: C | S8: R | U8: R | AB8: R | AQ8: R | AS8: R | AZ8: R | BB8: =COUNTIF(D8:BA8,"C") | BC8: =COUNTIF(D8:BA8,"R")
B9: C01-04 | C9: =IFERROR(INDEX(ケイパビリティマップ!$E:$E,MATCH(B9,ケイパビリティマップ!$A:$A,0)),"（IDなし）") | E9: R | H9: R | N9: R | O9: C | P9: R | Q9: R | R9: R | U9: C | AL9: R | AO9: R | AQ9: R | AR9: R | AS9: R | AU9: R | BB9: =COUNTIF(D9:BA9,"C") | BC9: =COUNTIF(D9:BA9,"R")
B10: C01-05 | C10: =IFERROR(INDEX(ケイパビリティマップ!$E:$E,MATCH(B10,ケイパビリティマップ!$A:$A,0)),"（IDなし）") | D10: R | M10: R | N10: R | P10: R | Q10: R | R10: R | S10: C | T10: C | AS10: R | BB10: =COUNTIF(D10:BA10,"C") | BC10: =COUNTIF(D10:BA10,"R")
A11: C02 ソリューション開発・導入 | B11: C02-01 | C11: =IFERROR(INDEX(ケイパビリティマップ!$E:$E,MATCH(B11,ケイパビリティマップ!$A:$A,0)),"（IDなし）") | J11: R | N11: R | Q11: R | R11: R | V11: C | X11: R | Y11: R | Z11: R | AW11: R | AX11: C | AY11: R | AZ11: R | BB11: =COUNTIF(D11:BA11,"C") | BC11: =COUNTIF(D11:BA11,"R")
B12: C02-02 | C12: =IFERROR(INDEX(ケイパビリティマップ!$E:$E,MATCH(B12,ケイパビリティマップ!$A:$A,0)),"（IDなし）") | I12: R | M12: R | N12: R | Q12: R | W12: C | X12: C | AC12: R | BB12: =COUNTIF(D12:BA12,"C") | BC12: =COUNTIF(D12:BA12,"R")
B13: C02-03 | C13: =IFERROR(INDEX(ケイパビリティマップ!$E:$E,MATCH(B13,ケイパビリティマップ!$A:$A,0)),"（IDなし）") | I13: R | N13: R | X13: R | Y13: C | AA13: C | BB13: =COUNTIF(D13:BA13,"C") | BC13: =COUNTIF(D13:BA13,"R")
B14: C02-04 | C14: =IFERROR(INDEX(ケイパビリティマップ!$E:$E,MATCH(B14,ケイパビリティマップ!$A:$A,0)),"（IDなし）") | D14: C | E14: C | G14: C | I14: R | W14: R | X14: R | Y14: R | Z14: C | AA14: C | AD14: R | AE14: R | BB14: =COUNTIF(D14:BA14,"C") | BC14: =COUNTIF(D14:BA14,"R")
A15: C03 ITサービス管理・運用 | B15: C03-01 | C15: =IFERROR(INDEX(ケイパビリティマップ!$E:$E,MATCH(B15,ケイパビリティマップ!$A:$A,0)),"（IDなし）") | D15: R | E15: R | G15: C | AJ15: C | AN15: R | AP15: R | AS15: C | AW15: R | AY15: R | BB15: =COUNTIF(D15:BA15,"C") | BC15: =COUNTIF(D15:BA15,"R")
B16: C03-02 | C16: =IFERROR(INDEX(ケイパビリティマップ!$E:$E,MATCH(B16,ケイパビリティマップ!$A:$A,0)),"（IDなし）") | G16: R | H16: R | AK16: C | AN16: R | AP16: C | BB16: =COUNTIF(D16:BA16,"C") | BC16: =COUNTIF(D16:BA16,"R")
B17: C03-03 | C17: =IFERROR(INDEX(ケイパビリティマップ!$E:$E,MATCH(B17,ケイパビリティマップ!$A:$A,0)),"（IDなし）") | E17: R | O17: R | AJ17: R | AN17: C | AO17: C | BB17: =COUNTIF(D17:BA17,"C") | BC17: =COUNTIF(D17:BA17,"R")
B18: C03-04 | C18: =IFERROR(INDEX(ケイパビリティマップ!$E:$E,MATCH(B18,ケイパビリティマップ!$A:$A,0)),"（IDなし）") | E18: R | AG18: R | AK18: R | AM18: C | AN18: R | AP18: C | AQ18: C | AT18: C | BB18: =COUNTIF(D18:BA18,"C") | BC18: =COUNTIF(D18:BA18,"R")
B19: C03-05 | C19: =IFERROR(INDEX(ケイパビリティマップ!$E:$E,MATCH(B19,ケイパビリティマップ!$A:$A,0)),"（IDなし）") | D19: C | E19: C | G19: C | I19: R | N19: R | R19: R | W19: R | Z19: C | AA19: R | AD19: R | AE19: R | AH19: R | AK19: R | AQ19: R | AR19: C | AU19: R | BB19: =COUNTIF(D19:BA19,"C") | BC19: =COUNTIF(D19:BA19,"R")
A20: C04 ITプラットフォーム | B20: C04-01 | C20: =IFERROR(INDEX(ケイパビリティマップ!$E:$E,MATCH(B20,ケイパビリティマップ!$A:$A,0)),"（IDなし）") | D20: R | E20: C | G20: R | N20: R | AA20: R | AE20: R | AJ20: R | AK20: R | AM20: R | AN20: R | AP20: R | AT20: R | BB20: =COUNTIF(D20:BA20,"C") | BC20: =COUNTIF(D20:BA20,"R")
B21: C04-02 | C21: =IFERROR(INDEX(ケイパビリティマップ!$E:$E,MATCH(B21,ケイパビリティマップ!$A:$A,0)),"（IDなし）") | E21: R | N21: R | AK21: R | AM21: R | AP21: R | AT21: R | BB21: =COUNTIF(D21:BA21,"C") | BC21: =COUNTIF(D21:BA21,"R")
B22: C04-03 | C22: =IFERROR(INDEX(ケイパビリティマップ!$E:$E,MATCH(B22,ケイパビリティマップ!$A:$A,0)),"（IDなし）") | E22: R | F22: C | H22: R | AK22: R | AL22: R | AN22: R | AU22: R | BB22: =COUNTIF(D22:BA22,"C") | BC22: =COUNTIF(D22:BA22,"R")
B23: C04-04 | C23: =IFERROR(INDEX(ケイパビリティマップ!$E:$E,MATCH(B23,ケイパビリティマップ!$A:$A,0)),"（IDなし）") | F23: C | H23: R | T23: C | AK23: R | BB23: =COUNTIF(D23:BA23,"C") | BC23: =COUNTIF(D23:BA23,"R")
A24: C05 サイバーセキュリティ | B24: C05-01 | C24: =IFERROR(INDEX(ケイパビリティマップ!$E:$E,MATCH(B24,ケイパビリティマップ!$A:$A,0)),"（IDなし）") | J24: R | M24: R | N24: R | O24: R | Q24: R | U24: R | W24: R | X24: R | AC24: R | AI24: R | AW24: R | AY24: R | BA24: R | BB24: =COUNTIF(D24:BA24,"C") | BC24: =COUNTIF(D24:BA24,"R")
B25: C05-02 | C25: =IFERROR(INDEX(ケイパビリティマップ!$E:$E,MATCH(B25,ケイパビリティマップ!$A:$A,0)),"（IDなし）") | E25: R | H25: C | Z25: R | AD25: R | AK25: R | AL25: C | AR25: R | BB25: =COUNTIF(D25:BA25,"C") | BC25: =COUNTIF(D25:BA25,"R")
B26: C05-03 | C26: =IFERROR(INDEX(ケイパビリティマップ!$E:$E,MATCH(B26,ケイパビリティマップ!$A:$A,0)),"（IDなし）") | E26: R | AI26: R | AN26: C | AP26: R | AR26: C | AU26: C | AV26: C | BB26: =COUNTIF(D26:BA26,"C") | BC26: =COUNTIF(D26:BA26,"R")
A27: C06 データ・GxPコンプライアンス | B27: C06-01 | C27: =IFERROR(INDEX(ケイパビリティマップ!$E:$E,MATCH(B27,ケイパビリティマップ!$A:$A,0)),"（IDなし）") | E27: C | O27: R | P27: R | V27: R | W27: R | X27: R | Z27: C | AB27: C | AC27: C | AD27: C | AE27: C | AF27: C | AG27: R | AL27: R | AP27: R | AQ27: R | AR27: C | AU27: R | BB27: =COUNTIF(D27:BA27,"C") | BC27: =COUNTIF(D27:BA27,"R")
B28: C06-02 | C28: =IFERROR(INDEX(ケイパビリティマップ!$E:$E,MATCH(B28,ケイパビリティマップ!$A:$A,0)),"（IDなし）") | D28: C | E28: R | I28: R | O28: R | R28: R | V28: R | W28: R | X28: C | Z28: R | AA28: R | AB28: R | AC28: R | AD28: R | AF28: R | AG28: C | AH28: C | AI28: C | AL28: R | AO28: R | AP28: C | AR28: R | BB28: =COUNTIF(D28:BA28,"C") | BC28: =COUNTIF(D28:BA28,"R")
B29: C06-03 | C29: =IFERROR(INDEX(ケイパビリティマップ!$E:$E,MATCH(B29,ケイパビリティマップ!$A:$A,0)),"（IDなし）") | D29: R | E29: R | I29: C | L29: R | M29: R | N29: R | W29: R | X29: R | Y29: R | Z29: R | AA29: R | AJ29: R | AN29: R | AP29: R | AS29: R | BB29: =COUNTIF(D29:BA29,"C") | BC29: =COUNTIF(D29:BA29,"R")
B30: C06-04 | C30: =IFERROR(INDEX(ケイパビリティマップ!$E:$E,MATCH(B30,ケイパビリティマップ!$A:$A,0)),"（IDなし）") | O30: R | W30: R | X30: R | AC30: R | AI30: C | AN30: R | AP30: R | AV30: C | BB30: =COUNTIF(D30:BA30,"C") | BC30: =COUNTIF(D30:BA30,"R")
A31: C07 IT組織・ソーシング基盤 | B31: C07-01 | C31: =IFERROR(INDEX(ケイパビリティマップ!$E:$E,MATCH(B31,ケイパビリティマップ!$A:$A,0)),"（IDなし）") | G31: R | J31: C | K31: R | L31: R | Q31: C | R31: R | U31: R | Z31: R | AJ31: R | AS31: R | AW31: C | AX31: C | AY31: C | AZ31: R | BB31: =COUNTIF(D31:BA31,"C") | BC31: =COUNTIF(D31:BA31,"R")
B32: C07-02 | C32: =IFERROR(INDEX(ケイパビリティマップ!$E:$E,MATCH(B32,ケイパビリティマップ!$A:$A,0)),"（IDなし）") | J32: R | O32: R | Q32: R | R32: R | V32: R | X32: R | AZ32: C | BA32: C | BB32: =COUNTIF(D32:BA32,"C") | BC32: =COUNTIF(D32:BA32,"R")
B33: C07-03 | C33: =IFERROR(INDEX(ケイパビリティマップ!$E:$E,MATCH(B33,ケイパビリティマップ!$A:$A,0)),"（IDなし）") | D33: R | E33: R | G33: R | N33: R | O33: R | U33: R | X33: R | AA33: R | AE33: R | AM33: C | AP33: R | BA33: R | BB33: =COUNTIF(D33:BA33,"C") | BC33: =COUNTIF(D33:BA33,"R")
C34: Cの数 | D34: =COUNTIF(D$6:D$33,"C") | E34: =COUNTIF(E$6:E$33,"C") | F34: =COUNTIF(F$6:F$33,"C") | G34: =COUNTIF(G$6:G$33,"C") | H34: =COUNTIF(H$6:H$33,"C") | I34: =COUNTIF(I$6:I$33,"C") | J34: =COUNTIF(J$6:J$33,"C") | K34: =COUNTIF(K$6:K$33,"C") | ... BA34: =COUNTIF(BA$6:BA$33,"C")
C35: Rの数 | D35: =COUNTIF(D$6:D$33,"R") | E35: =COUNTIF(E$6:E$33,"R") | F35: =COUNTIF(F$6:F$33,"R") | G35: =COUNTIF(G$6:G$33,"R") | H35: =COUNTIF(H$6:H$33,"R") | I35: =COUNTIF(I$6:I$33,"R") | J35: =COUNTIF(J$6:J$33,"R") | K35: =COUNTIF(K$6:K$33,"R") | ... BA35: =COUNTIF(BA$6:BA$33,"R")

Sheet アプリケーション
A1: アプリケーション（正本：種類の単位）
A2: 1行1種類。製品名ではなく、機能のまとまり（種類）で定義する。現状のシステム名との対応は別の工程で行う。灰色の列は数式（編集しない）。関連法令・規制がGxPのものは、コンピュータ化システムバリデーションの対象候補。金商法のものは、IT全般統制の評価の対象候補。
A3: ID | B3: 領域 | C3: アプリケーション種類 | D3: 略称・通称 | E3: 主な機能 | F3: 主な関連法令・規制 | G3: 主に支える ケイパビリティ数 | H3: 部分的に支える ケイパビリティ数
A4: APP-01 | B4: 戦略 | C4: ITポートフォリオ・プロジェクト管理 | D4: PPM／SPM | E4: 需要・投資案件・ポートフォリオと、プロジェクトの計画・進捗・資源を管理する | F4: なし | G4: =COUNTIF('ケイパビリティ×アプリケーション'!D$6:D$33,"●") | H4: =COUNTIF('ケイパビリティ×アプリケーション'!D$6:D$33,"○")
A5: APP-02 | B5: 戦略 | C5: EA・アプリケーションポートフォリオ管理 | D5: EAツール／APM | E5: アーキテクチャのモデルとアプリケーション台帳を管理し、ライフサイクルを評価する | F5: GxP | G5: =COUNTIF('ケイパビリティ×アプリケーション'!E$6:E$33,"●") | H5: =COUNTIF('ケイパビリティ×アプリケーション'!E$6:E$33,"○")
A6: APP-03 | B6: 戦略 | C6: IT財務管理 | D6: ITFM／TBM | E6: IT予算・費用の実績と、サービス・部門への配賦を管理する | F6: なし | G6: =COUNTIF('ケイパビリティ×アプリケーション'!F$6:F$33,"●") | H6: =COUNTIF('ケイパビリティ×アプリケーション'!F$6:F$33,"○")
A7: APP-04 | B7: 開発 | C7: 要件・テスト管理 | D7: ALM | E7: 要求・設計・テストを管理し、トレーサビリティを保つ | F7: GxP | G7: =COUNTIF('ケイパビリティ×アプリケーション'!G$6:G$33,"●") | H7: =COUNTIF('ケイパビリティ×アプリケーション'!G$6:G$33,"○")
A8: APP-05 | B8: 開発 | C8: ソースコード管理・CI/CD | D8: コードリポジトリ／CI/CDパイプライン | E8: ソースコードと設定を版管理し、ビルド・テスト・配備を自動化する | F8: なし | G8: =COUNTIF('ケイパビリティ×アプリケーション'!H$6:H$33,"●") | H8: =COUNTIF('ケイパビリティ×アプリケーション'!H$6:H$33,"○")
A9: APP-06 | B9: GxP | C9: バリデーション管理 | D9: VLMS（ペーパーレスバリデーション） | E9: バリデーションの計画・実施・承認を電子的に行い、トレーサビリティを保つ | F9: GxP | G9: =COUNTIF('ケイパビリティ×アプリケーション'!I$6:I$33,"●") | H9: =COUNTIF('ケイパビリティ×アプリケーション'!I$6:I$33,"○")
A10: APP-07 | B10: GxP | C10: 文書管理 | D10: eDMS | E10: IT規程・手順書・バリデーション文書を版管理し、承認と電子署名を行う | F10: GxP | G10: =COUNTIF('ケイパビリティ×アプリケーション'!J$6:J$33,"●") | H10: =COUNTIF('ケイパビリティ×アプリケーション'!J$6:J$33,"○")
A11: APP-08 | B11: GxP | C11: 教育管理 | D11: LMS | E11: 教育の計画・受講・記録と、資格を管理する | F11: GxP | G11: =COUNTIF('ケイパビリティ×アプリケーション'!K$6:K$33,"●") | H11: =COUNTIF('ケイパビリティ×アプリケーション'!K$6:K$33,"○")
A12: APP-09 | B12: サービス | C12: ITサービス管理 | D12: ITSM | E12: サービスデスク・申請・インシデント・問題・変更・SLAを一元管理する | F12: GxP・金商法 | G12: =COUNTIF('ケイパビリティ×アプリケーション'!L$6:L$33,"●") | H12: =COUNTIF('ケイパビリティ×アプリケーション'!L$6:L$33,"○")
A13: APP-10 | B13: サービス | C13: 構成管理データベース | D13: CMDB | E13: 構成情報と関係を管理し、変更・障害の影響範囲を示す | F13: 金商法 | G13: =COUNTIF('ケイパビリティ×アプリケーション'!M$6:M$33,"●") | H13: =COUNTIF('ケイパビリティ×アプリケーション'!M$6:M$33,"○")
A14: APP-11 | B14: 運用 | C14: 統合監視 | D14: 監視ツール／オブザーバビリティ | E14: 稼働・性能・ログを監視し、アラートを通知する | F14: なし | G14: =COUNTIF('ケイパビリティ×アプリケーション'!N$6:N$33,"●") | H14: =COUNTIF('ケイパビリティ×アプリケーション'!N$6:N$33,"○")
A15: APP-12 | B15: 運用 | C15: ジョブ管理・バックアップ | D15: ジョブスケジューラ／バックアップ | E15: ジョブを自動実行し、データをバックアップ・復元する | F15: GxP・金商法 | G15: =COUNTIF('ケイパビリティ×アプリケーション'!O$6:O$33,"●") | H15: =COUNTIF('ケイパビリティ×アプリケーション'!O$6:O$33,"○")
A16: APP-13 | B16: 基盤 | C16: クラウド管理 | D16: クラウド管理ポータル／FinOps | E16: クラウドの環境・設定・利用量・費用を管理する | F16: なし | G16: =COUNTIF('ケイパビリティ×アプリケーション'!P$6:P$33,"●") | H16: =COUNTIF('ケイパビリティ×アプリケーション'!P$6:P$33,"○")
A17: APP-14 | B17: 基盤 | C17: ネットワーク管理 | D17: NMS／SASE | E17: ネットワーク機器・接続と、社外からの安全な接続を管理する | F17: なし | G17: =COUNTIF('ケイパビリティ×アプリケーション'!Q$6:Q$33,"●") | H17: =COUNTIF('ケイパビリティ×アプリケーション'!Q$6:Q$33,"○")
A18: APP-15 | B18: 基盤 | C18: エンドポイント管理 | D18: UEM（MDM） | E18: 端末の設定・配布・更新・紛失時の対応を管理する | F18: なし | G18: =COUNTIF('ケイパビリティ×アプリケーション'!R$6:R$33,"●") | H18: =COUNTIF('ケイパビリティ×アプリケーション'!R$6:R$33,"○")
A19: APP-16 | B19: 基盤 | C19: コラボレーション基盤 | D19: メール・会議・ファイル共有 | E19: メール・会議・チャット・ファイル共有を提供する | F19: 個人情報保護法 | G19: =COUNTIF('ケイパビリティ×アプリケーション'!S$6:S$33,"●") | H19: =COUNTIF('ケイパビリティ×アプリケーション'!S$6:S$33,"○")
A20: APP-17 | B20: 基盤 | C20: IT資産・ライセンス管理 | D20: ITAM／SAM | E20: ハードウェア資産とライセンス・SaaSの割当・利用を管理する | F20: なし | G20: =COUNTIF('ケイパビリティ×アプリケーション'!T$6:T$33,"●") | H20: =COUNTIF('ケイパビリティ×アプリケーション'!T$6:T$33,"○")
A21: APP-18 | B21: セキュリティ | C21: ID・アクセス管理 | D21: IAM／IGA・SSO | E21: IDのライフサイクル・認証・権限の付与と棚卸を管理する | F21: GxP・金商法 | G21: =COUNTIF('ケイパビリティ×アプリケーション'!U$6:U$33,"●") | H21: =COUNTIF('ケイパビリティ×アプリケーション'!U$6:U$33,"○")
A22: APP-19 | B22: セキュリティ | C22: 特権ID管理 | D22: PAM | E22: 管理者権限の貸出・記録・点検を行う | F22: GxP・金商法 | G22: =COUNTIF('ケイパビリティ×アプリケーション'!V$6:V$33,"●") | H22: =COUNTIF('ケイパビリティ×アプリケーション'!V$6:V$33,"○")
A23: APP-20 | B23: セキュリティ | C23: セキュリティ監視 | D23: SIEM／EDR | E23: ログと端末を監視し、攻撃の兆候を検知・分析する | F23: なし | G23: =COUNTIF('ケイパビリティ×アプリケーション'!W$6:W$33,"●") | H23: =COUNTIF('ケイパビリティ×アプリケーション'!W$6:W$33,"○")
A24: APP-21 | B24: セキュリティ | C24: 脆弱性管理 | D24: 脆弱性スキャナ／ASM | E24: 脆弱性を検出し、深刻度と対応の状況を管理する | F24: なし | G24: =COUNTIF('ケイパビリティ×アプリケーション'!X$6:X$33,"●") | H24: =COUNTIF('ケイパビリティ×アプリケーション'!X$6:X$33,"○")
A25: APP-22 | B25: データ | C25: マスタデータ管理・データカタログ | D25: MDM／データカタログ | E25: マスタデータの正本と、データの定義・所在・責任者を管理する | F25: なし | G25: =COUNTIF('ケイパビリティ×アプリケーション'!Y$6:Y$33,"●") | H25: =COUNTIF('ケイパビリティ×アプリケーション'!Y$6:Y$33,"○")
A26: APP-23 | B26: データ | C26: データ・分析基盤 | D26: データレイク／DWH／BI | E26: データを集約し、分析・可視化する | F26: なし | G26: =COUNTIF('ケイパビリティ×アプリケーション'!Z$6:Z$33,"●") | H26: =COUNTIF('ケイパビリティ×アプリケーション'!Z$6:Z$33,"○")
A27: APP-24 | B27: データ | C27: 個人情報管理 | D27: プライバシー管理ツール | E27: 個人情報の取扱台帳と、漏えい等の報告の対応を管理する | F27: 個人情報保護法 | G27: =COUNTIF('ケイパビリティ×アプリケーション'!AA$6:AA$33,"●") | H27: =COUNTIF('ケイパビリティ×アプリケーション'!AA$6:AA$33,"○")
A28: APP-25 | B28: 共通 | C28: GRC・IT統制管理 | D28: GRC | E28: IT規程・リスク登録簿・統制の評価・監査の指摘を管理する | F28: 金商法 | G28: =COUNTIF('ケイパビリティ×アプリケーション'!AB$6:AB$33,"●") | H28: =COUNTIF('ケイパビリティ×アプリケーション'!AB$6:AB$33,"○")
A29: APP-26 | B29: 共通 | C29: ベンダー・契約管理 | D29: CLM／購買システム | E29: 委託先の情報・契約・発注・検収と評価を管理する | F29: 取適法 | G29: =COUNTIF('ケイパビリティ×アプリケーション'!AC$6:AC$33,"●") | H29: =COUNTIF('ケイパビリティ×アプリケーション'!AC$6:AC$33,"○")

Sheet ケイパビリティ×アプリケーション
A1: ケイパビリティ×アプリケーション（正本：行＝ケイパビリティL2 × 列＝アプリケーション種類）
A2: ●＝主に支える（その能力の中核の業務を実行するシステム） ○＝部分的に支える（一部の業務やデータの受け渡しで使う） 空欄＝関係なし。このシートに直接記入する。右端と最下行の数は数式。
A4: ケイパビリティL1 | B4: L2 ID | C4: ケイパビリティL2 | D4: 戦略 | G4: 開発 | I4: GxP | L4: サービス | N4: 運用 | P4: 基盤 | U4: セキュリティ | Y4: データ | AB4: 共通 | AD4: ●の数 | AE4: ○の数
D5: =アプリケーション!C4 | E5: =アプリケーション!C5 | F5: =アプリケーション!C6 | G5: =アプリケーション!C7 | H5: =アプリケーション!C8 | I5: =アプリケーション!C9 | J5: =アプリケーション!C10 | K5: =アプリケーション!C11 | L5: =アプリケーション!C12 | M5: =アプリケーション!C13 | N5: =アプリケーション!C14 | O5: =アプリケーション!C15 | P5: =アプリケーション!C16 | Q5: =アプリケーション!C17 | R5: =アプリケーション!C18 | S5: =アプリケーション!C19 | T5: =アプリケーション!C20 | U5: =アプリケーション!C21 | V5: =アプリケーション!C22 | W5: =アプリケーション!C23 | X5: =アプリケーション!C24 | Y5: =アプリケーション!C25 | Z5: =アプリケーション!C26 | AA5: =アプリケーション!C27 | AB5: =アプリケーション!C28 | AC5: =アプリケーション!C29
A6: C01 IT戦略・ガバナンス | B6: C01-01 | C6: =IFERROR(INDEX(ケイパビリティマップ!$E:$E,MATCH(B6,ケイパビリティマップ!$A:$A,0)),"（IDなし）") | D6: ○ | AD6: =COUNTIF(D6:AC6,"●") | AE6: =COUNTIF(D6:AC6,"○")
B7: C01-02 | C7: =IFERROR(INDEX(ケイパビリティマップ!$E:$E,MATCH(B7,ケイパビリティマップ!$A:$A,0)),"（IDなし）") | E7: ● | M7: ○ | Y7: ○ | AD7: =COUNTIF(D7:AC7,"●") | AE7: =COUNTIF(D7:AC7,"○")
B8: C01-03 | C8: =IFERROR(INDEX(ケイパビリティマップ!$E:$E,MATCH(B8,ケイパビリティマップ!$A:$A,0)),"（IDなし）") | D8: ● | E8: ○ | F8: ○ | AD8: =COUNTIF(D8:AC8,"●") | AE8: =COUNTIF(D8:AC8,"○")
B9: C01-04 | C9: =IFERROR(INDEX(ケイパビリティマップ!$E:$E,MATCH(B9,ケイパビリティマップ!$A:$A,0)),"（IDなし）") | J9: ○ | U9: ○ | AB9: ● | AD9: =COUNTIF(D9:AC9,"●") | AE9: =COUNTIF(D9:AC9,"○")
B10: C01-05 | C10: =IFERROR(INDEX(ケイパビリティマップ!$E:$E,MATCH(B10,ケイパビリティマップ!$A:$A,0)),"（IDなし）") | D10: ○ | F10: ● | P10: ○ | T10: ○ | AD10: =COUNTIF(D10:AC10,"●") | AE10: =COUNTIF(D10:AC10,"○")
A11: C02 ソリューション開発・導入 | B11: C02-01 | C11: =IFERROR(INDEX(ケイパビリティマップ!$E:$E,MATCH(B11,ケイパビリティマップ!$A:$A,0)),"（IDなし）") | D11: ● | AC11: ○ | AD11: =COUNTIF(D11:AC11,"●") | AE11: =COUNTIF(D11:AC11,"○")
B12: C02-02 | C12: =IFERROR(INDEX(ケイパビリティマップ!$E:$E,MATCH(B12,ケイパビリティマップ!$A:$A,0)),"（IDなし）") | G12: ● | AD12: =COUNTIF(D12:AC12,"●") | AE12: =COUNTIF(D12:AC12,"○")
B13: C02-03 | C13: =IFERROR(INDEX(ケイパビリティマップ!$E:$E,MATCH(B13,ケイパビリティマップ!$A:$A,0)),"（IDなし）") | G13: ○ | H13: ● | AD13: =COUNTIF(D13:AC13,"●") | AE13: =COUNTIF(D13:AC13,"○")
B14: C02-04 | C14: =IFERROR(INDEX(ケイパビリティマップ!$E:$E,MATCH(B14,ケイパビリティマップ!$A:$A,0)),"（IDなし）") | G14: ● | H14: ○ | I14: ○ | AD14: =COUNTIF(D14:AC14,"●") | AE14: =COUNTIF(D14:AC14,"○")
A15: C03 ITサービス管理・運用 | B15: C03-01 | C15: =IFERROR(INDEX(ケイパビリティマップ!$E:$E,MATCH(B15,ケイパビリティマップ!$A:$A,0)),"（IDなし）") | L15: ● | N15: ○ | Z15: ○ | AD15: =COUNTIF(D15:AC15,"●") | AE15: =COUNTIF(D15:AC15,"○")
B16: C03-02 | C16: =IFERROR(INDEX(ケイパビリティマップ!$E:$E,MATCH(B16,ケイパビリティマップ!$A:$A,0)),"（IDなし）") | L16: ● | AD16: =COUNTIF(D16:AC16,"●") | AE16: =COUNTIF(D16:AC16,"○")
B17: C03-03 | C17: =IFERROR(INDEX(ケイパビリティマップ!$E:$E,MATCH(B17,ケイパビリティマップ!$A:$A,0)),"（IDなし）") | N17: ● | O17: ● | AD17: =COUNTIF(D17:AC17,"●") | AE17: =COUNTIF(D17:AC17,"○")
B18: C03-04 | C18: =IFERROR(INDEX(ケイパビリティマップ!$E:$E,MATCH(B18,ケイパビリティマップ!$A:$A,0)),"（IDなし）") | L18: ● | M18: ○ | N18: ○ | AD18: =COUNTIF(D18:AC18,"●") | AE18: =COUNTIF(D18:AC18,"○")
B19: C03-05 | C19: =IFERROR(INDEX(ケイパビリティマップ!$E:$E,MATCH(B19,ケイパビリティマップ!$A:$A,0)),"（IDなし）") | H19: ○ | L19: ● | M19: ● | AD19: =COUNTIF(D19:AC19,"●") | AE19: =COUNTIF(D19:AC19,"○")
A20: C04 ITプラットフォーム | B20: C04-01 | C20: =IFERROR(INDEX(ケイパビリティマップ!$E:$E,MATCH(B20,ケイパビリティマップ!$A:$A,0)),"（IDなし）") | N20: ○ | P20: ● | AD20: =COUNTIF(D20:AC20,"●") | AE20: =COUNTIF(D20:AC20,"○")
B21: C04-02 | C21: =IFERROR(INDEX(ケイパビリティマップ!$E:$E,MATCH(B21,ケイパビリティマップ!$A:$A,0)),"（IDなし）") | Q21: ● | AD21: =COUNTIF(D21:AC21,"●") | AE21: =COUNTIF(D21:AC21,"○")
B22: C04-03 | C22: =IFERROR(INDEX(ケイパビリティマップ!$E:$E,MATCH(B22,ケイパビリティマップ!$A:$A,0)),"（IDなし）") | R22: ● | S22: ● | AD22: =COUNTIF(D22:AC22,"●") | AE22: =COUNTIF(D22:AC22,"○")
B23: C04-04 | C23: =IFERROR(INDEX(ケイパビリティマップ!$E:$E,MATCH(B23,ケイパビリティマップ!$A:$A,0)),"（IDなし）") | M23: ○ | R23: ○ | T23: ● | AD23: =COUNTIF(D23:AC23,"●") | AE23: =COUNTIF(D23:AC23,"○")
A24: C05 サイバーセキュリティ | B24: C05-01 | C24: =IFERROR(INDEX(ケイパビリティマップ!$E:$E,MATCH(B24,ケイパビリティマップ!$A:$A,0)),"（IDなし）") | K24: ○ | AB24: ● | AD24: =COUNTIF(D24:AC24,"●") | AE24: =COUNTIF(D24:AC24,"○")
B25: C05-02 | C25: =IFERROR(INDEX(ケイパビリティマップ!$E:$E,MATCH(B25,ケイパビリティマップ!$A:$A,0)),"（IDなし）") | L25: ○ | U25: ● | V25: ● | AD25: =COUNTIF(D25:AC25,"●") | AE25: =COUNTIF(D25:AC25,"○")
B26: C05-03 | C26: =IFERROR(INDEX(ケイパビリティマップ!$E:$E,MATCH(B26,ケイパビリティマップ!$A:$A,0)),"（IDなし）") | L26: ○ | W26: ● | X26: ● | AD26: =COUNTIF(D26:AC26,"●") | AE26: =COUNTIF(D26:AC26,"○")
A27: C06 データ・GxPコンプライアンス | B27: C06-01 | C27: =IFERROR(INDEX(ケイパビリティマップ!$E:$E,MATCH(B27,ケイパビリティマップ!$A:$A,0)),"（IDなし）") | G27: ○ | I27: ● | J27: ○ | AD27: =COUNTIF(D27:AC27,"●") | AE27: =COUNTIF(D27:AC27,"○")
B28: C06-02 | C28: =IFERROR(INDEX(ケイパビリティマップ!$E:$E,MATCH(B28,ケイパビリティマップ!$A:$A,0)),"（IDなし）") | J28: ● | O28: ○ | V28: ○ | AD28: =COUNTIF(D28:AC28,"●") | AE28: =COUNTIF(D28:AC28,"○")
B29: C06-03 | C29: =IFERROR(INDEX(ケイパビリティマップ!$E:$E,MATCH(B29,ケイパビリティマップ!$A:$A,0)),"（IDなし）") | Y29: ● | Z29: ● | AD29: =COUNTIF(D29:AC29,"●") | AE29: =COUNTIF(D29:AC29,"○")
B30: C06-04 | C30: =IFERROR(INDEX(ケイパビリティマップ!$E:$E,MATCH(B30,ケイパビリティマップ!$A:$A,0)),"（IDなし）") | S30: ○ | W30: ○ | AA30: ● | AD30: =COUNTIF(D30:AC30,"●") | AE30: =COUNTIF(D30:AC30,"○")
A31: C07 IT組織・ソーシング基盤 | B31: C07-01 | C31: =IFERROR(INDEX(ケイパビリティマップ!$E:$E,MATCH(B31,ケイパビリティマップ!$A:$A,0)),"（IDなし）") | AB31: ○ | AC31: ● | AD31: =COUNTIF(D31:AC31,"●") | AE31: =COUNTIF(D31:AC31,"○")
B32: C07-02 | C32: =IFERROR(INDEX(ケイパビリティマップ!$E:$E,MATCH(B32,ケイパビリティマップ!$A:$A,0)),"（IDなし）") | K32: ● | AD32: =COUNTIF(D32:AC32,"●") | AE32: =COUNTIF(D32:AC32,"○")
B33: C07-03 | C33: =IFERROR(INDEX(ケイパビリティマップ!$E:$E,MATCH(B33,ケイパビリティマップ!$A:$A,0)),"（IDなし）") | J33: ● | L33: ○ | AD33: =COUNTIF(D33:AC33,"●") | AE33: =COUNTIF(D33:AC33,"○")
C34: ●の数 | D34: =COUNTIF(D$6:D$33,"●") | E34: =COUNTIF(E$6:E$33,"●") | F34: =COUNTIF(F$6:F$33,"●") | G34: =COUNTIF(G$6:G$33,"●") | H34: =COUNTIF(H$6:H$33,"●") | I34: =COUNTIF(I$6:I$33,"●") | J34: =COUNTIF(J$6:J$33,"●") | K34: =COUNTIF(K$6:K$33,"●") | ... AC34: =COUNTIF(AC$6:AC$33,"●")
C35: ○の数 | D35: =COUNTIF(D$6:D$33,"○") | E35: =COUNTIF(E$6:E$33,"○") | F35: =COUNTIF(F$6:F$33,"○") | G35: =COUNTIF(G$6:G$33,"○") | H35: =COUNTIF(H$6:H$33,"○") | I35: =COUNTIF(I$6:I$33,"○") | J35: =COUNTIF(J$6:J$33,"○") | K35: =COUNTIF(K$6:K$33,"○") | ... AC35: =COUNTIF(AC$6:AC$33,"○")

Sheet アプリケーション×情報オブジェクト
A1: アプリケーション×情報オブジェクト（行＝アプリケーション × 列＝情報オブジェクト）
A2: C＝作成・更新 R＝利用 空欄＝関係なし。ケイパビリティ経由で導出：アプリが●（主に支える）のL2で、そのL2がC／Rの情報オブジェクトを割り当て（CとRが重なる場合はC）
A4: 領域 | B4: ID | C4: アプリケーション種類 | D4: 共通・マスタ | K4: 戦略・投資 | V4: 開発・導入 | AB4: GxP・データ | AJ4: サービス提供 | AN4: 運用 | AU4: セキュリティ | AW4: ソーシング・人材 | BB4: Cの数 | BC4: Rの数
D5: =情報オブジェクト!C4 | E5: =情報オブジェクト!C5 | F5: =情報オブジェクト!C6 | G5: =情報オブジェクト!C7 | H5: =情報オブジェクト!C8 | I5: =情報オブジェクト!C9 | J5: =情報オブジェクト!C10 | K5: =情報オブジェクト!C11 | L5: =情報オブジェクト!C12 | M5: =情報オブジェクト!C13 | N5: =情報オブジェクト!C14 | O5: =情報オブジェクト!C15 | P5: =情報オブジェクト!C16 | Q5: =情報オブジェクト!C17 | R5: =情報オブジェクト!C18 | S5: =情報オブジェクト!C19 | T5: =情報オブジェクト!C20 | U5: =情報オブジェクト!C21 | V5: =情報オブジェクト!C22 | W5: =情報オブジェクト!C23 | X5: =情報オブジェクト!C24 | Y5: =情報オブジェクト!C25 | Z5: =情報オブジェクト!C26 | AA5: =情報オブジェクト!C27 | AB5: =情報オブジェクト!C28 | AC5: =情報オブジェクト!C29 | AD5: =情報オブジェクト!C30 | AE5: =情報オブジェクト!C31 | AF5: =情報オブジェクト!C32 | AG5: =情報オブジェクト!C33 | AH5: =情報オブジェクト!C34 | AI5: =情報オブジェクト!C35 | AJ5: =情報オブジェクト!C36 | AK5: =情報オブジェクト!C37 | AL5: =情報オブジェクト!C38 | AM5: =情報オブジェクト!C39 | AN5: =情報オブジェクト!C40 | AO5: =情報オブジェクト!C41 | AP5: =情報オブジェクト!C42 | AQ5: =情報オブジェクト!C43 | AR5: =情報オブジェクト!C44 | AS5: =情報オブジェクト!C45 | AT5: =情報オブジェクト!C46 | AU5: =情報オブジェクト!C47 | AV5: =情報オブジェクト!C48 | AW5: =情報オブジェクト!C49 | AX5: =情報オブジェクト!C50 | AY5: =情報オブジェクト!C51 | AZ5: =情報オブジェクト!C52 | BA5: =情報オブジェクト!C53
A6: 戦略 | B6: APP-01 | C6: =IFERROR(INDEX(アプリケーション!$C:$C,MATCH(B6,アプリケーション!$A:$A,0)),"（IDなし）") | D6: C | J6: R | K6: R | M6: R | N6: R | O6: R | P6: C | Q6: C | R6: C | S6: R | U6: R | V6: C | X6: R | Y6: R | Z6: R | AB6: R | AQ6: R | AS6: R | AW6: R | AX6: C | AY6: R | AZ6: R | BB6: =COUNTIF(D6:BA6,"C") | BC6: =COUNTIF(D6:BA6,"R")
B7: APP-02 | C7: =IFERROR(INDEX(アプリケーション!$C:$C,MATCH(B7,アプリケーション!$A:$A,0)),"（IDなし）") | D7: C | E7: R | I7: C | K7: R | L7: R | M7: C | N7: C | P7: R | Q7: R | R7: C | S7: R | U7: R | W7: R | X7: R | AH7: R | AS7: R | BB7: =COUNTIF(D7:BA7,"C") | BC7: =COUNTIF(D7:BA7,"R")
B8: APP-03 | C8: =IFERROR(INDEX(アプリケーション!$C:$C,MATCH(B8,アプリケーション!$A:$A,0)),"（IDなし）") | D8: R | M8: R | N8: R | P8: R | Q8: R | R8: R | S8: C | T8: C | AS8: R | BB8: =COUNTIF(D8:BA8,"C") | BC8: =COUNTIF(D8:BA8,"R")
A9: 開発 | B9: APP-04 | C9: =IFERROR(INDEX(アプリケーション!$C:$C,MATCH(B9,アプリケーション!$A:$A,0)),"（IDなし）") | D9: C | E9: C | G9: C | I9: R | M9: R | N9: R | Q9: R | W9: C | X9: C | Y9: R | Z9: C | AA9: C | AC9: R | AD9: R | AE9: R | BB9: =COUNTIF(D9:BA9,"C") | BC9: =COUNTIF(D9:BA9,"R")
B10: APP-05 | C10: =IFERROR(INDEX(アプリケーション!$C:$C,MATCH(B10,アプリケーション!$A:$A,0)),"（IDなし）") | I10: R | N10: R | X10: R | Y10: C | AA10: C | BB10: =COUNTIF(D10:BA10,"C") | BC10: =COUNTIF(D10:BA10,"R")
A11: GxP | B11: APP-06 | C11: =IFERROR(INDEX(アプリケーション!$C:$C,MATCH(B11,アプリケーション!$A:$A,0)),"（IDなし）") | E11: C | O11: R | P11: R | V11: R | W11: R | X11: R | Z11: C | AB11: C | AC11: C | AD11: C | AE11: C | AF11: C | AG11: R | AL11: R | AP11: R | AQ11: R | AR11: C | AU11: R | BB11: =COUNTIF(D11:BA11,"C") | BC11: =COUNTIF(D11:BA11,"R")
B12: APP-07 | C12: =IFERROR(INDEX(アプリケーション!$C:$C,MATCH(B12,アプリケーション!$A:$A,0)),"（IDなし）") | D12: C | E12: R | G12: R | I12: R | N12: R | O12: R | R12: R | U12: R | V12: R | W12: R | X12: C | Z12: R | AA12: R | AB12: R | AC12: R | AD12: R | AE12: R | AF12: R | AG12: C | AH12: C | AI12: C | AL12: R | AM12: C | AO12: R | AP12: C | AR12: R | BA12: R | BB12: =COUNTIF(D12:BA12,"C") | BC12: =COUNTIF(D12:BA12,"R")
B13: APP-08 | C13: =IFERROR(INDEX(アプリケーション!$C:$C,MATCH(B13,アプリケーション!$A:$A,0)),"（IDなし）") | J13: R | O13: R | Q13: R | R13: R | V13: R | X13: R | AZ13: C | BA13: C | BB13: =COUNTIF(D13:BA13,"C") | BC13: =COUNTIF(D13:BA13,"R")
A14: サービス | B14: APP-09 | C14: =IFERROR(INDEX(アプリケーション!$C:$C,MATCH(B14,アプリケーション!$A:$A,0)),"（IDなし）") | D14: C | E14: C | G14: C | H14: R | I14: R | N14: R | R14: R | W14: R | Z14: C | AA14: R | AD14: R | AE14: R | AG14: R | AH14: R | AJ14: C | AK14: C | AM14: C | AN14: R | AP14: C | AQ14: C | AR14: C | AS14: C | AT14: C | AU14: R | AW14: R | AY14: R | BB14: =COUNTIF(D14:BA14,"C") | BC14: =COUNTIF(D14:BA14,"R")
B15: APP-10 | C15: =IFERROR(INDEX(アプリケーション!$C:$C,MATCH(B15,アプリケーション!$A:$A,0)),"（IDなし）") | D15: C | E15: C | G15: C | I15: R | N15: R | R15: R | W15: R | Z15: C | AA15: R | AD15: R | AE15: R | AH15: R | AK15: R | AQ15: R | AR15: C | AU15: R | BB15: =COUNTIF(D15:BA15,"C") | BC15: =COUNTIF(D15:BA15,"R")
A16: 運用 | B16: APP-11 | C16: =IFERROR(INDEX(アプリケーション!$C:$C,MATCH(B16,アプリケーション!$A:$A,0)),"（IDなし）") | E16: R | O16: R | AJ16: R | AN16: C | AO16: C | BB16: =COUNTIF(D16:BA16,"C") | BC16: =COUNTIF(D16:BA16,"R")
B17: APP-12 | C17: =IFERROR(INDEX(アプリケーション!$C:$C,MATCH(B17,アプリケーション!$A:$A,0)),"（IDなし）") | E17: R | O17: R | AJ17: R | AN17: C | AO17: C | BB17: =COUNTIF(D17:BA17,"C") | BC17: =COUNTIF(D17:BA17,"R")
A18: 基盤 | B18: APP-13 | C18: =IFERROR(INDEX(アプリケーション!$C:$C,MATCH(B18,アプリケーション!$A:$A,0)),"（IDなし）") | D18: R | E18: C | G18: R | N18: R | AA18: R | AE18: R | AJ18: R | AK18: R | AM18: R | AN18: R | AP18: R | AT18: R | BB18: =COUNTIF(D18:BA18,"C") | BC18: =COUNTIF(D18:BA18,"R")
B19: APP-14 | C19: =IFERROR(INDEX(アプリケーション!$C:$C,MATCH(B19,アプリケーション!$A:$A,0)),"（IDなし）") | E19: R | N19: R | AK19: R | AM19: R | AP19: R | AT19: R | BB19: =COUNTIF(D19:BA19,"C") | BC19: =COUNTIF(D19:BA19,"R")
B20: APP-15 | C20: =IFERROR(INDEX(アプリケーション!$C:$C,MATCH(B20,アプリケーション!$A:$A,0)),"（IDなし）") | E20: R | F20: C | H20: R | AK20: R | AL20: R | AN20: R | AU20: R | BB20: =COUNTIF(D20:BA20,"C") | BC20: =COUNTIF(D20:BA20,"R")
B21: APP-16 | C21: =IFERROR(INDEX(アプリケーション!$C:$C,MATCH(B21,アプリケーション!$A:$A,0)),"（IDなし）") | E21: R | F21: C | H21: R | AK21: R | AL21: R | AN21: R | AU21: R | BB21: =COUNTIF(D21:BA21,"C") | BC21: =COUNTIF(D21:BA21,"R")
B22: APP-17 | C22: =IFERROR(INDEX(アプリケーション!$C:$C,MATCH(B22,アプリケーション!$A:$A,0)),"（IDなし）") | F22: C | H22: R | T22: C | AK22: R | BB22: =COUNTIF(D22:BA22,"C") | BC22: =COUNTIF(D22:BA22,"R")
A23: セキュリティ | B23: APP-18 | C23: =IFERROR(INDEX(アプリケーション!$C:$C,MATCH(B23,アプリケーション!$A:$A,0)),"（IDなし）") | E23: R | H23: C | Z23: R | AD23: R | AK23: R | AL23: C | AR23: R | BB23: =COUNTIF(D23:BA23,"C") | BC23: =COUNTIF(D23:BA23,"R")
B24: APP-19 | C24: =IFERROR(INDEX(アプリケーション!$C:$C,MATCH(B24,アプリケーション!$A:$A,0)),"（IDなし）") | E24: R | H24: C | Z24: R | AD24: R | AK24: R | AL24: C | AR24: R | BB24: =COUNTIF(D24:BA24,"C") | BC24: =COUNTIF(D24:BA24,"R")
B25: APP-20 | C25: =IFERROR(INDEX(アプリケーション!$C:$C,MATCH(B25,アプリケーション!$A:$A,0)),"（IDなし）") | E25: R | AI25: R | AN25: C | AP25: R | AR25: C | AU25: C | AV25: C | BB25: =COUNTIF(D25:BA25,"C") | BC25: =COUNTIF(D25:BA25,"R")
B26: APP-21 | C26: =IFERROR(INDEX(アプリケーション!$C:$C,MATCH(B26,アプリケーション!$A:$A,0)),"（IDなし）") | E26: R | AI26: R | AN26: C | AP26: R | AR26: C | AU26: C | AV26: C | BB26: =COUNTIF(D26:BA26,"C") | BC26: =COUNTIF(D26:BA26,"R")
A27: データ | B27: APP-22 | C27: =IFERROR(INDEX(アプリケーション!$C:$C,MATCH(B27,アプリケーション!$A:$A,0)),"（IDなし）") | D27: R | E27: R | I27: C | L27: R | M27: R | N27: R | W27: R | X27: R | Y27: R | Z27: R | AA27: R | AJ27: R | AN27: R | AP27: R | AS27: R | BB27: =COUNTIF(D27:BA27,"C") | BC27: =COUNTIF(D27:BA27,"R")
B28: APP-23 | C28: =IFERROR(INDEX(アプリケーション!$C:$C,MATCH(B28,アプリケーション!$A:$A,0)),"（IDなし）") | D28: R | E28: R | I28: C | L28: R | M28: R | N28: R | W28: R | X28: R | Y28: R | Z28: R | AA28: R | AJ28: R | AN28: R | AP28: R | AS28: R | BB28: =COUNTIF(D28:BA28,"C") | BC28: =COUNTIF(D28:BA28,"R")
B29: APP-24 | C29: =IFERROR(INDEX(アプリケーション!$C:$C,MATCH(B29,アプリケーション!$A:$A,0)),"（IDなし）") | O29: R | W29: R | X29: R | AC29: R | AI29: C | AN29: R | AP29: R | AV29: C | BB29: =COUNTIF(D29:BA29,"C") | BC29: =COUNTIF(D29:BA29,"R")
A30: 共通 | B30: APP-25 | C30: =IFERROR(INDEX(アプリケーション!$C:$C,MATCH(B30,アプリケーション!$A:$A,0)),"（IDなし）") | E30: R | H30: R | J30: R | M30: R | N30: R | O30: C | P30: R | Q30: R | R30: R | U30: C | W30: R | X30: R | AC30: R | AI30: R | AL30: R | AO30: R | AQ30: R | AR30: R | AS30: R | AU30: R | AW30: R | AY30: R | BA30: R | BB30: =COUNTIF(D30:BA30,"C") | BC30: =COUNTIF(D30:BA30,"R")
B31: APP-26 | C31: =IFERROR(INDEX(アプリケーション!$C:$C,MATCH(B31,アプリケーション!$A:$A,0)),"（IDなし）") | G31: R | J31: C | K31: R | L31: R | Q31: C | R31: R | U31: R | Z31: R | AJ31: R | AS31: R | AW31: C | AX31: C | AY31: C | AZ31: R | BB31: =COUNTIF(D31:BA31,"C") | BC31: =COUNTIF(D31:BA31,"R")
C32: Cの数 | D32: =COUNTIF(D$6:D$31,"C") | E32: =COUNTIF(E$6:E$31,"C") | F32: =COUNTIF(F$6:F$31,"C") | G32: =COUNTIF(G$6:G$31,"C") | H32: =COUNTIF(H$6:H$31,"C") | I32: =COUNTIF(I$6:I$31,"C") | J32: =COUNTIF(J$6:J$31,"C") | K32: =COUNTIF(K$6:K$31,"C") | ... BA32: =COUNTIF(BA$6:BA$31,"C")
C33: Rの数 | D33: =COUNTIF(D$6:D$31,"R") | E33: =COUNTIF(E$6:E$31,"R") | F33: =COUNTIF(F$6:F$31,"R") | G33: =COUNTIF(G$6:G$31,"R") | H33: =COUNTIF(H$6:H$31,"R") | I33: =COUNTIF(I$6:I$31,"R") | J33: =COUNTIF(J$6:J$31,"R") | K33: =COUNTIF(K$6:K$31,"R") | ... BA33: =COUNTIF(BA$6:BA$31,"R")

Sheet 選択肢（追加分）
A1: 入力規則の選択肢（追加したシート用）
A4: 共有地区分 | C4: 主従
A5: 共有地 | C5: 主
A6: 現場 | C6: 従
A7: 混在
