Workbook

Sheet バリューストリーム
A1: バリューストリーム（L1〜L4）
A2: 対象：日本の事業会社（正社員中心、新卒・経験者採用、月給制）／日本の法令・制度基準（労基法・安衛法・社会保険・税法ほか）。1行1項目。L1〜L4列の●がその行のレベル。出口はL2、入力・出力情報・関連法令・主な関与者はL4の項目。 入力情報・出力情報はVS定義の過程で得られる正本（直接入力する）。情報オブジェクトはこれを取りまとめて一覧化したもの。★＝日本の制度・雇用慣行に固有の項目。
A3: ID | B3: L1 | C3: L2 | D3: L3 | E3: L4 | F3: VS項目名 | G3: VSの定義 | H3: 出口（ゲート） | I3: 入力情報 | J3: 出力情報 | K3: 関連法令 | L3: 主な関与者（社内／外部）
A4: VS | B4: ● | F4: Hire-to-Retire | G4: 事業に必要な人材を計画・採用し、入社から育成・評価・処遇・配置を経て退職まで、従業員の雇用ライフサイクル全体を通じて組織に能力を供給し、従業員の成長と働きがいを高める
A5: 01 | C5: ● | F5: 人員計画・採用 | G5: 事業計画から必要な人材を見定め、候補者を集めて公正に選考し、内定の承諾を得るまでの段階 | H5: 内定承諾
A6: 01-01 | D6: ● | F6: 人事戦略・要員計画 | G6: 経営戦略から人事戦略と要員計画を定め、人件費予算と採用計画に落とし込む
A7: 01-01-01 | E7: ● | F7: 人事戦略・人的資本KPIの設定 | I7: 人的資本開示情報 | J7: 人事戦略・人的資本KPI | K7: なし | L7: 経営・人事企画／—
A8: 01-01-02 | E8: ● | F8: 要員計画の策定（職種・等級・雇用形態別） | I8: 人事戦略・人的資本KPI、組織マスタ、従業員マスタ | J8: 要員計画 | K8: なし | L8: 人事企画・事業部門／—
A9: 01-01-03 | E9: ● | F9: 人件費予算の策定 | I9: 要員計画、報酬テーブル、人件費実績 | J9: 人件費予算 | K9: なし | L9: 人事企画・経理／—
A10: 01-01-04 | E10: ● | F10: 職務・ポジション要件の定義 | I10: 要員計画、職務・ポジション | J10: 職務・ポジション | K10: なし | L10: 人事・配属部門／—
A11: 01-01-05 | E11: ● | F11: 採用計画の策定（新卒・経験者別の人数・時期・チャネル） | I11: 要員計画、採用チャネル実績 | J11: 採用計画 | K11: なし | L11: 採用担当・事業部門／—
A12: 01-02 | D12: ● | F12: 母集団形成 | G12: 会社の魅力を発信し、求人を公開して、応募者を集める
A13: 01-02-01 | E13: ● | F13: 採用ブランディング・採用広報 | I13: 採用計画、人的資本開示情報 | J13: 求人票 | K13: 職安法 | L13: 採用・広報／採用媒体
A14: 01-02-02 | E14: ● | F14: ★求人票の作成・公開（業務・就業場所の変更の範囲を含む労働条件の明示） | I14: 職務・ポジション、就業規則・人事規程、報酬テーブル | J14: 求人票 | K14: 職安法 | L14: 採用／求人媒体、ハローワーク
A15: 01-02-03 | E15: ● | F15: ★インターンシップ・会社説明会の運営（新卒） | I15: 採用計画、求人票 | J15: 応募者情報 | K15: 職安法・個人情報保護法 | L15: 採用・現場社員／大学、就職情報会社
A16: 01-02-04 | E16: ● | F16: 人材紹介・リファラル・ダイレクトリクルーティングの活用（経験者） | I16: 求人票 | J16: 応募者情報、採用チャネル実績 | K16: 職安法・個人情報保護法 | L16: 採用・現場社員／人材紹介会社
A17: 01-03 | D17: ● | F17: 選考 | G17: 書類・適性検査・面接で、職務への適性と能力を公正に評価し、採否を決める
A18: 01-03-01 | E18: ● | F18: 書類選考（エントリーシート・職務経歴書） | I18: 応募者情報、職務・ポジション | J18: 選考記録 | K18: 職安法・個人情報保護法 | L18: 採用・面接官／—
A19: 01-03-02 | E19: ● | F19: 適性検査・面接の実施 | I19: 応募者情報、選考記録 | J19: 選考記録 | K19: 職安法 | L19: 面接官・採用／適性検査会社
A20: 01-03-03 | E20: ● | F20: ★公正な採用選考の点検（本人に責任のない事項・思想信条を選考に用いない） | I20: 選考記録 | J20: 選考記録 | K20: 職安法 | L20: 採用・面接官／—
A21: 01-03-04 | E21: ● | F21: 採否の判定 | I21: 選考記録、採用計画 | J21: 選考記録 | K21: なし | L21: 採用・部門長／—
A22: 01-04 | D22: ● | F22: 内定 | G22: 処遇条件を決めて内定を出し、承諾を得て入社まで関係を保つ
A23: 01-04-01 | E23: ● | F23: 処遇条件の決定・オファー提示 | I23: 選考記録、報酬テーブル、等級制度 | J23: 内定・オファー | K23: 職安法 | L23: 採用・人事企画／—
A24: 01-04-02 | E24: ● | F24: ★内定通知・内定承諾の取得（労働条件の明示を含む） | I24: 内定・オファー、就業規則・人事規程 | J24: 内定・オファー | K24: 職安法・労基法 | L24: 採用／—
A25: 01-04-03 | E25: ● | F25: ★内定者フォロー（内定式・内定者研修、辞退の防止） | I25: 内定・オファー、応募者情報 | J25: 内定・オファー | K25: なし | L25: 採用・現場社員／—
A26: 01-04-04 | E26: ● | F26: 不採用者への通知と応募者情報の返却・廃棄 | I26: 応募者情報、選考記録 | J26: 応募者情報 | K26: 個人情報保護法 | L26: 採用／—
A27: 01-04-05 | E27: ● | F27: 採用活動の振り返り（チャネル別の実績・コスト） | I27: 選考記録、採用計画、内定・オファー | J27: 採用チャネル実績 | K27: なし | L27: 採用／—
A28: 02 | C28: ● | F28: 入社・オンボーディング | G28: 雇用契約と入社手続きを完了し、受入れ・研修・定着支援を経て本採用に至るまでの段階 | H28: 本採用（試用期間終了）
A29: 02-01 | D29: ● | F29: 雇用契約・入社手続き | G29: 雇用契約を結び、入社書類・マイナンバー・社会保険の手続きと従業員情報の登録を行う
A30: 02-01-01 | E30: ● | F30: 雇用契約の締結・労働条件通知書の交付 | I30: 内定・オファー、就業規則・人事規程 | J30: 雇用契約 | K30: 労基法 | L30: 人事労務／—
A31: 02-01-02 | E31: ● | F31: 入社書類の回収（誓約書・身元保証書・扶養・通勤・口座） | I31: 雇用契約 | J31: 入社書類、源泉徴収・年末調整情報 | K31: 個人情報保護法・税法 | L31: 人事労務・入社者／—
A32: 02-01-03 | E32: ● | F32: ★マイナンバーの収集・本人確認 | I32: 入社書類 | J32: マイナンバー | K32: 番号法 | L32: 人事労務・入社者／—
A33: 02-01-04 | E33: ● | F33: 従業員情報の登録（社員番号・所属・等級）と労働者名簿の作成 | I33: 雇用契約、入社書類、組織マスタ | J33: 従業員マスタ、労働者名簿、異動・発令履歴 | K33: 労基法 | L33: 人事労務／—
A34: 02-01-05 | E34: ● | F34: ★社会保険・雇用保険の資格取得届（健保・厚年は5日以内、雇用保険は翌月10日まで） | I34: 従業員マスタ、マイナンバー、入社書類 | J34: 社会保険・雇用保険の資格情報 | K34: 社会保険・雇用保険 | L34: 人事労務／年金事務所、ハローワーク、健康保険組合
A35: 02-01-06 | E35: ● | F35: 給与・勤怠の初期設定（支給項目・通勤手当・勤務形態） | I35: 雇用契約、従業員マスタ、入社書類 | J35: 従業員マスタ、勤務予定・勤怠記録 | K35: 労基法 | L35: 人事労務／—
A36: 02-02 | D36: ● | F36: 受入れ準備 | G36: 配属先・貸与物・アカウントを整え、雇入時の健康診断と安全衛生教育を行う
A37: 02-02-01 | E37: ● | F37: 配属先の決定・受入れ準備 | I37: 要員計画、選考記録 | J37: 異動・発令履歴、オンボーディング計画 | K37: なし | L37: 人事・配属部門／—
A38: 02-02-02 | E38: ● | F38: PC・社員証などの貸与とアカウントの発行 | I38: 従業員マスタ | J38: 貸与物・アカウント記録 | K38: なし | L38: 人事・情報システム／—
A39: 02-02-03 | E39: ● | F39: ★雇入時の健康診断 | I39: 従業員マスタ | J39: 健康診断・面接指導記録 | K39: 安衛法 | L39: 人事・産業医／健診機関
A40: 02-02-04 | E40: ● | F40: ★雇入れ時の安全衛生教育 | I40: 育成体系・研修カタログ | J40: 受講記録 | K40: 安衛法 | L40: 人事・配属部門／—
A41: 02-03 | D41: ● | F41: オンボーディング・定着 | G41: 入社時研修とメンターの支援で早期に立ち上げ、試用期間の評価で本採用を決める
A42: 02-03-01 | E42: ● | F42: 入社時研修（会社理解・就業規則・コンプライアンス・情報セキュリティ） | I42: 育成体系・研修カタログ、就業規則・人事規程 | J42: 受講記録 | K42: なし | L42: 人事・研修担当／—
A43: 02-03-02 | E43: ● | F43: ★新卒入社者の集合研修とOJT体制の整備 | I43: 育成体系・研修カタログ | J43: 受講記録、オンボーディング計画 | K43: なし | L43: 人事・配属部門／研修会社
A44: 02-03-03 | E44: ● | F44: オンボーディング計画の作成とメンター・バディの設定 | I44: 従業員マスタ、職務・ポジション | J44: オンボーディング計画 | K44: なし | L44: 配属部門・人事／—
A45: 02-03-04 | E45: ● | F45: 定着フォロー（入社後の1on1・入社後サーベイ） | I45: オンボーディング計画 | J45: オンボーディング計画、エンゲージメント調査結果 | K45: なし | L45: 上司・メンター・人事／—
A46: 02-03-05 | E46: ● | F46: 試用期間の評価・本採用の判定 | I46: オンボーディング計画、目標 | J46: 人事評価結果、異動・発令履歴 | K46: 労基法・労働契約法 | L46: 上司・人事／—
A47: 03 | C47: ● | F47: 人材育成・能力開発 | G47: 求める人材像に向けて育成を計画し、研修・学習とスキル・資格の習得、キャリア開発を進める段階 | H47: 必要な能力の習得（スキル・資格の認定）
A48: 03-01 | D48: ● | F48: 育成計画 | G48: 求める人材像とスキル体系を定め、全社と個人の育成計画を立てる
A49: 03-01-01 | E49: ● | F49: 求める人材像・スキル体系の定義 | I49: 人事戦略・人的資本KPI、職務・ポジション | J49: スキル・資格情報 | K49: なし | L49: 人事・事業部門／—
A50: 03-01-02 | E50: ● | F50: 育成体系・年間研修計画の策定 | I50: 人事戦略・人的資本KPI、スキル・資格情報 | J50: 育成体系・研修カタログ | K50: なし | L50: 人事・研修担当／—
A51: 03-01-03 | E51: ● | F51: 個人別育成計画の作成（上司との合意） | I51: 目標、人事評価結果、スキル・資格情報 | J51: キャリア面談記録 | K51: なし | L51: 本人・上司／—
A52: 03-02 | D52: ● | F52: 研修・学習 | G52: 階層別・職種別・法定の研修と自己啓発で、知識とスキルを身につける
A53: 03-02-01 | E53: ● | F53: ★階層別研修（若手・中堅・新任管理職・昇格者） | I53: 育成体系・研修カタログ、異動・発令履歴 | J53: 受講記録 | K53: なし | L53: 人事・研修担当／研修会社
A54: 03-02-02 | E54: ● | F54: 職種別・専門研修とOJT | I54: 育成体系・研修カタログ | J54: 受講記録 | K54: なし | L54: 事業部門・研修担当／研修会社
A55: 03-02-03 | E55: ● | F55: コンプライアンス・ハラスメント防止・情報セキュリティ研修 | I55: 就業規則・人事規程、育成体系・研修カタログ | J55: 受講記録 | K55: 労働施策総合推進法等 | L55: 人事・法務・情報システム／—
A56: 03-02-04 | E56: ● | F56: ★作業内容の変更時・職長などの安全衛生教育 | I56: 育成体系・研修カタログ、異動・発令履歴 | J56: 受講記録 | K56: 安衛法 | L56: 安全衛生担当・事業部門／—
A57: 03-02-05 | E57: ● | F57: 自己啓発・eラーニングの提供 | I57: 育成体系・研修カタログ | J57: 受講記録 | K57: なし | L57: 本人・人事／教育サービス事業者
A58: 03-02-06 | E58: ● | F58: 研修効果の測定・改善 | I58: 受講記録、人事評価結果 | J58: 育成体系・研修カタログ | K58: なし | L58: 人事・研修担当／—
A59: 03-03 | D59: ● | F59: スキル・資格の習得 | G59: スキルを可視化し、資格の取得とリスキリングを進める
A60: 03-03-01 | E60: ● | F60: スキルの自己申告・上司評価による可視化 | I60: スキル・資格情報 | J60: スキル・資格情報 | K60: なし | L60: 本人・上司／—
A61: 03-03-02 | E61: ● | F61: 資格取得の支援と保有資格・法定の選任者の登録 | I61: スキル・資格情報 | J61: スキル・資格情報 | K61: 各業法 | L61: 本人・人事／資格試験機関
A62: 03-03-03 | E62: ● | F62: リスキリング（デジタル人材育成・職種転換）の実施 | I62: スキル・資格情報、要員計画 | J62: 受講記録、スキル・資格情報 | K62: なし | L62: 人事・事業部門／教育サービス事業者
A63: 03-04 | D63: ● | F63: キャリア開発 | G63: 面談と研修で本人のキャリアの希望を明らかにし、自律的な成長を支援する
A64: 03-04-01 | E64: ● | F64: ★キャリア面談・自己申告 | I64: 従業員マスタ、スキル・資格情報、人事評価結果 | J64: キャリア面談記録 | K64: なし | L64: 本人・上司・人事／—
A65: 03-04-02 | E65: ● | F65: キャリア研修（年代別・節目の研修） | I65: 育成体系・研修カタログ | J65: 受講記録、キャリア面談記録 | K65: なし | L65: 人事／キャリアコンサルタント
A66: 04 | C66: ● | F66: 評価・処遇 | G66: 目標と評価で成果に報い、給与・社会保険・福利厚生を提供し、労働時間・健康・職場環境を管理する段階（在籍中は毎年繰り返す） | H66: 評価の確定・報酬の支払
A67: 04-01 | D67: ● | F67: 目標設定・評価 | G67: 期初に目標を合意し、期中に支援して、期末に評価・調整・フィードバックする
A68: 04-01-01 | E68: ● | F68: 期初の目標設定（MBO／OKR）と上司との合意 | I68: 人事戦略・人的資本KPI、職務・ポジション、等級制度 | J68: 目標 | K68: なし | L68: 本人・上司／—
A69: 04-01-02 | E69: ● | F69: 期中の1on1・フィードバック | I69: 目標 | J69: 目標 | K69: なし | L69: 本人・上司／—
A70: 04-01-03 | E70: ● | F70: 評価者研修の実施 | I70: 育成体系・研修カタログ、等級制度 | J70: 受講記録 | K70: なし | L70: 人事／—
A71: 04-01-04 | E71: ● | F71: 自己評価・一次／二次評価の実施 | I71: 目標、等級制度 | J71: 人事評価結果 | K71: なし | L71: 本人・上司・部門長／—
A72: 04-01-05 | E72: ● | F72: 評価調整会議（キャリブレーション）と評価の確定 | I72: 人事評価結果 | J72: 人事評価結果 | K72: なし | L72: 部門長・人事／—
A73: 04-01-06 | E73: ● | F73: 評価結果のフィードバック面談 | I73: 人事評価結果 | J73: 人事評価結果 | K73: なし | L73: 本人・上司／—
A74: 04-02 | D74: ● | F74: 報酬決定 | G74: 報酬制度を設計・点検し、評価と原資に基づいて昇給・賞与を決める
A75: 04-02-01 | E75: ● | F75: 等級・報酬制度の設計・改定（同一労働同一賃金の点検を含む） | I75: 等級制度、報酬市場データ、人事戦略・人的資本KPI | J75: 報酬テーブル、等級制度 | K75: パート有期法 | L75: 人事企画・経営／報酬コンサルタント
A76: 04-02-02 | E76: ● | F76: ★昇給（ベースアップ・定期昇給）の決定 | I76: 人事評価結果、報酬テーブル、人件費予算 | J76: 昇給・賞与決定 | K76: なし | L76: 人事・経営／労働組合
A77: 04-02-03 | E77: ● | F77: ★賞与（夏季・冬季）の決定 | I77: 人事評価結果、報酬テーブル、人件費予算 | J77: 昇給・賞与決定 | K77: なし | L77: 人事・経営／労働組合
A78: 04-02-04 | E78: ● | F78: 最低賃金・市場の報酬水準の点検 | I78: 報酬テーブル、報酬市場データ | J78: 報酬テーブル | K78: 最低賃金法 | L78: 人事企画／—
A79: 04-03 | D79: ● | F79: 勤怠・休暇管理 | G79: 労働時間を記録して上限を守り、休暇・休業を管理する
A80: 04-03-01 | E80: ● | F80: 労働時間の記録と月次の勤怠の締め | I80: 勤務予定・勤怠記録 | J80: 勤務予定・勤怠記録 | K80: 労基法・安衛法 | L80: 本人・上司・人事労務／—
A81: 04-03-02 | E81: ● | F81: ★36協定の締結・届出 | I81: 勤務予定・勤怠記録、労使協定・労使協議記録 | J81: 労使協定・労使協議記録 | K81: 労基法 | L81: 人事労務／労働組合（過半数代表）、労働基準監督署
A82: 04-03-03 | E82: ● | F82: ★時間外・休日労働の上限管理 | I82: 勤務予定・勤怠記録、労使協定・労使協議記録 | J82: 勤務予定・勤怠記録 | K82: 労基法 | L82: 上司・人事労務／—
A83: 04-03-04 | E83: ● | F83: ★年次有給休暇の付与と年5日取得の管理（年次有給休暇管理簿） | I83: 勤務予定・勤怠記録、従業員マスタ | J83: 休暇・休業記録 | K83: 労基法 | L83: 上司・人事労務／—
A84: 04-03-05 | E84: ● | F84: ★産前産後・育児・介護休業と休職の申出受付・管理（個別の周知・意向確認を含む） | I84: 従業員マスタ、就業規則・人事規程 | J84: 休暇・休業記録 | K84: 育介法・労基法 | L84: 本人・上司・人事労務／—
A85: 04-03-06 | E85: ● | F85: ★柔軟な働き方の制度運用（テレワーク・時差出勤・短時間勤務） | I85: 就業規則・人事規程、休暇・休業記録 | J85: 勤務予定・勤怠記録 | K85: 育介法 | L85: 本人・上司・人事／—
A86: 04-04 | D86: ● | F86: 給与・社会保険・福利厚生 | G86: 給与・賞与を支払い、税・社会保険の手続きを行い、福利厚生と人件費を管理する
A87: 04-04-01 | E87: ● | F87: 月次給与計算（勤怠・手当・控除の反映） | I87: 勤務予定・勤怠記録、従業員マスタ、報酬テーブル、社会保険・雇用保険の資格情報、住民税特別徴収情報 | J87: 給与・賞与計算結果、賃金台帳 | K87: 労基法・税法 | L87: 人事労務／給与計算の委託先
A88: 04-04-02 | E88: ● | F88: 給与の支払と給与明細の交付 | I88: 給与・賞与計算結果 | J88: 給与・賞与計算結果 | K88: 労基法 | L88: 人事労務・経理／銀行
A89: 04-04-03 | E89: ● | F89: 賞与の計算・支払と賞与支払届 | I89: 昇給・賞与決定、社会保険・雇用保険の資格情報 | J89: 給与・賞与計算結果、社会保険・労働保険の届出 | K89: 社会保険・税法 | L89: 人事労務／年金事務所、健康保険組合
A90: 04-04-04 | E90: ● | F90: ★年末調整と源泉徴収票・法定調書の作成 | I90: 源泉徴収・年末調整情報、給与・賞与計算結果、マイナンバー | J90: 源泉徴収・年末調整情報 | K90: 税法・番号法 | L90: 本人・人事労務／税務署、市区町村
A91: 04-04-05 | E91: ● | F91: ★住民税の特別徴収と納付 | I91: 住民税特別徴収情報 | J91: 住民税特別徴収情報 | K91: 税法 | L91: 人事労務／市区町村
A92: 04-04-06 | E92: ● | F92: ★社会保険・労働保険の定例手続き（算定基礎届・月額変更届・年度更新） | I92: 給与・賞与計算結果、社会保険・雇用保険の資格情報 | J92: 社会保険・労働保険の届出、社会保険・雇用保険の資格情報 | K92: 社会保険・雇用保険 | L92: 人事労務／年金事務所、健康保険組合、労働局
A93: 04-04-07 | E93: ● | F93: 福利厚生制度の運営（住宅・持株会・カフェテリアプランなど） | I93: 従業員マスタ | J93: 福利厚生利用情報 | K93: なし | L93: 人事・総務／福利厚生サービス事業者
A94: 04-04-08 | E94: ● | F94: 退職金・企業年金の管理（掛金・算定基礎の更新） | I94: 従業員マスタ、給与・賞与計算結果 | J94: 退職給付情報 | K94: 確定給付・確定拠出年金法 | L94: 人事／信託銀行、運営管理機関
A95: 04-04-09 | E95: ● | F95: 人件費の会計計上と予算実績管理 | I95: 給与・賞与計算結果、人件費予算 | J95: 人件費実績 | K95: 税法 | L95: 人事・経理／—
A96: 04-05 | D96: ● | F96: 健康・安全・職場環境 | G96: 健康と安全を守り、相談に応え、働きがいを高める
A97: 04-05-01 | E97: ● | F97: ★定期健康診断と事後措置（医師の意見に基づく就業判定） | I97: 従業員マスタ | J97: 健康診断・面接指導記録 | K97: 安衛法 | L97: 人事・産業医／健診機関
A98: 04-05-02 | E98: ● | F98: ★ストレスチェックの実施と高ストレス者の面接指導 | I98: 従業員マスタ | J98: ストレスチェック結果、健康診断・面接指導記録 | K98: 安衛法 | L98: 産業医・実施事務従事者／外部実施機関
A99: 04-05-03 | E99: ● | F99: ★長時間労働者への医師の面接指導 | I99: 勤務予定・勤怠記録 | J99: 健康診断・面接指導記録 | K99: 安衛法 | L99: 産業医・人事労務／—
A100: 04-05-04 | E100: ● | F100: 労働災害の報告と再発防止 | I100: 勤務予定・勤怠記録 | J100: 労働災害記録 | K100: 安衛法 | L100: 安全衛生担当・人事労務／労働基準監督署
...

Sheet ケイパビリティマップ
A1: ビジネス・ケイパビリティマップ（L1〜L3）
A2: 対象：日本の事業会社（正社員中心、新卒・経験者採用、月給制）／日本の法令・制度基準（労基法・安衛法・社会保険・税法ほか）。1行1項目。L1〜L3列の●がその行のレベル。区分はL1、範囲・アウトカムはL3の項目。★＝日本の制度・雇用慣行に固有、または特に強調する能力。
A3: ID | B3: L1 | C3: L2 | D3: L3 | E3: ケイパビリティ名 | F3: ケイパビリティの定義 | G3: 区分 | H3: 範囲（含む） | I3: 範囲（含まない） | J3: アウトカム
A4: C01 | B4: ● | E4: 人事戦略・組織設計 | F4: 経営戦略を人と組織の方針に落とし込み、要員・人件費・組織・等級の枠組みを定める能力 | G4: 戦略
A5: C01-01 | C5: ● | E5: 人事戦略・人的資本経営★ | F5: 経営戦略と連動した人事戦略と人的資本の指標を定め、人事制度・規程と開示を統制する
A6: C01-01-01 | D6: ● | E6: 人事戦略策定 | F6: 経営戦略・事業計画を受けて、人材・組織の方針と重点施策を定める | H6: 人材ポートフォリオの方針、重点施策、人的資本KPIの設定 | I6: 要員数の計画（C01-02-01） | J6: 経営戦略と連動した人事戦略
A7: C01-01-02 | D7: ● | E7: 人的資本情報の開示★ | F7: 有価証券報告書・統合報告書などで人的資本の方針・指標を開示する | H7: 人材育成方針・社内環境整備方針、指標と目標、女性管理職比率・男性育休取得率・男女賃金差異の開示 | I7: 女性活躍推進法の行動計画策定（C07-04-01） | J7: 投資家・求職者に信頼される人的資本の開示
A8: C01-01-03 | D8: ● | E8: 就業規則・人事規程管理★ | F8: 就業規則・人事規程を制定・改定し、労働基準監督署への届出と従業員への周知を行う | H8: 規程の起案・改定、過半数代表の意見聴取、届出、周知 | I8: 労使協定の締結（C06-03-01） | J8: 法令に適合し、周知された就業規則
A9: C01-02 | C9: ● | E9: 要員計画・人件費管理 | F9: 事業計画に必要な人員と人件費を計画し、実績を管理する
A10: C01-02-01 | D10: ● | E10: 要員計画策定 | F10: 事業計画から職種・等級・雇用区分別の必要人員と過不足を見積もる | H10: 必要人員の見積もり、過不足分析、採用・異動・育成での充足方針 | I10: 個々の採用計画（C02-01-01） | J10: 事業計画を実現できる要員計画
A11: C01-02-02 | D11: ● | E11: 人件費予算・実績管理 | F11: 人件費の予算を立て、給与計算の結果から実績を把握する | H11: 人件費予算、人件費の会計計上、予実管理 | I11: 給与計算そのもの（C05-03-01） | J11: 予算内に管理された人件費
A12: C01-02-03 | D12: ● | E12: 雇用形態ポートフォリオ管理 | F12: 正社員・有期契約・パートタイム・派遣・業務委託の構成を管理する | H12: 雇用形態別の構成、派遣受入れ期間の管理 | I12: 有期契約の更新手続き（C03-01-05） | J12: 事業に合った雇用形態の組み合わせ
A13: C01-03 | C13: ● | E13: 組織・職務設計 | F13: 組織構造・職務・等級の枠組みを設計する
A14: C01-03-01 | D14: ● | E14: 組織設計・組織改編 | F14: 組織構造を設計し、組織改編を計画・実施する | H14: 組織図、組織改編、組織コード | I14: 異動の発令（C07-01-02） | J14: 事業戦略に合った組織
A15: C01-03-02 | D15: ● | E15: 職務・ポジション定義 | F15: 職務の役割・責任・要件と、ポジション（定員）を定義する | H15: 職務記述書、ポジション管理、職務要件 | I15: スキル体系の定義（C04-02-01） | J15: 役割と要件が明確な職務
A16: C01-03-03 | D16: ● | E16: 等級制度設計 | F16: 職能・職務・役割などに基づく等級制度を設計・改定する | H16: 等級の定義、等級と報酬・評価の対応 | I16: 賃金テーブルの設計（C05-02-01） | J16: 期待役割が明確な等級制度
A17: C02 | B17: ● | E17: タレント獲得 | F17: 必要な人材を惹きつけ、公正に選考して採用する能力 | G17: コア
A18: C02-01 | C18: ● | E18: 採用計画・採用ブランディング | F18: 採用計画を立て、候補者に選ばれるための発信と採用チャネルを管理する
A19: C02-01-01 | D19: ● | E19: 採用計画策定 | F19: 要員計画から新卒・経験者別の採用人数・時期・予算を決める | H19: 採用人数・時期・予算、職種別の優先順位 | I19: 要員計画の策定（C01-02-01） | J19: 要員計画と整合した採用計画
A20: C02-01-02 | D20: ● | E20: 採用ブランディング・採用広報 | F20: 会社の魅力と働き方を候補者に伝える | H20: 採用サイト、SNS、説明会資料、社員の発信 | I20: 商品・企業広報 | J20: 候補者から選ばれる雇用主のブランド
A21: C02-01-03 | D21: ● | E21: 採用チャネル管理 | F21: 求人媒体・人材紹介・リファラル・ダイレクトリクルーティングを選び、実績を管理する | H21: チャネルの選定・契約、チャネル別の実績とコスト | I21: 個々の候補者の選考（C02-03-02） | J21: 費用対効果の高い採用チャネル
A22: C02-02 | C22: ● | E22: 新卒採用★ | F22: 学生を対象に、インターンシップから内定者フォローまでを一括して行う
A23: C02-02-01 | D23: ● | E23: インターンシップ・母集団形成★ | F23: インターンシップ・説明会で学生との接点をつくり、応募者を集める | H23: インターンシップ、会社説明会、大学との連携 | I23: 経験者向けの求人公開（C02-03-01） | J23: 質・量ともに十分な応募者
A24: C02-02-02 | D24: ● | E24: 新卒選考運営 | F24: エントリーシート・適性検査・面接で選考する | H24: ES、適性検査、グループ討議、面接 | I24: 採否の最終判定の基準づくり（C02-04-01） | J24: 基準に沿って選ばれた内定者
A25: C02-02-03 | D25: ● | E25: 内定者管理・フォロー★ | F25: 内定から入社までの関係を維持し、辞退を防ぐ | H25: 内定式、内定者研修、内定者との連絡 | I25: 入社後の研修（C03-02-01） | J25: 辞退が少なく、準備ができた入社者
A26: C02-03 | C26: ● | E26: 経験者採用 | F26: 職務に合った経験者を募集・選考し、条件を提示して採用する
A27: C02-03-01 | D27: ● | E27: 求人票作成・求人公開 | F27: 職務要件と労働条件を記載した求人票を作り、公開する | H27: 求人票、労働条件の明示、求人の公開 | I27: 労働条件通知書の交付（C03-01-01） | J27: 正確で魅力的な求人
A28: C02-03-02 | D28: ● | E28: 候補者選考・面接 | F28: 書類選考・適性検査・面接で候補者を評価し、採否を決める | H28: 書類選考、適性検査、面接、採否の判定 | I28: 新卒の選考（C02-02-02） | J28: 職務に合った候補者の選抜
A29: C02-03-03 | D29: ● | E29: 条件提示・オファー | F29: 処遇条件を決めてオファーを出し、承諾を得る | H29: 等級・報酬の決定、オファーレター、条件交渉 | I29: 賃金テーブルの設計（C05-02-01） | J29: 承諾されたオファー
A30: C02-04 | C30: ● | E30: 採用コンプライアンス★ | F30: 採用の過程で公正さと法令順守、応募者の個人情報の保護を確保する
A31: C02-04-01 | D31: ● | E31: 公正な採用選考★ | F31: 本人に責任のない事項や思想・信条などを選考に用いず、適性と能力で判断する | H31: 面接官研修、質問の禁止事項、選考基準の点検 | I31: 評価者研修（C05-01-02） | J31: 公正で説明できる選考
A32: C02-04-02 | D32: ● | E32: 労働条件の明示★ | F32: 求人・内定の時点で労働条件（業務・就業場所の変更の範囲等）を明示する | H32: 求人時・内定時の明示事項、変更時の明示 | I32: 雇用契約の締結（C03-01-01） | J32: 候補者が正しく理解した労働条件
A33: C02-04-03 | D33: ● | E33: 応募者個人情報管理 | F33: 応募者の個人情報を目的の範囲で扱い、不採用者の情報を返却・廃棄する | H33: 利用目的の通知、保管期間、返却・廃棄 | I33: 従業員の個人情報保護（C09-03-01） | J33: 漏えい・目的外利用のない応募者情報
A34: C03 | B34: ● | E34: 入社・雇用管理 | F34: 雇用契約を結び、入社手続きを行い、従業員の情報を正確に管理する能力 | G34: コア
A35: C03-01 | C35: ● | E35: 雇用契約・入社手続き★ | F35: 雇用契約の締結と、社会保険・税・マイナンバーの入社時手続きを行う
A36: C03-01-01 | D36: ● | E36: 雇用契約締結 | F36: 労働条件通知書を交付し、雇用契約を締結する | H36: 労働条件通知書、雇用契約書、電子契約 | I36: 求人時の労働条件の明示（C02-04-02） | J36: 双方が合意した雇用契約
A37: C03-01-02 | D37: ● | E37: 社会保険・雇用保険の資格取得★ | F37: 健康保険・厚生年金・雇用保険の資格取得届を期限内に提出する | H37: 資格取得届、被扶養者届、電子申請 | I37: 定例の届出（C05-04-01） | J37: 入社日から保険の資格がある従業員
A38: C03-01-03 | D38: ● | E38: マイナンバー収集・管理★ | F38: マイナンバーを本人確認とともに収集し、安全に管理する | H38: 利用目的の通知、本人確認、保管・廃棄 | I38: マイナンバーの安全管理措置全般（C09-03-01） | J38: 適法に収集・管理された特定個人情報
A39: C03-01-04 | D39: ● | E39: 入社書類管理 | F39: 誓約書・身元保証書・扶養情報などの入社書類を回収・確認する | H39: 書類の案内・回収・確認・保管 | I39: マイナンバーの収集（C03-01-03） | J39: 不備のない入社書類
A40: C03-01-05 | D40: ● | E40: 有期契約の更新・無期転換★ | F40: 有期労働契約の更新・雇止めと、無期転換の申込みを管理する | H40: 契約期間・更新上限の管理、無期転換の申込権の通知 | I40: 定年後の再雇用（C08-02-02） | J40: 紛争のない契約更新と無期転換
A41: C03-02 | C41: ● | E41: オンボーディング | F41: 新しく入った従業員が組織に適応し、早く戦力になるよう支援する
A42: C03-02-01 | D42: ● | E42: 入社時研修 | F42: 会社・規程・コンプライアンス・業務の基礎を教える | H42: 入社時研修、新卒集合研修 | I42: 階層別研修（C04-01-03） | J42: 基礎を理解した入社者
A43: C03-02-02 | D43: ● | E43: 配属・受入れ支援 | F43: 配属先を決め、受入れの準備とメンター・バディを整える | H43: 配属先の決定、受入れ準備、メンター・バディ | I43: 定期異動（C07-01-02） | J43: 迷わず仕事を始められる入社者
A44: C03-02-03 | D44: ● | E44: 定着フォロー・試用期間管理 | F44: 入社後の面談・サーベイで適応を確認し、試用期間の評価を行う | H44: 入社後面談、サーベイ、試用期間の評価と本採用の判定 | I44: 期末の人事評価（C05-01-02） | J44: 定着し、戦力になった入社者
A45: C03-03 | C45: ● | E45: 従業員情報管理★ | F45: 従業員の基本情報と、法定の帳簿を正確に管理する
A46: C03-03-01 | D46: ● | E46: 従業員マスタ管理 | F46: 社員番号・所属・等級・雇用区分などの基本情報を登録・更新する | H46: 登録、発令の反映、履歴管理 | I46: 組織コードの設計（C01-03-01） | J46: 正確で最新の従業員情報
A47: C03-03-02 | D47: ● | E47: 法定帳簿管理★ | F47: 労働者名簿・賃金台帳・出勤簿を作成し、法定の期間保存する | H47: 法定三帳簿、年次有給休暇管理簿、保存期間の管理 | I47: 給与計算（C05-03-01） | J47: 監督署の調査に耐える帳簿
A48: C04 | B48: ● | E48: 人材育成・能力開発 | F48: 従業員が必要な知識・スキルを身につけ、自律的にキャリアを築けるよう支援する能力 | G48: コア
A49: C04-01 | C49: ● | E49: 育成体系・研修管理 | F49: 育成体系を設計し、研修を企画・運営する
A50: C04-01-01 | D50: ● | E50: 育成体系設計 | F50: 求める人材像から、階層別・職種別の育成体系と年間計画を定める | H50: 育成体系、年間研修計画、研修予算 | I50: スキル体系の定義（C04-02-01） | J50: 人材戦略と整合した育成体系
A51: C04-01-02 | D51: ● | E51: 研修企画・運営・効果測定 | F51: 研修を企画・実施し、効果を測って改善する | H51: 研修の企画、講師・外部機関の手配、受講記録、効果測定 | I51: 法定・コンプライアンス教育（C04-04） | J51: 効果の出る研修
A52: C04-01-03 | D52: ● | E52: 階層別研修★ | F52: 新任管理職・昇格者など、階層や節目に応じた研修を行う | H52: 新入社員・若手・中堅・管理職研修、昇格者研修 | I52: 選抜型リーダー育成（C07-03-02） | J52: 役割に必要な力を身につけた従業員
A53: C04-02 | C53: ● | E53: スキル・資格管理 | F53: スキルを定義・可視化し、資格とリスキリングを管理する
A54: C04-02-01 | D54: ● | E54: スキル定義・可視化 | F54: スキル体系を定め、従業員のスキルを評価・登録する | H54: スキル体系、自己申告・上司評価、スキルマップ | I54: 職務要件の定義（C01-03-02） | J54: 見える化された組織のスキル
A55: C04-02-02 | D55: ● | E55: 資格取得支援・資格管理 | F55: 資格の取得を支援し、業務に必要な資格・法定の選任者を管理する | H55: 資格取得の奨励・費用補助、資格の登録・期限管理、法定の選任者 | I55: 教育の記録（C04-01-02） | J55: 必要な資格を持つ人が必要な業務に就いている状態
A56: C04-02-03 | D56: ● | E56: リスキリング | F56: 事業の変化に合わせて、新しいスキルの習得を計画的に進める | H56: デジタル人材育成、職種転換の教育 | I56: 自己啓発の支援（C04-03-02） | J56: 変化に対応できる人材
A57: C04-03 | C57: ● | E57: キャリア開発支援 | F57: 従業員の自律的なキャリア形成を支援する
A58: C04-03-01 | D58: ● | E58: キャリア面談・自己申告★ | F58: 上司・人事との面談や自己申告で、キャリアの希望と育成計画を合意する | H58: キャリア面談、自己申告、個人別育成計画、キャリア研修 | I58: 異動の決定（C07-01-02） | J58: 本人と会社が合意した育成計画
A59: C04-03-02 | D59: ● | E59: 自己啓発支援 | F59: eラーニングや通信教育、学び直しの機会を提供する | H59: eラーニング、通信教育、費用補助 | I59: 業務上必要な研修（C04-01-02） | J59: 自ら学ぶ従業員
A60: C04-04 | C60: ● | E60: 法定・コンプライアンス教育 | F60: 法令や社会の要請で求められる教育を、対象者に確実に行う
A61: C04-04-01 | D61: ● | E61: コンプライアンス・ハラスメント防止研修 | F61: 行動規範・ハラスメント防止・インサイダー取引防止などを教育する | H61: 全従業員研修、管理職向け研修、受講記録 | I61: 相談・ハラスメント事案への対応（C06-03-02） | J61: ルールを理解し守る従業員
A62: C04-04-02 | D62: ● | E62: 安全衛生教育★ | F62: 雇入れ時・作業内容の変更時などに安全衛生教育を行う | H62: 雇入れ時教育、作業変更時教育、職長教育 | I62: 労働災害への対応（C06-02-04） | J62: 安全に働ける従業員
A63: C04-04-03 | D63: ● | E63: 情報セキュリティ教育 | F63: 情報セキュリティと個人情報の取扱いを教育する | H63: 全従業員研修、標的型メール訓練 | I63: アクセス管理（C09-03-02） | J63: 情報を適切に扱う従業員
A64: C05 | B64: ● | E64: パフォーマンス・報酬管理 | F64: 成果と行動を評価し、公正に報い、給与と社会保険・福利厚生を確実に提供する能力 | G64: コア
A65: C05-01 | C65: ● | E65: 目標・評価管理 | F65: 目標を設定し、成果と行動を評価して、結果を本人に伝える
A66: C05-01-01 | D66: ● | E66: 目標設定・期中フィードバック | F66: 期初に目標を合意し、1on1などで進捗と成長を支援する | H66: MBO・OKR、1on1、期中の目標修正 | I66: 個人別育成計画（C04-03-01） | J66: 組織の目標とつながった個人の目標
A67: C05-01-02 | D67: ● | E67: 評価実施・評価者育成 | F67: 自己評価と上司による一次・二次評価を行い、評価者を育成する | H67: 評価シート、一次・二次評価、評価者研修、試用期間の評価 | I67: 採用選考の評価（C02-03-02） | J67: 基準に沿った評価
A68: C05-01-03 | D68: ● | E68: 評価調整・フィードバック | F68: 評価を部門間で調整して確定し、本人にフィードバックする | H68: 評価調整会議、評価確定、フィードバック面談、苦情処理 | I68: 報酬の決定（C05-02-02） | J68: 納得感のある評価結果
A69: C05-02 | C69: ● | E69: 報酬制度・報酬決定 | F69: 報酬制度を設計し、昇給・賞与を決める
A70: C05-02-01 | D70: ● | E70: 報酬制度設計 | F70: 基本給・手当・賞与・退職金の制度と賃金テーブルを設計・改定する | H70: 賃金テーブル、手当、賞与・退職金の算定方式、同一労働同一賃金の点検 | I70: 等級制度の設計（C01-03-03） | J70: 公正で競争力のある報酬制度
A71: C05-02-02 | D71: ● | E71: 昇給・賞与決定★ | F71: 評価と原資に基づいて、昇給（ベースアップ・定期昇給）と賞与の額を決める | H71: 昇給・賞与の原資、配分、個人別の決定 | I71: 給与計算（C05-03-01） | J71: 評価に報いる昇給・賞与
A72: C05-02-03 | D72: ● | E72: 報酬水準の点検 | F72: 市場の報酬水準と最低賃金を確認し、自社の水準を点検する | H72: 報酬サーベイ、最低賃金の確認 | I72: — | J72: 市場と法令に照らして適正な報酬水準
A73: C05-03 | C73: ● | E73: 給与計算・支払★ | F73: 給与・賞与を正確に計算して支払い、税の源泉徴収・年末調整を行う
A74: C05-03-01 | D74: ● | E74: 月次給与計算・支払 | F74: 勤怠・手当・控除を反映して給与を計算し、支払って明細を交付する | H74: 給与計算、振込、給与明細、賃金台帳 | I74: 報酬額の決定（C05-02-02） | J74: 正確で期日どおりの給与
A75: C05-03-02 | D75: ● | E75: 賞与計算・支払 | F75: 賞与を計算・支払い、社会保険の賞与支払届を出す | H75: 賞与計算、賞与支払届 | I75: 賞与額の決定（C05-02-02） | J75: 正確な賞与
A76: C05-03-03 | D76: ● | E76: 年末調整・源泉徴収★ | F76: 所得税を源泉徴収し、年末調整と源泉徴収票の交付・法定調書の提出を行う | H76: 扶養控除等申告書、年末調整、源泉徴収票、法定調書 | I76: マイナンバーの収集（C03-01-03） | J76: 正しく精算された所得税
A77: C05-03-04 | D77: ● | E77: 住民税特別徴収★ | F77: 住民税を給与から特別徴収し、市区町村に納付する | H77: 特別徴収税額の反映、納付、異動届 | I77: — | J77: 正しく納付された住民税
A78: C05-04 | C78: ● | E78: 社会保険・福利厚生 | F78: 社会保険・労働保険の定例手続きを行い、福利厚生と退職給付を提供する
A79: C05-04-01 | D79: ● | E79: 社会保険・労働保険の定例手続き★ | F79: 算定基礎届・月額変更届・労働保険の年度更新などを行う | H79: 算定基礎届、月額変更届、年度更新、育児休業等の保険料免除 | I79: 資格取得・喪失の届出（C03-01-02／C08-01-02） | J79: 正しい保険料と給付
A80: C05-04-02 | D80: ● | E80: 福利厚生制度運営 | F80: 住宅・持株会・カフェテリアプランなどの福利厚生を提供する | H80: 制度の運営、外部サービスの管理 | I80: 健康管理（C06-02） | J80: 従業員に活用される福利厚生
A81: C05-04-03 | D81: ● | E81: 退職給付管理 | F81: 退職金・企業年金（確定給付・確定拠出）を管理する | H81: 退職金の算定、企業年金の運営、掛金 | I81: 退職時の精算（C08-01-03） | J81: 約束どおりに支払われる退職給付
A82: C06 | B82: ● | E82: 就業・労務管理 | F82: 労働時間・休暇・健康・安全・労使関係を適切に管理し、安心して働ける環境を整える能力 | G82: コア
A83: C06-01 | C83: ● | E83: 勤怠・休暇管理★ | F83: 労働時間を客観的に記録し、時間外労働と休暇・休業を管理する
A84: C06-01-01 | D84: ● | E84: 勤怠記録・労働時間管理 | F84: 出退勤と労働時間を客観的に記録し、月次で締める | H84: 打刻、勤務予定・シフト、勤怠の締め | I84: 給与計算（C05-03-01） | J84: 正確な労働時間の記録
A85: C06-01-02 | D85: ● | E85: 時間外労働の上限管理★ | F85: 36協定の範囲で時間外・休日労働を管理し、上限を超えないようにする | H85: 36協定の管理、上限の監視、警告 | I85: 36協定の締結（C06-03-01） | J85: 法定の上限を超えない労働時間
A86: C06-01-03 | D86: ● | E86: 年次有給休暇管理★ | F86: 有給休暇を付与し、年5日の取得義務を管理する | H86: 付与、取得管理、年次有給休暇管理簿 | I86: — | J86: 取得義務を満たした有給休暇
A87: C06-01-04 | D87: ● | E87: 休業・休職管理★ | F87: 産前産後・育児・介護休業や休職の申出を受け付け、復職まで管理する | H87: 申出の受付、個別の周知・意向確認、休業中の管理、復職 | I87: 保険料免除の手続き（C05-04-01） | J87: 安心して休み、復帰できる従業員
A88: C06-02 | C88: ● | E88: 健康・安全管理★ | F88: 健康診断・ストレスチェック・面接指導を行い、労働災害を防ぐ
A89: C06-02-01 | D89: ● | E89: 健康診断・事後措置★ | F89: 雇入時・定期の健康診断を行い、医師の意見に基づく就業上の措置をとる | H89: 健診の実施、結果の管理、就業判定 | I89: ストレスチェック（C06-02-02） | J89: 健康状態に応じて働ける従業員
A90: C06-02-02 | D90: ● | E90: ストレスチェック★ | F90: ストレスチェックを実施し、高ストレス者に医師の面接指導を行う | H90: 実施、面接指導、集団分析 | I90: — | J90: 心の不調の予防
A91: C06-02-03 | D91: ● | E91: 長時間労働者の面接指導★ | F91: 時間外労働が基準を超えた従業員に、医師の面接指導を行う | H91: 対象者の抽出、面接指導、事後措置 | I91: 時間外労働の上限管理（C06-01-02） | J91: 過重労働による健康障害の防止
A92: C06-02-04 | D92: ● | E92: 労働災害対応 | F92: 労働災害を報告し、原因を調べて再発を防ぐ | H92: 労災保険の請求支援、労働者死傷病報告、再発防止 | I92: — | J92: 災害が繰り返されない職場
A93: C06-03 | C93: ● | E93: 労使関係・従業員対応 | F93: 労働組合・過半数代表と協議し、従業員の相談と紛争に対応する
A94: C06-03-01 | D94: ● | E94: 労使協議・労使協定 | F94: 労働組合・過半数代表と協議し、36協定などの労使協定を結ぶ | H94: 団体交渉、労使協議、労使協定の締結・届出 | I94: 就業規則の改定（C01-01-03） | J94: 信頼に基づく労使関係
A95: C06-03-02 | D95: ● | E95: 相談窓口・ハラスメント対応 | F95: 相談・通報を受け付け、事実を確認して対応する | H95: 相談窓口、内部通報、調査、再発防止 | I95: ハラスメント防止研修（C04-04-01） | J95: 安心して相談できる職場
A96: C06-03-03 | D96: ● | E96: 懲戒・紛争対応 | F96: 就業規則に基づいて懲戒・解雇を行い、労働紛争に対応する | H96: 懲戒手続き、解雇予告、労働審判・あっせんへの対応 | I96: 退職手続き（C08-01） | J96: 公正で法令に沿った処分
A97: C06-04 | C97: ● | E97: エンゲージメント・働き方 | F97: 従業員のエンゲージメントを測って高め、柔軟な働き方を整える
A98: C06-04-01 | D98: ● | E98: エンゲージメント調査・改善 | F98: エンゲージメント調査を行い、職場ごとに改善を進める | H98: サーベイ、パルスサーベイ、改善活動 | I98: ストレスチェック（C06-02-02） | J98: 働きがいのある職場
A99: C06-04-02 | D99: ● | E99: 柔軟な働き方の制度運用★ | F99: テレワーク・時差出勤・短時間勤務などの制度を運用する | H99: 制度の設計・運用、育児・介護中の従業員への措置 | I99: 勤怠の記録（C06-01-01） | J99: 事情に合わせて働き続けられる従業員
A100: C07 | B100: ● | E100: タレントマネジメント・配置 | F100: 人材を見極めて最適に配置し、次の担い手と多様な人材の活躍を実現する能力 | G100: コア
...

Sheet ケイパビリティレベル
A1: ケイパビリティの成熟度レベル（L2ごとの定義）
A2: 対象：日本の事業会社（正社員中心、新卒・経験者採用、月給制）／日本の法令・制度基準（労基法・安衛法・社会保険・税法ほか）。評価の対象はL2。法令上の最低水準：労働法令・社会保険・税などの法令順守が関わるL2はレベル3が事実上の最低水準。
A3: レベル | B3: 名称 | C3: 共通定義
A4: 1 | B4: 初期 | C4: 属人的・場当たり的。成果が個人に依存し、再現できない
A5: 2 | B5: 管理された | C5: 部門・拠点ごとに計画・管理され、再現できる。ただし方法は部門・拠点で異なる
A6: 3 | B6: 定義された | C6: 全社標準のプロセス・役割・データ定義があり、一貫して運用される
A7: 4 | B7: 定量的に管理された | C7: 指標で成果・品質を測定し、データに基づいて管理・予測する
A8: 5 | B8: 最適化された | C8: 継続的な改善と先進的な手法により、変化に先回りし、先進的な水準にある
A10: L2 ID | B10: ケイパビリティL1 | C10: ケイパビリティL2 | D10: 法令上の最低水準 | E10: レベル1 初期 | F10: レベル2 管理された | G10: レベル3 定義された | H10: レベル4 定量的に管理された | I10: レベル5 最適化された
A11: C01-01 | B11: 人事戦略・組織設計 | C11: 人事戦略・人的資本経営★ | D11: レベル3（労基法・金商法） | E11: 人事方針が明文化されておらず、施策が場当たり的 | F11: 人事施策ごとに方針を定めるが、経営戦略との結びつきが弱い | G11: 経営戦略と連動した人事戦略・人的資本KPIを定め、規程と開示を全社で一貫して管理する | H11: 人的資本KPIを定期的に測定し、戦略の達成度に基づいて施策を見直す | I11: 人的資本の投資対効果を分析し、経営の意思決定に人事の視点を先回りして組み込む
A12: C01-02 | C12: 要員計画・人件費管理 | D12: — | E12: 要員・人件費の計画がなく、欠員が出てから補充する | F12: 部門ごとに要員・人件費の計画を立てるが、方法がばらばら | G12: 全社共通の方法で雇用区分別の要員計画と人件費予算を立て、実績と比較する | H12: 要員・人件費の予実差を指標で管理し、先行して計画を修正する | I12: 事業シナリオに応じた人員構成をシミュレーションし、先回りして人材を確保する
A13: C01-03 | C13: 組織・職務設計 | D13: — | E13: 組織・職務の定義がなく、担当者が口頭で運用する | F13: 組織図と職務記述を部門ごとに作成する | G13: 全社標準の組織・職務・等級の定義を持ち、変更を一元管理する | H13: 組織・職務の変更の効果（スパン・コスト等）を指標で評価する | I13: 事業の変化に先回りして、組織と職務を柔軟に組み替える
A14: C02-01 | B14: タレント獲得 | C14: 採用計画・採用ブランディング | D14: — | E14: 欠員が出てから場当たり的に募集する | F14: 年度ごとに採用計画を立てるが、チャネルの効果を振り返らない | G14: 全社標準の採用計画・チャネル管理・採用広報の仕組みを持つ | H14: チャネル別の応募・内定・定着・コストを指標で管理し、配分を最適化する | I14: 採用市場の変化に先回りし、候補者との長期的な関係を築く
A15: C02-02 | C15: 新卒採用★ | D15: レベル3（職安法） | E15: 採用担当者の経験に頼って選考する | F15: 年度ごとの採用スケジュールと選考基準がある | G15: 全社標準の選考基準・スケジュール・内定者フォローの仕組みを持つ | H15: 選考段階別の歩留まりと入社後の活躍・定着を指標で検証する | I15: 入社後の活躍データを選考に反映し、採用手法を先回りして改善する
A16: C02-03 | C16: 経験者採用 | D16: レベル3（職安法） | E16: 部門の個別判断で募集・選考する | F16: 募集ポジションごとに要件と選考手順を定める | G16: 全社標準の求人・選考・オファーの手順と面接官の基準を持つ | H16: 採用までの期間・内定承諾率・入社後の評価を指標で管理する | I16: 外部人材市場の動きに先回りして、候補者プールを常に維持する
A17: C02-04 | C17: 採用コンプライアンス★ | D17: レベル3（職安法・個人情報保護法） | E17: 面接官が質問してはいけない事項を知らない | F17: 採用担当者が法令を理解しているが、面接官への徹底は不十分 | G17: 公正採用の基準・面接官研修・応募者情報の取扱いルールを全社で運用する | H17: 違反の兆候や応募者からの苦情を指標で監視し、再発を防ぐ | I17: 採用のAI活用などの新しい手法についても、公正さを先回りして評価する
A18: C03-01 | B18: 入社・雇用管理 | C18: 雇用契約・入社手続き★ | D18: レベル3（労基法・社会保険・番号法） | E18: 手続きが担当者の記憶頼りで、届出の漏れ・遅れがある | F18: チェックリストで手続きを管理する | G18: 全社標準の手続きと電子申請で、期限内に確実に処理する | H18: 手続きのリードタイムと誤りを指標で管理する | I18: 入社前から自動で手続きが進み、従業員の手間を最小にする
A19: C03-02 | C19: オンボーディング | D19: — | E19: 受入れが配属先任せで、立ち上がりに差がある | F19: 入社時研修と受入れの手順がある | G19: 全社標準のオンボーディング計画（研修・メンター・面談）を運用する | H19: 立ち上がりの期間と早期離職率を指標で管理する | I19: 入社者の経験データから、一人ひとりに合った受入れを先回りして設計する
A20: C03-03 | C20: 従業員情報管理★ | D20: レベル3（労基法） | E20: 従業員情報が部門やファイルごとに分散している | F20: 人事部門が台帳で従業員情報を管理する | G20: 人事システムで従業員情報を一元管理し、法定帳簿を整える | H20: データの正確さ・更新の遅れを指標で管理する | I20: 従業員情報を全社の意思決定の基盤として活用する
A21: C04-01 | B21: 人材育成・能力開発 | C21: 育成体系・研修管理 | D21: — | E21: 研修が単発で、体系がない | F21: 部門ごとに研修を企画・実施する | G21: 全社の育成体系（階層別・職種別）に沿って研修を計画・運営し、記録する | H21: 研修の受講率・効果・費用を指標で管理する | I21: 事業と人材の変化に先回りして、学びの仕組みを組み替える
A22: C04-02 | C22: スキル・資格管理 | D22: — | E22: 誰がどのスキルを持つか把握していない | F22: 部門ごとにスキル表を作る | G22: 全社共通のスキル体系で、スキルと資格を一元管理する | H22: スキルの過不足を指標で管理し、育成・採用の計画に反映する | I22: 将来必要なスキルを先回りして特定し、計画的に獲得する
A23: C04-03 | C23: キャリア開発支援 | D23: — | E23: キャリアは会社任せで、本人の希望を聞かない | F23: 自己申告制度があるが、活用が限られる | G23: キャリア面談・キャリア研修・自己啓発支援を全社で運用する | H23: キャリアの希望と配置の実現度を指標で管理する | I23: 社内外の機会を先回りして示し、自律的なキャリアを後押しする
A24: C04-04 | C24: 法定・コンプライアンス教育 | D24: レベル3（安衛法・労働施策総合推進法） | E24: 教育の対象者・記録が不明確 | F24: 部門ごとに必要な教育を実施する | G24: 対象者・頻度・記録を定めて、全社で確実に実施する | H24: 受講率と違反・事故の発生を指標で管理する | I24: 新しいリスクに先回りして教育内容を更新する
A25: C05-01 | B25: パフォーマンス・報酬管理 | C25: 目標・評価管理 | D25: — | E25: 評価基準がなく、上司の主観で決まる | F25: 部門ごとに評価の方法と時期を決める | G25: 全社標準の目標設定・評価・調整・フィードバックの仕組みを運用する | H25: 評価の分布・納得度を指標で管理し、評価の質を改善する | I25: 継続的なフィードバックで、成長と成果を同時に高める
A26: C05-02 | C26: 報酬制度・報酬決定 | D26: レベル3（最低賃金法・パート有期法） | E26: 報酬が個別交渉や慣行で決まる | F26: 賃金テーブルがあるが、見直しが不定期 | G26: 全社標準の報酬制度で、評価と連動した昇給・賞与を決める | H26: 市場水準・社内の公平性（同一労働同一賃金、男女差異）を指標で管理する | I26: 人材戦略に合わせて報酬を先回りして設計し、競争力を保つ
A27: C05-03 | C27: 給与計算・支払★ | D27: レベル3（労基法・税法） | E27: 手計算が多く、誤りが起きる | F27: 給与システムで計算するが、確認が人手に頼る | G27: 全社標準の手順とシステムで、正確に期日どおり支払う | H27: 誤りの件数と処理時間を指標で管理する | I27: 勤怠から支払・会計まで自動でつながり、誤りが起きない
A28: C05-04 | C28: 社会保険・福利厚生 | D28: レベル3（社会保険・雇用保険） | E28: 届出が遅れ、保険料の誤りが起きる | F28: 年間の手続きカレンダーで管理する | G28: 全社標準の手続きと電子申請で、定例の届出を確実に行う | H28: 届出の誤り・遅れと福利厚生の利用率を指標で管理する | I28: 従業員のニーズに先回りして、福利厚生を設計し直す
A29: C06-01 | B29: 就業・労務管理 | C29: 勤怠・休暇管理★ | D29: レベル3（労基法・安衛法・育介法） | E29: 労働時間を自己申告だけで把握している | F29: 勤怠システムで記録するが、上限の管理が事後になる | G29: 客観的な記録と、36協定の上限・有給休暇の取得義務を全社で管理する | H29: 長時間労働・休暇取得を指標で監視し、事前に手を打つ | I29: 働き方のデータから、業務と人員配置を先回りして見直す
A30: C06-02 | C30: 健康・安全管理★ | D30: レベル3（安衛法） | E30: 健康診断の実施・事後措置が不十分 | F30: 健康診断は実施するが、事後措置が拠点任せ | G30: 健康診断・ストレスチェック・面接指導・労災対応を全社標準で運用する | H30: 受診率・有所見率・休業災害を指標で管理する | I30: 健康データを活用し、不調や災害を先回りして防ぐ
A31: C06-03 | C31: 労使関係・従業員対応 | D31: レベル3（労基法・労働施策総合推進法） | E31: 相談窓口がなく、問題が表に出ない | F31: 相談窓口はあるが、対応が担当者任せ | G31: 労使協議・相談対応・懲戒の手順を全社で定め、公正に運用する | H31: 相談件数・対応期間・再発を指標で管理する | I31: 従業員の声から問題を先回りして見つけ、制度を改善する
A32: C06-04 | C32: エンゲージメント・働き方 | D32: — | E32: 従業員の声を聞く仕組みがない | F32: 不定期に満足度調査を行う | G32: 定期的なエンゲージメント調査と改善、柔軟な働き方の制度を全社で運用する | H32: エンゲージメントと離職・生産性の関係を指標で分析する | I32: データに基づいて職場ごとに先回りして改善する
A33: C07-01 | B33: タレントマネジメント・配置 | C33: タレントレビュー・配置 | D33: — | E33: 異動が上司の個人的な判断で決まる | F33: 部門ごとに人材の見極めと異動を行う | G33: 全社共通のタレントレビューと異動のルールで配置を決める | H33: 配置後の活躍・定着を指標で検証する | I33: 本人のキャリア希望と事業ニーズを先回りして組み合わせる
A34: C07-02 | C34: 昇格・登用 | D34: — | E34: 昇格が年功や上司の推薦だけで決まる | F34: 昇格の基準があるが、運用が部門ごと | G34: 全社共通の昇格基準・審査（試験・アセスメント）で決める | H34: 昇格者の登用後の活躍を指標で検証する | I34: 将来の役割から逆算して、登用を先回りして計画する
A35: C07-03 | C35: 後継者・リーダー育成 | D35: — | E35: 後継者を決めていない | F35: 一部の役員ポストについて後継者を検討する | G35: 重要ポストの後継者計画と選抜型育成を全社で運用する | H35: 後継者の準備度とポストの充足率を指標で管理する | I35: 経営環境に先回りして、リーダー層を計画的に厚くする
A36: C07-04 | C36: 多様な人材の活躍推進★ | D36: レベル3（女性活躍推進法・障害者雇用促進法・高年法） | E36: 法定の計画・報告が期限直前の対応になる | F36: 法定の計画・報告は行うが、施策が限られる | G36: 行動計画・雇用率・情報公表を全社で管理し、施策を実行する | H36: 多様性の指標と目標の達成度を管理する | I36: 多様性を事業の強みとして先回りして生かす
A37: C08-01 | B37: 退職・雇用終了 | C37: 退職手続き★ | D37: レベル3（労基法・社会保険・税法） | E37: 手続きの漏れや書類の交付遅れがある | F37: チェックリストで手続きを管理する | G37: 全社標準の手続きと電子申請で、期限内に確実に処理する | H37: 手続きの期間・誤りを指標で管理する | I37: 退職の申出から手続きまで自動でつながる
A38: C08-02 | C38: 定年・再雇用★ | D38: レベル3（高年法） | E38: 定年到達者の把握が遅れる | F38: 定年到達者ごとに再雇用を個別に判断する | G38: 全社標準の手順で意向確認・再雇用契約・処遇を決める | H38: 再雇用者の活躍と処遇の納得度を指標で管理する | I38: 年齢に関係なく役割で処遇する仕組みに先回りして移行する
A39: C08-03 | C39: オフボーディング | D39: — | E39: 引継ぎやアカウント停止が漏れる | F39: 退職時チェックリストで管理する | G39: 全社標準のオフボーディングで、引継ぎ・返却・停止を確実に行う | H39: 離職理由を分析し、定着策に反映する | I39: アルムナイとの関係を生かして、再入社や協業につなげる
A40: C09-01 | B40: 人事基盤 | C40: 人事データ・分析 | D40: — | E40: 人事データの集計が手作業で、時間がかかる | F40: 定型のレポートを定期的に作成する | G40: 全社共通の定義で人事データを集約し、ダッシュボードで提供する | H40: 指標の予測・要因分析で施策の効果を検証する | I40: データに基づく人事判断が組織の標準になっている
A41: C09-02 | C41: 人事サービス提供 | D41: — | E41: 問い合わせが担当者個人に集中する | F41: 問い合わせ窓口を設けている | G41: 人事ポータル・セルフサービス・問い合わせ管理を全社で運用する | H41: 問い合わせの件数・解決時間・満足度を指標で管理する | I41: 問い合わせを先回りして減らすよう、制度と情報提供を改善する
A42: C09-03 | C42: 人事情報セキュリティ・個人情報保護★ | D42: レベル3（個人情報保護法・番号法） | E42: 人事情報のアクセス制限が不十分 | F42: 人事部門内でアクセスを制限する | G42: 情報の区分（要配慮・特定個人情報）に応じた保護とアクセス管理を全社で運用する | H42: アクセスログを監視し、違反を早期に検知する | I42: 新しい技術・規制に先回りして保護の仕組みを更新する

Sheet VS×ケイパビリティ関係
A1: VS×ケイパビリティ関係（正本：VS L4 × ケイパビリティL3）
A2: 1行1関係。区分は「主」（そのL4の中核）か「支援」（下支え）。マトリクスはこのシートから数式で集計する。関係の追加・変更はこのシートで行う。灰色の列は数式（編集しない）。
A3: VS L4 ID | B3: VS L4 | C3: ケイパビリティL3 ID | D3: ケイパビリティL3 | E3: 区分 | F3: VS L3 ID | G3: ケイパビリティL2 ID
A4: 01-01-01 | B4: 人事戦略・人的資本KPIの設定 | C4: C01-01-01 | D4: =IFERROR(INDEX(ケイパビリティマップ!$E:$E,MATCH(C4,ケイパビリティマップ!$A:$A,0)),"（IDなし）") | E4: 主 | F4: =LEFT(A4,5) | G4: =LEFT(C4,6)
A5: 01-01-02 | B5: 要員計画の策定（職種・等級・雇用形態別） | C5: C01-02-01 | D5: =IFERROR(INDEX(ケイパビリティマップ!$E:$E,MATCH(C5,ケイパビリティマップ!$A:$A,0)),"（IDなし）") | E5: 主 | F5: =LEFT(A5,5) | G5: =LEFT(C5,6)
A6: 01-01-02 | B6: 要員計画の策定（職種・等級・雇用形態別） | C6: C01-02-03 | D6: =IFERROR(INDEX(ケイパビリティマップ!$E:$E,MATCH(C6,ケイパビリティマップ!$A:$A,0)),"（IDなし）") | E6: 支援 | F6: =LEFT(A6,5) | G6: =LEFT(C6,6)
A7: 01-01-03 | B7: 人件費予算の策定 | C7: C01-02-02 | D7: =IFERROR(INDEX(ケイパビリティマップ!$E:$E,MATCH(C7,ケイパビリティマップ!$A:$A,0)),"（IDなし）") | E7: 主 | F7: =LEFT(A7,5) | G7: =LEFT(C7,6)
A8: 01-01-04 | B8: 職務・ポジション要件の定義 | C8: C01-03-02 | D8: =IFERROR(INDEX(ケイパビリティマップ!$E:$E,MATCH(C8,ケイパビリティマップ!$A:$A,0)),"（IDなし）") | E8: 主 | F8: =LEFT(A8,5) | G8: =LEFT(C8,6)
A9: 01-01-05 | B9: 採用計画の策定（新卒・経験者別の人数・時期・チャネル） | C9: C02-01-01 | D9: =IFERROR(INDEX(ケイパビリティマップ!$E:$E,MATCH(C9,ケイパビリティマップ!$A:$A,0)),"（IDなし）") | E9: 主 | F9: =LEFT(A9,5) | G9: =LEFT(C9,6)
A10: 01-01-05 | B10: 採用計画の策定（新卒・経験者別の人数・時期・チャネル） | C10: C02-01-03 | D10: =IFERROR(INDEX(ケイパビリティマップ!$E:$E,MATCH(C10,ケイパビリティマップ!$A:$A,0)),"（IDなし）") | E10: 支援 | F10: =LEFT(A10,5) | G10: =LEFT(C10,6)
A11: 01-02-01 | B11: 採用ブランディング・採用広報 | C11: C02-01-02 | D11: =IFERROR(INDEX(ケイパビリティマップ!$E:$E,MATCH(C11,ケイパビリティマップ!$A:$A,0)),"（IDなし）") | E11: 主 | F11: =LEFT(A11,5) | G11: =LEFT(C11,6)
A12: 01-02-02 | B12: ★求人票の作成・公開（業務・就業場所の変更の範囲を含む労働条件の明示） | C12: C02-03-01 | D12: =IFERROR(INDEX(ケイパビリティマップ!$E:$E,MATCH(C12,ケイパビリティマップ!$A:$A,0)),"（IDなし）") | E12: 主 | F12: =LEFT(A12,5) | G12: =LEFT(C12,6)
A13: 01-02-02 | B13: ★求人票の作成・公開（業務・就業場所の変更の範囲を含む労働条件の明示） | C13: C02-04-02 | D13: =IFERROR(INDEX(ケイパビリティマップ!$E:$E,MATCH(C13,ケイパビリティマップ!$A:$A,0)),"（IDなし）") | E13: 支援 | F13: =LEFT(A13,5) | G13: =LEFT(C13,6)
A14: 01-02-03 | B14: ★インターンシップ・会社説明会の運営（新卒） | C14: C02-02-01 | D14: =IFERROR(INDEX(ケイパビリティマップ!$E:$E,MATCH(C14,ケイパビリティマップ!$A:$A,0)),"（IDなし）") | E14: 主 | F14: =LEFT(A14,5) | G14: =LEFT(C14,6)
A15: 01-02-03 | B15: ★インターンシップ・会社説明会の運営（新卒） | C15: C02-04-03 | D15: =IFERROR(INDEX(ケイパビリティマップ!$E:$E,MATCH(C15,ケイパビリティマップ!$A:$A,0)),"（IDなし）") | E15: 支援 | F15: =LEFT(A15,5) | G15: =LEFT(C15,6)
... A170: 06-04-05 | B170: 離職分析とアルムナイ・ネットワークの運営 | C170: C08-03-04 | D170: =IFERROR(INDEX(ケイパビリティマップ!$E:$E,MATCH(C170,ケイパビリティマップ!$A:$A,0)),"（IDなし）") | E170: 主 | F170: =LEFT(A170,5) | G170: =LEFT(C170,6)
D171: =IF(C171="","",IFERROR(INDEX(ケイパビリティマップ!$E:$E,MATCH(C171,ケイパビリティマップ!$A:$A,0)),"（IDなし）")) | F171: =IF(A171="","",LEFT(A171,5)) | G171: =IF(C171="","",LEFT(C171,6))
D172: =IF(C172="","",IFERROR(INDEX(ケイパビリティマップ!$E:$E,MATCH(C172,ケイパビリティマップ!$A:$A,0)),"（IDなし）")) | F172: =IF(A172="","",LEFT(A172,5)) | G172: =IF(C172="","",LEFT(C172,6))
D173: =IF(C173="","",IFERROR(INDEX(ケイパビリティマップ!$E:$E,MATCH(C173,ケイパビリティマップ!$A:$A,0)),"（IDなし）")) | F173: =IF(A173="","",LEFT(A173,5)) | G173: =IF(C173="","",LEFT(C173,6))
D174: =IF(C174="","",IFERROR(INDEX(ケイパビリティマップ!$E:$E,MATCH(C174,ケイパビリティマップ!$A:$A,0)),"（IDなし）")) | F174: =IF(A174="","",LEFT(A174,5)) | G174: =IF(C174="","",LEFT(C174,6))
D175: =IF(C175="","",IFERROR(INDEX(ケイパビリティマップ!$E:$E,MATCH(C175,ケイパビリティマップ!$A:$A,0)),"（IDなし）")) | F175: =IF(A175="","",LEFT(A175,5)) | G175: =IF(C175="","",LEFT(C175,6))
D176: =IF(C176="","",IFERROR(INDEX(ケイパビリティマップ!$E:$E,MATCH(C176,ケイパビリティマップ!$A:$A,0)),"（IDなし）")) | F176: =IF(A176="","",LEFT(A176,5)) | G176: =IF(C176="","",LEFT(C176,6))
D177: =IF(C177="","",IFERROR(INDEX(ケイパビリティマップ!$E:$E,MATCH(C177,ケイパビリティマップ!$A:$A,0)),"（IDなし）")) | F177: =IF(A177="","",LEFT(A177,5)) | G177: =IF(C177="","",LEFT(C177,6))
D178: =IF(C178="","",IFERROR(INDEX(ケイパビリティマップ!$E:$E,MATCH(C178,ケイパビリティマップ!$A:$A,0)),"（IDなし）")) | F178: =IF(A178="","",LEFT(A178,5)) | G178: =IF(C178="","",LEFT(C178,6))
D179: =IF(C179="","",IFERROR(INDEX(ケイパビリティマップ!$E:$E,MATCH(C179,ケイパビリティマップ!$A:$A,0)),"（IDなし）")) | F179: =IF(A179="","",LEFT(A179,5)) | G179: =IF(C179="","",LEFT(C179,6))
D180: =IF(C180="","",IFERROR(INDEX(ケイパビリティマップ!$E:$E,MATCH(C180,ケイパビリティマップ!$A:$A,0)),"（IDなし）")) | F180: =IF(A180="","",LEFT(A180,5)) | G180: =IF(C180="","",LEFT(C180,6))
D181: =IF(C181="","",IFERROR(INDEX(ケイパビリティマップ!$E:$E,MATCH(C181,ケイパビリティマップ!$A:$A,0)),"（IDなし）")) | F181: =IF(A181="","",LEFT(A181,5)) | G181: =IF(C181="","",LEFT(C181,6))
D182: =IF(C182="","",IFERROR(INDEX(ケイパビリティマップ!$E:$E,MATCH(C182,ケイパビリティマップ!$A:$A,0)),"（IDなし）")) | F182: =IF(A182="","",LEFT(A182,5)) | G182: =IF(C182="","",LEFT(C182,6))
... D370: =IF(C370="","",IFERROR(INDEX(ケイパビリティマップ!$E:$E,MATCH(C370,ケイパビリティマップ!$A:$A,0)),"（IDなし）")) | F370: =IF(A370="","",LEFT(A370,5)) | G370: =IF(C370="","",LEFT(C370,6))

Sheet VS×ケイパビリティ
A1: バリューストリーム×ケイパビリティマップ（行：バリューストリームL3 × 列：ケイパビリティL2）
A2: ●＝主（配下のL4×L3の関係に「主」が1つ以上） ○＝支援のみ 空欄＝関係なし。各セルは「VS×ケイパビリティ関係」シートから数式で集計（直接入力しない）。
A4: VS L2 | B4: L3 ID | C4: VS L3 | D4: C01 人事戦略・組織設計 | G4: C02 タレント獲得 | K4: C03 入社・雇用管理 | N4: C04 人材育成・能力開発 | R4: C05 パフォーマンス・報酬管理 | V4: C06 就業・労務管理 | Z4: C07 タレントマネジメント・配置 | AD4: C08 退職・雇用終了 | AG4: C09 人事基盤 | AJ4: ●の数 | AK4: ○の数
D5: C01-01 | E5: C01-02 | F5: C01-03 | G5: C02-01 | H5: C02-02 | I5: C02-03 | J5: C02-04 | K5: C03-01 | L5: C03-02 | M5: C03-03 | N5: C04-01 | O5: C04-02 | P5: C04-03 | Q5: C04-04 | R5: C05-01 | S5: C05-02 | T5: C05-03 | U5: C05-04 | V5: C06-01 | W5: C06-02 | X5: C06-03 | Y5: C06-04 | Z5: C07-01 | AA5: C07-02 | AB5: C07-03 | AC5: C07-04 | AD5: C08-01 | AE5: C08-02 | AF5: C08-03 | AG5: C09-01 | AH5: C09-02 | AI5: C09-03
D6: 人事戦略・人的資本経営★ | E6: 要員計画・人件費管理 | F6: 組織・職務設計 | G6: 採用計画・採用ブランディング | H6: 新卒採用★ | I6: 経験者採用 | J6: 採用コンプライアンス★ | K6: 雇用契約・入社手続き★ | L6: オンボーディング | M6: 従業員情報管理★ | N6: 育成体系・研修管理 | O6: スキル・資格管理 | P6: キャリア開発支援 | Q6: 法定・コンプライアンス教育 | R6: 目標・評価管理 | S6: 報酬制度・報酬決定 | T6: 給与計算・支払★ | U6: 社会保険・福利厚生 | V6: 勤怠・休暇管理★ | W6: 健康・安全管理★ | X6: 労使関係・従業員対応 | Y6: エンゲージメント・働き方 | Z6: タレントレビュー・配置 | AA6: 昇格・登用 | AB6: 後継者・リーダー育成 | AC6: 多様な人材の活躍推進★ | AD6: 退職手続き★ | AE6: 定年・再雇用★ | AF6: オフボーディング | AG6: 人事データ・分析 | AH6: 人事サービス提供 | AI6: 人事情報セキュリティ・個人情報保護★
A7: 01 人員計画・採用 | B7: 01-01 | C7: 人事戦略・要員計画 | D7: =IF(COUNTIFS('VS×ケイパビリティ関係'!$F$4:$F$370,$B7,'VS×ケイパビリティ関係'!$G$4:$G$370,D$5,'VS×ケイパビリティ関係'!$E$4:$E$370,"主")>0,"●",IF(COUNTIFS('VS×ケイパビリティ関係'!$F$4:$F$370,$B7,'VS×ケイパビリティ関係'!$G$4:$G$370,D$5,'VS×ケイパビリティ関係'!$E$4:$E$370,"支援")>0,"○","")) | E7: =IF(COUNTIFS('VS×ケイパビリティ関係'!$F$4:$F$370,$B7,'VS×ケイパビリティ関係'!$G$4:$G$370,E$5,'VS×ケイパビリティ関係'!$E$4:$E$370,"主")>0,"●",IF(COUNTIFS('VS×ケイパビリティ関係'!$F$4:$F$370,$B7,'VS×ケイパビリティ関係'!$G$4:$G$370,E$5,'VS×ケイパビリティ関係'!$E$4:$E$370,"支援")>0,"○","")) | F7: =IF(COUNTIFS('VS×ケイパビリティ関係'!$F$4:$F$370,$B7,'VS×ケイパビリティ関係'!$G$4:$G$370,F$5,'VS×ケイパビリティ関係'!$E$4:$E$370,"主")>0,"●",IF(COUNTIFS('VS×ケイパビリティ関係'!$F$4:$F$370,$B7,'VS×ケイパビリティ関係'!$G$4:$G$370,F$5,'VS×ケイパビリティ関係'!$E$4:$E$370,"支援")>0,"○","")) | G7: =IF(COUNTIFS('VS×ケイパビリティ関係'!$F$4:$F$370,$B7,'VS×ケイパビリティ関係'!$G$4:$G$370,G$5,'VS×ケイパビリティ関係'!$E$4:$E$370,"主")>0,"●",IF(COUNTIFS('VS×ケイパビリティ関係'!$F$4:$F$370,$B7,'VS×ケイパビリティ関係'!$G$4:$G$370,G$5,'VS×ケイパビリティ関係'!$E$4:$E$370,"支援")>0,"○","")) | H7: =IF(COUNTIFS('VS×ケイパビリティ関係'!$F$4:$F$370,$B7,'VS×ケイパビリティ関係'!$G$4:$G$370,H$5,'VS×ケイパビリティ関係'!$E$4:$E$370,"主")>0,"●",IF(COUNTIFS('VS×ケイパビリティ関係'!$F$4:$F$370,$B7,'VS×ケイパビリティ関係'!$G$4:$G$370,H$5,'VS×ケイパビリティ関係'!$E$4:$E$370,"支援")>0,"○","")) | I7: =IF(COUNTIFS('VS×ケイパビリティ関係'!$F$4:$F$370,$B7,'VS×ケイパビリティ関係'!$G$4:$G$370,I$5,'VS×ケイパビリティ関係'!$E$4:$E$370,"主")>0,"●",IF(COUNTIFS('VS×ケイパビリティ関係'!$F$4:$F$370,$B7,'VS×ケイパビリティ関係'!$G$4:$G$370,I$5,'VS×ケイパビリティ関係'!$E$4:$E$370,"支援")>0,"○","")) | J7: =IF(COUNTIFS('VS×ケイパビリティ関係'!$F$4:$F$370,$B7,'VS×ケイパビリティ関係'!$G$4:$G$370,J$5,'VS×ケイパビリティ関係'!$E$4:$E$370,"主")>0,"●",IF(COUNTIFS('VS×ケイパビリティ関係'!$F$4:$F$370,$B7,'VS×ケイパビリティ関係'!$G$4:$G$370,J$5,'VS×ケイパビリティ関係'!$E$4:$E$370,"支援")>0,"○","")) | K7: =IF(COUNTIFS('VS×ケイパビリティ関係'!$F$4:$F$370,$B7,'VS×ケイパビリティ関係'!$G$4:$G$370,K$5,'VS×ケイパビリティ関係'!$E$4:$E$370,"主")>0,"●",IF(COUNTIFS('VS×ケイパビリティ関係'!$F$4:$F$370,$B7,'VS×ケイパビリティ関係'!$G$4:$G$370,K$5,'VS×ケイパビリティ関係'!$E$4:$E$370,"支援")>0,"○","")) | ... AI7: =IF(COUNTIFS('VS×ケイパビリティ関係'!$F$4:$F$370,$B7,'VS×ケイパビリティ関係'!$G$4:$G$370,AI$5,'VS×ケイパビリティ関係'!$E$4:$E$370,"主")>0,"●",IF(COUNTIFS('VS×ケイパビリティ関係'!$F$4:$F$370,$B7,'VS×ケイパビリティ関係'!$G$4:$G$370,AI$5,'VS×ケイパビリティ関係'!$E$4:$E$370,"支援")>0,"○","")) | AJ7: =COUNTIF(D7:AI7,"●") | AK7: =COUNTIF(D7:AI7,"○")
B8: 01-02 | C8: 母集団形成 | D8: =IF(COUNTIFS('VS×ケイパビリティ関係'!$F$4:$F$370,$B8,'VS×ケイパビリティ関係'!$G$4:$G$370,D$5,'VS×ケイパビリティ関係'!$E$4:$E$370,"主")>0,"●",IF(COUNTIFS('VS×ケイパビリティ関係'!$F$4:$F$370,$B8,'VS×ケイパビリティ関係'!$G$4:$G$370,D$5,'VS×ケイパビリティ関係'!$E$4:$E$370,"支援")>0,"○","")) | E8: =IF(COUNTIFS('VS×ケイパビリティ関係'!$F$4:$F$370,$B8,'VS×ケイパビリティ関係'!$G$4:$G$370,E$5,'VS×ケイパビリティ関係'!$E$4:$E$370,"主")>0,"●",IF(COUNTIFS('VS×ケイパビリティ関係'!$F$4:$F$370,$B8,'VS×ケイパビリティ関係'!$G$4:$G$370,E$5,'VS×ケイパビリティ関係'!$E$4:$E$370,"支援")>0,"○","")) | F8: =IF(COUNTIFS('VS×ケイパビリティ関係'!$F$4:$F$370,$B8,'VS×ケイパビリティ関係'!$G$4:$G$370,F$5,'VS×ケイパビリティ関係'!$E$4:$E$370,"主")>0,"●",IF(COUNTIFS('VS×ケイパビリティ関係'!$F$4:$F$370,$B8,'VS×ケイパビリティ関係'!$G$4:$G$370,F$5,'VS×ケイパビリティ関係'!$E$4:$E$370,"支援")>0,"○","")) | G8: =IF(COUNTIFS('VS×ケイパビリティ関係'!$F$4:$F$370,$B8,'VS×ケイパビリティ関係'!$G$4:$G$370,G$5,'VS×ケイパビリティ関係'!$E$4:$E$370,"主")>0,"●",IF(COUNTIFS('VS×ケイパビリティ関係'!$F$4:$F$370,$B8,'VS×ケイパビリティ関係'!$G$4:$G$370,G$5,'VS×ケイパビリティ関係'!$E$4:$E$370,"支援")>0,"○","")) | H8: =IF(COUNTIFS('VS×ケイパビリティ関係'!$F$4:$F$370,$B8,'VS×ケイパビリティ関係'!$G$4:$G$370,H$5,'VS×ケイパビリティ関係'!$E$4:$E$370,"主")>0,"●",IF(COUNTIFS('VS×ケイパビリティ関係'!$F$4:$F$370,$B8,'VS×ケイパビリティ関係'!$G$4:$G$370,H$5,'VS×ケイパビリティ関係'!$E$4:$E$370,"支援")>0,"○","")) | I8: =IF(COUNTIFS('VS×ケイパビリティ関係'!$F$4:$F$370,$B8,'VS×ケイパビリティ関係'!$G$4:$G$370,I$5,'VS×ケイパビリティ関係'!$E$4:$E$370,"主")>0,"●",IF(COUNTIFS('VS×ケイパビリティ関係'!$F$4:$F$370,$B8,'VS×ケイパビリティ関係'!$G$4:$G$370,I$5,'VS×ケイパビリティ関係'!$E$4:$E$370,"支援")>0,"○","")) | J8: =IF(COUNTIFS('VS×ケイパビリティ関係'!$F$4:$F$370,$B8,'VS×ケイパビリティ関係'!$G$4:$G$370,J$5,'VS×ケイパビリティ関係'!$E$4:$E$370,"主")>0,"●",IF(COUNTIFS('VS×ケイパビリティ関係'!$F$4:$F$370,$B8,'VS×ケイパビリティ関係'!$G$4:$G$370,J$5,'VS×ケイパビリティ関係'!$E$4:$E$370,"支援")>0,"○","")) | K8: =IF(COUNTIFS('VS×ケイパビリティ関係'!$F$4:$F$370,$B8,'VS×ケイパビリティ関係'!$G$4:$G$370,K$5,'VS×ケイパビリティ関係'!$E$4:$E$370,"主")>0,"●",IF(COUNTIFS('VS×ケイパビリティ関係'!$F$4:$F$370,$B8,'VS×ケイパビリティ関係'!$G$4:$G$370,K$5,'VS×ケイパビリティ関係'!$E$4:$E$370,"支援")>0,"○","")) | ... AI8: =IF(COUNTIFS('VS×ケイパビリティ関係'!$F$4:$F$370,$B8,'VS×ケイパビリティ関係'!$G$4:$G$370,AI$5,'VS×ケイパビリティ関係'!$E$4:$E$370,"主")>0,"●",IF(COUNTIFS('VS×ケイパビリティ関係'!$F$4:$F$370,$B8,'VS×ケイパビリティ関係'!$G$4:$G$370,AI$5,'VS×ケイパビリティ関係'!$E$4:$E$370,"支援")>0,"○","")) | AJ8: =COUNTIF(D8:AI8,"●") | AK8: =COUNTIF(D8:AI8,"○")
B9: 01-03 | C9: 選考 | D9: =IF(COUNTIFS('VS×ケイパビリティ関係'!$F$4:$F$370,$B9,'VS×ケイパビリティ関係'!$G$4:$G$370,D$5,'VS×ケイパビリティ関係'!$E$4:$E$370,"主")>0,"●",IF(COUNTIFS('VS×ケイパビリティ関係'!$F$4:$F$370,$B9,'VS×ケイパビリティ関係'!$G$4:$G$370,D$5,'VS×ケイパビリティ関係'!$E$4:$E$370,"支援")>0,"○","")) | E9: =IF(COUNTIFS('VS×ケイパビリティ関係'!$F$4:$F$370,$B9,'VS×ケイパビリティ関係'!$G$4:$G$370,E$5,'VS×ケイパビリティ関係'!$E$4:$E$370,"主")>0,"●",IF(COUNTIFS('VS×ケイパビリティ関係'!$F$4:$F$370,$B9,'VS×ケイパビリティ関係'!$G$4:$G$370,E$5,'VS×ケイパビリティ関係'!$E$4:$E$370,"支援")>0,"○","")) | F9: =IF(COUNTIFS('VS×ケイパビリティ関係'!$F$4:$F$370,$B9,'VS×ケイパビリティ関係'!$G$4:$G$370,F$5,'VS×ケイパビリティ関係'!$E$4:$E$370,"主")>0,"●",IF(COUNTIFS('VS×ケイパビリティ関係'!$F$4:$F$370,$B9,'VS×ケイパビリティ関係'!$G$4:$G$370,F$5,'VS×ケイパビリティ関係'!$E$4:$E$370,"支援")>0,"○","")) | G9: =IF(COUNTIFS('VS×ケイパビリティ関係'!$F$4:$F$370,$B9,'VS×ケイパビリティ関係'!$G$4:$G$370,G$5,'VS×ケイパビリティ関係'!$E$4:$E$370,"主")>0,"●",IF(COUNTIFS('VS×ケイパビリティ関係'!$F$4:$F$370,$B9,'VS×ケイパビリティ関係'!$G$4:$G$370,G$5,'VS×ケイパビリティ関係'!$E$4:$E$370,"支援")>0,"○","")) | H9: =IF(COUNTIFS('VS×ケイパビリティ関係'!$F$4:$F$370,$B9,'VS×ケイパビリティ関係'!$G$4:$G$370,H$5,'VS×ケイパビリティ関係'!$E$4:$E$370,"主")>0,"●",IF(COUNTIFS('VS×ケイパビリティ関係'!$F$4:$F$370,$B9,'VS×ケイパビリティ関係'!$G$4:$G$370,H$5,'VS×ケイパビリティ関係'!$E$4:$E$370,"支援")>0,"○","")) | I9: =IF(COUNTIFS('VS×ケイパビリティ関係'!$F$4:$F$370,$B9,'VS×ケイパビリティ関係'!$G$4:$G$370,I$5,'VS×ケイパビリティ関係'!$E$4:$E$370,"主")>0,"●",IF(COUNTIFS('VS×ケイパビリティ関係'!$F$4:$F$370,$B9,'VS×ケイパビリティ関係'!$G$4:$G$370,I$5,'VS×ケイパビリティ関係'!$E$4:$E$370,"支援")>0,"○","")) | J9: =IF(COUNTIFS('VS×ケイパビリティ関係'!$F$4:$F$370,$B9,'VS×ケイパビリティ関係'!$G$4:$G$370,J$5,'VS×ケイパビリティ関係'!$E$4:$E$370,"主")>0,"●",IF(COUNTIFS('VS×ケイパビリティ関係'!$F$4:$F$370,$B9,'VS×ケイパビリティ関係'!$G$4:$G$370,J$5,'VS×ケイパビリティ関係'!$E$4:$E$370,"支援")>0,"○","")) | K9: =IF(COUNTIFS('VS×ケイパビリティ関係'!$F$4:$F$370,$B9,'VS×ケイパビリティ関係'!$G$4:$G$370,K$5,'VS×ケイパビリティ関係'!$E$4:$E$370,"主")>0,"●",IF(COUNTIFS('VS×ケイパビリティ関係'!$F$4:$F$370,$B9,'VS×ケイパビリティ関係'!$G$4:$G$370,K$5,'VS×ケイパビリティ関係'!$E$4:$E$370,"支援")>0,"○","")) | ... AI9: =IF(COUNTIFS('VS×ケイパビリティ関係'!$F$4:$F$370,$B9,'VS×ケイパビリティ関係'!$G$4:$G$370,AI$5,'VS×ケイパビリティ関係'!$E$4:$E$370,"主")>0,"●",IF(COUNTIFS('VS×ケイパビリティ関係'!$F$4:$F$370,$B9,'VS×ケイパビリティ関係'!$G$4:$G$370,AI$5,'VS×ケイパビリティ関係'!$E$4:$E$370,"支援")>0,"○","")) | AJ9: =COUNTIF(D9:AI9,"●") | AK9: =COUNTIF(D9:AI9,"○")
B10: 01-04 | C10: 内定 | D10: =IF(COUNTIFS('VS×ケイパビリティ関係'!$F$4:$F$370,$B10,'VS×ケイパビリティ関係'!$G$4:$G$370,D$5,'VS×ケイパビリティ関係'!$E$4:$E$370,"主")>0,"●",IF(COUNTIFS('VS×ケイパビリティ関係'!$F$4:$F$370,$B10,'VS×ケイパビリティ関係'!$G$4:$G$370,D$5,'VS×ケイパビリティ関係'!$E$4:$E$370,"支援")>0,"○","")) | E10: =IF(COUNTIFS('VS×ケイパビリティ関係'!$F$4:$F$370,$B10,'VS×ケイパビリティ関係'!$G$4:$G$370,E$5,'VS×ケイパビリティ関係'!$E$4:$E$370,"主")>0,"●",IF(COUNTIFS('VS×ケイパビリティ関係'!$F$4:$F$370,$B10,'VS×ケイパビリティ関係'!$G$4:$G$370,E$5,'VS×ケイパビリティ関係'!$E$4:$E$370,"支援")>0,"○","")) | F10: =IF(COUNTIFS('VS×ケイパビリティ関係'!$F$4:$F$370,$B10,'VS×ケイパビリティ関係'!$G$4:$G$370,F$5,'VS×ケイパビリティ関係'!$E$4:$E$370,"主")>0,"●",IF(COUNTIFS('VS×ケイパビリティ関係'!$F$4:$F$370,$B10,'VS×ケイパビリティ関係'!$G$4:$G$370,F$5,'VS×ケイパビリティ関係'!$E$4:$E$370,"支援")>0,"○","")) | G10: =IF(COUNTIFS('VS×ケイパビリティ関係'!$F$4:$F$370,$B10,'VS×ケイパビリティ関係'!$G$4:$G$370,G$5,'VS×ケイパビリティ関係'!$E$4:$E$370,"主")>0,"●",IF(COUNTIFS('VS×ケイパビリティ関係'!$F$4:$F$370,$B10,'VS×ケイパビリティ関係'!$G$4:$G$370,G$5,'VS×ケイパビリティ関係'!$E$4:$E$370,"支援")>0,"○","")) | H10: =IF(COUNTIFS('VS×ケイパビリティ関係'!$F$4:$F$370,$B10,'VS×ケイパビリティ関係'!$G$4:$G$370,H$5,'VS×ケイパビリティ関係'!$E$4:$E$370,"主")>0,"●",IF(COUNTIFS('VS×ケイパビリティ関係'!$F$4:$F$370,$B10,'VS×ケイパビリティ関係'!$G$4:$G$370,H$5,'VS×ケイパビリティ関係'!$E$4:$E$370,"支援")>0,"○","")) | I10: =IF(COUNTIFS('VS×ケイパビリティ関係'!$F$4:$F$370,$B10,'VS×ケイパビリティ関係'!$G$4:$G$370,I$5,'VS×ケイパビリティ関係'!$E$4:$E$370,"主")>0,"●",IF(COUNTIFS('VS×ケイパビリティ関係'!$F$4:$F$370,$B10,'VS×ケイパビリティ関係'!$G$4:$G$370,I$5,'VS×ケイパビリティ関係'!$E$4:$E$370,"支援")>0,"○","")) | J10: =IF(COUNTIFS('VS×ケイパビリティ関係'!$F$4:$F$370,$B10,'VS×ケイパビリティ関係'!$G$4:$G$370,J$5,'VS×ケイパビリティ関係'!$E$4:$E$370,"主")>0,"●",IF(COUNTIFS('VS×ケイパビリティ関係'!$F$4:$F$370,$B10,'VS×ケイパビリティ関係'!$G$4:$G$370,J$5,'VS×ケイパビリティ関係'!$E$4:$E$370,"支援")>0,"○","")) | K10: =IF(COUNTIFS('VS×ケイパビリティ関係'!$F$4:$F$370,$B10,'VS×ケイパビリティ関係'!$G$4:$G$370,K$5,'VS×ケイパビリティ関係'!$E$4:$E$370,"主")>0,"●",IF(COUNTIFS('VS×ケイパビリティ関係'!$F$4:$F$370,$B10,'VS×ケイパビリティ関係'!$G$4:$G$370,K$5,'VS×ケイパビリティ関係'!$E$4:$E$370,"支援")>0,"○","")) | ... AI10: =IF(COUNTIFS('VS×ケイパビリティ関係'!$F$4:$F$370,$B10,'VS×ケイパビリティ関係'!$G$4:$G$370,AI$5,'VS×ケイパビリティ関係'!$E$4:$E$370,"主")>0,"●",IF(COUNTIFS('VS×ケイパビリティ関係'!$F$4:$F$370,$B10,'VS×ケイパビリティ関係'!$G$4:$G$370,AI$5,'VS×ケイパビリティ関係'!$E$4:$E$370,"支援")>0,"○","")) | AJ10: =COUNTIF(D10:AI10,"●") | AK10: =COUNTIF(D10:AI10,"○")
A11: 02 入社・オンボーディング | B11: 02-01 | C11: 雇用契約・入社手続き | D11: =IF(COUNTIFS('VS×ケイパビリティ関係'!$F$4:$F$370,$B11,'VS×ケイパビリティ関係'!$G$4:$G$370,D$5,'VS×ケイパビリティ関係'!$E$4:$E$370,"主")>0,"●",IF(COUNTIFS('VS×ケイパビリティ関係'!$F$4:$F$370,$B11,'VS×ケイパビリティ関係'!$G$4:$G$370,D$5,'VS×ケイパビリティ関係'!$E$4:$E$370,"支援")>0,"○","")) | E11: =IF(COUNTIFS('VS×ケイパビリティ関係'!$F$4:$F$370,$B11,'VS×ケイパビリティ関係'!$G$4:$G$370,E$5,'VS×ケイパビリティ関係'!$E$4:$E$370,"主")>0,"●",IF(COUNTIFS('VS×ケイパビリティ関係'!$F$4:$F$370,$B11,'VS×ケイパビリティ関係'!$G$4:$G$370,E$5,'VS×ケイパビリティ関係'!$E$4:$E$370,"支援")>0,"○","")) | F11: =IF(COUNTIFS('VS×ケイパビリティ関係'!$F$4:$F$370,$B11,'VS×ケイパビリティ関係'!$G$4:$G$370,F$5,'VS×ケイパビリティ関係'!$E$4:$E$370,"主")>0,"●",IF(COUNTIFS('VS×ケイパビリティ関係'!$F$4:$F$370,$B11,'VS×ケイパビリティ関係'!$G$4:$G$370,F$5,'VS×ケイパビリティ関係'!$E$4:$E$370,"支援")>0,"○","")) | G11: =IF(COUNTIFS('VS×ケイパビリティ関係'!$F$4:$F$370,$B11,'VS×ケイパビリティ関係'!$G$4:$G$370,G$5,'VS×ケイパビリティ関係'!$E$4:$E$370,"主")>0,"●",IF(COUNTIFS('VS×ケイパビリティ関係'!$F$4:$F$370,$B11,'VS×ケイパビリティ関係'!$G$4:$G$370,G$5,'VS×ケイパビリティ関係'!$E$4:$E$370,"支援")>0,"○","")) | H11: =IF(COUNTIFS('VS×ケイパビリティ関係'!$F$4:$F$370,$B11,'VS×ケイパビリティ関係'!$G$4:$G$370,H$5,'VS×ケイパビリティ関係'!$E$4:$E$370,"主")>0,"●",IF(COUNTIFS('VS×ケイパビリティ関係'!$F$4:$F$370,$B11,'VS×ケイパビリティ関係'!$G$4:$G$370,H$5,'VS×ケイパビリティ関係'!$E$4:$E$370,"支援")>0,"○","")) | I11: =IF(COUNTIFS('VS×ケイパビリティ関係'!$F$4:$F$370,$B11,'VS×ケイパビリティ関係'!$G$4:$G$370,I$5,'VS×ケイパビリティ関係'!$E$4:$E$370,"主")>0,"●",IF(COUNTIFS('VS×ケイパビリティ関係'!$F$4:$F$370,$B11,'VS×ケイパビリティ関係'!$G$4:$G$370,I$5,'VS×ケイパビリティ関係'!$E$4:$E$370,"支援")>0,"○","")) | J11: =IF(COUNTIFS('VS×ケイパビリティ関係'!$F$4:$F$370,$B11,'VS×ケイパビリティ関係'!$G$4:$G$370,J$5,'VS×ケイパビリティ関係'!$E$4:$E$370,"主")>0,"●",IF(COUNTIFS('VS×ケイパビリティ関係'!$F$4:$F$370,$B11,'VS×ケイパビリティ関係'!$G$4:$G$370,J$5,'VS×ケイパビリティ関係'!$E$4:$E$370,"支援")>0,"○","")) | K11: =IF(COUNTIFS('VS×ケイパビリティ関係'!$F$4:$F$370,$B11,'VS×ケイパビリティ関係'!$G$4:$G$370,K$5,'VS×ケイパビリティ関係'!$E$4:$E$370,"主")>0,"●",IF(COUNTIFS('VS×ケイパビリティ関係'!$F$4:$F$370,$B11,'VS×ケイパビリティ関係'!$G$4:$G$370,K$5,'VS×ケイパビリティ関係'!$E$4:$E$370,"支援")>0,"○","")) | ... AI11: =IF(COUNTIFS('VS×ケイパビリティ関係'!$F$4:$F$370,$B11,'VS×ケイパビリティ関係'!$G$4:$G$370,AI$5,'VS×ケイパビリティ関係'!$E$4:$E$370,"主")>0,"●",IF(COUNTIFS('VS×ケイパビリティ関係'!$F$4:$F$370,$B11,'VS×ケイパビリティ関係'!$G$4:$G$370,AI$5,'VS×ケイパビリティ関係'!$E$4:$E$370,"支援")>0,"○","")) | AJ11: =COUNTIF(D11:AI11,"●") | AK11: =COUNTIF(D11:AI11,"○")
B12: 02-02 | C12: 受入れ準備 | D12: =IF(COUNTIFS('VS×ケイパビリティ関係'!$F$4:$F$370,$B12,'VS×ケイパビリティ関係'!$G$4:$G$370,D$5,'VS×ケイパビリティ関係'!$E$4:$E$370,"主")>0,"●",IF(COUNTIFS('VS×ケイパビリティ関係'!$F$4:$F$370,$B12,'VS×ケイパビリティ関係'!$G$4:$G$370,D$5,'VS×ケイパビリティ関係'!$E$4:$E$370,"支援")>0,"○","")) | E12: =IF(COUNTIFS('VS×ケイパビリティ関係'!$F$4:$F$370,$B12,'VS×ケイパビリティ関係'!$G$4:$G$370,E$5,'VS×ケイパビリティ関係'!$E$4:$E$370,"主")>0,"●",IF(COUNTIFS('VS×ケイパビリティ関係'!$F$4:$F$370,$B12,'VS×ケイパビリティ関係'!$G$4:$G$370,E$5,'VS×ケイパビリティ関係'!$E$4:$E$370,"支援")>0,"○","")) | F12: =IF(COUNTIFS('VS×ケイパビリティ関係'!$F$4:$F$370,$B12,'VS×ケイパビリティ関係'!$G$4:$G$370,F$5,'VS×ケイパビリティ関係'!$E$4:$E$370,"主")>0,"●",IF(COUNTIFS('VS×ケイパビリティ関係'!$F$4:$F$370,$B12,'VS×ケイパビリティ関係'!$G$4:$G$370,F$5,'VS×ケイパビリティ関係'!$E$4:$E$370,"支援")>0,"○","")) | G12: =IF(COUNTIFS('VS×ケイパビリティ関係'!$F$4:$F$370,$B12,'VS×ケイパビリティ関係'!$G$4:$G$370,G$5,'VS×ケイパビリティ関係'!$E$4:$E$370,"主")>0,"●",IF(COUNTIFS('VS×ケイパビリティ関係'!$F$4:$F$370,$B12,'VS×ケイパビリティ関係'!$G$4:$G$370,G$5,'VS×ケイパビリティ関係'!$E$4:$E$370,"支援")>0,"○","")) | H12: =IF(COUNTIFS('VS×ケイパビリティ関係'!$F$4:$F$370,$B12,'VS×ケイパビリティ関係'!$G$4:$G$370,H$5,'VS×ケイパビリティ関係'!$E$4:$E$370,"主")>0,"●",IF(COUNTIFS('VS×ケイパビリティ関係'!$F$4:$F$370,$B12,'VS×ケイパビリティ関係'!$G$4:$G$370,H$5,'VS×ケイパビリティ関係'!$E$4:$E$370,"支援")>0,"○","")) | I12: =IF(COUNTIFS('VS×ケイパビリティ関係'!$F$4:$F$370,$B12,'VS×ケイパビリティ関係'!$G$4:$G$370,I$5,'VS×ケイパビリティ関係'!$E$4:$E$370,"主")>0,"●",IF(COUNTIFS('VS×ケイパビリティ関係'!$F$4:$F$370,$B12,'VS×ケイパビリティ関係'!$G$4:$G$370,I$5,'VS×ケイパビリティ関係'!$E$4:$E$370,"支援")>0,"○","")) | J12: =IF(COUNTIFS('VS×ケイパビリティ関係'!$F$4:$F$370,$B12,'VS×ケイパビリティ関係'!$G$4:$G$370,J$5,'VS×ケイパビリティ関係'!$E$4:$E$370,"主")>0,"●",IF(COUNTIFS('VS×ケイパビリティ関係'!$F$4:$F$370,$B12,'VS×ケイパビリティ関係'!$G$4:$G$370,J$5,'VS×ケイパビリティ関係'!$E$4:$E$370,"支援")>0,"○","")) | K12: =IF(COUNTIFS('VS×ケイパビリティ関係'!$F$4:$F$370,$B12,'VS×ケイパビリティ関係'!$G$4:$G$370,K$5,'VS×ケイパビリティ関係'!$E$4:$E$370,"主")>0,"●",IF(COUNTIFS('VS×ケイパビリティ関係'!$F$4:$F$370,$B12,'VS×ケイパビリティ関係'!$G$4:$G$370,K$5,'VS×ケイパビリティ関係'!$E$4:$E$370,"支援")>0,"○","")) | ... AI12: =IF(COUNTIFS('VS×ケイパビリティ関係'!$F$4:$F$370,$B12,'VS×ケイパビリティ関係'!$G$4:$G$370,AI$5,'VS×ケイパビリティ関係'!$E$4:$E$370,"主")>0,"●",IF(COUNTIFS('VS×ケイパビリティ関係'!$F$4:$F$370,$B12,'VS×ケイパビリティ関係'!$G$4:$G$370,AI$5,'VS×ケイパビリティ関係'!$E$4:$E$370,"支援")>0,"○","")) | AJ12: =COUNTIF(D12:AI12,"●") | AK12: =COUNTIF(D12:AI12,"○")
B13: 02-03 | C13: オンボーディング・定着 | D13: =IF(COUNTIFS('VS×ケイパビリティ関係'!$F$4:$F$370,$B13,'VS×ケイパビリティ関係'!$G$4:$G$370,D$5,'VS×ケイパビリティ関係'!$E$4:$E$370,"主")>0,"●",IF(COUNTIFS('VS×ケイパビリティ関係'!$F$4:$F$370,$B13,'VS×ケイパビリティ関係'!$G$4:$G$370,D$5,'VS×ケイパビリティ関係'!$E$4:$E$370,"支援")>0,"○","")) | E13: =IF(COUNTIFS('VS×ケイパビリティ関係'!$F$4:$F$370,$B13,'VS×ケイパビリティ関係'!$G$4:$G$370,E$5,'VS×ケイパビリティ関係'!$E$4:$E$370,"主")>0,"●",IF(COUNTIFS('VS×ケイパビリティ関係'!$F$4:$F$370,$B13,'VS×ケイパビリティ関係'!$G$4:$G$370,E$5,'VS×ケイパビリティ関係'!$E$4:$E$370,"支援")>0,"○","")) | F13: =IF(COUNTIFS('VS×ケイパビリティ関係'!$F$4:$F$370,$B13,'VS×ケイパビリティ関係'!$G$4:$G$370,F$5,'VS×ケイパビリティ関係'!$E$4:$E$370,"主")>0,"●",IF(COUNTIFS('VS×ケイパビリティ関係'!$F$4:$F$370,$B13,'VS×ケイパビリティ関係'!$G$4:$G$370,F$5,'VS×ケイパビリティ関係'!$E$4:$E$370,"支援")>0,"○","")) | G13: =IF(COUNTIFS('VS×ケイパビリティ関係'!$F$4:$F$370,$B13,'VS×ケイパビリティ関係'!$G$4:$G$370,G$5,'VS×ケイパビリティ関係'!$E$4:$E$370,"主")>0,"●",IF(COUNTIFS('VS×ケイパビリティ関係'!$F$4:$F$370,$B13,'VS×ケイパビリティ関係'!$G$4:$G$370,G$5,'VS×ケイパビリティ関係'!$E$4:$E$370,"支援")>0,"○","")) | H13: =IF(COUNTIFS('VS×ケイパビリティ関係'!$F$4:$F$370,$B13,'VS×ケイパビリティ関係'!$G$4:$G$370,H$5,'VS×ケイパビリティ関係'!$E$4:$E$370,"主")>0,"●",IF(COUNTIFS('VS×ケイパビリティ関係'!$F$4:$F$370,$B13,'VS×ケイパビリティ関係'!$G$4:$G$370,H$5,'VS×ケイパビリティ関係'!$E$4:$E$370,"支援")>0,"○","")) | I13: =IF(COUNTIFS('VS×ケイパビリティ関係'!$F$4:$F$370,$B13,'VS×ケイパビリティ関係'!$G$4:$G$370,I$5,'VS×ケイパビリティ関係'!$E$4:$E$370,"主")>0,"●",IF(COUNTIFS('VS×ケイパビリティ関係'!$F$4:$F$370,$B13,'VS×ケイパビリティ関係'!$G$4:$G$370,I$5,'VS×ケイパビリティ関係'!$E$4:$E$370,"支援")>0,"○","")) | J13: =IF(COUNTIFS('VS×ケイパビリティ関係'!$F$4:$F$370,$B13,'VS×ケイパビリティ関係'!$G$4:$G$370,J$5,'VS×ケイパビリティ関係'!$E$4:$E$370,"主")>0,"●",IF(COUNTIFS('VS×ケイパビリティ関係'!$F$4:$F$370,$B13,'VS×ケイパビリティ関係'!$G$4:$G$370,J$5,'VS×ケイパビリティ関係'!$E$4:$E$370,"支援")>0,"○","")) | K13: =IF(COUNTIFS('VS×ケイパビリティ関係'!$F$4:$F$370,$B13,'VS×ケイパビリティ関係'!$G$4:$G$370,K$5,'VS×ケイパビリティ関係'!$E$4:$E$370,"主")>0,"●",IF(COUNTIFS('VS×ケイパビリティ関係'!$F$4:$F$370,$B13,'VS×ケイパビリティ関係'!$G$4:$G$370,K$5,'VS×ケイパビリティ関係'!$E$4:$E$370,"支援")>0,"○","")) | ... AI13: =IF(COUNTIFS('VS×ケイパビリティ関係'!$F$4:$F$370,$B13,'VS×ケイパビリティ関係'!$G$4:$G$370,AI$5,'VS×ケイパビリティ関係'!$E$4:$E$370,"主")>0,"●",IF(COUNTIFS('VS×ケイパビリティ関係'!$F$4:$F$370,$B13,'VS×ケイパビリティ関係'!$G$4:$G$370,AI$5,'VS×ケイパビリティ関係'!$E$4:$E$370,"支援")>0,"○","")) | AJ13: =COUNTIF(D13:AI13,"●") | AK13: =COUNTIF(D13:AI13,"○")
A14: 03 人材育成・能力開発 | B14: 03-01 | C14: 育成計画 | D14: =IF(COUNTIFS('VS×ケイパビリティ関係'!$F$4:$F$370,$B14,'VS×ケイパビリティ関係'!$G$4:$G$370,D$5,'VS×ケイパビリティ関係'!$E$4:$E$370,"主")>0,"●",IF(COUNTIFS('VS×ケイパビリティ関係'!$F$4:$F$370,$B14,'VS×ケイパビリティ関係'!$G$4:$G$370,D$5,'VS×ケイパビリティ関係'!$E$4:$E$370,"支援")>0,"○","")) | E14: =IF(COUNTIFS('VS×ケイパビリティ関係'!$F$4:$F$370,$B14,'VS×ケイパビリティ関係'!$G$4:$G$370,E$5,'VS×ケイパビリティ関係'!$E$4:$E$370,"主")>0,"●",IF(COUNTIFS('VS×ケイパビリティ関係'!$F$4:$F$370,$B14,'VS×ケイパビリティ関係'!$G$4:$G$370,E$5,'VS×ケイパビリティ関係'!$E$4:$E$370,"支援")>0,"○","")) | F14: =IF(COUNTIFS('VS×ケイパビリティ関係'!$F$4:$F$370,$B14,'VS×ケイパビリティ関係'!$G$4:$G$370,F$5,'VS×ケイパビリティ関係'!$E$4:$E$370,"主")>0,"●",IF(COUNTIFS('VS×ケイパビリティ関係'!$F$4:$F$370,$B14,'VS×ケイパビリティ関係'!$G$4:$G$370,F$5,'VS×ケイパビリティ関係'!$E$4:$E$370,"支援")>0,"○","")) | G14: =IF(COUNTIFS('VS×ケイパビリティ関係'!$F$4:$F$370,$B14,'VS×ケイパビリティ関係'!$G$4:$G$370,G$5,'VS×ケイパビリティ関係'!$E$4:$E$370,"主")>0,"●",IF(COUNTIFS('VS×ケイパビリティ関係'!$F$4:$F$370,$B14,'VS×ケイパビリティ関係'!$G$4:$G$370,G$5,'VS×ケイパビリティ関係'!$E$4:$E$370,"支援")>0,"○","")) | H14: =IF(COUNTIFS('VS×ケイパビリティ関係'!$F$4:$F$370,$B14,'VS×ケイパビリティ関係'!$G$4:$G$370,H$5,'VS×ケイパビリティ関係'!$E$4:$E$370,"主")>0,"●",IF(COUNTIFS('VS×ケイパビリティ関係'!$F$4:$F$370,$B14,'VS×ケイパビリティ関係'!$G$4:$G$370,H$5,'VS×ケイパビリティ関係'!$E$4:$E$370,"支援")>0,"○","")) | I14: =IF(COUNTIFS('VS×ケイパビリティ関係'!$F$4:$F$370,$B14,'VS×ケイパビリティ関係'!$G$4:$G$370,I$5,'VS×ケイパビリティ関係'!$E$4:$E$370,"主")>0,"●",IF(COUNTIFS('VS×ケイパビリティ関係'!$F$4:$F$370,$B14,'VS×ケイパビリティ関係'!$G$4:$G$370,I$5,'VS×ケイパビリティ関係'!$E$4:$E$370,"支援")>0,"○","")) | J14: =IF(COUNTIFS('VS×ケイパビリティ関係'!$F$4:$F$370,$B14,'VS×ケイパビリティ関係'!$G$4:$G$370,J$5,'VS×ケイパビリティ関係'!$E$4:$E$370,"主")>0,"●",IF(COUNTIFS('VS×ケイパビリティ関係'!$F$4:$F$370,$B14,'VS×ケイパビリティ関係'!$G$4:$G$370,J$5,'VS×ケイパビリティ関係'!$E$4:$E$370,"支援")>0,"○","")) | K14: =IF(COUNTIFS('VS×ケイパビリティ関係'!$F$4:$F$370,$B14,'VS×ケイパビリティ関係'!$G$4:$G$370,K$5,'VS×ケイパビリティ関係'!$E$4:$E$370,"主")>0,"●",IF(COUNTIFS('VS×ケイパビリティ関係'!$F$4:$F$370,$B14,'VS×ケイパビリティ関係'!$G$4:$G$370,K$5,'VS×ケイパビリティ関係'!$E$4:$E$370,"支援")>0,"○","")) | ... AI14: =IF(COUNTIFS('VS×ケイパビリティ関係'!$F$4:$F$370,$B14,'VS×ケイパビリティ関係'!$G$4:$G$370,AI$5,'VS×ケイパビリティ関係'!$E$4:$E$370,"主")>0,"●",IF(COUNTIFS('VS×ケイパビリティ関係'!$F$4:$F$370,$B14,'VS×ケイパビリティ関係'!$G$4:$G$370,AI$5,'VS×ケイパビリティ関係'!$E$4:$E$370,"支援")>0,"○","")) | AJ14: =COUNTIF(D14:AI14,"●") | AK14: =COUNTIF(D14:AI14,"○")
B15: 03-02 | C15: 研修・学習 | D15: =IF(COUNTIFS('VS×ケイパビリティ関係'!$F$4:$F$370,$B15,'VS×ケイパビリティ関係'!$G$4:$G$370,D$5,'VS×ケイパビリティ関係'!$E$4:$E$370,"主")>0,"●",IF(COUNTIFS('VS×ケイパビリティ関係'!$F$4:$F$370,$B15,'VS×ケイパビリティ関係'!$G$4:$G$370,D$5,'VS×ケイパビリティ関係'!$E$4:$E$370,"支援")>0,"○","")) | E15: =IF(COUNTIFS('VS×ケイパビリティ関係'!$F$4:$F$370,$B15,'VS×ケイパビリティ関係'!$G$4:$G$370,E$5,'VS×ケイパビリティ関係'!$E$4:$E$370,"主")>0,"●",IF(COUNTIFS('VS×ケイパビリティ関係'!$F$4:$F$370,$B15,'VS×ケイパビリティ関係'!$G$4:$G$370,E$5,'VS×ケイパビリティ関係'!$E$4:$E$370,"支援")>0,"○","")) | F15: =IF(COUNTIFS('VS×ケイパビリティ関係'!$F$4:$F$370,$B15,'VS×ケイパビリティ関係'!$G$4:$G$370,F$5,'VS×ケイパビリティ関係'!$E$4:$E$370,"主")>0,"●",IF(COUNTIFS('VS×ケイパビリティ関係'!$F$4:$F$370,$B15,'VS×ケイパビリティ関係'!$G$4:$G$370,F$5,'VS×ケイパビリティ関係'!$E$4:$E$370,"支援")>0,"○","")) | G15: =IF(COUNTIFS('VS×ケイパビリティ関係'!$F$4:$F$370,$B15,'VS×ケイパビリティ関係'!$G$4:$G$370,G$5,'VS×ケイパビリティ関係'!$E$4:$E$370,"主")>0,"●",IF(COUNTIFS('VS×ケイパビリティ関係'!$F$4:$F$370,$B15,'VS×ケイパビリティ関係'!$G$4:$G$370,G$5,'VS×ケイパビリティ関係'!$E$4:$E$370,"支援")>0,"○","")) | H15: =IF(COUNTIFS('VS×ケイパビリティ関係'!$F$4:$F$370,$B15,'VS×ケイパビリティ関係'!$G$4:$G$370,H$5,'VS×ケイパビリティ関係'!$E$4:$E$370,"主")>0,"●",IF(COUNTIFS('VS×ケイパビリティ関係'!$F$4:$F$370,$B15,'VS×ケイパビリティ関係'!$G$4:$G$370,H$5,'VS×ケイパビリティ関係'!$E$4:$E$370,"支援")>0,"○","")) | I15: =IF(COUNTIFS('VS×ケイパビリティ関係'!$F$4:$F$370,$B15,'VS×ケイパビリティ関係'!$G$4:$G$370,I$5,'VS×ケイパビリティ関係'!$E$4:$E$370,"主")>0,"●",IF(COUNTIFS('VS×ケイパビリティ関係'!$F$4:$F$370,$B15,'VS×ケイパビリティ関係'!$G$4:$G$370,I$5,'VS×ケイパビリティ関係'!$E$4:$E$370,"支援")>0,"○","")) | J15: =IF(COUNTIFS('VS×ケイパビリティ関係'!$F$4:$F$370,$B15,'VS×ケイパビリティ関係'!$G$4:$G$370,J$5,'VS×ケイパビリティ関係'!$E$4:$E$370,"主")>0,"●",IF(COUNTIFS('VS×ケイパビリティ関係'!$F$4:$F$370,$B15,'VS×ケイパビリティ関係'!$G$4:$G$370,J$5,'VS×ケイパビリティ関係'!$E$4:$E$370,"支援")>0,"○","")) | K15: =IF(COUNTIFS('VS×ケイパビリティ関係'!$F$4:$F$370,$B15,'VS×ケイパビリティ関係'!$G$4:$G$370,K$5,'VS×ケイパビリティ関係'!$E$4:$E$370,"主")>0,"●",IF(COUNTIFS('VS×ケイパビリティ関係'!$F$4:$F$370,$B15,'VS×ケイパビリティ関係'!$G$4:$G$370,K$5,'VS×ケイパビリティ関係'!$E$4:$E$370,"支援")>0,"○","")) | ... AI15: =IF(COUNTIFS('VS×ケイパビリティ関係'!$F$4:$F$370,$B15,'VS×ケイパビリティ関係'!$G$4:$G$370,AI$5,'VS×ケイパビリティ関係'!$E$4:$E$370,"主")>0,"●",IF(COUNTIFS('VS×ケイパビリティ関係'!$F$4:$F$370,$B15,'VS×ケイパビリティ関係'!$G$4:$G$370,AI$5,'VS×ケイパビリティ関係'!$E$4:$E$370,"支援")>0,"○","")) | AJ15: =COUNTIF(D15:AI15,"●") | AK15: =COUNTIF(D15:AI15,"○")
B16: 03-03 | C16: スキル・資格の習得 | D16: =IF(COUNTIFS('VS×ケイパビリティ関係'!$F$4:$F$370,$B16,'VS×ケイパビリティ関係'!$G$4:$G$370,D$5,'VS×ケイパビリティ関係'!$E$4:$E$370,"主")>0,"●",IF(COUNTIFS('VS×ケイパビリティ関係'!$F$4:$F$370,$B16,'VS×ケイパビリティ関係'!$G$4:$G$370,D$5,'VS×ケイパビリティ関係'!$E$4:$E$370,"支援")>0,"○","")) | E16: =IF(COUNTIFS('VS×ケイパビリティ関係'!$F$4:$F$370,$B16,'VS×ケイパビリティ関係'!$G$4:$G$370,E$5,'VS×ケイパビリティ関係'!$E$4:$E$370,"主")>0,"●",IF(COUNTIFS('VS×ケイパビリティ関係'!$F$4:$F$370,$B16,'VS×ケイパビリティ関係'!$G$4:$G$370,E$5,'VS×ケイパビリティ関係'!$E$4:$E$370,"支援")>0,"○","")) | F16: =IF(COUNTIFS('VS×ケイパビリティ関係'!$F$4:$F$370,$B16,'VS×ケイパビリティ関係'!$G$4:$G$370,F$5,'VS×ケイパビリティ関係'!$E$4:$E$370,"主")>0,"●",IF(COUNTIFS('VS×ケイパビリティ関係'!$F$4:$F$370,$B16,'VS×ケイパビリティ関係'!$G$4:$G$370,F$5,'VS×ケイパビリティ関係'!$E$4:$E$370,"支援")>0,"○","")) | G16: =IF(COUNTIFS('VS×ケイパビリティ関係'!$F$4:$F$370,$B16,'VS×ケイパビリティ関係'!$G$4:$G$370,G$5,'VS×ケイパビリティ関係'!$E$4:$E$370,"主")>0,"●",IF(COUNTIFS('VS×ケイパビリティ関係'!$F$4:$F$370,$B16,'VS×ケイパビリティ関係'!$G$4:$G$370,G$5,'VS×ケイパビリティ関係'!$E$4:$E$370,"支援")>0,"○","")) | H16: =IF(COUNTIFS('VS×ケイパビリティ関係'!$F$4:$F$370,$B16,'VS×ケイパビリティ関係'!$G$4:$G$370,H$5,'VS×ケイパビリティ関係'!$E$4:$E$370,"主")>0,"●",IF(COUNTIFS('VS×ケイパビリティ関係'!$F$4:$F$370,$B16,'VS×ケイパビリティ関係'!$G$4:$G$370,H$5,'VS×ケイパビリティ関係'!$E$4:$E$370,"支援")>0,"○","")) | I16: =IF(COUNTIFS('VS×ケイパビリティ関係'!$F$4:$F$370,$B16,'VS×ケイパビリティ関係'!$G$4:$G$370,I$5,'VS×ケイパビリティ関係'!$E$4:$E$370,"主")>0,"●",IF(COUNTIFS('VS×ケイパビリティ関係'!$F$4:$F$370,$B16,'VS×ケイパビリティ関係'!$G$4:$G$370,I$5,'VS×ケイパビリティ関係'!$E$4:$E$370,"支援")>0,"○","")) | J16: =IF(COUNTIFS('VS×ケイパビリティ関係'!$F$4:$F$370,$B16,'VS×ケイパビリティ関係'!$G$4:$G$370,J$5,'VS×ケイパビリティ関係'!$E$4:$E$370,"主")>0,"●",IF(COUNTIFS('VS×ケイパビリティ関係'!$F$4:$F$370,$B16,'VS×ケイパビリティ関係'!$G$4:$G$370,J$5,'VS×ケイパビリティ関係'!$E$4:$E$370,"支援")>0,"○","")) | K16: =IF(COUNTIFS('VS×ケイパビリティ関係'!$F$4:$F$370,$B16,'VS×ケイパビリティ関係'!$G$4:$G$370,K$5,'VS×ケイパビリティ関係'!$E$4:$E$370,"主")>0,"●",IF(COUNTIFS('VS×ケイパビリティ関係'!$F$4:$F$370,$B16,'VS×ケイパビリティ関係'!$G$4:$G$370,K$5,'VS×ケイパビリティ関係'!$E$4:$E$370,"支援")>0,"○","")) | ... AI16: =IF(COUNTIFS('VS×ケイパビリティ関係'!$F$4:$F$370,$B16,'VS×ケイパビリティ関係'!$G$4:$G$370,AI$5,'VS×ケイパビリティ関係'!$E$4:$E$370,"主")>0,"●",IF(COUNTIFS('VS×ケイパビリティ関係'!$F$4:$F$370,$B16,'VS×ケイパビリティ関係'!$G$4:$G$370,AI$5,'VS×ケイパビリティ関係'!$E$4:$E$370,"支援")>0,"○","")) | AJ16: =COUNTIF(D16:AI16,"●") | AK16: =COUNTIF(D16:AI16,"○")
B17: 03-04 | C17: キャリア開発 | D17: =IF(COUNTIFS('VS×ケイパビリティ関係'!$F$4:$F$370,$B17,'VS×ケイパビリティ関係'!$G$4:$G$370,D$5,'VS×ケイパビリティ関係'!$E$4:$E$370,"主")>0,"●",IF(COUNTIFS('VS×ケイパビリティ関係'!$F$4:$F$370,$B17,'VS×ケイパビリティ関係'!$G$4:$G$370,D$5,'VS×ケイパビリティ関係'!$E$4:$E$370,"支援")>0,"○","")) | E17: =IF(COUNTIFS('VS×ケイパビリティ関係'!$F$4:$F$370,$B17,'VS×ケイパビリティ関係'!$G$4:$G$370,E$5,'VS×ケイパビリティ関係'!$E$4:$E$370,"主")>0,"●",IF(COUNTIFS('VS×ケイパビリティ関係'!$F$4:$F$370,$B17,'VS×ケイパビリティ関係'!$G$4:$G$370,E$5,'VS×ケイパビリティ関係'!$E$4:$E$370,"支援")>0,"○","")) | F17: =IF(COUNTIFS('VS×ケイパビリティ関係'!$F$4:$F$370,$B17,'VS×ケイパビリティ関係'!$G$4:$G$370,F$5,'VS×ケイパビリティ関係'!$E$4:$E$370,"主")>0,"●",IF(COUNTIFS('VS×ケイパビリティ関係'!$F$4:$F$370,$B17,'VS×ケイパビリティ関係'!$G$4:$G$370,F$5,'VS×ケイパビリティ関係'!$E$4:$E$370,"支援")>0,"○","")) | G17: =IF(COUNTIFS('VS×ケイパビリティ関係'!$F$4:$F$370,$B17,'VS×ケイパビリティ関係'!$G$4:$G$370,G$5,'VS×ケイパビリティ関係'!$E$4:$E$370,"主")>0,"●",IF(COUNTIFS('VS×ケイパビリティ関係'!$F$4:$F$370,$B17,'VS×ケイパビリティ関係'!$G$4:$G$370,G$5,'VS×ケイパビリティ関係'!$E$4:$E$370,"支援")>0,"○","")) | H17: =IF(COUNTIFS('VS×ケイパビリティ関係'!$F$4:$F$370,$B17,'VS×ケイパビリティ関係'!$G$4:$G$370,H$5,'VS×ケイパビリティ関係'!$E$4:$E$370,"主")>0,"●",IF(COUNTIFS('VS×ケイパビリティ関係'!$F$4:$F$370,$B17,'VS×ケイパビリティ関係'!$G$4:$G$370,H$5,'VS×ケイパビリティ関係'!$E$4:$E$370,"支援")>0,"○","")) | I17: =IF(COUNTIFS('VS×ケイパビリティ関係'!$F$4:$F$370,$B17,'VS×ケイパビリティ関係'!$G$4:$G$370,I$5,'VS×ケイパビリティ関係'!$E$4:$E$370,"主")>0,"●",IF(COUNTIFS('VS×ケイパビリティ関係'!$F$4:$F$370,$B17,'VS×ケイパビリティ関係'!$G$4:$G$370,I$5,'VS×ケイパビリティ関係'!$E$4:$E$370,"支援")>0,"○","")) | J17: =IF(COUNTIFS('VS×ケイパビリティ関係'!$F$4:$F$370,$B17,'VS×ケイパビリティ関係'!$G$4:$G$370,J$5,'VS×ケイパビリティ関係'!$E$4:$E$370,"主")>0,"●",IF(COUNTIFS('VS×ケイパビリティ関係'!$F$4:$F$370,$B17,'VS×ケイパビリティ関係'!$G$4:$G$370,J$5,'VS×ケイパビリティ関係'!$E$4:$E$370,"支援")>0,"○","")) | K17: =IF(COUNTIFS('VS×ケイパビリティ関係'!$F$4:$F$370,$B17,'VS×ケイパビリティ関係'!$G$4:$G$370,K$5,'VS×ケイパビリティ関係'!$E$4:$E$370,"主")>0,"●",IF(COUNTIFS('VS×ケイパビリティ関係'!$F$4:$F$370,$B17,'VS×ケイパビリティ関係'!$G$4:$G$370,K$5,'VS×ケイパビリティ関係'!$E$4:$E$370,"支援")>0,"○","")) | ... AI17: =IF(COUNTIFS('VS×ケイパビリティ関係'!$F$4:$F$370,$B17,'VS×ケイパビリティ関係'!$G$4:$G$370,AI$5,'VS×ケイパビリティ関係'!$E$4:$E$370,"主")>0,"●",IF(COUNTIFS('VS×ケイパビリティ関係'!$F$4:$F$370,$B17,'VS×ケイパビリティ関係'!$G$4:$G$370,AI$5,'VS×ケイパビリティ関係'!$E$4:$E$370,"支援")>0,"○","")) | AJ17: =COUNTIF(D17:AI17,"●") | AK17: =COUNTIF(D17:AI17,"○")
A18: 04 評価・処遇 | B18: 04-01 | C18: 目標設定・評価 | D18: =IF(COUNTIFS('VS×ケイパビリティ関係'!$F$4:$F$370,$B18,'VS×ケイパビリティ関係'!$G$4:$G$370,D$5,'VS×ケイパビリティ関係'!$E$4:$E$370,"主")>0,"●",IF(COUNTIFS('VS×ケイパビリティ関係'!$F$4:$F$370,$B18,'VS×ケイパビリティ関係'!$G$4:$G$370,D$5,'VS×ケイパビリティ関係'!$E$4:$E$370,"支援")>0,"○","")) | E18: =IF(COUNTIFS('VS×ケイパビリティ関係'!$F$4:$F$370,$B18,'VS×ケイパビリティ関係'!$G$4:$G$370,E$5,'VS×ケイパビリティ関係'!$E$4:$E$370,"主")>0,"●",IF(COUNTIFS('VS×ケイパビリティ関係'!$F$4:$F$370,$B18,'VS×ケイパビリティ関係'!$G$4:$G$370,E$5,'VS×ケイパビリティ関係'!$E$4:$E$370,"支援")>0,"○","")) | F18: =IF(COUNTIFS('VS×ケイパビリティ関係'!$F$4:$F$370,$B18,'VS×ケイパビリティ関係'!$G$4:$G$370,F$5,'VS×ケイパビリティ関係'!$E$4:$E$370,"主")>0,"●",IF(COUNTIFS('VS×ケイパビリティ関係'!$F$4:$F$370,$B18,'VS×ケイパビリティ関係'!$G$4:$G$370,F$5,'VS×ケイパビリティ関係'!$E$4:$E$370,"支援")>0,"○","")) | G18: =IF(COUNTIFS('VS×ケイパビリティ関係'!$F$4:$F$370,$B18,'VS×ケイパビリティ関係'!$G$4:$G$370,G$5,'VS×ケイパビリティ関係'!$E$4:$E$370,"主")>0,"●",IF(COUNTIFS('VS×ケイパビリティ関係'!$F$4:$F$370,$B18,'VS×ケイパビリティ関係'!$G$4:$G$370,G$5,'VS×ケイパビリティ関係'!$E$4:$E$370,"支援")>0,"○","")) | H18: =IF(COUNTIFS('VS×ケイパビリティ関係'!$F$4:$F$370,$B18,'VS×ケイパビリティ関係'!$G$4:$G$370,H$5,'VS×ケイパビリティ関係'!$E$4:$E$370,"主")>0,"●",IF(COUNTIFS('VS×ケイパビリティ関係'!$F$4:$F$370,$B18,'VS×ケイパビリティ関係'!$G$4:$G$370,H$5,'VS×ケイパビリティ関係'!$E$4:$E$370,"支援")>0,"○","")) | I18: =IF(COUNTIFS('VS×ケイパビリティ関係'!$F$4:$F$370,$B18,'VS×ケイパビリティ関係'!$G$4:$G$370,I$5,'VS×ケイパビリティ関係'!$E$4:$E$370,"主")>0,"●",IF(COUNTIFS('VS×ケイパビリティ関係'!$F$4:$F$370,$B18,'VS×ケイパビリティ関係'!$G$4:$G$370,I$5,'VS×ケイパビリティ関係'!$E$4:$E$370,"支援")>0,"○","")) | J18: =IF(COUNTIFS('VS×ケイパビリティ関係'!$F$4:$F$370,$B18,'VS×ケイパビリティ関係'!$G$4:$G$370,J$5,'VS×ケイパビリティ関係'!$E$4:$E$370,"主")>0,"●",IF(COUNTIFS('VS×ケイパビリティ関係'!$F$4:$F$370,$B18,'VS×ケイパビリティ関係'!$G$4:$G$370,J$5,'VS×ケイパビリティ関係'!$E$4:$E$370,"支援")>0,"○","")) | K18: =IF(COUNTIFS('VS×ケイパビリティ関係'!$F$4:$F$370,$B18,'VS×ケイパビリティ関係'!$G$4:$G$370,K$5,'VS×ケイパビリティ関係'!$E$4:$E$370,"主")>0,"●",IF(COUNTIFS('VS×ケイパビリティ関係'!$F$4:$F$370,$B18,'VS×ケイパビリティ関係'!$G$4:$G$370,K$5,'VS×ケイパビリティ関係'!$E$4:$E$370,"支援")>0,"○","")) | ... AI18: =IF(COUNTIFS('VS×ケイパビリティ関係'!$F$4:$F$370,$B18,'VS×ケイパビリティ関係'!$G$4:$G$370,AI$5,'VS×ケイパビリティ関係'!$E$4:$E$370,"主")>0,"●",IF(COUNTIFS('VS×ケイパビリティ関係'!$F$4:$F$370,$B18,'VS×ケイパビリティ関係'!$G$4:$G$370,AI$5,'VS×ケイパビリティ関係'!$E$4:$E$370,"支援")>0,"○","")) | AJ18: =COUNTIF(D18:AI18,"●") | AK18: =COUNTIF(D18:AI18,"○")
B19: 04-02 | C19: 報酬決定 | D19: =IF(COUNTIFS('VS×ケイパビリティ関係'!$F$4:$F$370,$B19,'VS×ケイパビリティ関係'!$G$4:$G$370,D$5,'VS×ケイパビリティ関係'!$E$4:$E$370,"主")>0,"●",IF(COUNTIFS('VS×ケイパビリティ関係'!$F$4:$F$370,$B19,'VS×ケイパビリティ関係'!$G$4:$G$370,D$5,'VS×ケイパビリティ関係'!$E$4:$E$370,"支援")>0,"○","")) | E19: =IF(COUNTIFS('VS×ケイパビリティ関係'!$F$4:$F$370,$B19,'VS×ケイパビリティ関係'!$G$4:$G$370,E$5,'VS×ケイパビリティ関係'!$E$4:$E$370,"主")>0,"●",IF(COUNTIFS('VS×ケイパビリティ関係'!$F$4:$F$370,$B19,'VS×ケイパビリティ関係'!$G$4:$G$370,E$5,'VS×ケイパビリティ関係'!$E$4:$E$370,"支援")>0,"○","")) | F19: =IF(COUNTIFS('VS×ケイパビリティ関係'!$F$4:$F$370,$B19,'VS×ケイパビリティ関係'!$G$4:$G$370,F$5,'VS×ケイパビリティ関係'!$E$4:$E$370,"主")>0,"●",IF(COUNTIFS('VS×ケイパビリティ関係'!$F$4:$F$370,$B19,'VS×ケイパビリティ関係'!$G$4:$G$370,F$5,'VS×ケイパビリティ関係'!$E$4:$E$370,"支援")>0,"○","")) | G19: =IF(COUNTIFS('VS×ケイパビリティ関係'!$F$4:$F$370,$B19,'VS×ケイパビリティ関係'!$G$4:$G$370,G$5,'VS×ケイパビリティ関係'!$E$4:$E$370,"主")>0,"●",IF(COUNTIFS('VS×ケイパビリティ関係'!$F$4:$F$370,$B19,'VS×ケイパビリティ関係'!$G$4:$G$370,G$5,'VS×ケイパビリティ関係'!$E$4:$E$370,"支援")>0,"○","")) | H19: =IF(COUNTIFS('VS×ケイパビリティ関係'!$F$4:$F$370,$B19,'VS×ケイパビリティ関係'!$G$4:$G$370,H$5,'VS×ケイパビリティ関係'!$E$4:$E$370,"主")>0,"●",IF(COUNTIFS('VS×ケイパビリティ関係'!$F$4:$F$370,$B19,'VS×ケイパビリティ関係'!$G$4:$G$370,H$5,'VS×ケイパビリティ関係'!$E$4:$E$370,"支援")>0,"○","")) | I19: =IF(COUNTIFS('VS×ケイパビリティ関係'!$F$4:$F$370,$B19,'VS×ケイパビリティ関係'!$G$4:$G$370,I$5,'VS×ケイパビリティ関係'!$E$4:$E$370,"主")>0,"●",IF(COUNTIFS('VS×ケイパビリティ関係'!$F$4:$F$370,$B19,'VS×ケイパビリティ関係'!$G$4:$G$370,I$5,'VS×ケイパビリティ関係'!$E$4:$E$370,"支援")>0,"○","")) | J19: =IF(COUNTIFS('VS×ケイパビリティ関係'!$F$4:$F$370,$B19,'VS×ケイパビリティ関係'!$G$4:$G$370,J$5,'VS×ケイパビリティ関係'!$E$4:$E$370,"主")>0,"●",IF(COUNTIFS('VS×ケイパビリティ関係'!$F$4:$F$370,$B19,'VS×ケイパビリティ関係'!$G$4:$G$370,J$5,'VS×ケイパビリティ関係'!$E$4:$E$370,"支援")>0,"○","")) | K19: =IF(COUNTIFS('VS×ケイパビリティ関係'!$F$4:$F$370,$B19,'VS×ケイパビリティ関係'!$G$4:$G$370,K$5,'VS×ケイパビリティ関係'!$E$4:$E$370,"主")>0,"●",IF(COUNTIFS('VS×ケイパビリティ関係'!$F$4:$F$370,$B19,'VS×ケイパビリティ関係'!$G$4:$G$370,K$5,'VS×ケイパビリティ関係'!$E$4:$E$370,"支援")>0,"○","")) | ... AI19: =IF(COUNTIFS('VS×ケイパビリティ関係'!$F$4:$F$370,$B19,'VS×ケイパビリティ関係'!$G$4:$G$370,AI$5,'VS×ケイパビリティ関係'!$E$4:$E$370,"主")>0,"●",IF(COUNTIFS('VS×ケイパビリティ関係'!$F$4:$F$370,$B19,'VS×ケイパビリティ関係'!$G$4:$G$370,AI$5,'VS×ケイパビリティ関係'!$E$4:$E$370,"支援")>0,"○","")) | AJ19: =COUNTIF(D19:AI19,"●") | AK19: =COUNTIF(D19:AI19,"○")
B20: 04-03 | C20: 勤怠・休暇管理 | D20: =IF(COUNTIFS('VS×ケイパビリティ関係'!$F$4:$F$370,$B20,'VS×ケイパビリティ関係'!$G$4:$G$370,D$5,'VS×ケイパビリティ関係'!$E$4:$E$370,"主")>0,"●",IF(COUNTIFS('VS×ケイパビリティ関係'!$F$4:$F$370,$B20,'VS×ケイパビリティ関係'!$G$4:$G$370,D$5,'VS×ケイパビリティ関係'!$E$4:$E$370,"支援")>0,"○","")) | E20: =IF(COUNTIFS('VS×ケイパビリティ関係'!$F$4:$F$370,$B20,'VS×ケイパビリティ関係'!$G$4:$G$370,E$5,'VS×ケイパビリティ関係'!$E$4:$E$370,"主")>0,"●",IF(COUNTIFS('VS×ケイパビリティ関係'!$F$4:$F$370,$B20,'VS×ケイパビリティ関係'!$G$4:$G$370,E$5,'VS×ケイパビリティ関係'!$E$4:$E$370,"支援")>0,"○","")) | F20: =IF(COUNTIFS('VS×ケイパビリティ関係'!$F$4:$F$370,$B20,'VS×ケイパビリティ関係'!$G$4:$G$370,F$5,'VS×ケイパビリティ関係'!$E$4:$E$370,"主")>0,"●",IF(COUNTIFS('VS×ケイパビリティ関係'!$F$4:$F$370,$B20,'VS×ケイパビリティ関係'!$G$4:$G$370,F$5,'VS×ケイパビリティ関係'!$E$4:$E$370,"支援")>0,"○","")) | G20: =IF(COUNTIFS('VS×ケイパビリティ関係'!$F$4:$F$370,$B20,'VS×ケイパビリティ関係'!$G$4:$G$370,G$5,'VS×ケイパビリティ関係'!$E$4:$E$370,"主")>0,"●",IF(COUNTIFS('VS×ケイパビリティ関係'!$F$4:$F$370,$B20,'VS×ケイパビリティ関係'!$G$4:$G$370,G$5,'VS×ケイパビリティ関係'!$E$4:$E$370,"支援")>0,"○","")) | H20: =IF(COUNTIFS('VS×ケイパビリティ関係'!$F$4:$F$370,$B20,'VS×ケイパビリティ関係'!$G$4:$G$370,H$5,'VS×ケイパビリティ関係'!$E$4:$E$370,"主")>0,"●",IF(COUNTIFS('VS×ケイパビリティ関係'!$F$4:$F$370,$B20,'VS×ケイパビリティ関係'!$G$4:$G$370,H$5,'VS×ケイパビリティ関係'!$E$4:$E$370,"支援")>0,"○","")) | I20: =IF(COUNTIFS('VS×ケイパビリティ関係'!$F$4:$F$370,$B20,'VS×ケイパビリティ関係'!$G$4:$G$370,I$5,'VS×ケイパビリティ関係'!$E$4:$E$370,"主")>0,"●",IF(COUNTIFS('VS×ケイパビリティ関係'!$F$4:$F$370,$B20,'VS×ケイパビリティ関係'!$G$4:$G$370,I$5,'VS×ケイパビリティ関係'!$E$4:$E$370,"支援")>0,"○","")) | J20: =IF(COUNTIFS('VS×ケイパビリティ関係'!$F$4:$F$370,$B20,'VS×ケイパビリティ関係'!$G$4:$G$370,J$5,'VS×ケイパビリティ関係'!$E$4:$E$370,"主")>0,"●",IF(COUNTIFS('VS×ケイパビリティ関係'!$F$4:$F$370,$B20,'VS×ケイパビリティ関係'!$G$4:$G$370,J$5,'VS×ケイパビリティ関係'!$E$4:$E$370,"支援")>0,"○","")) | K20: =IF(COUNTIFS('VS×ケイパビリティ関係'!$F$4:$F$370,$B20,'VS×ケイパビリティ関係'!$G$4:$G$370,K$5,'VS×ケイパビリティ関係'!$E$4:$E$370,"主")>0,"●",IF(COUNTIFS('VS×ケイパビリティ関係'!$F$4:$F$370,$B20,'VS×ケイパビリティ関係'!$G$4:$G$370,K$5,'VS×ケイパビリティ関係'!$E$4:$E$370,"支援")>0,"○","")) | ... AI20: =IF(COUNTIFS('VS×ケイパビリティ関係'!$F$4:$F$370,$B20,'VS×ケイパビリティ関係'!$G$4:$G$370,AI$5,'VS×ケイパビリティ関係'!$E$4:$E$370,"主")>0,"●",IF(COUNTIFS('VS×ケイパビリティ関係'!$F$4:$F$370,$B20,'VS×ケイパビリティ関係'!$G$4:$G$370,AI$5,'VS×ケイパビリティ関係'!$E$4:$E$370,"支援")>0,"○","")) | AJ20: =COUNTIF(D20:AI20,"●") | AK20: =COUNTIF(D20:AI20,"○")
B21: 04-04 | C21: 給与・社会保険・福利厚生 | D21: =IF(COUNTIFS('VS×ケイパビリティ関係'!$F$4:$F$370,$B21,'VS×ケイパビリティ関係'!$G$4:$G$370,D$5,'VS×ケイパビリティ関係'!$E$4:$E$370,"主")>0,"●",IF(COUNTIFS('VS×ケイパビリティ関係'!$F$4:$F$370,$B21,'VS×ケイパビリティ関係'!$G$4:$G$370,D$5,'VS×ケイパビリティ関係'!$E$4:$E$370,"支援")>0,"○","")) | E21: =IF(COUNTIFS('VS×ケイパビリティ関係'!$F$4:$F$370,$B21,'VS×ケイパビリティ関係'!$G$4:$G$370,E$5,'VS×ケイパビリティ関係'!$E$4:$E$370,"主")>0,"●",IF(COUNTIFS('VS×ケイパビリティ関係'!$F$4:$F$370,$B21,'VS×ケイパビリティ関係'!$G$4:$G$370,E$5,'VS×ケイパビリティ関係'!$E$4:$E$370,"支援")>0,"○","")) | F21: =IF(COUNTIFS('VS×ケイパビリティ関係'!$F$4:$F$370,$B21,'VS×ケイパビリティ関係'!$G$4:$G$370,F$5,'VS×ケイパビリティ関係'!$E$4:$E$370,"主")>0,"●",IF(COUNTIFS('VS×ケイパビリティ関係'!$F$4:$F$370,$B21,'VS×ケイパビリティ関係'!$G$4:$G$370,F$5,'VS×ケイパビリティ関係'!$E$4:$E$370,"支援")>0,"○","")) | G21: =IF(COUNTIFS('VS×ケイパビリティ関係'!$F$4:$F$370,$B21,'VS×ケイパビリティ関係'!$G$4:$G$370,G$5,'VS×ケイパビリティ関係'!$E$4:$E$370,"主")>0,"●",IF(COUNTIFS('VS×ケイパビリティ関係'!$F$4:$F$370,$B21,'VS×ケイパビリティ関係'!$G$4:$G$370,G$5,'VS×ケイパビリティ関係'!$E$4:$E$370,"支援")>0,"○","")) | H21: =IF(COUNTIFS('VS×ケイパビリティ関係'!$F$4:$F$370,$B21,'VS×ケイパビリティ関係'!$G$4:$G$370,H$5,'VS×ケイパビリティ関係'!$E$4:$E$370,"主")>0,"●",IF(COUNTIFS('VS×ケイパビリティ関係'!$F$4:$F$370,$B21,'VS×ケイパビリティ関係'!$G$4:$G$370,H$5,'VS×ケイパビリティ関係'!$E$4:$E$370,"支援")>0,"○","")) | I21: =IF(COUNTIFS('VS×ケイパビリティ関係'!$F$4:$F$370,$B21,'VS×ケイパビリティ関係'!$G$4:$G$370,I$5,'VS×ケイパビリティ関係'!$E$4:$E$370,"主")>0,"●",IF(COUNTIFS('VS×ケイパビリティ関係'!$F$4:$F$370,$B21,'VS×ケイパビリティ関係'!$G$4:$G$370,I$5,'VS×ケイパビリティ関係'!$E$4:$E$370,"支援")>0,"○","")) | J21: =IF(COUNTIFS('VS×ケイパビリティ関係'!$F$4:$F$370,$B21,'VS×ケイパビリティ関係'!$G$4:$G$370,J$5,'VS×ケイパビリティ関係'!$E$4:$E$370,"主")>0,"●",IF(COUNTIFS('VS×ケイパビリティ関係'!$F$4:$F$370,$B21,'VS×ケイパビリティ関係'!$G$4:$G$370,J$5,'VS×ケイパビリティ関係'!$E$4:$E$370,"支援")>0,"○","")) | K21: =IF(COUNTIFS('VS×ケイパビリティ関係'!$F$4:$F$370,$B21,'VS×ケイパビリティ関係'!$G$4:$G$370,K$5,'VS×ケイパビリティ関係'!$E$4:$E$370,"主")>0,"●",IF(COUNTIFS('VS×ケイパビリティ関係'!$F$4:$F$370,$B21,'VS×ケイパビリティ関係'!$G$4:$G$370,K$5,'VS×ケイパビリティ関係'!$E$4:$E$370,"支援")>0,"○","")) | ... AI21: =IF(COUNTIFS('VS×ケイパビリティ関係'!$F$4:$F$370,$B21,'VS×ケイパビリティ関係'!$G$4:$G$370,AI$5,'VS×ケイパビリティ関係'!$E$4:$E$370,"主")>0,"●",IF(COUNTIFS('VS×ケイパビリティ関係'!$F$4:$F$370,$B21,'VS×ケイパビリティ関係'!$G$4:$G$370,AI$5,'VS×ケイパビリティ関係'!$E$4:$E$370,"支援")>0,"○","")) | AJ21: =COUNTIF(D21:AI21,"●") | AK21: =COUNTIF(D21:AI21,"○")
B22: 04-05 | C22: 健康・安全・職場環境 | D22: =IF(COUNTIFS('VS×ケイパビリティ関係'!$F$4:$F$370,$B22,'VS×ケイパビリティ関係'!$G$4:$G$370,D$5,'VS×ケイパビリティ関係'!$E$4:$E$370,"主")>0,"●",IF(COUNTIFS('VS×ケイパビリティ関係'!$F$4:$F$370,$B22,'VS×ケイパビリティ関係'!$G$4:$G$370,D$5,'VS×ケイパビリティ関係'!$E$4:$E$370,"支援")>0,"○","")) | E22: =IF(COUNTIFS('VS×ケイパビリティ関係'!$F$4:$F$370,$B22,'VS×ケイパビリティ関係'!$G$4:$G$370,E$5,'VS×ケイパビリティ関係'!$E$4:$E$370,"主")>0,"●",IF(COUNTIFS('VS×ケイパビリティ関係'!$F$4:$F$370,$B22,'VS×ケイパビリティ関係'!$G$4:$G$370,E$5,'VS×ケイパビリティ関係'!$E$4:$E$370,"支援")>0,"○","")) | F22: =IF(COUNTIFS('VS×ケイパビリティ関係'!$F$4:$F$370,$B22,'VS×ケイパビリティ関係'!$G$4:$G$370,F$5,'VS×ケイパビリティ関係'!$E$4:$E$370,"主")>0,"●",IF(COUNTIFS('VS×ケイパビリティ関係'!$F$4:$F$370,$B22,'VS×ケイパビリティ関係'!$G$4:$G$370,F$5,'VS×ケイパビリティ関係'!$E$4:$E$370,"支援")>0,"○","")) | G22: =IF(COUNTIFS('VS×ケイパビリティ関係'!$F$4:$F$370,$B22,'VS×ケイパビリティ関係'!$G$4:$G$370,G$5,'VS×ケイパビリティ関係'!$E$4:$E$370,"主")>0,"●",IF(COUNTIFS('VS×ケイパビリティ関係'!$F$4:$F$370,$B22,'VS×ケイパビリティ関係'!$G$4:$G$370,G$5,'VS×ケイパビリティ関係'!$E$4:$E$370,"支援")>0,"○","")) | H22: =IF(COUNTIFS('VS×ケイパビリティ関係'!$F$4:$F$370,$B22,'VS×ケイパビリティ関係'!$G$4:$G$370,H$5,'VS×ケイパビリティ関係'!$E$4:$E$370,"主")>0,"●",IF(COUNTIFS('VS×ケイパビリティ関係'!$F$4:$F$370,$B22,'VS×ケイパビリティ関係'!$G$4:$G$370,H$5,'VS×ケイパビリティ関係'!$E$4:$E$370,"支援")>0,"○","")) | I22: =IF(COUNTIFS('VS×ケイパビリティ関係'!$F$4:$F$370,$B22,'VS×ケイパビリティ関係'!$G$4:$G$370,I$5,'VS×ケイパビリティ関係'!$E$4:$E$370,"主")>0,"●",IF(COUNTIFS('VS×ケイパビリティ関係'!$F$4:$F$370,$B22,'VS×ケイパビリティ関係'!$G$4:$G$370,I$5,'VS×ケイパビリティ関係'!$E$4:$E$370,"支援")>0,"○","")) | J22: =IF(COUNTIFS('VS×ケイパビリティ関係'!$F$4:$F$370,$B22,'VS×ケイパビリティ関係'!$G$4:$G$370,J$5,'VS×ケイパビリティ関係'!$E$4:$E$370,"主")>0,"●",IF(COUNTIFS('VS×ケイパビリティ関係'!$F$4:$F$370,$B22,'VS×ケイパビリティ関係'!$G$4:$G$370,J$5,'VS×ケイパビリティ関係'!$E$4:$E$370,"支援")>0,"○","")) | K22: =IF(COUNTIFS('VS×ケイパビリティ関係'!$F$4:$F$370,$B22,'VS×ケイパビリティ関係'!$G$4:$G$370,K$5,'VS×ケイパビリティ関係'!$E$4:$E$370,"主")>0,"●",IF(COUNTIFS('VS×ケイパビリティ関係'!$F$4:$F$370,$B22,'VS×ケイパビリティ関係'!$G$4:$G$370,K$5,'VS×ケイパビリティ関係'!$E$4:$E$370,"支援")>0,"○","")) | ... AI22: =IF(COUNTIFS('VS×ケイパビリティ関係'!$F$4:$F$370,$B22,'VS×ケイパビリティ関係'!$G$4:$G$370,AI$5,'VS×ケイパビリティ関係'!$E$4:$E$370,"主")>0,"●",IF(COUNTIFS('VS×ケイパビリティ関係'!$F$4:$F$370,$B22,'VS×ケイパビリティ関係'!$G$4:$G$370,AI$5,'VS×ケイパビリティ関係'!$E$4:$E$370,"支援")>0,"○","")) | AJ22: =COUNTIF(D22:AI22,"●") | AK22: =COUNTIF(D22:AI22,"○")
A23: 05 キャリア・配置 | B23: 05-01 | C23: タレントレビュー | D23: =IF(COUNTIFS('VS×ケイパビリティ関係'!$F$4:$F$370,$B23,'VS×ケイパビリティ関係'!$G$4:$G$370,D$5,'VS×ケイパビリティ関係'!$E$4:$E$370,"主")>0,"●",IF(COUNTIFS('VS×ケイパビリティ関係'!$F$4:$F$370,$B23,'VS×ケイパビリティ関係'!$G$4:$G$370,D$5,'VS×ケイパビリティ関係'!$E$4:$E$370,"支援")>0,"○","")) | E23: =IF(COUNTIFS('VS×ケイパビリティ関係'!$F$4:$F$370,$B23,'VS×ケイパビリティ関係'!$G$4:$G$370,E$5,'VS×ケイパビリティ関係'!$E$4:$E$370,"主")>0,"●",IF(COUNTIFS('VS×ケイパビリティ関係'!$F$4:$F$370,$B23,'VS×ケイパビリティ関係'!$G$4:$G$370,E$5,'VS×ケイパビリティ関係'!$E$4:$E$370,"支援")>0,"○","")) | F23: =IF(COUNTIFS('VS×ケイパビリティ関係'!$F$4:$F$370,$B23,'VS×ケイパビリティ関係'!$G$4:$G$370,F$5,'VS×ケイパビリティ関係'!$E$4:$E$370,"主")>0,"●",IF(COUNTIFS('VS×ケイパビリティ関係'!$F$4:$F$370,$B23,'VS×ケイパビリティ関係'!$G$4:$G$370,F$5,'VS×ケイパビリティ関係'!$E$4:$E$370,"支援")>0,"○","")) | G23: =IF(COUNTIFS('VS×ケイパビリティ関係'!$F$4:$F$370,$B23,'VS×ケイパビリティ関係'!$G$4:$G$370,G$5,'VS×ケイパビリティ関係'!$E$4:$E$370,"主")>0,"●",IF(COUNTIFS('VS×ケイパビリティ関係'!$F$4:$F$370,$B23,'VS×ケイパビリティ関係'!$G$4:$G$370,G$5,'VS×ケイパビリティ関係'!$E$4:$E$370,"支援")>0,"○","")) | H23: =IF(COUNTIFS('VS×ケイパビリティ関係'!$F$4:$F$370,$B23,'VS×ケイパビリティ関係'!$G$4:$G$370,H$5,'VS×ケイパビリティ関係'!$E$4:$E$370,"主")>0,"●",IF(COUNTIFS('VS×ケイパビリティ関係'!$F$4:$F$370,$B23,'VS×ケイパビリティ関係'!$G$4:$G$370,H$5,'VS×ケイパビリティ関係'!$E$4:$E$370,"支援")>0,"○","")) | I23: =IF(COUNTIFS('VS×ケイパビリティ関係'!$F$4:$F$370,$B23,'VS×ケイパビリティ関係'!$G$4:$G$370,I$5,'VS×ケイパビリティ関係'!$E$4:$E$370,"主")>0,"●",IF(COUNTIFS('VS×ケイパビリティ関係'!$F$4:$F$370,$B23,'VS×ケイパビリティ関係'!$G$4:$G$370,I$5,'VS×ケイパビリティ関係'!$E$4:$E$370,"支援")>0,"○","")) | J23: =IF(COUNTIFS('VS×ケイパビリティ関係'!$F$4:$F$370,$B23,'VS×ケイパビリティ関係'!$G$4:$G$370,J$5,'VS×ケイパビリティ関係'!$E$4:$E$370,"主")>0,"●",IF(COUNTIFS('VS×ケイパビリティ関係'!$F$4:$F$370,$B23,'VS×ケイパビリティ関係'!$G$4:$G$370,J$5,'VS×ケイパビリティ関係'!$E$4:$E$370,"支援")>0,"○","")) | K23: =IF(COUNTIFS('VS×ケイパビリティ関係'!$F$4:$F$370,$B23,'VS×ケイパビリティ関係'!$G$4:$G$370,K$5,'VS×ケイパビリティ関係'!$E$4:$E$370,"主")>0,"●",IF(COUNTIFS('VS×ケイパビリティ関係'!$F$4:$F$370,$B23,'VS×ケイパビリティ関係'!$G$4:$G$370,K$5,'VS×ケイパビリティ関係'!$E$4:$E$370,"支援")>0,"○","")) | ... AI23: =IF(COUNTIFS('VS×ケイパビリティ関係'!$F$4:$F$370,$B23,'VS×ケイパビリティ関係'!$G$4:$G$370,AI$5,'VS×ケイパビリティ関係'!$E$4:$E$370,"主")>0,"●",IF(COUNTIFS('VS×ケイパビリティ関係'!$F$4:$F$370,$B23,'VS×ケイパビリティ関係'!$G$4:$G$370,AI$5,'VS×ケイパビリティ関係'!$E$4:$E$370,"支援")>0,"○","")) | AJ23: =COUNTIF(D23:AI23,"●") | AK23: =COUNTIF(D23:AI23,"○")
B24: 05-02 | C24: 異動・配置 | D24: =IF(COUNTIFS('VS×ケイパビリティ関係'!$F$4:$F$370,$B24,'VS×ケイパビリティ関係'!$G$4:$G$370,D$5,'VS×ケイパビリティ関係'!$E$4:$E$370,"主")>0,"●",IF(COUNTIFS('VS×ケイパビリティ関係'!$F$4:$F$370,$B24,'VS×ケイパビリティ関係'!$G$4:$G$370,D$5,'VS×ケイパビリティ関係'!$E$4:$E$370,"支援")>0,"○","")) | E24: =IF(COUNTIFS('VS×ケイパビリティ関係'!$F$4:$F$370,$B24,'VS×ケイパビリティ関係'!$G$4:$G$370,E$5,'VS×ケイパビリティ関係'!$E$4:$E$370,"主")>0,"●",IF(COUNTIFS('VS×ケイパビリティ関係'!$F$4:$F$370,$B24,'VS×ケイパビリティ関係'!$G$4:$G$370,E$5,'VS×ケイパビリティ関係'!$E$4:$E$370,"支援")>0,"○","")) | F24: =IF(COUNTIFS('VS×ケイパビリティ関係'!$F$4:$F$370,$B24,'VS×ケイパビリティ関係'!$G$4:$G$370,F$5,'VS×ケイパビリティ関係'!$E$4:$E$370,"主")>0,"●",IF(COUNTIFS('VS×ケイパビリティ関係'!$F$4:$F$370,$B24,'VS×ケイパビリティ関係'!$G$4:$G$370,F$5,'VS×ケイパビリティ関係'!$E$4:$E$370,"支援")>0,"○","")) | G24: =IF(COUNTIFS('VS×ケイパビリティ関係'!$F$4:$F$370,$B24,'VS×ケイパビリティ関係'!$G$4:$G$370,G$5,'VS×ケイパビリティ関係'!$E$4:$E$370,"主")>0,"●",IF(COUNTIFS('VS×ケイパビリティ関係'!$F$4:$F$370,$B24,'VS×ケイパビリティ関係'!$G$4:$G$370,G$5,'VS×ケイパビリティ関係'!$E$4:$E$370,"支援")>0,"○","")) | H24: =IF(COUNTIFS('VS×ケイパビリティ関係'!$F$4:$F$370,$B24,'VS×ケイパビリティ関係'!$G$4:$G$370,H$5,'VS×ケイパビリティ関係'!$E$4:$E$370,"主")>0,"●",IF(COUNTIFS('VS×ケイパビリティ関係'!$F$4:$F$370,$B24,'VS×ケイパビリティ関係'!$G$4:$G$370,H$5,'VS×ケイパビリティ関係'!$E$4:$E$370,"支援")>0,"○","")) | I24: =IF(COUNTIFS('VS×ケイパビリティ関係'!$F$4:$F$370,$B24,'VS×ケイパビリティ関係'!$G$4:$G$370,I$5,'VS×ケイパビリティ関係'!$E$4:$E$370,"主")>0,"●",IF(COUNTIFS('VS×ケイパビリティ関係'!$F$4:$F$370,$B24,'VS×ケイパビリティ関係'!$G$4:$G$370,I$5,'VS×ケイパビリティ関係'!$E$4:$E$370,"支援")>0,"○","")) | J24: =IF(COUNTIFS('VS×ケイパビリティ関係'!$F$4:$F$370,$B24,'VS×ケイパビリティ関係'!$G$4:$G$370,J$5,'VS×ケイパビリティ関係'!$E$4:$E$370,"主")>0,"●",IF(COUNTIFS('VS×ケイパビリティ関係'!$F$4:$F$370,$B24,'VS×ケイパビリティ関係'!$G$4:$G$370,J$5,'VS×ケイパビリティ関係'!$E$4:$E$370,"支援")>0,"○","")) | K24: =IF(COUNTIFS('VS×ケイパビリティ関係'!$F$4:$F$370,$B24,'VS×ケイパビリティ関係'!$G$4:$G$370,K$5,'VS×ケイパビリティ関係'!$E$4:$E$370,"主")>0,"●",IF(COUNTIFS('VS×ケイパビリティ関係'!$F$4:$F$370,$B24,'VS×ケイパビリティ関係'!$G$4:$G$370,K$5,'VS×ケイパビリティ関係'!$E$4:$E$370,"支援")>0,"○","")) | ... AI24: =IF(COUNTIFS('VS×ケイパビリティ関係'!$F$4:$F$370,$B24,'VS×ケイパビリティ関係'!$G$4:$G$370,AI$5,'VS×ケイパビリティ関係'!$E$4:$E$370,"主")>0,"●",IF(COUNTIFS('VS×ケイパビリティ関係'!$F$4:$F$370,$B24,'VS×ケイパビリティ関係'!$G$4:$G$370,AI$5,'VS×ケイパビリティ関係'!$E$4:$E$370,"支援")>0,"○","")) | AJ24: =COUNTIF(D24:AI24,"●") | AK24: =COUNTIF(D24:AI24,"○")
B25: 05-03 | C25: 昇格・登用 | D25: =IF(COUNTIFS('VS×ケイパビリティ関係'!$F$4:$F$370,$B25,'VS×ケイパビリティ関係'!$G$4:$G$370,D$5,'VS×ケイパビリティ関係'!$E$4:$E$370,"主")>0,"●",IF(COUNTIFS('VS×ケイパビリティ関係'!$F$4:$F$370,$B25,'VS×ケイパビリティ関係'!$G$4:$G$370,D$5,'VS×ケイパビリティ関係'!$E$4:$E$370,"支援")>0,"○","")) | E25: =IF(COUNTIFS('VS×ケイパビリティ関係'!$F$4:$F$370,$B25,'VS×ケイパビリティ関係'!$G$4:$G$370,E$5,'VS×ケイパビリティ関係'!$E$4:$E$370,"主")>0,"●",IF(COUNTIFS('VS×ケイパビリティ関係'!$F$4:$F$370,$B25,'VS×ケイパビリティ関係'!$G$4:$G$370,E$5,'VS×ケイパビリティ関係'!$E$4:$E$370,"支援")>0,"○","")) | F25: =IF(COUNTIFS('VS×ケイパビリティ関係'!$F$4:$F$370,$B25,'VS×ケイパビリティ関係'!$G$4:$G$370,F$5,'VS×ケイパビリティ関係'!$E$4:$E$370,"主")>0,"●",IF(COUNTIFS('VS×ケイパビリティ関係'!$F$4:$F$370,$B25,'VS×ケイパビリティ関係'!$G$4:$G$370,F$5,'VS×ケイパビリティ関係'!$E$4:$E$370,"支援")>0,"○","")) | G25: =IF(COUNTIFS('VS×ケイパビリティ関係'!$F$4:$F$370,$B25,'VS×ケイパビリティ関係'!$G$4:$G$370,G$5,'VS×ケイパビリティ関係'!$E$4:$E$370,"主")>0,"●",IF(COUNTIFS('VS×ケイパビリティ関係'!$F$4:$F$370,$B25,'VS×ケイパビリティ関係'!$G$4:$G$370,G$5,'VS×ケイパビリティ関係'!$E$4:$E$370,"支援")>0,"○","")) | H25: =IF(COUNTIFS('VS×ケイパビリティ関係'!$F$4:$F$370,$B25,'VS×ケイパビリティ関係'!$G$4:$G$370,H$5,'VS×ケイパビリティ関係'!$E$4:$E$370,"主")>0,"●",IF(COUNTIFS('VS×ケイパビリティ関係'!$F$4:$F$370,$B25,'VS×ケイパビリティ関係'!$G$4:$G$370,H$5,'VS×ケイパビリティ関係'!$E$4:$E$370,"支援")>0,"○","")) | I25: =IF(COUNTIFS('VS×ケイパビリティ関係'!$F$4:$F$370,$B25,'VS×ケイパビリティ関係'!$G$4:$G$370,I$5,'VS×ケイパビリティ関係'!$E$4:$E$370,"主")>0,"●",IF(COUNTIFS('VS×ケイパビリティ関係'!$F$4:$F$370,$B25,'VS×ケイパビリティ関係'!$G$4:$G$370,I$5,'VS×ケイパビリティ関係'!$E$4:$E$370,"支援")>0,"○","")) | J25: =IF(COUNTIFS('VS×ケイパビリティ関係'!$F$4:$F$370,$B25,'VS×ケイパビリティ関係'!$G$4:$G$370,J$5,'VS×ケイパビリティ関係'!$E$4:$E$370,"主")>0,"●",IF(COUNTIFS('VS×ケイパビリティ関係'!$F$4:$F$370,$B25,'VS×ケイパビリティ関係'!$G$4:$G$370,J$5,'VS×ケイパビリティ関係'!$E$4:$E$370,"支援")>0,"○","")) | K25: =IF(COUNTIFS('VS×ケイパビリティ関係'!$F$4:$F$370,$B25,'VS×ケイパビリティ関係'!$G$4:$G$370,K$5,'VS×ケイパビリティ関係'!$E$4:$E$370,"主")>0,"●",IF(COUNTIFS('VS×ケイパビリティ関係'!$F$4:$F$370,$B25,'VS×ケイパビリティ関係'!$G$4:$G$370,K$5,'VS×ケイパビリティ関係'!$E$4:$E$370,"支援")>0,"○","")) | ... AI25: =IF(COUNTIFS('VS×ケイパビリティ関係'!$F$4:$F$370,$B25,'VS×ケイパビリティ関係'!$G$4:$G$370,AI$5,'VS×ケイパビリティ関係'!$E$4:$E$370,"主")>0,"●",IF(COUNTIFS('VS×ケイパビリティ関係'!$F$4:$F$370,$B25,'VS×ケイパビリティ関係'!$G$4:$G$370,AI$5,'VS×ケイパビリティ関係'!$E$4:$E$370,"支援")>0,"○","")) | AJ25: =COUNTIF(D25:AI25,"●") | AK25: =COUNTIF(D25:AI25,"○")
B26: 05-04 | C26: 後継者・リーダー育成 | D26: =IF(COUNTIFS('VS×ケイパビリティ関係'!$F$4:$F$370,$B26,'VS×ケイパビリティ関係'!$G$4:$G$370,D$5,'VS×ケイパビリティ関係'!$E$4:$E$370,"主")>0,"●",IF(COUNTIFS('VS×ケイパビリティ関係'!$F$4:$F$370,$B26,'VS×ケイパビリティ関係'!$G$4:$G$370,D$5,'VS×ケイパビリティ関係'!$E$4:$E$370,"支援")>0,"○","")) | E26: =IF(COUNTIFS('VS×ケイパビリティ関係'!$F$4:$F$370,$B26,'VS×ケイパビリティ関係'!$G$4:$G$370,E$5,'VS×ケイパビリティ関係'!$E$4:$E$370,"主")>0,"●",IF(COUNTIFS('VS×ケイパビリティ関係'!$F$4:$F$370,$B26,'VS×ケイパビリティ関係'!$G$4:$G$370,E$5,'VS×ケイパビリティ関係'!$E$4:$E$370,"支援")>0,"○","")) | F26: =IF(COUNTIFS('VS×ケイパビリティ関係'!$F$4:$F$370,$B26,'VS×ケイパビリティ関係'!$G$4:$G$370,F$5,'VS×ケイパビリティ関係'!$E$4:$E$370,"主")>0,"●",IF(COUNTIFS('VS×ケイパビリティ関係'!$F$4:$F$370,$B26,'VS×ケイパビリティ関係'!$G$4:$G$370,F$5,'VS×ケイパビリティ関係'!$E$4:$E$370,"支援")>0,"○","")) | G26: =IF(COUNTIFS('VS×ケイパビリティ関係'!$F$4:$F$370,$B26,'VS×ケイパビリティ関係'!$G$4:$G$370,G$5,'VS×ケイパビリティ関係'!$E$4:$E$370,"主")>0,"●",IF(COUNTIFS('VS×ケイパビリティ関係'!$F$4:$F$370,$B26,'VS×ケイパビリティ関係'!$G$4:$G$370,G$5,'VS×ケイパビリティ関係'!$E$4:$E$370,"支援")>0,"○","")) | H26: =IF(COUNTIFS('VS×ケイパビリティ関係'!$F$4:$F$370,$B26,'VS×ケイパビリティ関係'!$G$4:$G$370,H$5,'VS×ケイパビリティ関係'!$E$4:$E$370,"主")>0,"●",IF(COUNTIFS('VS×ケイパビリティ関係'!$F$4:$F$370,$B26,'VS×ケイパビリティ関係'!$G$4:$G$370,H$5,'VS×ケイパビリティ関係'!$E$4:$E$370,"支援")>0,"○","")) | I26: =IF(COUNTIFS('VS×ケイパビリティ関係'!$F$4:$F$370,$B26,'VS×ケイパビリティ関係'!$G$4:$G$370,I$5,'VS×ケイパビリティ関係'!$E$4:$E$370,"主")>0,"●",IF(COUNTIFS('VS×ケイパビリティ関係'!$F$4:$F$370,$B26,'VS×ケイパビリティ関係'!$G$4:$G$370,I$5,'VS×ケイパビリティ関係'!$E$4:$E$370,"支援")>0,"○","")) | J26: =IF(COUNTIFS('VS×ケイパビリティ関係'!$F$4:$F$370,$B26,'VS×ケイパビリティ関係'!$G$4:$G$370,J$5,'VS×ケイパビリティ関係'!$E$4:$E$370,"主")>0,"●",IF(COUNTIFS('VS×ケイパビリティ関係'!$F$4:$F$370,$B26,'VS×ケイパビリティ関係'!$G$4:$G$370,J$5,'VS×ケイパビリティ関係'!$E$4:$E$370,"支援")>0,"○","")) | K26: =IF(COUNTIFS('VS×ケイパビリティ関係'!$F$4:$F$370,$B26,'VS×ケイパビリティ関係'!$G$4:$G$370,K$5,'VS×ケイパビリティ関係'!$E$4:$E$370,"主")>0,"●",IF(COUNTIFS('VS×ケイパビリティ関係'!$F$4:$F$370,$B26,'VS×ケイパビリティ関係'!$G$4:$G$370,K$5,'VS×ケイパビリティ関係'!$E$4:$E$370,"支援")>0,"○","")) | ... AI26: =IF(COUNTIFS('VS×ケイパビリティ関係'!$F$4:$F$370,$B26,'VS×ケイパビリティ関係'!$G$4:$G$370,AI$5,'VS×ケイパビリティ関係'!$E$4:$E$370,"主")>0,"●",IF(COUNTIFS('VS×ケイパビリティ関係'!$F$4:$F$370,$B26,'VS×ケイパビリティ関係'!$G$4:$G$370,AI$5,'VS×ケイパビリティ関係'!$E$4:$E$370,"支援")>0,"○","")) | AJ26: =COUNTIF(D26:AI26,"●") | AK26: =COUNTIF(D26:AI26,"○")
B27: 05-05 | C27: 多様な人材の活躍 | D27: =IF(COUNTIFS('VS×ケイパビリティ関係'!$F$4:$F$370,$B27,'VS×ケイパビリティ関係'!$G$4:$G$370,D$5,'VS×ケイパビリティ関係'!$E$4:$E$370,"主")>0,"●",IF(COUNTIFS('VS×ケイパビリティ関係'!$F$4:$F$370,$B27,'VS×ケイパビリティ関係'!$G$4:$G$370,D$5,'VS×ケイパビリティ関係'!$E$4:$E$370,"支援")>0,"○","")) | E27: =IF(COUNTIFS('VS×ケイパビリティ関係'!$F$4:$F$370,$B27,'VS×ケイパビリティ関係'!$G$4:$G$370,E$5,'VS×ケイパビリティ関係'!$E$4:$E$370,"主")>0,"●",IF(COUNTIFS('VS×ケイパビリティ関係'!$F$4:$F$370,$B27,'VS×ケイパビリティ関係'!$G$4:$G$370,E$5,'VS×ケイパビリティ関係'!$E$4:$E$370,"支援")>0,"○","")) | F27: =IF(COUNTIFS('VS×ケイパビリティ関係'!$F$4:$F$370,$B27,'VS×ケイパビリティ関係'!$G$4:$G$370,F$5,'VS×ケイパビリティ関係'!$E$4:$E$370,"主")>0,"●",IF(COUNTIFS('VS×ケイパビリティ関係'!$F$4:$F$370,$B27,'VS×ケイパビリティ関係'!$G$4:$G$370,F$5,'VS×ケイパビリティ関係'!$E$4:$E$370,"支援")>0,"○","")) | G27: =IF(COUNTIFS('VS×ケイパビリティ関係'!$F$4:$F$370,$B27,'VS×ケイパビリティ関係'!$G$4:$G$370,G$5,'VS×ケイパビリティ関係'!$E$4:$E$370,"主")>0,"●",IF(COUNTIFS('VS×ケイパビリティ関係'!$F$4:$F$370,$B27,'VS×ケイパビリティ関係'!$G$4:$G$370,G$5,'VS×ケイパビリティ関係'!$E$4:$E$370,"支援")>0,"○","")) | H27: =IF(COUNTIFS('VS×ケイパビリティ関係'!$F$4:$F$370,$B27,'VS×ケイパビリティ関係'!$G$4:$G$370,H$5,'VS×ケイパビリティ関係'!$E$4:$E$370,"主")>0,"●",IF(COUNTIFS('VS×ケイパビリティ関係'!$F$4:$F$370,$B27,'VS×ケイパビリティ関係'!$G$4:$G$370,H$5,'VS×ケイパビリティ関係'!$E$4:$E$370,"支援")>0,"○","")) | I27: =IF(COUNTIFS('VS×ケイパビリティ関係'!$F$4:$F$370,$B27,'VS×ケイパビリティ関係'!$G$4:$G$370,I$5,'VS×ケイパビリティ関係'!$E$4:$E$370,"主")>0,"●",IF(COUNTIFS('VS×ケイパビリティ関係'!$F$4:$F$370,$B27,'VS×ケイパビリティ関係'!$G$4:$G$370,I$5,'VS×ケイパビリティ関係'!$E$4:$E$370,"支援")>0,"○","")) | J27: =IF(COUNTIFS('VS×ケイパビリティ関係'!$F$4:$F$370,$B27,'VS×ケイパビリティ関係'!$G$4:$G$370,J$5,'VS×ケイパビリティ関係'!$E$4:$E$370,"主")>0,"●",IF(COUNTIFS('VS×ケイパビリティ関係'!$F$4:$F$370,$B27,'VS×ケイパビリティ関係'!$G$4:$G$370,J$5,'VS×ケイパビリティ関係'!$E$4:$E$370,"支援")>0,"○","")) | K27: =IF(COUNTIFS('VS×ケイパビリティ関係'!$F$4:$F$370,$B27,'VS×ケイパビリティ関係'!$G$4:$G$370,K$5,'VS×ケイパビリティ関係'!$E$4:$E$370,"主")>0,"●",IF(COUNTIFS('VS×ケイパビリティ関係'!$F$4:$F$370,$B27,'VS×ケイパビリティ関係'!$G$4:$G$370,K$5,'VS×ケイパビリティ関係'!$E$4:$E$370,"支援")>0,"○","")) | ... AI27: =IF(COUNTIFS('VS×ケイパビリティ関係'!$F$4:$F$370,$B27,'VS×ケイパビリティ関係'!$G$4:$G$370,AI$5,'VS×ケイパビリティ関係'!$E$4:$E$370,"主")>0,"●",IF(COUNTIFS('VS×ケイパビリティ関係'!$F$4:$F$370,$B27,'VS×ケイパビリティ関係'!$G$4:$G$370,AI$5,'VS×ケイパビリティ関係'!$E$4:$E$370,"支援")>0,"○","")) | AJ27: =COUNTIF(D27:AI27,"●") | AK27: =COUNTIF(D27:AI27,"○")
A28: 06 退職・オフボーディング | B28: 06-01 | C28: 退職の受付 | D28: =IF(COUNTIFS('VS×ケイパビリティ関係'!$F$4:$F$370,$B28,'VS×ケイパビリティ関係'!$G$4:$G$370,D$5,'VS×ケイパビリティ関係'!$E$4:$E$370,"主")>0,"●",IF(COUNTIFS('VS×ケイパビリティ関係'!$F$4:$F$370,$B28,'VS×ケイパビリティ関係'!$G$4:$G$370,D$5,'VS×ケイパビリティ関係'!$E$4:$E$370,"支援")>0,"○","")) | E28: =IF(COUNTIFS('VS×ケイパビリティ関係'!$F$4:$F$370,$B28,'VS×ケイパビリティ関係'!$G$4:$G$370,E$5,'VS×ケイパビリティ関係'!$E$4:$E$370,"主")>0,"●",IF(COUNTIFS('VS×ケイパビリティ関係'!$F$4:$F$370,$B28,'VS×ケイパビリティ関係'!$G$4:$G$370,E$5,'VS×ケイパビリティ関係'!$E$4:$E$370,"支援")>0,"○","")) | F28: =IF(COUNTIFS('VS×ケイパビリティ関係'!$F$4:$F$370,$B28,'VS×ケイパビリティ関係'!$G$4:$G$370,F$5,'VS×ケイパビリティ関係'!$E$4:$E$370,"主")>0,"●",IF(COUNTIFS('VS×ケイパビリティ関係'!$F$4:$F$370,$B28,'VS×ケイパビリティ関係'!$G$4:$G$370,F$5,'VS×ケイパビリティ関係'!$E$4:$E$370,"支援")>0,"○","")) | G28: =IF(COUNTIFS('VS×ケイパビリティ関係'!$F$4:$F$370,$B28,'VS×ケイパビリティ関係'!$G$4:$G$370,G$5,'VS×ケイパビリティ関係'!$E$4:$E$370,"主")>0,"●",IF(COUNTIFS('VS×ケイパビリティ関係'!$F$4:$F$370,$B28,'VS×ケイパビリティ関係'!$G$4:$G$370,G$5,'VS×ケイパビリティ関係'!$E$4:$E$370,"支援")>0,"○","")) | H28: =IF(COUNTIFS('VS×ケイパビリティ関係'!$F$4:$F$370,$B28,'VS×ケイパビリティ関係'!$G$4:$G$370,H$5,'VS×ケイパビリティ関係'!$E$4:$E$370,"主")>0,"●",IF(COUNTIFS('VS×ケイパビリティ関係'!$F$4:$F$370,$B28,'VS×ケイパビリティ関係'!$G$4:$G$370,H$5,'VS×ケイパビリティ関係'!$E$4:$E$370,"支援")>0,"○","")) | I28: =IF(COUNTIFS('VS×ケイパビリティ関係'!$F$4:$F$370,$B28,'VS×ケイパビリティ関係'!$G$4:$G$370,I$5,'VS×ケイパビリティ関係'!$E$4:$E$370,"主")>0,"●",IF(COUNTIFS('VS×ケイパビリティ関係'!$F$4:$F$370,$B28,'VS×ケイパビリティ関係'!$G$4:$G$370,I$5,'VS×ケイパビリティ関係'!$E$4:$E$370,"支援")>0,"○","")) | J28: =IF(COUNTIFS('VS×ケイパビリティ関係'!$F$4:$F$370,$B28,'VS×ケイパビリティ関係'!$G$4:$G$370,J$5,'VS×ケイパビリティ関係'!$E$4:$E$370,"主")>0,"●",IF(COUNTIFS('VS×ケイパビリティ関係'!$F$4:$F$370,$B28,'VS×ケイパビリティ関係'!$G$4:$G$370,J$5,'VS×ケイパビリティ関係'!$E$4:$E$370,"支援")>0,"○","")) | K28: =IF(COUNTIFS('VS×ケイパビリティ関係'!$F$4:$F$370,$B28,'VS×ケイパビリティ関係'!$G$4:$G$370,K$5,'VS×ケイパビリティ関係'!$E$4:$E$370,"主")>0,"●",IF(COUNTIFS('VS×ケイパビリティ関係'!$F$4:$F$370,$B28,'VS×ケイパビリティ関係'!$G$4:$G$370,K$5,'VS×ケイパビリティ関係'!$E$4:$E$370,"支援")>0,"○","")) | ... AI28: =IF(COUNTIFS('VS×ケイパビリティ関係'!$F$4:$F$370,$B28,'VS×ケイパビリティ関係'!$G$4:$G$370,AI$5,'VS×ケイパビリティ関係'!$E$4:$E$370,"主")>0,"●",IF(COUNTIFS('VS×ケイパビリティ関係'!$F$4:$F$370,$B28,'VS×ケイパビリティ関係'!$G$4:$G$370,AI$5,'VS×ケイパビリティ関係'!$E$4:$E$370,"支援")>0,"○","")) | AJ28: =COUNTIF(D28:AI28,"●") | AK28: =COUNTIF(D28:AI28,"○")
B29: 06-02 | C29: 定年・再雇用 | D29: =IF(COUNTIFS('VS×ケイパビリティ関係'!$F$4:$F$370,$B29,'VS×ケイパビリティ関係'!$G$4:$G$370,D$5,'VS×ケイパビリティ関係'!$E$4:$E$370,"主")>0,"●",IF(COUNTIFS('VS×ケイパビリティ関係'!$F$4:$F$370,$B29,'VS×ケイパビリティ関係'!$G$4:$G$370,D$5,'VS×ケイパビリティ関係'!$E$4:$E$370,"支援")>0,"○","")) | E29: =IF(COUNTIFS('VS×ケイパビリティ関係'!$F$4:$F$370,$B29,'VS×ケイパビリティ関係'!$G$4:$G$370,E$5,'VS×ケイパビリティ関係'!$E$4:$E$370,"主")>0,"●",IF(COUNTIFS('VS×ケイパビリティ関係'!$F$4:$F$370,$B29,'VS×ケイパビリティ関係'!$G$4:$G$370,E$5,'VS×ケイパビリティ関係'!$E$4:$E$370,"支援")>0,"○","")) | F29: =IF(COUNTIFS('VS×ケイパビリティ関係'!$F$4:$F$370,$B29,'VS×ケイパビリティ関係'!$G$4:$G$370,F$5,'VS×ケイパビリティ関係'!$E$4:$E$370,"主")>0,"●",IF(COUNTIFS('VS×ケイパビリティ関係'!$F$4:$F$370,$B29,'VS×ケイパビリティ関係'!$G$4:$G$370,F$5,'VS×ケイパビリティ関係'!$E$4:$E$370,"支援")>0,"○","")) | G29: =IF(COUNTIFS('VS×ケイパビリティ関係'!$F$4:$F$370,$B29,'VS×ケイパビリティ関係'!$G$4:$G$370,G$5,'VS×ケイパビリティ関係'!$E$4:$E$370,"主")>0,"●",IF(COUNTIFS('VS×ケイパビリティ関係'!$F$4:$F$370,$B29,'VS×ケイパビリティ関係'!$G$4:$G$370,G$5,'VS×ケイパビリティ関係'!$E$4:$E$370,"支援")>0,"○","")) | H29: =IF(COUNTIFS('VS×ケイパビリティ関係'!$F$4:$F$370,$B29,'VS×ケイパビリティ関係'!$G$4:$G$370,H$5,'VS×ケイパビリティ関係'!$E$4:$E$370,"主")>0,"●",IF(COUNTIFS('VS×ケイパビリティ関係'!$F$4:$F$370,$B29,'VS×ケイパビリティ関係'!$G$4:$G$370,H$5,'VS×ケイパビリティ関係'!$E$4:$E$370,"支援")>0,"○","")) | I29: =IF(COUNTIFS('VS×ケイパビリティ関係'!$F$4:$F$370,$B29,'VS×ケイパビリティ関係'!$G$4:$G$370,I$5,'VS×ケイパビリティ関係'!$E$4:$E$370,"主")>0,"●",IF(COUNTIFS('VS×ケイパビリティ関係'!$F$4:$F$370,$B29,'VS×ケイパビリティ関係'!$G$4:$G$370,I$5,'VS×ケイパビリティ関係'!$E$4:$E$370,"支援")>0,"○","")) | J29: =IF(COUNTIFS('VS×ケイパビリティ関係'!$F$4:$F$370,$B29,'VS×ケイパビリティ関係'!$G$4:$G$370,J$5,'VS×ケイパビリティ関係'!$E$4:$E$370,"主")>0,"●",IF(COUNTIFS('VS×ケイパビリティ関係'!$F$4:$F$370,$B29,'VS×ケイパビリティ関係'!$G$4:$G$370,J$5,'VS×ケイパビリティ関係'!$E$4:$E$370,"支援")>0,"○","")) | K29: =IF(COUNTIFS('VS×ケイパビリティ関係'!$F$4:$F$370,$B29,'VS×ケイパビリティ関係'!$G$4:$G$370,K$5,'VS×ケイパビリティ関係'!$E$4:$E$370,"主")>0,"●",IF(COUNTIFS('VS×ケイパビリティ関係'!$F$4:$F$370,$B29,'VS×ケイパビリティ関係'!$G$4:$G$370,K$5,'VS×ケイパビリティ関係'!$E$4:$E$370,"支援")>0,"○","")) | ... AI29: =IF(COUNTIFS('VS×ケイパビリティ関係'!$F$4:$F$370,$B29,'VS×ケイパビリティ関係'!$G$4:$G$370,AI$5,'VS×ケイパビリティ関係'!$E$4:$E$370,"主")>0,"●",IF(COUNTIFS('VS×ケイパビリティ関係'!$F$4:$F$370,$B29,'VS×ケイパビリティ関係'!$G$4:$G$370,AI$5,'VS×ケイパビリティ関係'!$E$4:$E$370,"支援")>0,"○","")) | AJ29: =COUNTIF(D29:AI29,"●") | AK29: =COUNTIF(D29:AI29,"○")
B30: 06-03 | C30: 退職手続き | D30: =IF(COUNTIFS('VS×ケイパビリティ関係'!$F$4:$F$370,$B30,'VS×ケイパビリティ関係'!$G$4:$G$370,D$5,'VS×ケイパビリティ関係'!$E$4:$E$370,"主")>0,"●",IF(COUNTIFS('VS×ケイパビリティ関係'!$F$4:$F$370,$B30,'VS×ケイパビリティ関係'!$G$4:$G$370,D$5,'VS×ケイパビリティ関係'!$E$4:$E$370,"支援")>0,"○","")) | E30: =IF(COUNTIFS('VS×ケイパビリティ関係'!$F$4:$F$370,$B30,'VS×ケイパビリティ関係'!$G$4:$G$370,E$5,'VS×ケイパビリティ関係'!$E$4:$E$370,"主")>0,"●",IF(COUNTIFS('VS×ケイパビリティ関係'!$F$4:$F$370,$B30,'VS×ケイパビリティ関係'!$G$4:$G$370,E$5,'VS×ケイパビリティ関係'!$E$4:$E$370,"支援")>0,"○","")) | F30: =IF(COUNTIFS('VS×ケイパビリティ関係'!$F$4:$F$370,$B30,'VS×ケイパビリティ関係'!$G$4:$G$370,F$5,'VS×ケイパビリティ関係'!$E$4:$E$370,"主")>0,"●",IF(COUNTIFS('VS×ケイパビリティ関係'!$F$4:$F$370,$B30,'VS×ケイパビリティ関係'!$G$4:$G$370,F$5,'VS×ケイパビリティ関係'!$E$4:$E$370,"支援")>0,"○","")) | G30: =IF(COUNTIFS('VS×ケイパビリティ関係'!$F$4:$F$370,$B30,'VS×ケイパビリティ関係'!$G$4:$G$370,G$5,'VS×ケイパビリティ関係'!$E$4:$E$370,"主")>0,"●",IF(COUNTIFS('VS×ケイパビリティ関係'!$F$4:$F$370,$B30,'VS×ケイパビリティ関係'!$G$4:$G$370,G$5,'VS×ケイパビリティ関係'!$E$4:$E$370,"支援")>0,"○","")) | H30: =IF(COUNTIFS('VS×ケイパビリティ関係'!$F$4:$F$370,$B30,'VS×ケイパビリティ関係'!$G$4:$G$370,H$5,'VS×ケイパビリティ関係'!$E$4:$E$370,"主")>0,"●",IF(COUNTIFS('VS×ケイパビリティ関係'!$F$4:$F$370,$B30,'VS×ケイパビリティ関係'!$G$4:$G$370,H$5,'VS×ケイパビリティ関係'!$E$4:$E$370,"支援")>0,"○","")) | I30: =IF(COUNTIFS('VS×ケイパビリティ関係'!$F$4:$F$370,$B30,'VS×ケイパビリティ関係'!$G$4:$G$370,I$5,'VS×ケイパビリティ関係'!$E$4:$E$370,"主")>0,"●",IF(COUNTIFS('VS×ケイパビリティ関係'!$F$4:$F$370,$B30,'VS×ケイパビリティ関係'!$G$4:$G$370,I$5,'VS×ケイパビリティ関係'!$E$4:$E$370,"支援")>0,"○","")) | J30: =IF(COUNTIFS('VS×ケイパビリティ関係'!$F$4:$F$370,$B30,'VS×ケイパビリティ関係'!$G$4:$G$370,J$5,'VS×ケイパビリティ関係'!$E$4:$E$370,"主")>0,"●",IF(COUNTIFS('VS×ケイパビリティ関係'!$F$4:$F$370,$B30,'VS×ケイパビリティ関係'!$G$4:$G$370,J$5,'VS×ケイパビリティ関係'!$E$4:$E$370,"支援")>0,"○","")) | K30: =IF(COUNTIFS('VS×ケイパビリティ関係'!$F$4:$F$370,$B30,'VS×ケイパビリティ関係'!$G$4:$G$370,K$5,'VS×ケイパビリティ関係'!$E$4:$E$370,"主")>0,"●",IF(COUNTIFS('VS×ケイパビリティ関係'!$F$4:$F$370,$B30,'VS×ケイパビリティ関係'!$G$4:$G$370,K$5,'VS×ケイパビリティ関係'!$E$4:$E$370,"支援")>0,"○","")) | ... AI30: =IF(COUNTIFS('VS×ケイパビリティ関係'!$F$4:$F$370,$B30,'VS×ケイパビリティ関係'!$G$4:$G$370,AI$5,'VS×ケイパビリティ関係'!$E$4:$E$370,"主")>0,"●",IF(COUNTIFS('VS×ケイパビリティ関係'!$F$4:$F$370,$B30,'VS×ケイパビリティ関係'!$G$4:$G$370,AI$5,'VS×ケイパビリティ関係'!$E$4:$E$370,"支援")>0,"○","")) | AJ30: =COUNTIF(D30:AI30,"●") | AK30: =COUNTIF(D30:AI30,"○")
B31: 06-04 | C31: オフボーディング | D31: =IF(COUNTIFS('VS×ケイパビリティ関係'!$F$4:$F$370,$B31,'VS×ケイパビリティ関係'!$G$4:$G$370,D$5,'VS×ケイパビリティ関係'!$E$4:$E$370,"主")>0,"●",IF(COUNTIFS('VS×ケイパビリティ関係'!$F$4:$F$370,$B31,'VS×ケイパビリティ関係'!$G$4:$G$370,D$5,'VS×ケイパビリティ関係'!$E$4:$E$370,"支援")>0,"○","")) | E31: =IF(COUNTIFS('VS×ケイパビリティ関係'!$F$4:$F$370,$B31,'VS×ケイパビリティ関係'!$G$4:$G$370,E$5,'VS×ケイパビリティ関係'!$E$4:$E$370,"主")>0,"●",IF(COUNTIFS('VS×ケイパビリティ関係'!$F$4:$F$370,$B31,'VS×ケイパビリティ関係'!$G$4:$G$370,E$5,'VS×ケイパビリティ関係'!$E$4:$E$370,"支援")>0,"○","")) | F31: =IF(COUNTIFS('VS×ケイパビリティ関係'!$F$4:$F$370,$B31,'VS×ケイパビリティ関係'!$G$4:$G$370,F$5,'VS×ケイパビリティ関係'!$E$4:$E$370,"主")>0,"●",IF(COUNTIFS('VS×ケイパビリティ関係'!$F$4:$F$370,$B31,'VS×ケイパビリティ関係'!$G$4:$G$370,F$5,'VS×ケイパビリティ関係'!$E$4:$E$370,"支援")>0,"○","")) | G31: =IF(COUNTIFS('VS×ケイパビリティ関係'!$F$4:$F$370,$B31,'VS×ケイパビリティ関係'!$G$4:$G$370,G$5,'VS×ケイパビリティ関係'!$E$4:$E$370,"主")>0,"●",IF(COUNTIFS('VS×ケイパビリティ関係'!$F$4:$F$370,$B31,'VS×ケイパビリティ関係'!$G$4:$G$370,G$5,'VS×ケイパビリティ関係'!$E$4:$E$370,"支援")>0,"○","")) | H31: =IF(COUNTIFS('VS×ケイパビリティ関係'!$F$4:$F$370,$B31,'VS×ケイパビリティ関係'!$G$4:$G$370,H$5,'VS×ケイパビリティ関係'!$E$4:$E$370,"主")>0,"●",IF(COUNTIFS('VS×ケイパビリティ関係'!$F$4:$F$370,$B31,'VS×ケイパビリティ関係'!$G$4:$G$370,H$5,'VS×ケイパビリティ関係'!$E$4:$E$370,"支援")>0,"○","")) | I31: =IF(COUNTIFS('VS×ケイパビリティ関係'!$F$4:$F$370,$B31,'VS×ケイパビリティ関係'!$G$4:$G$370,I$5,'VS×ケイパビリティ関係'!$E$4:$E$370,"主")>0,"●",IF(COUNTIFS('VS×ケイパビリティ関係'!$F$4:$F$370,$B31,'VS×ケイパビリティ関係'!$G$4:$G$370,I$5,'VS×ケイパビリティ関係'!$E$4:$E$370,"支援")>0,"○","")) | J31: =IF(COUNTIFS('VS×ケイパビリティ関係'!$F$4:$F$370,$B31,'VS×ケイパビリティ関係'!$G$4:$G$370,J$5,'VS×ケイパビリティ関係'!$E$4:$E$370,"主")>0,"●",IF(COUNTIFS('VS×ケイパビリティ関係'!$F$4:$F$370,$B31,'VS×ケイパビリティ関係'!$G$4:$G$370,J$5,'VS×ケイパビリティ関係'!$E$4:$E$370,"支援")>0,"○","")) | K31: =IF(COUNTIFS('VS×ケイパビリティ関係'!$F$4:$F$370,$B31,'VS×ケイパビリティ関係'!$G$4:$G$370,K$5,'VS×ケイパビリティ関係'!$E$4:$E$370,"主")>0,"●",IF(COUNTIFS('VS×ケイパビリティ関係'!$F$4:$F$370,$B31,'VS×ケイパビリティ関係'!$G$4:$G$370,K$5,'VS×ケイパビリティ関係'!$E$4:$E$370,"支援")>0,"○","")) | ... AI31: =IF(COUNTIFS('VS×ケイパビリティ関係'!$F$4:$F$370,$B31,'VS×ケイパビリティ関係'!$G$4:$G$370,AI$5,'VS×ケイパビリティ関係'!$E$4:$E$370,"主")>0,"●",IF(COUNTIFS('VS×ケイパビリティ関係'!$F$4:$F$370,$B31,'VS×ケイパビリティ関係'!$G$4:$G$370,AI$5,'VS×ケイパビリティ関係'!$E$4:$E$370,"支援")>0,"○","")) | AJ31: =COUNTIF(D31:AI31,"●") | AK31: =COUNTIF(D31:AI31,"○")

Sheet 情報オブジェクト
A1: 情報オブジェクト（正本：用語集と分類）
A2: 1行1オブジェクト。業務上ひとまとまりで管理される情報の単位（状態の違いは属性として扱う）。名称・分類・オーナーはこのシートで編集する。灰色の列は数式（編集しない）。個人情報の区分：要配慮個人情報（健康・休業事由など）、特定個人情報（マイナンバー）は取扱いを特に厳格にする。
A3: ID | B3: 領域 | C3: 情報オブジェクト | D3: 英語名 | E3: 説明 | F3: データ種別 | G3: 関連法令 | H3: 法定保存・届出 の対象 | I3: 個人情報 | J3: オーナー ケイパビリティL2 ID | K3: オーナー ケイパビリティL2 | L3: 作成する ケイパビリティL2の数 | M3: 利用する ケイパビリティL2の数
A4: ORG-01 | B4: 共通・組織 | C4: 組織マスタ | D4: Organization Master | E4: 組織コード・組織名・階層・責任者。組織改編の履歴を含む | F4: マスタ | G4: なし | H4: =IF(G4="なし","—","対象候補") | I4: なし | J4: C01-03 | K4: =IFERROR(INDEX(ケイパビリティマップ!$E:$E,MATCH(J4,ケイパビリティマップ!$A:$A,0)),"（IDなし）") | L4: =COUNTIF('ケイパビリティ×情報オブジェクト'!D$6:D$37,"C") | M4: =COUNTIF('ケイパビリティ×情報オブジェクト'!D$6:D$37,"R")
A5: ORG-02 | B5: 共通・組織 | C5: 職務・ポジション | D5: Job & Position | E5: 職務記述書（役割・責任・要件）とポジション（定員・空席） | F5: 定義・仕様 | G5: なし | H5: =IF(G5="なし","—","対象候補") | I5: なし | J5: C01-03 | K5: =IFERROR(INDEX(ケイパビリティマップ!$E:$E,MATCH(J5,ケイパビリティマップ!$A:$A,0)),"（IDなし）") | L5: =COUNTIF('ケイパビリティ×情報オブジェクト'!E$6:E$37,"C") | M5: =COUNTIF('ケイパビリティ×情報オブジェクト'!E$6:E$37,"R")
A6: ORG-03 | B6: 共通・組織 | C6: 等級制度 | D6: Grade Structure | E6: 等級の定義と、等級ごとの期待役割・報酬・評価との対応 | F6: 定義・仕様 | G6: なし | H6: =IF(G6="なし","—","対象候補") | I6: なし | J6: C01-03 | K6: =IFERROR(INDEX(ケイパビリティマップ!$E:$E,MATCH(J6,ケイパビリティマップ!$A:$A,0)),"（IDなし）") | L6: =COUNTIF('ケイパビリティ×情報オブジェクト'!F$6:F$37,"C") | M6: =COUNTIF('ケイパビリティ×情報オブジェクト'!F$6:F$37,"R")
A7: ORG-04 | B7: 共通・組織 | C7: 就業規則・人事規程 | D7: Work Rules & HR Policies | E7: 就業規則・賃金規程・育児介護休業規程などの規程と、届出・周知の記録 | F7: 文書 | G7: 労基法 | H7: =IF(G7="なし","—","対象候補") | I7: なし | J7: C01-01 | K7: =IFERROR(INDEX(ケイパビリティマップ!$E:$E,MATCH(J7,ケイパビリティマップ!$A:$A,0)),"（IDなし）") | L7: =COUNTIF('ケイパビリティ×情報オブジェクト'!G$6:G$37,"C") | M7: =COUNTIF('ケイパビリティ×情報オブジェクト'!G$6:G$37,"R")
A8: ORG-05 | B8: 共通・組織 | C8: 人事戦略・人的資本KPI | D8: HR Strategy & Human Capital KPI | E8: 人事戦略、重点施策、人的資本の指標と目標 | F8: 文書 | G8: なし | H8: =IF(G8="なし","—","対象候補") | I8: なし | J8: C01-01 | K8: =IFERROR(INDEX(ケイパビリティマップ!$E:$E,MATCH(J8,ケイパビリティマップ!$A:$A,0)),"（IDなし）") | L8: =COUNTIF('ケイパビリティ×情報オブジェクト'!H$6:H$37,"C") | M8: =COUNTIF('ケイパビリティ×情報オブジェクト'!H$6:H$37,"R")
A9: ORG-06 | B9: 共通・組織 | C9: 人的資本開示情報 | D9: Human Capital Disclosure | E9: 有価証券報告書などで開示する人的資本の方針・指標・実績 | F9: 文書 | G9: 金商法 | H9: =IF(G9="なし","—","対象候補") | I9: なし | J9: C01-01 | K9: =IFERROR(INDEX(ケイパビリティマップ!$E:$E,MATCH(J9,ケイパビリティマップ!$A:$A,0)),"（IDなし）") | L9: =COUNTIF('ケイパビリティ×情報オブジェクト'!I$6:I$37,"C") | M9: =COUNTIF('ケイパビリティ×情報オブジェクト'!I$6:I$37,"R")
A10: ORG-07 | B10: 共通・組織 | C10: 要員計画 | D10: Workforce Plan | E10: 職種・等級・雇用形態別の必要人員と過不足、充足方針 | F10: 分析・評価 | G10: なし | H10: =IF(G10="なし","—","対象候補") | I10: なし | J10: C01-02 | K10: =IFERROR(INDEX(ケイパビリティマップ!$E:$E,MATCH(J10,ケイパビリティマップ!$A:$A,0)),"（IDなし）") | L10: =COUNTIF('ケイパビリティ×情報オブジェクト'!J$6:J$37,"C") | M10: =COUNTIF('ケイパビリティ×情報オブジェクト'!J$6:J$37,"R")
A11: ORG-08 | B11: 共通・組織 | C11: 人件費予算 | D11: Personnel Cost Budget | E11: 部門別・費目別の人件費の予算 | F11: トランザクション | G11: なし | H11: =IF(G11="なし","—","対象候補") | I11: なし | J11: C01-02 | K11: =IFERROR(INDEX(ケイパビリティマップ!$E:$E,MATCH(J11,ケイパビリティマップ!$A:$A,0)),"（IDなし）") | L11: =COUNTIF('ケイパビリティ×情報オブジェクト'!K$6:K$37,"C") | M11: =COUNTIF('ケイパビリティ×情報オブジェクト'!K$6:K$37,"R")
A12: ORG-09 | B12: 共通・組織 | C12: 人件費実績 | D12: Personnel Cost Actual | E12: 給与計算の結果を会計に計上した人件費の実績 | F12: トランザクション | G12: 税法 | H12: =IF(G12="なし","—","対象候補") | I12: なし | J12: C01-02 | K12: =IFERROR(INDEX(ケイパビリティマップ!$E:$E,MATCH(J12,ケイパビリティマップ!$A:$A,0)),"（IDなし）") | L12: =COUNTIF('ケイパビリティ×情報オブジェクト'!L$6:L$37,"C") | M12: =COUNTIF('ケイパビリティ×情報オブジェクト'!L$6:L$37,"R")
A13: REC-01 | B13: 採用 | C13: 採用計画 | D13: Recruitment Plan | E13: 新卒・経験者別の採用人数・時期・チャネル・予算 | F13: 文書 | G13: なし | H13: =IF(G13="なし","—","対象候補") | I13: なし | J13: C02-01 | K13: =IFERROR(INDEX(ケイパビリティマップ!$E:$E,MATCH(J13,ケイパビリティマップ!$A:$A,0)),"（IDなし）") | L13: =COUNTIF('ケイパビリティ×情報オブジェクト'!M$6:M$37,"C") | M13: =COUNTIF('ケイパビリティ×情報オブジェクト'!M$6:M$37,"R")
A14: REC-02 | B14: 採用 | C14: 求人票 | D14: Job Posting | E14: 募集職種・業務内容・労働条件（業務・就業場所の変更の範囲を含む） | F14: 文書 | G14: 職安法 | H14: =IF(G14="なし","—","対象候補") | I14: なし | J14: C02-03 | K14: =IFERROR(INDEX(ケイパビリティマップ!$E:$E,MATCH(J14,ケイパビリティマップ!$A:$A,0)),"（IDなし）") | L14: =COUNTIF('ケイパビリティ×情報オブジェクト'!N$6:N$37,"C") | M14: =COUNTIF('ケイパビリティ×情報オブジェクト'!N$6:N$37,"R")
A15: REC-03 | B15: 採用 | C15: 応募者情報 | D15: Candidate Profile | E15: 応募者の連絡先・学歴・職歴・選考状況。不採用後は返却・廃棄の対象 | F15: トランザクション | G15: 個人情報保護法 | H15: =IF(G15="なし","—","対象候補") | I15: 個人情報 | J15: C02-03 | K15: =IFERROR(INDEX(ケイパビリティマップ!$E:$E,MATCH(J15,ケイパビリティマップ!$A:$A,0)),"（IDなし）") | L15: =COUNTIF('ケイパビリティ×情報オブジェクト'!O$6:O$37,"C") | M15: =COUNTIF('ケイパビリティ×情報オブジェクト'!O$6:O$37,"R")
A16: REC-04 | B16: 採用 | C16: 選考記録 | D16: Selection Record | E16: 書類選考・適性検査・面接の評価と採否の判定 | F16: 分析・評価 | G16: 職安法 | H16: =IF(G16="なし","—","対象候補") | I16: 個人情報 | J16: C02-03 | K16: =IFERROR(INDEX(ケイパビリティマップ!$E:$E,MATCH(J16,ケイパビリティマップ!$A:$A,0)),"（IDなし）") | L16: =COUNTIF('ケイパビリティ×情報オブジェクト'!P$6:P$37,"C") | M16: =COUNTIF('ケイパビリティ×情報オブジェクト'!P$6:P$37,"R")
A17: REC-05 | B17: 採用 | C17: 内定・オファー | D17: Offer | E17: 処遇条件・入社日・労働条件の明示内容と、内定の承諾状況 | F17: トランザクション | G17: 職安法 | H17: =IF(G17="なし","—","対象候補") | I17: 個人情報 | J17: C02-03 | K17: =IFERROR(INDEX(ケイパビリティマップ!$E:$E,MATCH(J17,ケイパビリティマップ!$A:$A,0)),"（IDなし）") | L17: =COUNTIF('ケイパビリティ×情報オブジェクト'!Q$6:Q$37,"C") | M17: =COUNTIF('ケイパビリティ×情報オブジェクト'!Q$6:Q$37,"R")
A18: REC-06 | B18: 採用 | C18: 採用チャネル実績 | D18: Sourcing Channel Performance | E18: チャネル別の応募数・内定数・入社数・コスト | F18: 分析・評価 | G18: なし | H18: =IF(G18="なし","—","対象候補") | I18: なし | J18: C02-01 | K18: =IFERROR(INDEX(ケイパビリティマップ!$E:$E,MATCH(J18,ケイパビリティマップ!$A:$A,0)),"（IDなし）") | L18: =COUNTIF('ケイパビリティ×情報オブジェクト'!R$6:R$37,"C") | M18: =COUNTIF('ケイパビリティ×情報オブジェクト'!R$6:R$37,"R")
A19: EMP-01 | B19: 雇用・従業員 | C19: 従業員マスタ | D19: Employee Master | E19: 社員番号・氏名・所属・等級・雇用区分・入社日など従業員の基本情報 | F19: マスタ | G19: なし | H19: =IF(G19="なし","—","対象候補") | I19: 個人情報 | J19: C03-03 | K19: =IFERROR(INDEX(ケイパビリティマップ!$E:$E,MATCH(J19,ケイパビリティマップ!$A:$A,0)),"（IDなし）") | L19: =COUNTIF('ケイパビリティ×情報オブジェクト'!S$6:S$37,"C") | M19: =COUNTIF('ケイパビリティ×情報オブジェクト'!S$6:S$37,"R")
A20: EMP-02 | B20: 雇用・従業員 | C20: 雇用契約 | D20: Employment Contract | E20: 労働条件通知書・雇用契約書。有期契約の期間・更新、出向契約を含む | F20: 文書 | G20: 労基法 | H20: =IF(G20="なし","—","対象候補") | I20: 個人情報 | J20: C03-01 | K20: =IFERROR(INDEX(ケイパビリティマップ!$E:$E,MATCH(J20,ケイパビリティマップ!$A:$A,0)),"（IDなし）") | L20: =COUNTIF('ケイパビリティ×情報オブジェクト'!T$6:T$37,"C") | M20: =COUNTIF('ケイパビリティ×情報オブジェクト'!T$6:T$37,"R")
A21: EMP-03 | B21: 雇用・従業員 | C21: 入社書類 | D21: Onboarding Documents | E21: 誓約書・身元保証書・扶養情報・通勤経路・振込口座などの届出 | F21: 文書 | G21: なし | H21: =IF(G21="なし","—","対象候補") | I21: 個人情報 | J21: C03-01 | K21: =IFERROR(INDEX(ケイパビリティマップ!$E:$E,MATCH(J21,ケイパビリティマップ!$A:$A,0)),"（IDなし）") | L21: =COUNTIF('ケイパビリティ×情報オブジェクト'!U$6:U$37,"C") | M21: =COUNTIF('ケイパビリティ×情報オブジェクト'!U$6:U$37,"R")
A22: EMP-04 | B22: 雇用・従業員 | C22: マイナンバー | D22: Individual Number | E22: 従業員と扶養家族の個人番号と本人確認の記録 | F22: マスタ | G22: 番号法 | H22: =IF(G22="なし","—","対象候補") | I22: 特定個人情報 | J22: C03-01 | K22: =IFERROR(INDEX(ケイパビリティマップ!$E:$E,MATCH(J22,ケイパビリティマップ!$A:$A,0)),"（IDなし）") | L22: =COUNTIF('ケイパビリティ×情報オブジェクト'!V$6:V$37,"C") | M22: =COUNTIF('ケイパビリティ×情報オブジェクト'!V$6:V$37,"R")
A23: EMP-05 | B23: 雇用・従業員 | C23: 労働者名簿 | D23: Worker Register | E23: 法定の労働者名簿（氏名・生年月日・履歴・雇入れ・退職等） | F23: 文書 | G23: 労基法 | H23: =IF(G23="なし","—","対象候補") | I23: 個人情報 | J23: C03-03 | K23: =IFERROR(INDEX(ケイパビリティマップ!$E:$E,MATCH(J23,ケイパビリティマップ!$A:$A,0)),"（IDなし）") | L23: =COUNTIF('ケイパビリティ×情報オブジェクト'!W$6:W$37,"C") | M23: =COUNTIF('ケイパビリティ×情報オブジェクト'!W$6:W$37,"R")
A24: EMP-06 | B24: 雇用・従業員 | C24: 社会保険・雇用保険の資格情報 | D24: Social Insurance Enrollment | E24: 健康保険・厚生年金・雇用保険の資格取得・喪失、標準報酬月額、被扶養者 | F24: マスタ | G24: 社会保険・雇用保険 | H24: =IF(G24="なし","—","対象候補") | I24: 個人情報 | J24: C03-01 | K24: =IFERROR(INDEX(ケイパビリティマップ!$E:$E,MATCH(J24,ケイパビリティマップ!$A:$A,0)),"（IDなし）") | L24: =COUNTIF('ケイパビリティ×情報オブジェクト'!X$6:X$37,"C") | M24: =COUNTIF('ケイパビリティ×情報オブジェクト'!X$6:X$37,"R")
A25: EMP-07 | B25: 雇用・従業員 | C25: 異動・発令履歴 | D25: Assignment History | E25: 入社・配属・異動・昇格・出向などの発令とその履歴 | F25: トランザクション | G25: なし | H25: =IF(G25="なし","—","対象候補") | I25: 個人情報 | J25: C03-03 | K25: =IFERROR(INDEX(ケイパビリティマップ!$E:$E,MATCH(J25,ケイパビリティマップ!$A:$A,0)),"（IDなし）") | L25: =COUNTIF('ケイパビリティ×情報オブジェクト'!Y$6:Y$37,"C") | M25: =COUNTIF('ケイパビリティ×情報オブジェクト'!Y$6:Y$37,"R")
A26: EMP-08 | B26: 雇用・従業員 | C26: オンボーディング計画 | D26: Onboarding Plan | E26: 入社者ごとの受入れ計画・メンター・面談記録・試用期間の評価 | F26: 文書 | G26: なし | H26: =IF(G26="なし","—","対象候補") | I26: 個人情報 | J26: C03-02 | K26: =IFERROR(INDEX(ケイパビリティマップ!$E:$E,MATCH(J26,ケイパビリティマップ!$A:$A,0)),"（IDなし）") | L26: =COUNTIF('ケイパビリティ×情報オブジェクト'!Z$6:Z$37,"C") | M26: =COUNTIF('ケイパビリティ×情報オブジェクト'!Z$6:Z$37,"R")
A27: EMP-09 | B27: 雇用・従業員 | C27: 貸与物・アカウント記録 | D27: Asset & Account Record | E27: PC・社員証などの貸与物と、システムのアカウント・権限 | F27: トランザクション | G27: なし | H27: =IF(G27="なし","—","対象候補") | I27: 個人情報 | J27: C09-03 | K27: =IFERROR(INDEX(ケイパビリティマップ!$E:$E,MATCH(J27,ケイパビリティマップ!$A:$A,0)),"（IDなし）") | L27: =COUNTIF('ケイパビリティ×情報オブジェクト'!AA$6:AA$37,"C") | M27: =COUNTIF('ケイパビリティ×情報オブジェクト'!AA$6:AA$37,"R")
A28: LRN-01 | B28: 育成 | C28: 育成体系・研修カタログ | D28: Learning Catalog | E28: 育成体系、研修の一覧・対象者・内容、年間研修計画 | F28: 定義・仕様 | G28: なし | H28: =IF(G28="なし","—","対象候補") | I28: なし | J28: C04-01 | K28: =IFERROR(INDEX(ケイパビリティマップ!$E:$E,MATCH(J28,ケイパビリティマップ!$A:$A,0)),"（IDなし）") | L28: =COUNTIF('ケイパビリティ×情報オブジェクト'!AB$6:AB$37,"C") | M28: =COUNTIF('ケイパビリティ×情報オブジェクト'!AB$6:AB$37,"R")
A29: LRN-02 | B29: 育成 | C29: 受講記録 | D29: Training Record | E29: 研修・eラーニングの受講・修了・テストの記録（法定教育を含む） | F29: トランザクション | G29: 安衛法 | H29: =IF(G29="なし","—","対象候補") | I29: 個人情報 | J29: C04-01 | K29: =IFERROR(INDEX(ケイパビリティマップ!$E:$E,MATCH(J29,ケイパビリティマップ!$A:$A,0)),"（IDなし）") | L29: =COUNTIF('ケイパビリティ×情報オブジェクト'!AC$6:AC$37,"C") | M29: =COUNTIF('ケイパビリティ×情報オブジェクト'!AC$6:AC$37,"R")
A30: LRN-03 | B30: 育成 | C30: スキル・資格情報 | D30: Skills & Certifications | E30: スキル体系と従業員のスキル評価、保有資格・有効期限・法定の選任 | F30: マスタ | G30: 各業法 | H30: =IF(G30="なし","—","対象候補") | I30: 個人情報 | J30: C04-02 | K30: =IFERROR(INDEX(ケイパビリティマップ!$E:$E,MATCH(J30,ケイパビリティマップ!$A:$A,0)),"（IDなし）") | L30: =COUNTIF('ケイパビリティ×情報オブジェクト'!AD$6:AD$37,"C") | M30: =COUNTIF('ケイパビリティ×情報オブジェクト'!AD$6:AD$37,"R")
A31: LRN-04 | B31: 育成 | C31: キャリア面談記録 | D31: Career Development Record | E31: キャリアの希望、自己申告、個人別育成計画 | F31: 文書 | G31: なし | H31: =IF(G31="なし","—","対象候補") | I31: 個人情報 | J31: C04-03 | K31: =IFERROR(INDEX(ケイパビリティマップ!$E:$E,MATCH(J31,ケイパビリティマップ!$A:$A,0)),"（IDなし）") | L31: =COUNTIF('ケイパビリティ×情報オブジェクト'!AE$6:AE$37,"C") | M31: =COUNTIF('ケイパビリティ×情報オブジェクト'!AE$6:AE$37,"R")
A32: PRF-01 | B32: 評価・報酬 | C32: 目標 | D32: Objectives | E32: 期初に合意した目標と、期中の進捗・フィードバック | F32: トランザクション | G32: なし | H32: =IF(G32="なし","—","対象候補") | I32: 個人情報 | J32: C05-01 | K32: =IFERROR(INDEX(ケイパビリティマップ!$E:$E,MATCH(J32,ケイパビリティマップ!$A:$A,0)),"（IDなし）") | L32: =COUNTIF('ケイパビリティ×情報オブジェクト'!AF$6:AF$37,"C") | M32: =COUNTIF('ケイパビリティ×情報オブジェクト'!AF$6:AF$37,"R")
A33: PRF-02 | B33: 評価・報酬 | C33: 人事評価結果 | D33: Performance Rating | E33: 自己評価・一次／二次評価・調整後の確定評価とフィードバック | F33: 分析・評価 | G33: なし | H33: =IF(G33="なし","—","対象候補") | I33: 個人情報 | J33: C05-01 | K33: =IFERROR(INDEX(ケイパビリティマップ!$E:$E,MATCH(J33,ケイパビリティマップ!$A:$A,0)),"（IDなし）") | L33: =COUNTIF('ケイパビリティ×情報オブジェクト'!AG$6:AG$37,"C") | M33: =COUNTIF('ケイパビリティ×情報オブジェクト'!AG$6:AG$37,"R")
A34: PRF-03 | B34: 評価・報酬 | C34: 報酬テーブル | D34: Pay Structure | E34: 賃金テーブル、手当・賞与・退職金の算定方式 | F34: 定義・仕様 | G34: 最低賃金法・パート有期法 | H34: =IF(G34="なし","—","対象候補") | I34: なし | J34: C05-02 | K34: =IFERROR(INDEX(ケイパビリティマップ!$E:$E,MATCH(J34,ケイパビリティマップ!$A:$A,0)),"（IDなし）") | L34: =COUNTIF('ケイパビリティ×情報オブジェクト'!AH$6:AH$37,"C") | M34: =COUNTIF('ケイパビリティ×情報オブジェクト'!AH$6:AH$37,"R")
A35: PRF-04 | B35: 評価・報酬 | C35: 報酬市場データ | D35: Compensation Benchmark | E35: 報酬サーベイ、地域別最低賃金などの外部データ | F35: 測定データ | G35: なし | H35: =IF(G35="なし","—","対象候補") | I35: なし | J35: C05-02 | K35: =IFERROR(INDEX(ケイパビリティマップ!$E:$E,MATCH(J35,ケイパビリティマップ!$A:$A,0)),"（IDなし）") | L35: =COUNTIF('ケイパビリティ×情報オブジェクト'!AI$6:AI$37,"C") | M35: =COUNTIF('ケイパビリティ×情報オブジェクト'!AI$6:AI$37,"R")
A36: PRF-05 | B36: 評価・報酬 | C36: 昇給・賞与決定 | D36: Salary Increase & Bonus Decision | E36: 昇給・賞与の原資と、個人別の決定額 | F36: トランザクション | G36: なし | H36: =IF(G36="なし","—","対象候補") | I36: 個人情報 | J36: C05-02 | K36: =IFERROR(INDEX(ケイパビリティマップ!$E:$E,MATCH(J36,ケイパビリティマップ!$A:$A,0)),"（IDなし）") | L36: =COUNTIF('ケイパビリティ×情報オブジェクト'!AJ$6:AJ$37,"C") | M36: =COUNTIF('ケイパビリティ×情報オブジェクト'!AJ$6:AJ$37,"R")
A37: PAY-01 | B37: 給与・社会保険 | C37: 給与・賞与計算結果 | D37: Payroll Result | E37: 支給・控除の明細と振込データ（最終給与・退職金を含む） | F37: トランザクション | G37: 労基法・税法 | H37: =IF(G37="なし","—","対象候補") | I37: 個人情報 | J37: C05-03 | K37: =IFERROR(INDEX(ケイパビリティマップ!$E:$E,MATCH(J37,ケイパビリティマップ!$A:$A,0)),"（IDなし）") | L37: =COUNTIF('ケイパビリティ×情報オブジェクト'!AK$6:AK$37,"C") | M37: =COUNTIF('ケイパビリティ×情報オブジェクト'!AK$6:AK$37,"R")
A38: PAY-02 | B38: 給与・社会保険 | C38: 賃金台帳 | D38: Wage Ledger | E38: 法定の賃金台帳（賃金計算期間・労働日数・労働時間・各支給控除額） | F38: 文書 | G38: 労基法 | H38: =IF(G38="なし","—","対象候補") | I38: 個人情報 | J38: C05-03 | K38: =IFERROR(INDEX(ケイパビリティマップ!$E:$E,MATCH(J38,ケイパビリティマップ!$A:$A,0)),"（IDなし）") | L38: =COUNTIF('ケイパビリティ×情報オブジェクト'!AL$6:AL$37,"C") | M38: =COUNTIF('ケイパビリティ×情報オブジェクト'!AL$6:AL$37,"R")
A39: PAY-03 | B39: 給与・社会保険 | C39: 源泉徴収・年末調整情報 | D39: Withholding & Year-end Adjustment | E39: 扶養控除等申告書・保険料控除申告書、年末調整の結果、源泉徴収票・法定調書 | F39: トランザクション | G39: 税法・番号法 | H39: =IF(G39="なし","—","対象候補") | I39: 個人情報 | J39: C05-03 | K39: =IFERROR(INDEX(ケイパビリティマップ!$E:$E,MATCH(J39,ケイパビリティマップ!$A:$A,0)),"（IDなし）") | L39: =COUNTIF('ケイパビリティ×情報オブジェクト'!AM$6:AM$37,"C") | M39: =COUNTIF('ケイパビリティ×情報オブジェクト'!AM$6:AM$37,"R")
A40: PAY-04 | B40: 給与・社会保険 | C40: 住民税特別徴収情報 | D40: Resident Tax Withholding | E40: 市区町村からの特別徴収税額の通知と、納付・異動届 | F40: トランザクション | G40: 税法 | H40: =IF(G40="なし","—","対象候補") | I40: 個人情報 | J40: C05-03 | K40: =IFERROR(INDEX(ケイパビリティマップ!$E:$E,MATCH(J40,ケイパビリティマップ!$A:$A,0)),"（IDなし）") | L40: =COUNTIF('ケイパビリティ×情報オブジェクト'!AN$6:AN$37,"C") | M40: =COUNTIF('ケイパビリティ×情報オブジェクト'!AN$6:AN$37,"R")
A41: PAY-05 | B41: 給与・社会保険 | C41: 社会保険・労働保険の届出 | D41: Social Insurance Filings | E41: 算定基礎届・月額変更届・賞与支払届・労働保険の年度更新 | F41: トランザクション | G41: 社会保険・雇用保険 | H41: =IF(G41="なし","—","対象候補") | I41: 個人情報 | J41: C05-04 | K41: =IFERROR(INDEX(ケイパビリティマップ!$E:$E,MATCH(J41,ケイパビリティマップ!$A:$A,0)),"（IDなし）") | L41: =COUNTIF('ケイパビリティ×情報オブジェクト'!AO$6:AO$37,"C") | M41: =COUNTIF('ケイパビリティ×情報オブジェクト'!AO$6:AO$37,"R")
A42: PAY-06 | B42: 給与・社会保険 | C42: 福利厚生利用情報 | D42: Benefits Enrollment | E42: 福利厚生制度の加入・利用の記録 | F42: トランザクション | G42: なし | H42: =IF(G42="なし","—","対象候補") | I42: 個人情報 | J42: C05-04 | K42: =IFERROR(INDEX(ケイパビリティマップ!$E:$E,MATCH(J42,ケイパビリティマップ!$A:$A,0)),"（IDなし）") | L42: =COUNTIF('ケイパビリティ×情報オブジェクト'!AP$6:AP$37,"C") | M42: =COUNTIF('ケイパビリティ×情報オブジェクト'!AP$6:AP$37,"R")
A43: PAY-07 | B43: 給与・社会保険 | C43: 退職給付情報 | D43: Retirement Benefits | E43: 退職金の算定基礎、企業年金の加入・掛金・給付 | F43: マスタ | G43: 確定給付・確定拠出年金法 | H43: =IF(G43="なし","—","対象候補") | I43: 個人情報 | J43: C05-04 | K43: =IFERROR(INDEX(ケイパビリティマップ!$E:$E,MATCH(J43,ケイパビリティマップ!$A:$A,0)),"（IDなし）") | L43: =COUNTIF('ケイパビリティ×情報オブジェクト'!AQ$6:AQ$37,"C") | M43: =COUNTIF('ケイパビリティ×情報オブジェクト'!AQ$6:AQ$37,"R")
A44: WRK-01 | B44: 就業・健康 | C44: 勤務予定・勤怠記録 | D44: Schedule & Time Record | E44: 勤務予定・シフト、出退勤、労働時間・時間外労働（出勤簿） | F44: 測定データ | G44: 労基法・安衛法 | H44: =IF(G44="なし","—","対象候補") | I44: 個人情報 | J44: C06-01 | K44: =IFERROR(INDEX(ケイパビリティマップ!$E:$E,MATCH(J44,ケイパビリティマップ!$A:$A,0)),"（IDなし）") | L44: =COUNTIF('ケイパビリティ×情報オブジェクト'!AR$6:AR$37,"C") | M44: =COUNTIF('ケイパビリティ×情報オブジェクト'!AR$6:AR$37,"R")
A45: WRK-02 | B45: 就業・健康 | C45: 休暇・休業記録 | D45: Leave Record | E45: 年次有給休暇の付与・取得（管理簿）、育児・介護休業、休職 | F45: トランザクション | G45: 労基法・育介法 | H45: =IF(G45="なし","—","対象候補") | I45: 要配慮個人情報 | J45: C06-01 | K45: =IFERROR(INDEX(ケイパビリティマップ!$E:$E,MATCH(J45,ケイパビリティマップ!$A:$A,0)),"（IDなし）") | L45: =COUNTIF('ケイパビリティ×情報オブジェクト'!AS$6:AS$37,"C") | M45: =COUNTIF('ケイパビリティ×情報オブジェクト'!AS$6:AS$37,"R")
A46: WRK-03 | B46: 就業・健康 | C46: 労使協定・労使協議記録 | D46: Labor Agreements | E46: 36協定などの労使協定、労働協約、労使協議の記録 | F46: 文書 | G46: 労基法 | H46: =IF(G46="なし","—","対象候補") | I46: なし | J46: C06-03 | K46: =IFERROR(INDEX(ケイパビリティマップ!$E:$E,MATCH(J46,ケイパビリティマップ!$A:$A,0)),"（IDなし）") | L46: =COUNTIF('ケイパビリティ×情報オブジェクト'!AT$6:AT$37,"C") | M46: =COUNTIF('ケイパビリティ×情報オブジェクト'!AT$6:AT$37,"R")
A47: WRK-04 | B47: 就業・健康 | C47: 健康診断・面接指導記録 | D47: Health Check & Physician Interview | E47: 健康診断の結果、医師の意見、長時間労働者などの面接指導の記録 | F47: 測定データ | G47: 安衛法 | H47: =IF(G47="なし","—","対象候補") | I47: 要配慮個人情報 | J47: C06-02 | K47: =IFERROR(INDEX(ケイパビリティマップ!$E:$E,MATCH(J47,ケイパビリティマップ!$A:$A,0)),"（IDなし）") | L47: =COUNTIF('ケイパビリティ×情報オブジェクト'!AU$6:AU$37,"C") | M47: =COUNTIF('ケイパビリティ×情報オブジェクト'!AU$6:AU$37,"R")
A48: WRK-05 | B48: 就業・健康 | C48: ストレスチェック結果 | D48: Stress Check Result | E48: ストレスチェックの個人結果（本人の同意なく会社は見られない）と集団分析 | F48: 測定データ | G48: 安衛法 | H48: =IF(G48="なし","—","対象候補") | I48: 要配慮個人情報 | J48: C06-02 | K48: =IFERROR(INDEX(ケイパビリティマップ!$E:$E,MATCH(J48,ケイパビリティマップ!$A:$A,0)),"（IDなし）") | L48: =COUNTIF('ケイパビリティ×情報オブジェクト'!AV$6:AV$37,"C") | M48: =COUNTIF('ケイパビリティ×情報オブジェクト'!AV$6:AV$37,"R")
A49: WRK-06 | B49: 就業・健康 | C49: 労働災害記録 | D49: Occupational Accident Record | E49: 労働災害の内容・原因・再発防止策、労働者死傷病報告 | F49: トランザクション | G49: 安衛法 | H49: =IF(G49="なし","—","対象候補") | I49: 要配慮個人情報 | J49: C06-02 | K49: =IFERROR(INDEX(ケイパビリティマップ!$E:$E,MATCH(J49,ケイパビリティマップ!$A:$A,0)),"（IDなし）") | L49: =COUNTIF('ケイパビリティ×情報オブジェクト'!AW$6:AW$37,"C") | M49: =COUNTIF('ケイパビリティ×情報オブジェクト'!AW$6:AW$37,"R")
A50: WRK-07 | B50: 就業・健康 | C50: 相談・ハラスメント事案記録 | D50: Grievance & Harassment Case | E50: 相談・通報の内容、調査、措置、再発防止（懲戒の記録を含む） | F50: トランザクション | G50: 労働施策総合推進法等 | H50: =IF(G50="なし","—","対象候補") | I50: 要配慮個人情報 | J50: C06-03 | K50: =IFERROR(INDEX(ケイパビリティマップ!$E:$E,MATCH(J50,ケイパビリティマップ!$A:$A,0)),"（IDなし）") | L50: =COUNTIF('ケイパビリティ×情報オブジェクト'!AX$6:AX$37,"C") | M50: =COUNTIF('ケイパビリティ×情報オブジェクト'!AX$6:AX$37,"R")
A51: WRK-08 | B51: 就業・健康 | C51: エンゲージメント調査結果 | D51: Engagement Survey Result | E51: エンゲージメント・入社後サーベイの結果と改善計画 | F51: 測定データ | G51: なし | H51: =IF(G51="なし","—","対象候補") | I51: 個人情報 | J51: C06-04 | K51: =IFERROR(INDEX(ケイパビリティマップ!$E:$E,MATCH(J51,ケイパビリティマップ!$A:$A,0)),"（IDなし）") | L51: =COUNTIF('ケイパビリティ×情報オブジェクト'!AY$6:AY$37,"C") | M51: =COUNTIF('ケイパビリティ×情報オブジェクト'!AY$6:AY$37,"R")
A52: TAL-01 | B52: タレント・配置 | C52: タレントレビュー結果 | D52: Talent Review | E52: 人材の見極め（ポテンシャル・準備度）と育成方針 | F52: 分析・評価 | G52: なし | H52: =IF(G52="なし","—","対象候補") | I52: 個人情報 | J52: C07-01 | K52: =IFERROR(INDEX(ケイパビリティマップ!$E:$E,MATCH(J52,ケイパビリティマップ!$A:$A,0)),"（IDなし）") | L52: =COUNTIF('ケイパビリティ×情報オブジェクト'!AZ$6:AZ$37,"C") | M52: =COUNTIF('ケイパビリティ×情報オブジェクト'!AZ$6:AZ$37,"R")
A53: TAL-02 | B53: タレント・配置 | C53: 異動計画 | D53: Transfer Plan | E53: 定期異動・社内公募・出向の計画と調整の状況 | F53: 文書 | G53: なし | H53: =IF(G53="なし","—","対象候補") | I53: 個人情報 | J53: C07-01 | K53: =IFERROR(INDEX(ケイパビリティマップ!$E:$E,MATCH(J53,ケイパビリティマップ!$A:$A,0)),"（IDなし）") | L53: =COUNTIF('ケイパビリティ×情報オブジェクト'!BA$6:BA$37,"C") | M53: =COUNTIF('ケイパビリティ×情報オブジェクト'!BA$6:BA$37,"R")
A54: TAL-03 | B54: タレント・配置 | C54: 昇格審査記録 | D54: Promotion Assessment | E54: 昇格候補者、試験・アセスメントの結果、昇格の判定 | F54: 分析・評価 | G54: なし | H54: =IF(G54="なし","—","対象候補") | I54: 個人情報 | J54: C07-02 | K54: =IFERROR(INDEX(ケイパビリティマップ!$E:$E,MATCH(J54,ケイパビリティマップ!$A:$A,0)),"（IDなし）") | L54: =COUNTIF('ケイパビリティ×情報オブジェクト'!BB$6:BB$37,"C") | M54: =COUNTIF('ケイパビリティ×情報オブジェクト'!BB$6:BB$37,"R")
A55: TAL-04 | B55: タレント・配置 | C55: 後継者計画 | D55: Succession Plan | E55: 重要ポストと後継候補、準備度、育成計画 | F55: 文書 | G55: なし | H55: =IF(G55="なし","—","対象候補") | I55: 個人情報 | J55: C07-03 | K55: =IFERROR(INDEX(ケイパビリティマップ!$E:$E,MATCH(J55,ケイパビリティマップ!$A:$A,0)),"（IDなし）") | L55: =COUNTIF('ケイパビリティ×情報オブジェクト'!BC$6:BC$37,"C") | M55: =COUNTIF('ケイパビリティ×情報オブジェクト'!BC$6:BC$37,"R")
A56: TAL-05 | B56: タレント・配置 | C56: ダイバーシティ行動計画・指標 | D56: Diversity Action Plan & Metrics | E56: 女性活躍・次世代法の行動計画、障害者雇用状況報告、公表する指標 | F56: 文書 | G56: 女性活躍推進法・障害者雇用促進法・育介法 | H56: =IF(G56="なし","—","対象候補") | I56: なし | J56: C07-04 | K56: =IFERROR(INDEX(ケイパビリティマップ!$E:$E,MATCH(J56,ケイパビリティマップ!$A:$A,0)),"（IDなし）") | L56: =COUNTIF('ケイパビリティ×情報オブジェクト'!BD$6:BD$37,"C") | M56: =COUNTIF('ケイパビリティ×情報オブジェクト'!BD$6:BD$37,"R")
A57: OFF-01 | B57: 退職 | C57: 退職情報 | D57: Separation Record | E57: 退職届、退職日・最終出社日、退職事由（自己都合・定年・契約満了・解雇等） | F57: トランザクション | G57: 労基法 | H57: =IF(G57="なし","—","対象候補") | I57: 個人情報 | J57: C08-01 | K57: =IFERROR(INDEX(ケイパビリティマップ!$E:$E,MATCH(J57,ケイパビリティマップ!$A:$A,0)),"（IDなし）") | L57: =COUNTIF('ケイパビリティ×情報オブジェクト'!BE$6:BE$37,"C") | M57: =COUNTIF('ケイパビリティ×情報オブジェクト'!BE$6:BE$37,"R")
A58: OFF-02 | B58: 退職 | C58: 資格喪失届・離職票 | D58: Loss of Coverage & Separation Notice | E58: 社会保険・雇用保険の資格喪失届、離職証明書・離職票 | F58: 文書 | G58: 社会保険・雇用保険 | H58: =IF(G58="なし","—","対象候補") | I58: 個人情報 | J58: C08-01 | K58: =IFERROR(INDEX(ケイパビリティマップ!$E:$E,MATCH(J58,ケイパビリティマップ!$A:$A,0)),"（IDなし）") | L58: =COUNTIF('ケイパビリティ×情報オブジェクト'!BF$6:BF$37,"C") | M58: =COUNTIF('ケイパビリティ×情報オブジェクト'!BF$6:BF$37,"R")
A59: OFF-03 | B59: 退職 | C59: 退職時交付書類 | D59: Separation Documents | E59: 源泉徴収票・退職所得の源泉徴収票・退職証明書・秘密保持の誓約書 | F59: 文書 | G59: 税法・労基法 | H59: =IF(G59="なし","—","対象候補") | I59: 個人情報 | J59: C08-01 | K59: =IFERROR(INDEX(ケイパビリティマップ!$E:$E,MATCH(J59,ケイパビリティマップ!$A:$A,0)),"（IDなし）") | L59: =COUNTIF('ケイパビリティ×情報オブジェクト'!BG$6:BG$37,"C") | M59: =COUNTIF('ケイパビリティ×情報オブジェクト'!BG$6:BG$37,"R")
A60: OFF-04 | B60: 退職 | C60: 引継ぎ記録 | D60: Handover Record | E60: 業務・ナレッジの引継ぎ計画と引継ぎ書 | F60: 文書 | G60: なし | H60: =IF(G60="なし","—","対象候補") | I60: なし | J60: C08-03 | K60: =IFERROR(INDEX(ケイパビリティマップ!$E:$E,MATCH(J60,ケイパビリティマップ!$A:$A,0)),"（IDなし）") | L60: =COUNTIF('ケイパビリティ×情報オブジェクト'!BH$6:BH$37,"C") | M60: =COUNTIF('ケイパビリティ×情報オブジェクト'!BH$6:BH$37,"R")
A61: OFF-05 | B61: 退職 | C61: 退職面談記録 | D61: Exit Interview | E61: 退職理由の聞き取りと、離職傾向の分析 | F61: 分析・評価 | G61: なし | H61: =IF(G61="なし","—","対象候補") | I61: 個人情報 | J61: C08-03 | K61: =IFERROR(INDEX(ケイパビリティマップ!$E:$E,MATCH(J61,ケイパビリティマップ!$A:$A,0)),"（IDなし）") | L61: =COUNTIF('ケイパビリティ×情報オブジェクト'!BI$6:BI$37,"C") | M61: =COUNTIF('ケイパビリティ×情報オブジェクト'!BI$6:BI$37,"R")
A62: OFF-06 | B62: 退職 | C62: 定年・再雇用情報 | D62: Retirement & Re-employment | E62: 定年予定者、継続雇用の意向、再雇用の条件、就業確保措置 | F62: トランザクション | G62: 高年法 | H62: =IF(G62="なし","—","対象候補") | I62: 個人情報 | J62: C08-02 | K62: =IFERROR(INDEX(ケイパビリティマップ!$E:$E,MATCH(J62,ケイパビリティマップ!$A:$A,0)),"（IDなし）") | L62: =COUNTIF('ケイパビリティ×情報オブジェクト'!BJ$6:BJ$37,"C") | M62: =COUNTIF('ケイパビリティ×情報オブジェクト'!BJ$6:BJ$37,"R")
A63: OFF-07 | B63: 退職 | C63: アルムナイ情報 | D63: Alumni | E63: 退職者の連絡先と、再入社・協業の意向（本人の同意に基づく） | F63: マスタ | G63: 個人情報保護法 | H63: =IF(G63="なし","—","対象候補") | I63: 個人情報 | J63: C08-03 | K63: =IFERROR(INDEX(ケイパビリティマップ!$E:$E,MATCH(J63,ケイパビリティマップ!$A:$A,0)),"（IDなし）") | L63: =COUNTIF('ケイパビリティ×情報オブジェクト'!BK$6:BK$37,"C") | M63: =COUNTIF('ケイパビリティ×情報オブジェクト'!BK$6:BK$37,"R")

Sheet ケイパビリティ×情報オブジェクト
A1: ケイパビリティ×情報オブジェクト（正本：行＝ケイパビリティL2 × 列＝情報オブジェクト）
A2: C＝作成・更新（その能力の中で生み出す／維持する情報。オーナーのL2は必ずC） R＝利用（その能力が入力として参照する情報） 空欄＝関係なし。VSのL4の入力情報（R）・出力情報（主の能力はC、支援の能力はR）から導いたうえで、オーナーのL2をCとした。
A4: ケイパビリティL1 | B4: L2 ID | C4: ケイパビリティL2 | D4: 共通・組織 | M4: 採用 | S4: 雇用・従業員 | AB4: 育成 | AF4: 評価・報酬 | AK4: 給与・社会保険 | AR4: 就業・健康 | AZ4: タレント・配置 | BE4: 退職 | BL4: Cの数 | BM4: Rの数
D5: =情報オブジェクト!C4 | E5: =情報オブジェクト!C5 | F5: =情報オブジェクト!C6 | G5: =情報オブジェクト!C7 | H5: =情報オブジェクト!C8 | I5: =情報オブジェクト!C9 | J5: =情報オブジェクト!C10 | K5: =情報オブジェクト!C11 | L5: =情報オブジェクト!C12 | M5: =情報オブジェクト!C13 | N5: =情報オブジェクト!C14 | O5: =情報オブジェクト!C15 | P5: =情報オブジェクト!C16 | Q5: =情報オブジェクト!C17 | R5: =情報オブジェクト!C18 | S5: =情報オブジェクト!C19 | T5: =情報オブジェクト!C20 | U5: =情報オブジェクト!C21 | V5: =情報オブジェクト!C22 | W5: =情報オブジェクト!C23 | X5: =情報オブジェクト!C24 | Y5: =情報オブジェクト!C25 | Z5: =情報オブジェクト!C26 | AA5: =情報オブジェクト!C27 | AB5: =情報オブジェクト!C28 | AC5: =情報オブジェクト!C29 | AD5: =情報オブジェクト!C30 | AE5: =情報オブジェクト!C31 | AF5: =情報オブジェクト!C32 | AG5: =情報オブジェクト!C33 | AH5: =情報オブジェクト!C34 | AI5: =情報オブジェクト!C35 | AJ5: =情報オブジェクト!C36 | AK5: =情報オブジェクト!C37 | AL5: =情報オブジェクト!C38 | AM5: =情報オブジェクト!C39 | AN5: =情報オブジェクト!C40 | AO5: =情報オブジェクト!C41 | AP5: =情報オブジェクト!C42 | AQ5: =情報オブジェクト!C43 | AR5: =情報オブジェクト!C44 | AS5: =情報オブジェクト!C45 | AT5: =情報オブジェクト!C46 | AU5: =情報オブジェクト!C47 | AV5: =情報オブジェクト!C48 | AW5: =情報オブジェクト!C49 | AX5: =情報オブジェクト!C50 | AY5: =情報オブジェクト!C51 | AZ5: =情報オブジェクト!C52 | BA5: =情報オブジェクト!C53 | BB5: =情報オブジェクト!C54 | BC5: =情報オブジェクト!C55 | BD5: =情報オブジェクト!C56 | BE5: =情報オブジェクト!C57 | BF5: =情報オブジェクト!C58 | BG5: =情報オブジェクト!C59 | BH5: =情報オブジェクト!C60 | BI5: =情報オブジェクト!C61 | BJ5: =情報オブジェクト!C62 | BK5: =情報オブジェクト!C63
A6: C01 人事戦略・組織設計 | B6: C01-01 | C6: =IFERROR(INDEX(ケイパビリティマップ!$E:$E,MATCH(B6,ケイパビリティマップ!$A:$A,0)),"（IDなし）") | G6: C | H6: C | I6: C | AC6: R | AT6: R | AY6: R | BD6: R | BL6: =COUNTIF(D6:BK6,"C") | BM6: =COUNTIF(D6:BK6,"R")
B7: C01-02 | C7: =IFERROR(INDEX(ケイパビリティマップ!$E:$E,MATCH(B7,ケイパビリティマップ!$A:$A,0)),"（IDなし）") | D7: R | H7: R | J7: C | K7: C | L7: C | S7: R | AH7: R | AK7: R | BL7: =COUNTIF(D7:BK7,"C") | BM7: =COUNTIF(D7:BK7,"R")
B8: C01-03 | C8: =IFERROR(INDEX(ケイパビリティマップ!$E:$E,MATCH(B8,ケイパビリティマップ!$A:$A,0)),"（IDなし）") | D8: C | E8: C | F8: C | H8: R | J8: R | AH8: C | AI8: R | BA8: C | BL8: =COUNTIF(D8:BK8,"C") | BM8: =COUNTIF(D8:BK8,"R")
A9: C02 タレント獲得 | B9: C02-01 | C9: =IFERROR(INDEX(ケイパビリティマップ!$E:$E,MATCH(B9,ケイパビリティマップ!$A:$A,0)),"（IDなし）") | I9: R | J9: R | M9: C | N9: C | O9: C | P9: R | Q9: R | R9: C | BL9: =COUNTIF(D9:BK9,"C") | BM9: =COUNTIF(D9:BK9,"R")
B10: C02-02 | C10: =IFERROR(INDEX(ケイパビリティマップ!$E:$E,MATCH(B10,ケイパビリティマップ!$A:$A,0)),"（IDなし）") | E10: R | M10: R | N10: R | O10: C | P10: C | Q10: C | BL10: =COUNTIF(D10:BK10,"C") | BM10: =COUNTIF(D10:BK10,"R")
B11: C02-03 | C11: =IFERROR(INDEX(ケイパビリティマップ!$E:$E,MATCH(B11,ケイパビリティマップ!$A:$A,0)),"（IDなし）") | E11: R | F11: R | G11: R | M11: R | N11: C | O11: C | P11: C | Q11: C | R11: R | AH11: R | BL11: =COUNTIF(D11:BK11,"C") | BM11: =COUNTIF(D11:BK11,"R")
B12: C02-04 | C12: =IFERROR(INDEX(ケイパビリティマップ!$E:$E,MATCH(B12,ケイパビリティマップ!$A:$A,0)),"（IDなし）") | E12: R | G12: R | M12: R | N12: R | O12: C | P12: C | Q12: C | AH12: R | BL12: =COUNTIF(D12:BK12,"C") | BM12: =COUNTIF(D12:BK12,"R")
A13: C03 入社・雇用管理 | B13: C03-01 | C13: =IFERROR(INDEX(ケイパビリティマップ!$E:$E,MATCH(B13,ケイパビリティマップ!$A:$A,0)),"（IDなし）") | G13: R | Q13: R | S13: R | T13: C | U13: C | V13: C | X13: C | Y13: R | AH13: R | AM13: C | BA13: R | BE13: C | BJ13: R | BL13: =COUNTIF(D13:BK13,"C") | BM13: =COUNTIF(D13:BK13,"R")
B14: C03-02 | C14: =IFERROR(INDEX(ケイパビリティマップ!$E:$E,MATCH(B14,ケイパビリティマップ!$A:$A,0)),"（IDなし）") | E14: R | G14: R | J14: R | P14: R | S14: R | Y14: C | Z14: C | AA14: R | AB14: R | AC14: C | AF14: R | AG14: C | AY14: C | BL14: =COUNTIF(D14:BK14,"C") | BM14: =COUNTIF(D14:BK14,"R")
B15: C03-03 | C15: =IFERROR(INDEX(ケイパビリティマップ!$E:$E,MATCH(B15,ケイパビリティマップ!$A:$A,0)),"（IDなし）") | D15: R | S15: C | T15: R | U15: R | V15: R | W15: C | Y15: C | AA15: C | AL15: R | AR15: R | AS15: R | BA15: R | BE15: R | BL15: =COUNTIF(D15:BK15,"C") | BM15: =COUNTIF(D15:BK15,"R")
A16: C04 人材育成・能力開発 | B16: C04-01 | C16: =IFERROR(INDEX(ケイパビリティマップ!$E:$E,MATCH(B16,ケイパビリティマップ!$A:$A,0)),"（IDなし）") | E16: R | F16: R | H16: R | Y16: R | Z16: R | AB16: C | AC16: C | AD16: R | AG16: R | BC16: R | BL16: =COUNTIF(D16:BK16,"C") | BM16: =COUNTIF(D16:BK16,"R")
B17: C04-02 | C17: =IFERROR(INDEX(ケイパビリティマップ!$E:$E,MATCH(B17,ケイパビリティマップ!$A:$A,0)),"（IDなし）") | E17: R | H17: R | J17: R | AC17: C | AD17: C | BL17: =COUNTIF(D17:BK17,"C") | BM17: =COUNTIF(D17:BK17,"R")
B18: C04-03 | C18: =IFERROR(INDEX(ケイパビリティマップ!$E:$E,MATCH(B18,ケイパビリティマップ!$A:$A,0)),"（IDなし）") | S18: R | AB18: R | AC18: C | AD18: R | AE18: C | AF18: R | AG18: R | BL18: =COUNTIF(D18:BK18,"C") | BM18: =COUNTIF(D18:BK18,"R")
B19: C04-04 | C19: =IFERROR(INDEX(ケイパビリティマップ!$E:$E,MATCH(B19,ケイパビリティマップ!$A:$A,0)),"（IDなし）") | G19: R | Y19: R | AB19: R | AC19: C | BL19: =COUNTIF(D19:BK19,"C") | BM19: =COUNTIF(D19:BK19,"R")
A20: C05 パフォーマンス・報酬管理 | B20: C05-01 | C20: =IFERROR(INDEX(ケイパビリティマップ!$E:$E,MATCH(B20,ケイパビリティマップ!$A:$A,0)),"（IDなし）") | E20: R | F20: R | H20: R | Y20: R | Z20: R | AB20: R | AC20: C | AD20: R | AE20: R | AF20: C | AG20: C | BL20: =COUNTIF(D20:BK20,"C") | BM20: =COUNTIF(D20:BK20,"R")
B21: C05-02 | C21: =IFERROR(INDEX(ケイパビリティマップ!$E:$E,MATCH(B21,ケイパビリティマップ!$A:$A,0)),"（IDなし）") | F21: C | H21: R | K21: R | P21: R | Q21: R | AG21: R | AH21: C | AI21: C | AJ21: C | BL21: =COUNTIF(D21:BK21,"C") | BM21: =COUNTIF(D21:BK21,"R")
B22: C05-03 | C22: =IFERROR(INDEX(ケイパビリティマップ!$E:$E,MATCH(B22,ケイパビリティマップ!$A:$A,0)),"（IDなし）") | S22: C | T22: R | U22: R | V22: R | X22: R | AH22: R | AJ22: R | AK22: C | AL22: C | AM22: C | AN22: C | AO22: C | AR22: C | BE22: R | BG22: R | BL22: =COUNTIF(D22:BK22,"C") | BM22: =COUNTIF(D22:BK22,"R")
B23: C05-04 | C23: =IFERROR(INDEX(ケイパビリティマップ!$E:$E,MATCH(B23,ケイパビリティマップ!$A:$A,0)),"（IDなし）") | G23: R | S23: R | X23: C | AJ23: R | AK23: R | AO23: C | AP23: C | AQ23: C | AR23: R | AS23: R | BE23: R | BL23: =COUNTIF(D23:BK23,"C") | BM23: =COUNTIF(D23:BK23,"R")
A24: C06 就業・労務管理 | B24: C06-01 | C24: =IFERROR(INDEX(ケイパビリティマップ!$E:$E,MATCH(B24,ケイパビリティマップ!$A:$A,0)),"（IDなし）") | G24: R | S24: R | T24: R | U24: R | AR24: C | AS24: C | AT24: R | AU24: R | BL24: =COUNTIF(D24:BK24,"C") | BM24: =COUNTIF(D24:BK24,"R")
B25: C06-02 | C25: =IFERROR(INDEX(ケイパビリティマップ!$E:$E,MATCH(B25,ケイパビリティマップ!$A:$A,0)),"（IDなし）") | S25: R | AR25: R | AU25: C | AV25: C | AW25: C | BL25: =COUNTIF(D25:BK25,"C") | BM25: =COUNTIF(D25:BK25,"R")
B26: C06-03 | C26: =IFERROR(INDEX(ケイパビリティマップ!$E:$E,MATCH(B26,ケイパビリティマップ!$A:$A,0)),"（IDなし）") | G26: R | K26: R | AG26: R | AH26: R | AJ26: R | AR26: R | AT26: C | AX26: C | BE26: C | BL26: =COUNTIF(D26:BK26,"C") | BM26: =COUNTIF(D26:BK26,"R")
B27: C06-04 | C27: =IFERROR(INDEX(ケイパビリティマップ!$E:$E,MATCH(B27,ケイパビリティマップ!$A:$A,0)),"（IDなし）") | D27: R | G27: R | S27: R | Z27: R | AR27: C | AS27: R | AY27: C | BL27: =COUNTIF(D27:BK27,"C") | BM27: =COUNTIF(D27:BK27,"R")
A28: C07 タレントマネジメント・配置 | B28: C07-01 | C28: =IFERROR(INDEX(ケイパビリティマップ!$E:$E,MATCH(B28,ケイパビリティマップ!$A:$A,0)),"（IDなし）") | D28: R | E28: R | J28: R | P28: R | S28: R | T28: C | Y28: C | Z28: R | AA28: R | AD28: R | AE28: R | AG28: R | AZ28: C | BA28: C | BL28: =COUNTIF(D28:BK28,"C") | BM28: =COUNTIF(D28:BK28,"R")
B29: C07-02 | C29: =IFERROR(INDEX(ケイパビリティマップ!$E:$E,MATCH(B29,ケイパビリティマップ!$A:$A,0)),"（IDなし）") | F29: R | Y29: C | AG29: R | AZ29: R | BB29: C | BL29: =COUNTIF(D29:BK29,"C") | BM29: =COUNTIF(D29:BK29,"R")
B30: C07-03 | C30: =IFERROR(INDEX(ケイパビリティマップ!$E:$E,MATCH(B30,ケイパビリティマップ!$A:$A,0)),"（IDなし）") | E30: R | AB30: R | AC30: C | AZ30: R | BC30: C | BL30: =COUNTIF(D30:BK30,"C") | BM30: =COUNTIF(D30:BK30,"R")
B31: C07-04 | C31: =IFERROR(INDEX(ケイパビリティマップ!$E:$E,MATCH(B31,ケイパビリティマップ!$A:$A,0)),"（IDなし）") | E31: C | S31: R | Y31: R | AK31: R | AS31: R | BD31: C | BJ31: R | BL31: =COUNTIF(D31:BK31,"C") | BM31: =COUNTIF(D31:BK31,"R")
A32: C08 退職・雇用終了 | B32: C08-01 | C32: =IFERROR(INDEX(ケイパビリティマップ!$E:$E,MATCH(B32,ケイパビリティマップ!$A:$A,0)),"（IDなし）") | S32: R | X32: C | AK32: C | AL32: R | AQ32: C | AR32: R | AS32: R | BE32: C | BF32: C | BG32: C | BL32: =COUNTIF(D32:BK32,"C") | BM32: =COUNTIF(D32:BK32,"R")
B33: C08-02 | C33: =IFERROR(INDEX(ケイパビリティマップ!$E:$E,MATCH(B33,ケイパビリティマップ!$A:$A,0)),"（IDなし）") | S33: R | T33: C | AH33: R | BJ33: C | BL33: =COUNTIF(D33:BK33,"C") | BM33: =COUNTIF(D33:BK33,"R")
B34: C08-03 | C34: =IFERROR(INDEX(ケイパビリティマップ!$E:$E,MATCH(B34,ケイパビリティマップ!$A:$A,0)),"（IDなし）") | E34: R | U34: R | AA34: C | BE34: R | BG34: C | BH34: C | BI34: C | BK34: C | BL34: =COUNTIF(D34:BK34,"C") | BM34: =COUNTIF(D34:BK34,"R")
A35: C09 人事基盤 | B35: C09-01 | C35: =IFERROR(INDEX(ケイパビリティマップ!$E:$E,MATCH(B35,ケイパビリティマップ!$A:$A,0)),"（IDなし）") | D35: R | H35: R | I35: R | M35: R | P35: R | Q35: R | R35: R | S35: R | Y35: R | AB35: R | AC35: R | AD35: R | AE35: R | AG35: R | AK35: R | AY35: R | AZ35: R | BD35: R | BL35: =COUNTIF(D35:BK35,"C") | BM35: =COUNTIF(D35:BK35,"R")
B36: C09-02 | C36: =IFERROR(INDEX(ケイパビリティマップ!$E:$E,MATCH(B36,ケイパビリティマップ!$A:$A,0)),"（IDなし）") | S36: R | V36: R | X36: R | AH36: R | AK36: R | AL36: R | AM36: R | AN36: R | AR36: R | BL36: =COUNTIF(D36:BK36,"C") | BM36: =COUNTIF(D36:BK36,"R")
B37: C09-03 | C37: =IFERROR(INDEX(ケイパビリティマップ!$E:$E,MATCH(B37,ケイパビリティマップ!$A:$A,0)),"（IDなし）") | O37: R | P37: R | S37: R | U37: R | V37: R | W37: R | Y37: R | AA37: C | AL37: R | AU37: R | AV37: R | BA37: R | BE37: R | BL37: =COUNTIF(D37:BK37,"C") | BM37: =COUNTIF(D37:BK37,"R")
C38: Cの数 | D38: =COUNTIF(D$6:D$37,"C") | E38: =COUNTIF(E$6:E$37,"C") | F38: =COUNTIF(F$6:F$37,"C") | G38: =COUNTIF(G$6:G$37,"C") | H38: =COUNTIF(H$6:H$37,"C") | I38: =COUNTIF(I$6:I$37,"C") | J38: =COUNTIF(J$6:J$37,"C") | K38: =COUNTIF(K$6:K$37,"C") | ... BK38: =COUNTIF(BK$6:BK$37,"C")
C39: Rの数 | D39: =COUNTIF(D$6:D$37,"R") | E39: =COUNTIF(E$6:E$37,"R") | F39: =COUNTIF(F$6:F$37,"R") | G39: =COUNTIF(G$6:G$37,"R") | H39: =COUNTIF(H$6:H$37,"R") | I39: =COUNTIF(I$6:I$37,"R") | J39: =COUNTIF(J$6:J$37,"R") | K39: =COUNTIF(K$6:K$37,"R") | ... BK39: =COUNTIF(BK$6:BK$37,"R")

Sheet アプリケーション
A1: アプリケーション（正本：種類の単位）
A2: 1行1種類。製品名ではなく、機能のまとまり（種類）で定義する。現状のシステム名との対応は別の工程で行う。灰色の列は数式（編集しない）。要配慮個人情報・特定個人情報を扱うものは、アクセス管理と委託先の監督を特に厳格にする。
A3: ID | B3: 領域 | C3: アプリケーション種類 | D3: 略称・通称 | E3: 主な機能 | F3: 主な関連法令 | G3: 主に支える ケイパビリティ数 | H3: 部分的に支える ケイパビリティ数
A4: APP-01 | B4: 雇用・労務 | C4: 人事管理（コアHR） | D4: HRIS／人事マスタ | E4: 従業員・組織・職務・発令の履歴を一元管理する人事の基幹システム | F4: 労基法 | G4: =COUNTIF('ケイパビリティ×アプリケーション'!D$6:D$37,"●") | H4: =COUNTIF('ケイパビリティ×アプリケーション'!D$6:D$37,"○")
A5: APP-02 | B5: 採用 | C5: 採用管理 | D5: ATS | E5: 求人の公開、応募者の管理、選考の進捗・評価、内定までを管理する | F5: 職安法・個人情報保護法 | G5: =COUNTIF('ケイパビリティ×アプリケーション'!E$6:E$37,"●") | H5: =COUNTIF('ケイパビリティ×アプリケーション'!E$6:E$37,"○")
A6: APP-03 | B6: 採用 | C6: 適性検査・オンライン面接 | D6: アセスメントツール | E6: 適性検査・Web面接・録画面接を行い、結果を採用管理へ渡す | F6: 職安法・個人情報保護法 | G6: =COUNTIF('ケイパビリティ×アプリケーション'!F$6:F$37,"●") | H6: =COUNTIF('ケイパビリティ×アプリケーション'!F$6:F$37,"○")
A7: APP-04 | B7: 雇用・労務 | C7: 労務手続き | D7: 労務管理クラウド（電子申請） | E7: 入退社・社会保険・雇用保険の手続きと、行政への電子申請を行う | F7: 社会保険・雇用保険 | G7: =COUNTIF('ケイパビリティ×アプリケーション'!G$6:G$37,"●") | H7: =COUNTIF('ケイパビリティ×アプリケーション'!G$6:G$37,"○")
A8: APP-05 | B8: 雇用・労務 | C8: 電子契約 | D8: 電子契約サービス | E8: 雇用契約・労働条件通知書・誓約書などを電子で締結・交付・保管する | F8: 労基法 | G8: =COUNTIF('ケイパビリティ×アプリケーション'!H$6:H$37,"●") | H8: =COUNTIF('ケイパビリティ×アプリケーション'!H$6:H$37,"○")
A9: APP-06 | B9: 雇用・労務 | C9: マイナンバー管理 | D9: マイナンバー管理 | E9: マイナンバーの収集・本人確認・保管・利用・廃棄を管理する | F9: 番号法 | G9: =COUNTIF('ケイパビリティ×アプリケーション'!I$6:I$37,"●") | H9: =COUNTIF('ケイパビリティ×アプリケーション'!I$6:I$37,"○")
A10: APP-07 | B10: 育成・評価 | C10: 学習管理 | D10: LMS | E10: 研修・eラーニングの計画・受講・修了の記録を管理する | F10: 安衛法 | G10: =COUNTIF('ケイパビリティ×アプリケーション'!J$6:J$37,"●") | H10: =COUNTIF('ケイパビリティ×アプリケーション'!J$6:J$37,"○")
A11: APP-08 | B11: 育成・評価 | C11: タレントマネジメント | D11: TMS | E11: スキル・キャリア希望・タレントレビュー・後継者計画・昇格を管理する | F11: なし | G11: =COUNTIF('ケイパビリティ×アプリケーション'!K$6:K$37,"●") | H11: =COUNTIF('ケイパビリティ×アプリケーション'!K$6:K$37,"○")
A12: APP-09 | B12: 育成・評価 | C12: 目標・評価管理 | D12: パフォーマンス管理 | E12: 目標設定・1on1・評価・調整・フィードバックを管理する | F12: なし | G12: =COUNTIF('ケイパビリティ×アプリケーション'!L$6:L$37,"●") | H12: =COUNTIF('ケイパビリティ×アプリケーション'!L$6:L$37,"○")
A13: APP-10 | B13: 就業・健康 | C13: 勤怠管理 | D13: 勤怠管理システム | E13: 打刻・シフト・労働時間・時間外労働の上限・休暇を管理する | F13: 労基法・安衛法 | G13: =COUNTIF('ケイパビリティ×アプリケーション'!M$6:M$37,"●") | H13: =COUNTIF('ケイパビリティ×アプリケーション'!M$6:M$37,"○")
A14: APP-11 | B14: 給与・福利 | C14: 給与計算 | D14: 給与計算システム（年末調整を含む） | E14: 給与・賞与の計算、明細、賃金台帳、年末調整・住民税を管理する | F14: 労基法・税法 | G14: =COUNTIF('ケイパビリティ×アプリケーション'!N$6:N$37,"●") | H14: =COUNTIF('ケイパビリティ×アプリケーション'!N$6:N$37,"○")
A15: APP-12 | B15: 就業・健康 | C15: 健康管理 | D15: 健康管理システム | E15: 健康診断・ストレスチェック・面接指導・就業判定を管理する | F15: 安衛法 | G15: =COUNTIF('ケイパビリティ×アプリケーション'!O$6:O$37,"●") | H15: =COUNTIF('ケイパビリティ×アプリケーション'!O$6:O$37,"○")
A16: APP-13 | B16: 給与・福利 | C16: 福利厚生 | D16: 福利厚生プラットフォーム | E16: 福利厚生メニューの提供と利用を管理する | F16: なし | G16: =COUNTIF('ケイパビリティ×アプリケーション'!P$6:P$37,"●") | H16: =COUNTIF('ケイパビリティ×アプリケーション'!P$6:P$37,"○")
A17: APP-14 | B17: 就業・健康 | C17: エンゲージメントサーベイ | D17: サーベイツール | E17: エンゲージメント・パルスサーベイを実施し、結果を分析する | F17: なし | G17: =COUNTIF('ケイパビリティ×アプリケーション'!Q$6:Q$37,"●") | H17: =COUNTIF('ケイパビリティ×アプリケーション'!Q$6:Q$37,"○")
A18: APP-15 | B18: 共通 | C18: 人事ポータル・問い合わせ管理 | D18: HRサービスデスク | E18: 人事情報の提供、FAQ、問い合わせ・各種申請の受付を行う | F18: なし | G18: =COUNTIF('ケイパビリティ×アプリケーション'!R$6:R$37,"●") | H18: =COUNTIF('ケイパビリティ×アプリケーション'!R$6:R$37,"○")
A19: APP-16 | B19: 共通 | C19: 内部通報・相談管理 | D19: 通報・相談窓口システム | E19: 相談・通報の受付、調査、対応の記録を秘密を守って管理する | F19: 公益通報者保護法 | G19: =COUNTIF('ケイパビリティ×アプリケーション'!S$6:S$37,"●") | H19: =COUNTIF('ケイパビリティ×アプリケーション'!S$6:S$37,"○")
A20: APP-17 | B20: 共通 | C20: 要員計画・人件費シミュレーション | D20: ワークフォースプランニング | E20: 要員計画・人件費予算を立て、シナリオを比較する | F20: なし | G20: =COUNTIF('ケイパビリティ×アプリケーション'!T$6:T$37,"●") | H20: =COUNTIF('ケイパビリティ×アプリケーション'!T$6:T$37,"○")
A21: APP-18 | B21: 共通 | C21: ピープルアナリティクス | D21: 人事DWH／BI | E21: 人事データを集約し、分析・可視化・定型レポートを提供する | F21: なし | G21: =COUNTIF('ケイパビリティ×アプリケーション'!U$6:U$37,"●") | H21: =COUNTIF('ケイパビリティ×アプリケーション'!U$6:U$37,"○")
A22: APP-19 | B22: 共通 | C22: ID・アカウント管理 | D22: IAM | E22: 人事の発令に連動して、アカウントと権限を発行・変更・停止する | F22: なし | G22: =COUNTIF('ケイパビリティ×アプリケーション'!V$6:V$37,"●") | H22: =COUNTIF('ケイパビリティ×アプリケーション'!V$6:V$37,"○")
A23: APP-20 | B23: 共通 | C23: 会計（ERP） | D23: ERP | E23: 人件費の会計計上、予算と実績の管理を行う | F23: 税法 | G23: =COUNTIF('ケイパビリティ×アプリケーション'!W$6:W$37,"●") | H23: =COUNTIF('ケイパビリティ×アプリケーション'!W$6:W$37,"○")
A24: APP-21 | B24: 共通 | C24: 規程・文書管理 | D24: 規程管理システム | E24: 就業規則・人事規程の版と、承認・周知の記録を管理する | F24: 労基法 | G24: =COUNTIF('ケイパビリティ×アプリケーション'!X$6:X$37,"●") | H24: =COUNTIF('ケイパビリティ×アプリケーション'!X$6:X$37,"○")

Sheet ケイパビリティ×アプリケーション
A1: ケイパビリティ×アプリケーション（正本：行＝ケイパビリティL2 × 列＝アプリケーション種類）
A2: ●＝主に支える（その能力の中核の業務を実行するシステム） ○＝部分的に支える（一部の業務やデータの受け渡しで使う） 空欄＝関係なし。このシートに直接記入する。右端と最下行の数は数式。
A4: ケイパビリティL1 | B4: L2 ID | C4: ケイパビリティL2 | D4: 雇用・労務 | E4: 採用 | G4: 雇用・労務 | J4: 育成・評価 | M4: 就業・健康 | N4: 給与・福利 | O4: 就業・健康 | P4: 給与・福利 | Q4: 就業・健康 | R4: 共通 | Y4: ●の数 | Z4: ○の数
D5: =アプリケーション!C4 | E5: =アプリケーション!C5 | F5: =アプリケーション!C6 | G5: =アプリケーション!C7 | H5: =アプリケーション!C8 | I5: =アプリケーション!C9 | J5: =アプリケーション!C10 | K5: =アプリケーション!C11 | L5: =アプリケーション!C12 | M5: =アプリケーション!C13 | N5: =アプリケーション!C14 | O5: =アプリケーション!C15 | P5: =アプリケーション!C16 | Q5: =アプリケーション!C17 | R5: =アプリケーション!C18 | S5: =アプリケーション!C19 | T5: =アプリケーション!C20 | U5: =アプリケーション!C21 | V5: =アプリケーション!C22 | W5: =アプリケーション!C23 | X5: =アプリケーション!C24
A6: C01 人事戦略・組織設計 | B6: C01-01 | C6: =IFERROR(INDEX(ケイパビリティマップ!$E:$E,MATCH(B6,ケイパビリティマップ!$A:$A,0)),"（IDなし）") | D6: ○ | U6: ○ | X6: ● | Y6: =COUNTIF(D6:X6,"●") | Z6: =COUNTIF(D6:X6,"○")
B7: C01-02 | C7: =IFERROR(INDEX(ケイパビリティマップ!$E:$E,MATCH(B7,ケイパビリティマップ!$A:$A,0)),"（IDなし）") | D7: ○ | T7: ● | U7: ○ | W7: ● | Y7: =COUNTIF(D7:X7,"●") | Z7: =COUNTIF(D7:X7,"○")
B8: C01-03 | C8: =IFERROR(INDEX(ケイパビリティマップ!$E:$E,MATCH(B8,ケイパビリティマップ!$A:$A,0)),"（IDなし）") | D8: ● | K8: ○ | T8: ○ | Y8: =COUNTIF(D8:X8,"●") | Z8: =COUNTIF(D8:X8,"○")
A9: C02 タレント獲得 | B9: C02-01 | C9: =IFERROR(INDEX(ケイパビリティマップ!$E:$E,MATCH(B9,ケイパビリティマップ!$A:$A,0)),"（IDなし）") | E9: ● | U9: ○ | Y9: =COUNTIF(D9:X9,"●") | Z9: =COUNTIF(D9:X9,"○")
B10: C02-02 | C10: =IFERROR(INDEX(ケイパビリティマップ!$E:$E,MATCH(B10,ケイパビリティマップ!$A:$A,0)),"（IDなし）") | E10: ● | F10: ○ | Y10: =COUNTIF(D10:X10,"●") | Z10: =COUNTIF(D10:X10,"○")
B11: C02-03 | C11: =IFERROR(INDEX(ケイパビリティマップ!$E:$E,MATCH(B11,ケイパビリティマップ!$A:$A,0)),"（IDなし）") | E11: ● | F11: ○ | H11: ○ | Y11: =COUNTIF(D11:X11,"●") | Z11: =COUNTIF(D11:X11,"○")
B12: C02-04 | C12: =IFERROR(INDEX(ケイパビリティマップ!$E:$E,MATCH(B12,ケイパビリティマップ!$A:$A,0)),"（IDなし）") | E12: ○ | J12: ○ | Y12: =COUNTIF(D12:X12,"●") | Z12: =COUNTIF(D12:X12,"○")
A13: C03 入社・雇用管理 | B13: C03-01 | C13: =IFERROR(INDEX(ケイパビリティマップ!$E:$E,MATCH(B13,ケイパビリティマップ!$A:$A,0)),"（IDなし）") | D13: ○ | G13: ● | H13: ● | I13: ○ | Y13: =COUNTIF(D13:X13,"●") | Z13: =COUNTIF(D13:X13,"○")
B14: C03-02 | C14: =IFERROR(INDEX(ケイパビリティマップ!$E:$E,MATCH(B14,ケイパビリティマップ!$A:$A,0)),"（IDなし）") | D14: ○ | J14: ○ | R14: ○ | V14: ○ | Y14: =COUNTIF(D14:X14,"●") | Z14: =COUNTIF(D14:X14,"○")
B15: C03-03 | C15: =IFERROR(INDEX(ケイパビリティマップ!$E:$E,MATCH(B15,ケイパビリティマップ!$A:$A,0)),"（IDなし）") | D15: ● | G15: ○ | Y15: =COUNTIF(D15:X15,"●") | Z15: =COUNTIF(D15:X15,"○")
A16: C04 人材育成・能力開発 | B16: C04-01 | C16: =IFERROR(INDEX(ケイパビリティマップ!$E:$E,MATCH(B16,ケイパビリティマップ!$A:$A,0)),"（IDなし）") | J16: ● | Y16: =COUNTIF(D16:X16,"●") | Z16: =COUNTIF(D16:X16,"○")
B17: C04-02 | C17: =IFERROR(INDEX(ケイパビリティマップ!$E:$E,MATCH(B17,ケイパビリティマップ!$A:$A,0)),"（IDなし）") | J17: ○ | K17: ● | Y17: =COUNTIF(D17:X17,"●") | Z17: =COUNTIF(D17:X17,"○")
B18: C04-03 | C18: =IFERROR(INDEX(ケイパビリティマップ!$E:$E,MATCH(B18,ケイパビリティマップ!$A:$A,0)),"（IDなし）") | J18: ○ | K18: ● | Y18: =COUNTIF(D18:X18,"●") | Z18: =COUNTIF(D18:X18,"○")
B19: C04-04 | C19: =IFERROR(INDEX(ケイパビリティマップ!$E:$E,MATCH(B19,ケイパビリティマップ!$A:$A,0)),"（IDなし）") | J19: ● | Y19: =COUNTIF(D19:X19,"●") | Z19: =COUNTIF(D19:X19,"○")
A20: C05 パフォーマンス・報酬管理 | B20: C05-01 | C20: =IFERROR(INDEX(ケイパビリティマップ!$E:$E,MATCH(B20,ケイパビリティマップ!$A:$A,0)),"（IDなし）") | K20: ○ | L20: ● | Y20: =COUNTIF(D20:X20,"●") | Z20: =COUNTIF(D20:X20,"○")
B21: C05-02 | C21: =IFERROR(INDEX(ケイパビリティマップ!$E:$E,MATCH(B21,ケイパビリティマップ!$A:$A,0)),"（IDなし）") | K21: ○ | N21: ○ | T21: ○ | Y21: =COUNTIF(D21:X21,"●") | Z21: =COUNTIF(D21:X21,"○")
B22: C05-03 | C22: =IFERROR(INDEX(ケイパビリティマップ!$E:$E,MATCH(B22,ケイパビリティマップ!$A:$A,0)),"（IDなし）") | I22: ○ | M22: ○ | N22: ● | W22: ○ | Y22: =COUNTIF(D22:X22,"●") | Z22: =COUNTIF(D22:X22,"○")
B23: C05-04 | C23: =IFERROR(INDEX(ケイパビリティマップ!$E:$E,MATCH(B23,ケイパビリティマップ!$A:$A,0)),"（IDなし）") | G23: ● | N23: ○ | P23: ● | Y23: =COUNTIF(D23:X23,"●") | Z23: =COUNTIF(D23:X23,"○")
A24: C06 就業・労務管理 | B24: C06-01 | C24: =IFERROR(INDEX(ケイパビリティマップ!$E:$E,MATCH(B24,ケイパビリティマップ!$A:$A,0)),"（IDなし）") | G24: ○ | M24: ● | Y24: =COUNTIF(D24:X24,"●") | Z24: =COUNTIF(D24:X24,"○")
B25: C06-02 | C25: =IFERROR(INDEX(ケイパビリティマップ!$E:$E,MATCH(B25,ケイパビリティマップ!$A:$A,0)),"（IDなし）") | M25: ○ | O25: ● | Y25: =COUNTIF(D25:X25,"●") | Z25: =COUNTIF(D25:X25,"○")
B26: C06-03 | C26: =IFERROR(INDEX(ケイパビリティマップ!$E:$E,MATCH(B26,ケイパビリティマップ!$A:$A,0)),"（IDなし）") | R26: ○ | S26: ● | X26: ○ | Y26: =COUNTIF(D26:X26,"●") | Z26: =COUNTIF(D26:X26,"○")
B27: C06-04 | C27: =IFERROR(INDEX(ケイパビリティマップ!$E:$E,MATCH(B27,ケイパビリティマップ!$A:$A,0)),"（IDなし）") | M27: ○ | Q27: ● | Y27: =COUNTIF(D27:X27,"●") | Z27: =COUNTIF(D27:X27,"○")
A28: C07 タレントマネジメント・配置 | B28: C07-01 | C28: =IFERROR(INDEX(ケイパビリティマップ!$E:$E,MATCH(B28,ケイパビリティマップ!$A:$A,0)),"（IDなし）") | D28: ○ | K28: ● | Y28: =COUNTIF(D28:X28,"●") | Z28: =COUNTIF(D28:X28,"○")
B29: C07-02 | C29: =IFERROR(INDEX(ケイパビリティマップ!$E:$E,MATCH(B29,ケイパビリティマップ!$A:$A,0)),"（IDなし）") | K29: ● | L29: ○ | Y29: =COUNTIF(D29:X29,"●") | Z29: =COUNTIF(D29:X29,"○")
B30: C07-03 | C30: =IFERROR(INDEX(ケイパビリティマップ!$E:$E,MATCH(B30,ケイパビリティマップ!$A:$A,0)),"（IDなし）") | K30: ● | Y30: =COUNTIF(D30:X30,"●") | Z30: =COUNTIF(D30:X30,"○")
B31: C07-04 | C31: =IFERROR(INDEX(ケイパビリティマップ!$E:$E,MATCH(B31,ケイパビリティマップ!$A:$A,0)),"（IDなし）") | D31: ○ | U31: ○ | Y31: =COUNTIF(D31:X31,"●") | Z31: =COUNTIF(D31:X31,"○")
A32: C08 退職・雇用終了 | B32: C08-01 | C32: =IFERROR(INDEX(ケイパビリティマップ!$E:$E,MATCH(B32,ケイパビリティマップ!$A:$A,0)),"（IDなし）") | D32: ○ | G32: ● | N32: ○ | Y32: =COUNTIF(D32:X32,"●") | Z32: =COUNTIF(D32:X32,"○")
B33: C08-02 | C33: =IFERROR(INDEX(ケイパビリティマップ!$E:$E,MATCH(B33,ケイパビリティマップ!$A:$A,0)),"（IDなし）") | D33: ● | H33: ○ | Y33: =COUNTIF(D33:X33,"●") | Z33: =COUNTIF(D33:X33,"○")
B34: C08-03 | C34: =IFERROR(INDEX(ケイパビリティマップ!$E:$E,MATCH(B34,ケイパビリティマップ!$A:$A,0)),"（IDなし）") | D34: ○ | R34: ○ | V34: ○ | Y34: =COUNTIF(D34:X34,"●") | Z34: =COUNTIF(D34:X34,"○")
A35: C09 人事基盤 | B35: C09-01 | C35: =IFERROR(INDEX(ケイパビリティマップ!$E:$E,MATCH(B35,ケイパビリティマップ!$A:$A,0)),"（IDなし）") | Q35: ○ | U35: ● | Y35: =COUNTIF(D35:X35,"●") | Z35: =COUNTIF(D35:X35,"○")
B36: C09-02 | C36: =IFERROR(INDEX(ケイパビリティマップ!$E:$E,MATCH(B36,ケイパビリティマップ!$A:$A,0)),"（IDなし）") | R36: ● | Y36: =COUNTIF(D36:X36,"●") | Z36: =COUNTIF(D36:X36,"○")
B37: C09-03 | C37: =IFERROR(INDEX(ケイパビリティマップ!$E:$E,MATCH(B37,ケイパビリティマップ!$A:$A,0)),"（IDなし）") | I37: ○ | V37: ● | Y37: =COUNTIF(D37:X37,"●") | Z37: =COUNTIF(D37:X37,"○")
C38: ●の数 | D38: =COUNTIF(D6:D37,"●") | E38: =COUNTIF(E6:E37,"●") | F38: =COUNTIF(F6:F37,"●") | G38: =COUNTIF(G6:G37,"●") | H38: =COUNTIF(H6:H37,"●") | I38: =COUNTIF(I6:I37,"●") | J38: =COUNTIF(J6:J37,"●") | K38: =COUNTIF(K6:K37,"●") | ... X38: =COUNTIF(X6:X37,"●")
C39: ○の数 | D39: =COUNTIF(D6:D37,"○") | E39: =COUNTIF(E6:E37,"○") | F39: =COUNTIF(F6:F37,"○") | G39: =COUNTIF(G6:G37,"○") | H39: =COUNTIF(H6:H37,"○") | I39: =COUNTIF(I6:I37,"○") | J39: =COUNTIF(J6:J37,"○") | K39: =COUNTIF(K6:K37,"○") | ... X39: =COUNTIF(X6:X37,"○")

Sheet アプリケーション×情報オブジェクト
A1: アプリケーション×情報オブジェクト（行＝アプリケーション × 列＝情報オブジェクト）
A2: C＝作成・更新 R＝利用 空欄＝関係なし。ケイパビリティ経由で導出：アプリが●（主に支える）のL2で、そのL2がC／Rの情報オブジェクトを割り当て（CとRが重なる場合はC）
A4: 領域 | B4: ID | C4: アプリケーション種類 | D4: 共通・組織 | M4: 採用 | S4: 雇用・従業員 | AB4: 育成 | AF4: 評価・報酬 | AK4: 給与・社会保険 | AR4: 就業・健康 | AZ4: タレント・配置 | BE4: 退職 | BL4: Cの数 | BM4: Rの数
D5: =情報オブジェクト!C4 | E5: =情報オブジェクト!C5 | F5: =情報オブジェクト!C6 | G5: =情報オブジェクト!C7 | H5: =情報オブジェクト!C8 | I5: =情報オブジェクト!C9 | J5: =情報オブジェクト!C10 | K5: =情報オブジェクト!C11 | L5: =情報オブジェクト!C12 | M5: =情報オブジェクト!C13 | N5: =情報オブジェクト!C14 | O5: =情報オブジェクト!C15 | P5: =情報オブジェクト!C16 | Q5: =情報オブジェクト!C17 | R5: =情報オブジェクト!C18 | S5: =情報オブジェクト!C19 | T5: =情報オブジェクト!C20 | U5: =情報オブジェクト!C21 | V5: =情報オブジェクト!C22 | W5: =情報オブジェクト!C23 | X5: =情報オブジェクト!C24 | Y5: =情報オブジェクト!C25 | Z5: =情報オブジェクト!C26 | AA5: =情報オブジェクト!C27 | AB5: =情報オブジェクト!C28 | AC5: =情報オブジェクト!C29 | AD5: =情報オブジェクト!C30 | AE5: =情報オブジェクト!C31 | AF5: =情報オブジェクト!C32 | AG5: =情報オブジェクト!C33 | AH5: =情報オブジェクト!C34 | AI5: =情報オブジェクト!C35 | AJ5: =情報オブジェクト!C36 | AK5: =情報オブジェクト!C37 | AL5: =情報オブジェクト!C38 | AM5: =情報オブジェクト!C39 | AN5: =情報オブジェクト!C40 | AO5: =情報オブジェクト!C41 | AP5: =情報オブジェクト!C42 | AQ5: =情報オブジェクト!C43 | AR5: =情報オブジェクト!C44 | AS5: =情報オブジェクト!C45 | AT5: =情報オブジェクト!C46 | AU5: =情報オブジェクト!C47 | AV5: =情報オブジェクト!C48 | AW5: =情報オブジェクト!C49 | AX5: =情報オブジェクト!C50 | AY5: =情報オブジェクト!C51 | AZ5: =情報オブジェクト!C52 | BA5: =情報オブジェクト!C53 | BB5: =情報オブジェクト!C54 | BC5: =情報オブジェクト!C55 | BD5: =情報オブジェクト!C56 | BE5: =情報オブジェクト!C57 | BF5: =情報オブジェクト!C58 | BG5: =情報オブジェクト!C59 | BH5: =情報オブジェクト!C60 | BI5: =情報オブジェクト!C61 | BJ5: =情報オブジェクト!C62 | BK5: =情報オブジェクト!C63
A6: 雇用・労務 | B6: APP-01 | C6: =IFERROR(INDEX(アプリケーション!$C:$C,MATCH(B6,アプリケーション!$A:$A,0)),"（IDなし）") | D6: C | E6: C | F6: C | H6: R | J6: R | S6: C | T6: C | U6: R | V6: R | W6: C | Y6: C | AA6: C | AH6: C | AI6: R | AL6: R | AR6: R | AS6: R | BA6: C | BE6: R | BJ6: C | BL6: =COUNTIF(D6:BK6,"C") | BM6: =COUNTIF(D6:BK6,"R")
A7: 採用 | B7: APP-02 | C7: =IFERROR(INDEX(アプリケーション!$C:$C,MATCH(B7,アプリケーション!$A:$A,0)),"（IDなし）") | E7: R | F7: R | G7: R | I7: R | J7: R | M7: C | N7: C | O7: C | P7: C | Q7: C | R7: C | AH7: R | BL7: =COUNTIF(D7:BK7,"C") | BM7: =COUNTIF(D7:BK7,"R")
B8: APP-03 | C8: =IFERROR(INDEX(アプリケーション!$C:$C,MATCH(B8,アプリケーション!$A:$A,0)),"（IDなし）") | BL8: =COUNTIF(D8:BK8,"C") | BM8: =COUNTIF(D8:BK8,"R")
A9: 雇用・労務 | B9: APP-04 | C9: =IFERROR(INDEX(アプリケーション!$C:$C,MATCH(B9,アプリケーション!$A:$A,0)),"（IDなし）") | G9: R | Q9: R | S9: R | T9: C | U9: C | V9: C | X9: C | Y9: R | AH9: R | AJ9: R | AK9: C | AL9: R | AM9: C | AO9: C | AP9: C | AQ9: C | AR9: R | AS9: R | BA9: R | BE9: C | BF9: C | BG9: C | BJ9: R | BL9: =COUNTIF(D9:BK9,"C") | BM9: =COUNTIF(D9:BK9,"R")
B10: APP-05 | C10: =IFERROR(INDEX(アプリケーション!$C:$C,MATCH(B10,アプリケーション!$A:$A,0)),"（IDなし）") | G10: R | Q10: R | S10: R | T10: C | U10: C | V10: C | X10: C | Y10: R | AH10: R | AM10: C | BA10: R | BE10: C | BJ10: R | BL10: =COUNTIF(D10:BK10,"C") | BM10: =COUNTIF(D10:BK10,"R")
B11: APP-06 | C11: =IFERROR(INDEX(アプリケーション!$C:$C,MATCH(B11,アプリケーション!$A:$A,0)),"（IDなし）") | BL11: =COUNTIF(D11:BK11,"C") | BM11: =COUNTIF(D11:BK11,"R")
A12: 育成・評価 | B12: APP-07 | C12: =IFERROR(INDEX(アプリケーション!$C:$C,MATCH(B12,アプリケーション!$A:$A,0)),"（IDなし）") | E12: R | F12: R | G12: R | H12: R | Y12: R | Z12: R | AB12: C | AC12: C | AD12: R | AG12: R | BC12: R | BL12: =COUNTIF(D12:BK12,"C") | BM12: =COUNTIF(D12:BK12,"R")
B13: APP-08 | C13: =IFERROR(INDEX(アプリケーション!$C:$C,MATCH(B13,アプリケーション!$A:$A,0)),"（IDなし）") | D13: R | E13: R | F13: R | H13: R | J13: R | P13: R | S13: R | T13: C | Y13: C | Z13: R | AA13: R | AB13: R | AC13: C | AD13: C | AE13: C | AF13: R | AG13: R | AZ13: C | BA13: C | BB13: C | BC13: C | BL13: =COUNTIF(D13:BK13,"C") | BM13: =COUNTIF(D13:BK13,"R")
B14: APP-09 | C14: =IFERROR(INDEX(アプリケーション!$C:$C,MATCH(B14,アプリケーション!$A:$A,0)),"（IDなし）") | E14: R | F14: R | H14: R | Y14: R | Z14: R | AB14: R | AC14: C | AD14: R | AE14: R | AF14: C | AG14: C | BL14: =COUNTIF(D14:BK14,"C") | BM14: =COUNTIF(D14:BK14,"R")
A15: 就業・健康 | B15: APP-10 | C15: =IFERROR(INDEX(アプリケーション!$C:$C,MATCH(B15,アプリケーション!$A:$A,0)),"（IDなし）") | G15: R | S15: R | T15: R | U15: R | AR15: C | AS15: C | AT15: R | AU15: R | BL15: =COUNTIF(D15:BK15,"C") | BM15: =COUNTIF(D15:BK15,"R")
A16: 給与・福利 | B16: APP-11 | C16: =IFERROR(INDEX(アプリケーション!$C:$C,MATCH(B16,アプリケーション!$A:$A,0)),"（IDなし）") | S16: C | T16: R | U16: R | V16: R | X16: R | AH16: R | AJ16: R | AK16: C | AL16: C | AM16: C | AN16: C | AO16: C | AR16: C | BE16: R | BG16: R | BL16: =COUNTIF(D16:BK16,"C") | BM16: =COUNTIF(D16:BK16,"R")
A17: 就業・健康 | B17: APP-12 | C17: =IFERROR(INDEX(アプリケーション!$C:$C,MATCH(B17,アプリケーション!$A:$A,0)),"（IDなし）") | S17: R | AR17: R | AU17: C | AV17: C | AW17: C | BL17: =COUNTIF(D17:BK17,"C") | BM17: =COUNTIF(D17:BK17,"R")
A18: 給与・福利 | B18: APP-13 | C18: =IFERROR(INDEX(アプリケーション!$C:$C,MATCH(B18,アプリケーション!$A:$A,0)),"（IDなし）") | G18: R | S18: R | X18: C | AJ18: R | AK18: R | AO18: C | AP18: C | AQ18: C | AR18: R | AS18: R | BE18: R | BL18: =COUNTIF(D18:BK18,"C") | BM18: =COUNTIF(D18:BK18,"R")
A19: 就業・健康 | B19: APP-14 | C19: =IFERROR(INDEX(アプリケーション!$C:$C,MATCH(B19,アプリケーション!$A:$A,0)),"（IDなし）") | D19: R | G19: R | S19: R | Z19: R | AR19: C | AS19: R | AY19: C | BL19: =COUNTIF(D19:BK19,"C") | BM19: =COUNTIF(D19:BK19,"R")
A20: 共通 | B20: APP-15 | C20: =IFERROR(INDEX(アプリケーション!$C:$C,MATCH(B20,アプリケーション!$A:$A,0)),"（IDなし）") | S20: R | V20: R | X20: R | AH20: R | AK20: R | AL20: R | AM20: R | AN20: R | AR20: R | BL20: =COUNTIF(D20:BK20,"C") | BM20: =COUNTIF(D20:BK20,"R")
B21: APP-16 | C21: =IFERROR(INDEX(アプリケーション!$C:$C,MATCH(B21,アプリケーション!$A:$A,0)),"（IDなし）") | G21: R | K21: R | AG21: R | AH21: R | AJ21: R | AR21: R | AT21: C | AX21: C | BE21: C | BL21: =COUNTIF(D21:BK21,"C") | BM21: =COUNTIF(D21:BK21,"R")
B22: APP-17 | C22: =IFERROR(INDEX(アプリケーション!$C:$C,MATCH(B22,アプリケーション!$A:$A,0)),"（IDなし）") | D22: R | H22: R | J22: C | K22: C | L22: C | S22: R | AH22: R | AK22: R | BL22: =COUNTIF(D22:BK22,"C") | BM22: =COUNTIF(D22:BK22,"R")
B23: APP-18 | C23: =IFERROR(INDEX(アプリケーション!$C:$C,MATCH(B23,アプリケーション!$A:$A,0)),"（IDなし）") | D23: R | H23: R | I23: R | M23: R | P23: R | Q23: R | R23: R | S23: R | Y23: R | AB23: R | AC23: R | AD23: R | AE23: R | AG23: R | AK23: R | AY23: R | AZ23: R | BD23: R | BL23: =COUNTIF(D23:BK23,"C") | BM23: =COUNTIF(D23:BK23,"R")
B24: APP-19 | C24: =IFERROR(INDEX(アプリケーション!$C:$C,MATCH(B24,アプリケーション!$A:$A,0)),"（IDなし）") | O24: R | P24: R | S24: R | U24: R | V24: R | W24: R | Y24: R | AA24: C | AL24: R | AU24: R | AV24: R | BA24: R | BE24: R | BL24: =COUNTIF(D24:BK24,"C") | BM24: =COUNTIF(D24:BK24,"R")
B25: APP-20 | C25: =IFERROR(INDEX(アプリケーション!$C:$C,MATCH(B25,アプリケーション!$A:$A,0)),"（IDなし）") | D25: R | H25: R | J25: C | K25: C | L25: C | S25: R | AH25: R | AK25: R | BL25: =COUNTIF(D25:BK25,"C") | BM25: =COUNTIF(D25:BK25,"R")
B26: APP-21 | C26: =IFERROR(INDEX(アプリケーション!$C:$C,MATCH(B26,アプリケーション!$A:$A,0)),"（IDなし）") | G26: C | H26: C | I26: C | AC26: R | AT26: R | AY26: R | BD26: R | BL26: =COUNTIF(D26:BK26,"C") | BM26: =COUNTIF(D26:BK26,"R")
C27: Cの数 | D27: =COUNTIF(D$6:D$26,"C") | E27: =COUNTIF(E$6:E$26,"C") | F27: =COUNTIF(F$6:F$26,"C") | G27: =COUNTIF(G$6:G$26,"C") | H27: =COUNTIF(H$6:H$26,"C") | I27: =COUNTIF(I$6:I$26,"C") | J27: =COUNTIF(J$6:J$26,"C") | K27: =COUNTIF(K$6:K$26,"C") | ... BK27: =COUNTIF(BK$6:BK$26,"C")
C28: Rの数 | D28: =COUNTIF(D$6:D$26,"R") | E28: =COUNTIF(E$6:E$26,"R") | F28: =COUNTIF(F$6:F$26,"R") | G28: =COUNTIF(G$6:G$26,"R") | H28: =COUNTIF(H$6:H$26,"R") | I28: =COUNTIF(I$6:I$26,"R") | J28: =COUNTIF(J$6:J$26,"R") | K28: =COUNTIF(K$6:K$26,"R") | ... BK28: =COUNTIF(BK$6:BK$26,"R")
